Workbook

Sheet Executive Dashboard
A1: EXECUTIVE SUMMARY DASHBOARD – Misc Database
A2: Counts include only records with Include in Totals = Y. Category rollups and untagged price-list items (Tag No. in parentheses) are excluded from Active Tags. No currency totals are shown.
A4: ACTIVE TAGS | C4: PACKAGES / RECORDS | E4: EQUIPMENT UNITS | G4: TOTAL RECORDS (incl. excluded)
A5: =SUMPRODUCT(('Master Database'!$AB$5:$AB$100="Y")*(LEFT('Master Database'!$D$5:$D$100,1)<>"(")) -> 15 | C5: =COUNTIF('Master Database'!$AB$5:$AB$100,"Y") -> 60 | E5: =SUMIF('Master Database'!$AB$5:$AB$100,"Y",'Master Database'!$G$5:$G$100) -> 586 | G5: =COUNTA('Master Database'!$A$5:$A$100) -> 69
A12: SUB-CATEGORY BREAKDOWN
A13: Sub-Category | B13: Sub-Category Name | C13: Active Tags | D13: Records | E13: Total Units | F13: Records Excluded
A14: PKG-STR | B14: Stripping Packages (Stripper Towers T-143 A/B) | C14: =SUMPRODUCT(('Master Database'!$F$5:$F$100=A14)*('Master Database'!$AB$5:$AB$100="Y")*(LEFT('Master Database'!$D$5:$D$100,1)<>"(")) -> 1 | D14: =COUNTIFS('Master Database'!$F$5:$F$100,A14,'Master Database'!$AB$5:$AB$100,"Y") -> 1 | E14: =SUMIFS('Master Database'!$G$5:$G$100,'Master Database'!$F$5:$F$100,A14,'Master Database'!$AB$5:$AB$100,"Y") -> 1 | F14: =COUNTIFS('Master Database'!$F$5:$F$100,A14,'Master Database'!$AB$5:$AB$100,"N") -> 1
A15: PKG-RO | B15: Reverse Osmosis Packages | C15: =SUMPRODUCT(('Master Database'!$F$5:$F$100=A15)*('Master Database'!$AB$5:$AB$100="Y")*(LEFT('Master Database'!$D$5:$D$100,1)<>"(")) -> 1 | D15: =COUNTIFS('Master Database'!$F$5:$F$100,A15,'Master Database'!$AB$5:$AB$100,"Y") -> 1 | E15: =SUMIFS('Master Database'!$G$5:$G$100,'Master Database'!$F$5:$F$100,A15,'Master Database'!$AB$5:$AB$100,"Y") -> 1 | F15: =COUNTIFS('Master Database'!$F$5:$F$100,A15,'Master Database'!$AB$5:$AB$100,"N") -> 0
A16: PKG-PIG | B16: Pig Launcher & Receiver | C16: =SUMPRODUCT(('Master Database'!$F$5:$F$100=A16)*('Master Database'!$AB$5:$AB$100="Y")*(LEFT('Master Database'!$D$5:$D$100,1)<>"(")) -> 0 | D16: =COUNTIFS('Master Database'!$F$5:$F$100,A16,'Master Database'!$AB$5:$AB$100,"Y") -> 2 | E16: =SUMIFS('Master Database'!$G$5:$G$100,'Master Database'!$F$5:$F$100,A16,'Master Database'!$AB$5:$AB$100,"Y") -> 1 | F16: =COUNTIFS('Master Database'!$F$5:$F$100,A16,'Master Database'!$AB$5:$AB$100,"N") -> 1
A17: SEP-OWS | B17: Oily Water / API Separators | C17: =SUMPRODUCT(('Master Database'!$F$5:$F$100=A17)*('Master Database'!$AB$5:$AB$100="Y")*(LEFT('Master Database'!$D$5:$D$100,1)<>"(")) -> 1 | D17: =COUNTIFS('Master Database'!$F$5:$F$100,A17,'Master Database'!$AB$5:$AB$100,"Y") -> 1 | E17: =SUMIFS('Master Database'!$G$5:$G$100,'Master Database'!$F$5:$F$100,A17,'Master Database'!$AB$5:$AB$100,"Y") -> 0 | F17: =COUNTIFS('Master Database'!$F$5:$F$100,A17,'Master Database'!$AB$5:$AB$100,"N") -> 0
A18: SEP-SKM | B18: Portable Skimmers | C18: =SUMPRODUCT(('Master Database'!$F$5:$F$100=A18)*('Master Database'!$AB$5:$AB$100="Y")*(LEFT('Master Database'!$D$5:$D$100,1)<>"(")) -> 1 | D18: =COUNTIFS('Master Database'!$F$5:$F$100,A18,'Master Database'!$AB$5:$AB$100,"Y") -> 1 | E18: =SUMIFS('Master Database'!$G$5:$G$100,'Master Database'!$F$5:$F$100,A18,'Master Database'!$AB$5:$AB$100,"Y") -> 0 | F18: =COUNTIFS('Master Database'!$F$5:$F$100,A18,'Master Database'!$AB$5:$AB$100,"N") -> 0
A19: ACX-AIR | B19: Air Coolers (Air-Cooled Heat Exchangers) | C19: =SUMPRODUCT(('Master Database'!$F$5:$F$100=A19)*('Master Database'!$AB$5:$AB$100="Y")*(LEFT('Master Database'!$D$5:$D$100,1)<>"(")) -> 0 | D19: =COUNTIFS('Master Database'!$F$5:$F$100,A19,'Master Database'!$AB$5:$AB$100,"Y") -> 1 | E19: =SUMIFS('Master Database'!$G$5:$G$100,'Master Database'!$F$5:$F$100,A19,'Master Database'!$AB$5:$AB$100,"Y") -> 0 | F19: =COUNTIFS('Master Database'!$F$5:$F$100,A19,'Master Database'!$AB$5:$AB$100,"N") -> 0
A20: HVAC-SYS | B20: HVAC Systems (incl. category rollups) | C20: =SUMPRODUCT(('Master Database'!$F$5:$F$100=A20)*('Master Database'!$AB$5:$AB$100="Y")*(LEFT('Master Database'!$D$5:$D$100,1)<>"(")) -> 0 | D20: =COUNTIFS('Master Database'!$F$5:$F$100,A20,'Master Database'!$AB$5:$AB$100,"Y") -> 10 | E20: =SUMIFS('Master Database'!$G$5:$G$100,'Master Database'!$F$5:$F$100,A20,'Master Database'!$AB$5:$AB$100,"Y") -> 8 | F20: =COUNTIFS('Master Database'!$F$5:$F$100,A20,'Master Database'!$AB$5:$AB$100,"N") -> 2
A21: SAF-SHW | B21: Safety Shower & Eye Wash | C21: =SUMPRODUCT(('Master Database'!$F$5:$F$100=A21)*('Master Database'!$AB$5:$AB$100="Y")*(LEFT('Master Database'!$D$5:$D$100,1)<>"(")) -> 0 | D21: =COUNTIFS('Master Database'!$F$5:$F$100,A21,'Master Database'!$AB$5:$AB$100,"Y") -> 2 | E21: =SUMIFS('Master Database'!$G$5:$G$100,'Master Database'!$F$5:$F$100,A21,'Master Database'!$AB$5:$AB$100,"Y") -> 12 | F21: =COUNTIFS('Master Database'!$F$5:$F$100,A21,'Master Database'!$AB$5:$AB$100,"N") -> 2
A22: PKG-EFF | B22: Effluent / Waste Water Treatment Packages | C22: =SUMPRODUCT(('Master Database'!$F$5:$F$100=A22)*('Master Database'!$AB$5:$AB$100="Y")*(LEFT('Master Database'!$D$5:$D$100,1)<>"(")) -> 0 | D22: =COUNTIFS('Master Database'!$F$5:$F$100,A22,'Master Database'!$AB$5:$AB$100,"Y") -> 1 | E22: =SUMIFS('Master Database'!$G$5:$G$100,'Master Database'!$F$5:$F$100,A22,'Master Database'!$AB$5:$AB$100,"Y") -> 0 | F22: =COUNTIFS('Master Database'!$F$5:$F$100,A22,'Master Database'!$AB$5:$AB$100,"N") -> 0
A23: PKG-WTR | B23: Water Treatment Packages | C23: =SUMPRODUCT(('Master Database'!$F$5:$F$100=A23)*('Master Database'!$AB$5:$AB$100="Y")*(LEFT('Master Database'!$D$5:$D$100,1)<>"(")) -> 0 | D23: =COUNTIFS('Master Database'!$F$5:$F$100,A23,'Master Database'!$AB$5:$AB$100,"Y") -> 1 | E23: =SUMIFS('Master Database'!$G$5:$G$100,'Master Database'!$F$5:$F$100,A23,'Master Database'!$AB$5:$AB$100,"Y") -> 0 | F23: =COUNTIFS('Master Database'!$F$5:$F$100,A23,'Master Database'!$AB$5:$AB$100,"N") -> 0
A24: PMP-WWP | B24: Waste Water & OWS Pumps | C24: =SUMPRODUCT(('Master Database'!$F$5:$F$100=A24)*('Master Database'!$AB$5:$AB$100="Y")*(LEFT('Master Database'!$D$5:$D$100,1)<>"(")) -> 3 | D24: =COUNTIFS('Master Database'!$F$5:$F$100,A24,'Master Database'!$AB$5:$AB$100,"Y") -> 3 | E24: =SUMIFS('Master Database'!$G$5:$G$100,'Master Database'!$F$5:$F$100,A24,'Master Database'!$AB$5:$AB$100,"Y") -> 5 | F24: =COUNTIFS('Master Database'!$F$5:$F$100,A24,'Master Database'!$AB$5:$AB$100,"N") -> 1
A25: TNK-SKM | B25: Oil Skimmer Tanks | C25: =SUMPRODUCT(('Master Database'!$F$5:$F$100=A25)*('Master Database'!$AB$5:$AB$100="Y")*(LEFT('Master Database'!$D$5:$D$100,1)<>"(")) -> 2 | D25: =COUNTIFS('Master Database'!$F$5:$F$100,A25,'Master Database'!$AB$5:$AB$100,"Y") -> 2 | E25: =SUMIFS('Master Database'!$G$5:$G$100,'Master Database'!$F$5:$F$100,A25,'Master Database'!$AB$5:$AB$100,"Y") -> 3 | F25: =COUNTIFS('Master Database'!$F$5:$F$100,A25,'Master Database'!$AB$5:$AB$100,"N") -> 0
... A33: CRN-FWP | B33: Fire Water Pumps Shelter Crane | C33: =SUMPRODUCT(('Master Database'!$F$5:$F$100=A33)*('Master Database'!$AB$5:$AB$100="Y")*(LEFT('Master Database'!$D$5:$D$100,1)<>"(")) -> 1 | D33: =COUNTIFS('Master Database'!$F$5:$F$100,A33,'Master Database'!$AB$5:$AB$100,"Y") -> 1 | E33: =SUMIFS('Master Database'!$G$5:$G$100,'Master Database'!$F$5:$F$100,A33,'Master Database'!$AB$5:$AB$100,"Y") -> 1 | F33: =COUNTIFS('Master Database'!$F$5:$F$100,A33,'Master Database'!$AB$5:$AB$100,"N") -> 0
A34: Total | C34: =SUM(C14:C33) -> 15 | D34: =SUM(D14:D33) -> 60 | E34: =SUM(E14:E33) -> 586 | F34: =SUM(F14:F33) -> 9
A36: NOTES & DATA GAPS
A37: • FX table has verified rates for 1392 (EUR only), 1393 (EUR only), 1402 (USD only), 1404 and 1405 only (reused from the Flare / Desalting Price Banks). 1394 (KPL stripping and RO packages, Rev. R03/Jan 2016) has no documented rate, so their converted price columns show "FX rate not entered for this year". Gachsaran 4 (1402) records convert to USD only; Maroon 3 1392 records convert to EUR only.
A38: • Unit Price (EUR/USD/IRR) in Master Database are formulas keyed off Cost Year; Unit Price (Reference) sits immediately next to Reference Currency in every sheet.
A39: • No Total Price / currency sums appear on this dashboard, per the same instruction used for the Flare database.
A40: • Category (PKG / SEP / ACX / HVAC / SAF / PMP / TNK / VSL) and Sub-Category codes carry cell comments spelling out the full names.
A41: • Tag No. in parentheses marks a project-wide category rollup or an untagged item taken from a price list. These are excluded from Active Tags but included in Records and Total Records. Real tags counted as Active Tags: PK-143, PK-152, SU-701, X-704 and OS-201.
A42: • SU-701 (Oily Water Separator) and X-704 (Portable Skimmer), Gachsaran 4, have process data sheets only: no price exists in P.ME, so their price cells are Not Stated; no value was invented.
A43: • v2 additions (from Change Log section C): effluent / water treatment packages 66.9 and 66.10, OS-201 tank, pumps P-148 and OWS pumps, safety & fire fighting package, HVAC / safety / pig group rollups. Records marked 'TO BE FILLED' in Remarks need prices from the project files (not opened in this pass). Pumps and the HVAC rollup are Include = N.
A44: • Air Cooler and Pig Launcher (price sample) are reference prices in USD with no cost year or quantity; they sit in Master Database (not on a separate sheet) because they are equipment. No air cooler, pig launcher, HVAC or safety shower record exists in the KPL or Pazanan 2 files.
A45: • v3 additions (stages 1-4 plus KPL fire water system; project reference files opened, installation costs excluded): OWS pumps P-703/P-704/P-750, KPL skimmer tanks, First Stage Separator price, rollup amounts, safety items P.ME 67.1-67.19 (Gachsaran 4, 1402) and priced items of SEFTY.p.1392 (Maroon 3, 1392), and KPL fire water tanks, pumps and crane (1394, pumps in EUR). KPL and Pazanan 2 OWS pumps were intentionally not added.

Sheet Master Database
A1: MASTER MISC EQUIPMENT & PRICE DATABASE (28-COLUMN AUDIT STRUCTURE)
A2: All extracted Misc records: stripping, reverse osmosis, pig launcher/receiver, oily water separator / skimmer, air cooler, HVAC and safety shower. Grey text = not stated in source. Unit Price (EUR/USD/IRR) are formulas keyed off Cost Year and the FX table; a year with no FX rate shows a message, not a number.
A4: Row | B4: Equipment Name | C4: Project Name | D4: Tag No. | E4: Category | F4: Sub-Category | G4: Quantity | H4: Unit | I4: Service Description | J4: Capacity / Flow Rate | K4: Design Pressure (Barg) | L4: Design Temp (°C) | M4: Material Class | N4: Design Code & Standard | O4: Weight / Power | P4: Manufacturer / Supplier | Q4: Cost Year / Date | R4: Reference Currency | S4: Unit Price (Reference) | T4: Unit Price (EUR) | U4: Unit Price (USD) | V4: Unit Price (IRR) | W4: Price Basis | X4: Estimate Class | Y4: Project Phase | Z4: Source Document / Sheet | AA4: Remarks & Scope Notes | AB4: Include in Totals (Y/N)
A5: 1 | B5: Stripping Package (Bangestan Train) | C5: Koopal Asmari/Bangestan Desalting Unit (Proj No. 53-51-91215) | D5: PK-143 | E5: PKG | F5: PKG-STR | G5: 1 | H5: Set | I5: Stripping Package including Stripper Towers T-143 A/B, Stripped Waste Water Pumps P-148 A/B/C, related piping, instruments, etc. | J5: Towers: lower section 2000 x 2500 mm (ID x L), upper section 800 x 5000 mm (ID x L), total length 9000 mm; internals: packing. Pumps (P-148 A/B/C): 50 m3/hr, 3 barg differential | K5: 5 (F.V.) | L5: -2 / 95 | M5: Shell/Heads: SA 516 Gr. 70; removable internals: Duplex S.S.; pumps API 610 material class D2 | N5: ASME VIII Div.1 & IPS-G-ME-150; pumps: API 610 & IPS-G-PM-105 | O5: Not Stated | P5: Not Stated | Q5: 1394 | R5: IRR | S5: 9000000000 | T5: =IF(NOT(ISNUMBER(S5)),"(Not stated)",IF(NOT(ISNUMBER(Q5)),"(Cost year not stated / not a Jalali year)",IFERROR(IF(N(IF(R5="EUR",S5,IF(R5="IRR",S5/INDEX('Assumptions & FX Reference'!$C$5:$C$25,MATCH(Q5,'Assumptions & FX Reference'!$A$5:$A$25,0)),IF(R5="USD",S5*INDEX('Assumptions & FX Reference'!$B$5:$B$25,MATCH(Q5,'Assumptions & FX Reference'!$A$5:$A$25,0))/INDEX('Assumptions & FX Reference'!$C$5:$C$25,MATCH(Q5,'Assumptions & FX Reference'!$A$5:$A$25,0)),"(Not stated)"))))>0,IF(R5="EUR",S5,IF(R5="IRR",S5/INDEX('Assumptions & FX Reference'!$C$5:$C$25,MATCH(Q5,'Assumptions & FX Reference'!$A$5:$A$25,0)),IF(R5="USD",S5*INDEX('Assumptions & FX Reference'!$B$5:$B$25,MATCH(Q5,'Assumptions & FX Reference'!$A$5:$A$25,0))/INDEX('Assumptions & FX Reference'!$C$5:$C$25,MATCH(Q5,'Assumptions & FX Reference'!$A$5:$A$25,0)),"(Not stated)"))),"(FX rate not entered for this year)"),"(FX rate not entered for this year)"))) -> 244897.96 | U5: =IF(NOT(ISNUMBER(S5)),"(Not stated)",IF(NOT(ISNUMBER(Q5)),"(Cost year not stated / not a Jalali year)",IFERROR(IF(N(IF(R5="USD",S5,IF(R5="IRR",S5/INDEX('Assumptions & FX Reference'!$B$5:$B$25,MATCH(Q5,'Assumptions & FX Reference'!$A$5:$A$25,0)),IF(R5="EUR",S5*INDEX('Assumptions & FX Reference'!$C$5:$C$25,MATCH(Q5,'Assumptions & FX Reference'!$A$5:$A$25,0))/INDEX('Assumptions & FX Reference'!$B$5:$B$25,MATCH(Q5,'Assumptions & FX Reference'!$A$5:$A$25,0)),"(Not stated)"))))>0,IF(R5="USD",S5,IF(R5="IRR",S5/INDEX('Assumptions & FX Reference'!$B$5:$B$25,MATCH(Q5,'Assumptions & FX Reference'!$A$5:$A$25,0)),IF(R5="EUR",S5*INDEX('Assumptions & FX Reference'!$C$5:$C$25,MATCH(Q5,'Assumptions & FX Reference'!$A$5:$A$25,0))/INDEX('Assumptions & FX Reference'!$B$5:$B$25,MATCH(Q5,'Assumptions & FX Reference'!$A$5:$A$25,0)),"(Not stated)"))),"(FX rate not entered for this year)"),"(FX rate not entered for this year)"))) -> 268256.33 | V5: =IF(NOT(ISNUMBER(S5)),"(Not stated)",IF(NOT(ISNUMBER(Q5)),"(Cost year not stated / not a Jalali year)",IFERROR(IF(N(IF(R5="IRR",S5,IF(R5="USD",S5*INDEX('Assumptions & FX Reference'!$B$5:$B$25,MATCH(Q5,'Assumptions & FX Reference'!$A$5:$A$25,0)),IF(R5="EUR",S5*INDEX('Assumptions & FX Reference'!$C$5:$C$25,MATCH(Q5,'Assumptions & FX Reference'!$A$5:$A$25,0)),"(Not stated)"))))>0,IF(R5="IRR",S5,IF(R5="USD",S5*INDEX('Assumptions & FX Reference'!$B$5:$B$25,MATCH(Q5,'Assumptions & FX Reference'!$A$5:$A$25,0)),IF(R5="EUR",S5*INDEX('Assumptions & FX Reference'!$C$5:$C$25,MATCH(Q5,'Assumptions & FX Reference'!$A$5:$A$25,0)),"(Not stated)"))),"(FX rate not entered for this year)"),"(FX rate not entered for this year)"))) -> 9000000000 | W5: Not Stated | X5: Class 2 (FEED) | Y5: FEED Package | Z5: 91215-KPL-ME-RE-476_R03_MTO_and_Cost_Estimation_Report.xlsx (Sheet STRIPPER-B) | AA5: Rev. R03 dated Jan. 2016 (~1394). Total Price (Euros) = 0 in source (no EUR quote). Lump-sum package price covers the two stripper towers, the stripped waste water pumps P-148 A/B/C (centrifugal, OH2), related piping and instruments; none of these is priced separately. Source sheet is headed BANGESTAN TRAIN; the report has no Asmari stripping sheet. Price basis not labelled in the source. | AB5: Y
A6: 2 | B6: Stripper Towers (Bangestan Train) | C6: Koopal Asmari/Bangestan Desalting Unit (Proj No. 53-51-91215) | D6: T-143 A/B | E6: PKG | F6: PKG-STR | G6: 2 | H6: No. | I6: Packed stripper towers T-143 A/B, supplied inside Stripping Package PK-143 | J6: Lower section 2000 x 2500 mm (ID x L); upper section 800 x 5000 mm (ID x L); total length 9000 mm; internals: packing | K6: 5 (F.V.) | L6: -2 / 95 | M6: Shell/Heads: SA 516 Gr. 70; removable internals: Duplex S.S. | N6: ASME VIII Div.1 & IPS-G-ME-150 | O6: Not Stated | P6: Not Stated | Q6: 1394 | R6: IRR | S6: Not Stated | T6: =IF(NOT(ISNUMBER(S6)),"(Not stated)",IF(NOT(ISNUMBER(Q6)),"(Cost year not stated / not a Jalali year)",IFERROR(IF(N(IF(R6="EUR",S6,IF(R6="IRR",S6/INDEX('Assumptions & FX Reference'!$C$5:$C$25,MATCH(Q6,'Assumptions & FX Reference'!$A$5:$A$25,0)),IF(R6="USD",S6*INDEX('Assumptions & FX Reference'!$B$5:$B$25,MATCH(Q6,'Assumptions & FX Reference'!$A$5:$A$25,0))/INDEX('Assumptions & FX Reference'!$C$5:$C$25,MATCH(Q6,'Assumptions & FX Reference'!$A$5:$A$25,0)),"(Not stated)"))))>0,IF(R6="EUR",S6,IF(R6="IRR",S6/INDEX('Assumptions & FX Reference'!$C$5:$C$25,MATCH(Q6,'Assumptions & FX Reference'!$A$5:$A$25,0)),IF(R6="USD",S6*INDEX('Assumptions & FX Reference'!$B$5:$B$25,MATCH(Q6,'Assumptions & FX Reference'!$A$5:$A$25,0))/INDEX('Assumptions & FX Reference'!$C$5:$C$25,MATCH(Q6,'Assumptions & FX Reference'!$A$5:$A$25,0)),"(Not stated)"))),"(FX rate not entered for this year)"),"(FX rate not entered for this year)"))) -> (Not stated) | U6: =IF(NOT(ISNUMBER(S6)),"(Not stated)",IF(NOT(ISNUMBER(Q6)),"(Cost year not stated / not a Jalali year)",IFERROR(IF(N(IF(R6="USD",S6,IF(R6="IRR",S6/INDEX('Assumptions & FX Reference'!$B$5:$B$25,MATCH(Q6,'Assumptions & FX Reference'!$A$5:$A$25,0)),IF(R6="EUR",S6*INDEX('Assumptions & FX Reference'!$C$5:$C$25,MATCH(Q6,'Assumptions & FX Reference'!$A$5:$A$25,0))/INDEX('Assumptions & FX Reference'!$B$5:$B$25,MATCH(Q6,'Assumptions & FX Reference'!$A$5:$A$25,0)),"(Not stated)"))))>0,IF(R6="USD",S6,IF(R6="IRR",S6/INDEX('Assumptions & FX Reference'!$B$5:$B$25,MATCH(Q6,'Assumptions & FX Reference'!$A$5:$A$25,0)),IF(R6="EUR",S6*INDEX('Assumptions & FX Reference'!$C$5:$C$25,MATCH(Q6,'Assumptions & FX Reference'!$A$5:$A$25,0))/INDEX('Assumptions & FX Reference'!$B$5:$B$25,MATCH(Q6,'Assumptions & FX Reference'!$A$5:$A$25,0)),"(Not stated)"))),"(FX rate not entered for this year)"),"(FX rate not entered for this year)"))) -> (Not stated) | V6: =IF(NOT(ISNUMBER(S6)),"(Not stated)",IF(NOT(ISNUMBER(Q6)),"(Cost year not stated / not a Jalali year)",IFERROR(IF(N(IF(R6="IRR",S6,IF(R6="USD",S6*INDEX('Assumptions & FX Reference'!$B$5:$B$25,MATCH(Q6,'Assumptions & FX Reference'!$A$5:$A$25,0)),IF(R6="EUR",S6*INDEX('Assumptions & FX Reference'!$C$5:$C$25,MATCH(Q6,'Assumptions & FX Reference'!$A$5:$A$25,0)),"(Not stated)"))))>0,IF(R6="IRR",S6,IF(R6="USD",S6*INDEX('Assumptions & FX Reference'!$B$5:$B$25,MATCH(Q6,'Assumptions & FX Reference'!$A$5:$A$25,0)),IF(R6="EUR",S6*INDEX('Assumptions & FX Reference'!$C$5:$C$25,MATCH(Q6,'Assumptions & FX Reference'!$A$5:$A$25,0)),"(Not stated)"))),"(FX rate not entered for this year)"),"(FX rate not entered for this year)"))) -> (Not stated) | W6: Not Stated | X6: Class 2 (FEED) | Y6: FEED Package | Z6: 91215-KPL-ME-RE-476_R03_MTO_and_Cost_Estimation_Report.xlsx (Sheet STRIPPER-B, row 23) | AA6: No separate price: the towers are inside the PK-143 lump sum (9,000,000,000 IRR). Record kept only so that tag T-143 A/B (MASTER_TAGS category Tower) stays traceable; excluded from totals to avoid double counting. | AB6: N
A7: 3 | B7: Reverse Osmosis Package (Asmari & Bangestan Trains) | C7: Koopal Asmari/Bangestan Desalting Unit (Proj No. 53-51-91215) | D7: PK-152 | E7: PKG | F7: PKG-RO | G7: 1 | H7: Set | I7: Reverse Osmosis Packages including Back Filters, R.O. Unit, C.I.P., Chemical Injection System & U.V. Lamp | J7: 1 m3/hr | K7: Not Stated | L7: Not Stated | M7: Not Stated | N7: Not Stated | O7: Not Stated | P7: Not Stated | Q7: 1394 | R7: IRR | S7: 800000000 | T7: =IF(NOT(ISNUMBER(S7)),"(Not stated)",IF(NOT(ISNUMBER(Q7)),"(Cost year not stated / not a Jalali year)",IFERROR(IF(N(IF(R7="EUR",S7,IF(R7="IRR",S7/INDEX('Assumptions & FX Reference'!$C$5:$C$25,MATCH(Q7,'Assumptions & FX Reference'!$A$5:$A$25,0)),IF(R7="USD",S7*INDEX('Assumptions & FX Reference'!$B$5:$B$25,MATCH(Q7,'Assumptions & FX Reference'!$A$5:$A$25,0))/INDEX('Assumptions & FX Reference'!$C$5:$C$25,MATCH(Q7,'Assumptions & FX Reference'!$A$5:$A$25,0)),"(Not stated)"))))>0,IF(R7="EUR",S7,IF(R7="IRR",S7/INDEX('Assumptions & FX Reference'!$C$5:$C$25,MATCH(Q7,'Assumptions & FX Reference'!$A$5:$A$25,0)),IF(R7="USD",S7*INDEX('Assumptions & FX Reference'!$B$5:$B$25,MATCH(Q7,'Assumptions & FX Reference'!$A$5:$A$25,0))/INDEX('Assumptions & FX Reference'!$C$5:$C$25,MATCH(Q7,'Assumptions & FX Reference'!$A$5:$A$25,0)),"(Not stated)"))),"(FX rate not entered for this year)"),"(FX rate not entered for this year)"))) -> 21768.707 | U7: =IF(NOT(ISNUMBER(S7)),"(Not stated)",IF(NOT(ISNUMBER(Q7)),"(Cost year not stated / not a Jalali year)",IFERROR(IF(N(IF(R7="USD",S7,IF(R7="IRR",S7/INDEX('Assumptions & FX Reference'!$B$5:$B$25,MATCH(Q7,'Assumptions & FX Reference'!$A$5:$A$25,0)),IF(R7="EUR",S7*INDEX('Assumptions & FX Reference'!$C$5:$C$25,MATCH(Q7,'Assumptions & FX Reference'!$A$5:$A$25,0))/INDEX('Assumptions & FX Reference'!$B$5:$B$25,MATCH(Q7,'Assumptions & FX Reference'!$A$5:$A$25,0)),"(Not stated)"))))>0,IF(R7="USD",S7,IF(R7="IRR",S7/INDEX('Assumptions & FX Reference'!$B$5:$B$25,MATCH(Q7,'Assumptions & FX Reference'!$A$5:$A$25,0)),IF(R7="EUR",S7*INDEX('Assumptions & FX Reference'!$C$5:$C$25,MATCH(Q7,'Assumptions & FX Reference'!$A$5:$A$25,0))/INDEX('Assumptions & FX Reference'!$B$5:$B$25,MATCH(Q7,'Assumptions & FX Reference'!$A$5:$A$25,0)),"(Not stated)"))),"(FX rate not entered for this year)"),"(FX rate not entered for this year)"))) -> 23845.007 | V7: =IF(NOT(ISNUMBER(S7)),"(Not stated)",IF(NOT(ISNUMBER(Q7)),"(Cost year not stated / not a Jalali year)",IFERROR(IF(N(IF(R7="IRR",S7,IF(R7="USD",S7*INDEX('Assumptions & FX Reference'!$B$5:$B$25,MATCH(Q7,'Assumptions & FX Reference'!$A$5:$A$25,0)),IF(R7="EUR",S7*INDEX('Assumptions & FX Reference'!$C$5:$C$25,MATCH(Q7,'Assumptions & FX Reference'!$A$5:$A$25,0)),"(Not stated)"))))>0,IF(R7="IRR",S7,IF(R7="USD",S7*INDEX('Assumptions & FX Reference'!$B$5:$B$25,MATCH(Q7,'Assumptions & FX Reference'!$A$5:$A$25,0)),IF(R7="EUR",S7*INDEX('Assumptions & FX Reference'!$C$5:$C$25,MATCH(Q7,'Assumptions & FX Reference'!$A$5:$A$25,0)),"(Not stated)"))),"(FX rate not entered for this year)"),"(FX rate not entered for this year)"))) -> 800000000 | W7: Not Stated | X7: Class 2 (FEED) | Y7: FEED Package | Z7: 91215-KPL-ME-RE-476_R03_MTO_and_Cost_Estimation_Report.xlsx (Sheet R.O.) | AA7: Rev. R03 dated Jan. 2016 (~1394). Total Price (Euros) = 0 in source (no EUR quote). One package serves both trains (sheet heading 'ASMARI & BANGESTAN TRAINS'), qty 1 Set. Installation sheet INS-PACK-C lists the same tag PK-152. Price basis not labelled in the source. | AB7: Y
A8: 4 | B8: Pig Launcher & Receiver | C8: Gachsaran 4 Development Plan (Proj No. 591111) | D8: (No Tag - P.ME item 68) | E8: PKG | F8: PKG-PIG | G8: 1 | H8: SET | I8: Pig Launcher & Receiver (pipeline pigging facilities) | J8: Not Stated | K8: Not Stated | L8: Not Stated | M8: Not Stated | N8: Not Stated | O8: Not Stated | P8: Not Stated | Q8: 1402 | R8: IRR | S8: 94500000000 | T8: =IF(NOT(ISNUMBER(S8)),"(Not stated)",IF(NOT(ISNUMBER(Q8)),"(Cost year not stated / not a Jalali year)",IFERROR(IF(N(IF(R8="EUR",S8,IF(R8="IRR",S8/INDEX('Assumptions & FX Reference'!$C$5:$C$25,MATCH(Q8,'Assumptions & FX Reference'!$A$5:$A$25,0)),IF(R8="USD",S8*INDEX('Assumptions & FX Reference'!$B$5:$B$25,MATCH(Q8,'Assumptions & FX Reference'!$A$5:$A$25,0))/INDEX('Assumptions & FX Reference'!$C$5:$C$25,MATCH(Q8,'Assumptions & FX Reference'!$A$5:$A$25,0)),"(Not stated)"))))>0,IF(R8="EUR",S8,IF(R8="IRR",S8/INDEX('Assumptions & FX Reference'!$C$5:$C$25,MATCH(Q8,'Assumptions & FX Reference'!$A$5:$A$25,0)),IF(R8="USD",S8*INDEX('Assumptions & FX Reference'!$B$5:$B$25,MATCH(Q8,'Assumptions & FX Reference'!$A$5:$A$25,0))/INDEX('Assumptions & FX Reference'!$C$5:$C$25,MATCH(Q8,'Assumptions & FX Reference'!$A$5:$A$25,0)),"(Not stated)"))),"(FX rate not entered for this year)"),"(FX rate not entered for this year)"))) -> 178470.25 | U8: =IF(NOT(ISNUMBER(S8)),"(Not stated)",IF(NOT(ISNUMBER(Q8)),"(Cost year not stated / not a Jalali year)",IFERROR(IF(N(IF(R8="USD",S8,IF(R8="IRR",S8/INDEX('Assumptions & FX Reference'!$B$5:$B$25,MATCH(Q8,'Assumptions & FX Reference'!$A$5:$A$25,0)),IF(R8="EUR",S8*INDEX('Assumptions & FX Reference'!$C$5:$C$25,MATCH(Q8,'Assumptions & FX Reference'!$A$5:$A$25,0))/INDEX('Assumptions & FX Reference'!$B$5:$B$25,MATCH(Q8,'Assumptions & FX Reference'!$A$5:$A$25,0)),"(Not stated)"))))>0,IF(R8="USD",S8,IF(R8="IRR",S8/INDEX('Assumptions & FX Reference'!$B$5:$B$25,MATCH(Q8,'Assumptions & FX Reference'!$A$5:$A$25,0)),IF(R8="EUR",S8*INDEX('Assumptions & FX Reference'!$C$5:$C$25,MATCH(Q8,'Assumptions & FX Reference'!$A$5:$A$25,0))/INDEX('Assumptions & FX Reference'!$B$5:$B$25,MATCH(Q8,'Assumptions & FX Reference'!$A$5:$A$25,0)),"(Not stated)"))),"(FX rate not entered for this year)"),"(FX rate not entered for this year)"))) -> 225000 | V8: =IF(NOT(ISNUMBER(S8)),"(Not stated)",IF(NOT(ISNUMBER(Q8)),"(Cost year not stated / not a Jalali year)",IFERROR(IF(N(IF(R8="IRR",S8,IF(R8="USD",S8*INDEX('Assumptions & FX Reference'!$B$5:$B$25,MATCH(Q8,'Assumptions & FX Reference'!$A$5:$A$25,0)),IF(R8="EUR",S8*INDEX('Assumptions & FX Reference'!$C$5:$C$25,MATCH(Q8,'Assumptions & FX Reference'!$A$5:$A$25,0)),"(Not stated)"))))>0,IF(R8="IRR",S8,IF(R8="USD",S8*INDEX('Assumptions & FX Reference'!$B$5:$B$25,MATCH(Q8,'Assumptions & FX Reference'!$A$5:$A$25,0)),IF(R8="EUR",S8*INDEX('Assumptions & FX Reference'!$C$5:$C$25,MATCH(Q8,'Assumptions & FX Reference'!$A$5:$A$25,0)),"(Not stated)"))),"(FX rate not entered for this year)"),"(FX rate not entered for this year)"))) -> 94500000000 | W8: FOB | X8: Class 3 (Basic) | Y8: Basic Engineering | Z8: PEP-Rev.140205_عزيزيان_Gachsaran_4.xlsx (Sheet P.ME, row 113) | AA8: Unit cost without overhead factor (هزینه واحد بدون ضریب). Source formula = 225,000 USD x USD_Change_IRR (420,000 IRR/USD) = 94,500,000,000 IRR. Freight allocation 241,488,427.26 IRR (P.ME col N; = 13,000,000 x IRR_Inflation_Factor) not included in Unit Price Reference; Customs clearance not stated. Same amount appears in the P.ME summary table row 141 (گیرنده و فرستنده توپک). Installation is a separate construction item (C.mECHANICAL 'LUNCHER AND RECEIVER') and is not included. | AB8: Y
A9: 5 | B9: Pig Launcher (Reference Price Sample) | C9: Not Stated (reference price sample, file نمونه_قیمتی_نمک_زدایی_overall.xlsx) | D9: (No Tag - price sample item 8) | E9: PKG | F9: PKG-PIG | G9: Not Stated | H9: Not Stated | I9: PIG Launcher (Type: Piping), from packages list of the price sample | J9: Length 4356 mm; diameters 16 / 12 inches | K9: 8 | L9: Not Stated | M9: C.S | N9: Not Stated | O9: Not Stated | P9: Not Stated | Q9: Not Stated | R9: USD | S9: 15000 | T9: =IF(NOT(ISNUMBER(S9)),"(Not stated)",IF(NOT(ISNUMBER(Q9)),"(Cost year not stated / not a Jalali year)",IFERROR(IF(N(IF(R9="EUR",S9,IF(R9="IRR",S9/INDEX('Assumptions & FX Reference'!$C$5:$C$25,MATCH(Q9,'Assumptions & FX Reference'!$A$5:$A$25,0)),IF(R9="USD",S9*INDEX('Assumptions & FX Reference'!$B$5:$B$25,MATCH(Q9,'Assumptions & FX Reference'!$A$5:$A$25,0))/INDEX('Assumptions & FX Reference'!$C$5:$C$25,MATCH(Q9,'Assumptions & FX Reference'!$A$5:$A$25,0)),"(Not stated)"))))>0,IF(R9="EUR",S9,IF(R9="IRR",S9/INDEX('Assumptions & FX Reference'!$C$5:$C$25,MATCH(Q9,'Assumptions & FX Reference'!$A$5:$A$25,0)),IF(R9="USD",S9*INDEX('Assumptions & FX Reference'!$B$5:$B$25,MATCH(Q9,'Assumptions & FX Reference'!$A$5:$A$25,0))/INDEX('Assumptions & FX Reference'!$C$5:$C$25,MATCH(Q9,'Assumptions & FX Reference'!$A$5:$A$25,0)),"(Not stated)"))),"(FX rate not entered for this year)"),"(FX rate not entered for this year)"))) -> (Cost year not stated / not a Jalali year) | U9: =IF(NOT(ISNUMBER(S9)),"(Not stated)",IF(NOT(ISNUMBER(Q9)),"(Cost year not stated / not a Jalali year)",IFERROR(IF(N(IF(R9="USD",S9,IF(R9="IRR",S9/INDEX('Assumptions & FX Reference'!$B$5:$B$25,MATCH(Q9,'Assumptions & FX Reference'!$A$5:$A$25,0)),IF(R9="EUR",S9*INDEX('Assumptions & FX Reference'!$C$5:$C$25,MATCH(Q9,'Assumptions & FX Reference'!$A$5:$A$25,0))/INDEX('Assumptions & FX Reference'!$B$5:$B$25,MATCH(Q9,'Assumptions & FX Reference'!$A$5:$A$25,0)),"(Not stated)"))))>0,IF(R9="USD",S9,IF(R9="IRR",S9/INDEX('Assumptions & FX Reference'!$B$5:$B$25,MATCH(Q9,'Assumptions & FX Reference'!$A$5:$A$25,0)),IF(R9="EUR",S9*INDEX('Assumptions & FX Reference'!$C$5:$C$25,MATCH(Q9,'Assumptions & FX Reference'!$A$5:$A$25,0))/INDEX('Assumptions & FX Reference'!$B$5:$B$25,MATCH(Q9,'Assumptions & FX Reference'!$A$5:$A$25,0)),"(Not stated)"))),"(FX rate not entered for this year)"),"(FX rate not entered for this year)"))) -> (Cost year not stated / not a Jalali year) | V9: =IF(NOT(ISNUMBER(S9)),"(Not stated)",IF(NOT(ISNUMBER(Q9)),"(Cost year not stated / not a Jalali year)",IFERROR(IF(N(IF(R9="IRR",S9,IF(R9="USD",S9*INDEX('Assumptions & FX Reference'!$B$5:$B$25,MATCH(Q9,'Assumptions & FX Reference'!$A$5:$A$25,0)),IF(R9="EUR",S9*INDEX('Assumptions & FX Reference'!$C$5:$C$25,MATCH(Q9,'Assumptions & FX Reference'!$A$5:$A$25,0)),"(Not stated)"))))>0,IF(R9="IRR",S9,IF(R9="USD",S9*INDEX('Assumptions & FX Reference'!$B$5:$B$25,MATCH(Q9,'Assumptions & FX Reference'!$A$5:$A$25,0)),IF(R9="EUR",S9*INDEX('Assumptions & FX Reference'!$C$5:$C$25,MATCH(Q9,'Assumptions & FX Reference'!$A$5:$A$25,0)),"(Not stated)"))),"(FX rate not entered for this year)"),"(FX rate not entered for this year)"))) -> (Cost year not stated / not a Jalali year) | W9: Not Stated | X9: Not Stated | Y9: Not Stated | Z9: نمونه_قیمتی_نمک_زدایی_overall.xlsx (Sheet packages, item 8, row 10) | AA9: Price ($) = 15,000 USD. Same figure in 18061405_Pump_only_CSV.csv (section packages, item 8, file row 65), where a separate 'Customs and transportation ($)' column = 900 USD (not included in Unit Price Reference). Sample lists a launcher only (no receiver); quantity, cost year and basis not stated. | AB9: Y
A10: 6 | B10: Oily Water Separator (API Separator) | C10: Gachsaran 4 Development Plan (Proj No. 591111) | D10: SU-701 | E10: SEP | F10: SEP-OWS | G10: Not Stated | H10: Not Stated | I10: Oily Water Separator SU-701 (Process Data Sheet, E.Process item 7.40) | J10: Not Stated | K10: Not Stated | L10: Not Stated | M10: Not Stated | N10: Not Stated | O10: Not Stated | P10: Not Stated | Q10: 1402 | R10: IRR | S10: Not Stated | T10: =IF(NOT(ISNUMBER(S10)),"(Not stated)",IF(NOT(ISNUMBER(Q10)),"(Cost year not stated / not a Jalali year)",IFERROR(IF(N(IF(R10="EUR",S10,IF(R10="IRR",S10/INDEX('Assumptions & FX Reference'!$C$5:$C$25,MATCH(Q10,'Assumptions & FX Reference'!$A$5:$A$25,0)),IF(R10="USD",S10*INDEX('Assumptions & FX Reference'!$B$5:$B$25,MATCH(Q10,'Assumptions & FX Reference'!$A$5:$A$25,0))/INDEX('Assumptions & FX Reference'!$C$5:$C$25,MATCH(Q10,'Assumptions & FX Reference'!$A$5:$A$25,0)),"(Not stated)"))))>0,IF(R10="EUR",S10,IF(R10="IRR",S10/INDEX('Assumptions & FX Reference'!$C$5:$C$25,MATCH(Q10,'Assumptions & FX Reference'!$A$5:$A$25,0)),IF(R10="USD",S10*INDEX('Assumptions & FX Reference'!$B$5:$B$25,MATCH(Q10,'Assumptions & FX Reference'!$A$5:$A$25,0))/INDEX('Assumptions & FX Reference'!$C$5:$C$25,MATCH(Q10,'Assumptions & FX Reference'!$A$5:$A$25,0)),"(Not stated)"))),"(FX rate not entered for this year)"),"(FX rate not entered for this year)"))) -> (Not stated) | U10: =IF(NOT(ISNUMBER(S10)),"(Not stated)",IF(NOT(ISNUMBER(Q10)),"(Cost year not stated / not a Jalali year)",IFERROR(IF(N(IF(R10="USD",S10,IF(R10="IRR",S10/INDEX('Assumptions & FX Reference'!$B$5:$B$25,MATCH(Q10,'Assumptions & FX Reference'!$A$5:$A$25,0)),IF(R10="EUR",S10*INDEX('Assumptions & FX Reference'!$C$5:$C$25,MATCH(Q10,'Assumptions & FX Reference'!$A$5:$A$25,0))/INDEX('Assumptions & FX Reference'!$B$5:$B$25,MATCH(Q10,'Assumptions & FX Reference'!$A$5:$A$25,0)),"(Not stated)"))))>0,IF(R10="USD",S10,IF(R10="IRR",S10/INDEX('Assumptions & FX Reference'!$B$5:$B$25,MATCH(Q10,'Assumptions & FX Reference'!$A$5:$A$25,0)),IF(R10="EUR",S10*INDEX('Assumptions & FX Reference'!$C$5:$C$25,MATCH(Q10,'Assumptions & FX Reference'!$A$5:$A$25,0))/INDEX('Assumptions & FX Reference'!$B$5:$B$25,MATCH(Q10,'Assumptions & FX Reference'!$A$5:$A$25,0)),"(Not stated)"))),"(FX rate not entered for this year)"),"(FX rate not entered for this year)"))) -> (Not stated) | V10: =IF(NOT(ISNUMBER(S10)),"(Not stated)",IF(NOT(ISNUMBER(Q10)),"(Cost year not stated / not a Jalali year)",IFERROR(IF(N(IF(R10="IRR",S10,IF(R10="USD",S10*INDEX('Assumptions & FX Reference'!$B$5:$B$25,MATCH(Q10,'Assumptions & FX Reference'!$A$5:$A$25,0)),IF(R10="EUR",S10*INDEX('Assumptions & FX Reference'!$C$5:$C$25,MATCH(Q10,'Assumptions & FX Reference'!$A$5:$A$25,0)),"(Not stated)"))))>0,IF(R10="IRR",S10,IF(R10="USD",S10*INDEX('Assumptions & FX Reference'!$B$5:$B$25,MATCH(Q10,'Assumptions & FX Reference'!$A$5:$A$25,0)),IF(R10="EUR",S10*INDEX('Assumptions & FX Reference'!$C$5:$C$25,MATCH(Q10,'Assumptions & FX Reference'!$A$5:$A$25,0)),"(Not stated)"))),"(FX rate not entered for this year)"),"(FX rate not entered for this year)"))) -> (Not stated) | W10: Not Stated | X10: Class 3 (Basic) | Y10: Basic Engineering | Z10: PEP-Rev.140205_عزيزيان_Gachsaran_4.xlsx (Sheet E.Process, row 110) | AA10: No price in the Gachsaran 4 procurement table. P.ME lists only the Oily Water Separator Pump P-750 (row 55; a pump, out of scope). The separator appears elsewhere only as civil work: C.OTHERS-1 row 18 (API SEPARATOR, civil quantities), E.Civil row 95 (Oily Water Separator Section And Details) and, in Maroon 3, CV1405 row 30 ('OILY WTER SEPARATOR', 12 m x 6 m, 75 m2, 500,000,000 IRR civil base). Those are civil scope, so no price is entered here to avoid inventing one. No mechanical data sheet exists for SU-701 in E.Mechanic. Tag is not present in MASTER_TAGS / SOURCES; found by searching the source workbook. | AB10: Y
A11: 7 | B11: Portable Skimmer | C11: Gachsaran 4 Development Plan (Proj No. 591111) | D11: X-704 | E11: SEP | F11: SEP-SKM | G11: Not Stated | H11: Not Stated | I11: Portable Skimmer X-704 (Process Data Sheet, E.Process item 7.57) | J11: Not Stated | K11: Not Stated | L11: Not Stated | M11: Not Stated | N11: Not Stated | O11: Not Stated | P11: Not Stated | Q11: 1402 | R11: IRR | S11: Not Stated | T11: =IF(NOT(ISNUMBER(S11)),"(Not stated)",IF(NOT(ISNUMBER(Q11)),"(Cost year not stated / not a Jalali year)",IFERROR(IF(N(IF(R11="EUR",S11,IF(R11="IRR",S11/INDEX('Assumptions & FX Reference'!$C$5:$C$25,MATCH(Q11,'Assumptions & FX Reference'!$A$5:$A$25,0)),IF(R11="USD",S11*INDEX('Assumptions & FX Reference'!$B$5:$B$25,MATCH(Q11,'Assumptions & FX Reference'!$A$5:$A$25,0))/INDEX('Assumptions & FX Reference'!$C$5:$C$25,MATCH(Q11,'Assumptions & FX Reference'!$A$5:$A$25,0)),"(Not stated)"))))>0,IF(R11="EUR",S11,IF(R11="IRR",S11/INDEX('Assumptions & FX Reference'!$C$5:$C$25,MATCH(Q11,'Assumptions & FX Reference'!$A$5:$A$25,0)),IF(R11="USD",S11*INDEX('Assumptions & FX Reference'!$B$5:$B$25,MATCH(Q11,'Assumptions & FX Reference'!$A$5:$A$25,0))/INDEX('Assumptions & FX Reference'!$C$5:$C$25,MATCH(Q11,'Assumptions & FX Reference'!$A$5:$A$25,0)),"(Not stated)"))),"(FX rate not entered for this year)"),"(FX rate not entered for this year)"))) -> (Not stated) | U11: =IF(NOT(ISNUMBER(S11)),"(Not stated)",IF(NOT(ISNUMBER(Q11)),"(Cost year not stated / not a Jalali year)",IFERROR(IF(N(IF(R11="USD",S11,IF(R11="IRR",S11/INDEX('Assumptions & FX Reference'!$B$5:$B$25,MATCH(Q11,'Assumptions & FX Reference'!$A$5:$A$25,0)),IF(R11="EUR",S11*INDEX('Assumptions & FX Reference'!$C$5:$C$25,MATCH(Q11,'Assumptions & FX Reference'!$A$5:$A$25,0))/INDEX('Assumptions & FX Reference'!$B$5:$B$25,MATCH(Q11,'Assumptions & FX Reference'!$A$5:$A$25,0)),"(Not stated)"))))>0,IF(R11="USD",S11,IF(R11="IRR",S11/INDEX('Assumptions & FX Reference'!$B$5:$B$25,MATCH(Q11,'Assumptions & FX Reference'!$A$5:$A$25,0)),IF(R11="EUR",S11*INDEX('Assumptions & FX Reference'!$C$5:$C$25,MATCH(Q11,'Assumptions & FX Reference'!$A$5:$A$25,0))/INDEX('Assumptions & FX Reference'!$B$5:$B$25,MATCH(Q11,'Assumptions & FX Reference'!$A$5:$A$25,0)),"(Not stated)"))),"(FX rate not entered for this year)"),"(FX rate not entered for this year)"))) -> (Not stated) | V11: =IF(NOT(ISNUMBER(S11)),"(Not stated)",IF(NOT(ISNUMBER(Q11)),"(Cost year not stated / not a Jalali year)",IFERROR(IF(N(IF(R11="IRR",S11,IF(R11="USD",S11*INDEX('Assumptions & FX Reference'!$B$5:$B$25,MATCH(Q11,'Assumptions & FX Reference'!$A$5:$A$25,0)),IF(R11="EUR",S11*INDEX('Assumptions & FX Reference'!$C$5:$C$25,MATCH(Q11,'Assumptions & FX Reference'!$A$5:$A$25,0)),"(Not stated)"))))>0,IF(R11="IRR",S11,IF(R11="USD",S11*INDEX('Assumptions & FX Reference'!$B$5:$B$25,MATCH(Q11,'Assumptions & FX Reference'!$A$5:$A$25,0)),IF(R11="EUR",S11*INDEX('Assumptions & FX Reference'!$C$5:$C$25,MATCH(Q11,'Assumptions & FX Reference'!$A$5:$A$25,0)),"(Not stated)"))),"(FX rate not entered for this year)"),"(FX rate not entered for this year)"))) -> (Not stated) | W11: Not Stated | X11: Class 3 (Basic) | Y11: Basic Engineering | Z11: PEP-Rev.140205_عزيزيان_Gachsaran_4.xlsx (Sheet E.Process, row 127) | AA11: No price in the Gachsaran 4 procurement table. Only a process data sheet is listed (no mechanical data sheet, no P.ME row). Not to be confused with Oil Skimmer Tank OS-201 (P.ME row 26, a tank priced per kg), which is excluded per the tank/drum scope. Tag is not present in MASTER_TAGS / SOURCES; found by searching the source workbook. | AB11: Y
A12: 8 | B12: Crude Aerial Cooler (Air Cooler) | C12: Not Stated (reference price sample, file نمونه_قیمتی_نمک_زدایی_overall.xlsx) | D12: (No Tag - price sample item 1) | E12: ACX | F12: ACX-AIR | G12: Not Stated | H12: Not Stated | I12: Air-cooled heat exchanger (crude service); Draft: Forced; fixed pitch, TEFC fan motors, speed control by VFD (per CSV) | J12: Duty 2.9 x 1.1 MW; bare area 475.7 m2/unit; 2 bays/unit; 4 fans/unit | K12: 7 | L12: 100 | M12: Header: C.S; Tube: C.S | N12: Not Stated | O12: 104.8 kW total consumed power per unit | P12: Not Stated | Q12: Not Stated | R12: USD | S12: 2200000 | T12: =IF(NOT(ISNUMBER(S12)),"(Not stated)",IF(NOT(ISNUMBER(Q12)),"(Cost year not stated / not a Jalali year)",IFERROR(IF(N(IF(R12="EUR",S12,IF(R12="IRR",S12/INDEX('Assumptions & FX Reference'!$C$5:$C$25,MATCH(Q12,'Assumptions & FX Reference'!$A$5:$A$25,0)),IF(R12="USD",S12*INDEX('Assumptions & FX Reference'!$B$5:$B$25,MATCH(Q12,'Assumptions & FX Reference'!$A$5:$A$25,0))/INDEX('Assumptions & FX Reference'!$C$5:$C$25,MATCH(Q12,'Assumptions & FX Reference'!$A$5:$A$25,0)),"(Not stated)"))))>0,IF(R12="EUR",S12,IF(R12="IRR",S12/INDEX('Assumptions & FX Reference'!$C$5:$C$25,MATCH(Q12,'Assumptions & FX Reference'!$A$5:$A$25,0)),IF(R12="USD",S12*INDEX('Assumptions & FX Reference'!$B$5:$B$25,MATCH(Q12,'Assumptions & FX Reference'!$A$5:$A$25,0))/INDEX('Assumptions & FX Reference'!$C$5:$C$25,MATCH(Q12,'Assumptions & FX Reference'!$A$5:$A$25,0)),"(Not stated)"))),"(FX rate not entered for this year)"),"(FX rate not entered for this year)"))) -> (Cost year not stated / not a Jalali year) | U12: =IF(NOT(ISNUMBER(S12)),"(Not stated)",IF(NOT(ISNUMBER(Q12)),"(Cost year not stated / not a Jalali year)",IFERROR(IF(N(IF(R12="USD",S12,IF(R12="IRR",S12/INDEX('Assumptions & FX Reference'!$B$5:$B$25,MATCH(Q12,'Assumptions & FX Reference'!$A$5:$A$25,0)),IF(R12="EUR",S12*INDEX('Assumptions & FX Reference'!$C$5:$C$25,MATCH(Q12,'Assumptions & FX Reference'!$A$5:$A$25,0))/INDEX('Assumptions & FX Reference'!$B$5:$B$25,MATCH(Q12,'Assumptions & FX Reference'!$A$5:$A$25,0)),"(Not stated)"))))>0,IF(R12="USD",S12,IF(R12="IRR",S12/INDEX('Assumptions & FX Reference'!$B$5:$B$25,MATCH(Q12,'Assumptions & FX Reference'!$A$5:$A$25,0)),IF(R12="EUR",S12*INDEX('Assumptions & FX Reference'!$C$5:$C$25,MATCH(Q12,'Assumptions & FX Reference'!$A$5:$A$25,0))/INDEX('Assumptions & FX Reference'!$B$5:$B$25,MATCH(Q12,'Assumptions & FX Reference'!$A$5:$A$25,0)),"(Not stated)"))),"(FX rate not entered for this year)"),"(FX rate not entered for this year)"))) -> (Cost year not stated / not a Jalali year) | V12: =IF(NOT(ISNUMBER(S12)),"(Not stated)",IF(NOT(ISNUMBER(Q12)),"(Cost year not stated / not a Jalali year)",IFERROR(IF(N(IF(R12="IRR",S12,IF(R12="USD",S12*INDEX('Assumptions & FX Reference'!$B$5:$B$25,MATCH(Q12,'Assumptions & FX Reference'!$A$5:$A$25,0)),IF(R12="EUR",S12*INDEX('Assumptions & FX Reference'!$C$5:$C$25,MATCH(Q12,'Assumptions & FX Reference'!$A$5:$A$25,0)),"(Not stated)"))))>0,IF(R12="IRR",S12,IF(R12="USD",S12*INDEX('Assumptions & FX Reference'!$B$5:$B$25,MATCH(Q12,'Assumptions & FX Reference'!$A$5:$A$25,0)),IF(R12="EUR",S12*INDEX('Assumptions & FX Reference'!$C$5:$C$25,MATCH(Q12,'Assumptions & FX Reference'!$A$5:$A$25,0)),"(Not stated)"))),"(FX rate not entered for this year)"),"(FX rate not entered for this year)"))) -> (Cost year not stated / not a Jalali year) | W12: Not Stated | X12: Not Stated | Y12: Not Stated | Z12: نمونه_قیمتی_نمک_زدایی_overall.xlsx (Sheet AIR COOLERS, item 1, row 3) | AA12: Price ($) = 2,200,000 USD. Same row in 18061405_Pump_only_CSV.csv (section AIR COOLERS, file row 43; area 476 m2, 105 kW rounded) with 'Customs and transportation ($)' = 132,000 USD (not included). The 'fixed pitch-TEFC-speed control by VFD' text sits under the Header Type column in the CSV and is blank in the xlsx, so it is recorded as a service note. Duty printed as '2.9 x 1.1' in source. Quantity, cost year and basis not stated. No air cooler found in KPL, Pazanan 2, Gachsaran 4 or Maroon 3 files. | AB12: Y
A13: 9 | B13: HVAC for Accommodation | C13: Gachsaran 4 Development Plan (Proj No. 591111) | D13: (No Tag - P.ME item 66.1) | E13: HVAC | F13: HVAC-SYS | G13: 1 | H13: SET | I13: HVAC for Accommodation (P.ME item 66.1 under HVAC group item 66) | J13: Not Stated | K13: Not Stated | L13: Not Stated | M13: Not Stated | N13: Not Stated | O13: Not Stated | P13: Not Stated | Q13: 1402 | R13: IRR | S13: 1300000000 | T13: =IF(NOT(ISNUMBER(S13)),"(Not stated)",IF(NOT(ISNUMBER(Q13)),"(Cost year not stated / not a Jalali year)",IFERROR(IF(N(IF(R13="EUR",S13,IF(R13="IRR",S13/INDEX('Assumptions & FX Reference'!$C$5:$C$25,MATCH(Q13,'Assumptions & FX Reference'!$A$5:$A$25,0)),IF(R13="USD",S13*INDEX('Assumptions & FX Reference'!$B$5:$B$25,MATCH(Q13,'Assumptions & FX Reference'!$A$5:$A$25,0))/INDEX('Assumptions & FX Reference'!$C$5:$C$25,MATCH(Q13,'Assumptions & FX Reference'!$A$5:$A$25,0)),"(Not stated)"))))>0,IF(R13="EUR",S13,IF(R13="IRR",S13/INDEX('Assumptions & FX Reference'!$C$5:$C$25,MATCH(Q13,'Assumptions & FX Reference'!$A$5:$A$25,0)),IF(R13="USD",S13*INDEX('Assumptions & FX Reference'!$B$5:$B$25,MATCH(Q13,'Assumptions & FX Reference'!$A$5:$A$25,0))/INDEX('Assumptions & FX Reference'!$C$5:$C$25,MATCH(Q13,'Assumptions & FX Reference'!$A$5:$A$25,0)),"(Not stated)"))),"(FX rate not entered for this year)"),"(FX rate not entered for this year)"))) -> 2455.1464 | U13: =IF(NOT(ISNUMBER(S13)),"(Not stated)",IF(NOT(ISNUMBER(Q13)),"(Cost year not stated / not a Jalali year)",IFERROR(IF(N(IF(R13="USD",S13,IF(R13="IRR",S13/INDEX('Assumptions & FX Reference'!$B$5:$B$25,MATCH(Q13,'Assumptions & FX Reference'!$A$5:$A$25,0)),IF(R13="EUR",S13*INDEX('Assumptions & FX Reference'!$C$5:$C$25,MATCH(Q13,'Assumptions & FX Reference'!$A$5:$A$25,0))/INDEX('Assumptions & FX Reference'!$B$5:$B$25,MATCH(Q13,'Assumptions & FX Reference'!$A$5:$A$25,0)),"(Not stated)"))))>0,IF(R13="USD",S13,IF(R13="IRR",S13/INDEX('Assumptions & FX Reference'!$B$5:$B$25,MATCH(Q13,'Assumptions & FX Reference'!$A$5:$A$25,0)),IF(R13="EUR",S13*INDEX('Assumptions & FX Reference'!$C$5:$C$25,MATCH(Q13,'Assumptions & FX Reference'!$A$5:$A$25,0))/INDEX('Assumptions & FX Reference'!$B$5:$B$25,MATCH(Q13,'Assumptions & FX Reference'!$A$5:$A$25,0)),"(Not stated)"))),"(FX rate not entered for this year)"),"(FX rate not entered for this year)"))) -> 3095.2381 | V13: =IF(NOT(ISNUMBER(S13)),"(Not stated)",IF(NOT(ISNUMBER(Q13)),"(Cost year not stated / not a Jalali year)",IFERROR(IF(N(IF(R13="IRR",S13,IF(R13="USD",S13*INDEX('Assumptions & FX Reference'!$B$5:$B$25,MATCH(Q13,'Assumptions & FX Reference'!$A$5:$A$25,0)),IF(R13="EUR",S13*INDEX('Assumptions & FX Reference'!$C$5:$C$25,MATCH(Q13,'Assumptions & FX Reference'!$A$5:$A$25,0)),"(Not stated)"))))>0,IF(R13="IRR",S13,IF(R13="USD",S13*INDEX('Assumptions & FX Reference'!$B$5:$B$25,MATCH(Q13,'Assumptions & FX Reference'!$A$5:$A$25,0)),IF(R13="EUR",S13*INDEX('Assumptions & FX Reference'!$C$5:$C$25,MATCH(Q13,'Assumptions & FX Reference'!$A$5:$A$25,0)),"(Not stated)"))),"(FX rate not entered for this year)"),"(FX rate not entered for this year)"))) -> 1300000000 | W13: FOB | X13: Class 3 (Basic) | Y13: Basic Engineering | Z13: PEP-Rev.140205_عزيزيان_Gachsaran_4.xlsx (Sheet P.ME, row 84) | AA13: Unit cost without overhead factor (هزینه واحد بدون ضریب). HVAC group header row 83 carries its own freight allocation of 1,207,442,136.32 IRR (not included); Customs clearance not stated. Equipment list / data sheets are in the E.HVAC document set. | AB13: Y
A14: 10 | B14: HVAC for DE4 Switchgear Room | C14: Gachsaran 4 Development Plan (Proj No. 591111) | D14: (No Tag - P.ME item 66.2) | E14: HVAC | F14: HVAC-SYS | G14: 1 | H14: SET | I14: HVAC for DE4 Switchgear Room (P.ME item 66.2 under HVAC group item 66) | J14: Not Stated | K14: Not Stated | L14: Not Stated | M14: Not Stated | N14: Not Stated | O14: Not Stated | P14: Not Stated | Q14: 1402 | R14: IRR | S14: 115920000000 | T14: =IF(NOT(ISNUMBER(S14)),"(Not stated)",IF(NOT(ISNUMBER(Q14)),"(Cost year not stated / not a Jalali year)",IFERROR(IF(N(IF(R14="EUR",S14,IF(R14="IRR",S14/INDEX('Assumptions & FX Reference'!$C$5:$C$25,MATCH(Q14,'Assumptions & FX Reference'!$A$5:$A$25,0)),IF(R14="USD",S14*INDEX('Assumptions & FX Reference'!$B$5:$B$25,MATCH(Q14,'Assumptions & FX Reference'!$A$5:$A$25,0))/INDEX('Assumptions & FX Reference'!$C$5:$C$25,MATCH(Q14,'Assumptions & FX Reference'!$A$5:$A$25,0)),"(Not stated)"))))>0,IF(R14="EUR",S14,IF(R14="IRR",S14/INDEX('Assumptions & FX Reference'!$C$5:$C$25,MATCH(Q14,'Assumptions & FX Reference'!$A$5:$A$25,0)),IF(R14="USD",S14*INDEX('Assumptions & FX Reference'!$B$5:$B$25,MATCH(Q14,'Assumptions & FX Reference'!$A$5:$A$25,0))/INDEX('Assumptions & FX Reference'!$C$5:$C$25,MATCH(Q14,'Assumptions & FX Reference'!$A$5:$A$25,0)),"(Not stated)"))),"(FX rate not entered for this year)"),"(FX rate not entered for this year)"))) -> 218923.51 | U14: =IF(NOT(ISNUMBER(S14)),"(Not stated)",IF(NOT(ISNUMBER(Q14)),"(Cost year not stated / not a Jalali year)",IFERROR(IF(N(IF(R14="USD",S14,IF(R14="IRR",S14/INDEX('Assumptions & FX Reference'!$B$5:$B$25,MATCH(Q14,'Assumptions & FX Reference'!$A$5:$A$25,0)),IF(R14="EUR",S14*INDEX('Assumptions & FX Reference'!$C$5:$C$25,MATCH(Q14,'Assumptions & FX Reference'!$A$5:$A$25,0))/INDEX('Assumptions & FX Reference'!$B$5:$B$25,MATCH(Q14,'Assumptions & FX Reference'!$A$5:$A$25,0)),"(Not stated)"))))>0,IF(R14="USD",S14,IF(R14="IRR",S14/INDEX('Assumptions & FX Reference'!$B$5:$B$25,MATCH(Q14,'Assumptions & FX Reference'!$A$5:$A$25,0)),IF(R14="EUR",S14*INDEX('Assumptions & FX Reference'!$C$5:$C$25,MATCH(Q14,'Assumptions & FX Reference'!$A$5:$A$25,0))/INDEX('Assumptions & FX Reference'!$B$5:$B$25,MATCH(Q14,'Assumptions & FX Reference'!$A$5:$A$25,0)),"(Not stated)"))),"(FX rate not entered for this year)"),"(FX rate not entered for this year)"))) -> 276000 | V14: =IF(NOT(ISNUMBER(S14)),"(Not stated)",IF(NOT(ISNUMBER(Q14)),"(Cost year not stated / not a Jalali year)",IFERROR(IF(N(IF(R14="IRR",S14,IF(R14="USD",S14*INDEX('Assumptions & FX Reference'!$B$5:$B$25,MATCH(Q14,'Assumptions & FX Reference'!$A$5:$A$25,0)),IF(R14="EUR",S14*INDEX('Assumptions & FX Reference'!$C$5:$C$25,MATCH(Q14,'Assumptions & FX Reference'!$A$5:$A$25,0)),"(Not stated)"))))>0,IF(R14="IRR",S14,IF(R14="USD",S14*INDEX('Assumptions & FX Reference'!$B$5:$B$25,MATCH(Q14,'Assumptions & FX Reference'!$A$5:$A$25,0)),IF(R14="EUR",S14*INDEX('Assumptions & FX Reference'!$C$5:$C$25,MATCH(Q14,'Assumptions & FX Reference'!$A$5:$A$25,0)),"(Not stated)"))),"(FX rate not entered for this year)"),"(FX rate not entered for this year)"))) -> 115920000000 | W14: FOB | X14: Class 3 (Basic) | Y14: Basic Engineering | Z14: PEP-Rev.140205_عزيزيان_Gachsaran_4.xlsx (Sheet P.ME, row 85) | AA14: Unit cost without overhead factor (هزینه واحد بدون ضریب). Source formula = 276,000 USD x USD_Change_IRR (420,000 IRR/USD) = 115,920,000,000 IRR. HVAC group header row 83 carries its own freight allocation of 1,207,442,136.32 IRR (not included); Customs clearance not stated. Equipment list / data sheets are in the E.HVAC document set. | AB14: Y
A15: 11 | B15: HVAC for DE4 Control Room | C15: Gachsaran 4 Development Plan (Proj No. 591111) | D15: (No Tag - P.ME item 66.3) | E15: HVAC | F15: HVAC-SYS | G15: 1 | H15: SET | I15: HVAC for DE4 Control Room (P.ME item 66.3 under HVAC group item 66) | J15: Not Stated | K15: Not Stated | L15: Not Stated | M15: Not Stated | N15: Not Stated | O15: Not Stated | P15: Not Stated | Q15: 1402 | R15: IRR | S15: 141120000000 | T15: =IF(NOT(ISNUMBER(S15)),"(Not stated)",IF(NOT(ISNUMBER(Q15)),"(Cost year not stated / not a Jalali year)",IFERROR(IF(N(IF(R15="EUR",S15,IF(R15="IRR",S15/INDEX('Assumptions & FX Reference'!$C$5:$C$25,MATCH(Q15,'Assumptions & FX Reference'!$A$5:$A$25,0)),IF(R15="USD",S15*INDEX('Assumptions & FX Reference'!$B$5:$B$25,MATCH(Q15,'Assumptions & FX Reference'!$A$5:$A$25,0))/INDEX('Assumptions & FX Reference'!$C$5:$C$25,MATCH(Q15,'Assumptions & FX Reference'!$A$5:$A$25,0)),"(Not stated)"))))>0,IF(R15="EUR",S15,IF(R15="IRR",S15/INDEX('Assumptions & FX Reference'!$C$5:$C$25,MATCH(Q15,'Assumptions & FX Reference'!$A$5:$A$25,0)),IF(R15="USD",S15*INDEX('Assumptions & FX Reference'!$B$5:$B$25,MATCH(Q15,'Assumptions & FX Reference'!$A$5:$A$25,0))/INDEX('Assumptions & FX Reference'!$C$5:$C$25,MATCH(Q15,'Assumptions & FX Reference'!$A$5:$A$25,0)),"(Not stated)"))),"(FX rate not entered for this year)"),"(FX rate not entered for this year)"))) -> 266515.58 | U15: =IF(NOT(ISNUMBER(S15)),"(Not stated)",IF(NOT(ISNUMBER(Q15)),"(Cost year not stated / not a Jalali year)",IFERROR(IF(N(IF(R15="USD",S15,IF(R15="IRR",S15/INDEX('Assumptions & FX Reference'!$B$5:$B$25,MATCH(Q15,'Assumptions & FX Reference'!$A$5:$A$25,0)),IF(R15="EUR",S15*INDEX('Assumptions & FX Reference'!$C$5:$C$25,MATCH(Q15,'Assumptions & FX Reference'!$A$5:$A$25,0))/INDEX('Assumptions & FX Reference'!$B$5:$B$25,MATCH(Q15,'Assumptions & FX Reference'!$A$5:$A$25,0)),"(Not stated)"))))>0,IF(R15="USD",S15,IF(R15="IRR",S15/INDEX('Assumptions & FX Reference'!$B$5:$B$25,MATCH(Q15,'Assumptions & FX Reference'!$A$5:$A$25,0)),IF(R15="EUR",S15*INDEX('Assumptions & FX Reference'!$C$5:$C$25,MATCH(Q15,'Assumptions & FX Reference'!$A$5:$A$25,0))/INDEX('Assumptions & FX Reference'!$B$5:$B$25,MATCH(Q15,'Assumptions & FX Reference'!$A$5:$A$25,0)),"(Not stated)"))),"(FX rate not entered for this year)"),"(FX rate not entered for this year)"))) -> 336000 | V15: =IF(NOT(ISNUMBER(S15)),"(Not stated)",IF(NOT(ISNUMBER(Q15)),"(Cost year not stated / not a Jalali year)",IFERROR(IF(N(IF(R15="IRR",S15,IF(R15="USD",S15*INDEX('Assumptions & FX Reference'!$B$5:$B$25,MATCH(Q15,'Assumptions & FX Reference'!$A$5:$A$25,0)),IF(R15="EUR",S15*INDEX('Assumptions & FX Reference'!$C$5:$C$25,MATCH(Q15,'Assumptions & FX Reference'!$A$5:$A$25,0)),"(Not stated)"))))>0,IF(R15="IRR",S15,IF(R15="USD",S15*INDEX('Assumptions & FX Reference'!$B$5:$B$25,MATCH(Q15,'Assumptions & FX Reference'!$A$5:$A$25,0)),IF(R15="EUR",S15*INDEX('Assumptions & FX Reference'!$C$5:$C$25,MATCH(Q15,'Assumptions & FX Reference'!$A$5:$A$25,0)),"(Not stated)"))),"(FX rate not entered for this year)"),"(FX rate not entered for this year)"))) -> 141120000000 | W15: FOB | X15: Class 3 (Basic) | Y15: Basic Engineering | Z15: PEP-Rev.140205_عزيزيان_Gachsaran_4.xlsx (Sheet P.ME, row 86) | AA15: Unit cost without overhead factor (هزینه واحد بدون ضریب). Source formula = 336,000 USD x USD_Change_IRR (420,000 IRR/USD) = 141,120,000,000 IRR. HVAC group header row 83 carries its own freight allocation of 1,207,442,136.32 IRR (not included); Customs clearance not stated. Equipment list / data sheets are in the E.HVAC document set. | AB15: Y
A16: 12 | B16: HVAC for 33 kV Station | C16: Gachsaran 4 Development Plan (Proj No. 591111) | D16: (No Tag - P.ME item 66.4) | E16: HVAC | F16: HVAC-SYS | G16: 1 | H16: SET | I16: HVAC for 33 kV Station (P.ME item 66.4 under HVAC group item 66) | J16: Not Stated | K16: Not Stated | L16: Not Stated | M16: Not Stated | N16: Not Stated | O16: Not Stated | P16: Not Stated | Q16: 1402 | R16: IRR | S16: 92400000000 | T16: =IF(NOT(ISNUMBER(S16)),"(Not stated)",IF(NOT(ISNUMBER(Q16)),"(Cost year not stated / not a Jalali year)",IFERROR(IF(N(IF(R16="EUR",S16,IF(R16="IRR",S16/INDEX('Assumptions & FX Reference'!$C$5:$C$25,MATCH(Q16,'Assumptions & FX Reference'!$A$5:$A$25,0)),IF(R16="USD",S16*INDEX('Assumptions & FX Reference'!$B$5:$B$25,MATCH(Q16,'Assumptions & FX Reference'!$A$5:$A$25,0))/INDEX('Assumptions & FX Reference'!$C$5:$C$25,MATCH(Q16,'Assumptions & FX Reference'!$A$5:$A$25,0)),"(Not stated)"))))>0,IF(R16="EUR",S16,IF(R16="IRR",S16/INDEX('Assumptions & FX Reference'!$C$5:$C$25,MATCH(Q16,'Assumptions & FX Reference'!$A$5:$A$25,0)),IF(R16="USD",S16*INDEX('Assumptions & FX Reference'!$B$5:$B$25,MATCH(Q16,'Assumptions & FX Reference'!$A$5:$A$25,0))/INDEX('Assumptions & FX Reference'!$C$5:$C$25,MATCH(Q16,'Assumptions & FX Reference'!$A$5:$A$25,0)),"(Not stated)"))),"(FX rate not entered for this year)"),"(FX rate not entered for this year)"))) -> 174504.25 | U16: =IF(NOT(ISNUMBER(S16)),"(Not stated)",IF(NOT(ISNUMBER(Q16)),"(Cost year not stated / not a Jalali year)",IFERROR(IF(N(IF(R16="USD",S16,IF(R16="IRR",S16/INDEX('Assumptions & FX Reference'!$B$5:$B$25,MATCH(Q16,'Assumptions & FX Reference'!$A$5:$A$25,0)),IF(R16="EUR",S16*INDEX('Assumptions & FX Reference'!$C$5:$C$25,MATCH(Q16,'Assumptions & FX Reference'!$A$5:$A$25,0))/INDEX('Assumptions & FX Reference'!$B$5:$B$25,MATCH(Q16,'Assumptions & FX Reference'!$A$5:$A$25,0)),"(Not stated)"))))>0,IF(R16="USD",S16,IF(R16="IRR",S16/INDEX('Assumptions & FX Reference'!$B$5:$B$25,MATCH(Q16,'Assumptions & FX Reference'!$A$5:$A$25,0)),IF(R16="EUR",S16*INDEX('Assumptions & FX Reference'!$C$5:$C$25,MATCH(Q16,'Assumptions & FX Reference'!$A$5:$A$25,0))/INDEX('Assumptions & FX Reference'!$B$5:$B$25,MATCH(Q16,'Assumptions & FX Reference'!$A$5:$A$25,0)),"(Not stated)"))),"(FX rate not entered for this year)"),"(FX rate not entered for this year)"))) -> 220000 | V16: =IF(NOT(ISNUMBER(S16)),"(Not stated)",IF(NOT(ISNUMBER(Q16)),"(Cost year not stated / not a Jalali year)",IFERROR(IF(N(IF(R16="IRR",S16,IF(R16="USD",S16*INDEX('Assumptions & FX Reference'!$B$5:$B$25,MATCH(Q16,'Assumptions & FX Reference'!$A$5:$A$25,0)),IF(R16="EUR",S16*INDEX('Assumptions & FX Reference'!$C$5:$C$25,MATCH(Q16,'Assumptions & FX Reference'!$A$5:$A$25,0)),"(Not stated)"))))>0,IF(R16="IRR",S16,IF(R16="USD",S16*INDEX('Assumptions & FX Reference'!$B$5:$B$25,MATCH(Q16,'Assumptions & FX Reference'!$A$5:$A$25,0)),IF(R16="EUR",S16*INDEX('Assumptions & FX Reference'!$C$5:$C$25,MATCH(Q16,'Assumptions & FX Reference'!$A$5:$A$25,0)),"(Not stated)"))),"(FX rate not entered for this year)"),"(FX rate not entered for this year)"))) -> 92400000000 | W16: FOB | X16: Class 3 (Basic) | Y16: Basic Engineering | Z16: PEP-Rev.140205_عزيزيان_Gachsaran_4.xlsx (Sheet P.ME, row 87) | AA16: Unit cost without overhead factor (هزینه واحد بدون ضریب). Source formula = 220,000 USD x USD_Change_IRR (420,000 IRR/USD) = 92,400,000,000 IRR. HVAC group header row 83 carries its own freight allocation of 1,207,442,136.32 IRR (not included); Customs clearance not stated. Equipment list / data sheets are in the E.HVAC document set. | AB16: Y
A17: 13 | B17: HVAC for 33/3.45 Station | C17: Gachsaran 4 Development Plan (Proj No. 591111) | D17: (No Tag - P.ME item 66.5) | E17: HVAC | F17: HVAC-SYS | G17: 1 | H17: SET | I17: HVAC for 33/3.45 Station (P.ME item 66.5 under HVAC group item 66) | J17: Not Stated | K17: Not Stated | L17: Not Stated | M17: Not Stated | N17: Not Stated | O17: Not Stated | P17: Not Stated | Q17: 1402 | R17: IRR | S17: 3700000000 | T17: =IF(NOT(ISNUMBER(S17)),"(Not stated)",IF(NOT(ISNUMBER(Q17)),"(Cost year not stated / not a Jalali year)",IFERROR(IF(N(IF(R17="EUR",S17,IF(R17="IRR",S17/INDEX('Assumptions & FX Reference'!$C$5:$C$25,MATCH(Q17,'Assumptions & FX Reference'!$A$5:$A$25,0)),IF(R17="USD",S17*INDEX('Assumptions & FX Reference'!$B$5:$B$25,MATCH(Q17,'Assumptions & FX Reference'!$A$5:$A$25,0))/INDEX('Assumptions & FX Reference'!$C$5:$C$25,MATCH(Q17,'Assumptions & FX Reference'!$A$5:$A$25,0)),"(Not stated)"))))>0,IF(R17="EUR",S17,IF(R17="IRR",S17/INDEX('Assumptions & FX Reference'!$C$5:$C$25,MATCH(Q17,'Assumptions & FX Reference'!$A$5:$A$25,0)),IF(R17="USD",S17*INDEX('Assumptions & FX Reference'!$B$5:$B$25,MATCH(Q17,'Assumptions & FX Reference'!$A$5:$A$25,0))/INDEX('Assumptions & FX Reference'!$C$5:$C$25,MATCH(Q17,'Assumptions & FX Reference'!$A$5:$A$25,0)),"(Not stated)"))),"(FX rate not entered for this year)"),"(FX rate not entered for this year)"))) -> 6987.7243 | U17: =IF(NOT(ISNUMBER(S17)),"(Not stated)",IF(NOT(ISNUMBER(Q17)),"(Cost year not stated / not a Jalali year)",IFERROR(IF(N(IF(R17="USD",S17,IF(R17="IRR",S17/INDEX('Assumptions & FX Reference'!$B$5:$B$25,MATCH(Q17,'Assumptions & FX Reference'!$A$5:$A$25,0)),IF(R17="EUR",S17*INDEX('Assumptions & FX Reference'!$C$5:$C$25,MATCH(Q17,'Assumptions & FX Reference'!$A$5:$A$25,0))/INDEX('Assumptions & FX Reference'!$B$5:$B$25,MATCH(Q17,'Assumptions & FX Reference'!$A$5:$A$25,0)),"(Not stated)"))))>0,IF(R17="USD",S17,IF(R17="IRR",S17/INDEX('Assumptions & FX Reference'!$B$5:$B$25,MATCH(Q17,'Assumptions & FX Reference'!$A$5:$A$25,0)),IF(R17="EUR",S17*INDEX('Assumptions & FX Reference'!$C$5:$C$25,MATCH(Q17,'Assumptions & FX Reference'!$A$5:$A$25,0))/INDEX('Assumptions & FX Reference'!$B$5:$B$25,MATCH(Q17,'Assumptions & FX Reference'!$A$5:$A$25,0)),"(Not stated)"))),"(FX rate not entered for this year)"),"(FX rate not entered for this year)"))) -> 8809.5238 | V17: =IF(NOT(ISNUMBER(S17)),"(Not stated)",IF(NOT(ISNUMBER(Q17)),"(Cost year not stated / not a Jalali year)",IFERROR(IF(N(IF(R17="IRR",S17,IF(R17="USD",S17*INDEX('Assumptions & FX Reference'!$B$5:$B$25,MATCH(Q17,'Assumptions & FX Reference'!$A$5:$A$25,0)),IF(R17="EUR",S17*INDEX('Assumptions & FX Reference'!$C$5:$C$25,MATCH(Q17,'Assumptions & FX Reference'!$A$5:$A$25,0)),"(Not stated)"))))>0,IF(R17="IRR",S17,IF(R17="USD",S17*INDEX('Assumptions & FX Reference'!$B$5:$B$25,MATCH(Q17,'Assumptions & FX Reference'!$A$5:$A$25,0)),IF(R17="EUR",S17*INDEX('Assumptions & FX Reference'!$C$5:$C$25,MATCH(Q17,'Assumptions & FX Reference'!$A$5:$A$25,0)),"(Not stated)"))),"(FX rate not entered for this year)"),"(FX rate not entered for this year)"))) -> 3700000000 | W17: FOB | X17: Class 3 (Basic) | Y17: Basic Engineering | Z17: PEP-Rev.140205_عزيزيان_Gachsaran_4.xlsx (Sheet P.ME, row 88) | AA17: Unit cost without overhead factor (هزینه واحد بدون ضریب). HVAC group header row 83 carries its own freight allocation of 1,207,442,136.32 IRR (not included); Customs clearance not stated. Equipment list / data sheets are in the E.HVAC document set. | AB17: Y
A18: 14 | B18: HVAC for Guard House | C18: Gachsaran 4 Development Plan (Proj No. 591111) | D18: (No Tag - P.ME item 66.6) | E18: HVAC | F18: HVAC-SYS | G18: 1 | H18: SET | I18: HVAC for Guard House (P.ME item 66.6 under HVAC group item 66) | J18: Not Stated | K18: Not Stated | L18: Not Stated | M18: Not Stated | N18: Not Stated | O18: Not Stated | P18: Not Stated | Q18: 1402 | R18: IRR | S18: 1300000000 | T18: =IF(NOT(ISNUMBER(S18)),"(Not stated)",IF(NOT(ISNUMBER(Q18)),"(Cost year not stated / not a Jalali year)",IFERROR(IF(N(IF(R18="EUR",S18,IF(R18="IRR",S18/INDEX('Assumptions & FX Reference'!$C$5:$C$25,MATCH(Q18,'Assumptions & FX Reference'!$A$5:$A$25,0)),IF(R18="USD",S18*INDEX('Assumptions & FX Reference'!$B$5:$B$25,MATCH(Q18,'Assumptions & FX Reference'!$A$5:$A$25,0))/INDEX('Assumptions & FX Reference'!$C$5:$C$25,MATCH(Q18,'Assumptions & FX Reference'!$A$5:$A$25,0)),"(Not stated)"))))>0,IF(R18="EUR",S18,IF(R18="IRR",S18/INDEX('Assumptions & FX Reference'!$C$5:$C$25,MATCH(Q18,'Assumptions & FX Reference'!$A$5:$A$25,0)),IF(R18="USD",S18*INDEX('Assumptions & FX Reference'!$B$5:$B$25,MATCH(Q18,'Assumptions & FX Reference'!$A$5:$A$25,0))/INDEX('Assumptions & FX Reference'!$C$5:$C$25,MATCH(Q18,'Assumptions & FX Reference'!$A$5:$A$25,0)),"(Not stated)"))),"(FX rate not entered for this year)"),"(FX rate not entered for this year)"))) -> 2455.1464 | U18: =IF(NOT(ISNUMBER(S18)),"(Not stated)",IF(NOT(ISNUMBER(Q18)),"(Cost year not stated / not a Jalali year)",IFERROR(IF(N(IF(R18="USD",S18,IF(R18="IRR",S18/INDEX('Assumptions & FX Reference'!$B$5:$B$25,MATCH(Q18,'Assumptions & FX Reference'!$A$5:$A$25,0)),IF(R18="EUR",S18*INDEX('Assumptions & FX Reference'!$C$5:$C$25,MATCH(Q18,'Assumptions & FX Reference'!$A$5:$A$25,0))/INDEX('Assumptions & FX Reference'!$B$5:$B$25,MATCH(Q18,'Assumptions & FX Reference'!$A$5:$A$25,0)),"(Not stated)"))))>0,IF(R18="USD",S18,IF(R18="IRR",S18/INDEX('Assumptions & FX Reference'!$B$5:$B$25,MATCH(Q18,'Assumptions & FX Reference'!$A$5:$A$25,0)),IF(R18="EUR",S18*INDEX('Assumptions & FX Reference'!$C$5:$C$25,MATCH(Q18,'Assumptions & FX Reference'!$A$5:$A$25,0))/INDEX('Assumptions & FX Reference'!$B$5:$B$25,MATCH(Q18,'Assumptions & FX Reference'!$A$5:$A$25,0)),"(Not stated)"))),"(FX rate not entered for this year)"),"(FX rate not entered for this year)"))) -> 3095.2381 | V18: =IF(NOT(ISNUMBER(S18)),"(Not stated)",IF(NOT(ISNUMBER(Q18)),"(Cost year not stated / not a Jalali year)",IFERROR(IF(N(IF(R18="IRR",S18,IF(R18="USD",S18*INDEX('Assumptions & FX Reference'!$B$5:$B$25,MATCH(Q18,'Assumptions & FX Reference'!$A$5:$A$25,0)),IF(R18="EUR",S18*INDEX('Assumptions & FX Reference'!$C$5:$C$25,MATCH(Q18,'Assumptions & FX Reference'!$A$5:$A$25,0)),"(Not stated)"))))>0,IF(R18="IRR",S18,IF(R18="USD",S18*INDEX('Assumptions & FX Reference'!$B$5:$B$25,MATCH(Q18,'Assumptions & FX Reference'!$A$5:$A$25,0)),IF(R18="EUR",S18*INDEX('Assumptions & FX Reference'!$C$5:$C$25,MATCH(Q18,'Assumptions & FX Reference'!$A$5:$A$25,0)),"(Not stated)"))),"(FX rate not entered for this year)"),"(FX rate not entered for this year)"))) -> 1300000000 | W18: FOB | X18: Class 3 (Basic) | Y18: Basic Engineering | Z18: PEP-Rev.140205_عزيزيان_Gachsaran_4.xlsx (Sheet P.ME, row 89) | AA18: Unit cost without overhead factor (هزینه واحد بدون ضریب). HVAC group header row 83 carries its own freight allocation of 1,207,442,136.32 IRR (not included); Customs clearance not stated. Equipment list / data sheets are in the E.HVAC document set. | AB18: Y
A19: 15 | B19: HVAC for Laboratory | C19: Gachsaran 4 Development Plan (Proj No. 591111) | D19: (No Tag - P.ME item 66.7) | E19: HVAC | F19: HVAC-SYS | G19: 1 | H19: SET | I19: HVAC for Laboratory (P.ME item 66.7 under HVAC group item 66) | J19: Not Stated | K19: Not Stated | L19: Not Stated | M19: Not Stated | N19: Not Stated | O19: Not Stated | P19: Not Stated | Q19: 1402 | R19: IRR | S19: 3000000000 | T19: =IF(NOT(ISNUMBER(S19)),"(Not stated)",IF(NOT(ISNUMBER(Q19)),"(Cost year not stated / not a Jalali year)",IFERROR(IF(N(IF(R19="EUR",S19,IF(R19="IRR",S19/INDEX('Assumptions & FX Reference'!$C$5:$C$25,MATCH(Q19,'Assumptions & FX Reference'!$A$5:$A$25,0)),IF(R19="USD",S19*INDEX('Assumptions & FX Reference'!$B$5:$B$25,MATCH(Q19,'Assumptions & FX Reference'!$A$5:$A$25,0))/INDEX('Assumptions & FX Reference'!$C$5:$C$25,MATCH(Q19,'Assumptions & FX Reference'!$A$5:$A$25,0)),"(Not stated)"))))>0,IF(R19="EUR",S19,IF(R19="IRR",S19/INDEX('Assumptions & FX Reference'!$C$5:$C$25,MATCH(Q19,'Assumptions & FX Reference'!$A$5:$A$25,0)),IF(R19="USD",S19*INDEX('Assumptions & FX Reference'!$B$5:$B$25,MATCH(Q19,'Assumptions & FX Reference'!$A$5:$A$25,0))/INDEX('Assumptions & FX Reference'!$C$5:$C$25,MATCH(Q19,'Assumptions & FX Reference'!$A$5:$A$25,0)),"(Not stated)"))),"(FX rate not entered for this year)"),"(FX rate not entered for this year)"))) -> 5665.7224 | U19: =IF(NOT(ISNUMBER(S19)),"(Not stated)",IF(NOT(ISNUMBER(Q19)),"(Cost year not stated / not a Jalali year)",IFERROR(IF(N(IF(R19="USD",S19,IF(R19="IRR",S19/INDEX('Assumptions & FX Reference'!$B$5:$B$25,MATCH(Q19,'Assumptions & FX Reference'!$A$5:$A$25,0)),IF(R19="EUR",S19*INDEX('Assumptions & FX Reference'!$C$5:$C$25,MATCH(Q19,'Assumptions & FX Reference'!$A$5:$A$25,0))/INDEX('Assumptions & FX Reference'!$B$5:$B$25,MATCH(Q19,'Assumptions & FX Reference'!$A$5:$A$25,0)),"(Not stated)"))))>0,IF(R19="USD",S19,IF(R19="IRR",S19/INDEX('Assumptions & FX Reference'!$B$5:$B$25,MATCH(Q19,'Assumptions & FX Reference'!$A$5:$A$25,0)),IF(R19="EUR",S19*INDEX('Assumptions & FX Reference'!$C$5:$C$25,MATCH(Q19,'Assumptions & FX Reference'!$A$5:$A$25,0))/INDEX('Assumptions & FX Reference'!$B$5:$B$25,MATCH(Q19,'Assumptions & FX Reference'!$A$5:$A$25,0)),"(Not stated)"))),"(FX rate not entered for this year)"),"(FX rate not entered for this year)"))) -> 7142.8571 | V19: =IF(NOT(ISNUMBER(S19)),"(Not stated)",IF(NOT(ISNUMBER(Q19)),"(Cost year not stated / not a Jalali year)",IFERROR(IF(N(IF(R19="IRR",S19,IF(R19="USD",S19*INDEX('Assumptions & FX Reference'!$B$5:$B$25,MATCH(Q19,'Assumptions & FX Reference'!$A$5:$A$25,0)),IF(R19="EUR",S19*INDEX('Assumptions & FX Reference'!$C$5:$C$25,MATCH(Q19,'Assumptions & FX Reference'!$A$5:$A$25,0)),"(Not stated)"))))>0,IF(R19="IRR",S19,IF(R19="USD",S19*INDEX('Assumptions & FX Reference'!$B$5:$B$25,MATCH(Q19,'Assumptions & FX Reference'!$A$5:$A$25,0)),IF(R19="EUR",S19*INDEX('Assumptions & FX Reference'!$C$5:$C$25,MATCH(Q19,'Assumptions & FX Reference'!$A$5:$A$25,0)),"(Not stated)"))),"(FX rate not entered for this year)"),"(FX rate not entered for this year)"))) -> 3000000000 | W19: FOB | X19: Class 3 (Basic) | Y19: Basic Engineering | Z19: PEP-Rev.140205_عزيزيان_Gachsaran_4.xlsx (Sheet P.ME, row 90) | AA19: Unit cost without overhead factor (هزینه واحد بدون ضریب). HVAC group header row 83 carries its own freight allocation of 1,207,442,136.32 IRR (not included); Customs clearance not stated. Equipment list / data sheets are in the E.HVAC document set. | AB19: Y
A20: 16 | B20: HVAC Bulk | C20: Gachsaran 4 Development Plan (Proj No. 591111) | D20: (No Tag - P.ME item 66.8) | E20: HVAC | F20: HVAC-SYS | G20: 1 | H20: No. | I20: HVAC Bulk (P.ME item 66.8 under HVAC group item 66) | J20: Not Stated | K20: Not Stated | L20: Not Stated | M20: Not Stated | N20: Not Stated | O20: Not Stated | P20: Not Stated | Q20: 1402 | R20: IRR | S20: 6000000000 | T20: =IF(NOT(ISNUMBER(S20)),"(Not stated)",IF(NOT(ISNUMBER(Q20)),"(Cost year not stated / not a Jalali year)",IFERROR(IF(N(IF(R20="EUR",S20,IF(R20="IRR",S20/INDEX('Assumptions & FX Reference'!$C$5:$C$25,MATCH(Q20,'Assumptions & FX Reference'!$A$5:$A$25,0)),IF(R20="USD",S20*INDEX('Assumptions & FX Reference'!$B$5:$B$25,MATCH(Q20,'Assumptions & FX Reference'!$A$5:$A$25,0))/INDEX('Assumptions & FX Reference'!$C$5:$C$25,MATCH(Q20,'Assumptions & FX Reference'!$A$5:$A$25,0)),"(Not stated)"))))>0,IF(R20="EUR",S20,IF(R20="IRR",S20/INDEX('Assumptions & FX Reference'!$C$5:$C$25,MATCH(Q20,'Assumptions & FX Reference'!$A$5:$A$25,0)),IF(R20="USD",S20*INDEX('Assumptions & FX Reference'!$B$5:$B$25,MATCH(Q20,'Assumptions & FX Reference'!$A$5:$A$25,0))/INDEX('Assumptions & FX Reference'!$C$5:$C$25,MATCH(Q20,'Assumptions & FX Reference'!$A$5:$A$25,0)),"(Not stated)"))),"(FX rate not entered for this year)"),"(FX rate not entered for this year)"))) -> 11331.445 | U20: =IF(NOT(ISNUMBER(S20)),"(Not stated)",IF(NOT(ISNUMBER(Q20)),"(Cost year not stated / not a Jalali year)",IFERROR(IF(N(IF(R20="USD",S20,IF(R20="IRR",S20/INDEX('Assumptions & FX Reference'!$B$5:$B$25,MATCH(Q20,'Assumptions & FX Reference'!$A$5:$A$25,0)),IF(R20="EUR",S20*INDEX('Assumptions & FX Reference'!$C$5:$C$25,MATCH(Q20,'Assumptions & FX Reference'!$A$5:$A$25,0))/INDEX('Assumptions & FX Reference'!$B$5:$B$25,MATCH(Q20,'Assumptions & FX Reference'!$A$5:$A$25,0)),"(Not stated)"))))>0,IF(R20="USD",S20,IF(R20="IRR",S20/INDEX('Assumptions & FX Reference'!$B$5:$B$25,MATCH(Q20,'Assumptions & FX Reference'!$A$5:$A$25,0)),IF(R20="EUR",S20*INDEX('Assumptions & FX Reference'!$C$5:$C$25,MATCH(Q20,'Assumptions & FX Reference'!$A$5:$A$25,0))/INDEX('Assumptions & FX Reference'!$B$5:$B$25,MATCH(Q20,'Assumptions & FX Reference'!$A$5:$A$25,0)),"(Not stated)"))),"(FX rate not entered for this year)"),"(FX rate not entered for this year)"))) -> 14285.714 | V20: =IF(NOT(ISNUMBER(S20)),"(Not stated)",IF(NOT(ISNUMBER(Q20)),"(Cost year not stated / not a Jalali year)",IFERROR(IF(N(IF(R20="IRR",S20,IF(R20="USD",S20*INDEX('Assumptions & FX Reference'!$B$5:$B$25,MATCH(Q20,'Assumptions & FX Reference'!$A$5:$A$25,0)),IF(R20="EUR",S20*INDEX('Assumptions & FX Reference'!$C$5:$C$25,MATCH(Q20,'Assumptions & FX Reference'!$A$5:$A$25,0)),"(Not stated)"))))>0,IF(R20="IRR",S20,IF(R20="USD",S20*INDEX('Assumptions & FX Reference'!$B$5:$B$25,MATCH(Q20,'Assumptions & FX Reference'!$A$5:$A$25,0)),IF(R20="EUR",S20*INDEX('Assumptions & FX Reference'!$C$5:$C$25,MATCH(Q20,'Assumptions & FX Reference'!$A$5:$A$25,0)),"(Not stated)"))),"(FX rate not entered for this year)"),"(FX rate not entered for this year)"))) -> 6000000000 | W20: FOB | X20: Class 3 (Basic) | Y20: Basic Engineering | Z20: PEP-Rev.140205_عزيزيان_Gachsaran_4.xlsx (Sheet P.ME, row 91) | AA20: Unit cost without overhead factor (هزینه واحد بدون ضریب). Freight allocation 603,721,068.16 IRR (row col N; = 32,500,000 x IRR_Inflation_Factor) not included in Unit Price Reference. HVAC group header row 83 carries its own freight allocation of 1,207,442,136.32 IRR (not included); Customs clearance not stated. Equipment list / data sheets are in the E.HVAC document set. | AB20: Y
A21: 17 | B21: HVAC System (Category Cost Rollup - FEED Estimate) | C21: Maroon 3 Bangestan Desalting Unit (Doc. Ref. 14050310) | D21: (Category Rollup - not a discrete Tag) | E21: HVAC | F21: HVAC-SYS | G21: Not Stated | H21: Lump Sum | I21: Aggregated procurement cost for the HVAC system, project-wide; FEED-stage old-vs-new contract comparison | J21: Not Stated | K21: Not Stated | L21: Not Stated | M21: Not Stated | N21: Not Stated | O21: Not Stated | P21: Not Stated | Q21: 1392 | R21: IRR | S21: 8425000000 | T21: =IF(NOT(ISNUMBER(S21)),"(Not stated)",IF(NOT(ISNUMBER(Q21)),"(Cost year not stated / not a Jalali year)",IFERROR(IF(N(IF(R21="EUR",S21,IF(R21="IRR",S21/INDEX('Assumptions & FX Reference'!$C$5:$C$25,MATCH(Q21,'Assumptions & FX Reference'!$A$5:$A$25,0)),IF(R21="USD",S21*INDEX('Assumptions & FX Reference'!$B$5:$B$25,MATCH(Q21,'Assumptions & FX Reference'!$A$5:$A$25,0))/INDEX('Assumptions & FX Reference'!$C$5:$C$25,MATCH(Q21,'Assumptions & FX Reference'!$A$5:$A$25,0)),"(Not stated)"))))>0,IF(R21="EUR",S21,IF(R21="IRR",S21/INDEX('Assumptions & FX Reference'!$C$5:$C$25,MATCH(Q21,'Assumptions & FX Reference'!$A$5:$A$25,0)),IF(R21="USD",S21*INDEX('Assumptions & FX Reference'!$B$5:$B$25,MATCH(Q21,'Assumptions & FX Reference'!$A$5:$A$25,0))/INDEX('Assumptions & FX Reference'!$C$5:$C$25,MATCH(Q21,'Assumptions & FX Reference'!$A$5:$A$25,0)),"(Not stated)"))),"(FX rate not entered for this year)"),"(FX rate not entered for this year)"))) -> 200595.24 | U21: =IF(NOT(ISNUMBER(S21)),"(Not stated)",IF(NOT(ISNUMBER(Q21)),"(Cost year not stated / not a Jalali year)",IFERROR(IF(N(IF(R21="USD",S21,IF(R21="IRR",S21/INDEX('Assumptions & FX Reference'!$B$5:$B$25,MATCH(Q21,'Assumptions & FX Reference'!$A$5:$A$25,0)),IF(R21="EUR",S21*INDEX('Assumptions & FX Reference'!$C$5:$C$25,MATCH(Q21,'Assumptions & FX Reference'!$A$5:$A$25,0))/INDEX('Assumptions & FX Reference'!$B$5:$B$25,MATCH(Q21,'Assumptions & FX Reference'!$A$5:$A$25,0)),"(Not stated)"))))>0,IF(R21="USD",S21,IF(R21="IRR",S21/INDEX('Assumptions & FX Reference'!$B$5:$B$25,MATCH(Q21,'Assumptions & FX Reference'!$A$5:$A$25,0)),IF(R21="EUR",S21*INDEX('Assumptions & FX Reference'!$C$5:$C$25,MATCH(Q21,'Assumptions & FX Reference'!$A$5:$A$25,0))/INDEX('Assumptions & FX Reference'!$B$5:$B$25,MATCH(Q21,'Assumptions & FX Reference'!$A$5:$A$25,0)),"(Not stated)"))),"(FX rate not entered for this year)"),"(FX rate not entered for this year)"))) -> 232093.66 | V21: =IF(NOT(ISNUMBER(S21)),"(Not stated)",IF(NOT(ISNUMBER(Q21)),"(Cost year not stated / not a Jalali year)",IFERROR(IF(N(IF(R21="IRR",S21,IF(R21="USD",S21*INDEX('Assumptions & FX Reference'!$B$5:$B$25,MATCH(Q21,'Assumptions & FX Reference'!$A$5:$A$25,0)),IF(R21="EUR",S21*INDEX('Assumptions & FX Reference'!$C$5:$C$25,MATCH(Q21,'Assumptions & FX Reference'!$A$5:$A$25,0)),"(Not stated)"))))>0,IF(R21="IRR",S21,IF(R21="USD",S21*INDEX('Assumptions & FX Reference'!$B$5:$B$25,MATCH(Q21,'Assumptions & FX Reference'!$A$5:$A$25,0)),IF(R21="EUR",S21*INDEX('Assumptions & FX Reference'!$C$5:$C$25,MATCH(Q21,'Assumptions & FX Reference'!$A$5:$A$25,0)),"(Not stated)"))),"(FX rate not entered for this year)"),"(FX rate not entered for this year)"))) -> 8425000000 | W21: Contract Reconciliation Estimate (New Contract Value) | X21: Class 4 (FEED Rollup) | Y21: FEED | Z21: برآورد_پروژه_نمکزدایی_مارون_3__بنگستان_تاریخ_14050310.xlsx (Sheet ME.p.1392, row 18) | AA21: Category-level rollup, not a single tag/package; excluded from Active Tags count. Source-native currency is IRR (column J 'ریال' under 1392 = 8,425,000,000; no Euro component). Old-contract value 2,625,392,658 IRR also recorded in source (columns G/H and K). | AB21: Y
A22: 18 | B22: HVAC System (Category Cost Rollup - 1405 Estimate) | C22: Maroon 3 Bangestan Desalting Unit (Doc. Ref. 14050310) | D22: (Category Rollup - not a discrete Tag) | E22: HVAC | F22: HVAC-SYS | G22: Not Stated | H22: Lump Sum | I22: Aggregated procurement cost for the HVAC system, project-wide; 1405 basic-estimate table | J22: Not Stated | K22: Not Stated | L22: Not Stated | M22: Not Stated | N22: Not Stated | O22: Not Stated | P22: Not Stated | Q22: 1405 | R22: IRR | S22: 4.1947573e+11 | T22: =IF(NOT(ISNUMBER(S22)),"(Not stated)",IF(NOT(ISNUMBER(Q22)),"(Cost year not stated / not a Jalali year)",IFERROR(IF(N(IF(R22="EUR",S22,IF(R22="IRR",S22/INDEX('Assumptions & FX Reference'!$C$5:$C$25,MATCH(Q22,'Assumptions & FX Reference'!$A$5:$A$25,0)),IF(R22="USD",S22*INDEX('Assumptions & FX Reference'!$B$5:$B$25,MATCH(Q22,'Assumptions & FX Reference'!$A$5:$A$25,0))/INDEX('Assumptions & FX Reference'!$C$5:$C$25,MATCH(Q22,'Assumptions & FX Reference'!$A$5:$A$25,0)),"(Not stated)"))))>0,IF(R22="EUR",S22,IF(R22="IRR",S22/INDEX('Assumptions & FX Reference'!$C$5:$C$25,MATCH(Q22,'Assumptions & FX Reference'!$A$5:$A$25,0)),IF(R22="USD",S22*INDEX('Assumptions & FX Reference'!$B$5:$B$25,MATCH(Q22,'Assumptions & FX Reference'!$A$5:$A$25,0))/INDEX('Assumptions & FX Reference'!$C$5:$C$25,MATCH(Q22,'Assumptions & FX Reference'!$A$5:$A$25,0)),"(Not stated)"))),"(FX rate not entered for this year)"),"(FX rate not entered for this year)"))) -> 209737.86 | U22: =IF(NOT(ISNUMBER(S22)),"(Not stated)",IF(NOT(ISNUMBER(Q22)),"(Cost year not stated / not a Jalali year)",IFERROR(IF(N(IF(R22="USD",S22,IF(R22="IRR",S22/INDEX('Assumptions & FX Reference'!$B$5:$B$25,MATCH(Q22,'Assumptions & FX Reference'!$A$5:$A$25,0)),IF(R22="EUR",S22*INDEX('Assumptions & FX Reference'!$C$5:$C$25,MATCH(Q22,'Assumptions & FX Reference'!$A$5:$A$25,0))/INDEX('Assumptions & FX Reference'!$B$5:$B$25,MATCH(Q22,'Assumptions & FX Reference'!$A$5:$A$25,0)),"(Not stated)"))))>0,IF(R22="USD",S22,IF(R22="IRR",S22/INDEX('Assumptions & FX Reference'!$B$5:$B$25,MATCH(Q22,'Assumptions & FX Reference'!$A$5:$A$25,0)),IF(R22="EUR",S22*INDEX('Assumptions & FX Reference'!$C$5:$C$25,MATCH(Q22,'Assumptions & FX Reference'!$A$5:$A$25,0))/INDEX('Assumptions & FX Reference'!$B$5:$B$25,MATCH(Q22,'Assumptions & FX Reference'!$A$5:$A$25,0)),"(Not stated)"))),"(FX rate not entered for this year)"),"(FX rate not entered for this year)"))) -> 230711.65 | V22: =IF(NOT(ISNUMBER(S22)),"(Not stated)",IF(NOT(ISNUMBER(Q22)),"(Cost year not stated / not a Jalali year)",IFERROR(IF(N(IF(R22="IRR",S22,IF(R22="USD",S22*INDEX('Assumptions & FX Reference'!$B$5:$B$25,MATCH(Q22,'Assumptions & FX Reference'!$A$5:$A$25,0)),IF(R22="EUR",S22*INDEX('Assumptions & FX Reference'!$C$5:$C$25,MATCH(Q22,'Assumptions & FX Reference'!$A$5:$A$25,0)),"(Not stated)"))))>0,IF(R22="IRR",S22,IF(R22="USD",S22*INDEX('Assumptions & FX Reference'!$B$5:$B$25,MATCH(Q22,'Assumptions & FX Reference'!$A$5:$A$25,0)),IF(R22="EUR",S22*INDEX('Assumptions & FX Reference'!$C$5:$C$25,MATCH(Q22,'Assumptions & FX Reference'!$A$5:$A$25,0)),"(Not stated)"))),"(FX rate not entered for this year)"),"(FX rate not entered for this year)"))) -> 4.1947573e+11 | W22: Basic Estimate (Category Rollup) | X22: Class 4 (FEED Rollup) | Y22: Basic Estimate | Z22: برآورد_پروژه_نمکزدایی_مارون_3__بنگستان_تاریخ_14050310.xlsx (Sheet ME.P.1405, row 20) | AA22: Category-level rollup, not a single tag/package; excluded from Active Tags count. Item 14 in the 1405 table (item 13 in the 1392 table). | AB22: Y
A23: 19 | B23: HVAC Works (Construction Line - Reference Price Sample) | C23: Not Stated (reference price sample, file 18061405_Pump_only_CSV) | D23: (No Tag - price sample construction item 11) | E23: HVAC | F23: HVAC-SYS | G23: Not Stated | H23: Lump Sum | I23: HVAC Works line of the Construction cost list in the price sample | J23: Not Stated | K23: Not Stated | L23: Not Stated | M23: Not Stated | N23: Not Stated | O23: Not Stated | P23: Not Stated | Q23: Not Stated | R23: USD | S23: 15000 | T23: =IF(NOT(ISNUMBER(S23)),"(Not stated)",IF(NOT(ISNUMBER(Q23)),"(Cost year not stated / not a Jalali year)",IFERROR(IF(N(IF(R23="EUR",S23,IF(R23="IRR",S23/INDEX('Assumptions & FX Reference'!$C$5:$C$25,MATCH(Q23,'Assumptions & FX Reference'!$A$5:$A$25,0)),IF(R23="USD",S23*INDEX('Assumptions & FX Reference'!$B$5:$B$25,MATCH(Q23,'Assumptions & FX Reference'!$A$5:$A$25,0))/INDEX('Assumptions & FX Reference'!$C$5:$C$25,MATCH(Q23,'Assumptions & FX Reference'!$A$5:$A$25,0)),"(Not stated)"))))>0,IF(R23="EUR",S23,IF(R23="IRR",S23/INDEX('Assumptions & FX Reference'!$C$5:$C$25,MATCH(Q23,'Assumptions & FX Reference'!$A$5:$A$25,0)),IF(R23="USD",S23*INDEX('Assumptions & FX Reference'!$B$5:$B$25,MATCH(Q23,'Assumptions & FX Reference'!$A$5:$A$25,0))/INDEX('Assumptions & FX Reference'!$C$5:$C$25,MATCH(Q23,'Assumptions & FX Reference'!$A$5:$A$25,0)),"(Not stated)"))),"(FX rate not entered for this year)"),"(FX rate not entered for this year)"))) -> (Cost year not stated / not a Jalali year) | U23: =IF(NOT(ISNUMBER(S23)),"(Not stated)",IF(NOT(ISNUMBER(Q23)),"(Cost year not stated / not a Jalali year)",IFERROR(IF(N(IF(R23="USD",S23,IF(R23="IRR",S23/INDEX('Assumptions & FX Reference'!$B$5:$B$25,MATCH(Q23,'Assumptions & FX Reference'!$A$5:$A$25,0)),IF(R23="EUR",S23*INDEX('Assumptions & FX Reference'!$C$5:$C$25,MATCH(Q23,'Assumptions & FX Reference'!$A$5:$A$25,0))/INDEX('Assumptions & FX Reference'!$B$5:$B$25,MATCH(Q23,'Assumptions & FX Reference'!$A$5:$A$25,0)),"(Not stated)"))))>0,IF(R23="USD",S23,IF(R23="IRR",S23/INDEX('Assumptions & FX Reference'!$B$5:$B$25,MATCH(Q23,'Assumptions & FX Reference'!$A$5:$A$25,0)),IF(R23="EUR",S23*INDEX('Assumptions & FX Reference'!$C$5:$C$25,MATCH(Q23,'Assumptions & FX Reference'!$A$5:$A$25,0))/INDEX('Assumptions & FX Reference'!$B$5:$B$25,MATCH(Q23,'Assumptions & FX Reference'!$A$5:$A$25,0)),"(Not stated)"))),"(FX rate not entered for this year)"),"(FX rate not entered for this year)"))) -> (Cost year not stated / not a Jalali year) | V23: =IF(NOT(ISNUMBER(S23)),"(Not stated)",IF(NOT(ISNUMBER(Q23)),"(Cost year not stated / not a Jalali year)",IFERROR(IF(N(IF(R23="IRR",S23,IF(R23="USD",S23*INDEX('Assumptions & FX Reference'!$B$5:$B$25,MATCH(Q23,'Assumptions & FX Reference'!$A$5:$A$25,0)),IF(R23="EUR",S23*INDEX('Assumptions & FX Reference'!$C$5:$C$25,MATCH(Q23,'Assumptions & FX Reference'!$A$5:$A$25,0)),"(Not stated)"))))>0,IF(R23="IRR",S23,IF(R23="USD",S23*INDEX('Assumptions & FX Reference'!$B$5:$B$25,MATCH(Q23,'Assumptions & FX Reference'!$A$5:$A$25,0)),IF(R23="EUR",S23*INDEX('Assumptions & FX Reference'!$C$5:$C$25,MATCH(Q23,'Assumptions & FX Reference'!$A$5:$A$25,0)),"(Not stated)"))),"(FX rate not entered for this year)"),"(FX rate not entered for this year)"))) -> (Cost year not stated / not a Jalali year) | W23: Not Stated | X23: Not Stated | Y23: Not Stated | Z23: 18061405_Pump_only_CSV.csv (section Construction, item 11, file row 128) | AA23: Construction-works line ('HVAC Works'), not equipment supply; scope, quantity, cost year and basis not stated. Recorded for reference and excluded from totals. | AB23: N
A24: 20 | B24: Safety Shower & Eye Wash | C24: Gachsaran 4 Development Plan (Proj No. 591111) | D24: (No Tag - P.ME item 67.8) | E24: SAF | F24: SAF-SHW | G24: 7 | H24: No. | I24: Safety Shower & Eye Wash (Safety Equipment list, P.ME item 67.8) | J24: Not Stated | K24: Not Stated | L24: Not Stated | M24: Not Stated | N24: Not Stated | O24: Not Stated | P24: Not Stated | Q24: 1402 | R24: IRR | S24: 1260000000 | T24: =IF(NOT(ISNUMBER(S24)),"(Not stated)",IF(NOT(ISNUMBER(Q24)),"(Cost year not stated / not a Jalali year)",IFERROR(IF(N(IF(R24="EUR",S24,IF(R24="IRR",S24/INDEX('Assumptions & FX Reference'!$C$5:$C$25,MATCH(Q24,'Assumptions & FX Reference'!$A$5:$A$25,0)),IF(R24="USD",S24*INDEX('Assumptions & FX Reference'!$B$5:$B$25,MATCH(Q24,'Assumptions & FX Reference'!$A$5:$A$25,0))/INDEX('Assumptions & FX Reference'!$C$5:$C$25,MATCH(Q24,'Assumptions & FX Reference'!$A$5:$A$25,0)),"(Not stated)"))))>0,IF(R24="EUR",S24,IF(R24="IRR",S24/INDEX('Assumptions & FX Reference'!$C$5:$C$25,MATCH(Q24,'Assumptions & FX Reference'!$A$5:$A$25,0)),IF(R24="USD",S24*INDEX('Assumptions & FX Reference'!$B$5:$B$25,MATCH(Q24,'Assumptions & FX Reference'!$A$5:$A$25,0))/INDEX('Assumptions & FX Reference'!$C$5:$C$25,MATCH(Q24,'Assumptions & FX Reference'!$A$5:$A$25,0)),"(Not stated)"))),"(FX rate not entered for this year)"),"(FX rate not entered for this year)"))) -> 2379.6034 | U24: =IF(NOT(ISNUMBER(S24)),"(Not stated)",IF(NOT(ISNUMBER(Q24)),"(Cost year not stated / not a Jalali year)",IFERROR(IF(N(IF(R24="USD",S24,IF(R24="IRR",S24/INDEX('Assumptions & FX Reference'!$B$5:$B$25,MATCH(Q24,'Assumptions & FX Reference'!$A$5:$A$25,0)),IF(R24="EUR",S24*INDEX('Assumptions & FX Reference'!$C$5:$C$25,MATCH(Q24,'Assumptions & FX Reference'!$A$5:$A$25,0))/INDEX('Assumptions & FX Reference'!$B$5:$B$25,MATCH(Q24,'Assumptions & FX Reference'!$A$5:$A$25,0)),"(Not stated)"))))>0,IF(R24="USD",S24,IF(R24="IRR",S24/INDEX('Assumptions & FX Reference'!$B$5:$B$25,MATCH(Q24,'Assumptions & FX Reference'!$A$5:$A$25,0)),IF(R24="EUR",S24*INDEX('Assumptions & FX Reference'!$C$5:$C$25,MATCH(Q24,'Assumptions & FX Reference'!$A$5:$A$25,0))/INDEX('Assumptions & FX Reference'!$B$5:$B$25,MATCH(Q24,'Assumptions & FX Reference'!$A$5:$A$25,0)),"(Not stated)"))),"(FX rate not entered for this year)"),"(FX rate not entered for this year)"))) -> 3000 | V24: =IF(NOT(ISNUMBER(S24)),"(Not stated)",IF(NOT(ISNUMBER(Q24)),"(Cost year not stated / not a Jalali year)",IFERROR(IF(N(IF(R24="IRR",S24,IF(R24="USD",S24*INDEX('Assumptions & FX Reference'!$B$5:$B$25,MATCH(Q24,'Assumptions & FX Reference'!$A$5:$A$25,0)),IF(R24="EUR",S24*INDEX('Assumptions & FX Reference'!$C$5:$C$25,MATCH(Q24,'Assumptions & FX Reference'!$A$5:$A$25,0)),"(Not stated)"))))>0,IF(R24="IRR",S24,IF(R24="USD",S24*INDEX('Assumptions & FX Reference'!$B$5:$B$25,MATCH(Q24,'Assumptions & FX Reference'!$A$5:$A$25,0)),IF(R24="EUR",S24*INDEX('Assumptions & FX Reference'!$C$5:$C$25,MATCH(Q24,'Assumptions & FX Reference'!$A$5:$A$25,0)),"(Not stated)"))),"(FX rate not entered for this year)"),"(FX rate not entered for this year)"))) -> 1260000000 | W24: FOB | X24: Class 3 (Basic) | Y24: Basic Engineering | Z24: PEP-Rev.140205_عزيزيان_Gachsaran_4.xlsx (Sheet P.ME, row 102) | AA24: Unit cost without overhead factor (هزینه واحد بدون ضریب). Source formula = 3,000 USD x USD_Change_IRR (420,000 IRR/USD) = 1,260,000,000 IRR per unit; total 8,820,000,000 IRR for 7 No. Data sheet: E.HSE item 4.11 ('Safety shower data sheet', not extracted). No freight allocation on this row; Customs clearance not stated. Installation is a separate construction item (C.mECHANICAL 'SAFETY SHOWER & EYE WASH') and is not included. | AB24: Y
A25: 21 | B25: Safety Shower & Eye Wash | C25: Maroon 3 Bangestan Desalting Unit (Doc. Ref. 14050310) | D25: (No Tag - SEFTY.p.1392 item 10) | E25: SAF | F25: SAF-SHW | G25: 5 | H25: Not Stated | I25: Safety Shower & Eye Wash (safety list of the 1392 estimate, item 10) | J25: Not Stated | K25: Not Stated | L25: Not Stated | M25: Not Stated | N25: Not Stated | O25: Not Stated | P25: Not Stated | Q25: 1392 | R25: IRR | S25: 31500000 | T25: =IF(NOT(ISNUMBER(S25)),"(Not stated)",IF(NOT(ISNUMBER(Q25)),"(Cost year not stated / not a Jalali year)",IFERROR(IF(N(IF(R25="EUR",S25,IF(R25="IRR",S25/INDEX('Assumptions & FX Reference'!$C$5:$C$25,MATCH(Q25,'Assumptions & FX Reference'!$A$5:$A$25,0)),IF(R25="USD",S25*INDEX('Assumptions & FX Reference'!$B$5:$B$25,MATCH(Q25,'Assumptions & FX Reference'!$A$5:$A$25,0))/INDEX('Assumptions & FX Reference'!$C$5:$C$25,MATCH(Q25,'Assumptions & FX Reference'!$A$5:$A$25,0)),"(Not stated)"))))>0,IF(R25="EUR",S25,IF(R25="IRR",S25/INDEX('Assumptions & FX Reference'!$C$5:$C$25,MATCH(Q25,'Assumptions & FX Reference'!$A$5:$A$25,0)),IF(R25="USD",S25*INDEX('Assumptions & FX Reference'!$B$5:$B$25,MATCH(Q25,'Assumptions & FX Reference'!$A$5:$A$25,0))/INDEX('Assumptions & FX Reference'!$C$5:$C$25,MATCH(Q25,'Assumptions & FX Reference'!$A$5:$A$25,0)),"(Not stated)"))),"(FX rate not entered for this year)"),"(FX rate not entered for this year)"))) -> 750 | U25: =IF(NOT(ISNUMBER(S25)),"(Not stated)",IF(NOT(ISNUMBER(Q25)),"(Cost year not stated / not a Jalali year)",IFERROR(IF(N(IF(R25="USD",S25,IF(R25="IRR",S25/INDEX('Assumptions & FX Reference'!$B$5:$B$25,MATCH(Q25,'Assumptions & FX Reference'!$A$5:$A$25,0)),IF(R25="EUR",S25*INDEX('Assumptions & FX Reference'!$C$5:$C$25,MATCH(Q25,'Assumptions & FX Reference'!$A$5:$A$25,0))/INDEX('Assumptions & FX Reference'!$B$5:$B$25,MATCH(Q25,'Assumptions & FX Reference'!$A$5:$A$25,0)),"(Not stated)"))))>0,IF(R25="USD",S25,IF(R25="IRR",S25/INDEX('Assumptions & FX Reference'!$B$5:$B$25,MATCH(Q25,'Assumptions & FX Reference'!$A$5:$A$25,0)),IF(R25="EUR",S25*INDEX('Assumptions & FX Reference'!$C$5:$C$25,MATCH(Q25,'Assumptions & FX Reference'!$A$5:$A$25,0))/INDEX('Assumptions & FX Reference'!$B$5:$B$25,MATCH(Q25,'Assumptions & FX Reference'!$A$5:$A$25,0)),"(Not stated)"))),"(FX rate not entered for this year)"),"(FX rate not entered for this year)"))) -> 867.7686 | V25: =IF(NOT(ISNUMBER(S25)),"(Not stated)",IF(NOT(ISNUMBER(Q25)),"(Cost year not stated / not a Jalali year)",IFERROR(IF(N(IF(R25="IRR",S25,IF(R25="USD",S25*INDEX('Assumptions & FX Reference'!$B$5:$B$25,MATCH(Q25,'Assumptions & FX Reference'!$A$5:$A$25,0)),IF(R25="EUR",S25*INDEX('Assumptions & FX Reference'!$C$5:$C$25,MATCH(Q25,'Assumptions & FX Reference'!$A$5:$A$25,0)),"(Not stated)"))))>0,IF(R25="IRR",S25,IF(R25="USD",S25*INDEX('Assumptions & FX Reference'!$B$5:$B$25,MATCH(Q25,'Assumptions & FX Reference'!$A$5:$A$25,0)),IF(R25="EUR",S25*INDEX('Assumptions & FX Reference'!$C$5:$C$25,MATCH(Q25,'Assumptions & FX Reference'!$A$5:$A$25,0)),"(Not stated)"))),"(FX rate not entered for this year)"),"(FX rate not entered for this year)"))) -> 31500000 | W25: Not Stated | X25: Not Stated | Y25: Not Stated | Z25: برآورد_پروژه_نمکزدایی_مارون_3__بنگستان_تاریخ_14050310.xlsx (Sheet SEFTY.p.1392, row 17) | AA25: Unit cost without factor (هزینه واحد بدون ضریب), purchase, Rials column = 31,500,000 IRR per unit (total 157,500,000 IRR for 5); Euro columns = 0. An unlabelled helper cell (J17) holds 750, which equals 31,500,000 / 42,000 (free-market euro rate in the same sheet, 'نرخ ازاد یورو'); it is not entered as a price. Unit and price basis not stated. | AB25: Y
A26: 22 | B26: Safety Shower & Eye Wash (Laboratory) | C26: Maroon 3 Bangestan Desalting Unit (Doc. Ref. 14050310) | D26: (No Tag - p.lab.1392 item 22) | E26: SAF | F26: SAF-SHW | G26: 4 | H26: Not Stated | I26: Safety shower & eyewash in the laboratory equipment list (item 22) | J26: Not Stated | K26: Not Stated | L26: Not Stated | M26: Not Stated | N26: Not Stated | O26: Not Stated | P26: Not Stated | Q26: 1392 | R26: IRR | S26: Not Stated | T26: =IF(NOT(ISNUMBER(S26)),"(Not stated)",IF(NOT(ISNUMBER(Q26)),"(Cost year not stated / not a Jalali year)",IFERROR(IF(N(IF(R26="EUR",S26,IF(R26="IRR",S26/INDEX('Assumptions & FX Reference'!$C$5:$C$25,MATCH(Q26,'Assumptions & FX Reference'!$A$5:$A$25,0)),IF(R26="USD",S26*INDEX('Assumptions & FX Reference'!$B$5:$B$25,MATCH(Q26,'Assumptions & FX Reference'!$A$5:$A$25,0))/INDEX('Assumptions & FX Reference'!$C$5:$C$25,MATCH(Q26,'Assumptions & FX Reference'!$A$5:$A$25,0)),"(Not stated)"))))>0,IF(R26="EUR",S26,IF(R26="IRR",S26/INDEX('Assumptions & FX Reference'!$C$5:$C$25,MATCH(Q26,'Assumptions & FX Reference'!$A$5:$A$25,0)),IF(R26="USD",S26*INDEX('Assumptions & FX Reference'!$B$5:$B$25,MATCH(Q26,'Assumptions & FX Reference'!$A$5:$A$25,0))/INDEX('Assumptions & FX Reference'!$C$5:$C$25,MATCH(Q26,'Assumptions & FX Reference'!$A$5:$A$25,0)),"(Not stated)"))),"(FX rate not entered for this year)"),"(FX rate not entered for this year)"))) -> (Not stated) | U26: =IF(NOT(ISNUMBER(S26)),"(Not stated)",IF(NOT(ISNUMBER(Q26)),"(Cost year not stated / not a Jalali year)",IFERROR(IF(N(IF(R26="USD",S26,IF(R26="IRR",S26/INDEX('Assumptions & FX Reference'!$B$5:$B$25,MATCH(Q26,'Assumptions & FX Reference'!$A$5:$A$25,0)),IF(R26="EUR",S26*INDEX('Assumptions & FX Reference'!$C$5:$C$25,MATCH(Q26,'Assumptions & FX Reference'!$A$5:$A$25,0))/INDEX('Assumptions & FX Reference'!$B$5:$B$25,MATCH(Q26,'Assumptions & FX Reference'!$A$5:$A$25,0)),"(Not stated)"))))>0,IF(R26="USD",S26,IF(R26="IRR",S26/INDEX('Assumptions & FX Reference'!$B$5:$B$25,MATCH(Q26,'Assumptions & FX Reference'!$A$5:$A$25,0)),IF(R26="EUR",S26*INDEX('Assumptions & FX Reference'!$C$5:$C$25,MATCH(Q26,'Assumptions & FX Reference'!$A$5:$A$25,0))/INDEX('Assumptions & FX Reference'!$B$5:$B$25,MATCH(Q26,'Assumptions & FX Reference'!$A$5:$A$25,0)),"(Not stated)"))),"(FX rate not entered for this year)"),"(FX rate not entered for this year)"))) -> (Not stated) | V26: =IF(NOT(ISNUMBER(S26)),"(Not stated)",IF(NOT(ISNUMBER(Q26)),"(Cost year not stated / not a Jalali year)",IFERROR(IF(N(IF(R26="IRR",S26,IF(R26="USD",S26*INDEX('Assumptions & FX Reference'!$B$5:$B$25,MATCH(Q26,'Assumptions & FX Reference'!$A$5:$A$25,0)),IF(R26="EUR",S26*INDEX('Assumptions & FX Reference'!$C$5:$C$25,MATCH(Q26,'Assumptions & FX Reference'!$A$5:$A$25,0)),"(Not stated)"))))>0,IF(R26="IRR",S26,IF(R26="USD",S26*INDEX('Assumptions & FX Reference'!$B$5:$B$25,MATCH(Q26,'Assumptions & FX Reference'!$A$5:$A$25,0)),IF(R26="EUR",S26*INDEX('Assumptions & FX Reference'!$C$5:$C$25,MATCH(Q26,'Assumptions & FX Reference'!$A$5:$A$25,0)),"(Not stated)"))),"(FX rate not entered for this year)"),"(FX rate not entered for this year)"))) -> (Not stated) | W26: Not Stated | X26: Not Stated | Y26: Not Stated | Z26: برآورد_پروژه_نمکزدایی_مارون_3__بنگستان_تاریخ_14050310.xlsx (Sheet p.lab.1392, row 28) | AA26: Price cell reads '(item19)': no separate price, it is bundled with lab item 19, the Industrial Hood set (1,050,000,000 IRR for qty 4, row 25). Excluded from totals (no own price; lab set already priced on item 19). | AB26: N
A27: 23 | B27: Safety Shower & Eyewash (Laboratory) | C27: Gachsaran 4 Development Plan (Proj No. 591111) | D27: (No Tag - P.LAB item 21) | E27: SAF | F27: SAF-SHW | G27: 4 | H27: Not Stated | I27: Safety shower & eyewash in the laboratory equipment list (P.LAB item 21) | J27: Not Stated | K27: Not Stated | L27: Not Stated | M27: Not Stated | N27: Not Stated | O27: Not Stated | P27: Not Stated | Q27: 1402 | R27: IRR | S27: Not Stated | T27: =IF(NOT(ISNUMBER(S27)),"(Not stated)",IF(NOT(ISNUMBER(Q27)),"(Cost year not stated / not a Jalali year)",IFERROR(IF(N(IF(R27="EUR",S27,IF(R27="IRR",S27/INDEX('Assumptions & FX Reference'!$C$5:$C$25,MATCH(Q27,'Assumptions & FX Reference'!$A$5:$A$25,0)),IF(R27="USD",S27*INDEX('Assumptions & FX Reference'!$B$5:$B$25,MATCH(Q27,'Assumptions & FX Reference'!$A$5:$A$25,0))/INDEX('Assumptions & FX Reference'!$C$5:$C$25,MATCH(Q27,'Assumptions & FX Reference'!$A$5:$A$25,0)),"(Not stated)"))))>0,IF(R27="EUR",S27,IF(R27="IRR",S27/INDEX('Assumptions & FX Reference'!$C$5:$C$25,MATCH(Q27,'Assumptions & FX Reference'!$A$5:$A$25,0)),IF(R27="USD",S27*INDEX('Assumptions & FX Reference'!$B$5:$B$25,MATCH(Q27,'Assumptions & FX Reference'!$A$5:$A$25,0))/INDEX('Assumptions & FX Reference'!$C$5:$C$25,MATCH(Q27,'Assumptions & FX Reference'!$A$5:$A$25,0)),"(Not stated)"))),"(FX rate not entered for this year)"),"(FX rate not entered for this year)"))) -> (Not stated) | U27: =IF(NOT(ISNUMBER(S27)),"(Not stated)",IF(NOT(ISNUMBER(Q27)),"(Cost year not stated / not a Jalali year)",IFERROR(IF(N(IF(R27="USD",S27,IF(R27="IRR",S27/INDEX('Assumptions & FX Reference'!$B$5:$B$25,MATCH(Q27,'Assumptions & FX Reference'!$A$5:$A$25,0)),IF(R27="EUR",S27*INDEX('Assumptions & FX Reference'!$C$5:$C$25,MATCH(Q27,'Assumptions & FX Reference'!$A$5:$A$25,0))/INDEX('Assumptions & FX Reference'!$B$5:$B$25,MATCH(Q27,'Assumptions & FX Reference'!$A$5:$A$25,0)),"(Not stated)"))))>0,IF(R27="USD",S27,IF(R27="IRR",S27/INDEX('Assumptions & FX Reference'!$B$5:$B$25,MATCH(Q27,'Assumptions & FX Reference'!$A$5:$A$25,0)),IF(R27="EUR",S27*INDEX('Assumptions & FX Reference'!$C$5:$C$25,MATCH(Q27,'Assumptions & FX Reference'!$A$5:$A$25,0))/INDEX('Assumptions & FX Reference'!$B$5:$B$25,MATCH(Q27,'Assumptions & FX Reference'!$A$5:$A$25,0)),"(Not stated)"))),"(FX rate not entered for this year)"),"(FX rate not entered for this year)"))) -> (Not stated) | V27: =IF(NOT(ISNUMBER(S27)),"(Not stated)",IF(NOT(ISNUMBER(Q27)),"(Cost year not stated / not a Jalali year)",IFERROR(IF(N(IF(R27="IRR",S27,IF(R27="USD",S27*INDEX('Assumptions & FX Reference'!$B$5:$B$25,MATCH(Q27,'Assumptions & FX Reference'!$A$5:$A$25,0)),IF(R27="EUR",S27*INDEX('Assumptions & FX Reference'!$C$5:$C$25,MATCH(Q27,'Assumptions & FX Reference'!$A$5:$A$25,0)),"(Not stated)"))))>0,IF(R27="IRR",S27,IF(R27="USD",S27*INDEX('Assumptions & FX Reference'!$B$5:$B$25,MATCH(Q27,'Assumptions & FX Reference'!$A$5:$A$25,0)),IF(R27="EUR",S27*INDEX('Assumptions & FX Reference'!$C$5:$C$25,MATCH(Q27,'Assumptions & FX Reference'!$A$5:$A$25,0)),"(Not stated)"))),"(FX rate not entered for this year)"),"(FX rate not entered for this year)"))) -> (Not stated) | W27: Not Stated | X27: Class 3 (Basic) | Y27: Basic Engineering | Z27: PEP-Rev.140205_عزيزيان_Gachsaran_4.xlsx (Sheet P.LAB, row 24) | AA27: Price cells read 'یک قلم در ردیف 19' (one item in row 19): no separate price, bundled with the lab furniture group (item 19 Sink line; the Industrial Hood set on item 18 carries 19,504,834,509.76 IRR). Excluded from totals. | AB27: N
A28: 24 | B28: Stripped Waste Water Pumps P-148 A/B/C (inside PK-143) | C28: Koopal Asmari/Bangestan Desalting Unit (Proj No. 53-51-91215) | D28: P-148 A/B/C | E28: PMP | F28: PMP-WWP | G28: 3 | H28: No. | I28: Stripped waste water pumps P-148 A/B/C, centrifugal OH2, supplied inside Stripping Package PK-143 | J28: 50 m3/hr, 3 barg differential | K28: Not Stated | L28: Not Stated | M28: API 610 material class D2 | N28: API 610 & IPS-G-PM-105 | O28: Not Stated | P28: Not Stated | Q28: 1394 | R28: IRR | S28: Not Stated | T28: =IF(NOT(ISNUMBER(S28)),"(Not stated)",IF(NOT(ISNUMBER(Q28)),"(Cost year not stated / not a Jalali year)",IFERROR(IF(N(IF(R28="EUR",S28,IF(R28="IRR",S28/INDEX('Assumptions & FX Reference'!$C$5:$C$25,MATCH(Q28,'Assumptions & FX Reference'!$A$5:$A$25,0)),IF(R28="USD",S28*INDEX('Assumptions & FX Reference'!$B$5:$B$25,MATCH(Q28,'Assumptions & FX Reference'!$A$5:$A$25,0))/INDEX('Assumptions & FX Reference'!$C$5:$C$25,MATCH(Q28,'Assumptions & FX Reference'!$A$5:$A$25,0)),"(Not stated)"))))>0,IF(R28="EUR",S28,IF(R28="IRR",S28/INDEX('Assumptions & FX Reference'!$C$5:$C$25,MATCH(Q28,'Assumptions & FX Reference'!$A$5:$A$25,0)),IF(R28="USD",S28*INDEX('Assumptions & FX Reference'!$B$5:$B$25,MATCH(Q28,'Assumptions & FX Reference'!$A$5:$A$25,0))/INDEX('Assumptions & FX Reference'!$C$5:$C$25,MATCH(Q28,'Assumptions & FX Reference'!$A$5:$A$25,0)),"(Not stated)"))),"(FX rate not entered for this year)"),"(FX rate not entered for this year)"))) -> (Not stated) | U28: =IF(NOT(ISNUMBER(S28)),"(Not stated)",IF(NOT(ISNUMBER(Q28)),"(Cost year not stated / not a Jalali year)",IFERROR(IF(N(IF(R28="USD",S28,IF(R28="IRR",S28/INDEX('Assumptions & FX Reference'!$B$5:$B$25,MATCH(Q28,'Assumptions & FX Reference'!$A$5:$A$25,0)),IF(R28="EUR",S28*INDEX('Assumptions & FX Reference'!$C$5:$C$25,MATCH(Q28,'Assumptions & FX Reference'!$A$5:$A$25,0))/INDEX('Assumptions & FX Reference'!$B$5:$B$25,MATCH(Q28,'Assumptions & FX Reference'!$A$5:$A$25,0)),"(Not stated)"))))>0,IF(R28="USD",S28,IF(R28="IRR",S28/INDEX('Assumptions & FX Reference'!$B$5:$B$25,MATCH(Q28,'Assumptions & FX Reference'!$A$5:$A$25,0)),IF(R28="EUR",S28*INDEX('Assumptions & FX Reference'!$C$5:$C$25,MATCH(Q28,'Assumptions & FX Reference'!$A$5:$A$25,0))/INDEX('Assumptions & FX Reference'!$B$5:$B$25,MATCH(Q28,'Assumptions & FX Reference'!$A$5:$A$25,0)),"(Not stated)"))),"(FX rate not entered for this year)"),"(FX rate not entered for this year)"))) -> (Not stated) | V28: =IF(NOT(ISNUMBER(S28)),"(Not stated)",IF(NOT(ISNUMBER(Q28)),"(Cost year not stated / not a Jalali year)",IFERROR(IF(N(IF(R28="IRR",S28,IF(R28="USD",S28*INDEX('Assumptions & FX Reference'!$B$5:$B$25,MATCH(Q28,'Assumptions & FX Reference'!$A$5:$A$25,0)),IF(R28="EUR",S28*INDEX('Assumptions & FX Reference'!$C$5:$C$25,MATCH(Q28,'Assumptions & FX Reference'!$A$5:$A$25,0)),"(Not stated)"))))>0,IF(R28="IRR",S28,IF(R28="USD",S28*INDEX('Assumptions & FX Reference'!$B$5:$B$25,MATCH(Q28,'Assumptions & FX Reference'!$A$5:$A$25,0)),IF(R28="EUR",S28*INDEX('Assumptions & FX Reference'!$C$5:$C$25,MATCH(Q28,'Assumptions & FX Reference'!$A$5:$A$25,0)),"(Not stated)"))),"(FX rate not entered for this year)"),"(FX rate not entered for this year)"))) -> (Not stated) | W28: Not Stated | X28: Class 2 (FEED) | Y28: FEED Package | Z28: 91215-KPL-ME-RE-476_R03_MTO_and_Cost_Estimation_Report.xlsx (Sheet STRIPPER-B) | AA28: Change Log section C: no separate price, priced inside PK-143 lump sum (9,000,000,000 IRR). Kept for traceability of the waste water disposal train; excluded from totals to avoid double counting. | AB28: N
A29: 25 | B29: OWS Clean Water Pumps P-703 A/B | C29: Gachsaran 4 Development Plan (Proj No. 591111) | D29: P-703 A/B | E29: PMP | F29: PMP-WWP | G29: 2 | H29: No. | I29: Clean water pumps of the oily water separator (OWS) system | J29: 11 m3/hr, 1.8 bar | K29: Not Stated | L29: Not Stated | M29: Not Stated | N29: Not Stated | O29: 0.54 kW | P29: Not Stated | Q29: 1402 | R29: IRR | S29: 13215061000 | T29: =IF(NOT(ISNUMBER(S29)),"(Not stated)",IF(NOT(ISNUMBER(Q29)),"(Cost year not stated / not a Jalali year)",IFERROR(IF(N(IF(R29="EUR",S29,IF(R29="IRR",S29/INDEX('Assumptions & FX Reference'!$C$5:$C$25,MATCH(Q29,'Assumptions & FX Reference'!$A$5:$A$25,0)),IF(R29="USD",S29*INDEX('Assumptions & FX Reference'!$B$5:$B$25,MATCH(Q29,'Assumptions & FX Reference'!$A$5:$A$25,0))/INDEX('Assumptions & FX Reference'!$C$5:$C$25,MATCH(Q29,'Assumptions & FX Reference'!$A$5:$A$25,0)),"(Not stated)"))))>0,IF(R29="EUR",S29,IF(R29="IRR",S29/INDEX('Assumptions & FX Reference'!$C$5:$C$25,MATCH(Q29,'Assumptions & FX Reference'!$A$5:$A$25,0)),IF(R29="USD",S29*INDEX('Assumptions & FX Reference'!$B$5:$B$25,MATCH(Q29,'Assumptions & FX Reference'!$A$5:$A$25,0))/INDEX('Assumptions & FX Reference'!$C$5:$C$25,MATCH(Q29,'Assumptions & FX Reference'!$A$5:$A$25,0)),"(Not stated)"))),"(FX rate not entered for this year)"),"(FX rate not entered for this year)"))) -> 24957.622 | U29: =IF(NOT(ISNUMBER(S29)),"(Not stated)",IF(NOT(ISNUMBER(Q29)),"(Cost year not stated / not a Jalali year)",IFERROR(IF(N(IF(R29="USD",S29,IF(R29="IRR",S29/INDEX('Assumptions & FX Reference'!$B$5:$B$25,MATCH(Q29,'Assumptions & FX Reference'!$A$5:$A$25,0)),IF(R29="EUR",S29*INDEX('Assumptions & FX Reference'!$C$5:$C$25,MATCH(Q29,'Assumptions & FX Reference'!$A$5:$A$25,0))/INDEX('Assumptions & FX Reference'!$B$5:$B$25,MATCH(Q29,'Assumptions & FX Reference'!$A$5:$A$25,0)),"(Not stated)"))))>0,IF(R29="USD",S29,IF(R29="IRR",S29/INDEX('Assumptions & FX Reference'!$B$5:$B$25,MATCH(Q29,'Assumptions & FX Reference'!$A$5:$A$25,0)),IF(R29="EUR",S29*INDEX('Assumptions & FX Reference'!$C$5:$C$25,MATCH(Q29,'Assumptions & FX Reference'!$A$5:$A$25,0))/INDEX('Assumptions & FX Reference'!$B$5:$B$25,MATCH(Q29,'Assumptions & FX Reference'!$A$5:$A$25,0)),"(Not stated)"))),"(FX rate not entered for this year)"),"(FX rate not entered for this year)"))) -> 31464.431 | V29: =IF(NOT(ISNUMBER(S29)),"(Not stated)",IF(NOT(ISNUMBER(Q29)),"(Cost year not stated / not a Jalali year)",IFERROR(IF(N(IF(R29="IRR",S29,IF(R29="USD",S29*INDEX('Assumptions & FX Reference'!$B$5:$B$25,MATCH(Q29,'Assumptions & FX Reference'!$A$5:$A$25,0)),IF(R29="EUR",S29*INDEX('Assumptions & FX Reference'!$C$5:$C$25,MATCH(Q29,'Assumptions & FX Reference'!$A$5:$A$25,0)),"(Not stated)"))))>0,IF(R29="IRR",S29,IF(R29="USD",S29*INDEX('Assumptions & FX Reference'!$B$5:$B$25,MATCH(Q29,'Assumptions & FX Reference'!$A$5:$A$25,0)),IF(R29="EUR",S29*INDEX('Assumptions & FX Reference'!$C$5:$C$25,MATCH(Q29,'Assumptions & FX Reference'!$A$5:$A$25,0)),"(Not stated)"))),"(FX rate not entered for this year)"),"(FX rate not entered for this year)"))) -> 13215061000 | W29: Purchase unit cost without overhead factor (هزینه واحد بدون ضریب) | X29: Class 3 (Basic) | Y29: Basic Engineering | Z29: PEP-Rev.140205_عزيزيان_Gachsaran_4.xlsx (Sheet P.ME, row 53) | AA29: Unit 13,215,061,000 IRR x 2 No. = 26,430,122,000 IRR (P.ME col. K). Freight (حمل) and customs clearance (ترخیص) are separate P.ME columns and are NOT included here; installation excluded (C.mECHANICAL). CHECK: the unit price is identical to the water/water heat exchanger E-002 (P.ME row 4-7), a possible copy-paste in the source; ask the estimator before relying on it. | AB29: Y
A30: 26 | B30: Oil Skimmer Tank OS-201 | C30: Gachsaran 4 Development Plan (Proj No. 591111) | D30: OS-201 | E30: TNK | F30: TNK-SKM | G30: 1 | H30: No. | I30: Oil skimmer tank OS-201 (oily water / skimming system), priced by weight | J30: 392.5 m3, H = 5000 mm, D = 10000 mm | K30: Not Stated | L30: Not Stated | M30: Not Stated | N30: Not Stated | O30: 45,900 kg | P30: Not Stated | Q30: 1402 | R30: IRR | S30: 30294000000 | T30: =IF(NOT(ISNUMBER(S30)),"(Not stated)",IF(NOT(ISNUMBER(Q30)),"(Cost year not stated / not a Jalali year)",IFERROR(IF(N(IF(R30="EUR",S30,IF(R30="IRR",S30/INDEX('Assumptions & FX Reference'!$C$5:$C$25,MATCH(Q30,'Assumptions & FX Reference'!$A$5:$A$25,0)),IF(R30="USD",S30*INDEX('Assumptions & FX Reference'!$B$5:$B$25,MATCH(Q30,'Assumptions & FX Reference'!$A$5:$A$25,0))/INDEX('Assumptions & FX Reference'!$C$5:$C$25,MATCH(Q30,'Assumptions & FX Reference'!$A$5:$A$25,0)),"(Not stated)"))))>0,IF(R30="EUR",S30,IF(R30="IRR",S30/INDEX('Assumptions & FX Reference'!$C$5:$C$25,MATCH(Q30,'Assumptions & FX Reference'!$A$5:$A$25,0)),IF(R30="USD",S30*INDEX('Assumptions & FX Reference'!$B$5:$B$25,MATCH(Q30,'Assumptions & FX Reference'!$A$5:$A$25,0))/INDEX('Assumptions & FX Reference'!$C$5:$C$25,MATCH(Q30,'Assumptions & FX Reference'!$A$5:$A$25,0)),"(Not stated)"))),"(FX rate not entered for this year)"),"(FX rate not entered for this year)"))) -> 57212.465 | U30: =IF(NOT(ISNUMBER(S30)),"(Not stated)",IF(NOT(ISNUMBER(Q30)),"(Cost year not stated / not a Jalali year)",IFERROR(IF(N(IF(R30="USD",S30,IF(R30="IRR",S30/INDEX('Assumptions & FX Reference'!$B$5:$B$25,MATCH(Q30,'Assumptions & FX Reference'!$A$5:$A$25,0)),IF(R30="EUR",S30*INDEX('Assumptions & FX Reference'!$C$5:$C$25,MATCH(Q30,'Assumptions & FX Reference'!$A$5:$A$25,0))/INDEX('Assumptions & FX Reference'!$B$5:$B$25,MATCH(Q30,'Assumptions & FX Reference'!$A$5:$A$25,0)),"(Not stated)"))))>0,IF(R30="USD",S30,IF(R30="IRR",S30/INDEX('Assumptions & FX Reference'!$B$5:$B$25,MATCH(Q30,'Assumptions & FX Reference'!$A$5:$A$25,0)),IF(R30="EUR",S30*INDEX('Assumptions & FX Reference'!$C$5:$C$25,MATCH(Q30,'Assumptions & FX Reference'!$A$5:$A$25,0))/INDEX('Assumptions & FX Reference'!$B$5:$B$25,MATCH(Q30,'Assumptions & FX Reference'!$A$5:$A$25,0)),"(Not stated)"))),"(FX rate not entered for this year)"),"(FX rate not entered for this year)"))) -> 72128.571 | V30: =IF(NOT(ISNUMBER(S30)),"(Not stated)",IF(NOT(ISNUMBER(Q30)),"(Cost year not stated / not a Jalali year)",IFERROR(IF(N(IF(R30="IRR",S30,IF(R30="USD",S30*INDEX('Assumptions & FX Reference'!$B$5:$B$25,MATCH(Q30,'Assumptions & FX Reference'!$A$5:$A$25,0)),IF(R30="EUR",S30*INDEX('Assumptions & FX Reference'!$C$5:$C$25,MATCH(Q30,'Assumptions & FX Reference'!$A$5:$A$25,0)),"(Not stated)"))))>0,IF(R30="IRR",S30,IF(R30="USD",S30*INDEX('Assumptions & FX Reference'!$B$5:$B$25,MATCH(Q30,'Assumptions & FX Reference'!$A$5:$A$25,0)),IF(R30="EUR",S30*INDEX('Assumptions & FX Reference'!$C$5:$C$25,MATCH(Q30,'Assumptions & FX Reference'!$A$5:$A$25,0)),"(Not stated)"))),"(FX rate not entered for this year)"),"(FX rate not entered for this year)"))) -> 30294000000 | W30: Per-kg pricing: 45,900 kg x 660,000 IRR/kg = 30,294,000,000 IRR (price per tank) | X30: Class 3 (Basic) | Y30: Basic Engineering | Z30: PEP-Rev.140205_عزيزيان_Gachsaran_4.xlsx (Sheet P.ME, row 26) | AA30: VERIFIED against P.ME row 26: unit Kg, qty 45,900, rate 660,000 IRR/kg, total K = 30,294,000,000 IRR = line total for the one tank (not a rate). Freight 2,414,884,272.64 IRR (col. N) excluded. Installation excluded (C.mECHANICAL). | AB30: Y
A31: 27 | B31: Skimmer Tanks TK-132 / TK-142 (KPL) | C31: Koopal Asmari/Bangestan Desalting Unit (Proj No. 53-51-91215) | D31: TK-132 / TK-142 | E31: TNK | F31: TNK-SKM | G31: 2 | H31: Set | I31: Skimmer tanks, Train A (TK-132) and Train B (TK-142) | J31: Not Stated | K31: Not Stated | L31: Not Stated | M31: Not Stated | N31: Not Stated | O31: Not Stated | P31: Not Stated | Q31: 1394 | R31: IRR | S31: 3000000000 | T31: =IF(NOT(ISNUMBER(S31)),"(Not stated)",IF(NOT(ISNUMBER(Q31)),"(Cost year not stated / not a Jalali year)",IFERROR(IF(N(IF(R31="EUR",S31,IF(R31="IRR",S31/INDEX('Assumptions & FX Reference'!$C$5:$C$25,MATCH(Q31,'Assumptions & FX Reference'!$A$5:$A$25,0)),IF(R31="USD",S31*INDEX('Assumptions & FX Reference'!$B$5:$B$25,MATCH(Q31,'Assumptions & FX Reference'!$A$5:$A$25,0))/INDEX('Assumptions & FX Reference'!$C$5:$C$25,MATCH(Q31,'Assumptions & FX Reference'!$A$5:$A$25,0)),"(Not stated)"))))>0,IF(R31="EUR",S31,IF(R31="IRR",S31/INDEX('Assumptions & FX Reference'!$C$5:$C$25,MATCH(Q31,'Assumptions & FX Reference'!$A$5:$A$25,0)),IF(R31="USD",S31*INDEX('Assumptions & FX Reference'!$B$5:$B$25,MATCH(Q31,'Assumptions & FX Reference'!$A$5:$A$25,0))/INDEX('Assumptions & FX Reference'!$C$5:$C$25,MATCH(Q31,'Assumptions & FX Reference'!$A$5:$A$25,0)),"(Not stated)"))),"(FX rate not entered for this year)"),"(FX rate not entered for this year)"))) -> 81632.653 | U31: =IF(NOT(ISNUMBER(S31)),"(Not stated)",IF(NOT(ISNUMBER(Q31)),"(Cost year not stated / not a Jalali year)",IFERROR(IF(N(IF(R31="USD",S31,IF(R31="IRR",S31/INDEX('Assumptions & FX Reference'!$B$5:$B$25,MATCH(Q31,'Assumptions & FX Reference'!$A$5:$A$25,0)),IF(R31="EUR",S31*INDEX('Assumptions & FX Reference'!$C$5:$C$25,MATCH(Q31,'Assumptions & FX Reference'!$A$5:$A$25,0))/INDEX('Assumptions & FX Reference'!$B$5:$B$25,MATCH(Q31,'Assumptions & FX Reference'!$A$5:$A$25,0)),"(Not stated)"))))>0,IF(R31="USD",S31,IF(R31="IRR",S31/INDEX('Assumptions & FX Reference'!$B$5:$B$25,MATCH(Q31,'Assumptions & FX Reference'!$A$5:$A$25,0)),IF(R31="EUR",S31*INDEX('Assumptions & FX Reference'!$C$5:$C$25,MATCH(Q31,'Assumptions & FX Reference'!$A$5:$A$25,0))/INDEX('Assumptions & FX Reference'!$B$5:$B$25,MATCH(Q31,'Assumptions & FX Reference'!$A$5:$A$25,0)),"(Not stated)"))),"(FX rate not entered for this year)"),"(FX rate not entered for this year)"))) -> 89418.778 | V31: =IF(NOT(ISNUMBER(S31)),"(Not stated)",IF(NOT(ISNUMBER(Q31)),"(Cost year not stated / not a Jalali year)",IFERROR(IF(N(IF(R31="IRR",S31,IF(R31="USD",S31*INDEX('Assumptions & FX Reference'!$B$5:$B$25,MATCH(Q31,'Assumptions & FX Reference'!$A$5:$A$25,0)),IF(R31="EUR",S31*INDEX('Assumptions & FX Reference'!$C$5:$C$25,MATCH(Q31,'Assumptions & FX Reference'!$A$5:$A$25,0)),"(Not stated)"))))>0,IF(R31="IRR",S31,IF(R31="USD",S31*INDEX('Assumptions & FX Reference'!$B$5:$B$25,MATCH(Q31,'Assumptions & FX Reference'!$A$5:$A$25,0)),IF(R31="EUR",S31*INDEX('Assumptions & FX Reference'!$C$5:$C$25,MATCH(Q31,'Assumptions & FX Reference'!$A$5:$A$25,0)),"(Not stated)"))),"(FX rate not entered for this year)"),"(FX rate not entered for this year)"))) -> 3000000000 | W31: Design & procurement of raw material only (excl. construction & installation) | X31: Class 2 (FEED) | Y31: FEED Package | Z31: 91215-KPL-ME-RE-476_R03_MTO_and_Cost_Estimation_Report.xlsx (Sheets TANKS-A (1) row 43, TANKS-B (2) row 27) | AA31: 1 Set each at 3,000,000,000 IRR (EUR = 0); total 6,000,000,000 IRR for 2. No capacity/size given in the sheet. Source note: cost is for design and procurement of raw material only; installation is in INS-TANK-A (4) / INS-TANK-B (5) and excluded here. | AB31: Y
A32: 28 | B32: First Stage Separator | C32: Not Stated (reference price sample, file نمونه_قیمتی_نمک_زدایی_overall.xlsx) | D32: (No Tag - price sample VESSELS item 3) | E32: VSL | F32: VSL-SEP | G32: Not Stated | H32: Not Stated | I32: First stage separator, three-phase process vessel from the price sample | J32: Horizontal; ID 3000 mm, T/T 14000 mm | K32: 27 | L32: Not Stated | M32: C.S (internals: demister pad, vortex breaker - S.S) | N32: Not Stated | O32: Not Stated | P32: Not Stated | Q32: Not Stated | R32: USD | S32: 6500000 | T32: =IF(NOT(ISNUMBER(S32)),"(Not stated)",IF(NOT(ISNUMBER(Q32)),"(Cost year not stated / not a Jalali year)",IFERROR(IF(N(IF(R32="EUR",S32,IF(R32="IRR",S32/INDEX('Assumptions & FX Reference'!$C$5:$C$25,MATCH(Q32,'Assumptions & FX Reference'!$A$5:$A$25,0)),IF(R32="USD",S32*INDEX('Assumptions & FX Reference'!$B$5:$B$25,MATCH(Q32,'Assumptions & FX Reference'!$A$5:$A$25,0))/INDEX('Assumptions & FX Reference'!$C$5:$C$25,MATCH(Q32,'Assumptions & FX Reference'!$A$5:$A$25,0)),"(Not stated)"))))>0,IF(R32="EUR",S32,IF(R32="IRR",S32/INDEX('Assumptions & FX Reference'!$C$5:$C$25,MATCH(Q32,'Assumptions & FX Reference'!$A$5:$A$25,0)),IF(R32="USD",S32*INDEX('Assumptions & FX Reference'!$B$5:$B$25,MATCH(Q32,'Assumptions & FX Reference'!$A$5:$A$25,0))/INDEX('Assumptions & FX Reference'!$C$5:$C$25,MATCH(Q32,'Assumptions & FX Reference'!$A$5:$A$25,0)),"(Not stated)"))),"(FX rate not entered for this year)"),"(FX rate not entered for this year)"))) -> (Cost year not stated / not a Jalali year) | U32: =IF(NOT(ISNUMBER(S32)),"(Not stated)",IF(NOT(ISNUMBER(Q32)),"(Cost year not stated / not a Jalali year)",IFERROR(IF(N(IF(R32="USD",S32,IF(R32="IRR",S32/INDEX('Assumptions & FX Reference'!$B$5:$B$25,MATCH(Q32,'Assumptions & FX Reference'!$A$5:$A$25,0)),IF(R32="EUR",S32*INDEX('Assumptions & FX Reference'!$C$5:$C$25,MATCH(Q32,'Assumptions & FX Reference'!$A$5:$A$25,0))/INDEX('Assumptions & FX Reference'!$B$5:$B$25,MATCH(Q32,'Assumptions & FX Reference'!$A$5:$A$25,0)),"(Not stated)"))))>0,IF(R32="USD",S32,IF(R32="IRR",S32/INDEX('Assumptions & FX Reference'!$B$5:$B$25,MATCH(Q32,'Assumptions & FX Reference'!$A$5:$A$25,0)),IF(R32="EUR",S32*INDEX('Assumptions & FX Reference'!$C$5:$C$25,MATCH(Q32,'Assumptions & FX Reference'!$A$5:$A$25,0))/INDEX('Assumptions & FX Reference'!$B$5:$B$25,MATCH(Q32,'Assumptions & FX Reference'!$A$5:$A$25,0)),"(Not stated)"))),"(FX rate not entered for this year)"),"(FX rate not entered for this year)"))) -> (Cost year not stated / not a Jalali year) | V32: =IF(NOT(ISNUMBER(S32)),"(Not stated)",IF(NOT(ISNUMBER(Q32)),"(Cost year not stated / not a Jalali year)",IFERROR(IF(N(IF(R32="IRR",S32,IF(R32="USD",S32*INDEX('Assumptions & FX Reference'!$B$5:$B$25,MATCH(Q32,'Assumptions & FX Reference'!$A$5:$A$25,0)),IF(R32="EUR",S32*INDEX('Assumptions & FX Reference'!$C$5:$C$25,MATCH(Q32,'Assumptions & FX Reference'!$A$5:$A$25,0)),"(Not stated)"))))>0,IF(R32="IRR",S32,IF(R32="USD",S32*INDEX('Assumptions & FX Reference'!$B$5:$B$25,MATCH(Q32,'Assumptions & FX Reference'!$A$5:$A$25,0)),IF(R32="EUR",S32*INDEX('Assumptions & FX Reference'!$C$5:$C$25,MATCH(Q32,'Assumptions & FX Reference'!$A$5:$A$25,0)),"(Not stated)"))),"(FX rate not entered for this year)"),"(FX rate not entered for this year)"))) -> (Cost year not stated / not a Jalali year) | W32: Reference price sample (Price ($) column); basis, cost year and quantity not stated | X32: Not Stated | Y32: Not Stated | Z32: نمونه_قیمتی_نمک_زدایی_overall.xlsx (Sheet VESSELS, row 3) | AA32: Price ($) = 6,500,000 USD for one first stage separator (price-sample row has no quantity). Design pressure 27 barg (internal), external pressure not given; corrosion allowance 3 mm; no insulation. Cost year not stated, so EUR/IRR columns show no conversion. Described in the Change Log as a three-phase process vessel, not an oily water separator. Installation excluded. | AB32: Y
A33: 29 | B33: Waste Water Treatment Package | C33: Gachsaran 4 Development Plan (Proj No. 591111) | D33: (No Tag - P.ME item 66.9) | E33: PKG | F33: PKG-EFF | G33: Not Stated | H33: Not Stated | I33: Waste water (effluent) treatment package; listed under HVAC group item 66 in P.ME but is a process package | J33: Not Stated | K33: Not Stated | L33: Not Stated | M33: Not Stated | N33: Not Stated | O33: Not Stated | P33: Not Stated | Q33: 1402 | R33: IRR | S33: 3600000000 | T33: =IF(NOT(ISNUMBER(S33)),"(Not stated)",IF(NOT(ISNUMBER(Q33)),"(Cost year not stated / not a Jalali year)",IFERROR(IF(N(IF(R33="EUR",S33,IF(R33="IRR",S33/INDEX('Assumptions & FX Reference'!$C$5:$C$25,MATCH(Q33,'Assumptions & FX Reference'!$A$5:$A$25,0)),IF(R33="USD",S33*INDEX('Assumptions & FX Reference'!$B$5:$B$25,MATCH(Q33,'Assumptions & FX Reference'!$A$5:$A$25,0))/INDEX('Assumptions & FX Reference'!$C$5:$C$25,MATCH(Q33,'Assumptions & FX Reference'!$A$5:$A$25,0)),"(Not stated)"))))>0,IF(R33="EUR",S33,IF(R33="IRR",S33/INDEX('Assumptions & FX Reference'!$C$5:$C$25,MATCH(Q33,'Assumptions & FX Reference'!$A$5:$A$25,0)),IF(R33="USD",S33*INDEX('Assumptions & FX Reference'!$B$5:$B$25,MATCH(Q33,'Assumptions & FX Reference'!$A$5:$A$25,0))/INDEX('Assumptions & FX Reference'!$C$5:$C$25,MATCH(Q33,'Assumptions & FX Reference'!$A$5:$A$25,0)),"(Not stated)"))),"(FX rate not entered for this year)"),"(FX rate not entered for this year)"))) -> 6798.8669 | U33: =IF(NOT(ISNUMBER(S33)),"(Not stated)",IF(NOT(ISNUMBER(Q33)),"(Cost year not stated / not a Jalali year)",IFERROR(IF(N(IF(R33="USD",S33,IF(R33="IRR",S33/INDEX('Assumptions & FX Reference'!$B$5:$B$25,MATCH(Q33,'Assumptions & FX Reference'!$A$5:$A$25,0)),IF(R33="EUR",S33*INDEX('Assumptions & FX Reference'!$C$5:$C$25,MATCH(Q33,'Assumptions & FX Reference'!$A$5:$A$25,0))/INDEX('Assumptions & FX Reference'!$B$5:$B$25,MATCH(Q33,'Assumptions & FX Reference'!$A$5:$A$25,0)),"(Not stated)"))))>0,IF(R33="USD",S33,IF(R33="IRR",S33/INDEX('Assumptions & FX Reference'!$B$5:$B$25,MATCH(Q33,'Assumptions & FX Reference'!$A$5:$A$25,0)),IF(R33="EUR",S33*INDEX('Assumptions & FX Reference'!$C$5:$C$25,MATCH(Q33,'Assumptions & FX Reference'!$A$5:$A$25,0))/INDEX('Assumptions & FX Reference'!$B$5:$B$25,MATCH(Q33,'Assumptions & FX Reference'!$A$5:$A$25,0)),"(Not stated)"))),"(FX rate not entered for this year)"),"(FX rate not entered for this year)"))) -> 8571.4286 | V33: =IF(NOT(ISNUMBER(S33)),"(Not stated)",IF(NOT(ISNUMBER(Q33)),"(Cost year not stated / not a Jalali year)",IFERROR(IF(N(IF(R33="IRR",S33,IF(R33="USD",S33*INDEX('Assumptions & FX Reference'!$B$5:$B$25,MATCH(Q33,'Assumptions & FX Reference'!$A$5:$A$25,0)),IF(R33="EUR",S33*INDEX('Assumptions & FX Reference'!$C$5:$C$25,MATCH(Q33,'Assumptions & FX Reference'!$A$5:$A$25,0)),"(Not stated)"))))>0,IF(R33="IRR",S33,IF(R33="USD",S33*INDEX('Assumptions & FX Reference'!$B$5:$B$25,MATCH(Q33,'Assumptions & FX Reference'!$A$5:$A$25,0)),IF(R33="EUR",S33*INDEX('Assumptions & FX Reference'!$C$5:$C$25,MATCH(Q33,'Assumptions & FX Reference'!$A$5:$A$25,0)),"(Not stated)"))),"(FX rate not entered for this year)"),"(FX rate not entered for this year)"))) -> 3600000000 | W33: Not Stated | X33: Class 3 (Basic) | Y33: Basic Engineering | Z33: PEP-Rev.140205_عزيزيان_Gachsaran_4.xlsx (Sheet P.ME, row 92) | AA33: Amount from Change Log section C. Price basis, quantity/unit and freight not carried in the Change Log (TO BE VERIFIED in P.ME row 92). Part of the 370,840,000,000 IRR HVAC summary (see Change Log D). | AB33: Y
A34: 30 | B34: Water Treatment Package | C34: Gachsaran 4 Development Plan (Proj No. 591111) | D34: (No Tag - P.ME item 66.10) | E34: PKG | F34: PKG-WTR | G34: Not Stated | H34: Not Stated | I34: Water treatment package; listed under HVAC group item 66 in P.ME but is a process package | J34: Not Stated | K34: Not Stated | L34: Not Stated | M34: Not Stated | N34: Not Stated | O34: Not Stated | P34: Not Stated | Q34: 1402 | R34: IRR | S34: 2500000000 | T34: =IF(NOT(ISNUMBER(S34)),"(Not stated)",IF(NOT(ISNUMBER(Q34)),"(Cost year not stated / not a Jalali year)",IFERROR(IF(N(IF(R34="EUR",S34,IF(R34="IRR",S34/INDEX('Assumptions & FX Reference'!$C$5:$C$25,MATCH(Q34,'Assumptions & FX Reference'!$A$5:$A$25,0)),IF(R34="USD",S34*INDEX('Assumptions & FX Reference'!$B$5:$B$25,MATCH(Q34,'Assumptions & FX Reference'!$A$5:$A$25,0))/INDEX('Assumptions & FX Reference'!$C$5:$C$25,MATCH(Q34,'Assumptions & FX Reference'!$A$5:$A$25,0)),"(Not stated)"))))>0,IF(R34="EUR",S34,IF(R34="IRR",S34/INDEX('Assumptions & FX Reference'!$C$5:$C$25,MATCH(Q34,'Assumptions & FX Reference'!$A$5:$A$25,0)),IF(R34="USD",S34*INDEX('Assumptions & FX Reference'!$B$5:$B$25,MATCH(Q34,'Assumptions & FX Reference'!$A$5:$A$25,0))/INDEX('Assumptions & FX Reference'!$C$5:$C$25,MATCH(Q34,'Assumptions & FX Reference'!$A$5:$A$25,0)),"(Not stated)"))),"(FX rate not entered for this year)"),"(FX rate not entered for this year)"))) -> 4721.4353 | U34: =IF(NOT(ISNUMBER(S34)),"(Not stated)",IF(NOT(ISNUMBER(Q34)),"(Cost year not stated / not a Jalali year)",IFERROR(IF(N(IF(R34="USD",S34,IF(R34="IRR",S34/INDEX('Assumptions & FX Reference'!$B$5:$B$25,MATCH(Q34,'Assumptions & FX Reference'!$A$5:$A$25,0)),IF(R34="EUR",S34*INDEX('Assumptions & FX Reference'!$C$5:$C$25,MATCH(Q34,'Assumptions & FX Reference'!$A$5:$A$25,0))/INDEX('Assumptions & FX Reference'!$B$5:$B$25,MATCH(Q34,'Assumptions & FX Reference'!$A$5:$A$25,0)),"(Not stated)"))))>0,IF(R34="USD",S34,IF(R34="IRR",S34/INDEX('Assumptions & FX Reference'!$B$5:$B$25,MATCH(Q34,'Assumptions & FX Reference'!$A$5:$A$25,0)),IF(R34="EUR",S34*INDEX('Assumptions & FX Reference'!$C$5:$C$25,MATCH(Q34,'Assumptions & FX Reference'!$A$5:$A$25,0))/INDEX('Assumptions & FX Reference'!$B$5:$B$25,MATCH(Q34,'Assumptions & FX Reference'!$A$5:$A$25,0)),"(Not stated)"))),"(FX rate not entered for this year)"),"(FX rate not entered for this year)"))) -> 5952.381 | V34: =IF(NOT(ISNUMBER(S34)),"(Not stated)",IF(NOT(ISNUMBER(Q34)),"(Cost year not stated / not a Jalali year)",IFERROR(IF(N(IF(R34="IRR",S34,IF(R34="USD",S34*INDEX('Assumptions & FX Reference'!$B$5:$B$25,MATCH(Q34,'Assumptions & FX Reference'!$A$5:$A$25,0)),IF(R34="EUR",S34*INDEX('Assumptions & FX Reference'!$C$5:$C$25,MATCH(Q34,'Assumptions & FX Reference'!$A$5:$A$25,0)),"(Not stated)"))))>0,IF(R34="IRR",S34,IF(R34="USD",S34*INDEX('Assumptions & FX Reference'!$B$5:$B$25,MATCH(Q34,'Assumptions & FX Reference'!$A$5:$A$25,0)),IF(R34="EUR",S34*INDEX('Assumptions & FX Reference'!$C$5:$C$25,MATCH(Q34,'Assumptions & FX Reference'!$A$5:$A$25,0)),"(Not stated)"))),"(FX rate not entered for this year)"),"(FX rate not entered for this year)"))) -> 2500000000 | W34: Not Stated | X34: Class 3 (Basic) | Y34: Basic Engineering | Z34: PEP-Rev.140205_عزيزيان_Gachsaran_4.xlsx (Sheet P.ME, row 93) | AA34: Amount from Change Log section C. Price basis, quantity/unit and freight not carried in the Change Log (TO BE VERIFIED in P.ME row 93). Part of the 370,840,000,000 IRR HVAC summary. | AB34: Y
A35: 31 | B35: HVAC Group Rollup (Gachsaran 4 Summary) | C35: Gachsaran 4 Development Plan (Proj No. 591111) | D35: (Category Rollup - not a discrete Tag) | E35: HVAC | F35: HVAC-SYS | G35: Not Stated | H35: Lump Sum | I35: HVAC group summary of P.ME (items 66.1-66.10) | J35: Not Stated | K35: Not Stated | L35: Not Stated | M35: Not Stated | N35: Not Stated | O35: Not Stated | P35: Not Stated | Q35: 1402 | R35: IRR | S35: 370840000000 | T35: =IF(NOT(ISNUMBER(S35)),"(Not stated)",IF(NOT(ISNUMBER(Q35)),"(Cost year not stated / not a Jalali year)",IFERROR(IF(N(IF(R35="EUR",S35,IF(R35="IRR",S35/INDEX('Assumptions & FX Reference'!$C$5:$C$25,MATCH(Q35,'Assumptions & FX Reference'!$A$5:$A$25,0)),IF(R35="USD",S35*INDEX('Assumptions & FX Reference'!$B$5:$B$25,MATCH(Q35,'Assumptions & FX Reference'!$A$5:$A$25,0))/INDEX('Assumptions & FX Reference'!$C$5:$C$25,MATCH(Q35,'Assumptions & FX Reference'!$A$5:$A$25,0)),"(Not stated)"))))>0,IF(R35="EUR",S35,IF(R35="IRR",S35/INDEX('Assumptions & FX Reference'!$C$5:$C$25,MATCH(Q35,'Assumptions & FX Reference'!$A$5:$A$25,0)),IF(R35="USD",S35*INDEX('Assumptions & FX Reference'!$B$5:$B$25,MATCH(Q35,'Assumptions & FX Reference'!$A$5:$A$25,0))/INDEX('Assumptions & FX Reference'!$C$5:$C$25,MATCH(Q35,'Assumptions & FX Reference'!$A$5:$A$25,0)),"(Not stated)"))),"(FX rate not entered for this year)"),"(FX rate not entered for this year)"))) -> 700358.83 | U35: =IF(NOT(ISNUMBER(S35)),"(Not stated)",IF(NOT(ISNUMBER(Q35)),"(Cost year not stated / not a Jalali year)",IFERROR(IF(N(IF(R35="USD",S35,IF(R35="IRR",S35/INDEX('Assumptions & FX Reference'!$B$5:$B$25,MATCH(Q35,'Assumptions & FX Reference'!$A$5:$A$25,0)),IF(R35="EUR",S35*INDEX('Assumptions & FX Reference'!$C$5:$C$25,MATCH(Q35,'Assumptions & FX Reference'!$A$5:$A$25,0))/INDEX('Assumptions & FX Reference'!$B$5:$B$25,MATCH(Q35,'Assumptions & FX Reference'!$A$5:$A$25,0)),"(Not stated)"))))>0,IF(R35="USD",S35,IF(R35="IRR",S35/INDEX('Assumptions & FX Reference'!$B$5:$B$25,MATCH(Q35,'Assumptions & FX Reference'!$A$5:$A$25,0)),IF(R35="EUR",S35*INDEX('Assumptions & FX Reference'!$C$5:$C$25,MATCH(Q35,'Assumptions & FX Reference'!$A$5:$A$25,0))/INDEX('Assumptions & FX Reference'!$B$5:$B$25,MATCH(Q35,'Assumptions & FX Reference'!$A$5:$A$25,0)),"(Not stated)"))),"(FX rate not entered for this year)"),"(FX rate not entered for this year)"))) -> 882952.38 | V35: =IF(NOT(ISNUMBER(S35)),"(Not stated)",IF(NOT(ISNUMBER(Q35)),"(Cost year not stated / not a Jalali year)",IFERROR(IF(N(IF(R35="IRR",S35,IF(R35="USD",S35*INDEX('Assumptions & FX Reference'!$B$5:$B$25,MATCH(Q35,'Assumptions & FX Reference'!$A$5:$A$25,0)),IF(R35="EUR",S35*INDEX('Assumptions & FX Reference'!$C$5:$C$25,MATCH(Q35,'Assumptions & FX Reference'!$A$5:$A$25,0)),"(Not stated)"))))>0,IF(R35="IRR",S35,IF(R35="USD",S35*INDEX('Assumptions & FX Reference'!$B$5:$B$25,MATCH(Q35,'Assumptions & FX Reference'!$A$5:$A$25,0)),IF(R35="EUR",S35*INDEX('Assumptions & FX Reference'!$C$5:$C$25,MATCH(Q35,'Assumptions & FX Reference'!$A$5:$A$25,0)),"(Not stated)"))),"(FX rate not entered for this year)"),"(FX rate not entered for this year)"))) -> 370840000000 | W35: Not Stated | X35: Class 3 (Basic) | Y35: Basic Engineering | Z35: PEP-Rev.140205_عزيزيان_Gachsaran_4.xlsx (Sheet P.ME, summary row 138) | AA35: Equals items 66.1-66.8 (364,740,000,000) + waste water (3,600,000,000) + water treatment (2,500,000,000) packages. Excluded: would double count the itemised rows. | AB35: N
A36: 32 | B36: Safety Group Rollup (Gachsaran 4 Summary) | C36: Gachsaran 4 Development Plan (Proj No. 591111) | D36: (Category Rollup - not a discrete Tag) | E36: SAF | F36: SAF-PKG | G36: Not Stated | H36: Lump Sum | I36: Safety equipment group summary of P.ME | J36: Not Stated | K36: Not Stated | L36: Not Stated | M36: Not Stated | N36: Not Stated | O36: Not Stated | P36: Not Stated | Q36: 1402 | R36: IRR | S36: 163763000000 | T36: =IF(NOT(ISNUMBER(S36)),"(Not stated)",IF(NOT(ISNUMBER(Q36)),"(Cost year not stated / not a Jalali year)",IFERROR(IF(N(IF(R36="EUR",S36,IF(R36="IRR",S36/INDEX('Assumptions & FX Reference'!$C$5:$C$25,MATCH(Q36,'Assumptions & FX Reference'!$A$5:$A$25,0)),IF(R36="USD",S36*INDEX('Assumptions & FX Reference'!$B$5:$B$25,MATCH(Q36,'Assumptions & FX Reference'!$A$5:$A$25,0))/INDEX('Assumptions & FX Reference'!$C$5:$C$25,MATCH(Q36,'Assumptions & FX Reference'!$A$5:$A$25,0)),"(Not stated)"))))>0,IF(R36="EUR",S36,IF(R36="IRR",S36/INDEX('Assumptions & FX Reference'!$C$5:$C$25,MATCH(Q36,'Assumptions & FX Reference'!$A$5:$A$25,0)),IF(R36="USD",S36*INDEX('Assumptions & FX Reference'!$B$5:$B$25,MATCH(Q36,'Assumptions & FX Reference'!$A$5:$A$25,0))/INDEX('Assumptions & FX Reference'!$C$5:$C$25,MATCH(Q36,'Assumptions & FX Reference'!$A$5:$A$25,0)),"(Not stated)"))),"(FX rate not entered for this year)"),"(FX rate not entered for this year)"))) -> 309278.56 | U36: =IF(NOT(ISNUMBER(S36)),"(Not stated)",IF(NOT(ISNUMBER(Q36)),"(Cost year not stated / not a Jalali year)",IFERROR(IF(N(IF(R36="USD",S36,IF(R36="IRR",S36/INDEX('Assumptions & FX Reference'!$B$5:$B$25,MATCH(Q36,'Assumptions & FX Reference'!$A$5:$A$25,0)),IF(R36="EUR",S36*INDEX('Assumptions & FX Reference'!$C$5:$C$25,MATCH(Q36,'Assumptions & FX Reference'!$A$5:$A$25,0))/INDEX('Assumptions & FX Reference'!$B$5:$B$25,MATCH(Q36,'Assumptions & FX Reference'!$A$5:$A$25,0)),"(Not stated)"))))>0,IF(R36="USD",S36,IF(R36="IRR",S36/INDEX('Assumptions & FX Reference'!$B$5:$B$25,MATCH(Q36,'Assumptions & FX Reference'!$A$5:$A$25,0)),IF(R36="EUR",S36*INDEX('Assumptions & FX Reference'!$C$5:$C$25,MATCH(Q36,'Assumptions & FX Reference'!$A$5:$A$25,0))/INDEX('Assumptions & FX Reference'!$B$5:$B$25,MATCH(Q36,'Assumptions & FX Reference'!$A$5:$A$25,0)),"(Not stated)"))),"(FX rate not entered for this year)"),"(FX rate not entered for this year)"))) -> 389911.9 | V36: =IF(NOT(ISNUMBER(S36)),"(Not stated)",IF(NOT(ISNUMBER(Q36)),"(Cost year not stated / not a Jalali year)",IFERROR(IF(N(IF(R36="IRR",S36,IF(R36="USD",S36*INDEX('Assumptions & FX Reference'!$B$5:$B$25,MATCH(Q36,'Assumptions & FX Reference'!$A$5:$A$25,0)),IF(R36="EUR",S36*INDEX('Assumptions & FX Reference'!$C$5:$C$25,MATCH(Q36,'Assumptions & FX Reference'!$A$5:$A$25,0)),"(Not stated)"))))>0,IF(R36="IRR",S36,IF(R36="USD",S36*INDEX('Assumptions & FX Reference'!$B$5:$B$25,MATCH(Q36,'Assumptions & FX Reference'!$A$5:$A$25,0)),IF(R36="EUR",S36*INDEX('Assumptions & FX Reference'!$C$5:$C$25,MATCH(Q36,'Assumptions & FX Reference'!$A$5:$A$25,0)),"(Not stated)"))),"(FX rate not entered for this year)"),"(FX rate not entered for this year)"))) -> 163763000000 | W36: Not Stated | X36: Class 3 (Basic) | Y36: Basic Engineering | Z36: PEP-Rev.140205_عزيزيان_Gachsaran_4.xlsx (Sheet P.ME, summary row 140) | AA36: Summary table 2.1 row 140 ("خرید اقلام ایمنی و آتش نشانی"), item 15, purchase column = 163,763,000,000 IRR. Itemised P.ME rows 95-112 (items 67.1-67.19, incl. the safety shower of 8,820,000,000 IRR already in Master row 20) sum to 163,762,195,576 IRR; difference ~0.8 million IRR is rounding in the summary. Excluded: would double count the itemised rows. Freight/customs and installation not included. | AB36: N
A37: 33 | B37: Pig Group Rollup (Gachsaran 4 Summary) | C37: Gachsaran 4 Development Plan (Proj No. 591111) | D37: (Category Rollup - not a discrete Tag) | E37: PKG | F37: PKG-PIG | G37: Not Stated | H37: Lump Sum | I37: Pig launcher & receiver group summary of P.ME | J37: Not Stated | K37: Not Stated | L37: Not Stated | M37: Not Stated | N37: Not Stated | O37: Not Stated | P37: Not Stated | Q37: 1402 | R37: IRR | S37: 94500000000 | T37: =IF(NOT(ISNUMBER(S37)),"(Not stated)",IF(NOT(ISNUMBER(Q37)),"(Cost year not stated / not a Jalali year)",IFERROR(IF(N(IF(R37="EUR",S37,IF(R37="IRR",S37/INDEX('Assumptions & FX Reference'!$C$5:$C$25,MATCH(Q37,'Assumptions & FX Reference'!$A$5:$A$25,0)),IF(R37="USD",S37*INDEX('Assumptions & FX Reference'!$B$5:$B$25,MATCH(Q37,'Assumptions & FX Reference'!$A$5:$A$25,0))/INDEX('Assumptions & FX Reference'!$C$5:$C$25,MATCH(Q37,'Assumptions & FX Reference'!$A$5:$A$25,0)),"(Not stated)"))))>0,IF(R37="EUR",S37,IF(R37="IRR",S37/INDEX('Assumptions & FX Reference'!$C$5:$C$25,MATCH(Q37,'Assumptions & FX Reference'!$A$5:$A$25,0)),IF(R37="USD",S37*INDEX('Assumptions & FX Reference'!$B$5:$B$25,MATCH(Q37,'Assumptions & FX Reference'!$A$5:$A$25,0))/INDEX('Assumptions & FX Reference'!$C$5:$C$25,MATCH(Q37,'Assumptions & FX Reference'!$A$5:$A$25,0)),"(Not stated)"))),"(FX rate not entered for this year)"),"(FX rate not entered for this year)"))) -> 178470.25 | U37: =IF(NOT(ISNUMBER(S37)),"(Not stated)",IF(NOT(ISNUMBER(Q37)),"(Cost year not stated / not a Jalali year)",IFERROR(IF(N(IF(R37="USD",S37,IF(R37="IRR",S37/INDEX('Assumptions & FX Reference'!$B$5:$B$25,MATCH(Q37,'Assumptions & FX Reference'!$A$5:$A$25,0)),IF(R37="EUR",S37*INDEX('Assumptions & FX Reference'!$C$5:$C$25,MATCH(Q37,'Assumptions & FX Reference'!$A$5:$A$25,0))/INDEX('Assumptions & FX Reference'!$B$5:$B$25,MATCH(Q37,'Assumptions & FX Reference'!$A$5:$A$25,0)),"(Not stated)"))))>0,IF(R37="USD",S37,IF(R37="IRR",S37/INDEX('Assumptions & FX Reference'!$B$5:$B$25,MATCH(Q37,'Assumptions & FX Reference'!$A$5:$A$25,0)),IF(R37="EUR",S37*INDEX('Assumptions & FX Reference'!$C$5:$C$25,MATCH(Q37,'Assumptions & FX Reference'!$A$5:$A$25,0))/INDEX('Assumptions & FX Reference'!$B$5:$B$25,MATCH(Q37,'Assumptions & FX Reference'!$A$5:$A$25,0)),"(Not stated)"))),"(FX rate not entered for this year)"),"(FX rate not entered for this year)"))) -> 225000 | V37: =IF(NOT(ISNUMBER(S37)),"(Not stated)",IF(NOT(ISNUMBER(Q37)),"(Cost year not stated / not a Jalali year)",IFERROR(IF(N(IF(R37="IRR",S37,IF(R37="USD",S37*INDEX('Assumptions & FX Reference'!$B$5:$B$25,MATCH(Q37,'Assumptions & FX Reference'!$A$5:$A$25,0)),IF(R37="EUR",S37*INDEX('Assumptions & FX Reference'!$C$5:$C$25,MATCH(Q37,'Assumptions & FX Reference'!$A$5:$A$25,0)),"(Not stated)"))))>0,IF(R37="IRR",S37,IF(R37="USD",S37*INDEX('Assumptions & FX Reference'!$B$5:$B$25,MATCH(Q37,'Assumptions & FX Reference'!$A$5:$A$25,0)),IF(R37="EUR",S37*INDEX('Assumptions & FX Reference'!$C$5:$C$25,MATCH(Q37,'Assumptions & FX Reference'!$A$5:$A$25,0)),"(Not stated)"))),"(FX rate not entered for this year)"),"(FX rate not entered for this year)"))) -> 94500000000 | W37: Not Stated | X37: Class 3 (Basic) | Y37: Basic Engineering | Z37: PEP-Rev.140205_عزيزيان_Gachsaran_4.xlsx (Sheet P.ME, summary row 141) | AA37: Summary table 2.1 row 141 ("گیرنده و فرستنده توپک"), item 16, purchase column = 94,500,000,000 IRR; equals P.ME row 113 (item 68, 1 SET, 225,000 USD x 420,000), already in Master row 8. Excluded: would double count. Freight 241,488,427 IRR and installation not included. | AB37: N
A38: 34 | B38: Safety & Fire Fighting Package | C38: Not Stated (reference price sample, file نمونه_قیمتی_نمک_زدایی_overall.xlsx) | D38: (No Tag - price sample CSV row 74) | E38: SAF | F38: SAF-PKG | G38: 1 | H38: Lump Sum | I38: Safety & fire fighting package for the whole fire and safety scope | J38: Not Stated | K38: Not Stated | L38: Not Stated | M38: Not Stated | N38: Not Stated | O38: Not Stated | P38: Not Stated | Q38: Not Stated | R38: USD | S38: 1800000 | T38: =IF(NOT(ISNUMBER(S38)),"(Not stated)",IF(NOT(ISNUMBER(Q38)),"(Cost year not stated / not a Jalali year)",IFERROR(IF(N(IF(R38="EUR",S38,IF(R38="IRR",S38/INDEX('Assumptions & FX Reference'!$C$5:$C$25,MATCH(Q38,'Assumptions & FX Reference'!$A$5:$A$25,0)),IF(R38="USD",S38*INDEX('Assumptions & FX Reference'!$B$5:$B$25,MATCH(Q38,'Assumptions & FX Reference'!$A$5:$A$25,0))/INDEX('Assumptions & FX Reference'!$C$5:$C$25,MATCH(Q38,'Assumptions & FX Reference'!$A$5:$A$25,0)),"(Not stated)"))))>0,IF(R38="EUR",S38,IF(R38="IRR",S38/INDEX('Assumptions & FX Reference'!$C$5:$C$25,MATCH(Q38,'Assumptions & FX Reference'!$A$5:$A$25,0)),IF(R38="USD",S38*INDEX('Assumptions & FX Reference'!$B$5:$B$25,MATCH(Q38,'Assumptions & FX Reference'!$A$5:$A$25,0))/INDEX('Assumptions & FX Reference'!$C$5:$C$25,MATCH(Q38,'Assumptions & FX Reference'!$A$5:$A$25,0)),"(Not stated)"))),"(FX rate not entered for this year)"),"(FX rate not entered for this year)"))) -> (Cost year not stated / not a Jalali year) | U38: =IF(NOT(ISNUMBER(S38)),"(Not stated)",IF(NOT(ISNUMBER(Q38)),"(Cost year not stated / not a Jalali year)",IFERROR(IF(N(IF(R38="USD",S38,IF(R38="IRR",S38/INDEX('Assumptions & FX Reference'!$B$5:$B$25,MATCH(Q38,'Assumptions & FX Reference'!$A$5:$A$25,0)),IF(R38="EUR",S38*INDEX('Assumptions & FX Reference'!$C$5:$C$25,MATCH(Q38,'Assumptions & FX Reference'!$A$5:$A$25,0))/INDEX('Assumptions & FX Reference'!$B$5:$B$25,MATCH(Q38,'Assumptions & FX Reference'!$A$5:$A$25,0)),"(Not stated)"))))>0,IF(R38="USD",S38,IF(R38="IRR",S38/INDEX('Assumptions & FX Reference'!$B$5:$B$25,MATCH(Q38,'Assumptions & FX Reference'!$A$5:$A$25,0)),IF(R38="EUR",S38*INDEX('Assumptions & FX Reference'!$C$5:$C$25,MATCH(Q38,'Assumptions & FX Reference'!$A$5:$A$25,0))/INDEX('Assumptions & FX Reference'!$B$5:$B$25,MATCH(Q38,'Assumptions & FX Reference'!$A$5:$A$25,0)),"(Not stated)"))),"(FX rate not entered for this year)"),"(FX rate not entered for this year)"))) -> (Cost year not stated / not a Jalali year) | V38: =IF(NOT(ISNUMBER(S38)),"(Not stated)",IF(NOT(ISNUMBER(Q38)),"(Cost year not stated / not a Jalali year)",IFERROR(IF(N(IF(R38="IRR",S38,IF(R38="USD",S38*INDEX('Assumptions & FX Reference'!$B$5:$B$25,MATCH(Q38,'Assumptions & FX Reference'!$A$5:$A$25,0)),IF(R38="EUR",S38*INDEX('Assumptions & FX Reference'!$C$5:$C$25,MATCH(Q38,'Assumptions & FX Reference'!$A$5:$A$25,0)),"(Not stated)"))))>0,IF(R38="IRR",S38,IF(R38="USD",S38*INDEX('Assumptions & FX Reference'!$B$5:$B$25,MATCH(Q38,'Assumptions & FX Reference'!$A$5:$A$25,0)),IF(R38="EUR",S38*INDEX('Assumptions & FX Reference'!$C$5:$C$25,MATCH(Q38,'Assumptions & FX Reference'!$A$5:$A$25,0)),"(Not stated)"))),"(FX rate not entered for this year)"),"(FX rate not entered for this year)"))) -> (Cost year not stated / not a Jalali year) | W38: Not Stated | X38: Not Stated | Y38: Not Stated | Z38: 18061405_Pump_only_CSV.csv (file row 74) | AA38: 1,800,000 USD lump sum for the whole fire and safety scope (not a shower line), per Change Log. Cost year, scope split, customs/transport not stated. Quantity 1 = lump sum. | AB38: Y
A39: 35 | B39: OWS Recovered Waste Oil Pumps P-704 A/B | C39: Gachsaran 4 Development Plan (Proj No. 591111) | D39: P-704 A/B | E39: PMP | F39: PMP-WWP | G39: 2 | H39: No. | I39: Recovered waste oil pumps of the oily water separator (OWS) system | J39: 11 m3/hr, 2.7 bar | K39: Not Stated | L39: Not Stated | M39: Not Stated | N39: Not Stated | O39: 0.8 kW | P39: Not Stated | Q39: 1402 | R39: IRR | S39: 15949212000 | T39: =IF(NOT(ISNUMBER(S39)),"(Not stated)",IF(NOT(ISNUMBER(Q39)),"(Cost year not stated / not a Jalali year)",IFERROR(IF(N(IF(R39="EUR",S39,IF(R39="IRR",S39/INDEX('Assumptions & FX Reference'!$C$5:$C$25,MATCH(Q39,'Assumptions & FX Reference'!$A$5:$A$25,0)),IF(R39="USD",S39*INDEX('Assumptions & FX Reference'!$B$5:$B$25,MATCH(Q39,'Assumptions & FX Reference'!$A$5:$A$25,0))/INDEX('Assumptions & FX Reference'!$C$5:$C$25,MATCH(Q39,'Assumptions & FX Reference'!$A$5:$A$25,0)),"(Not stated)"))))>0,IF(R39="EUR",S39,IF(R39="IRR",S39/INDEX('Assumptions & FX Reference'!$C$5:$C$25,MATCH(Q39,'Assumptions & FX Reference'!$A$5:$A$25,0)),IF(R39="USD",S39*INDEX('Assumptions & FX Reference'!$B$5:$B$25,MATCH(Q39,'Assumptions & FX Reference'!$A$5:$A$25,0))/INDEX('Assumptions & FX Reference'!$C$5:$C$25,MATCH(Q39,'Assumptions & FX Reference'!$A$5:$A$25,0)),"(Not stated)"))),"(FX rate not entered for this year)"),"(FX rate not entered for this year)"))) -> 30121.269 | U39: =IF(NOT(ISNUMBER(S39)),"(Not stated)",IF(NOT(ISNUMBER(Q39)),"(Cost year not stated / not a Jalali year)",IFERROR(IF(N(IF(R39="USD",S39,IF(R39="IRR",S39/INDEX('Assumptions & FX Reference'!$B$5:$B$25,MATCH(Q39,'Assumptions & FX Reference'!$A$5:$A$25,0)),IF(R39="EUR",S39*INDEX('Assumptions & FX Reference'!$C$5:$C$25,MATCH(Q39,'Assumptions & FX Reference'!$A$5:$A$25,0))/INDEX('Assumptions & FX Reference'!$B$5:$B$25,MATCH(Q39,'Assumptions & FX Reference'!$A$5:$A$25,0)),"(Not stated)"))))>0,IF(R39="USD",S39,IF(R39="IRR",S39/INDEX('Assumptions & FX Reference'!$B$5:$B$25,MATCH(Q39,'Assumptions & FX Reference'!$A$5:$A$25,0)),IF(R39="EUR",S39*INDEX('Assumptions & FX Reference'!$C$5:$C$25,MATCH(Q39,'Assumptions & FX Reference'!$A$5:$A$25,0))/INDEX('Assumptions & FX Reference'!$B$5:$B$25,MATCH(Q39,'Assumptions & FX Reference'!$A$5:$A$25,0)),"(Not stated)"))),"(FX rate not entered for this year)"),"(FX rate not entered for this year)"))) -> 37974.314 | V39: =IF(NOT(ISNUMBER(S39)),"(Not stated)",IF(NOT(ISNUMBER(Q39)),"(Cost year not stated / not a Jalali year)",IFERROR(IF(N(IF(R39="IRR",S39,IF(R39="USD",S39*INDEX('Assumptions & FX Reference'!$B$5:$B$25,MATCH(Q39,'Assumptions & FX Reference'!$A$5:$A$25,0)),IF(R39="EUR",S39*INDEX('Assumptions & FX Reference'!$C$5:$C$25,MATCH(Q39,'Assumptions & FX Reference'!$A$5:$A$25,0)),"(Not stated)"))))>0,IF(R39="IRR",S39,IF(R39="USD",S39*INDEX('Assumptions & FX Reference'!$B$5:$B$25,MATCH(Q39,'Assumptions & FX Reference'!$A$5:$A$25,0)),IF(R39="EUR",S39*INDEX('Assumptions & FX Reference'!$C$5:$C$25,MATCH(Q39,'Assumptions & FX Reference'!$A$5:$A$25,0)),"(Not stated)"))),"(FX rate not entered for this year)"),"(FX rate not entered for this year)"))) -> 15949212000 | W39: Purchase unit cost without overhead factor (هزینه واحد بدون ضریب) | X39: Class 3 (Basic) | Y39: Basic Engineering | Z39: PEP-Rev.140205_عزيزيان_Gachsaran_4.xlsx (Sheet P.ME, row 54) | AA39: Unit 15,949,212,000 IRR x 2 No. = 31,898,424,000 IRR (P.ME col. K). Freight (حمل) and customs clearance (ترخیص) are separate P.ME columns and are NOT included here; installation excluded (C.mECHANICAL). | AB39: Y
A40: 36 | B40: Oily Water Separator Pump P-750 | C40: Gachsaran 4 Development Plan (Proj No. 591111) | D40: P-750 | E40: PMP | F40: PMP-WWP | G40: 1 | H40: No. | I40: Oily water separator pump (OWS system) | J40: 1 m3/hr, 0.84 bar | K40: Not Stated | L40: Not Stated | M40: Not Stated | N40: Not Stated | O40: 0.02 kW | P40: Not Stated | Q40: 1402 | R40: IRR | S40: 6083485000 | T40: =IF(NOT(ISNUMBER(S40)),"(Not stated)",IF(NOT(ISNUMBER(Q40)),"(Cost year not stated / not a Jalali year)",IFERROR(IF(N(IF(R40="EUR",S40,IF(R40="IRR",S40/INDEX('Assumptions & FX Reference'!$C$5:$C$25,MATCH(Q40,'Assumptions & FX Reference'!$A$5:$A$25,0)),IF(R40="USD",S40*INDEX('Assumptions & FX Reference'!$B$5:$B$25,MATCH(Q40,'Assumptions & FX Reference'!$A$5:$A$25,0))/INDEX('Assumptions & FX Reference'!$C$5:$C$25,MATCH(Q40,'Assumptions & FX Reference'!$A$5:$A$25,0)),"(Not stated)"))))>0,IF(R40="EUR",S40,IF(R40="IRR",S40/INDEX('Assumptions & FX Reference'!$C$5:$C$25,MATCH(Q40,'Assumptions & FX Reference'!$A$5:$A$25,0)),IF(R40="USD",S40*INDEX('Assumptions & FX Reference'!$B$5:$B$25,MATCH(Q40,'Assumptions & FX Reference'!$A$5:$A$25,0))/INDEX('Assumptions & FX Reference'!$C$5:$C$25,MATCH(Q40,'Assumptions & FX Reference'!$A$5:$A$25,0)),"(Not stated)"))),"(FX rate not entered for this year)"),"(FX rate not entered for this year)"))) -> 11489.112 | U40: =IF(NOT(ISNUMBER(S40)),"(Not stated)",IF(NOT(ISNUMBER(Q40)),"(Cost year not stated / not a Jalali year)",IFERROR(IF(N(IF(R40="USD",S40,IF(R40="IRR",S40/INDEX('Assumptions & FX Reference'!$B$5:$B$25,MATCH(Q40,'Assumptions & FX Reference'!$A$5:$A$25,0)),IF(R40="EUR",S40*INDEX('Assumptions & FX Reference'!$C$5:$C$25,MATCH(Q40,'Assumptions & FX Reference'!$A$5:$A$25,0))/INDEX('Assumptions & FX Reference'!$B$5:$B$25,MATCH(Q40,'Assumptions & FX Reference'!$A$5:$A$25,0)),"(Not stated)"))))>0,IF(R40="USD",S40,IF(R40="IRR",S40/INDEX('Assumptions & FX Reference'!$B$5:$B$25,MATCH(Q40,'Assumptions & FX Reference'!$A$5:$A$25,0)),IF(R40="EUR",S40*INDEX('Assumptions & FX Reference'!$C$5:$C$25,MATCH(Q40,'Assumptions & FX Reference'!$A$5:$A$25,0))/INDEX('Assumptions & FX Reference'!$B$5:$B$25,MATCH(Q40,'Assumptions & FX Reference'!$A$5:$A$25,0)),"(Not stated)"))),"(FX rate not entered for this year)"),"(FX rate not entered for this year)"))) -> 14484.488 | V40: =IF(NOT(ISNUMBER(S40)),"(Not stated)",IF(NOT(ISNUMBER(Q40)),"(Cost year not stated / not a Jalali year)",IFERROR(IF(N(IF(R40="IRR",S40,IF(R40="USD",S40*INDEX('Assumptions & FX Reference'!$B$5:$B$25,MATCH(Q40,'Assumptions & FX Reference'!$A$5:$A$25,0)),IF(R40="EUR",S40*INDEX('Assumptions & FX Reference'!$C$5:$C$25,MATCH(Q40,'Assumptions & FX Reference'!$A$5:$A$25,0)),"(Not stated)"))))>0,IF(R40="IRR",S40,IF(R40="USD",S40*INDEX('Assumptions & FX Reference'!$B$5:$B$25,MATCH(Q40,'Assumptions & FX Reference'!$A$5:$A$25,0)),IF(R40="EUR",S40*INDEX('Assumptions & FX Reference'!$C$5:$C$25,MATCH(Q40,'Assumptions & FX Reference'!$A$5:$A$25,0)),"(Not stated)"))),"(FX rate not entered for this year)"),"(FX rate not entered for this year)"))) -> 6083485000 | W40: Purchase unit cost without overhead factor (هزینه واحد بدون ضریب) | X40: Class 3 (Basic) | Y40: Basic Engineering | Z40: PEP-Rev.140205_عزيزيان_Gachsaran_4.xlsx (Sheet P.ME, row 55) | AA40: Unit 6,083,485,000 IRR x 1 No. = 6,083,485,000 IRR (P.ME col. K). Freight (حمل) and customs clearance (ترخیص) are separate P.ME columns and are NOT included here; installation excluded (C.mECHANICAL). Note: price looks high for a 0.02 kW pump; as stated in source. | AB40: Y
A41: 37 | B41: Water Hydrant 6" | C41: Gachsaran 4 Development Plan (Proj No. 591111) | D41: (No Tag - P.ME item 67.1) | E41: SAF | F41: SAF-HYD | G41: 13 | H41: No. | I41: Water Hydrant 6" (Safety Equipment list, P.ME item 67.1) | J41: 6" | K41: Not Stated | L41: Not Stated | M41: Not Stated | N41: Not Stated | O41: Not Stated | P41: Not Stated | Q41: 1402 | R41: IRR | S41: 3.7307177e+08 | T41: =IF(NOT(ISNUMBER(S41)),"(Not stated)",IF(NOT(ISNUMBER(Q41)),"(Cost year not stated / not a Jalali year)",IFERROR(IF(N(IF(R41="EUR",S41,IF(R41="IRR",S41/INDEX('Assumptions & FX Reference'!$C$5:$C$25,MATCH(Q41,'Assumptions & FX Reference'!$A$5:$A$25,0)),IF(R41="USD",S41*INDEX('Assumptions & FX Reference'!$B$5:$B$25,MATCH(Q41,'Assumptions & FX Reference'!$A$5:$A$25,0))/INDEX('Assumptions & FX Reference'!$C$5:$C$25,MATCH(Q41,'Assumptions & FX Reference'!$A$5:$A$25,0)),"(Not stated)"))))>0,IF(R41="EUR",S41,IF(R41="IRR",S41/INDEX('Assumptions & FX Reference'!$C$5:$C$25,MATCH(Q41,'Assumptions & FX Reference'!$A$5:$A$25,0)),IF(R41="USD",S41*INDEX('Assumptions & FX Reference'!$B$5:$B$25,MATCH(Q41,'Assumptions & FX Reference'!$A$5:$A$25,0))/INDEX('Assumptions & FX Reference'!$C$5:$C$25,MATCH(Q41,'Assumptions & FX Reference'!$A$5:$A$25,0)),"(Not stated)"))),"(FX rate not entered for this year)"),"(FX rate not entered for this year)"))) -> 704.57369 | U41: =IF(NOT(ISNUMBER(S41)),"(Not stated)",IF(NOT(ISNUMBER(Q41)),"(Cost year not stated / not a Jalali year)",IFERROR(IF(N(IF(R41="USD",S41,IF(R41="IRR",S41/INDEX('Assumptions & FX Reference'!$B$5:$B$25,MATCH(Q41,'Assumptions & FX Reference'!$A$5:$A$25,0)),IF(R41="EUR",S41*INDEX('Assumptions & FX Reference'!$C$5:$C$25,MATCH(Q41,'Assumptions & FX Reference'!$A$5:$A$25,0))/INDEX('Assumptions & FX Reference'!$B$5:$B$25,MATCH(Q41,'Assumptions & FX Reference'!$A$5:$A$25,0)),"(Not stated)"))))>0,IF(R41="USD",S41,IF(R41="IRR",S41/INDEX('Assumptions & FX Reference'!$B$5:$B$25,MATCH(Q41,'Assumptions & FX Reference'!$A$5:$A$25,0)),IF(R41="EUR",S41*INDEX('Assumptions & FX Reference'!$C$5:$C$25,MATCH(Q41,'Assumptions & FX Reference'!$A$5:$A$25,0))/INDEX('Assumptions & FX Reference'!$B$5:$B$25,MATCH(Q41,'Assumptions & FX Reference'!$A$5:$A$25,0)),"(Not stated)"))),"(FX rate not entered for this year)"),"(FX rate not entered for this year)"))) -> 888.26611 | V41: =IF(NOT(ISNUMBER(S41)),"(Not stated)",IF(NOT(ISNUMBER(Q41)),"(Cost year not stated / not a Jalali year)",IFERROR(IF(N(IF(R41="IRR",S41,IF(R41="USD",S41*INDEX('Assumptions & FX Reference'!$B$5:$B$25,MATCH(Q41,'Assumptions & FX Reference'!$A$5:$A$25,0)),IF(R41="EUR",S41*INDEX('Assumptions & FX Reference'!$C$5:$C$25,MATCH(Q41,'Assumptions & FX Reference'!$A$5:$A$25,0)),"(Not stated)"))))>0,IF(R41="IRR",S41,IF(R41="USD",S41*INDEX('Assumptions & FX Reference'!$B$5:$B$25,MATCH(Q41,'Assumptions & FX Reference'!$A$5:$A$25,0)),IF(R41="EUR",S41*INDEX('Assumptions & FX Reference'!$C$5:$C$25,MATCH(Q41,'Assumptions & FX Reference'!$A$5:$A$25,0)),"(Not stated)"))),"(FX rate not entered for this year)"),"(FX rate not entered for this year)"))) -> 3.7307177e+08 | W41: Purchase unit cost without overhead factor (هزینه واحد بدون ضریب) | X41: Class 3 (Basic) | Y41: Basic Engineering | Z41: PEP-Rev.140205_عزيزيان_Gachsaran_4.xlsx (Sheet P.ME, row 95) | AA41: Unit 373,071,767.26 IRR x 13 = line total 4,849,932,974.42 IRR (P.ME col. K). No freight/customs given on this row; installation excluded (C.HSE / C.mECHANICAL). | AB41: Y
A42: 38 | B42: Water Hydrant with Monitor 6" | C42: Gachsaran 4 Development Plan (Proj No. 591111) | D42: (No Tag - P.ME item 67.2) | E42: SAF | F42: SAF-HYD | G42: 27 | H42: No. | I42: Water Hydrant with Monitor 6" (Safety Equipment list, P.ME item 67.2) | J42: 6" | K42: Not Stated | L42: Not Stated | M42: Not Stated | N42: Not Stated | O42: Not Stated | P42: Not Stated | Q42: 1402 | R42: IRR | S42: 9.0603143e+08 | T42: =IF(NOT(ISNUMBER(S42)),"(Not stated)",IF(NOT(ISNUMBER(Q42)),"(Cost year not stated / not a Jalali year)",IFERROR(IF(N(IF(R42="EUR",S42,IF(R42="IRR",S42/INDEX('Assumptions & FX Reference'!$C$5:$C$25,MATCH(Q42,'Assumptions & FX Reference'!$A$5:$A$25,0)),IF(R42="USD",S42*INDEX('Assumptions & FX Reference'!$B$5:$B$25,MATCH(Q42,'Assumptions & FX Reference'!$A$5:$A$25,0))/INDEX('Assumptions & FX Reference'!$C$5:$C$25,MATCH(Q42,'Assumptions & FX Reference'!$A$5:$A$25,0)),"(Not stated)"))))>0,IF(R42="EUR",S42,IF(R42="IRR",S42/INDEX('Assumptions & FX Reference'!$C$5:$C$25,MATCH(Q42,'Assumptions & FX Reference'!$A$5:$A$25,0)),IF(R42="USD",S42*INDEX('Assumptions & FX Reference'!$B$5:$B$25,MATCH(Q42,'Assumptions & FX Reference'!$A$5:$A$25,0))/INDEX('Assumptions & FX Reference'!$C$5:$C$25,MATCH(Q42,'Assumptions & FX Reference'!$A$5:$A$25,0)),"(Not stated)"))),"(FX rate not entered for this year)"),"(FX rate not entered for this year)"))) -> 1711.1075 | U42: =IF(NOT(ISNUMBER(S42)),"(Not stated)",IF(NOT(ISNUMBER(Q42)),"(Cost year not stated / not a Jalali year)",IFERROR(IF(N(IF(R42="USD",S42,IF(R42="IRR",S42/INDEX('Assumptions & FX Reference'!$B$5:$B$25,MATCH(Q42,'Assumptions & FX Reference'!$A$5:$A$25,0)),IF(R42="EUR",S42*INDEX('Assumptions & FX Reference'!$C$5:$C$25,MATCH(Q42,'Assumptions & FX Reference'!$A$5:$A$25,0))/INDEX('Assumptions & FX Reference'!$B$5:$B$25,MATCH(Q42,'Assumptions & FX Reference'!$A$5:$A$25,0)),"(Not stated)"))))>0,IF(R42="USD",S42,IF(R42="IRR",S42/INDEX('Assumptions & FX Reference'!$B$5:$B$25,MATCH(Q42,'Assumptions & FX Reference'!$A$5:$A$25,0)),IF(R42="EUR",S42*INDEX('Assumptions & FX Reference'!$C$5:$C$25,MATCH(Q42,'Assumptions & FX Reference'!$A$5:$A$25,0))/INDEX('Assumptions & FX Reference'!$B$5:$B$25,MATCH(Q42,'Assumptions & FX Reference'!$A$5:$A$25,0)),"(Not stated)"))),"(FX rate not entered for this year)"),"(FX rate not entered for this year)"))) -> 2157.2177 | V42: =IF(NOT(ISNUMBER(S42)),"(Not stated)",IF(NOT(ISNUMBER(Q42)),"(Cost year not stated / not a Jalali year)",IFERROR(IF(N(IF(R42="IRR",S42,IF(R42="USD",S42*INDEX('Assumptions & FX Reference'!$B$5:$B$25,MATCH(Q42,'Assumptions & FX Reference'!$A$5:$A$25,0)),IF(R42="EUR",S42*INDEX('Assumptions & FX Reference'!$C$5:$C$25,MATCH(Q42,'Assumptions & FX Reference'!$A$5:$A$25,0)),"(Not stated)"))))>0,IF(R42="IRR",S42,IF(R42="USD",S42*INDEX('Assumptions & FX Reference'!$B$5:$B$25,MATCH(Q42,'Assumptions & FX Reference'!$A$5:$A$25,0)),IF(R42="EUR",S42*INDEX('Assumptions & FX Reference'!$C$5:$C$25,MATCH(Q42,'Assumptions & FX Reference'!$A$5:$A$25,0)),"(Not stated)"))),"(FX rate not entered for this year)"),"(FX rate not entered for this year)"))) -> 9.0603143e+08 | W42: Purchase unit cost without overhead factor (هزینه واحد بدون ضریب) | X42: Class 3 (Basic) | Y42: Basic Engineering | Z42: PEP-Rev.140205_عزيزيان_Gachsaran_4.xlsx (Sheet P.ME, row 96) | AA42: Unit 906,031,434.78 IRR x 27 = line total 24,462,848,739.12 IRR (P.ME col. K). No freight/customs given on this row; installation excluded (C.HSE / C.mECHANICAL). | AB42: Y
A43: 39 | B43: Deluge Valve 4" | C43: Gachsaran 4 Development Plan (Proj No. 591111) | D43: (No Tag - P.ME item 67.3) | E43: SAF | F43: SAF-HYD | G43: 2 | H43: No. | I43: Deluge Valve 4" (Safety Equipment list, P.ME item 67.3) | J43: 4" | K43: Not Stated | L43: Not Stated | M43: Not Stated | N43: Not Stated | O43: Not Stated | P43: Not Stated | Q43: 1402 | R43: IRR | S43: 6300000000 | T43: =IF(NOT(ISNUMBER(S43)),"(Not stated)",IF(NOT(ISNUMBER(Q43)),"(Cost year not stated / not a Jalali year)",IFERROR(IF(N(IF(R43="EUR",S43,IF(R43="IRR",S43/INDEX('Assumptions & FX Reference'!$C$5:$C$25,MATCH(Q43,'Assumptions & FX Reference'!$A$5:$A$25,0)),IF(R43="USD",S43*INDEX('Assumptions & FX Reference'!$B$5:$B$25,MATCH(Q43,'Assumptions & FX Reference'!$A$5:$A$25,0))/INDEX('Assumptions & FX Reference'!$C$5:$C$25,MATCH(Q43,'Assumptions & FX Reference'!$A$5:$A$25,0)),"(Not stated)"))))>0,IF(R43="EUR",S43,IF(R43="IRR",S43/INDEX('Assumptions & FX Reference'!$C$5:$C$25,MATCH(Q43,'Assumptions & FX Reference'!$A$5:$A$25,0)),IF(R43="USD",S43*INDEX('Assumptions & FX Reference'!$B$5:$B$25,MATCH(Q43,'Assumptions & FX Reference'!$A$5:$A$25,0))/INDEX('Assumptions & FX Reference'!$C$5:$C$25,MATCH(Q43,'Assumptions & FX Reference'!$A$5:$A$25,0)),"(Not stated)"))),"(FX rate not entered for this year)"),"(FX rate not entered for this year)"))) -> 11898.017 | U43: =IF(NOT(ISNUMBER(S43)),"(Not stated)",IF(NOT(ISNUMBER(Q43)),"(Cost year not stated / not a Jalali year)",IFERROR(IF(N(IF(R43="USD",S43,IF(R43="IRR",S43/INDEX('Assumptions & FX Reference'!$B$5:$B$25,MATCH(Q43,'Assumptions & FX Reference'!$A$5:$A$25,0)),IF(R43="EUR",S43*INDEX('Assumptions & FX Reference'!$C$5:$C$25,MATCH(Q43,'Assumptions & FX Reference'!$A$5:$A$25,0))/INDEX('Assumptions & FX Reference'!$B$5:$B$25,MATCH(Q43,'Assumptions & FX Reference'!$A$5:$A$25,0)),"(Not stated)"))))>0,IF(R43="USD",S43,IF(R43="IRR",S43/INDEX('Assumptions & FX Reference'!$B$5:$B$25,MATCH(Q43,'Assumptions & FX Reference'!$A$5:$A$25,0)),IF(R43="EUR",S43*INDEX('Assumptions & FX Reference'!$C$5:$C$25,MATCH(Q43,'Assumptions & FX Reference'!$A$5:$A$25,0))/INDEX('Assumptions & FX Reference'!$B$5:$B$25,MATCH(Q43,'Assumptions & FX Reference'!$A$5:$A$25,0)),"(Not stated)"))),"(FX rate not entered for this year)"),"(FX rate not entered for this year)"))) -> 15000 | V43: =IF(NOT(ISNUMBER(S43)),"(Not stated)",IF(NOT(ISNUMBER(Q43)),"(Cost year not stated / not a Jalali year)",IFERROR(IF(N(IF(R43="IRR",S43,IF(R43="USD",S43*INDEX('Assumptions & FX Reference'!$B$5:$B$25,MATCH(Q43,'Assumptions & FX Reference'!$A$5:$A$25,0)),IF(R43="EUR",S43*INDEX('Assumptions & FX Reference'!$C$5:$C$25,MATCH(Q43,'Assumptions & FX Reference'!$A$5:$A$25,0)),"(Not stated)"))))>0,IF(R43="IRR",S43,IF(R43="USD",S43*INDEX('Assumptions & FX Reference'!$B$5:$B$25,MATCH(Q43,'Assumptions & FX Reference'!$A$5:$A$25,0)),IF(R43="EUR",S43*INDEX('Assumptions & FX Reference'!$C$5:$C$25,MATCH(Q43,'Assumptions & FX Reference'!$A$5:$A$25,0)),"(Not stated)"))),"(FX rate not entered for this year)"),"(FX rate not entered for this year)"))) -> 6300000000 | W43: Purchase unit cost without overhead factor (هزینه واحد بدون ضریب) | X43: Class 3 (Basic) | Y43: Basic Engineering | Z43: PEP-Rev.140205_عزيزيان_Gachsaran_4.xlsx (Sheet P.ME, row 97) | AA43: Unit 6,300,000,000 IRR x 2 = line total 12,600,000,000 IRR (P.ME col. K). No freight/customs given on this row; installation excluded (C.HSE / C.mECHANICAL). | AB43: Y
A44: 40 | B44: Dry Powder Portable Fire Extinguisher 12 kg | C44: Gachsaran 4 Development Plan (Proj No. 591111) | D44: (No Tag - P.ME item 67.4) | E44: SAF | F44: SAF-EXT | G44: 32 | H44: No. | I44: Dry Powder Portable Fire Extinguisher 12 kg (Safety Equipment list, P.ME item 67.4) | J44: 12 KG | K44: Not Stated | L44: Not Stated | M44: Not Stated | N44: Not Stated | O44: Not Stated | P44: Not Stated | Q44: 1402 | R44: IRR | S44: 47966370 | T44: =IF(NOT(ISNUMBER(S44)),"(Not stated)",IF(NOT(ISNUMBER(Q44)),"(Cost year not stated / not a Jalali year)",IFERROR(IF(N(IF(R44="EUR",S44,IF(R44="IRR",S44/INDEX('Assumptions & FX Reference'!$C$5:$C$25,MATCH(Q44,'Assumptions & FX Reference'!$A$5:$A$25,0)),IF(R44="USD",S44*INDEX('Assumptions & FX Reference'!$B$5:$B$25,MATCH(Q44,'Assumptions & FX Reference'!$A$5:$A$25,0))/INDEX('Assumptions & FX Reference'!$C$5:$C$25,MATCH(Q44,'Assumptions & FX Reference'!$A$5:$A$25,0)),"(Not stated)"))))>0,IF(R44="EUR",S44,IF(R44="IRR",S44/INDEX('Assumptions & FX Reference'!$C$5:$C$25,MATCH(Q44,'Assumptions & FX Reference'!$A$5:$A$25,0)),IF(R44="USD",S44*INDEX('Assumptions & FX Reference'!$B$5:$B$25,MATCH(Q44,'Assumptions & FX Reference'!$A$5:$A$25,0))/INDEX('Assumptions & FX Reference'!$C$5:$C$25,MATCH(Q44,'Assumptions & FX Reference'!$A$5:$A$25,0)),"(Not stated)"))),"(FX rate not entered for this year)"),"(FX rate not entered for this year)"))) -> 90.588045 | U44: =IF(NOT(ISNUMBER(S44)),"(Not stated)",IF(NOT(ISNUMBER(Q44)),"(Cost year not stated / not a Jalali year)",IFERROR(IF(N(IF(R44="USD",S44,IF(R44="IRR",S44/INDEX('Assumptions & FX Reference'!$B$5:$B$25,MATCH(Q44,'Assumptions & FX Reference'!$A$5:$A$25,0)),IF(R44="EUR",S44*INDEX('Assumptions & FX Reference'!$C$5:$C$25,MATCH(Q44,'Assumptions & FX Reference'!$A$5:$A$25,0))/INDEX('Assumptions & FX Reference'!$B$5:$B$25,MATCH(Q44,'Assumptions & FX Reference'!$A$5:$A$25,0)),"(Not stated)"))))>0,IF(R44="USD",S44,IF(R44="IRR",S44/INDEX('Assumptions & FX Reference'!$B$5:$B$25,MATCH(Q44,'Assumptions & FX Reference'!$A$5:$A$25,0)),IF(R44="EUR",S44*INDEX('Assumptions & FX Reference'!$C$5:$C$25,MATCH(Q44,'Assumptions & FX Reference'!$A$5:$A$25,0))/INDEX('Assumptions & FX Reference'!$B$5:$B$25,MATCH(Q44,'Assumptions & FX Reference'!$A$5:$A$25,0)),"(Not stated)"))),"(FX rate not entered for this year)"),"(FX rate not entered for this year)"))) -> 114.20564 | V44: =IF(NOT(ISNUMBER(S44)),"(Not stated)",IF(NOT(ISNUMBER(Q44)),"(Cost year not stated / not a Jalali year)",IFERROR(IF(N(IF(R44="IRR",S44,IF(R44="USD",S44*INDEX('Assumptions & FX Reference'!$B$5:$B$25,MATCH(Q44,'Assumptions & FX Reference'!$A$5:$A$25,0)),IF(R44="EUR",S44*INDEX('Assumptions & FX Reference'!$C$5:$C$25,MATCH(Q44,'Assumptions & FX Reference'!$A$5:$A$25,0)),"(Not stated)"))))>0,IF(R44="IRR",S44,IF(R44="USD",S44*INDEX('Assumptions & FX Reference'!$B$5:$B$25,MATCH(Q44,'Assumptions & FX Reference'!$A$5:$A$25,0)),IF(R44="EUR",S44*INDEX('Assumptions & FX Reference'!$C$5:$C$25,MATCH(Q44,'Assumptions & FX Reference'!$A$5:$A$25,0)),"(Not stated)"))),"(FX rate not entered for this year)"),"(FX rate not entered for this year)"))) -> 47966370 | W44: Purchase unit cost without overhead factor (هزینه واحد بدون ضریب) | X44: Class 3 (Basic) | Y44: Basic Engineering | Z44: PEP-Rev.140205_عزيزيان_Gachsaran_4.xlsx (Sheet P.ME, row 98) | AA44: Unit 47,966,370.08 IRR x 32 = line total 1,534,923,842.45 IRR (P.ME col. K). No freight/customs given on this row; installation excluded (C.HSE / C.mECHANICAL). | AB44: Y
A45: 41 | B45: Dry Powder Wheeled Fire Extinguisher 75 kg | C45: Gachsaran 4 Development Plan (Proj No. 591111) | D45: (No Tag - P.ME item 67.5) | E45: SAF | F45: SAF-EXT | G45: 12 | H45: No. | I45: Dry Powder Wheeled Fire Extinguisher 75 kg (Safety Equipment list, P.ME item 67.5) | J45: 75 KG | K45: Not Stated | L45: Not Stated | M45: Not Stated | N45: Not Stated | O45: Not Stated | P45: Not Stated | Q45: 1402 | R45: IRR | S45: 3.197758e+08 | T45: =IF(NOT(ISNUMBER(S45)),"(Not stated)",IF(NOT(ISNUMBER(Q45)),"(Cost year not stated / not a Jalali year)",IFERROR(IF(N(IF(R45="EUR",S45,IF(R45="IRR",S45/INDEX('Assumptions & FX Reference'!$C$5:$C$25,MATCH(Q45,'Assumptions & FX Reference'!$A$5:$A$25,0)),IF(R45="USD",S45*INDEX('Assumptions & FX Reference'!$B$5:$B$25,MATCH(Q45,'Assumptions & FX Reference'!$A$5:$A$25,0))/INDEX('Assumptions & FX Reference'!$C$5:$C$25,MATCH(Q45,'Assumptions & FX Reference'!$A$5:$A$25,0)),"(Not stated)"))))>0,IF(R45="EUR",S45,IF(R45="IRR",S45/INDEX('Assumptions & FX Reference'!$C$5:$C$25,MATCH(Q45,'Assumptions & FX Reference'!$A$5:$A$25,0)),IF(R45="USD",S45*INDEX('Assumptions & FX Reference'!$B$5:$B$25,MATCH(Q45,'Assumptions & FX Reference'!$A$5:$A$25,0))/INDEX('Assumptions & FX Reference'!$C$5:$C$25,MATCH(Q45,'Assumptions & FX Reference'!$A$5:$A$25,0)),"(Not stated)"))),"(FX rate not entered for this year)"),"(FX rate not entered for this year)"))) -> 603.9203 | U45: =IF(NOT(ISNUMBER(S45)),"(Not stated)",IF(NOT(ISNUMBER(Q45)),"(Cost year not stated / not a Jalali year)",IFERROR(IF(N(IF(R45="USD",S45,IF(R45="IRR",S45/INDEX('Assumptions & FX Reference'!$B$5:$B$25,MATCH(Q45,'Assumptions & FX Reference'!$A$5:$A$25,0)),IF(R45="EUR",S45*INDEX('Assumptions & FX Reference'!$C$5:$C$25,MATCH(Q45,'Assumptions & FX Reference'!$A$5:$A$25,0))/INDEX('Assumptions & FX Reference'!$B$5:$B$25,MATCH(Q45,'Assumptions & FX Reference'!$A$5:$A$25,0)),"(Not stated)"))))>0,IF(R45="USD",S45,IF(R45="IRR",S45/INDEX('Assumptions & FX Reference'!$B$5:$B$25,MATCH(Q45,'Assumptions & FX Reference'!$A$5:$A$25,0)),IF(R45="EUR",S45*INDEX('Assumptions & FX Reference'!$C$5:$C$25,MATCH(Q45,'Assumptions & FX Reference'!$A$5:$A$25,0))/INDEX('Assumptions & FX Reference'!$B$5:$B$25,MATCH(Q45,'Assumptions & FX Reference'!$A$5:$A$25,0)),"(Not stated)"))),"(FX rate not entered for this year)"),"(FX rate not entered for this year)"))) -> 761.37095 | V45: =IF(NOT(ISNUMBER(S45)),"(Not stated)",IF(NOT(ISNUMBER(Q45)),"(Cost year not stated / not a Jalali year)",IFERROR(IF(N(IF(R45="IRR",S45,IF(R45="USD",S45*INDEX('Assumptions & FX Reference'!$B$5:$B$25,MATCH(Q45,'Assumptions & FX Reference'!$A$5:$A$25,0)),IF(R45="EUR",S45*INDEX('Assumptions & FX Reference'!$C$5:$C$25,MATCH(Q45,'Assumptions & FX Reference'!$A$5:$A$25,0)),"(Not stated)"))))>0,IF(R45="IRR",S45,IF(R45="USD",S45*INDEX('Assumptions & FX Reference'!$B$5:$B$25,MATCH(Q45,'Assumptions & FX Reference'!$A$5:$A$25,0)),IF(R45="EUR",S45*INDEX('Assumptions & FX Reference'!$C$5:$C$25,MATCH(Q45,'Assumptions & FX Reference'!$A$5:$A$25,0)),"(Not stated)"))),"(FX rate not entered for this year)"),"(FX rate not entered for this year)"))) -> 3.197758e+08 | W45: Purchase unit cost without overhead factor (هزینه واحد بدون ضریب) | X45: Class 3 (Basic) | Y45: Basic Engineering | Z45: PEP-Rev.140205_عزيزيان_Gachsaran_4.xlsx (Sheet P.ME, row 99) | AA45: Unit 319,775,800.51 IRR x 12 = line total 3,837,309,606.14 IRR (P.ME col. K). No freight/customs given on this row; installation excluded (C.HSE / C.mECHANICAL). | AB45: Y
A46: 42 | B46: CO2 Portable Fire Extinguisher 5 kg | C46: Gachsaran 4 Development Plan (Proj No. 591111) | D46: (No Tag - P.ME item 67.6) | E46: SAF | F46: SAF-EXT | G46: 42 | H46: No. | I46: CO2 Portable Fire Extinguisher 5 kg (Safety Equipment list, P.ME item 67.6) | J46: 5 KG | K46: Not Stated | L46: Not Stated | M46: Not Stated | N46: Not Stated | O46: Not Stated | P46: Not Stated | Q46: 1402 | R46: IRR | S46: 37307177 | T46: =IF(NOT(ISNUMBER(S46)),"(Not stated)",IF(NOT(ISNUMBER(Q46)),"(Cost year not stated / not a Jalali year)",IFERROR(IF(N(IF(R46="EUR",S46,IF(R46="IRR",S46/INDEX('Assumptions & FX Reference'!$C$5:$C$25,MATCH(Q46,'Assumptions & FX Reference'!$A$5:$A$25,0)),IF(R46="USD",S46*INDEX('Assumptions & FX Reference'!$B$5:$B$25,MATCH(Q46,'Assumptions & FX Reference'!$A$5:$A$25,0))/INDEX('Assumptions & FX Reference'!$C$5:$C$25,MATCH(Q46,'Assumptions & FX Reference'!$A$5:$A$25,0)),"(Not stated)"))))>0,IF(R46="EUR",S46,IF(R46="IRR",S46/INDEX('Assumptions & FX Reference'!$C$5:$C$25,MATCH(Q46,'Assumptions & FX Reference'!$A$5:$A$25,0)),IF(R46="USD",S46*INDEX('Assumptions & FX Reference'!$B$5:$B$25,MATCH(Q46,'Assumptions & FX Reference'!$A$5:$A$25,0))/INDEX('Assumptions & FX Reference'!$C$5:$C$25,MATCH(Q46,'Assumptions & FX Reference'!$A$5:$A$25,0)),"(Not stated)"))),"(FX rate not entered for this year)"),"(FX rate not entered for this year)"))) -> 70.457369 | U46: =IF(NOT(ISNUMBER(S46)),"(Not stated)",IF(NOT(ISNUMBER(Q46)),"(Cost year not stated / not a Jalali year)",IFERROR(IF(N(IF(R46="USD",S46,IF(R46="IRR",S46/INDEX('Assumptions & FX Reference'!$B$5:$B$25,MATCH(Q46,'Assumptions & FX Reference'!$A$5:$A$25,0)),IF(R46="EUR",S46*INDEX('Assumptions & FX Reference'!$C$5:$C$25,MATCH(Q46,'Assumptions & FX Reference'!$A$5:$A$25,0))/INDEX('Assumptions & FX Reference'!$B$5:$B$25,MATCH(Q46,'Assumptions & FX Reference'!$A$5:$A$25,0)),"(Not stated)"))))>0,IF(R46="USD",S46,IF(R46="IRR",S46/INDEX('Assumptions & FX Reference'!$B$5:$B$25,MATCH(Q46,'Assumptions & FX Reference'!$A$5:$A$25,0)),IF(R46="EUR",S46*INDEX('Assumptions & FX Reference'!$C$5:$C$25,MATCH(Q46,'Assumptions & FX Reference'!$A$5:$A$25,0))/INDEX('Assumptions & FX Reference'!$B$5:$B$25,MATCH(Q46,'Assumptions & FX Reference'!$A$5:$A$25,0)),"(Not stated)"))),"(FX rate not entered for this year)"),"(FX rate not entered for this year)"))) -> 88.826611 | V46: =IF(NOT(ISNUMBER(S46)),"(Not stated)",IF(NOT(ISNUMBER(Q46)),"(Cost year not stated / not a Jalali year)",IFERROR(IF(N(IF(R46="IRR",S46,IF(R46="USD",S46*INDEX('Assumptions & FX Reference'!$B$5:$B$25,MATCH(Q46,'Assumptions & FX Reference'!$A$5:$A$25,0)),IF(R46="EUR",S46*INDEX('Assumptions & FX Reference'!$C$5:$C$25,MATCH(Q46,'Assumptions & FX Reference'!$A$5:$A$25,0)),"(Not stated)"))))>0,IF(R46="IRR",S46,IF(R46="USD",S46*INDEX('Assumptions & FX Reference'!$B$5:$B$25,MATCH(Q46,'Assumptions & FX Reference'!$A$5:$A$25,0)),IF(R46="EUR",S46*INDEX('Assumptions & FX Reference'!$C$5:$C$25,MATCH(Q46,'Assumptions & FX Reference'!$A$5:$A$25,0)),"(Not stated)"))),"(FX rate not entered for this year)"),"(FX rate not entered for this year)"))) -> 37307177 | W46: Purchase unit cost without overhead factor (هزینه واحد بدون ضریب) | X46: Class 3 (Basic) | Y46: Basic Engineering | Z46: PEP-Rev.140205_عزيزيان_Gachsaran_4.xlsx (Sheet P.ME, row 100) | AA46: Unit 37,307,176.73 IRR x 42 = line total 1,566,901,422.51 IRR (P.ME col. K). No freight/customs given on this row; installation excluded (C.HSE / C.mECHANICAL). | AB46: Y
A47: 43 | B47: CO2 Wheeled Fire Extinguisher 30 kg | C47: Gachsaran 4 Development Plan (Proj No. 591111) | D47: (No Tag - P.ME item 67.7) | E47: SAF | F47: SAF-EXT | G47: 24 | H47: No. | I47: CO2 Wheeled Fire Extinguisher 30 kg (Safety Equipment list, P.ME item 67.7) | J47: 30 KG | K47: Not Stated | L47: Not Stated | M47: Not Stated | N47: Not Stated | O47: Not Stated | P47: Not Stated | Q47: 1402 | R47: IRR | S47: 2.6647983e+08 | T47: =IF(NOT(ISNUMBER(S47)),"(Not stated)",IF(NOT(ISNUMBER(Q47)),"(Cost year not stated / not a Jalali year)",IFERROR(IF(N(IF(R47="EUR",S47,IF(R47="IRR",S47/INDEX('Assumptions & FX Reference'!$C$5:$C$25,MATCH(Q47,'Assumptions & FX Reference'!$A$5:$A$25,0)),IF(R47="USD",S47*INDEX('Assumptions & FX Reference'!$B$5:$B$25,MATCH(Q47,'Assumptions & FX Reference'!$A$5:$A$25,0))/INDEX('Assumptions & FX Reference'!$C$5:$C$25,MATCH(Q47,'Assumptions & FX Reference'!$A$5:$A$25,0)),"(Not stated)"))))>0,IF(R47="EUR",S47,IF(R47="IRR",S47/INDEX('Assumptions & FX Reference'!$C$5:$C$25,MATCH(Q47,'Assumptions & FX Reference'!$A$5:$A$25,0)),IF(R47="USD",S47*INDEX('Assumptions & FX Reference'!$B$5:$B$25,MATCH(Q47,'Assumptions & FX Reference'!$A$5:$A$25,0))/INDEX('Assumptions & FX Reference'!$C$5:$C$25,MATCH(Q47,'Assumptions & FX Reference'!$A$5:$A$25,0)),"(Not stated)"))),"(FX rate not entered for this year)"),"(FX rate not entered for this year)"))) -> 503.26692 | U47: =IF(NOT(ISNUMBER(S47)),"(Not stated)",IF(NOT(ISNUMBER(Q47)),"(Cost year not stated / not a Jalali year)",IFERROR(IF(N(IF(R47="USD",S47,IF(R47="IRR",S47/INDEX('Assumptions & FX Reference'!$B$5:$B$25,MATCH(Q47,'Assumptions & FX Reference'!$A$5:$A$25,0)),IF(R47="EUR",S47*INDEX('Assumptions & FX Reference'!$C$5:$C$25,MATCH(Q47,'Assumptions & FX Reference'!$A$5:$A$25,0))/INDEX('Assumptions & FX Reference'!$B$5:$B$25,MATCH(Q47,'Assumptions & FX Reference'!$A$5:$A$25,0)),"(Not stated)"))))>0,IF(R47="USD",S47,IF(R47="IRR",S47/INDEX('Assumptions & FX Reference'!$B$5:$B$25,MATCH(Q47,'Assumptions & FX Reference'!$A$5:$A$25,0)),IF(R47="EUR",S47*INDEX('Assumptions & FX Reference'!$C$5:$C$25,MATCH(Q47,'Assumptions & FX Reference'!$A$5:$A$25,0))/INDEX('Assumptions & FX Reference'!$B$5:$B$25,MATCH(Q47,'Assumptions & FX Reference'!$A$5:$A$25,0)),"(Not stated)"))),"(FX rate not entered for this year)"),"(FX rate not entered for this year)"))) -> 634.47579 | V47: =IF(NOT(ISNUMBER(S47)),"(Not stated)",IF(NOT(ISNUMBER(Q47)),"(Cost year not stated / not a Jalali year)",IFERROR(IF(N(IF(R47="IRR",S47,IF(R47="USD",S47*INDEX('Assumptions & FX Reference'!$B$5:$B$25,MATCH(Q47,'Assumptions & FX Reference'!$A$5:$A$25,0)),IF(R47="EUR",S47*INDEX('Assumptions & FX Reference'!$C$5:$C$25,MATCH(Q47,'Assumptions & FX Reference'!$A$5:$A$25,0)),"(Not stated)"))))>0,IF(R47="IRR",S47,IF(R47="USD",S47*INDEX('Assumptions & FX Reference'!$B$5:$B$25,MATCH(Q47,'Assumptions & FX Reference'!$A$5:$A$25,0)),IF(R47="EUR",S47*INDEX('Assumptions & FX Reference'!$C$5:$C$25,MATCH(Q47,'Assumptions & FX Reference'!$A$5:$A$25,0)),"(Not stated)"))),"(FX rate not entered for this year)"),"(FX rate not entered for this year)"))) -> 2.6647983e+08 | W47: Purchase unit cost without overhead factor (هزینه واحد بدون ضریب) | X47: Class 3 (Basic) | Y47: Basic Engineering | Z47: PEP-Rev.140205_عزيزيان_Gachsaran_4.xlsx (Sheet P.ME, row 101) | AA47: Unit 266,479,833.76 IRR x 24 = line total 6,395,516,010.23 IRR (P.ME col. K). No freight/customs given on this row; installation excluded (C.HSE / C.mECHANICAL). | AB47: Y
A48: 44 | B48: First Aid Kit | C48: Gachsaran 4 Development Plan (Proj No. 591111) | D48: (No Tag - P.ME item 67.9) | E48: SAF | F48: SAF-EQP | G48: 4 | H48: No. | I48: First Aid Kit (Safety Equipment list, P.ME item 67.9) | J48: Not Stated | K48: Not Stated | L48: Not Stated | M48: Not Stated | N48: Not Stated | O48: Not Stated | P48: Not Stated | Q48: 1402 | R48: IRR | S48: 1.3856951e+08 | T48: =IF(NOT(ISNUMBER(S48)),"(Not stated)",IF(NOT(ISNUMBER(Q48)),"(Cost year not stated / not a Jalali year)",IFERROR(IF(N(IF(R48="EUR",S48,IF(R48="IRR",S48/INDEX('Assumptions & FX Reference'!$C$5:$C$25,MATCH(Q48,'Assumptions & FX Reference'!$A$5:$A$25,0)),IF(R48="USD",S48*INDEX('Assumptions & FX Reference'!$B$5:$B$25,MATCH(Q48,'Assumptions & FX Reference'!$A$5:$A$25,0))/INDEX('Assumptions & FX Reference'!$C$5:$C$25,MATCH(Q48,'Assumptions & FX Reference'!$A$5:$A$25,0)),"(Not stated)"))))>0,IF(R48="EUR",S48,IF(R48="IRR",S48/INDEX('Assumptions & FX Reference'!$C$5:$C$25,MATCH(Q48,'Assumptions & FX Reference'!$A$5:$A$25,0)),IF(R48="USD",S48*INDEX('Assumptions & FX Reference'!$B$5:$B$25,MATCH(Q48,'Assumptions & FX Reference'!$A$5:$A$25,0))/INDEX('Assumptions & FX Reference'!$C$5:$C$25,MATCH(Q48,'Assumptions & FX Reference'!$A$5:$A$25,0)),"(Not stated)"))),"(FX rate not entered for this year)"),"(FX rate not entered for this year)"))) -> 261.6988 | U48: =IF(NOT(ISNUMBER(S48)),"(Not stated)",IF(NOT(ISNUMBER(Q48)),"(Cost year not stated / not a Jalali year)",IFERROR(IF(N(IF(R48="USD",S48,IF(R48="IRR",S48/INDEX('Assumptions & FX Reference'!$B$5:$B$25,MATCH(Q48,'Assumptions & FX Reference'!$A$5:$A$25,0)),IF(R48="EUR",S48*INDEX('Assumptions & FX Reference'!$C$5:$C$25,MATCH(Q48,'Assumptions & FX Reference'!$A$5:$A$25,0))/INDEX('Assumptions & FX Reference'!$B$5:$B$25,MATCH(Q48,'Assumptions & FX Reference'!$A$5:$A$25,0)),"(Not stated)"))))>0,IF(R48="USD",S48,IF(R48="IRR",S48/INDEX('Assumptions & FX Reference'!$B$5:$B$25,MATCH(Q48,'Assumptions & FX Reference'!$A$5:$A$25,0)),IF(R48="EUR",S48*INDEX('Assumptions & FX Reference'!$C$5:$C$25,MATCH(Q48,'Assumptions & FX Reference'!$A$5:$A$25,0))/INDEX('Assumptions & FX Reference'!$B$5:$B$25,MATCH(Q48,'Assumptions & FX Reference'!$A$5:$A$25,0)),"(Not stated)"))),"(FX rate not entered for this year)"),"(FX rate not entered for this year)"))) -> 329.92741 | V48: =IF(NOT(ISNUMBER(S48)),"(Not stated)",IF(NOT(ISNUMBER(Q48)),"(Cost year not stated / not a Jalali year)",IFERROR(IF(N(IF(R48="IRR",S48,IF(R48="USD",S48*INDEX('Assumptions & FX Reference'!$B$5:$B$25,MATCH(Q48,'Assumptions & FX Reference'!$A$5:$A$25,0)),IF(R48="EUR",S48*INDEX('Assumptions & FX Reference'!$C$5:$C$25,MATCH(Q48,'Assumptions & FX Reference'!$A$5:$A$25,0)),"(Not stated)"))))>0,IF(R48="IRR",S48,IF(R48="USD",S48*INDEX('Assumptions & FX Reference'!$B$5:$B$25,MATCH(Q48,'Assumptions & FX Reference'!$A$5:$A$25,0)),IF(R48="EUR",S48*INDEX('Assumptions & FX Reference'!$C$5:$C$25,MATCH(Q48,'Assumptions & FX Reference'!$A$5:$A$25,0)),"(Not stated)"))),"(FX rate not entered for this year)"),"(FX rate not entered for this year)"))) -> 1.3856951e+08 | W48: Purchase unit cost without overhead factor (هزینه واحد بدون ضریب) | X48: Class 3 (Basic) | Y48: Basic Engineering | Z48: PEP-Rev.140205_عزيزيان_Gachsaran_4.xlsx (Sheet P.ME, row 103) | AA48: Unit 138,569,513.55 IRR x 4 = line total 554,278,054.22 IRR (P.ME col. K). No freight/customs given on this row; installation excluded (C.HSE / C.mECHANICAL). | AB48: Y
A49: 45 | B49: OS&Y Gate Valve - Isolating Valve 12" | C49: Gachsaran 4 Development Plan (Proj No. 591111) | D49: (No Tag - P.ME item 67.11) | E49: SAF | F49: SAF-HYD | G49: 2 | H49: No. | I49: OS&Y Gate Valve - Isolating Valve 12" (Safety Equipment list, P.ME item 67.11) | J49: Not Stated | K49: Not Stated | L49: Not Stated | M49: Not Stated | N49: Not Stated | O49: Not Stated | P49: Not Stated | Q49: 1402 | R49: IRR | S49: 1680000000 | T49: =IF(NOT(ISNUMBER(S49)),"(Not stated)",IF(NOT(ISNUMBER(Q49)),"(Cost year not stated / not a Jalali year)",IFERROR(IF(N(IF(R49="EUR",S49,IF(R49="IRR",S49/INDEX('Assumptions & FX Reference'!$C$5:$C$25,MATCH(Q49,'Assumptions & FX Reference'!$A$5:$A$25,0)),IF(R49="USD",S49*INDEX('Assumptions & FX Reference'!$B$5:$B$25,MATCH(Q49,'Assumptions & FX Reference'!$A$5:$A$25,0))/INDEX('Assumptions & FX Reference'!$C$5:$C$25,MATCH(Q49,'Assumptions & FX Reference'!$A$5:$A$25,0)),"(Not stated)"))))>0,IF(R49="EUR",S49,IF(R49="IRR",S49/INDEX('Assumptions & FX Reference'!$C$5:$C$25,MATCH(Q49,'Assumptions & FX Reference'!$A$5:$A$25,0)),IF(R49="USD",S49*INDEX('Assumptions & FX Reference'!$B$5:$B$25,MATCH(Q49,'Assumptions & FX Reference'!$A$5:$A$25,0))/INDEX('Assumptions & FX Reference'!$C$5:$C$25,MATCH(Q49,'Assumptions & FX Reference'!$A$5:$A$25,0)),"(Not stated)"))),"(FX rate not entered for this year)"),"(FX rate not entered for this year)"))) -> 3172.8045 | U49: =IF(NOT(ISNUMBER(S49)),"(Not stated)",IF(NOT(ISNUMBER(Q49)),"(Cost year not stated / not a Jalali year)",IFERROR(IF(N(IF(R49="USD",S49,IF(R49="IRR",S49/INDEX('Assumptions & FX Reference'!$B$5:$B$25,MATCH(Q49,'Assumptions & FX Reference'!$A$5:$A$25,0)),IF(R49="EUR",S49*INDEX('Assumptions & FX Reference'!$C$5:$C$25,MATCH(Q49,'Assumptions & FX Reference'!$A$5:$A$25,0))/INDEX('Assumptions & FX Reference'!$B$5:$B$25,MATCH(Q49,'Assumptions & FX Reference'!$A$5:$A$25,0)),"(Not stated)"))))>0,IF(R49="USD",S49,IF(R49="IRR",S49/INDEX('Assumptions & FX Reference'!$B$5:$B$25,MATCH(Q49,'Assumptions & FX Reference'!$A$5:$A$25,0)),IF(R49="EUR",S49*INDEX('Assumptions & FX Reference'!$C$5:$C$25,MATCH(Q49,'Assumptions & FX Reference'!$A$5:$A$25,0))/INDEX('Assumptions & FX Reference'!$B$5:$B$25,MATCH(Q49,'Assumptions & FX Reference'!$A$5:$A$25,0)),"(Not stated)"))),"(FX rate not entered for this year)"),"(FX rate not entered for this year)"))) -> 4000 | V49: =IF(NOT(ISNUMBER(S49)),"(Not stated)",IF(NOT(ISNUMBER(Q49)),"(Cost year not stated / not a Jalali year)",IFERROR(IF(N(IF(R49="IRR",S49,IF(R49="USD",S49*INDEX('Assumptions & FX Reference'!$B$5:$B$25,MATCH(Q49,'Assumptions & FX Reference'!$A$5:$A$25,0)),IF(R49="EUR",S49*INDEX('Assumptions & FX Reference'!$C$5:$C$25,MATCH(Q49,'Assumptions & FX Reference'!$A$5:$A$25,0)),"(Not stated)"))))>0,IF(R49="IRR",S49,IF(R49="USD",S49*INDEX('Assumptions & FX Reference'!$B$5:$B$25,MATCH(Q49,'Assumptions & FX Reference'!$A$5:$A$25,0)),IF(R49="EUR",S49*INDEX('Assumptions & FX Reference'!$C$5:$C$25,MATCH(Q49,'Assumptions & FX Reference'!$A$5:$A$25,0)),"(Not stated)"))),"(FX rate not entered for this year)"),"(FX rate not entered for this year)"))) -> 1680000000 | W49: Purchase unit cost without overhead factor (هزینه واحد بدون ضریب) | X49: Class 3 (Basic) | Y49: Basic Engineering | Z49: PEP-Rev.140205_عزيزيان_Gachsaran_4.xlsx (Sheet P.ME, row 104) | AA49: Unit 1,680,000,000 IRR x 2 = line total 3,360,000,000 IRR (P.ME col. K). No freight/customs given on this row; installation excluded (C.HSE / C.mECHANICAL). | AB49: Y
A50: 46 | B50: OS&Y Gate Valve - Isolating Valve 6" | C50: Gachsaran 4 Development Plan (Proj No. 591111) | D50: (No Tag - P.ME item 67.12) | E50: SAF | F50: SAF-HYD | G50: 19 | H50: No. | I50: OS&Y Gate Valve - Isolating Valve 6" (Safety Equipment list, P.ME item 67.12) | J50: Not Stated | K50: Not Stated | L50: Not Stated | M50: Not Stated | N50: Not Stated | O50: Not Stated | P50: Not Stated | Q50: 1402 | R50: IRR | S50: 840000000 | T50: =IF(NOT(ISNUMBER(S50)),"(Not stated)",IF(NOT(ISNUMBER(Q50)),"(Cost year not stated / not a Jalali year)",IFERROR(IF(N(IF(R50="EUR",S50,IF(R50="IRR",S50/INDEX('Assumptions & FX Reference'!$C$5:$C$25,MATCH(Q50,'Assumptions & FX Reference'!$A$5:$A$25,0)),IF(R50="USD",S50*INDEX('Assumptions & FX Reference'!$B$5:$B$25,MATCH(Q50,'Assumptions & FX Reference'!$A$5:$A$25,0))/INDEX('Assumptions & FX Reference'!$C$5:$C$25,MATCH(Q50,'Assumptions & FX Reference'!$A$5:$A$25,0)),"(Not stated)"))))>0,IF(R50="EUR",S50,IF(R50="IRR",S50/INDEX('Assumptions & FX Reference'!$C$5:$C$25,MATCH(Q50,'Assumptions & FX Reference'!$A$5:$A$25,0)),IF(R50="USD",S50*INDEX('Assumptions & FX Reference'!$B$5:$B$25,MATCH(Q50,'Assumptions & FX Reference'!$A$5:$A$25,0))/INDEX('Assumptions & FX Reference'!$C$5:$C$25,MATCH(Q50,'Assumptions & FX Reference'!$A$5:$A$25,0)),"(Not stated)"))),"(FX rate not entered for this year)"),"(FX rate not entered for this year)"))) -> 1586.4023 | U50: =IF(NOT(ISNUMBER(S50)),"(Not stated)",IF(NOT(ISNUMBER(Q50)),"(Cost year not stated / not a Jalali year)",IFERROR(IF(N(IF(R50="USD",S50,IF(R50="IRR",S50/INDEX('Assumptions & FX Reference'!$B$5:$B$25,MATCH(Q50,'Assumptions & FX Reference'!$A$5:$A$25,0)),IF(R50="EUR",S50*INDEX('Assumptions & FX Reference'!$C$5:$C$25,MATCH(Q50,'Assumptions & FX Reference'!$A$5:$A$25,0))/INDEX('Assumptions & FX Reference'!$B$5:$B$25,MATCH(Q50,'Assumptions & FX Reference'!$A$5:$A$25,0)),"(Not stated)"))))>0,IF(R50="USD",S50,IF(R50="IRR",S50/INDEX('Assumptions & FX Reference'!$B$5:$B$25,MATCH(Q50,'Assumptions & FX Reference'!$A$5:$A$25,0)),IF(R50="EUR",S50*INDEX('Assumptions & FX Reference'!$C$5:$C$25,MATCH(Q50,'Assumptions & FX Reference'!$A$5:$A$25,0))/INDEX('Assumptions & FX Reference'!$B$5:$B$25,MATCH(Q50,'Assumptions & FX Reference'!$A$5:$A$25,0)),"(Not stated)"))),"(FX rate not entered for this year)"),"(FX rate not entered for this year)"))) -> 2000 | V50: =IF(NOT(ISNUMBER(S50)),"(Not stated)",IF(NOT(ISNUMBER(Q50)),"(Cost year not stated / not a Jalali year)",IFERROR(IF(N(IF(R50="IRR",S50,IF(R50="USD",S50*INDEX('Assumptions & FX Reference'!$B$5:$B$25,MATCH(Q50,'Assumptions & FX Reference'!$A$5:$A$25,0)),IF(R50="EUR",S50*INDEX('Assumptions & FX Reference'!$C$5:$C$25,MATCH(Q50,'Assumptions & FX Reference'!$A$5:$A$25,0)),"(Not stated)"))))>0,IF(R50="IRR",S50,IF(R50="USD",S50*INDEX('Assumptions & FX Reference'!$B$5:$B$25,MATCH(Q50,'Assumptions & FX Reference'!$A$5:$A$25,0)),IF(R50="EUR",S50*INDEX('Assumptions & FX Reference'!$C$5:$C$25,MATCH(Q50,'Assumptions & FX Reference'!$A$5:$A$25,0)),"(Not stated)"))),"(FX rate not entered for this year)"),"(FX rate not entered for this year)"))) -> 840000000 | W50: Purchase unit cost without overhead factor (هزینه واحد بدون ضریب) | X50: Class 3 (Basic) | Y50: Basic Engineering | Z50: PEP-Rev.140205_عزيزيان_Gachsaran_4.xlsx (Sheet P.ME, row 105) | AA50: Unit 840,000,000 IRR x 19 = line total 15,960,000,000 IRR (P.ME col. K). No freight/customs given on this row; installation excluded (C.HSE / C.mECHANICAL). | AB50: Y
... A73: 69 | B73: Fire Water Pumps Shelter Crane CN-271 | C73: Koopal Asmari/Bangestan Desalting Unit (Proj No. 53-51-91215) | D73: CN-271 | E73: CRN | F73: CRN-FWP | G73: 1 | H73: Set | I73: Fire water pumps shelter crane (overhead crane) | J73: Not Stated | K73: Not Stated | L73: Not Stated | M73: Not Stated | N73: Not Stated | O73: Not Stated | P73: Not Stated | Q73: 1394 | R73: IRR | S73: 950000000 | T73: =IF(NOT(ISNUMBER(S73)),"(Not stated)",IF(NOT(ISNUMBER(Q73)),"(Cost year not stated / not a Jalali year)",IFERROR(IF(N(IF(R73="EUR",S73,IF(R73="IRR",S73/INDEX('Assumptions & FX Reference'!$C$5:$C$25,MATCH(Q73,'Assumptions & FX Reference'!$A$5:$A$25,0)),IF(R73="USD",S73*INDEX('Assumptions & FX Reference'!$B$5:$B$25,MATCH(Q73,'Assumptions & FX Reference'!$A$5:$A$25,0))/INDEX('Assumptions & FX Reference'!$C$5:$C$25,MATCH(Q73,'Assumptions & FX Reference'!$A$5:$A$25,0)),"(Not stated)"))))>0,IF(R73="EUR",S73,IF(R73="IRR",S73/INDEX('Assumptions & FX Reference'!$C$5:$C$25,MATCH(Q73,'Assumptions & FX Reference'!$A$5:$A$25,0)),IF(R73="USD",S73*INDEX('Assumptions & FX Reference'!$B$5:$B$25,MATCH(Q73,'Assumptions & FX Reference'!$A$5:$A$25,0))/INDEX('Assumptions & FX Reference'!$C$5:$C$25,MATCH(Q73,'Assumptions & FX Reference'!$A$5:$A$25,0)),"(Not stated)"))),"(FX rate not entered for this year)"),"(FX rate not entered for this year)"))) -> 25850.34 | U73: =IF(NOT(ISNUMBER(S73)),"(Not stated)",IF(NOT(ISNUMBER(Q73)),"(Cost year not stated / not a Jalali year)",IFERROR(IF(N(IF(R73="USD",S73,IF(R73="IRR",S73/INDEX('Assumptions & FX Reference'!$B$5:$B$25,MATCH(Q73,'Assumptions & FX Reference'!$A$5:$A$25,0)),IF(R73="EUR",S73*INDEX('Assumptions & FX Reference'!$C$5:$C$25,MATCH(Q73,'Assumptions & FX Reference'!$A$5:$A$25,0))/INDEX('Assumptions & FX Reference'!$B$5:$B$25,MATCH(Q73,'Assumptions & FX Reference'!$A$5:$A$25,0)),"(Not stated)"))))>0,IF(R73="USD",S73,IF(R73="IRR",S73/INDEX('Assumptions & FX Reference'!$B$5:$B$25,MATCH(Q73,'Assumptions & FX Reference'!$A$5:$A$25,0)),IF(R73="EUR",S73*INDEX('Assumptions & FX Reference'!$C$5:$C$25,MATCH(Q73,'Assumptions & FX Reference'!$A$5:$A$25,0))/INDEX('Assumptions & FX Reference'!$B$5:$B$25,MATCH(Q73,'Assumptions & FX Reference'!$A$5:$A$25,0)),"(Not stated)"))),"(FX rate not entered for this year)"),"(FX rate not entered for this year)"))) -> 28315.946 | V73: =IF(NOT(ISNUMBER(S73)),"(Not stated)",IF(NOT(ISNUMBER(Q73)),"(Cost year not stated / not a Jalali year)",IFERROR(IF(N(IF(R73="IRR",S73,IF(R73="USD",S73*INDEX('Assumptions & FX Reference'!$B$5:$B$25,MATCH(Q73,'Assumptions & FX Reference'!$A$5:$A$25,0)),IF(R73="EUR",S73*INDEX('Assumptions & FX Reference'!$C$5:$C$25,MATCH(Q73,'Assumptions & FX Reference'!$A$5:$A$25,0)),"(Not stated)"))))>0,IF(R73="IRR",S73,IF(R73="USD",S73*INDEX('Assumptions & FX Reference'!$B$5:$B$25,MATCH(Q73,'Assumptions & FX Reference'!$A$5:$A$25,0)),IF(R73="EUR",S73*INDEX('Assumptions & FX Reference'!$C$5:$C$25,MATCH(Q73,'Assumptions & FX Reference'!$A$5:$A$25,0)),"(Not stated)"))),"(FX rate not entered for this year)"),"(FX rate not entered for this year)"))) -> 950000000 | W73: Unit price (Rials) | X73: Class 2 (FEED) | Y73: FEED Package | Z73: 91215-KPL-ME-RE-476_R03_MTO_and_Cost_Estimation_Report.xlsx (Sheet CRANES (2), row 35) | AA73: 1 Set x 950,000,000 IRR = 950,000,000 IRR; Euro = 0. Capacity not stated; installation excluded (INS-CRANE). | AB73: Y

Sheet Assumptions & FX Reference
A1: JALALI FX RATES TABLE (1385 – 1405, full 21-year range)
A2: Reused from the Flare / Desalting Price Bank FX table (same verified source documents); only rates for 1392, 1393, 1402, 1404 and 1405 are documented in the project source files — all other years are blank until a source is found.
A4: Jalali Year | B4: USD → IRR | C4: EUR → IRR | D4: EUR / USD Ratio | E4: Basis / Document Reference Source
A5: 1385 | B5: 9148 | C5: 11285 | D5: =C5/B5 -> 1.233603 | E5: (not found in the source files – add if needed)
A6: 1386 | B6: 9202 | C6: 11781 | D6: =C6/B6 -> 1.2802652 | E6: (not found in the source files – add if needed)
A7: 1387 | B7: 9300 | C7: 14260 | D7: =C7/B7 -> 1.5333333 | E7: (not found in the source files – add if needed)
A8: 1388 | B8: 9900 | C8: 13400 | D8: =C8/B7 -> 1.4408602 | E8: (not found in the source files – add if needed)
A9: 1389 | B9: 10200 | C9: 13800 | D9: =C9/B9 -> 1.3529412 | E9: (not found in the source files – add if needed)
A10: 1390 | B10: 11300 | C10: 15750 | D10: =C10/B10 -> 1.3938053 | E10: (not found in the source files – add if needed)
A11: 1391 | B11: 19000 | C11: 25500 | D11: =C11/B11 -> 1.3421053 | E11: (not found in the source files – add if needed)
A12: 1392 | B12: 36300 | C12: 42000 | D12: =C12/B12 -> 1.1570248 | E12: EUR: free-market euro rate 42,000 (label 'نرخ آزاد یورو', Maroon3 sheets p.lab.1392 / SEFTY.p.1392).
A13: 1393 | B13: 31000 | C13: 40530.8 | D13: =C13/B13 -> 1.3074452 | E13: EUR: 40,530.8 – Maroon3 sheet Inflation, label 'نرخ تسعیر ارز سال 93' (currency not written in the label; presumed EUR – verify).
A14: 1394 | B14: 33550 | C14: 36750 | D14: =C14/B14 -> 1.09538 | E14: (not found in the source files – add if needed)
A15: 1395 | B15: 34600 | C15: 38800 | D15: =C15/B15 -> 1.1213873 | E15: (not found in the source files – add if needed)
A16: 1396 | B16: 37300 | C16: 40250 | D16: =C16/B16 -> 1.0790885 | E16: (not found in the source files – add if needed)
A17: 1397 | B17: 47700 | C17: 59000 | D17: =C17/B17 -> 1.2368973 | E17: (not found in the source files – add if needed)
A18: 1398 | B18: 135000 | C18: 152800 | D18: =C18/B18 -> 1.1318519 | E18: (not found in the source files – add if needed)
A19: 1399 | B19: 161000 | C19: 172200 | D19: =C19/B19 -> 1.0695652 | E19: (not found in the source files – add if needed)
A20: 1400 | B20: 252000 | C20: 298400 | D20: =C20/B20 -> 1.184127 | E20: (not found in the source files – add if needed)
... A24: 1404 | B24: 658533 | C24: 695268 | D24: =C24/B24 -> 1.0557831 | E24: USD: 658,533 = cached external-link value used by Pazanan2 formulas (assumed IRR per USD; verify). EUR = USD x 1.0558 (cached ratio) – derived.
A25: 1405 | B25: =C25/D25 -> 1818181.8 | C25: 2000000 | D25: 1.1 | E25: EUR: 2,000,000 – Maroon3 sheet Inflation, label 'یورو به ریال' (1405 estimate). USD = EUR / 1.1 (same sheet) – derived.
A28: NOTES
A29: • Unit Price (EUR/USD/IRR) formulas in Master Database look up the Cost Year in this table: USD → IRR (column B) and EUR → IRR (column C); a year without a rate shows a message instead of a number.
A30: • Only 1392, 1393, 1402, 1404 and 1405 have a rate found in the project source files; yellow/blue cells are inputs, grey cells are not found in the sources – add if needed.
A31: • Where only one of the two rates is documented, the other is derived by formula from the EUR / USD ratio (1404: EUR = USD x ratio; 1405: USD = EUR / ratio) – see column E.
A32: • Unit Price (Reference) sits immediately next to Reference Currency in every sheet. Cost Years used in this Misc database: 1392 (Maroon 3 HVAC rollup and safety shower; EUR rate only), 1394 (KPL stripping / RO; no documented rate), 1402 (Gachsaran 4; USD rate only), 1405 (Maroon 3 HVAC rollup; both rates). Price-sample rows have no Cost Year, so their converted columns show a message.
A33: • Category (PKG / SEP / ACX / HVAC / SAF) and Sub-Category (PKG-STR, PKG-RO, PKG-PIG, SEP-OWS, SEP-SKM, ACX-AIR, HVAC-SYS, SAF-SHW) codes carry cell comments with the full names in Master Database and Executive Dashboard. v2 adds: PKG-EFF, PKG-WTR, PMP-WWP, TNK-SKM, VSL-SEP, SAF-PKG (comments on each code).
A34: • Gachsaran 4 (1402) prices are stored in IRR because the source cells are IRR (several are formulas of USD x 420,000). The 1402 row has only the USD rate, so EUR conversion of those records shows 'FX rate not entered for this year'.

Sheet Change Log
A1: CHANGE LOG, VERIFICATION & OPEN QUESTIONS
A2: New database built from the project reference files and MASTER_TAGS / SOURCES (587 tag records, 5 projects), using the Flare Price Bank (Flare_Price_Bank_Final_v2) as the structural template. Every priced value was re-read from the source workbook while building the file.
A4: A. Records created (no existing content was changed)
A5: Type | B5: Record | C5: Field | D5: Old value | E5: New value | F5: Evidence in reference files
A6: Added | B6: PK-143 | C6: New record | D6: — | E6: KPL Stripping Package | F6: Sheet STRIPPER-B; tower tag T-143 A/B in cell F23; MASTER_TAGS category Package / Skid and Tower.
A7: Added | B7: T-143 A/B | C7: New record | D7: — | E7: KPL Stripper Towers (Include = N) | F7: Same sheet; price is inside PK-143.
A8: Added | B8: PK-152 | C8: New record | D8: — | E8: KPL Reverse Osmosis Package | F8: Sheet R.O.; installation sheet INS-PACK-C.
A9: Added | B9: Pig Launcher & Receiver | C9: New record | D9: — | E9: Gachsaran 4 | F9: P.ME row 113 (item 68); summary table row 141.
A10: Added | B10: Pig Launcher (sample) | C10: New record | D10: — | E10: Price sample | F10: Sheet packages row 10; CSV row 65.
A11: Added | B11: SU-701 | C11: New record | D11: — | E11: Gachsaran 4 Oily Water Separator | F11: E.Process row 110 (process data sheet only).
A12: Added | B12: X-704 | C12: New record | D12: — | E12: Gachsaran 4 Portable Skimmer | F12: E.Process row 127 (process data sheet only).
A13: Added | B13: Crude Aerial Cooler | C13: New record | D13: — | E13: Price sample | F13: Sheet AIR COOLERS row 3; CSV row 43.
A14: Added | B14: HVAC items 66.1 to 66.8 | C14: New record | D14: — | E14: Gachsaran 4 (8 records) | F14: P.ME rows 84 to 91.
A15: Added | B15: HVAC rollups 1392 / 1405 | C15: New record | D15: — | E15: Maroon 3 (2 records) | F15: ME.p.1392 row 18; ME.P.1405 row 20.
A16: Added | B16: HVAC Works | C16: New record | D16: — | E16: Price sample (Include = N) | F16: CSV construction section, row 128.
... A18: Added | B18: Lab Safety Shower & Eyewash | C18: New record | D18: — | E18: Maroon 3 and Gachsaran 4 (Include = N) | F18: p.lab.1392 row 28; P.LAB row 24.
A20: B. Verification of records vs. project reference files
A21: Tag | B21: Record | C21: What was checked | D21: Result
A22: PK-143 | B22: KPL stripping | C22: Qty 1 Set; 9,000,000,000 IRR; EUR = 0; towers 2000 x 2500 / 800 x 5000 mm, 9000 mm total; 5 (F.V.) barg; -2 / 95 C; SA 516 Gr. 70; ASME VIII Div.1 & IPS-G-ME-150 | D22: Matches STRIPPER-B.
A23: PK-152 | B23: KPL reverse osmosis | C23: Qty 1 Set; 800,000,000 IRR; EUR = 0; 1 m3/hr; back filters, RO unit, CIP, chemical injection, UV lamp | D23: Matches R.O.
A24: Pig | B24: Gachsaran 4 | C24: 1 SET; 94,500,000,000 IRR (= 225,000 USD x 420,000); freight 241,488,427.26 IRR | D24: Matches P.ME row 113.
A25: Pig / Air Cooler | B25: Price sample | C25: 15,000 USD; 2,200,000 USD; air cooler duty, pressure, temperature, area, bays, fans, power | D25: Match xlsx and CSV (CSV rounds area and power).
A26: HVAC 66.1 to 66.8 | B26: Gachsaran 4 | C26: Eight IRR amounts; three are USD x 420,000 formulas (276,000, 336,000, 220,000 USD) | D26: Match P.ME rows 84 to 91. Their sum is 364,740,000,000 IRR.
A27: HVAC rollups | B27: Maroon 3 | C27: 1392 new-contract 8,425,000,000 IRR (old 2,625,392,658); 1405 419,475,728,208.74 IRR | D27: Match ME.p.1392 row 18 and ME.P.1405 row 20.
A28: Safety shower | B28: Gachsaran 4 / Maroon 3 | C28: 7 No. x 1,260,000,000 IRR (= 3,000 USD x 420,000); 5 x 31,500,000 IRR (helper 750 x 42,000 euro rate) | D28: Match P.ME row 102 and SEFTY.p.1392 row 17.
A29: SU-701 / X-704 | B29: Gachsaran 4 | C29: Searched every sheet of all six reference files for a price | D29: None found; price cells left Not Stated.
A31: C. Items searched but not added / out of scope
A32: Item | B32: Project | C32: Source | D32: Status | E32: Note
A33: P-148 A/B/C stripped waste water pumps | B33: KPL | C33: STRIPPER-B | D33: Added v2 (Include = N) | E33: Pumps out of scope; priced inside PK-143.
A34: OS-201 Oil Skimmer Tank | B34: Gachsaran 4 | C34: P.ME row 26 | D34: Updated v3 (stage 1: OS-201 verified) | E34: OS-201: 45,900 kg x 660,000 IRR/kg = 30,294,000,000 IRR (line total, verified). KPL skimmer tanks TK-132 / TK-142: 3,000,000,000 IRR each, Include = Y.
A35: OWS pumps P-703 / P-704 / P-750 | B35: Gachsaran 4 / KPL | C35: P.ME rows 53, 54, 55 | D35: Updated v3 (stage 1: priced, Include = Y) | E35: Gachsaran 4 P.ME rows 53-55 priced and split into three records (P-703 A/B, P-704 A/B, P-750).
A36: First Stage Separator | B36: Price sample | C36: VESSELS row 3 | D36: Updated v3 (stage 2: priced, Include = Y) | E36: 6,500,000 USD from VESSELS row 3 (horizontal, ID 3000 x T/T 14000 mm, 27 barg, C.S). Cost year and quantity not stated.
A37: HVAC 66.9 / 66.10 (waste water and water treatment packages) | B37: Gachsaran 4 | C37: P.ME rows 92, 93 | D37: Added v2 (Include = Y) | E37: Sit under the HVAC group in P.ME but are process packages (3,600,000,000 and 2,500,000,000 IRR).
A38: Group rollups: HVAC, safety, pig | B38: Gachsaran 4 | C38: P.ME summary rows 138, 140, 141 | D38: Updated v3 (stage 3: amounts filled, Include = N) | E38: HVAC rollup 370,840,000,000 IRR (N); safety rollup 163,763,000,000 IRR (N); pig rollup 94,500,000,000 IRR (N).
A39: Safety & Fire Fighting package | B39: Price sample | C39: CSV row 74 | D39: Added v2 (Include = Y) | E39: 1,800,000 USD lump sum for the whole fire and safety scope, not a shower line.
A40: Pazanan 2 | B40: Pazanan 2 | C40: All sheets | D40: No records | E40: No air cooler, pig launcher, HVAC, separator or safety shower line found.
A42: D. Observations
A43: Topic | B43: Note
A44: Tags missing from MASTER_TAGS | B44: SU-701 and X-704 exist only as titles in E.Process (rows 110 and 127) of the Gachsaran 4 workbook and are not in MASTER_TAGS / SOURCES. Air Cooler, Pig, HVAC and Safety Shower categories are also absent from MASTER_TAGS.
A45: HVAC rollup reconciliation | B45: Gachsaran 4 HVAC summary of 370,840,000,000 IRR equals items 66.1 to 66.8 (364,740,000,000) plus the waste water (3,600,000,000) and water treatment (2,500,000,000) packages.
A46: Pig launcher scale | B46: Gachsaran 4 pig launcher and receiver (225,000 USD per set) vs. the sample launcher (15,000 USD, 16 / 12 in). Not reconciled: no size data for the Gachsaran 4 system.
A47: Currency reference | B47: Gachsaran 4 rows are IRR at 420,000 IRR/USD, matching the FX table (1402). 1394 (KPL) has no documented FX rate.
A48: Structure | B48: Same 28 columns, formulas, conditional formatting and dashboard as the Flare Price Bank. The Flare Pipelines sheet has no equivalent here because no Misc item needed a separate sheet. Only the flare file was supplied as structural reference; the compressor file mentioned was not available in this session.
A51: E. Update v2 - records added from section C (Change Log + chat request only; project reference files NOT opened)
A52: Type | B52: Record | C52: Field | D52: Old value | E52: New value | F52: Evidence / status
A53: Added | B53: Stripped Waste Water Pumps P-148 A/B/C (inside PK-143) | C53: New record (Master row 28) | D53: — | E53: Include = N | F53: Price: not stated / to fill. 91215-KPL-ME-RE-476_R03_MTO_and_Cost_Estimation_Report.xlsx (Sheet STRIPPER-B)
A54: Added | B54: Oily Water Separator Pumps P-703 / P-704 / P-750 | C54: New record (Master row 29) | D54: — | E54: Include = N | F54: Price: not stated / to fill. PEP-Rev.140205_عزيزيان_Gachsaran_4.xlsx (Sheet P.ME, rows 53, 54, 55)
A55: Added | B55: Oil Skimmer Tank OS-201 | C55: New record (Master row 30) | D55: — | E55: Include = Y | F55: Price: 30,294,000,000 IRR. PEP-Rev.140205_عزيزيان_Gachsaran_4.xlsx (Sheet P.ME, row 26)
A56: Added | B56: Skimmer Tanks (KPL TANKS-A / TANKS-B) | C56: New record (Master row 31) | D56: — | E56: Include = N | F56: Price: not stated / to fill. 91215-KPL-ME-RE-476_R03_MTO_and_Cost_Estimation_Report.xlsx (Sheets TANKS-A row 43, TANKS-B row 27)
A57: Added | B57: First Stage Separator | C57: New record (Master row 32) | D57: — | E57: Include = N | F57: Price: not stated / to fill. نمونه_قیمتی_نمک_زدایی_overall.xlsx (Sheet VESSELS, row 3)
A58: Added | B58: Waste Water Treatment Package | C58: New record (Master row 33) | D58: — | E58: Include = Y | F58: Price: 3,600,000,000 IRR. PEP-Rev.140205_عزيزيان_Gachsaran_4.xlsx (Sheet P.ME, row 92)
A59: Added | B59: Water Treatment Package | C59: New record (Master row 34) | D59: — | E59: Include = Y | F59: Price: 2,500,000,000 IRR. PEP-Rev.140205_عزيزيان_Gachsaran_4.xlsx (Sheet P.ME, row 93)
A60: Added | B60: HVAC Group Rollup (Gachsaran 4 Summary) | C60: New record (Master row 35) | D60: — | E60: Include = N | F60: Price: 370,840,000,000 IRR. PEP-Rev.140205_عزيزيان_Gachsaran_4.xlsx (Sheet P.ME, summary row 138)
A61: Added | B61: Safety Group Rollup (Gachsaran 4 Summary) | C61: New record (Master row 36) | D61: — | E61: Include = N | F61: Price: not stated / to fill. PEP-Rev.140205_عزيزيان_Gachsaran_4.xlsx (Sheet P.ME, summary row 140)
A62: Added | B62: Pig Group Rollup (Gachsaran 4 Summary) | C62: New record (Master row 37) | D62: — | E62: Include = N | F62: Price: not stated / to fill. PEP-Rev.140205_عزيزيان_Gachsaran_4.xlsx (Sheet P.ME, summary row 141)
A63: Added | B63: Safety & Fire Fighting Package | C63: New record (Master row 38) | D63: — | E63: Include = Y | F63: Price: 1,800,000 USD. 18061405_Pump_only_CSV.csv (file row 74)
A65: Still needed from project files (access required)
A66: Open item 1 | B66: No price gaps left from the original open list. Remaining: cost years of price-sample rows (left Not Stated by user); packages 66.9/66.10 basis check.
A67: Open item 2 | B67: Packages 66.9 and 66.10: price basis/quantity still to verify in P.ME rows 92, 93. (OS-201 verified in v3.)
A68: Open item 3 | B68: Other safety items (P.ME 67.1-67.19 hydrant, extinguishers, first aid etc.; SEFTY.p.1392), installation sheets (INS-PACK-B/C, C.mECHANICAL) and Pazanan 2: not in the Change Log, not added.
A70: F. Update v3 - Stage 1 (OWS pumps and KPL skimmer tanks; project reference files opened; installation costs excluded by instruction)
A71: Type | B71: Record | C71: Field | D71: Old value | E71: New value | F71: Evidence / status
A72: Updated | B72: OS-201 (Master row 26) | C72: Quantity / Unit / Basis | D72: Not Stated; VERIFY | E72: 1 No.; per-kg basis resolved | F72: P.ME row 26: G = 45,900 Kg, H = 660,000, K = 30,294,000,000 = G x H, so K is the line total. Weight and capacity filled.
A73: Updated | B73: P-703 A/B (Master row 25) | C73: Prices | D73: Not Stated, Include = N | E73: 2 x 13,215,061,000 IRR, Include = Y | F73: P.ME row 53. Unit price equals the water/water heat exchanger E-002 price: possible source copy error (flagged).
A74: Added | B74: P-704 A/B (Master row 35) | C74: New record | D74: — | E74: 2 x 15,949,212,000 IRR, Include = Y | F74: P.ME row 54.
A75: Added | B75: P-750 (Master row 36) | C75: New record | D75: — | E75: 1 x 6,083,485,000 IRR, Include = Y | F75: P.ME row 55.
A76: Updated | B76: KPL Skimmer Tanks TK-132 / TK-142 (Master row 27) | C76: Prices | D76: Not Stated, Include = N | E76: 2 x 3,000,000,000 IRR, Include = Y | F76: TANKS-A (1) row 43 and TANKS-B (2) row 27; cost year 1394; design + raw material only.
A77: Updated | B77: First Stage Separator (Master row 28) | C77: Price / Include | D77: Not Stated, Include = N | E77: 6,500,000 USD, Include = Y | F77: Sheet VESSELS row 3 of the price sample (stage 2). Dimensions, pressure and material filled; no cost year, so no conversion to EUR/IRR.
A78: Stage 3 (rollups)
A79: Updated | B79: Safety Group Rollup (Master row 32) | C79: Price | D79: Not Stated | E79: 163,763,000,000 IRR (Include = N) | F79: P.ME summary row 140. Items 67.1-67.19 sum to 163,762,195,576 IRR (diff ~0.8 million, rounding). Safety shower (67.8) is already in Master row 20.
A80: Updated | B80: Pig Group Rollup (Master row 33) | C80: Price | D80: Not Stated | E80: 94,500,000,000 IRR (Include = N) | F80: P.ME summary row 141 = P.ME row 113 (item 68), already in Master row 8.
A81: Stage 4 (other safety items)
A82: Added | B82: Safety items P.ME 67.1-67.7, 67.9, 67.11-67.19 (Master rows 37-53) | C82: New records (17, Include = Y) | D82: — | E82: Separate records, 1402, IRR | F82: Gachsaran 4 P.ME rows 95-112. Item 67.8 (shower) already in Master row 20; item 67.10 does not exist in the source. Their sum equals the safety rollup (Master row 32, Include = N) within rounding.
A83: Added | B83: Maroon 3 safety items priced in SEFTY.p.1392 (Master rows 54-63) | C83: New records (10: 9 Y, 1 N) | D83: — | E83: Separate records, 1392, IRR | F83: Hydrants, extinguishers, first aid kit, fire shed (Y). CO2 total flooding (N): unit price entered but sheet total = 0.
A84: Note | B84: Maroon 3 unpriced safety items | C84: Not added | D84: — | E84: — | F84: Valves, deluge, wind sock, hose reel, emergency box, breathing apparatus, cabinet, stretcher, hose system, water spray, signs, axe, flashlight, breathing recovery: price cells are 0 or empty in SEFTY.p.1392.
A85: Note | B85: KPL fire water system | C85: Not added | D85: — | E85: — | F85: Fire water tank (TANKS-C), fire water pumps/jockey/loading pumps (PUMPS-C) and crane exist in the KPL report; not requested in stage 4.
A87: Fire water system (KPL)
A88: Added | B88: KPL fire water system (Master rows 64-69) | C88: New records (6, Include = Y) | D88: — | E88: TK-270 A/B 12,000,000,000 IRR; P-270 70,000 EUR; P-271 90,000 EUR; P-272 A/B 30,000 EUR; P-273 6,500 EUR; CN-271 950,000,000 IRR | F88: KPL report: TANKS-C row 27, PUMPS-C (2) rows 27 and 36, PUMPS-C (3) rows 19 and 28, CRANES (2) row 35. Pumps are EUR-priced (1394); other columns converted with the FX table 1394 rate.
A89: Note | B89: KPL (P-231/232/241/242) and Pazanan 2 (P-163/164/165) OWS pumps | C89: Not added | D89: — | E89: — | F89: Decision by user: do not add.
