Workbook
Name ________________GEN1: [1]D!#REF!
Name ________________GEN1: [1]D!#REF!
Name ________________GEN1: [1]D!#REF!
Name ________________GEN1: [1]D!#REF!
Name ________________GEN1: [1]D!#REF!
Name ________________GEN1: [1]D!#REF!
Name ________________GEN1: [1]D!#REF!
Name ________________GEN1: [1]D!#REF!
Name ________________GEN1: [1]D!#REF!
Name ________________GEN1: [1]D!#REF!
Name ________________GEN1: [1]D!#REF!
Name ________________GEN1: [1]D!#REF!
Name ________________GEN1: [1]D!#REF!
Name ________________GEN1: [1]D!#REF!
Name ________________GEN1: [1]D!#REF!
Name ________________GEN1: [1]D!#REF!
Name ________________GEN1: [1]D!#REF!
Name ________________GEN1: [1]D!#REF!
Name ______GEN1: [1]D!#REF!
Name ______GEN1: [1]D!#REF!
Name _____GEN1: [1]D!#REF!
Name _____GEN1: [1]D!#REF!
Name ____GEN1: [1]D!#REF!
Name ____GEN1: [1]D!#REF!
Name ____GEN1: [1]D!#REF!
Name ____GEN1: [1]D!#REF!
Name ____GEN1: [1]D!#REF!
Name ____GEN1: [1]D!#REF!
Name ____GEN1: [1]D!#REF!
Name ____GEN1: [1]D!#REF!
Name ____GEN1: [1]D!#REF!
Name ____GEN1: [1]D!#REF!
Name ____GEN1: [1]D!#REF!
Name ____GEN1: [1]D!#REF!
Name ____GEN1: [1]D!#REF!
Name ____GEN1: [1]D!#REF!
Name ____GEN1: [1]D!#REF!
Name ____GEN1: [1]D!#REF!
Name ____GEN1: [1]D!#REF!
Name ____GEN1: [1]D!#REF!
Name ____GEN1: [1]D!#REF!
Name ____GEN1: [1]D!#REF!
Name ___GEN1: [1]D!#REF!
Name ___GEN1: [1]D!#REF!
Name _GEN1: [1]D!#REF!
Name _GEN1: [1]D!#REF!
Name _GEN1: [1]D!#REF!
Name _GEN1: [1]D!#REF!
Name _GEN1: [1]D!#REF!
Name _GEN1: [1]D!#REF!
Name _GEN1: [1]D!#REF!
Name _GEN1: [1]D!#REF!
Name _GEN1: [1]D!#REF!
Name _GEN1: [1]D!#REF!
Name _GEN1: [1]D!#REF!
Name _GEN1: [1]D!#REF!
Name _GEN1: [1]D!#REF!
Name _GEN1: [1]D!#REF!
Name _GEN1: [1]D!#REF!
Name _GEN1: [1]D!#REF!

Sheet Cover
A1: Project Title: Revamping of Pazanan II Desalting Plant
A2: Sub-Project Title: Basic Design Studies and Preparation of FEED Package for Revamping of Pazanan II Desalting Plant
A3: Project Budget Ref. 03229 (formerly 53-51-91211)
A4: Doc. Title: BASIC MTO & COST ESTMATION REPORT (MECHANICAL)
A5: Doc. Ref. 91211-PZN-ME-RE-451-R02
A7: DOCUMENT TITLE: MECHANICAL BASIC DESIGN MTO & COST ESTIMATION REPORT
A65: R02 | D65: FEB. 2015 | I65: 91211-TN-ME-0316 | P65: IBB | U65: M.F. | Z65: M.Kh. | AE65: M.M.
A66: R01 | D66: SEP. 2014 | I66: 91211-TN-ME-0304 | P66: IBB | U66: M.F. | Z66: M.Kh. | AE66: M.M.
A67: R00 | D67: JUN. 2014 | I67: 91211-TN-ME-0286 | P67: IFC | U67: M.F. | Z67: M.Kh. | AE67: M.M.
A68: REV. | D68: DATE | I68: TRANS. No. | P68: P.O.I. | U68: PREPARED | Z68: CHECKED | AE68: APPROVED | AJ68: AUTHORIZED

Sheet Record Sheet
A1: Project Title: Revamping of Pazanan II Desalting Plant
A2: Sub-Project Title: Basic Design Studies and Preparation of FEED Package for Revamping of Pazanan II Desalting Plant
A3: Project Budget Ref. 03229 (formerly 53-51-91211)
A4: Doc. Title: BASIC MTO & COST ESTMATION REPORT (MECHANICAL)
A5: Doc. Ref. 91211-PZN-ME-RE-451-R02
P9: CHANGE RECORD SHEET
E11: PAGE | G11: R01 | J11: R02 | M11: R03 | P11: R04 | X11: PAGE | Z11: R01 | AC11: R02 | AF11: R03 | AI11: R04
E12: 1 | G12: X | X12: 51
E13: 2 | G13: X | X13: 52
E14: 3 | G14: X | X14: 53
E15: 4 | G15: X | X15: 54
E16: 5 | G16: X | X16: 55
E17: 6 | G17: X | X17: 56
E18: 7 | G18: X | X18: 57
E19: 8 | G19: X | X19: 58
E20: 9 | G20: X | X20: 59
E21: 10 | G21: X | X21: 60
E22: 11 | G22: X | X22: 61
E23: 12 | G23: X | X23: 62
... E60: 49 | G60: X | X60: 99
E61: 50 | X61: 100

Sheet TITLE
A1: Project Title: Revamping of Pazanan II Desalting Plant
A2: Sub-Project Title: Basic Design Studies and Preparation of FEED Package for Revamping of Pazanan II Desalting Plant
A3: Project Budget Ref. 03229 (formerly 53-51-91211)
A4: Doc. Title: BASIC MTO & COST ESTMATION REPORT (MECHANICAL)
A5: Doc. Ref. 91211-PZN-ME-RE-451-R02
A7: PROCUREMENT MTO & COST ESTIMATION

Sheet DESALTER
A1: Project Title: Revamping of Pazanan II Desalting Plant
A2: Sub-Project Title: Basic Design Studies and Preparation of FEED Package for Revamping of Pazanan II Desalting Plant
A3: Project Budget Ref. 03229 (formerly 53-51-91211)
A4: Doc. Title: BASIC MTO & COST ESTMATION REPORT (MECHANICAL)
A5: Doc. Ref. 91211-PZN-ME-RE-451-R02
A6: DESALTING PACKAGES | I6: استعلام 1 | N6: استعلام 2 | S6: استعلام 3 | X6: استعلام 4 | AC6: استعلام 5 | AU6: استعلام 6 | AZ6: استعلام 7 | BE6: استعلام 8 | BJ6: استعلام 9 | BO6: استعلام 10 | BT6: استعلام 11
A7: Item No. | B7: Description | C7: Qty. (Set) | E7: GOING UNIT PRICE IRR 1404Q1 | F7: GOING UNIT PRICE FOB EUR 1404Q1 | G7: TOTAL PRICE ریال | H7: TOTAL PRICE FOB € | I7: منبع | J7: بهای واحد (ریال) | K7: بهای واحد (یورو) | L7: بهای واحد (دلار) | M7: تاریخ مرجع | N7: منبع | O7: بهای واحد (ریال) | P7: بهای واحد (یورو) | Q7: بهای واحد (دلار) | R7: تاریخ مرجع | S7: منبع | T7: بهای واحد (ریال) | U7: بهای واحد (یورو) | V7: بهای واحد (دلار) | W7: تاریخ مرجع | X7: منبع | Y7: بهای واحد (ریال) | Z7: بهای واحد (یورو) | AA7: بهای واحد (دلار) | AB7: تاریخ مرجع | AC7: منبع | AD7: بهای واحد (ریال) | AE7: بهای واحد (یورو) | AF7: بهای واحد (دلار) | AG7: تاریخ مرجع | AH7: No. of available quotations in IRR | AI7: No. of available quotations in EUR | AJ7: No. of available quotations in USD | AK7: avg. of IRR quotations converted to EUR | AL7: avg. of EUR quotations EUR | AM7: avg. of USD quotations converted to EUR | AN7: aggregate average quoted unit price (all in EUR) | AO7: Ref. Currency | AP7: quoted unit price | AQ7: UNIT PRICE ریال 1393Q3 | AR7: UNIT PRICE FOB € - 1393Q3 | AS7: NEW ITEM unit price IRR | AT7: NEW ITEM unit price EUR | AU7: منبع | AV7: بهای واحد (ریال) | AW7: بهای واحد (یورو) | AX7: بهای واحد (دلار) | AY7: تاریخ مرجع | AZ7: منبع | BA7: بهای واحد (ریال) | BB7: بهای واحد (یورو) | BC7: بهای واحد (دلار) | BD7: تاریخ مرجع | BE7: منبع | BF7: بهای واحد (ریال) | BG7: بهای واحد (یورو) | BH7: بهای واحد (دلار) | BI7: تاریخ مرجع | BJ7: منبع | BK7: بهای واحد (ریال) | BL7: بهای واحد (یورو) | BM7: بهای واحد (دلار) | BN7: تاریخ مرجع | BO7: منبع | BP7: بهای واحد (ریال) | BQ7: بهای واحد (یورو) | BR7: بهای واحد (دلار) | BS7: تاریخ مرجع | BT7: منبع | BU7: بهای واحد (ریال) | BV7: بهای واحد (یورو) | BW7: بهای واحد (دلار) | BX7: تاریخ مرجع
A8: PK-111 | B8: Desalting Package Type: Electrostatic - AC / DC Including 1st Desalter (W/ 3 x 50% Transformer), Recycle Pumps, Related Piping, Instruments, etc. Desalter Vessel Tag No.: DE-111 Vessels Dim. (ID x TL-TL): 3658 x 16764 mm Vessels Design Pressure: 15.5 Barg Vessels Design Temperature: -2.8 / 95 oC Vessels Mat. (Shell/Heads): SA 516 Gr. 70 NACE 'MR-0175' Required: Yes Vessel Design Code & Standard: ASME VIII, DIV.1 & IPS-G-ME-150 Recycle Pumps Tag Nos.: P-112 A/B Pumps Type: Centrifugal (OH2) Pumps Rated Flow (m3/hr): 20.2 Pumps Differential Pressure (Barg): 4.5 Pumps Material Class(Acc. to API 610): D2 NACE 'MR-0175' Required: Yes Pumps Design Code & Standard: API 610 & IPS-G-PM-105 | C8: 1 | E8: =IF(AND(AO8="IRR",SUM(AH8:AJ8)>0),AP8,IF(AND(AO8="IRR",AQ8<>""),AQ8*'[5]Basic INFO'!$E$127,IF(AO8="IRR",AS8,""))) | F8: =IF(AND(AO8="EUR",SUM(AH8:AJ8)>0),AP8,IF(AND(AO8="EUR",AR8<>""),AR8*'[5]Basic INFO'!$C$138,IF(AO8="EUR",AT8,""))) -> 1932650.5 | G8: =IF(AO8="IRR",C8*E8,"") | H8: =IF(AO8="EUR",C8*F8,"") -> 1932650.5 | I8: گازتک ایرانیان | K8: 1815301 | M8: 45686 | N8: مصنوعات فلزی سنگین | P8: 2050000 | R8: 45716 | S8: Thermo Engineering, Italy | W8: declined | X8: خرد صنعت | AB8: no reply | AC8: Petro Technca, Canada | AG8: no reply | AH8: =IF(B8="","",COUNT(J8,O8,T8,Y8,AD8)) -> 0 | AI8: =IF(B8="","",COUNT(K8,P8,U8,Z8,AE8)) -> 2 | AJ8: =IF(B8="","",COUNT(L8,Q8,V8,AA8,AF8)) -> 0 | AK8: =IF(AND(AH8<>"",AH8>0),AVERAGE(J8,O8,T8,Y8,AD8)/('[5]Basic INFO'!$C$101*'[5]Basic INFO'!$C$103),"") | AL8: =IF(AND(AI8<>"",AI8>0),AVERAGE(K8,P8,U8,Z8,AE8),"") -> 1932650.5 | AM8: =IF(AND(AJ8<>"",AJ8>0),AVERAGE(L8,Q8,V8,AA8,AF8)/'[5]Basic INFO'!$C$103,"") | AN8: =IF(SUM(AH8:AJ8)<>0,AVERAGE(AK8:AM8),"") -> 1932650.5 | AO8: EUR | AP8: =IF(B8="","",IF(SUM(AH8:AJ8)=0,"",IF(AO8="IRR",AN8*('[5]Basic INFO'!$C$101*'[5]Basic INFO'!$C$103),IF(AO8="EUR",AN8,AP8)))) -> 1932650.5 | AR8: 2500000 | AU8: Aker Solutions, Norway | AY8: no reply | AZ8: Axens, France | BD8: no reply | BE8: Desalters LLC, USA | BI8: no reply | BJ8: Sulzer, USA | BN8: no reply | BO8: Howe Baker | BS8: no reply | BT8: Process Systems, France | BX8: no reply
B9: برآورد هزینه بدون سربار و مالیات بر ارزش افزوده | G9: =SUM(G8) -> 0 | H9: =SUM(H8) -> 1932650.5
B10: ضریب سربار تأمین کالا | G10: 1.18 | H10: 1.18
B11: مالیات بر ارزش افزوده | G11: 0.1 | H11: 0.1
B12: هزینه تأمین کالا + سربار + مالیات بر ارزش افزوده | G12: =ROUND((G9*G10*(1+G11))/1000000,0)*1000000 -> 0 | H12: =ROUND(H9*H10*(1+H11)/1000,0)*1000 -> 2509000
G13: =ROUND(SUMIF(AP:AP,">0",G:G)*G10*(1+G11)/1000000,0)*1000000 -> 0 | H13: =ROUND(SUMIF(AP:AP,">0",H:H)*H10*(1+H11)/1000,0)*1000 -> 2509000

Sheet HEATERS
A1: Project Title: Revamping of Pazanan II Desalting Plant
A2: Sub-Project Title: Basic Design Studies and Preparation of FEED Package for Revamping of Pazanan II Desalting Plant
A3: Project Budget Ref. 03229 (formerly 53-51-91211)
A4: Doc. Title: BASIC MTO & COST ESTMATION REPORT (MECHANICAL)
A5: Doc. Ref. 91211-PZN-ME-RE-451-R02
A6: INDIRECT FIRED HEATER PACKAGES | I6: استعلام 1 | N6: استعلام 2 | S6: استعلام 3 | X6: استعلام 4 | AC6: استعلام 5 | AU6: استعلام 6 | AZ6: استعلام 7 | BE6: استعلام 8 | BJ6: استعلام 9 | BO6: استعلام 10 | BT6: استعلام 11 | BY6: استعلام 12 | CD6: استعلام 13
A7: Item No. | B7: Description | C7: Qty. (Set) | E7: GOING UNIT PRICE IRR 1404Q1 | F7: GOING UNIT PRICE FOB EUR 1404Q1 | G7: TOTAL PRICE ریال | H7: TOTAL PRICE FOB € | I7: منبع | J7: بهای واحد (ریال) | K7: بهای واحد (یورو) | L7: بهای واحد (دلار) | M7: تاریخ مرجع | N7: منبع | O7: بهای واحد (ریال) | P7: بهای واحد (یورو) | Q7: بهای واحد (دلار) | R7: تاریخ مرجع | S7: منبع | T7: بهای واحد (ریال) | U7: بهای واحد (یورو) | V7: بهای واحد (دلار) | W7: تاریخ مرجع | X7: منبع | Y7: بهای واحد (ریال) | Z7: بهای واحد (یورو) | AA7: بهای واحد (دلار) | AB7: تاریخ مرجع | AC7: منبع | AD7: بهای واحد (ریال) | AE7: بهای واحد (یورو) | AF7: بهای واحد (دلار) | AG7: تاریخ مرجع | AH7: No. of available quotations in IRR | AI7: No. of available quotations in EUR | AJ7: No. of available quotations in USD | AK7: avg. of IRR quotations converted to EUR | AL7: avg. of EUR quotations EUR | AM7: avg. of USD quotations converted to EUR | AN7: aggregate average quoted unit price (all in EUR) | AO7: Ref. Currency | AP7: quoted unit price | AQ7: UNIT PRICE ریال 1393Q3 | AR7: UNIT PRICE FOB € - 1393Q3 | AS7: NEW ITEM unit price IRR | AT7: NEW ITEM unit price EUR | AU7: منبع | AV7: بهای واحد (ریال) | AW7: بهای واحد (یورو) | AX7: بهای واحد (دلار) | AY7: تاریخ مرجع | AZ7: منبع | BA7: بهای واحد (ریال) | BB7: بهای واحد (یورو) | BC7: بهای واحد (دلار) | BD7: تاریخ مرجع | BE7: منبع | BF7: بهای واحد (ریال) | BG7: بهای واحد (یورو) | BH7: بهای واحد (دلار) | BI7: تاریخ مرجع | BJ7: منبع | BK7: بهای واحد (ریال) | BL7: بهای واحد (یورو) | BM7: بهای واحد (دلار) | BN7: تاریخ مرجع | BO7: منبع | BP7: بهای واحد (ریال) | BQ7: بهای واحد (یورو) | BR7: بهای واحد (دلار) | BS7: تاریخ مرجع | BT7: منبع | BU7: بهای واحد (ریال) | BV7: بهای واحد (یورو) | BW7: بهای واحد (دلار) | BX7: تاریخ مرجع | BY7: منبع | BZ7: بهای واحد (ریال) | CA7: بهای واحد (یورو) | CB7: بهای واحد (دلار) | CC7: تاریخ مرجع | CD7: منبع | CE7: بهای واحد (ریال) | CF7: بهای واحد (یورو) | CG7: بهای واحد (دلار) | CH7: تاریخ مرجع
A8: H-111 A/B | B8: Oil Indirect Fired Heater Packages Rated Heat Exchanged (KW): 7725 Shell Dim. (ID x TL-TL): 3900 x 12000 mm Design Press. (Shell/Coils): 0.3/15.5 Barg Design Temperature: -2.8 / 120 oC Material (Shell/Heads): SA 516 Gr. 70 Material (Coils): SA 106 Gr. B NACE 'MR-0175' Required: Yes (for Coils) Design Code & Standard: API Spec.12K , ASME VIII, DIV.1 & IPS-G-ME-200 | C8: 2 | E8: =IF(AND(AO8="IRR",SUM(AH8:AJ8)>0),AP8,IF(AND(AO8="IRR",AQ8<>""),AQ8*'[5]Basic INFO'!$E$127,IF(AO8="IRR",AS8,""))) | F8: =IF(AND(AO8="EUR",SUM(AH8:AJ8)>0),AP8,IF(AND(AO8="EUR",AR8<>""),AR8*'[5]Basic INFO'!$C$138,IF(AO8="EUR",AT8,""))) -> 1164712.8 | G8: =IF(AO8="IRR",C8*E8,"") | H8: =IF(AO8="EUR",C8*F8,"") -> 2329425.7 | I8: گازتک ایرانیان | K8: 1044138.5 | M8: 45686 | N8: انرزی گستر ماد | P8: 1400000 | S8: مصنوعات فلزی سنگین | U8: 1050000 | W8: 45716 | X8: Thermo Engineering, Italy | AB8: declined | AC8: خرد صنعت | AG8: no reply | AH8: =IF(B8="","",COUNT(J8,O8,T8,Y8,AD8)) -> 0 | AI8: =IF(B8="","",COUNT(K8,P8,U8,Z8,AE8)) -> 3 | AJ8: =IF(B8="","",COUNT(L8,Q8,V8,AA8,AF8)) -> 0 | AK8: =IF(AND(AH8<>"",AH8>0),AVERAGE(J8,O8,T8,Y8,AD8)/('[5]Basic INFO'!$C$101*'[5]Basic INFO'!$C$103),"") | AL8: =IF(AND(AI8<>"",AI8>0),AVERAGE(K8,P8,U8,Z8,AE8),"") -> 1164712.8 | AM8: =IF(AND(AJ8<>"",AJ8>0),AVERAGE(L8,Q8,V8,AA8,AF8)/'[5]Basic INFO'!$C$103,"") | AN8: =IF(SUM(AH8:AJ8)<>0,AVERAGE(AK8:AM8),"") -> 1164712.8 | AO8: EUR | AP8: =IF(B8="","",IF(SUM(AH8:AJ8)=0,"",IF(AO8="IRR",AN8*('[5]Basic INFO'!$C$101*'[5]Basic INFO'!$C$103),IF(AO8="EUR",AN8,AP8)))) -> 1164712.8 | AR8: 800000 | AU8: Petro Technca, Canada | AY8: no reply | AZ8: Aker Solutions, Norway | BD8: no reply | BE8: Axens, France | BI8: no reply | BJ8: Desalters LLC, USA | BN8: no reply | BO8: Sulzer, USA | BS8: no reply | BT8: Howe Baker | BX8: no reply | BY8: Process Systems, France | CC8: no reply | CD8: شرکت چمان | CH8: no reply
A9: H-112 | B9: Water Indirect Fired Heater Packages Rated Heat Exchanged (KW): 4174 Dimsion (ID x TL-TL): 2800 x 10400 mm Design Press. (Shell/Coils): 0.3/15.5 Barg Design Temperature: -2.8 / 120 oC Material (Shell/Heads): SA 516 Gr. 70 Material (Coils): SA 106 Gr. B Design Code & Standard: API Spec.12K , ASME VIII, DIV.1 & IPS-G-ME-200 | C9: 1 | E9: =IF(AND(AO9="IRR",SUM(AH9:AJ9)>0),AP9,IF(AND(AO9="IRR",AQ9<>""),AQ9*'[5]Basic INFO'!$E$127,IF(AO9="IRR",AS9,""))) | F9: =IF(AND(AO9="EUR",SUM(AH9:AJ9)>0),AP9,IF(AND(AO9="EUR",AR9<>""),AR9*'[5]Basic INFO'!$C$138,IF(AO9="EUR",AT9,""))) -> 1090791.3 | G9: =IF(AO9="IRR",C9*E9,"") | H9: =IF(AO9="EUR",C9*F9,"") -> 1090791.3 | I9: گازتک ایرانیان | K9: 1452374 | M9: 45686 | N9: انرزی گستر ماد | P9: 1200000 | S9: مصنوعات فلزی سنگین | U9: 620000 | W9: 45716 | X9: Thermo Engineering, Italy | AB9: declined | AC9: خرد صنعت | AG9: no reply | AH9: =IF(B9="","",COUNT(J9,O9,T9,Y9,AD9)) -> 0 | AI9: =IF(B9="","",COUNT(K9,P9,U9,Z9,AE9)) -> 3 | AJ9: =IF(B9="","",COUNT(L9,Q9,V9,AA9,AF9)) -> 0 | AK9: =IF(AND(AH9<>"",AH9>0),AVERAGE(J9,O9,T9,Y9,AD9)/('[5]Basic INFO'!$C$101*'[5]Basic INFO'!$C$103),"") | AL9: =IF(AND(AI9<>"",AI9>0),AVERAGE(K9,P9,U9,Z9,AE9),"") -> 1090791.3 | AM9: =IF(AND(AJ9<>"",AJ9>0),AVERAGE(L9,Q9,V9,AA9,AF9)/'[5]Basic INFO'!$C$103,"") | AN9: =IF(SUM(AH9:AJ9)<>0,AVERAGE(AK9:AM9),"") -> 1090791.3 | AO9: EUR | AP9: =IF(B9="","",IF(SUM(AH9:AJ9)=0,"",IF(AO9="IRR",AN9*('[5]Basic INFO'!$C$101*'[5]Basic INFO'!$C$103),IF(AO9="EUR",AN9,AP9)))) -> 1090791.3 | AR9: 680000 | AU9: Petro Technca, Canada | AY9: no reply | AZ9: Aker Solutions, Norway | BD9: no reply | BE9: Axens, France | BI9: no reply | BJ9: Desalters LLC, USA | BN9: no reply | BO9: Sulzer, USA | BS9: no reply | BT9: Howe Baker | BX9: no reply | BY9: Process Systems, France | CC9: no reply | CD9: شرکت چمان | CH9: no reply
B10: برآورد هزینه بدون سربار و مالیات بر ارزش افزوده | G10: =SUM(G8:G9) -> 0 | H10: =SUM(H8:H9) -> 3420217
B11: ضریب سربار تأمین کالا | G11: 1.18 | H11: 1.18
B12: مالیات بر ارزش افزوده | G12: 0.1 | H12: 0.1
B13: هزینه تأمین کالا + سربار + مالیات بر ارزش افزوده | G13: =ROUND((G10*G11*(1+G12))/1000000,0)*1000000 -> 0 | H13: =ROUND(H10*H11*(1+H12)/1000,0)*1000 -> 4439000
G14: =ROUND(SUMIF(AP:AP,">0",G:G)*G11*(1+G12)/1000000,0)*1000000 -> 0 | H14: =ROUND(SUMIF(AP:AP,">0",H:H)*H11*(1+H12)/1000,0)*1000 -> 4439000

Sheet VESSELS
A1: Project Title: Revamping of Pazanan II Desalting Plant
A2: Sub-Project Title: Basic Design Studies and Preparation of FEED Package for Revamping of Pazanan II Desalting Plant
A3: Project Budget Ref. 03229 (formerly 53-51-91211)
A4: Doc. Title: BASIC MTO & COST ESTMATION REPORT (MECHANICAL)
A5: Doc. Ref. 91211-PZN-ME-RE-451-R02
A6: VESSELS | I6: استعلام 1 | N6: استعلام 2 | S6: استعلام 3 | X6: استعلام 4 | AC6: استعلام 5
A7: Item No. | B7: Description | C7: Qty. (Set) | E7: GOING UNIT PRICE IRR 1404Q1 | F7: GOING UNIT PRICE FOB EUR 1404Q1 | G7: TOTAL PRICE ریال | H7: TOTAL PRICE FOB € | I7: منبع | J7: بهای واحد (ریال) | K7: بهای واحد (یورو) | L7: بهای واحد (دلار) | M7: تاریخ مرجع | N7: منبع | O7: بهای واحد (ریال) | P7: بهای واحد (یورو) | Q7: بهای واحد (دلار) | R7: تاریخ مرجع | S7: منبع | T7: بهای واحد (ریال) | U7: بهای واحد (یورو) | V7: بهای واحد (دلار) | W7: تاریخ مرجع | X7: منبع | Y7: بهای واحد (ریال) | Z7: بهای واحد (یورو) | AA7: بهای واحد (دلار) | AB7: تاریخ مرجع | AC7: منبع | AD7: بهای واحد (ریال) | AE7: بهای واحد (یورو) | AF7: بهای واحد (دلار) | AG7: تاریخ مرجع | AH7: No. of available quotations in IRR | AI7: No. of available quotations in EUR | AJ7: No. of available quotations in USD | AK7: avg. of IRR quotations converted to EUR | AL7: avg. of EUR quotations EUR | AM7: avg. of USD quotations converted to EUR | AN7: aggregate average quoted unit price (all in EUR) | AO7: Ref. Currency | AP7: quoted unit price | AQ7: Unit Price (Rials) | AR7: Unit Price 'FOB' (€) | AS7: NEW ITEM unit price IRR | AT7: NEW ITEM unit price EUR
A8: V-141 | B8: Air Receiver Size (ID x TL-TL): 2300 x 6900 mm Installation Position: Vertical Design Pressure: 13.5 Barg Design Temperature: -2.8 / 85 oC Material (Shell/Heads): SA 516 Gr. 70 Design Code & Standard: ASME VIII, DIV.1 & IPS-G-ME-150 | C8: 1 | E8: =IF(AND(AO8="IRR",SUM(AH8:AJ8)>0),AP8,IF(AND(AO8="IRR",AQ8<>""),AQ8*'[5]Basic INFO'!$E$127,IF(AO8="IRR",AS8,""))) -> 4.5889668e+10 | F8: =IF(AND(AO8="EUR",SUM(AH8:AJ8)>0),AP8,IF(AND(AO8="EUR",AR8<>""),AR8*'[5]Basic INFO'!$C$138,IF(AO8="EUR",AT8,""))) | G8: =IF(AO8="IRR",C8*E8,"") -> 4.5889668e+10 | H8: =IF(AO8="EUR",C8*F8,"") | I8: طرح مکانیک گستر شیراز | M8: no reply | N8: پایساز | R8: no reply | S8: تاشا | W8: no reply | X8: ماشین سازی اراک | Z8: 84000 | AB8: 02/29/2025 | AC8: پولادورزان کیمیا | AE8: =4*12000 -> 48000 | AG8: 45801 | AH8: =IF(B8="","",COUNT(J8,O8,T8,Y8,AD8)) -> 0 | AI8: =IF(B8="","",COUNT(K8,P8,U8,Z8,AE8)) -> 2 | AJ8: =IF(B8="","",COUNT(L8,Q8,V8,AA8,AF8)) -> 0 | AK8: =IF(AND(AH8<>"",AH8>0),AVERAGE(J8,O8,T8,Y8,AD8)/('[5]Basic INFO'!$C$101*'[5]Basic INFO'!$C$103),"") | AL8: =IF(AND(AI8<>"",AI8>0),AVERAGE(K8,P8,U8,Z8,AE8),"") -> 66000 | AM8: =IF(AND(AJ8<>"",AJ8>0),AVERAGE(L8,Q8,V8,AA8,AF8)/'[5]Basic INFO'!$C$103,"") | AN8: =IF(SUM(AH8:AJ8)<>0,AVERAGE(AK8:AM8),"") -> 66000 | AO8: IRR | AP8: =IF(B8="","",IF(SUM(AH8:AJ8)=0,"",IF(AO8="IRR",AN8*('[5]Basic INFO'!$C$101*'[5]Basic INFO'!$C$103),IF(AO8="EUR",AN8,AP8)))) -> 4.5889668e+10 | AQ8: 1700000000
A9: V-151 | B9: Flare K.O. Drum Size (ID x TL-TL): 1300 x 3900 mm Installation Position: Horizontal Design Pressure: 3.5 (F.V.) Barg Design Temperature: -2.8 / 85 oC Material (Shell/Heads): SA 516 Gr. 70 NACE 'MR-0175' Required: Yes Design Code & Standard: ASME VIII, DIV.1 & IPS-G-ME-150 | C9: 1 | E9: =IF(AND(AO9="IRR",SUM(AH9:AJ9)>0),AP9,IF(AND(AO9="IRR",AQ9<>""),AQ9*'[5]Basic INFO'!$E$127,IF(AO9="IRR",AS9,""))) -> 1.1124768e+10 | F9: =IF(AND(AO9="EUR",SUM(AH9:AJ9)>0),AP9,IF(AND(AO9="EUR",AR9<>""),AR9*'[5]Basic INFO'!$C$138,IF(AO9="EUR",AT9,""))) | G9: =IF(AO9="IRR",C9*E9,"") -> 1.1124768e+10 | H9: =IF(AO9="EUR",C9*F9,"") | I9: طرح مکانیک گستر شیراز | M9: no reply | N9: پایساز | R9: no reply | S9: تاشا | W9: no reply | X9: ماشین سازی اراک | Z9: 16000 | AB9: 02/29/2025 | AC9: پولادورزان کیمیا | AE9: =4*4000 -> 16000 | AG9: 45801 | AH9: =IF(B9="","",COUNT(J9,O9,T9,Y9,AD9)) -> 0 | AI9: =IF(B9="","",COUNT(K9,P9,U9,Z9,AE9)) -> 2 | AJ9: =IF(B9="","",COUNT(L9,Q9,V9,AA9,AF9)) -> 0 | AK9: =IF(AND(AH9<>"",AH9>0),AVERAGE(J9,O9,T9,Y9,AD9)/('[5]Basic INFO'!$C$101*'[5]Basic INFO'!$C$103),"") | AL9: =IF(AND(AI9<>"",AI9>0),AVERAGE(K9,P9,U9,Z9,AE9),"") -> 16000 | AM9: =IF(AND(AJ9<>"",AJ9>0),AVERAGE(L9,Q9,V9,AA9,AF9)/'[5]Basic INFO'!$C$103,"") | AN9: =IF(SUM(AH9:AJ9)<>0,AVERAGE(AK9:AM9),"") -> 16000 | AO9: IRR | AP9: =IF(B9="","",IF(SUM(AH9:AJ9)=0,"",IF(AO9="IRR",AN9*('[5]Basic INFO'!$C$101*'[5]Basic INFO'!$C$103),IF(AO9="EUR",AN9,AP9)))) -> 1.1124768e+10 | AQ9: 675000000
A10: V-161 | B10: Closed Drain Drum Size (ID x TL-TL): 2000 x 8000 mm Installation Position: Horizontal Design Pressure: 3.5 (F.V.) Barg Design Temperature: -2.8 / 85 oC Material (Shell/Heads): SA 516 Gr. 70 NACE 'MR-0175' Required: Yes Design Code & Standard: ASME VIII, DIV.1 & IPS-G-ME-150 | C10: 1 | E10: =IF(AND(AO10="IRR",SUM(AH10:AJ10)>0),AP10,IF(AND(AO10="IRR",AQ10<>""),AQ10*'[5]Basic INFO'!$E$127,IF(AO10="IRR",AS10,""))) -> 3.6711734e+10 | F10: =IF(AND(AO10="EUR",SUM(AH10:AJ10)>0),AP10,IF(AND(AO10="EUR",AR10<>""),AR10*'[5]Basic INFO'!$C$138,IF(AO10="EUR",AT10,""))) | G10: =IF(AO10="IRR",C10*E10,"") -> 3.6711734e+10 | H10: =IF(AO10="EUR",C10*F10,"") | I10: طرح مکانیک گستر شیراز | M10: no reply | N10: پایساز | R10: no reply | S10: تاشا | W10: no reply | X10: ماشین سازی اراک | Z10: 65600 | AB10: 2/29/2025 | AC10: پولادورزان کیمیا | AE10: =4*10000 -> 40000 | AG10: 45801 | AH10: =IF(B10="","",COUNT(J10,O10,T10,Y10,AD10)) -> 0 | AI10: =IF(B10="","",COUNT(K10,P10,U10,Z10,AE10)) -> 2 | AJ10: =IF(B10="","",COUNT(L10,Q10,V10,AA10,AF10)) -> 0 | AK10: =IF(AND(AH10<>"",AH10>0),AVERAGE(J10,O10,T10,Y10,AD10)/('[5]Basic INFO'!$C$101*'[5]Basic INFO'!$C$103),"") | AL10: =IF(AND(AI10<>"",AI10>0),AVERAGE(K10,P10,U10,Z10,AE10),"") -> 52800 | AM10: =IF(AND(AJ10<>"",AJ10>0),AVERAGE(L10,Q10,V10,AA10,AF10)/'[5]Basic INFO'!$C$103,"") | AN10: =IF(SUM(AH10:AJ10)<>0,AVERAGE(AK10:AM10),"") -> 52800 | AO10: IRR | AP10: =IF(B10="","",IF(SUM(AH10:AJ10)=0,"",IF(AO10="IRR",AN10*('[5]Basic INFO'!$C$101*'[5]Basic INFO'!$C$103),IF(AO10="EUR",AN10,AP10)))) -> 3.6711734e+10 | AQ10: 1600000000
A11: V-171 | B11: Fuel Oil Storage Drum Size (ID x TL-TL): 1500 x 4500 mm Installation Position: Horizontal Design Pressure: Atm. + Full of Liquid Design Temperature: -2.8 / 85 oC Material (Shell/Heads): SA 285 Gr. C Design Code & Standard: ASME VIII, DIV.1 & IPS-G-ME-150 | C11: 1 | E11: =IF(AND(AO11="IRR",SUM(AH11:AJ11)>0),AP11,IF(AND(AO11="IRR",AQ11<>""),AQ11*'[5]Basic INFO'!$E$127,IF(AO11="IRR",AS11,""))) -> 1.029041e+10 | F11: =IF(AND(AO11="EUR",SUM(AH11:AJ11)>0),AP11,IF(AND(AO11="EUR",AR11<>""),AR11*'[5]Basic INFO'!$C$138,IF(AO11="EUR",AT11,""))) | G11: =IF(AO11="IRR",C11*E11,"") -> 1.029041e+10 | H11: =IF(AO11="EUR",C11*F11,"") | I11: طرح مکانیک گستر شیراز | M11: no reply | N11: پایساز | R11: no reply | S11: تاشا | W11: no reply | X11: ماشین سازی اراک | Z11: 21600 | AB11: 2/29/2025 | AC11: پولادورزان کیمیا | AE11: =4*2000 -> 8000 | AG11: 45801 | AH11: =IF(B11="","",COUNT(J11,O11,T11,Y11,AD11)) -> 0 | AI11: =IF(B11="","",COUNT(K11,P11,U11,Z11,AE11)) -> 2 | AJ11: =IF(B11="","",COUNT(L11,Q11,V11,AA11,AF11)) -> 0 | AK11: =IF(AND(AH11<>"",AH11>0),AVERAGE(J11,O11,T11,Y11,AD11)/('[5]Basic INFO'!$C$101*'[5]Basic INFO'!$C$103),"") | AL11: =IF(AND(AI11<>"",AI11>0),AVERAGE(K11,P11,U11,Z11,AE11),"") -> 14800 | AM11: =IF(AND(AJ11<>"",AJ11>0),AVERAGE(L11,Q11,V11,AA11,AF11)/'[5]Basic INFO'!$C$103,"") | AN11: =IF(SUM(AH11:AJ11)<>0,AVERAGE(AK11:AM11),"") -> 14800 | AO11: IRR | AP11: =IF(B11="","",IF(SUM(AH11:AJ11)=0,"",IF(AO11="IRR",AN11*('[5]Basic INFO'!$C$101*'[5]Basic INFO'!$C$103),IF(AO11="EUR",AN11,AP11)))) -> 1.029041e+10 | AQ11: 370000000
B12: برآورد هزینه بدون سربار و مالیات بر ارزش افزوده | G12: =SUM(G8:G11) -> 1.0401658e+11 | H12: =SUM(H8:H11) -> 0 | AQ12: Total Price (Rials) | AR12: Total Price (Euros)
B13: ضریب سربار تأمین کالا | G13: 1.18 | H13: 1.18
B14: مالیات بر ارزش افزوده | G14: 0.1 | H14: 0.1
B15: هزینه تأمین کالا + سربار + مالیات بر ارزش افزوده | G15: =ROUND((G12*G13*(1+G14))/1000000,0)*1000000 -> 135014000000 | H15: =ROUND(H12*H13*(1+H14)/1000,0)*1000 -> 0
G16: =ROUND(SUMIF(AP:AP,">0",G:G)*G13*(1+G14)/1000000,0)*1000000 -> 135014000000 | H16: =ROUND(SUMIF(AP:AP,">0",H:H)*H13*(1+H14)/1000,0)*1000 -> 0

Sheet TANKS
A1: Project Title: Revamping of Pazanan II Desalting Plant
A2: Sub-Project Title: Basic Design Studies and Preparation of FEED Package for Revamping of Pazanan II Desalting Plant
A3: Project Budget Ref. 03229 (formerly 53-51-91211)
A4: Doc. Title: BASIC MTO & COST ESTMATION REPORT (MECHANICAL)
A5: Doc. Ref. 91211-PZN-ME-RE-451-R02
A6: TANKS | I6: استعلام 1 | N6: استعلام 2 | S6: استعلام 3 | X6: استعلام 4 | AC6: استعلام 5
A7: Item No. | B7: Description | C7: Qty. (Set) | E7: GOING UNIT PRICE IRR 1404Q1 | F7: GOING UNIT PRICE FOB EUR 1404Q1 | G7: TOTAL PRICE ریال | H7: TOTAL PRICE FOB € | I7: منبع | J7: بهای واحد (ریال) | K7: بهای واحد (یورو) | L7: بهای واحد (دلار) | M7: تاریخ مرجع | N7: منبع | O7: بهای واحد (ریال) | P7: بهای واحد (یورو) | Q7: بهای واحد (دلار) | R7: تاریخ مرجع | S7: منبع | T7: بهای واحد (ریال) | U7: بهای واحد (یورو) | V7: بهای واحد (دلار) | W7: تاریخ مرجع | X7: منبع | Y7: بهای واحد (ریال) | Z7: بهای واحد (یورو) | AA7: بهای واحد (دلار) | AB7: تاریخ مرجع | AC7: منبع | AD7: بهای واحد (ریال) | AE7: بهای واحد (یورو) | AF7: بهای واحد (دلار) | AG7: تاریخ مرجع | AH7: No. of available quotations in IRR | AI7: No. of available quotations in EUR | AJ7: No. of available quotations in USD | AK7: avg. of IRR quotations converted to EUR | AL7: avg. of EUR quotations EUR | AM7: avg. of USD quotations converted to EUR | AN7: aggregate average quoted unit price (all in EUR) | AO7: Ref. Currency | AP7: quoted unit price | AQ7: Unit Price (Rials) | AR7: Unit Price 'FOB' (€) | AS7: NEW ITEM unit price IRR | AT7: NEW ITEM unit price EUR
A8: TK-111 | B8: Off Spec. Tank Size (D x H): 20000 x 13000 mm Roof Type: Dome Design Pressure: -0.4 / 25 Kpa(g) Design Temperature: -2.8 / 85 oC Material (Shell/Bottom/Roof): A 283 Gr. C NACE 'MR-0175' Required: Yes Design Code & Standard: API 620 & IPS-G-ME-110 | C8: 1 | E8: =IF(AND(AO8="IRR",SUM(AH8:AJ8)>0),AP8,IF(AND(AO8="IRR",AQ8<>""),AQ8*'[5]Basic INFO'!$E$127,IF(AO8="IRR",AS8,""))) -> 2.8333393e+11 | F8: =IF(AND(AO8="EUR",SUM(AH8:AJ8)>0),AP8,IF(AND(AO8="EUR",AR8<>""),AR8*'[5]Basic INFO'!$C$138,IF(AO8="EUR",AT8,""))) | G8: =IF(AO8="IRR",C8*E8,"") -> 2.8333393e+11 | H8: =IF(AO8="EUR",C8*F8,"") | I8: طرح مکانیک گستر شیراز | M8: no reply | N8: پایساز | R8: no reply | S8: تاشا | W8: no reply | X8: ماشین سازی اراک | Z8: 540000 | AB8: 02/29/2025 | AC8: پولادورزان کیمیا | AE8: =2.5*110000 -> 275000 | AG8: 45801 | AH8: =IF(B8="","",COUNT(J8,O8,T8,Y8,AD8)) -> 0 | AI8: =IF(B8="","",COUNT(K8,P8,U8,Z8,AE8)) -> 2 | AJ8: =IF(B8="","",COUNT(L8,Q8,V8,AA8,AF8)) -> 0 | AK8: =IF(AND(AH8<>"",AH8>0),AVERAGE(J8,O8,T8,Y8,AD8)/('[5]Basic INFO'!$C$101*'[5]Basic INFO'!$C$103),"") | AL8: =IF(AND(AI8<>"",AI8>0),AVERAGE(K8,P8,U8,Z8,AE8),"") -> 407500 | AM8: =IF(AND(AJ8<>"",AJ8>0),AVERAGE(L8,Q8,V8,AA8,AF8)/'[5]Basic INFO'!$C$103,"") | AN8: =IF(SUM(AH8:AJ8)<>0,AVERAGE(AK8:AM8),"") -> 407500 | AO8: IRR | AP8: =IF(B8="","",IF(SUM(AH8:AJ8)=0,"",IF(AO8="IRR",AN8*('[5]Basic INFO'!$C$101*'[5]Basic INFO'!$C$103),IF(AO8="EUR",AN8,AP8)))) -> 2.8333393e+11 | AQ8: 22500000000
A9: TK-191 A/B | B9: Fire Water Tank Size (D x H): 15000 x 10000 mm Roof Type: Cone Design Pressure: Atm. Design Temperature: -2.8 / 85 oC Material (Shell/Bottom/Roof): A 283 Gr. C Design Code & Standard: API 650 & IPS-G-ME-100 | C9: 2 | E9: =IF(AND(AO9="IRR",SUM(AH9:AJ9)>0),AP9,IF(AND(AO9="IRR",AQ9<>""),AQ9*'[5]Basic INFO'!$E$127,IF(AO9="IRR",AS9,""))) -> 1.6252591e+11 | F9: =IF(AND(AO9="EUR",SUM(AH9:AJ9)>0),AP9,IF(AND(AO9="EUR",AR9<>""),AR9*'[5]Basic INFO'!$C$138,IF(AO9="EUR",AT9,""))) | G9: =IF(AO9="IRR",C9*E9,"") -> 3.2505181e+11 | H9: =IF(AO9="EUR",C9*F9,"") | I9: طرح مکانیک گستر شیراز | M9: no reply | N9: پایساز | R9: no reply | S9: تاشا | W9: no reply | X9: ماشین سازی اراک | Z9: 292500 | AB9: 2/29/2025 | AC9: پولادورزان کیمیا | AE9: =2.5*70000 -> 175000 | AG9: 45801 | AH9: =IF(B9="","",COUNT(J9,O9,T9,Y9,AD9)) -> 0 | AI9: =IF(B9="","",COUNT(K9,P9,U9,Z9,AE9)) -> 2 | AJ9: =IF(B9="","",COUNT(L9,Q9,V9,AA9,AF9)) -> 0 | AK9: =IF(AND(AH9<>"",AH9>0),AVERAGE(J9,O9,T9,Y9,AD9)/('[5]Basic INFO'!$C$101*'[5]Basic INFO'!$C$103),"") | AL9: =IF(AND(AI9<>"",AI9>0),AVERAGE(K9,P9,U9,Z9,AE9),"") -> 233750 | AM9: =IF(AND(AJ9<>"",AJ9>0),AVERAGE(L9,Q9,V9,AA9,AF9)/'[5]Basic INFO'!$C$103,"") | AN9: =IF(SUM(AH9:AJ9)<>0,AVERAGE(AK9:AM9),"") -> 233750 | AO9: IRR | AP9: =IF(B9="","",IF(SUM(AH9:AJ9)=0,"",IF(AO9="IRR",AN9*('[5]Basic INFO'!$C$101*'[5]Basic INFO'!$C$103),IF(AO9="EUR",AN9,AP9)))) -> 1.6252591e+11 | AQ9: 13000000000
B10: برآورد هزینه بدون سربار و مالیات بر ارزش افزوده | G10: =SUM(G8:G9) -> 6.0838575e+11 | H10: =SUM(H8:H9) -> 0 | AQ10: Total Price (Rials) | AR10: Total Price (Euros)
B11: ضریب سربار تأمین کالا | G11: 1.18 | H11: 1.18
B12: مالیات بر ارزش افزوده | G12: 0.1 | H12: 0.1
B13: هزینه تأمین کالا + سربار + مالیات بر ارزش افزوده | G13: =ROUND((G10*G11*(1+G12))/1000000,0)*1000000 -> 789685000000 | H13: =ROUND(H10*H11*(1+H12)/1000,0)*1000 -> 0
G14: =ROUND(SUMIF(AP:AP,">0",G:G)*G11*(1+G12)/1000000,0)*1000000 -> 789685000000 | H14: =ROUND(SUMIF(AP:AP,">0",H:H)*H11*(1+H12)/1000,0)*1000 -> 0

Sheet EXCHANG.
A1: Project Title: Revamping of Pazanan II Desalting Plant
A2: Sub-Project Title: Basic Design Studies and Preparation of FEED Package for Revamping of Pazanan II Desalting Plant
A3: Project Budget Ref. 03229 (formerly 53-51-91211)
A4: Doc. Title: BASIC MTO & COST ESTMATION REPORT (MECHANICAL)
A5: Doc. Ref. 91211-PZN-ME-RE-451-R02
A6: PLATE & FRAME HEAT EXCHANGERS | I6: استعلام 1 | N6: استعلام 2 | S6: استعلام 3
A7: Item No. | B7: Description | C7: Qty. (Set) | E7: GOING UNIT PRICE IRR 1404Q1 | F7: GOING UNIT PRICE FOB EUR 1404Q1 | G7: TOTAL PRICE ریال | H7: TOTAL PRICE FOB € | I7: منبع | J7: بهای واحد (ریال) | K7: بهای واحد (یورو) | L7: بهای واحد (دلار) | M7: تاریخ مرجع | N7: منبع | O7: بهای واحد (ریال) | P7: بهای واحد (یورو) | Q7: بهای واحد (دلار) | R7: تاریخ مرجع | S7: منبع | T7: بهای واحد (ریال) | U7: بهای واحد (یورو) | V7: بهای واحد (دلار) | W7: تاریخ مرجع | AH7: No. of available quotations in IRR | AI7: No. of available quotations in EUR | AJ7: No. of available quotations in USD | AK7: avg. of IRR quotations converted to EUR | AL7: avg. of EUR quotations EUR | AM7: avg. of USD quotations converted to EUR | AN7: aggregate average quoted unit price (all in EUR) | AO7: Ref. Currency | AP7: quoted unit price | AQ7: Unit Price (Rials) | AR7: Unit Price 'FOB' (€) | AS7: NEW ITEM unit price IRR | AT7: NEW ITEM unit price EUR
A8: E-111 | B8: Dilution Water / Waste Water H.E. Heat Exchanged (KW): 3155 (Dirty Cond.) Design Pressure: 15.5 Barg Design Temperature: -2.8 / 95 oC Material (Plates/Gaskets): Titanium / HNBR Design Code & Standard: API 662 & ASME VIII, DIV.1 | C8: 1 | E8: =IF(AND(AO8="IRR",SUM(AH8:AJ8)>0),AP8,IF(AND(AO8="IRR",AQ8<>""),AQ8*'[5]Basic INFO'!$E$127,IF(AO8="IRR",AS8,""))) | F8: =IF(AND(AO8="EUR",SUM(AH8:AJ8)>0),AP8,IF(AND(AO8="EUR",AR8<>""),AR8*'[5]Basic INFO'!$C$138,IF(AO8="EUR",AT8,""))) -> 38801.906 | G8: =IF(AO8="IRR",C8*E8,"") | H8: =IF(AO8="EUR",C8*F8,"") -> 38801.906 | I8: گرما گستر | M8: no reply | N8: کول سامر | R8: no reply | S8: پرگاسیران | W8: no reply | AH8: =IF(B8="","",COUNT(J8,O8,T8,Y8,AD8)) -> 0 | AI8: =IF(B8="","",COUNT(K8,P8,U8,Z8,AE8)) -> 0 | AJ8: =IF(B8="","",COUNT(L8,Q8,V8,AA8,AF8)) -> 0 | AK8: =IF(AND(AH8<>"",AH8>0),AVERAGE(J8,O8,T8,Y8,AD8)/('[5]Basic INFO'!$C$101*'[5]Basic INFO'!$C$103),"") | AL8: =IF(AND(AI8<>"",AI8>0),AVERAGE(K8,P8,U8,Z8,AE8),"") | AM8: =IF(AND(AJ8<>"",AJ8>0),AVERAGE(L8,Q8,V8,AA8,AF8)/'[5]Basic INFO'!$C$103,"") | AN8: =IF(SUM(AH8:AJ8)<>0,AVERAGE(AK8:AM8),"") | AO8: EUR | AP8: =IF(B8="","",IF(SUM(AH8:AJ8)=0,"",IF(AO8="IRR",AN8*('[5]Basic INFO'!$C$101*'[5]Basic INFO'!$C$103),IF(AO8="EUR",AN8,AP8)))) | AR8: 25000
B9: برآورد هزینه بدون سربار و مالیات بر ارزش افزوده | G9: =SUM(G8) -> 0 | H9: =SUM(H8) -> 38801.906 | AQ9: Total Price (Rials) | AR9: Total Price (Euros)
B10: ضریب سربار تأمین کالا | G10: 1.18 | H10: 1.18
B11: مالیات بر ارزش افزوده | G11: 0.1 | H11: 0.1
B12: هزینه تأمین کالا + سربار + مالیات بر ارزش افزوده | G12: =ROUND((G9*G10*(1+G11))/1000000,0)*1000000 -> 0 | H12: =ROUND(H9*H10*(1+H11)/1000,0)*1000 -> 50000
G13: =ROUND(SUMIF(AP:AP,">0",G:G)*G10*(1+G11)/1000000,0)*1000000 -> 0 | H13: =ROUND(SUMIF(AP:AP,">0",H:H)*H10*(1+H11)/1000,0)*1000 -> 0

Sheet PUMPS
A1: Project Title: Revamping of Pazanan II Desalting Plant
A2: Sub-Project Title: Basic Design Studies and Preparation of FEED Package for Revamping of Pazanan II Desalting Plant
A3: Project Budget Ref. 03229 (formerly 53-51-91211)
A4: Doc. Title: BASIC MTO & COST ESTMATION REPORT (MECHANICAL)
A5: Doc. Ref. 91211-PZN-ME-RE-451-R02
A6: PUMPS | I6: استعلام 1 | N6: استعلام 2 | S6: استعلام 3 | X6: استعلام 4 | AC6: استعلام 5
A7: Item No. | B7: Description | C7: Qty. (Set) | E7: GOING UNIT PRICE IRR 1404Q1 | F7: GOING UNIT PRICE FOB EUR 1404Q1 | G7: TOTAL PRICE ریال | H7: TOTAL PRICE FOB € | I7: منبع | J7: بهای واحد (ریال) | K7: بهای واحد (یورو) | L7: بهای واحد (دلار) | M7: تاریخ مرجع | N7: منبع | O7: بهای واحد (ریال) | P7: بهای واحد (یورو) | Q7: بهای واحد (دلار) | R7: تاریخ مرجع | S7: منبع | T7: بهای واحد (ریال) | U7: بهای واحد (یورو) | V7: بهای واحد (دلار) | W7: تاریخ مرجع | X7: منبع | Y7: بهای واحد (ریال) | Z7: بهای واحد (یورو) | AA7: بهای واحد (دلار) | AB7: تاریخ مرجع | AC7: منبع | AD7: بهای واحد (ریال) | AE7: بهای واحد (یورو) | AF7: بهای واحد (دلار) | AG7: تاریخ مرجع | AH7: No. of available quotations in IRR | AI7: No. of available quotations in EUR | AJ7: No. of available quotations in USD | AK7: avg. of IRR quotations converted to EUR | AL7: avg. of EUR quotations EUR | AM7: avg. of USD quotations converted to EUR | AN7: aggregate average quoted unit price (all in EUR) | AO7: Ref. Currency | AP7: quoted unit price | AQ7: Unit Price (Rials) | AR7: Unit Price 'FOB' (€) | AS7: NEW ITEM unit price IRR | AT7: NEW ITEM unit price EUR
A8: P-111 A/B | B8: Off Spec. Crude Pumps Type: Centrifugal (VS6) Rated Flow (m3/hr): 45 Differential Head (m): 139.1 Discharge Pressure (Barg): 14.5 Material Class(Acc. to API 610): D1 NACE 'MR-0175' Required: Yes Design Code & Standard: API 610 & IPS-G-PM-105 | C8: 2 | E8: =IF(AND(AO8="IRR",SUM(AH8:AJ8)>0),AP8,IF(AND(AO8="IRR",AQ8<>""),AQ8*'[5]Basic INFO'!$E$127,IF(AO8="IRR",AS8,""))) | F8: =IF(AND(AO8="EUR",SUM(AH8:AJ8)>0),AP8,IF(AND(AO8="EUR",AR8<>""),AR8*'[5]Basic INFO'!$C$138,IF(AO8="EUR",AT8,""))) -> 111500 | G8: =IF(AO8="IRR",C8*E8,"") | H8: =IF(AO8="EUR",C8*F8,"") -> 223000 | I8: آریا سپهر کیهان | K8: 43000 | M8: 45703 | N8: پمپیران | P8: 180000 | R8: 45781 | S8: کالای پمپ | W8: declined | X8: دالاهو پارس کیش (دمکو) | AB8: no reply | AH8: =IF(B8="","",COUNT(J8,O8,T8,Y8,AD8)) -> 0 | AI8: =IF(B8="","",COUNT(K8,P8,U8,Z8,AE8)) -> 2 | AJ8: =IF(B8="","",COUNT(L8,Q8,V8,AA8,AF8)) -> 0 | AK8: =IF(AND(AH8<>"",AH8>0),AVERAGE(J8,O8,T8,Y8,AD8)/('[5]Basic INFO'!$C$101*'[5]Basic INFO'!$C$103),"") | AL8: =IF(AND(AI8<>"",AI8>0),AVERAGE(K8,P8,U8,Z8,AE8),"") -> 111500 | AM8: =IF(AND(AJ8<>"",AJ8>0),AVERAGE(L8,Q8,V8,AA8,AF8)/'[5]Basic INFO'!$C$103,"") | AN8: =IF(SUM(AH8:AJ8)<>0,AVERAGE(AK8:AM8),"") -> 111500 | AO8: EUR | AP8: =IF(B8="","",IF(SUM(AH8:AJ8)=0,"",IF(AO8="IRR",AN8*('[5]Basic INFO'!$C$101*'[5]Basic INFO'!$C$103),IF(AO8="EUR",AN8,AP8)))) -> 111500 | AR8: 75000
A9: P-122 A/B | B9: Deaerated Water Pumps Type: Centrifugal (Horizontal) Rated Flow (m3/hr): 53 Differential Head (m): 35.7 Discharge Pressure (Barg): 2.9 Material Class(Acc. to API 610): I2 Design Code & Standard: ISO 5199 & IPS-M-PM-115 | C9: 2 | E9: =IF(AND(AO9="IRR",SUM(AH9:AJ9)>0),AP9,IF(AND(AO9="IRR",AQ9<>""),AQ9*'[5]Basic INFO'!$E$127,IF(AO9="IRR",AS9,""))) | F9: =IF(AND(AO9="EUR",SUM(AH9:AJ9)>0),AP9,IF(AND(AO9="EUR",AR9<>""),AR9*'[5]Basic INFO'!$C$138,IF(AO9="EUR",AT9,""))) -> 15050 | G9: =IF(AO9="IRR",C9*E9,"") | H9: =IF(AO9="EUR",C9*F9,"") -> 30100 | I9: آریا سپهر کیهان | K9: 14100 | M9: 45703 | N9: پمپیران | P9: 16000 | R9: 45781 | S9: کالای پمپ | W9: declined | X9: دالاهو پارس کیش (دمکو) | AB9: no reply | AH9: =IF(B9="","",COUNT(J9,O9,T9,Y9,AD9)) -> 0 | AI9: =IF(B9="","",COUNT(K9,P9,U9,Z9,AE9)) -> 2 | AJ9: =IF(B9="","",COUNT(L9,Q9,V9,AA9,AF9)) -> 0 | AK9: =IF(AND(AH9<>"",AH9>0),AVERAGE(J9,O9,T9,Y9,AD9)/('[5]Basic INFO'!$C$101*'[5]Basic INFO'!$C$103),"") | AL9: =IF(AND(AI9<>"",AI9>0),AVERAGE(K9,P9,U9,Z9,AE9),"") -> 15050 | AM9: =IF(AND(AJ9<>"",AJ9>0),AVERAGE(L9,Q9,V9,AA9,AF9)/'[5]Basic INFO'!$C$103,"") | AN9: =IF(SUM(AH9:AJ9)<>0,AVERAGE(AK9:AM9),"") -> 15050 | AO9: EUR | AP9: =IF(B9="","",IF(SUM(AH9:AJ9)=0,"",IF(AO9="IRR",AN9*('[5]Basic INFO'!$C$101*'[5]Basic INFO'!$C$103),IF(AO9="EUR",AN9,AP9)))) -> 15050 | AR9: 10000
A10: P-124 | B10: Dilution Water Pump Type: Centrifugal (OH2) Rated Flow (m3/hr): 53 Differential Head (m): 122.3 Discharge Pressure (Barg): 12 Material Class(Acc. to API 610): I2 Design Code & Standard: API 610 & IPS-G-PM-105 | C10: 1 | E10: =IF(AND(AO10="IRR",SUM(AH10:AJ10)>0),AP10,IF(AND(AO10="IRR",AQ10<>""),AQ10*'[5]Basic INFO'!$E$127,IF(AO10="IRR",AS10,""))) | F10: =IF(AND(AO10="EUR",SUM(AH10:AJ10)>0),AP10,IF(AND(AO10="EUR",AR10<>""),AR10*'[5]Basic INFO'!$C$138,IF(AO10="EUR",AT10,""))) -> 22250 | G10: =IF(AO10="IRR",C10*E10,"") | H10: =IF(AO10="EUR",C10*F10,"") -> 22250 | I10: آریا سپهر کیهان | K10: 28500 | M10: 45703 | N10: پمپیران | P10: 16000 | R10: 45781 | S10: کالای پمپ | W10: declined | X10: دالاهو پارس کیش (دمکو) | AB10: no reply | AH10: =IF(B10="","",COUNT(J10,O10,T10,Y10,AD10)) -> 0 | AI10: =IF(B10="","",COUNT(K10,P10,U10,Z10,AE10)) -> 2 | AJ10: =IF(B10="","",COUNT(L10,Q10,V10,AA10,AF10)) -> 0 | AK10: =IF(AND(AH10<>"",AH10>0),AVERAGE(J10,O10,T10,Y10,AD10)/('[5]Basic INFO'!$C$101*'[5]Basic INFO'!$C$103),"") | AL10: =IF(AND(AI10<>"",AI10>0),AVERAGE(K10,P10,U10,Z10,AE10),"") -> 22250 | AM10: =IF(AND(AJ10<>"",AJ10>0),AVERAGE(L10,Q10,V10,AA10,AF10)/'[5]Basic INFO'!$C$103,"") | AN10: =IF(SUM(AH10:AJ10)<>0,AVERAGE(AK10:AM10),"") -> 22250 | AO10: EUR | AP10: =IF(B10="","",IF(SUM(AH10:AJ10)=0,"",IF(AO10="IRR",AN10*('[5]Basic INFO'!$C$101*'[5]Basic INFO'!$C$103),IF(AO10="EUR",AN10,AP10)))) -> 22250 | AR10: 15000
A11: P-125 A/B | B11: Dilution Water Pumps Type: Centrifugal (OH2) Rated Flow (m3/hr): 31 Differential Head (m): 122 Discharge Pressure (Barg): 13 Material Class(Acc. to API 610): I2 Design Code & Standard: API 610 & IPS-G-PM-105 | C11: 2 | E11: =IF(AND(AO11="IRR",SUM(AH11:AJ11)>0),AP11,IF(AND(AO11="IRR",AQ11<>""),AQ11*'[5]Basic INFO'!$E$127,IF(AO11="IRR",AS11,""))) | F11: =IF(AND(AO11="EUR",SUM(AH11:AJ11)>0),AP11,IF(AND(AO11="EUR",AR11<>""),AR11*'[5]Basic INFO'!$C$138,IF(AO11="EUR",AT11,""))) -> 21500 | G11: =IF(AO11="IRR",C11*E11,"") | H11: =IF(AO11="EUR",C11*F11,"") -> 43000 | I11: آریا سپهر کیهان | K11: 27000 | M11: 45703 | N11: پمپیران | P11: 16000 | R11: 45781 | S11: کالای پمپ | W11: declined | X11: دالاهو پارس کیش (دمکو) | AB11: no reply | AH11: =IF(B11="","",COUNT(J11,O11,T11,Y11,AD11)) -> 0 | AI11: =IF(B11="","",COUNT(K11,P11,U11,Z11,AE11)) -> 2 | AJ11: =IF(B11="","",COUNT(L11,Q11,V11,AA11,AF11)) -> 0 | AK11: =IF(AND(AH11<>"",AH11>0),AVERAGE(J11,O11,T11,Y11,AD11)/('[5]Basic INFO'!$C$101*'[5]Basic INFO'!$C$103),"") | AL11: =IF(AND(AI11<>"",AI11>0),AVERAGE(K11,P11,U11,Z11,AE11),"") -> 21500 | AM11: =IF(AND(AJ11<>"",AJ11>0),AVERAGE(L11,Q11,V11,AA11,AF11)/'[5]Basic INFO'!$C$103,"") | AN11: =IF(SUM(AH11:AJ11)<>0,AVERAGE(AK11:AM11),"") -> 21500 | AO11: EUR | AP11: =IF(B11="","",IF(SUM(AH11:AJ11)=0,"",IF(AO11="IRR",AN11*('[5]Basic INFO'!$C$101*'[5]Basic INFO'!$C$103),IF(AO11="EUR",AN11,AP11)))) -> 21500 | AR11: 12000
A12: P-136 A/B | B12: Disposal Water InjectionPumps Type: Centrifugal (BB3) Rated Flow (m3/hr): 91 Differential Head (m): 650 Discharge Pressure (Barg): 72.8 Material Class(Acc. to API 610): D2 NACE 'MR-0175' Required: Yes Design Code & Standard: API 610 & IPS-G-PM-105 | C12: 2 | E12: =IF(AND(AO12="IRR",SUM(AH12:AJ12)>0),AP12,IF(AND(AO12="IRR",AQ12<>""),AQ12*'[5]Basic INFO'!$E$127,IF(AO12="IRR",AS12,""))) | F12: =IF(AND(AO12="EUR",SUM(AH12:AJ12)>0),AP12,IF(AND(AO12="EUR",AR12<>""),AR12*'[5]Basic INFO'!$C$138,IF(AO12="EUR",AT12,""))) -> 317500 | G12: =IF(AO12="IRR",C12*E12,"") | H12: =IF(AO12="EUR",C12*F12,"") -> 635000 | I12: آریا سپهر کیهان | K12: 335000 | M12: 45703 | N12: پمپیران | P12: 300000 | R12: 45781 | S12: کالای پمپ | W12: declined | X12: دالاهو پارس کیش (دمکو) | AB12: no reply | AH12: =IF(B12="","",COUNT(J12,O12,T12,Y12,AD12)) -> 0 | AI12: =IF(B12="","",COUNT(K12,P12,U12,Z12,AE12)) -> 2 | AJ12: =IF(B12="","",COUNT(L12,Q12,V12,AA12,AF12)) -> 0 | AK12: =IF(AND(AH12<>"",AH12>0),AVERAGE(J12,O12,T12,Y12,AD12)/('[5]Basic INFO'!$C$101*'[5]Basic INFO'!$C$103),"") | AL12: =IF(AND(AI12<>"",AI12>0),AVERAGE(K12,P12,U12,Z12,AE12),"") -> 317500 | AM12: =IF(AND(AJ12<>"",AJ12>0),AVERAGE(L12,Q12,V12,AA12,AF12)/'[5]Basic INFO'!$C$103,"") | AN12: =IF(SUM(AH12:AJ12)<>0,AVERAGE(AK12:AM12),"") -> 317500 | AO12: EUR | AP12: =IF(B12="","",IF(SUM(AH12:AJ12)=0,"",IF(AO12="IRR",AN12*('[5]Basic INFO'!$C$101*'[5]Basic INFO'!$C$103),IF(AO12="EUR",AN12,AP12)))) -> 317500 | AR12: 260000
A13: P-137 A/B | B13: Dirty Oil Pumps Type: P.D.-Rotary (Ext. Gear) Rated Flow (m3/hr): 5 Discharge Pressure (Barg): 8 Material Class(Acc. to API 610): D1 NACE 'MR-0175' Required: Yes Design Code & Standard: API 676 & IPS-M-PM-140 | C13: 2 | E13: =IF(AND(AO13="IRR",SUM(AH13:AJ13)>0),AP13,IF(AND(AO13="IRR",AQ13<>""),AQ13*'[5]Basic INFO'!$E$127,IF(AO13="IRR",AS13,""))) | F13: =IF(AND(AO13="EUR",SUM(AH13:AJ13)>0),AP13,IF(AND(AO13="EUR",AR13<>""),AR13*'[5]Basic INFO'!$C$138,IF(AO13="EUR",AT13,""))) -> 30000 | G13: =IF(AO13="IRR",C13*E13,"") | H13: =IF(AO13="EUR",C13*F13,"") -> 60000 | I13: آریا سپهر کیهان | K13: 30000 | M13: 45703 | N13: پمپیران | R13: declined | S13: کالای پمپ | W13: declined | X13: دالاهو پارس کیش (دمکو) | AB13: no reply | AH13: =IF(B13="","",COUNT(J13,O13,T13,Y13,AD13)) -> 0 | AI13: =IF(B13="","",COUNT(K13,P13,U13,Z13,AE13)) -> 1 | AJ13: =IF(B13="","",COUNT(L13,Q13,V13,AA13,AF13)) -> 0 | AK13: =IF(AND(AH13<>"",AH13>0),AVERAGE(J13,O13,T13,Y13,AD13)/('[5]Basic INFO'!$C$101*'[5]Basic INFO'!$C$103),"") | AL13: =IF(AND(AI13<>"",AI13>0),AVERAGE(K13,P13,U13,Z13,AE13),"") -> 30000 | AM13: =IF(AND(AJ13<>"",AJ13>0),AVERAGE(L13,Q13,V13,AA13,AF13)/'[5]Basic INFO'!$C$103,"") | AN13: =IF(SUM(AH13:AJ13)<>0,AVERAGE(AK13:AM13),"") -> 30000 | AO13: EUR | AP13: =IF(B13="","",IF(SUM(AH13:AJ13)=0,"",IF(AO13="IRR",AN13*('[5]Basic INFO'!$C$101*'[5]Basic INFO'!$C$103),IF(AO13="EUR",AN13,AP13)))) -> 30000 | AR13: 10000
A14: P-138 A/B | B14: Evaporation Pond Water Return Pumps Type: Centrifugal (OH2) Rated Flow (m3/hr): 15 Differential Head (m): 27 Discharge Pressure (Barg): 3.2 Material Class(Acc. to API 610): D2 Design Code & Standard: API 610 & IPS-G-PM-105 | C14: 2 | E14: =IF(AND(AO14="IRR",SUM(AH14:AJ14)>0),AP14,IF(AND(AO14="IRR",AQ14<>""),AQ14*'[5]Basic INFO'!$E$127,IF(AO14="IRR",AS14,""))) | F14: =IF(AND(AO14="EUR",SUM(AH14:AJ14)>0),AP14,IF(AND(AO14="EUR",AR14<>""),AR14*'[5]Basic INFO'!$C$138,IF(AO14="EUR",AT14,""))) -> 29000 | G14: =IF(AO14="IRR",C14*E14,"") | H14: =IF(AO14="EUR",C14*F14,"") -> 58000 | I14: آریا سپهر کیهان | K14: 28000 | M14: 45703 | N14: پمپیران | P14: 30000 | R14: 45781 | S14: کالای پمپ | W14: declined | X14: دالاهو پارس کیش (دمکو) | AB14: no reply | AH14: =IF(B14="","",COUNT(J14,O14,T14,Y14,AD14)) -> 0 | AI14: =IF(B14="","",COUNT(K14,P14,U14,Z14,AE14)) -> 2 | AJ14: =IF(B14="","",COUNT(L14,Q14,V14,AA14,AF14)) -> 0 | AK14: =IF(AND(AH14<>"",AH14>0),AVERAGE(J14,O14,T14,Y14,AD14)/('[5]Basic INFO'!$C$101*'[5]Basic INFO'!$C$103),"") | AL14: =IF(AND(AI14<>"",AI14>0),AVERAGE(K14,P14,U14,Z14,AE14),"") -> 29000 | AM14: =IF(AND(AJ14<>"",AJ14>0),AVERAGE(L14,Q14,V14,AA14,AF14)/'[5]Basic INFO'!$C$103,"") | AN14: =IF(SUM(AH14:AJ14)<>0,AVERAGE(AK14:AM14),"") -> 29000 | AO14: EUR | AP14: =IF(B14="","",IF(SUM(AH14:AJ14)=0,"",IF(AO14="IRR",AN14*('[5]Basic INFO'!$C$101*'[5]Basic INFO'!$C$103),IF(AO14="EUR",AN14,AP14)))) -> 29000 | AR14: 35000
A15: P-139 A/B/C | B15: Disposal Water InjectionPumps Type: Centrifugal (BB3) Rated Flow (m3/hr): 44 Differential Head (m): 385 Discharge Pressure (Barg): 48.2 Material Class(Acc. to API 610): D2 NACE 'MR-0175' Required: Yes Design Code & Standard: API 610 & IPS-G-PM-105 | C15: 3 | E15: =IF(AND(AO15="IRR",SUM(AH15:AJ15)>0),AP15,IF(AND(AO15="IRR",AQ15<>""),AQ15*'[5]Basic INFO'!$E$127,IF(AO15="IRR",AS15,""))) | F15: =IF(AND(AO15="EUR",SUM(AH15:AJ15)>0),AP15,IF(AND(AO15="EUR",AR15<>""),AR15*'[5]Basic INFO'!$C$138,IF(AO15="EUR",AT15,""))) -> 247500 | G15: =IF(AO15="IRR",C15*E15,"") | H15: =IF(AO15="EUR",C15*F15,"") -> 742500 | I15: آریا سپهر کیهان | K15: 225000 | M15: 45703 | N15: پمپیران | P15: 270000 | R15: 45781 | S15: کالای پمپ | W15: declined | X15: دالاهو پارس کیش (دمکو) | AB15: no reply | AH15: =IF(B15="","",COUNT(J15,O15,T15,Y15,AD15)) -> 0 | AI15: =IF(B15="","",COUNT(K15,P15,U15,Z15,AE15)) -> 2 | AJ15: =IF(B15="","",COUNT(L15,Q15,V15,AA15,AF15)) -> 0 | AK15: =IF(AND(AH15<>"",AH15>0),AVERAGE(J15,O15,T15,Y15,AD15)/('[5]Basic INFO'!$C$101*'[5]Basic INFO'!$C$103),"") | AL15: =IF(AND(AI15<>"",AI15>0),AVERAGE(K15,P15,U15,Z15,AE15),"") -> 247500 | AM15: =IF(AND(AJ15<>"",AJ15>0),AVERAGE(L15,Q15,V15,AA15,AF15)/'[5]Basic INFO'!$C$103,"") | AN15: =IF(SUM(AH15:AJ15)<>0,AVERAGE(AK15:AM15),"") -> 247500 | AO15: EUR | AP15: =IF(B15="","",IF(SUM(AH15:AJ15)=0,"",IF(AO15="IRR",AN15*('[5]Basic INFO'!$C$101*'[5]Basic INFO'!$C$103),IF(AO15="EUR",AN15,AP15)))) -> 247500 | AR15: 180000
A16: P-151 A/B | B16: Flare K.O. Drum Pumps Type: Centrifugal (OH2) Rated Flow (m3/hr): 10 Differential Head (m): 40 Discharge Pressure (Barg): 6.8 Material Class(Acc. to API 610): S6 Design Code & Standard: API 610 & IPS-G-PM-105 | C16: 2 | E16: =IF(AND(AO16="IRR",SUM(AH16:AJ16)>0),AP16,IF(AND(AO16="IRR",AQ16<>""),AQ16*'[5]Basic INFO'!$E$127,IF(AO16="IRR",AS16,""))) | F16: =IF(AND(AO16="EUR",SUM(AH16:AJ16)>0),AP16,IF(AND(AO16="EUR",AR16<>""),AR16*'[5]Basic INFO'!$C$138,IF(AO16="EUR",AT16,""))) -> 25500 | G16: =IF(AO16="IRR",C16*E16,"") | H16: =IF(AO16="EUR",C16*F16,"") -> 51000 | I16: آریا سپهر کیهان | K16: 21000 | M16: 45703 | N16: پمپیران | P16: 30000 | R16: 45781 | S16: کالای پمپ | W16: declined | X16: دالاهو پارس کیش (دمکو) | AB16: no reply | AH16: =IF(B16="","",COUNT(J16,O16,T16,Y16,AD16)) -> 0 | AI16: =IF(B16="","",COUNT(K16,P16,U16,Z16,AE16)) -> 2 | AJ16: =IF(B16="","",COUNT(L16,Q16,V16,AA16,AF16)) -> 0 | AK16: =IF(AND(AH16<>"",AH16>0),AVERAGE(J16,O16,T16,Y16,AD16)/('[5]Basic INFO'!$C$101*'[5]Basic INFO'!$C$103),"") | AL16: =IF(AND(AI16<>"",AI16>0),AVERAGE(K16,P16,U16,Z16,AE16),"") -> 25500 | AM16: =IF(AND(AJ16<>"",AJ16>0),AVERAGE(L16,Q16,V16,AA16,AF16)/'[5]Basic INFO'!$C$103,"") | AN16: =IF(SUM(AH16:AJ16)<>0,AVERAGE(AK16:AM16),"") -> 25500 | AO16: EUR | AP16: =IF(B16="","",IF(SUM(AH16:AJ16)=0,"",IF(AO16="IRR",AN16*('[5]Basic INFO'!$C$101*'[5]Basic INFO'!$C$103),IF(AO16="EUR",AN16,AP16)))) -> 25500 | AR16: 15000
A17: P-161 A/B | B17: Closed Drain Drum Pumps Type: Centrifugal (OH2) Rated Flow (m3/hr): 25 Differential Head (m): 55 Discharge Pressure (Barg): 5 Material Class(Acc. to API 610): D2 NACE 'MR-0175' Required: Yes Design Code & Standard: API 610 & IPS-G-PM-105 | C17: 2 | E17: =IF(AND(AO17="IRR",SUM(AH17:AJ17)>0),AP17,IF(AND(AO17="IRR",AQ17<>""),AQ17*'[5]Basic INFO'!$E$127,IF(AO17="IRR",AS17,""))) | F17: =IF(AND(AO17="EUR",SUM(AH17:AJ17)>0),AP17,IF(AND(AO17="EUR",AR17<>""),AR17*'[5]Basic INFO'!$C$138,IF(AO17="EUR",AT17,""))) -> 31000 | G17: =IF(AO17="IRR",C17*E17,"") | H17: =IF(AO17="EUR",C17*F17,"") -> 62000 | I17: آریا سپهر کیهان | K17: 32000 | M17: 45703 | N17: پمپیران | P17: 30000 | R17: 45781 | S17: کالای پمپ | W17: declined | X17: دالاهو پارس کیش (دمکو) | AB17: no reply | AH17: =IF(B17="","",COUNT(J17,O17,T17,Y17,AD17)) -> 0 | AI17: =IF(B17="","",COUNT(K17,P17,U17,Z17,AE17)) -> 2 | AJ17: =IF(B17="","",COUNT(L17,Q17,V17,AA17,AF17)) -> 0 | AK17: =IF(AND(AH17<>"",AH17>0),AVERAGE(J17,O17,T17,Y17,AD17)/('[5]Basic INFO'!$C$101*'[5]Basic INFO'!$C$103),"") | AL17: =IF(AND(AI17<>"",AI17>0),AVERAGE(K17,P17,U17,Z17,AE17),"") -> 31000 | AM17: =IF(AND(AJ17<>"",AJ17>0),AVERAGE(L17,Q17,V17,AA17,AF17)/'[5]Basic INFO'!$C$103,"") | AN17: =IF(SUM(AH17:AJ17)<>0,AVERAGE(AK17:AM17),"") -> 31000 | AO17: EUR | AP17: =IF(B17="","",IF(SUM(AH17:AJ17)=0,"",IF(AO17="IRR",AN17*('[5]Basic INFO'!$C$101*'[5]Basic INFO'!$C$103),IF(AO17="EUR",AN17,AP17)))) -> 31000 | AR17: 32000
A18: P-162 | B18: C. D. Drum / Flare K.O. Drum Sump Pump Type: Centrifugal (VS4) Rated Flow (m3/hr): 5 Differential Head (m): 21.4 Discharge Pressure (Barg): 2 Material Class(Acc. to API 610): S6 Design Code & Standard: API 610 & IPS-G-PM-105 | C18: 1 | E18: =IF(AND(AO18="IRR",SUM(AH18:AJ18)>0),AP18,IF(AND(AO18="IRR",AQ18<>""),AQ18*'[5]Basic INFO'!$E$127,IF(AO18="IRR",AS18,""))) | F18: =IF(AND(AO18="EUR",SUM(AH18:AJ18)>0),AP18,IF(AND(AO18="EUR",AR18<>""),AR18*'[5]Basic INFO'!$C$138,IF(AO18="EUR",AT18,""))) -> 34500 | G18: =IF(AO18="IRR",C18*E18,"") | H18: =IF(AO18="EUR",C18*F18,"") -> 34500 | I18: آریا سپهر کیهان | K18: 24000 | M18: 45703 | N18: پمپیران | P18: 45000 | R18: 45781 | S18: کالای پمپ | W18: declined | X18: دالاهو پارس کیش (دمکو) | AB18: no reply | AH18: =IF(B18="","",COUNT(J18,O18,T18,Y18,AD18)) -> 0 | AI18: =IF(B18="","",COUNT(K18,P18,U18,Z18,AE18)) -> 2 | AJ18: =IF(B18="","",COUNT(L18,Q18,V18,AA18,AF18)) -> 0 | AK18: =IF(AND(AH18<>"",AH18>0),AVERAGE(J18,O18,T18,Y18,AD18)/('[5]Basic INFO'!$C$101*'[5]Basic INFO'!$C$103),"") | AL18: =IF(AND(AI18<>"",AI18>0),AVERAGE(K18,P18,U18,Z18,AE18),"") -> 34500 | AM18: =IF(AND(AJ18<>"",AJ18>0),AVERAGE(L18,Q18,V18,AA18,AF18)/'[5]Basic INFO'!$C$103,"") | AN18: =IF(SUM(AH18:AJ18)<>0,AVERAGE(AK18:AM18),"") -> 34500 | AO18: EUR | AP18: =IF(B18="","",IF(SUM(AH18:AJ18)=0,"",IF(AO18="IRR",AN18*('[5]Basic INFO'!$C$101*'[5]Basic INFO'!$C$103),IF(AO18="EUR",AN18,AP18)))) -> 34500 | AR18: 15000
A19: P-163 A/B | B19: O.W.S. Oil Pumps Type: P.D.-Rotary (Progressing Cavity) Rated Flow (m3/hr): 5 Discharge Pressure (Barg): 6.4 Material Class(Acc. to API 610): D1 NACE 'MR-0175' Required: Yes Design Code & Standard: API 676 & IPS-M-PM-140 | C19: 2 | E19: =IF(AND(AO19="IRR",SUM(AH19:AJ19)>0),AP19,IF(AND(AO19="IRR",AQ19<>""),AQ19*'[5]Basic INFO'!$E$127,IF(AO19="IRR",AS19,""))) | F19: =IF(AND(AO19="EUR",SUM(AH19:AJ19)>0),AP19,IF(AND(AO19="EUR",AR19<>""),AR19*'[5]Basic INFO'!$C$138,IF(AO19="EUR",AT19,""))) -> 38801.906 | G19: =IF(AO19="IRR",C19*E19,"") | H19: =IF(AO19="EUR",C19*F19,"") -> 77603.812 | I19: آریا سپهر کیهان | M19: declined | N19: پمپیران | R19: declined | S19: کالای پمپ | W19: declined | X19: دالاهو پارس کیش (دمکو) | AB19: no reply | AH19: =IF(B19="","",COUNT(J19,O19,T19,Y19,AD19)) -> 0 | AI19: =IF(B19="","",COUNT(K19,P19,U19,Z19,AE19)) -> 0 | AJ19: =IF(B19="","",COUNT(L19,Q19,V19,AA19,AF19)) -> 0 | AK19: =IF(AND(AH19<>"",AH19>0),AVERAGE(J19,O19,T19,Y19,AD19)/('[5]Basic INFO'!$C$101*'[5]Basic INFO'!$C$103),"") | AL19: =IF(AND(AI19<>"",AI19>0),AVERAGE(K19,P19,U19,Z19,AE19),"") | AM19: =IF(AND(AJ19<>"",AJ19>0),AVERAGE(L19,Q19,V19,AA19,AF19)/'[5]Basic INFO'!$C$103,"") | AN19: =IF(SUM(AH19:AJ19)<>0,AVERAGE(AK19:AM19),"") | AO19: EUR | AP19: =IF(B19="","",IF(SUM(AH19:AJ19)=0,"",IF(AO19="IRR",AN19*('[5]Basic INFO'!$C$101*'[5]Basic INFO'!$C$103),IF(AO19="EUR",AN19,AP19)))) | AR19: 25000
A20: P-164 A/B | B20: O.W.S. Water Pumps Type: Centrifugal (OH2) Rated Flow (m3/hr): 15 Differential Head (m): 50 Discharge Pressure (Barg): 5.7 Material Class(Acc. to API 610): D2 NACE 'MR-0175' Required: Yes Design Code & Standard: API 610 & IPS-G-PM-105 | C20: 2 | E20: =IF(AND(AO20="IRR",SUM(AH20:AJ20)>0),AP20,IF(AND(AO20="IRR",AQ20<>""),AQ20*'[5]Basic INFO'!$E$127,IF(AO20="IRR",AS20,""))) | F20: =IF(AND(AO20="EUR",SUM(AH20:AJ20)>0),AP20,IF(AND(AO20="EUR",AR20<>""),AR20*'[5]Basic INFO'!$C$138,IF(AO20="EUR",AT20,""))) -> 29600 | G20: =IF(AO20="IRR",C20*E20,"") | H20: =IF(AO20="EUR",C20*F20,"") -> 59200 | I20: آریا سپهر کیهان | K20: 29200 | M20: 45703 | N20: پمپیران | P20: 30000 | R20: 45781 | S20: کالای پمپ | W20: declined | X20: دالاهو پارس کیش (دمکو) | AB20: no reply | AH20: =IF(B20="","",COUNT(J20,O20,T20,Y20,AD20)) -> 0 | AI20: =IF(B20="","",COUNT(K20,P20,U20,Z20,AE20)) -> 2 | AJ20: =IF(B20="","",COUNT(L20,Q20,V20,AA20,AF20)) -> 0 | AK20: =IF(AND(AH20<>"",AH20>0),AVERAGE(J20,O20,T20,Y20,AD20)/('[5]Basic INFO'!$C$101*'[5]Basic INFO'!$C$103),"") | AL20: =IF(AND(AI20<>"",AI20>0),AVERAGE(K20,P20,U20,Z20,AE20),"") -> 29600 | AM20: =IF(AND(AJ20<>"",AJ20>0),AVERAGE(L20,Q20,V20,AA20,AF20)/'[5]Basic INFO'!$C$103,"") | AN20: =IF(SUM(AH20:AJ20)<>0,AVERAGE(AK20:AM20),"") -> 29600 | AO20: EUR | AP20: =IF(B20="","",IF(SUM(AH20:AJ20)=0,"",IF(AO20="IRR",AN20*('[5]Basic INFO'!$C$101*'[5]Basic INFO'!$C$103),IF(AO20="EUR",AN20,AP20)))) -> 29600 | AR20: 15000
A21: P-165 A/B | B21: Oily Water Basin Pumps Type: Centrifugal (OH2) Rated Flow (m3/hr): 15 Differential Head (m): 20 Discharge Pressure (Barg): 2.5 Material Class(Acc. to API 610): S6 Design Code & Standard: API 610 & IPS-G-PM-105 | C21: 2 | E21: =IF(AND(AO21="IRR",SUM(AH21:AJ21)>0),AP21,IF(AND(AO21="IRR",AQ21<>""),AQ21*'[5]Basic INFO'!$E$127,IF(AO21="IRR",AS21,""))) | F21: =IF(AND(AO21="EUR",SUM(AH21:AJ21)>0),AP21,IF(AND(AO21="EUR",AR21<>""),AR21*'[5]Basic INFO'!$C$138,IF(AO21="EUR",AT21,""))) -> 26250 | G21: =IF(AO21="IRR",C21*E21,"") | H21: =IF(AO21="EUR",C21*F21,"") -> 52500 | I21: آریا سپهر کیهان | K21: 22500 | M21: 45703 | N21: پمپیران | P21: 30000 | R21: 45781 | S21: کالای پمپ | W21: declined | X21: دالاهو پارس کیش (دمکو) | AB21: no reply | AH21: =IF(B21="","",COUNT(J21,O21,T21,Y21,AD21)) -> 0 | AI21: =IF(B21="","",COUNT(K21,P21,U21,Z21,AE21)) -> 2 | AJ21: =IF(B21="","",COUNT(L21,Q21,V21,AA21,AF21)) -> 0 | AK21: =IF(AND(AH21<>"",AH21>0),AVERAGE(J21,O21,T21,Y21,AD21)/('[5]Basic INFO'!$C$101*'[5]Basic INFO'!$C$103),"") | AL21: =IF(AND(AI21<>"",AI21>0),AVERAGE(K21,P21,U21,Z21,AE21),"") -> 26250 | AM21: =IF(AND(AJ21<>"",AJ21>0),AVERAGE(L21,Q21,V21,AA21,AF21)/'[5]Basic INFO'!$C$103,"") | AN21: =IF(SUM(AH21:AJ21)<>0,AVERAGE(AK21:AM21),"") -> 26250 | AO21: EUR | AP21: =IF(B21="","",IF(SUM(AH21:AJ21)=0,"",IF(AO21="IRR",AN21*('[5]Basic INFO'!$C$101*'[5]Basic INFO'!$C$103),IF(AO21="EUR",AN21,AP21)))) -> 26250 | AR21: 15000
A22: P-171 | B22: Fuel Oil Pump Type: Centrifugal (Horizontal) Rated Flow (m3/hr): 10 Differential Head (m): 21 Discharge Pressure (Barg): 2 Material Class(Acc. to API 610): S1 Design Code & Standard: ISO 5199 & IPS-M-PM-115 | C22: 1 | E22: =IF(AND(AO22="IRR",SUM(AH22:AJ22)>0),AP22,IF(AND(AO22="IRR",AQ22<>""),AQ22*'[5]Basic INFO'!$E$127,IF(AO22="IRR",AS22,""))) | F22: =IF(AND(AO22="EUR",SUM(AH22:AJ22)>0),AP22,IF(AND(AO22="EUR",AR22<>""),AR22*'[5]Basic INFO'!$C$138,IF(AO22="EUR",AT22,""))) -> 21000 | G22: =IF(AO22="IRR",C22*E22,"") | H22: =IF(AO22="EUR",C22*F22,"") -> 21000 | I22: آریا سپهر کیهان | K22: 12000 | M22: 45703 | N22: پمپیران | P22: 30000 | R22: 45781 | S22: کالای پمپ | W22: declined | X22: دالاهو پارس کیش (دمکو) | AB22: no reply | AH22: =IF(B22="","",COUNT(J22,O22,T22,Y22,AD22)) -> 0 | AI22: =IF(B22="","",COUNT(K22,P22,U22,Z22,AE22)) -> 2 | AJ22: =IF(B22="","",COUNT(L22,Q22,V22,AA22,AF22)) -> 0 | AK22: =IF(AND(AH22<>"",AH22>0),AVERAGE(J22,O22,T22,Y22,AD22)/('[5]Basic INFO'!$C$101*'[5]Basic INFO'!$C$103),"") | AL22: =IF(AND(AI22<>"",AI22>0),AVERAGE(K22,P22,U22,Z22,AE22),"") -> 21000 | AM22: =IF(AND(AJ22<>"",AJ22>0),AVERAGE(L22,Q22,V22,AA22,AF22)/'[5]Basic INFO'!$C$103,"") | AN22: =IF(SUM(AH22:AJ22)<>0,AVERAGE(AK22:AM22),"") -> 21000 | AO22: EUR | AP22: =IF(B22="","",IF(SUM(AH22:AJ22)=0,"",IF(AO22="IRR",AN22*('[5]Basic INFO'!$C$101*'[5]Basic INFO'!$C$103),IF(AO22="EUR",AN22,AP22)))) -> 21000 | AR22: 10000
A23: P-191 | B23: Fire Water Loading Pump Type: Centrifugal (Horizontal) Rated Flow (m3/hr): 33 Differential Head (m): 31 Discharge Pressure (Barg): 2.9 Material Class(Acc. to API 610): I2 Design Code & Standard: ISO 5199 & IPS-M-PM-115 | C23: 1 | E23: =IF(AND(AO23="IRR",SUM(AH23:AJ23)>0),AP23,IF(AND(AO23="IRR",AQ23<>""),AQ23*'[5]Basic INFO'!$E$127,IF(AO23="IRR",AS23,""))) | F23: =IF(AND(AO23="EUR",SUM(AH23:AJ23)>0),AP23,IF(AND(AO23="EUR",AR23<>""),AR23*'[5]Basic INFO'!$C$138,IF(AO23="EUR",AT23,""))) -> 16000 | G23: =IF(AO23="IRR",C23*E23,"") | H23: =IF(AO23="EUR",C23*F23,"") -> 16000 | I23: آریا سپهر کیهان | K23: 19000 | M23: 45703 | N23: پمپیران | P23: 13000 | R23: 45781 | S23: کالای پمپ | W23: declined | X23: دالاهو پارس کیش (دمکو) | AB23: no reply | AH23: =IF(B23="","",COUNT(J23,O23,T23,Y23,AD23)) -> 0 | AI23: =IF(B23="","",COUNT(K23,P23,U23,Z23,AE23)) -> 2 | AJ23: =IF(B23="","",COUNT(L23,Q23,V23,AA23,AF23)) -> 0 | AK23: =IF(AND(AH23<>"",AH23>0),AVERAGE(J23,O23,T23,Y23,AD23)/('[5]Basic INFO'!$C$101*'[5]Basic INFO'!$C$103),"") | AL23: =IF(AND(AI23<>"",AI23>0),AVERAGE(K23,P23,U23,Z23,AE23),"") -> 16000 | AM23: =IF(AND(AJ23<>"",AJ23>0),AVERAGE(L23,Q23,V23,AA23,AF23)/'[5]Basic INFO'!$C$103,"") | AN23: =IF(SUM(AH23:AJ23)<>0,AVERAGE(AK23:AM23),"") -> 16000 | AO23: EUR | AP23: =IF(B23="","",IF(SUM(AH23:AJ23)=0,"",IF(AO23="IRR",AN23*('[5]Basic INFO'!$C$101*'[5]Basic INFO'!$C$103),IF(AO23="EUR",AN23,AP23)))) -> 16000 | AR23: 6500
A24: P-192 | B24: Fire Water Pump-Elect. Motor Driven Type: Centrifugal (Horizontal, Impeller Between Bearings Design) Rated Flow (m3/hr): 825 Differential Head (m): 107 Discharge Pressure (Barg): 11.3 Material Class(Acc. to API 610): I2 Design Code & Standard: NFPA 20 & IPS-M-PM-125 | C24: 1 | E24: =IF(AND(AO24="IRR",SUM(AH24:AJ24)>0),AP24,IF(AND(AO24="IRR",AQ24<>""),AQ24*'[5]Basic INFO'!$E$127,IF(AO24="IRR",AS24,""))) | F24: =IF(AND(AO24="EUR",SUM(AH24:AJ24)>0),AP24,IF(AND(AO24="EUR",AR24<>""),AR24*'[5]Basic INFO'!$C$138,IF(AO24="EUR",AT24,""))) -> 309660.11 | G24: =IF(AO24="IRR",C24*E24,"") | H24: =IF(AO24="EUR",C24*F24,"") -> 309660.11 | I24: آریا سپهر کیهان | K24: 200000 | M24: 45703 | N24: پمپیران | P24: 30000 | R24: 45781 | S24: کالای پمپ | U24: 698980.33 | W24: 45709 | X24: دالاهو پارس کیش (دمکو) | AB24: no reply | AH24: =IF(B24="","",COUNT(J24,O24,T24,Y24,AD24)) -> 0 | AI24: =IF(B24="","",COUNT(K24,P24,U24,Z24,AE24)) -> 3 | AJ24: =IF(B24="","",COUNT(L24,Q24,V24,AA24,AF24)) -> 0 | AK24: =IF(AND(AH24<>"",AH24>0),AVERAGE(J24,O24,T24,Y24,AD24)/('[5]Basic INFO'!$C$101*'[5]Basic INFO'!$C$103),"") | AL24: =IF(AND(AI24<>"",AI24>0),AVERAGE(K24,P24,U24,Z24,AE24),"") -> 309660.11 | AM24: =IF(AND(AJ24<>"",AJ24>0),AVERAGE(L24,Q24,V24,AA24,AF24)/'[5]Basic INFO'!$C$103,"") | AN24: =IF(SUM(AH24:AJ24)<>0,AVERAGE(AK24:AM24),"") -> 309660.11 | AO24: EUR | AP24: =IF(B24="","",IF(SUM(AH24:AJ24)=0,"",IF(AO24="IRR",AN24*('[5]Basic INFO'!$C$101*'[5]Basic INFO'!$C$103),IF(AO24="EUR",AN24,AP24)))) -> 309660.11 | AR24: 80000
A25: P-193 | B25: Fire Water Pump-Diesel Engine Driven Type: Centrifugal (Horizontal, Impeller Between Bearings Design) Rated Flow (m3/hr): 825 Differential Head (m): 107 Discharge Pressure (Barg): 11.3 Material Class(Acc. to API 610): I2 Design Code & Standard: NFPA 20 & IPS-M-PM-125 | C25: 1 | E25: =IF(AND(AO25="IRR",SUM(AH25:AJ25)>0),AP25,IF(AND(AO25="IRR",AQ25<>""),AQ25*'[5]Basic INFO'!$E$127,IF(AO25="IRR",AS25,""))) | F25: =IF(AND(AO25="EUR",SUM(AH25:AJ25)>0),AP25,IF(AND(AO25="EUR",AR25<>""),AR25*'[5]Basic INFO'!$C$138,IF(AO25="EUR",AT25,""))) -> 202973.76 | G25: =IF(AO25="IRR",C25*E25,"") | H25: =IF(AO25="EUR",C25*F25,"") -> 202973.76 | I25: آریا سپهر کیهان | K25: 225000 | M25: 45703 | N25: پمپیران | P25: 120000 | R25: 45781 | S25: کالای پمپ | U25: 263921.27 | W25: 45709 | X25: دالاهو پارس کیش (دمکو) | AB25: no reply | AH25: =IF(B25="","",COUNT(J25,O25,T25,Y25,AD25)) -> 0 | AI25: =IF(B25="","",COUNT(K25,P25,U25,Z25,AE25)) -> 3 | AJ25: =IF(B25="","",COUNT(L25,Q25,V25,AA25,AF25)) -> 0 | AK25: =IF(AND(AH25<>"",AH25>0),AVERAGE(J25,O25,T25,Y25,AD25)/('[5]Basic INFO'!$C$101*'[5]Basic INFO'!$C$103),"") | AL25: =IF(AND(AI25<>"",AI25>0),AVERAGE(K25,P25,U25,Z25,AE25),"") -> 202973.76 | AM25: =IF(AND(AJ25<>"",AJ25>0),AVERAGE(L25,Q25,V25,AA25,AF25)/'[5]Basic INFO'!$C$103,"") | AN25: =IF(SUM(AH25:AJ25)<>0,AVERAGE(AK25:AM25),"") -> 202973.76 | AO25: EUR | AP25: =IF(B25="","",IF(SUM(AH25:AJ25)=0,"",IF(AO25="IRR",AN25*('[5]Basic INFO'!$C$101*'[5]Basic INFO'!$C$103),IF(AO25="EUR",AN25,AP25)))) -> 202973.76 | AR25: 100000
A26: P-194 A/B | B26: Fire Water Jockey Pumps Type: Centrifugal (Horizontal, Overhung Impeller Design) Rated Flow (m3/hr): 16.5 Differential Head (m): 107 Discharge Pressure (Barg): 11.3 Material Class(Acc. to API 610): I2 Design Code & Standard: NFPA 20 & IPS-M-PM-125 | C26: 2 | E26: =IF(AND(AO26="IRR",SUM(AH26:AJ26)>0),AP26,IF(AND(AO26="IRR",AQ26<>""),AQ26*'[5]Basic INFO'!$E$127,IF(AO26="IRR",AS26,""))) | F26: =IF(AND(AO26="EUR",SUM(AH26:AJ26)>0),AP26,IF(AND(AO26="EUR",AR26<>""),AR26*'[5]Basic INFO'!$C$138,IF(AO26="EUR",AT26,""))) -> 26808.067 | G26: =IF(AO26="IRR",C26*E26,"") | H26: =IF(AO26="EUR",C26*F26,"") -> 53616.133 | I26: آریا سپهر کیهان | K26: 19000 | M26: 45703 | N26: پمپیران | P26: 21000 | R26: 45781 | S26: کالای پمپ | U26: 40424.2 | W26: 45709 | X26: دالاهو پارس کیش (دمکو) | AB26: no reply | AH26: =IF(B26="","",COUNT(J26,O26,T26,Y26,AD26)) -> 0 | AI26: =IF(B26="","",COUNT(K26,P26,U26,Z26,AE26)) -> 3 | AJ26: =IF(B26="","",COUNT(L26,Q26,V26,AA26,AF26)) -> 0 | AK26: =IF(AND(AH26<>"",AH26>0),AVERAGE(J26,O26,T26,Y26,AD26)/('[5]Basic INFO'!$C$101*'[5]Basic INFO'!$C$103),"") | AL26: =IF(AND(AI26<>"",AI26>0),AVERAGE(K26,P26,U26,Z26,AE26),"") -> 26808.067 | AM26: =IF(AND(AJ26<>"",AJ26>0),AVERAGE(L26,Q26,V26,AA26,AF26)/'[5]Basic INFO'!$C$103,"") | AN26: =IF(SUM(AH26:AJ26)<>0,AVERAGE(AK26:AM26),"") -> 26808.067 | AO26: EUR | AP26: =IF(B26="","",IF(SUM(AH26:AJ26)=0,"",IF(AO26="IRR",AN26*('[5]Basic INFO'!$C$101*'[5]Basic INFO'!$C$103),IF(AO26="EUR",AN26,AP26)))) -> 26808.067 | AR26: 15000
A27: P-210 A/B | B27: Chemical Loading Pumps Type: Portable Barrel Pump Rated Flow (Lit/min): 160 Differential Pressure (Bar): 2 Material: S.S. 316 L | C27: 2 | E27: =IF(AND(AO27="IRR",SUM(AH27:AJ27)>0),AP27,IF(AND(AO27="IRR",AQ27<>""),AQ27*'[5]Basic INFO'!$E$127,IF(AO27="IRR",AS27,""))) -> 1.6259615e+09 | F27: =IF(AND(AO27="EUR",SUM(AH27:AJ27)>0),AP27,IF(AND(AO27="EUR",AR27<>""),AR27*'[5]Basic INFO'!$C$138,IF(AO27="EUR",AT27,""))) | G27: =IF(AO27="IRR",C27*E27,"") -> 3.2519231e+09 | H27: =IF(AO27="EUR",C27*F27,"") | I27: آریا سپهر کیهان | M27: declined | N27: پمپیران | R27: declined | S27: کالای پمپ | W27: declined | X27: دالاهو پارس کیش (دمکو) | AB27: no reply | AH27: =IF(B27="","",COUNT(J27,O27,T27,Y27,AD27)) -> 0 | AI27: =IF(B27="","",COUNT(K27,P27,U27,Z27,AE27)) -> 0 | AJ27: =IF(B27="","",COUNT(L27,Q27,V27,AA27,AF27)) -> 0 | AK27: =IF(AND(AH27<>"",AH27>0),AVERAGE(J27,O27,T27,Y27,AD27)/('[5]Basic INFO'!$C$101*'[5]Basic INFO'!$C$103),"") | AL27: =IF(AND(AI27<>"",AI27>0),AVERAGE(K27,P27,U27,Z27,AE27),"") | AM27: =IF(AND(AJ27<>"",AJ27>0),AVERAGE(L27,Q27,V27,AA27,AF27)/'[5]Basic INFO'!$C$103,"") | AN27: =IF(SUM(AH27:AJ27)<>0,AVERAGE(AK27:AM27),"") | AO27: IRR | AP27: =IF(B27="","",IF(SUM(AH27:AJ27)=0,"",IF(AO27="IRR",AN27*('[5]Basic INFO'!$C$101*'[5]Basic INFO'!$C$103),IF(AO27="EUR",AN27,AP27)))) | AQ27: 100000000
A28: P-211 | B28: Chemical Loading Pumps Type: Portable Barrel Pump Rated Flow (Lit/min): 160 Differential Pressure (Bar): 2 Material: S.S. 316 L | C28: 1 | E28: =IF(AND(AO28="IRR",SUM(AH28:AJ28)>0),AP28,IF(AND(AO28="IRR",AQ28<>""),AQ28*'[5]Basic INFO'!$E$127,IF(AO28="IRR",AS28,""))) -> 1.6259615e+09 | F28: =IF(AND(AO28="EUR",SUM(AH28:AJ28)>0),AP28,IF(AND(AO28="EUR",AR28<>""),AR28*'[5]Basic INFO'!$C$138,IF(AO28="EUR",AT28,""))) | G28: =IF(AO28="IRR",C28*E28,"") -> 1.6259615e+09 | H28: =IF(AO28="EUR",C28*F28,"") | I28: آریا سپهر کیهان | M28: declined | N28: پمپیران | R28: declined | S28: کالای پمپ | W28: declined | X28: دالاهو پارس کیش (دمکو) | AB28: no reply | AH28: =IF(B28="","",COUNT(J28,O28,T28,Y28,AD28)) -> 0 | AI28: =IF(B28="","",COUNT(K28,P28,U28,Z28,AE28)) -> 0 | AJ28: =IF(B28="","",COUNT(L28,Q28,V28,AA28,AF28)) -> 0 | AK28: =IF(AND(AH28<>"",AH28>0),AVERAGE(J28,O28,T28,Y28,AD28)/('[5]Basic INFO'!$C$101*'[5]Basic INFO'!$C$103),"") | AL28: =IF(AND(AI28<>"",AI28>0),AVERAGE(K28,P28,U28,Z28,AE28),"") | AM28: =IF(AND(AJ28<>"",AJ28>0),AVERAGE(L28,Q28,V28,AA28,AF28)/'[5]Basic INFO'!$C$103,"") | AN28: =IF(SUM(AH28:AJ28)<>0,AVERAGE(AK28:AM28),"") | AO28: IRR | AP28: =IF(B28="","",IF(SUM(AH28:AJ28)=0,"",IF(AO28="IRR",AN28*('[5]Basic INFO'!$C$101*'[5]Basic INFO'!$C$103),IF(AO28="EUR",AN28,AP28)))) | AQ28: 100000000
B29: برآورد هزینه بدون سربار و مالیات بر ارزش افزوده | G29: =SUM(G8:G28) -> 4.8778846e+09 | H29: =SUM(H8:H28) -> 2753903.8 | AQ29: Total Price (Rials) | AR29: Total Price (Euros)
B30: ضریب سربار تأمین کالا | G30: 1.18 | H30: 1.18
B31: مالیات بر ارزش افزوده | G31: 0.1 | H31: 0.1
B32: هزینه تأمین کالا + سربار + مالیات بر ارزش افزوده | G32: =ROUND((G29*G30*(1+G31))/1000000,0)*1000000 -> 6331000000 | H32: =ROUND(H29*H30*(1+H31)/1000,0)*1000 -> 3575000
G33: =ROUND(SUMIF(AP:AP,">0",G:G)*G30*(1+G31)/1000000,0)*1000000 -> 0 | H33: =ROUND(SUMIF(AP:AP,">0",H:H)*H30*(1+H31)/1000,0)*1000 -> 3474000

Sheet C.I.P.
A1: Project Title: Revamping of Pazanan II Desalting Plant
A2: Sub-Project Title: Basic Design Studies and Preparation of FEED Package for Revamping of Pazanan II Desalting Plant
A3: Project Budget Ref. 03229 (formerly 53-51-91211)
A4: Doc. Title: BASIC MTO & COST ESTMATION REPORT (MECHANICAL)
A5: Doc. Ref. 91211-PZN-ME-RE-451-R02
A6: CHEMICAL INJECTION PACKAGES | I6: استعلام 1 | N6: استعلام 2 | S6: استعلام 3 | X6: استعلام 4 | AC6: استعلام 5
A7: Item No. | B7: Description | C7: Qty. (Set) | E7: GOING UNIT PRICE IRR 1404Q1 | F7: GOING UNIT PRICE FOB EUR 1404Q1 | G7: TOTAL PRICE ریال | H7: TOTAL PRICE FOB € | I7: منبع | J7: بهای واحد (ریال) | K7: بهای واحد (یورو) | L7: بهای واحد (دلار) | M7: تاریخ مرجع | N7: منبع | O7: بهای واحد (ریال) | P7: بهای واحد (یورو) | Q7: بهای واحد (دلار) | R7: تاریخ مرجع | S7: منبع | T7: بهای واحد (ریال) | U7: بهای واحد (یورو) | V7: بهای واحد (دلار) | W7: تاریخ مرجع | X7: منبع | Y7: بهای واحد (ریال) | Z7: بهای واحد (یورو) | AA7: بهای واحد (دلار) | AB7: تاریخ مرجع | AC7: منبع | AD7: بهای واحد (ریال) | AE7: بهای واحد (یورو) | AF7: بهای واحد (دلار) | AG7: تاریخ مرجع | AH7: No. of available quotations in IRR | AI7: No. of available quotations in EUR | AJ7: No. of available quotations in USD | AK7: avg. of IRR quotations converted to EUR | AL7: avg. of EUR quotations EUR | AM7: avg. of USD quotations converted to EUR | AN7: aggregate average quoted unit price (all in EUR) | AO7: Ref. Currency | AP7: quoted unit price | AQ7: Unit Price (Rials) | AR7: Unit Price 'FOB' (€) | AS7: NEW ITEM unit price IRR | AT7: NEW ITEM unit price EUR
A8: PK-180 | B8: Anti Scale Injection Package Max. Injection Rate (Lit/hr): 3 Max. Discharge Pressure (Barg): 3 Pumps Qty.: 2 Pumps Material: S.S. 316 L Pumps Design Code & Standard: API 675 & IPS-M-PM-135 Tank Capacity (m3): 0.5 Tank Design Pressure (Barg): 3.5 Tank Design Temperature (oC): -2.8 / 55 Tank Material: S.S. 316 L Agitator Required: Yes Tank Design Code & Standard: ASME VIII, DIV.1 & IPS-G-ME-150 | C8: 1 | E8: =IF(AND(AO8="IRR",SUM(AH8:AJ8)>0),AP8,IF(AND(AO8="IRR",AQ8<>""),AQ8*'[5]Basic INFO'!$E$127,IF(AO8="IRR",AS8,""))) -> 4.9878867e+10 | F8: =IF(AND(AO8="EUR",SUM(AH8:AJ8)>0),AP8,IF(AND(AO8="EUR",AR8<>""),AR8*'[5]Basic INFO'!$C$138,IF(AO8="EUR",AT8,""))) | G8: =IF(AO8="IRR",C8*E8,"") -> 4.9878867e+10 | H8: =IF(AO8="EUR",C8*F8,"") | I8: کاردانان شرق | L8: 55000 | M8: 45727 | N8: کندر صنعت پارتیان | O8: 62000000000 | R8: 2/29/2025 | S8: ماشین سازی نیو | U8: 73950 | W8: 45802 | AH8: =IF(B8="","",COUNT(J8,O8,T8,Y8,AD8)) -> 1 | AI8: =IF(B8="","",COUNT(K8,P8,U8,Z8,AE8)) -> 1 | AJ8: =IF(B8="","",COUNT(L8,Q8,V8,AA8,AF8)) -> 1 | AK8: =IF(AND(AH8<>"",AH8>0),AVERAGE(J8,O8,T8,Y8,AD8)/('[5]Basic INFO'!$C$101*'[5]Basic INFO'!$C$103),"") -> 89170.399 | AL8: =IF(AND(AI8<>"",AI8>0),AVERAGE(K8,P8,U8,Z8,AE8),"") -> 73950 | AM8: =IF(AND(AJ8<>"",AJ8>0),AVERAGE(L8,Q8,V8,AA8,AF8)/'[5]Basic INFO'!$C$103,"") -> 52091.787 | AN8: =IF(SUM(AH8:AJ8)<>0,AVERAGE(AK8:AM8),"") -> 71737.395 | AO8: IRR | AP8: =IF(B8="","",IF(SUM(AH8:AJ8)=0,"",IF(AO8="IRR",AN8*('[5]Basic INFO'!$C$101*'[5]Basic INFO'!$C$103),IF(AO8="EUR",AN8,AP8)))) -> 4.9878867e+10 | AQ8: 1750000000
A9: PK-181 | B9: Demulsifier Injection Package Max. Injection Rate (Lit/hr): 44 Max. Discharge Pressure (Barg): 11 Pumps Qty.: 3 Pumps Material: S.S. 316 L Pumps Design Code & Standard: API 675 & IPS-M-PM-135 Tank Qty.: 2 Sets Tank Capacity (m3): 0.5 & 2.5 Tank Design Pressure (Barg): 3.5 Tank Design Temperature (oC): -2.8 / 55 Tank Material: S.S. 316 L Agitator Required: Yes Tank Design Code & Standard: ASME VIII, DIV.1 & IPS-G-ME-150 | C9: 1 | E9: =IF(AND(AO9="IRR",SUM(AH9:AJ9)>0),AP9,IF(AND(AO9="IRR",AQ9<>""),AQ9*'[5]Basic INFO'!$E$127,IF(AO9="IRR",AS9,""))) -> 7.3692915e+10 | F9: =IF(AND(AO9="EUR",SUM(AH9:AJ9)>0),AP9,IF(AND(AO9="EUR",AR9<>""),AR9*'[5]Basic INFO'!$C$138,IF(AO9="EUR",AT9,""))) | G9: =IF(AO9="IRR",C9*E9,"") -> 7.3692915e+10 | H9: =IF(AO9="EUR",C9*F9,"") | I9: کاردانان شرق | L9: 85000 | N9: کندر صنعت پارتیان | O9: 86500000000 | R9: 2/29/2025 | S9: ماشین سازی نیو | U9: 113050 | W9: 45802 | AH9: =IF(B9="","",COUNT(J9,O9,T9,Y9,AD9)) -> 1 | AI9: =IF(B9="","",COUNT(K9,P9,U9,Z9,AE9)) -> 1 | AJ9: =IF(B9="","",COUNT(L9,Q9,V9,AA9,AF9)) -> 1 | AK9: =IF(AND(AH9<>"",AH9>0),AVERAGE(J9,O9,T9,Y9,AD9)/('[5]Basic INFO'!$C$101*'[5]Basic INFO'!$C$103),"") -> 124407.09 | AL9: =IF(AND(AI9<>"",AI9>0),AVERAGE(K9,P9,U9,Z9,AE9),"") -> 113050 | AM9: =IF(AND(AJ9<>"",AJ9>0),AVERAGE(L9,Q9,V9,AA9,AF9)/'[5]Basic INFO'!$C$103,"") -> 80505.488 | AN9: =IF(SUM(AH9:AJ9)<>0,AVERAGE(AK9:AM9),"") -> 105987.53 | AO9: IRR | AP9: =IF(B9="","",IF(SUM(AH9:AJ9)=0,"",IF(AO9="IRR",AN9*('[5]Basic INFO'!$C$101*'[5]Basic INFO'!$C$103),IF(AO9="EUR",AN9,AP9)))) -> 7.3692915e+10 | AQ9: 3000000000
A10: PK-182 | B10: Reverse Demulsifier Injection Package Max. Injection Rate (Lit/hr): 13 Max. Discharge Pressure (Barg): 3 Pumps Qty.: 2 Pumps Material: S.S. 316 L Pumps Design Code & Standard: API 675 & IPS-M-PM-135 Tank Capacity (m3): 0.5 Tank Design Pressure (Barg): 3.5 Tank Design Temperature (oC): -2.8 / 55 Tank Material: S.S. 316 L Agitator Required: Yes Tank Design Code & Standard: ASME VIII, DIV.1 & IPS-G-ME-150 | C10: 1 | E10: =IF(AND(AO10="IRR",SUM(AH10:AJ10)>0),AP10,IF(AND(AO10="IRR",AQ10<>""),AQ10*'[5]Basic INFO'!$E$127,IF(AO10="IRR",AS10,""))) -> 5.0976422e+10 | F10: =IF(AND(AO10="EUR",SUM(AH10:AJ10)>0),AP10,IF(AND(AO10="EUR",AR10<>""),AR10*'[5]Basic INFO'!$C$138,IF(AO10="EUR",AT10,""))) | G10: =IF(AO10="IRR",C10*E10,"") -> 5.0976422e+10 | H10: =IF(AO10="EUR",C10*F10,"") | I10: کاردانان شرق | L10: 60000 | N10: کندر صنعت پارتیان | O10: 62000000000 | R10: 2/29/2025 | S10: ماشین سازی نیو | U10: 73950 | W10: 45802 | AH10: =IF(B10="","",COUNT(J10,O10,T10,Y10,AD10)) -> 1 | AI10: =IF(B10="","",COUNT(K10,P10,U10,Z10,AE10)) -> 1 | AJ10: =IF(B10="","",COUNT(L10,Q10,V10,AA10,AF10)) -> 1 | AK10: =IF(AND(AH10<>"",AH10>0),AVERAGE(J10,O10,T10,Y10,AD10)/('[5]Basic INFO'!$C$101*'[5]Basic INFO'!$C$103),"") -> 89170.399 | AL10: =IF(AND(AI10<>"",AI10>0),AVERAGE(K10,P10,U10,Z10,AE10),"") -> 73950 | AM10: =IF(AND(AJ10<>"",AJ10>0),AVERAGE(L10,Q10,V10,AA10,AF10)/'[5]Basic INFO'!$C$103,"") -> 56827.404 | AN10: =IF(SUM(AH10:AJ10)<>0,AVERAGE(AK10:AM10),"") -> 73315.934 | AO10: IRR | AP10: =IF(B10="","",IF(SUM(AH10:AJ10)=0,"",IF(AO10="IRR",AN10*('[5]Basic INFO'!$C$101*'[5]Basic INFO'!$C$103),IF(AO10="EUR",AN10,AP10)))) -> 5.0976422e+10 | AQ10: 1750000000
A11: PK-183 | B11: Biocide Injection Package Max. Injection Rate (Lit/hr): 66 Max. Discharge Pressure (Barg): 6 Pumps Qty.: 2 Pumps Material: S.S. 316 L Pumps Design Code & Standard: API 675 & IPS-M-PM-135 Tank Capacity (m3): 0.5 Tank Design Pressure (Barg): 3.5 Tank Design Temperature (oC): -2.8 / 55 Tank Material: S.S. 316 L Agitator Required: Yes Tank Design Code & Standard: ASME VIII, DIV.1 & IPS-G-ME-150 | C11: 1 | E11: =IF(AND(AO11="IRR",SUM(AH11:AJ11)>0),AP11,IF(AND(AO11="IRR",AQ11<>""),AQ11*'[5]Basic INFO'!$E$127,IF(AO11="IRR",AS11,""))) -> 5.2073977e+10 | F11: =IF(AND(AO11="EUR",SUM(AH11:AJ11)>0),AP11,IF(AND(AO11="EUR",AR11<>""),AR11*'[5]Basic INFO'!$C$138,IF(AO11="EUR",AT11,""))) | G11: =IF(AO11="IRR",C11*E11,"") -> 5.2073977e+10 | H11: =IF(AO11="EUR",C11*F11,"") | I11: کاردانان شرق | L11: 65000 | N11: کندر صنعت پارتیان | O11: 62000000000 | R11: 2/29/2025 | S11: ماشین سازی نیو | U11: 73950 | W11: 45802 | AH11: =IF(B11="","",COUNT(J11,O11,T11,Y11,AD11)) -> 1 | AI11: =IF(B11="","",COUNT(K11,P11,U11,Z11,AE11)) -> 1 | AJ11: =IF(B11="","",COUNT(L11,Q11,V11,AA11,AF11)) -> 1 | AK11: =IF(AND(AH11<>"",AH11>0),AVERAGE(J11,O11,T11,Y11,AD11)/('[5]Basic INFO'!$C$101*'[5]Basic INFO'!$C$103),"") -> 89170.399 | AL11: =IF(AND(AI11<>"",AI11>0),AVERAGE(K11,P11,U11,Z11,AE11),"") -> 73950 | AM11: =IF(AND(AJ11<>"",AJ11>0),AVERAGE(L11,Q11,V11,AA11,AF11)/'[5]Basic INFO'!$C$103,"") -> 61563.02 | AN11: =IF(SUM(AH11:AJ11)<>0,AVERAGE(AK11:AM11),"") -> 74894.473 | AO11: IRR | AP11: =IF(B11="","",IF(SUM(AH11:AJ11)=0,"",IF(AO11="IRR",AN11*('[5]Basic INFO'!$C$101*'[5]Basic INFO'!$C$103),IF(AO11="EUR",AN11,AP11)))) -> 5.2073977e+10 | AQ11: 1900000000
A12: PK-184 | B12: Oxygen Scavenger Injection Package Max. Injection Rate (Lit/hr): 9 Max. Discharge Pressure (Barg): 6 Pumps Qty.: 2 Pumps Material: S.S. 316 L Pumps Design Code & Standard: API 675 & IPS-M-PM-135 Tank Capacity (m3): N/A (Portable Barrel) Agitator Required: N/A | C12: 1 | E12: =IF(AND(AO12="IRR",SUM(AH12:AJ12)>0),AP12,IF(AND(AO12="IRR",AQ12<>""),AQ12*'[5]Basic INFO'!$E$127,IF(AO12="IRR",AS12,""))) -> 4.0488071e+10 | F12: =IF(AND(AO12="EUR",SUM(AH12:AJ12)>0),AP12,IF(AND(AO12="EUR",AR12<>""),AR12*'[5]Basic INFO'!$C$138,IF(AO12="EUR",AT12,""))) | G12: =IF(AO12="IRR",C12*E12,"") -> 4.0488071e+10 | H12: =IF(AO12="EUR",C12*F12,"") | I12: کاردانان شرق | L12: 65000 | N12: کندر صنعت پارتیان | O12: 50500000000 | R12: 2/29/2025 | S12: ماشین سازی نیو | U12: 40500 | W12: 45802 | AH12: =IF(B12="","",COUNT(J12,O12,T12,Y12,AD12)) -> 1 | AI12: =IF(B12="","",COUNT(K12,P12,U12,Z12,AE12)) -> 1 | AJ12: =IF(B12="","",COUNT(L12,Q12,V12,AA12,AF12)) -> 1 | AK12: =IF(AND(AH12<>"",AH12>0),AVERAGE(J12,O12,T12,Y12,AD12)/('[5]Basic INFO'!$C$101*'[5]Basic INFO'!$C$103),"") -> 72630.728 | AL12: =IF(AND(AI12<>"",AI12>0),AVERAGE(K12,P12,U12,Z12,AE12),"") -> 40500 | AM12: =IF(AND(AJ12<>"",AJ12>0),AVERAGE(L12,Q12,V12,AA12,AF12)/'[5]Basic INFO'!$C$103,"") -> 61563.02 | AN12: =IF(SUM(AH12:AJ12)<>0,AVERAGE(AK12:AM12),"") -> 58231.25 | AO12: IRR | AP12: =IF(B12="","",IF(SUM(AH12:AJ12)=0,"",IF(AO12="IRR",AN12*('[5]Basic INFO'!$C$101*'[5]Basic INFO'!$C$103),IF(AO12="EUR",AN12,AP12)))) -> 4.0488071e+10 | AQ12: 1350000000
A13: PK-185 | B13: Anti Scale Injection Package Max. Injection Rate (Lit/hr): 2 Max. Discharge Pressure (Barg): 6 Pumps Qty.: 2 Pumps Material: S.S. 316 L Pumps Design Code & Standard: API 675 & IPS-M-PM-135 Tank Capacity (m3): 0.5 Tank Design Pressure (Barg): 3.5 Tank Design Temperature (oC): -2.8 / 55 Tank Material: S.S. 316 L Agitator Required: Yes Tank Design Code & Standard: ASME VIII, DIV.1 & IPS-G-ME-150 | C13: 1 | E13: =IF(AND(AO13="IRR",SUM(AH13:AJ13)>0),AP13,IF(AND(AO13="IRR",AQ13<>""),AQ13*'[5]Basic INFO'!$E$127,IF(AO13="IRR",AS13,""))) -> 5.2073977e+10 | F13: =IF(AND(AO13="EUR",SUM(AH13:AJ13)>0),AP13,IF(AND(AO13="EUR",AR13<>""),AR13*'[5]Basic INFO'!$C$138,IF(AO13="EUR",AT13,""))) | G13: =IF(AO13="IRR",C13*E13,"") -> 5.2073977e+10 | H13: =IF(AO13="EUR",C13*F13,"") | I13: کاردانان شرق | L13: 65000 | N13: کندر صنعت پارتیان | O13: 62000000000 | R13: 2/29/2025 | S13: ماشین سازی نیو | U13: 73950 | W13: 45802 | AH13: =IF(B13="","",COUNT(J13,O13,T13,Y13,AD13)) -> 1 | AI13: =IF(B13="","",COUNT(K13,P13,U13,Z13,AE13)) -> 1 | AJ13: =IF(B13="","",COUNT(L13,Q13,V13,AA13,AF13)) -> 1 | AK13: =IF(AND(AH13<>"",AH13>0),AVERAGE(J13,O13,T13,Y13,AD13)/('[5]Basic INFO'!$C$101*'[5]Basic INFO'!$C$103),"") -> 89170.399 | AL13: =IF(AND(AI13<>"",AI13>0),AVERAGE(K13,P13,U13,Z13,AE13),"") -> 73950 | AM13: =IF(AND(AJ13<>"",AJ13>0),AVERAGE(L13,Q13,V13,AA13,AF13)/'[5]Basic INFO'!$C$103,"") -> 61563.02 | AN13: =IF(SUM(AH13:AJ13)<>0,AVERAGE(AK13:AM13),"") -> 74894.473 | AO13: IRR | AP13: =IF(B13="","",IF(SUM(AH13:AJ13)=0,"",IF(AO13="IRR",AN13*('[5]Basic INFO'!$C$101*'[5]Basic INFO'!$C$103),IF(AO13="EUR",AN13,AP13)))) -> 5.2073977e+10 | AQ13: 1750000000
A14: PK-186 | B14: Corrosion Inhibitor Injection Package Max. Injection Rate (Lit/hr): 12 Max. Discharge Pressure (Barg): 6 Pumps Qty.: 2 Pumps Material: S.S. 316 L Pumps Design Code & Standard: API 675 & IPS-M-PM-135 Tank Capacity (m3): 0.5 Tank Design Pressure (Barg): 3.5 Tank Design Temperature (oC): -2.8 / 55 Tank Material: S.S. 316 L Agitator Required: Yes Tank Design Code & Standard: ASME VIII, DIV.1 & IPS-G-ME-150 | C14: 1 | E14: =IF(AND(AO14="IRR",SUM(AH14:AJ14)>0),AP14,IF(AND(AO14="IRR",AQ14<>""),AQ14*'[5]Basic INFO'!$E$127,IF(AO14="IRR",AS14,""))) -> 5.2073977e+10 | F14: =IF(AND(AO14="EUR",SUM(AH14:AJ14)>0),AP14,IF(AND(AO14="EUR",AR14<>""),AR14*'[5]Basic INFO'!$C$138,IF(AO14="EUR",AT14,""))) | G14: =IF(AO14="IRR",C14*E14,"") -> 5.2073977e+10 | H14: =IF(AO14="EUR",C14*F14,"") | I14: کاردانان شرق | L14: 65000 | N14: کندر صنعت پارتیان | O14: 62000000000 | R14: 2/29/2025 | S14: ماشین سازی نیو | U14: 73950 | W14: 45802 | AH14: =IF(B14="","",COUNT(J14,O14,T14,Y14,AD14)) -> 1 | AI14: =IF(B14="","",COUNT(K14,P14,U14,Z14,AE14)) -> 1 | AJ14: =IF(B14="","",COUNT(L14,Q14,V14,AA14,AF14)) -> 1 | AK14: =IF(AND(AH14<>"",AH14>0),AVERAGE(J14,O14,T14,Y14,AD14)/('[5]Basic INFO'!$C$101*'[5]Basic INFO'!$C$103),"") -> 89170.399 | AL14: =IF(AND(AI14<>"",AI14>0),AVERAGE(K14,P14,U14,Z14,AE14),"") -> 73950 | AM14: =IF(AND(AJ14<>"",AJ14>0),AVERAGE(L14,Q14,V14,AA14,AF14)/'[5]Basic INFO'!$C$103,"") -> 61563.02 | AN14: =IF(SUM(AH14:AJ14)<>0,AVERAGE(AK14:AM14),"") -> 74894.473 | AO14: IRR | AP14: =IF(B14="","",IF(SUM(AH14:AJ14)=0,"",IF(AO14="IRR",AN14*('[5]Basic INFO'!$C$101*'[5]Basic INFO'!$C$103),IF(AO14="EUR",AN14,AP14)))) -> 5.2073977e+10 | AQ14: 1750000000
A15: PK-187 | B15: Anti Scale Injection Package Max. Injection Rate (Lit/hr): 4.5 Max. Discharge Pressure (Barg): 6 Pumps Qty.: 2 Pumps Material: S.S. 316 L Pumps Design Code & Standard: API 675 & IPS-M-PM-135 Tank Capacity (m3): 0.5 Tank Design Pressure (Barg): 3.5 Tank Design Temperature (oC): -2.8 / 55 Tank Material: S.S. 316 L Agitator Required: Yes Tank Design Code & Standard: ASME VIII, DIV.1 & IPS-G-ME-150 | C15: 1 | E15: =IF(AND(AO15="IRR",SUM(AH15:AJ15)>0),AP15,IF(AND(AO15="IRR",AQ15<>""),AQ15*'[5]Basic INFO'!$E$127,IF(AO15="IRR",AS15,""))) -> 5.2073977e+10 | F15: =IF(AND(AO15="EUR",SUM(AH15:AJ15)>0),AP15,IF(AND(AO15="EUR",AR15<>""),AR15*'[5]Basic INFO'!$C$138,IF(AO15="EUR",AT15,""))) | G15: =IF(AO15="IRR",C15*E15,"") -> 5.2073977e+10 | H15: =IF(AO15="EUR",C15*F15,"") | I15: کاردانان شرق | L15: 65000 | N15: کندر صنعت پارتیان | O15: 62000000000 | R15: 2/29/2025 | S15: ماشین سازی نیو | U15: 73950 | W15: 45802 | AH15: =IF(B15="","",COUNT(J15,O15,T15,Y15,AD15)) -> 1 | AI15: =IF(B15="","",COUNT(K15,P15,U15,Z15,AE15)) -> 1 | AJ15: =IF(B15="","",COUNT(L15,Q15,V15,AA15,AF15)) -> 1 | AK15: =IF(AND(AH15<>"",AH15>0),AVERAGE(J15,O15,T15,Y15,AD15)/('[5]Basic INFO'!$C$101*'[5]Basic INFO'!$C$103),"") -> 89170.399 | AL15: =IF(AND(AI15<>"",AI15>0),AVERAGE(K15,P15,U15,Z15,AE15),"") -> 73950 | AM15: =IF(AND(AJ15<>"",AJ15>0),AVERAGE(L15,Q15,V15,AA15,AF15)/'[5]Basic INFO'!$C$103,"") -> 61563.02 | AN15: =IF(SUM(AH15:AJ15)<>0,AVERAGE(AK15:AM15),"") -> 74894.473 | AO15: IRR | AP15: =IF(B15="","",IF(SUM(AH15:AJ15)=0,"",IF(AO15="IRR",AN15*('[5]Basic INFO'!$C$101*'[5]Basic INFO'!$C$103),IF(AO15="EUR",AN15,AP15)))) -> 5.2073977e+10 | AQ15: 1750000000
A16: PK-188 | B16: Oxygen Scavenger Injection Package Max. Injection Rate (Lit/hr): 0.2 Max. Discharge Pressure (Barg): 6 Pumps Qty.: 2 Pumps Material: S.S. 316 L Pumps Design Code & Standard: API 675 & IPS-M-PM-135 Tank Capacity (m3): N/A (Portable Barrel) Agitator Required: N/A | C16: 1 | E16: =IF(AND(AO16="IRR",SUM(AH16:AJ16)>0),AP16,IF(AND(AO16="IRR",AQ16<>""),AQ16*'[5]Basic INFO'!$E$127,IF(AO16="IRR",AS16,""))) -> 4.3780736e+10 | F16: =IF(AND(AO16="EUR",SUM(AH16:AJ16)>0),AP16,IF(AND(AO16="EUR",AR16<>""),AR16*'[5]Basic INFO'!$C$138,IF(AO16="EUR",AT16,""))) | G16: =IF(AO16="IRR",C16*E16,"") -> 4.3780736e+10 | H16: =IF(AO16="EUR",C16*F16,"") | I16: کاردانان شرق | L16: 80000 | N16: کندر صنعت پارتیان | O16: 50500000000 | R16: 2/29/2025 | S16: ماشین سازی نیو | U16: 40500 | W16: 45802 | AH16: =IF(B16="","",COUNT(J16,O16,T16,Y16,AD16)) -> 1 | AI16: =IF(B16="","",COUNT(K16,P16,U16,Z16,AE16)) -> 1 | AJ16: =IF(B16="","",COUNT(L16,Q16,V16,AA16,AF16)) -> 1 | AK16: =IF(AND(AH16<>"",AH16>0),AVERAGE(J16,O16,T16,Y16,AD16)/('[5]Basic INFO'!$C$101*'[5]Basic INFO'!$C$103),"") -> 72630.728 | AL16: =IF(AND(AI16<>"",AI16>0),AVERAGE(K16,P16,U16,Z16,AE16),"") -> 40500 | AM16: =IF(AND(AJ16<>"",AJ16>0),AVERAGE(L16,Q16,V16,AA16,AF16)/'[5]Basic INFO'!$C$103,"") -> 75769.871 | AN16: =IF(SUM(AH16:AJ16)<>0,AVERAGE(AK16:AM16),"") -> 62966.866 | AO16: IRR | AP16: =IF(B16="","",IF(SUM(AH16:AJ16)=0,"",IF(AO16="IRR",AN16*('[5]Basic INFO'!$C$101*'[5]Basic INFO'!$C$103),IF(AO16="EUR",AN16,AP16)))) -> 4.3780736e+10 | AQ16: 1400000000
A17: PK-189 | B17: Oxygen Scavenger Injection Package Max. Injection Rate (Lit/hr): 3 Max. Discharge Pressure (Barg): 4 Pumps Qty.: 2 Pumps Material: S.S. 316 L Pumps Design Code & Standard: API 675 & IPS-M-PM-135 Tank Capacity (m3): N/A (Portable Barrel) Agitator Required: N/A | C17: 1 | E17: =IF(AND(AO17="IRR",SUM(AH17:AJ17)>0),AP17,IF(AND(AO17="IRR",AQ17<>""),AQ17*'[5]Basic INFO'!$E$127,IF(AO17="IRR",AS17,""))) -> 4.0488071e+10 | F17: =IF(AND(AO17="EUR",SUM(AH17:AJ17)>0),AP17,IF(AND(AO17="EUR",AR17<>""),AR17*'[5]Basic INFO'!$C$138,IF(AO17="EUR",AT17,""))) | G17: =IF(AO17="IRR",C17*E17,"") -> 4.0488071e+10 | H17: =IF(AO17="EUR",C17*F17,"") | I17: کاردانان شرق | L17: 65000 | N17: کندر صنعت پارتیان | O17: 50500000000 | R17: 2/29/2025 | S17: ماشین سازی نیو | U17: 40500 | W17: 45802 | AH17: =IF(B17="","",COUNT(J17,O17,T17,Y17,AD17)) -> 1 | AI17: =IF(B17="","",COUNT(K17,P17,U17,Z17,AE17)) -> 1 | AJ17: =IF(B17="","",COUNT(L17,Q17,V17,AA17,AF17)) -> 1 | AK17: =IF(AND(AH17<>"",AH17>0),AVERAGE(J17,O17,T17,Y17,AD17)/('[5]Basic INFO'!$C$101*'[5]Basic INFO'!$C$103),"") -> 72630.728 | AL17: =IF(AND(AI17<>"",AI17>0),AVERAGE(K17,P17,U17,Z17,AE17),"") -> 40500 | AM17: =IF(AND(AJ17<>"",AJ17>0),AVERAGE(L17,Q17,V17,AA17,AF17)/'[5]Basic INFO'!$C$103,"") -> 61563.02 | AN17: =IF(SUM(AH17:AJ17)<>0,AVERAGE(AK17:AM17),"") -> 58231.25 | AO17: IRR | AP17: =IF(B17="","",IF(SUM(AH17:AJ17)=0,"",IF(AO17="IRR",AN17*('[5]Basic INFO'!$C$101*'[5]Basic INFO'!$C$103),IF(AO17="EUR",AN17,AP17)))) -> 4.0488071e+10 | AQ17: 1350000000
A18: PK-212 | B18: Demulsifier Injection Package (Production Unit) Max. Injection Rate (Lit/hr): 44 Max. Discharge Pressure (Barg): 11 Pumps Qty.: 2 Pumps Material: S.S. 316 L Pumps Design Code & Standard: API 675 & IPS-M-PM-135 Tank Capacity (m3): 2.5 Tank Design Pressure (Barg): 3.5 Tank Design Temperature (oC): -2.8 / 55 Tank Material: S.S. 316 L Agitator Required: Yes Tank Design Code & Standard: ASME VIII, DIV.1 & IPS-G-ME-150 | C18: 1 | E18: =IF(AND(AO18="IRR",SUM(AH18:AJ18)>0),AP18,IF(AND(AO18="IRR",AQ18<>""),AQ18*'[5]Basic INFO'!$E$127,IF(AO18="IRR",AS18,""))) -> 5.5035754e+10 | F18: =IF(AND(AO18="EUR",SUM(AH18:AJ18)>0),AP18,IF(AND(AO18="EUR",AR18<>""),AR18*'[5]Basic INFO'!$C$138,IF(AO18="EUR",AT18,""))) | G18: =IF(AO18="IRR",C18*E18,"") -> 5.5035754e+10 | H18: =IF(AO18="EUR",C18*F18,"") | I18: کاردانان شرق | L18: 75000 | N18: کندر صنعت پارتیان | O18: 64300000000 | R18: 2/29/2025 | S18: ماشین سازی نیو | U18: 73950 | W18: 45802 | AH18: =IF(B18="","",COUNT(J18,O18,T18,Y18,AD18)) -> 1 | AI18: =IF(B18="","",COUNT(K18,P18,U18,Z18,AE18)) -> 1 | AJ18: =IF(B18="","",COUNT(L18,Q18,V18,AA18,AF18)) -> 1 | AK18: =IF(AND(AH18<>"",AH18>0),AVERAGE(J18,O18,T18,Y18,AD18)/('[5]Basic INFO'!$C$101*'[5]Basic INFO'!$C$103),"") -> 92478.333 | AL18: =IF(AND(AI18<>"",AI18>0),AVERAGE(K18,P18,U18,Z18,AE18),"") -> 73950 | AM18: =IF(AND(AJ18<>"",AJ18>0),AVERAGE(L18,Q18,V18,AA18,AF18)/'[5]Basic INFO'!$C$103,"") -> 71034.254 | AN18: =IF(SUM(AH18:AJ18)<>0,AVERAGE(AK18:AM18),"") -> 79154.196 | AO18: IRR | AP18: =IF(B18="","",IF(SUM(AH18:AJ18)=0,"",IF(AO18="IRR",AN18*('[5]Basic INFO'!$C$101*'[5]Basic INFO'!$C$103),IF(AO18="EUR",AN18,AP18)))) -> 5.5035754e+10 | AQ18: 1900000000
B19: برآورد هزینه بدون سربار و مالیات بر ارزش افزوده | G19: =SUM(G8:G18) -> 5.6263675e+11 | H19: =SUM(H8:H18) -> 0 | AQ19: Total Price (Rials) | AR19: Total Price (Euros)
B20: ضریب سربار تأمین کالا | G20: 1.18 | H20: 1.18
B21: مالیات بر ارزش افزوده | G21: 0.1 | H21: 0.1
B22: هزینه تأمین کالا + سربار + مالیات بر ارزش افزوده | G22: =ROUND((G19*G20*(1+G21))/1000000,0)*1000000 -> 730302000000 | H22: =ROUND(H19*H20*(1+H21)/1000,0)*1000 -> 0
G23: =ROUND(SUMIF(AP:AP,">0",G:G)*G20*(1+G21)/1000000,0)*1000000 -> 730302000000 | H23: =ROUND(SUMIF(AP:AP,">0",H:H)*H20*(1+H21)/1000,0)*1000 -> 0

Sheet DEAERATOR
A1: Project Title: Revamping of Pazanan II Desalting Plant
A2: Sub-Project Title: Basic Design Studies and Preparation of FEED Package for Revamping of Pazanan II Desalting Plant
A3: Project Budget Ref. 03229 (formerly 53-51-91211)
A4: Doc. Title: BASIC MTO & COST ESTMATION REPORT (MECHANICAL)
A5: Doc. Ref. 91211-PZN-ME-RE-451-R02
A6: DEAERATION PACKAGES | I6: استعلام 1 | N6: استعلام 2 | S6: استعلام 3 | X6: استعلام 4 | AC6: استعلام 5
A7: Item No. | B7: Description | C7: Qty. (Set) | E7: GOING UNIT PRICE IRR 1404Q1 | F7: GOING UNIT PRICE FOB EUR 1404Q1 | G7: TOTAL PRICE ریال | H7: TOTAL PRICE FOB € | I7: منبع | J7: بهای واحد (ریال) | K7: بهای واحد (یورو) | L7: بهای واحد (دلار) | M7: تاریخ مرجع | N7: منبع | O7: بهای واحد (ریال) | P7: بهای واحد (یورو) | Q7: بهای واحد (دلار) | R7: تاریخ مرجع | S7: منبع | T7: بهای واحد (ریال) | U7: بهای واحد (یورو) | V7: بهای واحد (دلار) | W7: تاریخ مرجع | X7: منبع | Y7: بهای واحد (ریال) | Z7: بهای واحد (یورو) | AA7: بهای واحد (دلار) | AB7: تاریخ مرجع | AC7: منبع | AD7: بهای واحد (ریال) | AE7: بهای واحد (یورو) | AF7: بهای واحد (دلار) | AG7: تاریخ مرجع | AH7: No. of available quotations in IRR | AI7: No. of available quotations in EUR | AJ7: No. of available quotations in USD | AK7: avg. of IRR quotations converted to EUR | AL7: avg. of EUR quotations EUR | AM7: avg. of USD quotations converted to EUR | AN7: aggregate average quoted unit price (all in EUR) | AO7: Ref. Currency | AP7: quoted unit price | AQ7: Unit Price (Rials) | AR7: Unit Price 'FOB' (€) | AS7: NEW ITEM unit price IRR | AT7: NEW ITEM unit price EUR
A8: PK-121 | B8: Deaeration Package Max. Flow Rate (m3/hr): 50 Including Deaerator Tower, Water Liquid Ring Return Pumps, Vacuum Liquid Ring Pumps, Air Ejector, Chilling Unit Recycle Water Tank Related Piping, Instruments, etc. Tower Tag No.: DA -121 Internals: Packing & Tray Design Pressure: 3.5 (F.V.) Barg Design Temperature: -2.8 / 85 oC Mat. (Shell/Heads): SA 516 Gr. 70 Mat. (Remov. Internals): S.S. 316L Design Code & Standard: ASME VIII, DIV.1 & IPS-G-ME-150 | C8: 1 | E8: =IF(AND(AO8="IRR",SUM(AH8:AJ8)>0),AP8,IF(AND(AO8="IRR",AQ8<>""),AQ8*'[5]Basic INFO'!$E$127,IF(AO8="IRR",AS8,""))) | F8: =IF(AND(AO8="EUR",SUM(AH8:AJ8)>0),AP8,IF(AND(AO8="EUR",AR8<>""),AR8*'[5]Basic INFO'!$C$138,IF(AO8="EUR",AT8,""))) -> 1850000 | G8: =IF(AO8="IRR",C8*E8,"") | H8: =IF(AO8="EUR",C8*F8,"") -> 1850000 | I8: نواندیشان آریا | M8: declined | N8: مصنوعات فلزی سنگین | R8: declined | S8: زلال ایران | U8: 1850000 | W8: 45729 | X8: چمان | AB8: no reply | AH8: =IF(B8="","",COUNT(J8,O8,T8,Y8,AD8)) -> 0 | AI8: =IF(B8="","",COUNT(K8,P8,U8,Z8,AE8)) -> 1 | AJ8: =IF(B8="","",COUNT(L8,Q8,V8,AA8,AF8)) -> 0 | AK8: =IF(AND(AH8<>"",AH8>0),AVERAGE(J8,O8,T8,Y8,AD8)/('[5]Basic INFO'!$C$101*'[5]Basic INFO'!$C$103),"") | AL8: =IF(AND(AI8<>"",AI8>0),AVERAGE(K8,P8,U8,Z8,AE8),"") -> 1850000 | AM8: =IF(AND(AJ8<>"",AJ8>0),AVERAGE(L8,Q8,V8,AA8,AF8)/'[5]Basic INFO'!$C$103,"") | AN8: =IF(SUM(AH8:AJ8)<>0,AVERAGE(AK8:AM8),"") -> 1850000 | AO8: EUR | AP8: =IF(B8="","",IF(SUM(AH8:AJ8)=0,"",IF(AO8="IRR",AN8*('[5]Basic INFO'!$C$101*'[5]Basic INFO'!$C$103),IF(AO8="EUR",AN8,AP8)))) -> 1850000 | AR8: 400000
B9: برآورد هزینه بدون سربار و مالیات بر ارزش افزوده | G9: =SUM(G8) -> 0 | H9: =SUM(H8) -> 1850000 | AQ9: Total Price (Rials) | AR9: Total Price (Euros)
B10: ضریب سربار تأمین کالا | G10: 1.18 | H10: 1.18
B11: مالیات بر ارزش افزوده | G11: 0.1 | H11: 0.1
B12: هزینه تأمین کالا + سربار + مالیات بر ارزش افزوده | G12: =ROUND((G9*G10*(1+G11))/1000000,0)*1000000 -> 0 | H12: =ROUND(H9*H10*(1+H11)/1000,0)*1000 -> 2401000
G13: =ROUND(SUMIF(AP:AP,">0",G:G)*G10*(1+G11)/1000000,0)*1000000 -> 0 | H13: =ROUND(SUMIF(AP:AP,">0",H:H)*H10*(1+H11)/1000,0)*1000 -> 2401000

Sheet IGF
A1: Project Title: Revamping of Pazanan II Desalting Plant
A2: Sub-Project Title: Basic Design Studies and Preparation of FEED Package for Revamping of Pazanan II Desalting Plant
A3: Project Budget Ref. 03229 (formerly 53-51-91211)
A4: Doc. Title: BASIC MTO & COST ESTMATION REPORT (MECHANICAL)
A5: Doc. Ref. 91211-PZN-ME-RE-451-R02
A6: IGF PACKAGES | I6: استعلام 1 | N6: استعلام 2 | S6: استعلام 3
A7: Item No. | B7: Description | C7: Qty. (Set) | E7: GOING UNIT PRICE IRR 1404Q1 | F7: GOING UNIT PRICE FOB EUR 1404Q1 | G7: TOTAL PRICE ریال | H7: TOTAL PRICE FOB € | I7: منبع | J7: بهای واحد (ریال) | K7: بهای واحد (یورو) | L7: بهای واحد (دلار) | M7: تاریخ مرجع | N7: منبع | O7: بهای واحد (ریال) | P7: بهای واحد (یورو) | Q7: بهای واحد (دلار) | R7: تاریخ مرجع | S7: منبع | T7: بهای واحد (ریال) | U7: بهای واحد (یورو) | V7: بهای واحد (دلار) | W7: تاریخ مرجع | AH7: No. of available quotations in IRR | AI7: No. of available quotations in EUR | AJ7: No. of available quotations in USD | AK7: avg. of IRR quotations converted to EUR | AL7: avg. of EUR quotations EUR | AM7: avg. of USD quotations converted to EUR | AN7: aggregate average quoted unit price (all in EUR) | AO7: Ref. Currency | AP7: quoted unit price | AQ7: Unit Price (Rials) | AR7: Unit Price 'FOB' (€) | AS7: NEW ITEM unit price IRR | AT7: NEW ITEM unit price EUR
A8: PK-131 | B8: IGF Package Design Flow (m3/hr): 132.5 Including IGF Vessel, Pumps (Water Recycle, De-oiled Water Booster, Recovered Waste Oil& Oily Sludge), Related Piping, Instruments, etc. Vessel Design Pressure (Barg): 5 (F.V.) Vessel Design Temperature (oC): 95 Vessel Mat. (Shell/Heads): SA 516 Gr.70 Removable Internals Mat.: Duplex S.S. Vessel Design Codes & Standards: ASME VIII, DIV.1 & IPS-G-ME-150 Eductor Supply Pumps: Type: Centrifugal (OH2), Material Class(Acc. to API 610): D2, Design Code & Standard: API 610 & IPS-G-PM-105 De-oiled Water Booster Pumps: Type: Centrifugal (OH2), Material Class(Acc. to API 610): D2, NACE 'MR-0175' Required: Yes, Design Code & Standard: API 610 & IPS-G-PM-105 Recovered Waste Oil Pumps: Type: P.D.-Rotary (Ext. Gear), Material Class(Acc. to API 610): D1, Design Code & Standard: API 676 & IPS-M-PM-140 Oily Sludge Pumps: Type: P.D.-Rotary (Twin Screw), Material Class(Acc. to API 610): D2, NACE 'MR-0175' Required: Yes, Design Code & Standard: API 610 & IPS-G-PM-105 Sump Drain Pump: Type: Centrifugal (VS4), Material Class(Acc. to API 610): S6, Design Code & Standard: API 610 & IPS-G-PM-105 | C8: 1 | E8: =IF(AND(AO8="IRR",SUM(AH8:AJ8)>0),AP8,IF(AND(AO8="IRR",AQ8<>""),AQ8*'[5]Basic INFO'!$E$127,IF(AO8="IRR",AS8,""))) | F8: =IF(AND(AO8="EUR",SUM(AH8:AJ8)>0),AP8,IF(AND(AO8="EUR",AR8<>""),AR8*'[5]Basic INFO'!$C$138,IF(AO8="EUR",AT8,""))) -> 556479.59 | G8: =IF(AO8="IRR",C8*E8,"") | H8: =IF(AO8="EUR",C8*F8,"") -> 556479.59 | I8: آبسان پالایش | M8: no reply | N8: چمان | R8: no reply | S8: هامون راه | U8: 556479.59 | W8: 45796 | AH8: =IF(B8="","",COUNT(J8,O8,T8,Y8,AD8)) -> 0 | AI8: =IF(B8="","",COUNT(K8,P8,U8,Z8,AE8)) -> 1 | AJ8: =IF(B8="","",COUNT(L8,Q8,V8,AA8,AF8)) -> 0 | AK8: =IF(AND(AH8<>"",AH8>0),AVERAGE(J8,O8,T8,Y8,AD8)/('[5]Basic INFO'!$C$101*'[5]Basic INFO'!$C$103),"") | AL8: =IF(AND(AI8<>"",AI8>0),AVERAGE(K8,P8,U8,Z8,AE8),"") -> 556479.59 | AM8: =IF(AND(AJ8<>"",AJ8>0),AVERAGE(L8,Q8,V8,AA8,AF8)/'[5]Basic INFO'!$C$103,"") | AN8: =IF(SUM(AH8:AJ8)<>0,AVERAGE(AK8:AM8),"") -> 556479.59 | AO8: EUR | AP8: =IF(B8="","",IF(SUM(AH8:AJ8)=0,"",IF(AO8="IRR",AN8*('[5]Basic INFO'!$C$101*'[5]Basic INFO'!$C$103),IF(AO8="EUR",AN8,AP8)))) -> 556479.59 | AR8: 700000
B9: برآورد هزینه بدون سربار و مالیات بر ارزش افزوده | G9: =SUM(G8) -> 0 | H9: =SUM(H8) -> 556479.59 | AQ9: Total Price (Rials) | AR9: Total Price (Euros)
B10: ضریب سربار تأمین کالا | G10: 1.18 | H10: 1.18
B11: مالیات بر ارزش افزوده | G11: 0.1 | H11: 0.1
B12: هزینه تأمین کالا + سربار + مالیات بر ارزش افزوده | G12: =ROUND((G9*G10*(1+G11))/1000000,0)*1000000 -> 0 | H12: =ROUND(H9*H10*(1+H11)/1000,0)*1000 -> 722000
G13: =ROUND(SUMIF(AP:AP,">0",G:G)*G10*(1+G11)/1000000,0)*1000000 -> 0 | H13: =ROUND(SUMIF(AP:AP,">0",H:H)*H10*(1+H11)/1000,0)*1000 -> 722000

Sheet FILTERS
A1: Project Title: Revamping of Pazanan II Desalting Plant
A2: Sub-Project Title: Basic Design Studies and Preparation of FEED Package for Revamping of Pazanan II Desalting Plant
A3: Project Budget Ref. 03229 (formerly 53-51-91211)
A4: Doc. Title: BASIC MTO & COST ESTMATION REPORT (MECHANICAL)
A5: Doc. Ref. 91211-PZN-ME-RE-451-R02
A6: FILTERS | I6: استعلام 1 | N6: استعلام 2 | S6: استعلام 3
A7: Item No. | B7: Description | C7: Qty. (Set) | E7: GOING UNIT PRICE IRR 1404Q1 | F7: GOING UNIT PRICE FOB EUR 1404Q1 | G7: TOTAL PRICE ریال | H7: TOTAL PRICE FOB € | I7: منبع | J7: بهای واحد (ریال) | K7: بهای واحد (یورو) | L7: بهای واحد (دلار) | M7: تاریخ مرجع | N7: منبع | O7: بهای واحد (ریال) | P7: بهای واحد (یورو) | Q7: بهای واحد (دلار) | R7: تاریخ مرجع | S7: منبع | T7: بهای واحد (ریال) | U7: بهای واحد (یورو) | V7: بهای واحد (دلار) | W7: تاریخ مرجع | AH7: No. of available quotations in IRR | AI7: No. of available quotations in EUR | AJ7: No. of available quotations in USD | AK7: avg. of IRR quotations converted to EUR | AL7: avg. of EUR quotations EUR | AM7: avg. of USD quotations converted to EUR | AN7: aggregate average quoted unit price (all in EUR) | AO7: Ref. Currency | AP7: quoted unit price | AQ7: Unit Price (Rials) | AR7: Unit Price 'FOB' (€) | AS7: NEW ITEM unit price IRR | AT7: NEW ITEM unit price EUR
A8: PK-132 | B8: Nutshell Filter Package Type: Auotomatic Backwashable Including: 2 x 100% Filter Vessels Rated Flow Rate (Kg/hr): 161650 Discharge Free Oil Content (ppmw): 25 Design Pressure: 10.5 Barg Design Temperature: -2.8 / 95 oC Material (Shell/Heads): SA 516 Gr. 70 Material (Internal Wetted Parts): Duplex S.S. NACE 'MR-0175' Required: Yes Agitator Required: Yes Design Code & Standard: ASME VIII, DIV.1 & IPS-G-ME-150 | C8: 1 | E8: =IF(AND(AO8="IRR",SUM(AH8:AJ8)>0),AP8,IF(AND(AO8="IRR",AQ8<>""),AQ8*'[5]Basic INFO'!$E$127,IF(AO8="IRR",AS8,""))) | F8: =IF(AND(AO8="EUR",SUM(AH8:AJ8)>0),AP8,IF(AND(AO8="EUR",AR8<>""),AR8*'[5]Basic INFO'!$C$138,IF(AO8="EUR",AT8,""))) -> 534220.41 | G8: =IF(AO8="IRR",C8*E8,"") | H8: =IF(AO8="EUR",C8*F8,"") -> 534220.41 | I8: آبسان پالایش | M8: no reply | N8: چمان | R8: no reply | S8: هامون راه | U8: 534220.41 | W8: 45796 | AH8: =IF(B8="","",COUNT(J8,O8,T8,Y8,AD8)) -> 0 | AI8: =IF(B8="","",COUNT(K8,P8,U8,Z8,AE8)) -> 1 | AJ8: =IF(B8="","",COUNT(L8,Q8,V8,AA8,AF8)) -> 0 | AK8: =IF(AND(AH8<>"",AH8>0),AVERAGE(J8,O8,T8,Y8,AD8)/('[5]Basic INFO'!$C$101*'[5]Basic INFO'!$C$103),"") | AL8: =IF(AND(AI8<>"",AI8>0),AVERAGE(K8,P8,U8,Z8,AE8),"") -> 534220.41 | AM8: =IF(AND(AJ8<>"",AJ8>0),AVERAGE(L8,Q8,V8,AA8,AF8)/'[5]Basic INFO'!$C$103,"") | AN8: =IF(SUM(AH8:AJ8)<>0,AVERAGE(AK8:AM8),"") -> 534220.41 | AO8: EUR | AP8: =IF(B8="","",IF(SUM(AH8:AJ8)=0,"",IF(AO8="IRR",AN8*('[5]Basic INFO'!$C$101*'[5]Basic INFO'!$C$103),IF(AO8="EUR",AN8,AP8)))) -> 534220.41 | AR8: 180000
A9: F-121 | B9: Pumps Sealing Water Filter Type: Auotomatic Self Cleaning Flow Rate: 3 m3/hr Design Pressure: 15.5 Barg Design Temperature: -2.8 / 85 oC Material (Shell/Heads): C.S. Design Code & Standard: ASME VIII, DIV.1 & IPS-G-ME-150 | C9: 1 | E9: =IF(AND(AO9="IRR",SUM(AH9:AJ9)>0),AP9,IF(AND(AO9="IRR",AQ9<>""),AQ9*'[5]Basic INFO'!$E$127,IF(AO9="IRR",AS9,""))) -> 1.6259615e+10 | F9: =IF(AND(AO9="EUR",SUM(AH9:AJ9)>0),AP9,IF(AND(AO9="EUR",AR9<>""),AR9*'[5]Basic INFO'!$C$138,IF(AO9="EUR",AT9,""))) | G9: =IF(AO9="IRR",C9*E9,"") -> 1.6259615e+10 | H9: =IF(AO9="EUR",C9*F9,"") | I9: آبسان پالایش | M9: no reply | N9: چمان | R9: no reply | S9: هامون راه | W9: declined | AH9: =IF(B9="","",COUNT(J9,O9,T9,Y9,AD9)) -> 0 | AI9: =IF(B9="","",COUNT(K9,P9,U9,Z9,AE9)) -> 0 | AJ9: =IF(B9="","",COUNT(L9,Q9,V9,AA9,AF9)) -> 0 | AK9: =IF(AND(AH9<>"",AH9>0),AVERAGE(J9,O9,T9,Y9,AD9)/('[5]Basic INFO'!$C$101*'[5]Basic INFO'!$C$103),"") | AL9: =IF(AND(AI9<>"",AI9>0),AVERAGE(K9,P9,U9,Z9,AE9),"") | AM9: =IF(AND(AJ9<>"",AJ9>0),AVERAGE(L9,Q9,V9,AA9,AF9)/'[5]Basic INFO'!$C$103,"") | AN9: =IF(SUM(AH9:AJ9)<>0,AVERAGE(AK9:AM9),"") | AO9: IRR | AP9: =IF(B9="","",IF(SUM(AH9:AJ9)=0,"",IF(AO9="IRR",AN9*('[5]Basic INFO'!$C$101*'[5]Basic INFO'!$C$103),IF(AO9="EUR",AN9,AP9)))) | AQ9: 1000000000
B10: برآورد هزینه بدون سربار و مالیات بر ارزش افزوده | G10: =SUM(G8:G9) -> 1.6259615e+10 | H10: =SUM(H8:H9) -> 534220.41 | AQ10: Total Price (Rials) | AR10: Total Price (Euros)
B11: ضریب سربار تأمین کالا | G11: 1.18 | H11: 1.18
B12: مالیات بر ارزش افزوده | G12: 0.1 | H12: 0.1
B13: هزینه تأمین کالا + سربار + مالیات بر ارزش افزوده | G13: =ROUND((G10*G11*(1+G12))/1000000,0)*1000000 -> 21105000000 | H13: =ROUND(H10*H11*(1+H12)/1000,0)*1000 -> 693000
G14: =ROUND(SUMIF(AP:AP,">0",G:G)*G11*(1+G12)/1000000,0)*1000000 -> 0 | H14: =ROUND(SUMIF(AP:AP,">0",H:H)*H11*(1+H12)/1000,0)*1000 -> 693000

Sheet FLARE
A1: Project Title: Revamping of Pazanan II Desalting Plant
A2: Sub-Project Title: Basic Design Studies and Preparation of FEED Package for Revamping of Pazanan II Desalting Plant
A3: Project Budget Ref. 03229 (formerly 53-51-91211)
A4: Doc. Title: BASIC MTO & COST ESTMATION REPORT (MECHANICAL)
A5: Doc. Ref. 91211-PZN-ME-RE-451-R02
A6: FLARE PACKAGES | I6: استعلام 1 | N6: استعلام 2 | S6: استعلام 3
A7: Item No. | B7: Description | C7: Qty. (Set) | E7: GOING UNIT PRICE IRR 1404Q1 | F7: GOING UNIT PRICE FOB EUR 1404Q1 | G7: TOTAL PRICE ریال | H7: TOTAL PRICE FOB € | I7: منبع | J7: بهای واحد (ریال) | K7: بهای واحد (یورو) | L7: بهای واحد (دلار) | M7: تاریخ مرجع | N7: منبع | O7: بهای واحد (ریال) | P7: بهای واحد (یورو) | Q7: بهای واحد (دلار) | R7: تاریخ مرجع | S7: منبع | T7: بهای واحد (ریال) | U7: بهای واحد (یورو) | V7: بهای واحد (دلار) | W7: تاریخ مرجع | AH7: No. of available quotations in IRR | AI7: No. of available quotations in EUR | AJ7: No. of available quotations in USD | AK7: avg. of IRR quotations converted to EUR | AL7: avg. of EUR quotations EUR | AM7: avg. of USD quotations converted to EUR | AN7: aggregate average quoted unit price (all in EUR) | AO7: Ref. Currency | AP7: quoted unit price | AQ7: Unit Price (Rials) | AR7: Unit Price 'FOB' (€) | AS7: NEW ITEM unit price IRR | AT7: NEW ITEM unit price EUR
A8: PK-151 | B8: Flare Package Total Capacity (Kg/hr): 13060 Ignition System Type: Flame Front Gen. (Compressed Air) Stack Size (D x H): 16 in x 12 m Stack Support System: Self-Supported Design Code & Standard: API RP 521, API-537, ASME STS-1, IPS-G-ME-210, & IPS-E-PR-460 | C8: 1 | E8: =IF(AND(AO8="IRR",SUM(AH8:AJ8)>0),AP8,IF(AND(AO8="IRR",AQ8<>""),AQ8*'[5]Basic INFO'!$E$127,IF(AO8="IRR",AS8,""))) -> 1.2619659e+11 | F8: =IF(AND(AO8="EUR",SUM(AH8:AJ8)>0),AP8,IF(AND(AO8="EUR",AR8<>""),AR8*'[5]Basic INFO'!$C$138,IF(AO8="EUR",AT8,""))) | G8: =IF(AO8="IRR",C8*E8,"") -> 1.2619659e+11 | H8: =IF(AO8="EUR",C8*F8,"") | I8: مصنوعات فلزی سنگین | J8: - | K8: 181500 | M8: 45697 | N8: ماشین فولاد جنوب | O8: - | P8: - | R8: no reply | S8: طرح مکانیک گستر شیراز | T8: - | U8: - | W8: no reply | AH8: =IF(B8="","",COUNT(J8,O8,T8,Y8,AD8)) -> 0 | AI8: =IF(B8="","",COUNT(K8,P8,U8,Z8,AE8)) -> 1 | AJ8: =IF(B8="","",COUNT(L8,Q8,V8,AA8,AF8)) -> 0 | AK8: =IF(AND(AH8<>"",AH8>0),AVERAGE(J8,O8,T8,Y8,AD8)/('[5]Basic INFO'!$C$101*'[5]Basic INFO'!$C$103),"") | AL8: =IF(AND(AI8<>"",AI8>0),AVERAGE(K8,P8,U8,Z8,AE8),"") -> 181500 | AM8: =IF(AND(AJ8<>"",AJ8>0),AVERAGE(L8,Q8,V8,AA8,AF8)/'[5]Basic INFO'!$C$103,"") | AN8: =IF(SUM(AH8:AJ8)<>0,AVERAGE(AK8:AM8),"") -> 181500 | AO8: IRR | AP8: =IF(B8="","",IF(SUM(AH8:AJ8)=0,"",IF(AO8="IRR",AN8*('[5]Basic INFO'!$C$101*'[5]Basic INFO'!$C$103),IF(AO8="EUR",AN8,AP8)))) -> 1.2619659e+11 | AQ8: 3000000000
B9: برآورد هزینه بدون سربار و مالیات بر ارزش افزوده | G9: =SUM(G8) -> 1.2619659e+11 | H9: =SUM(H8) -> 0 | AQ9: Total Price (Rials) | AR9: Total Price (Euros)
B10: ضریب سربار تأمین کالا | G10: 1.18 | H10: 1.18
B11: مالیات بر ارزش افزوده | G11: 0.1 | H11: 0.1
B12: هزینه تأمین کالا + سربار + مالیات بر ارزش افزوده | G12: =ROUND((G9*G10*(1+G11))/1000000,0)*1000000 -> 163803000000 | H12: =ROUND(H9*H10*(1+H11)/1000,0)*1000 -> 0
G13: =ROUND(SUMIF(AP:AP,">0",G:G)*G10*(1+G11)/1000000,0)*1000000 -> 163803000000 | H13: =ROUND(SUMIF(AP:AP,">0",H:H)*H10*(1+H11)/1000,0)*1000 -> 0

Sheet BURN PIT
A1: Project Title: Revamping of Pazanan II Desalting Plant
A2: Sub-Project Title: Basic Design Studies and Preparation of FEED Package for Revamping of Pazanan II Desalting Plant
A3: Project Budget Ref. 03229 (formerly 53-51-91211)
A4: Doc. Title: BASIC MTO & COST ESTMATION REPORT (MECHANICAL)
A5: Doc. Ref. 91211-PZN-ME-RE-451-R02
A6: BURN PIT IGNITION PACKAGES | I6: استعلام 1 | N6: استعلام 2 | S6: استعلام 3
A7: Item No. | B7: Description | C7: Qty. (Set) | E7: GOING UNIT PRICE IRR 1404Q1 | F7: GOING UNIT PRICE FOB EUR 1404Q1 | G7: TOTAL PRICE ریال | H7: TOTAL PRICE FOB € | I7: منبع | J7: بهای واحد (ریال) | K7: بهای واحد (یورو) | L7: بهای واحد (دلار) | M7: تاریخ مرجع | N7: منبع | O7: بهای واحد (ریال) | P7: بهای واحد (یورو) | Q7: بهای واحد (دلار) | R7: تاریخ مرجع | S7: منبع | T7: بهای واحد (ریال) | U7: بهای واحد (یورو) | V7: بهای واحد (دلار) | W7: تاریخ مرجع | AH7: No. of available quotations in IRR | AI7: No. of available quotations in EUR | AJ7: No. of available quotations in USD | AK7: avg. of IRR quotations converted to EUR | AL7: avg. of EUR quotations EUR | AM7: avg. of USD quotations converted to EUR | AN7: aggregate average quoted unit price (all in EUR) | AO7: Ref. Currency | AP7: quoted unit price | AQ7: Unit Price (Rials) | AR7: Unit Price 'FOB' (€) | AS7: NEW ITEM unit price IRR | AT7: NEW ITEM unit price EUR
A8: PK-201 | B8: Burn Pit Ignition Package Ignition System Type: Flame Front Gen. (Compressed Air) Burn Pit Diameter: 11 m Electrical Duty: 1 KW Min. Elect. Equip. Protection: IP 56 | C8: 1 | E8: =IF(AND(AO8="IRR",SUM(AH8:AJ8)>0),AP8,IF(AND(AO8="IRR",AQ8<>""),AQ8*'[5]Basic INFO'!$E$127,IF(AO8="IRR",AS8,""))) -> 7.300629e+10 | F8: =IF(AND(AO8="EUR",SUM(AH8:AJ8)>0),AP8,IF(AND(AO8="EUR",AR8<>""),AR8*'[5]Basic INFO'!$C$138,IF(AO8="EUR",AT8,""))) | G8: =IF(AO8="IRR",C8*E8,"") -> 7.300629e+10 | H8: =IF(AO8="EUR",C8*F8,"") | I8: مصنوعات فلزی سنگین | J8: - | K8: 105000 | M8: 45697 | N8: ماشین فولاد جنوب | O8: - | P8: - | R8: no reply | S8: طرح مکانیک گستر شیراز | T8: - | U8: - | W8: no reply | AH8: =IF(B8="","",COUNT(J8,O8,T8,Y8,AD8)) -> 0 | AI8: =IF(B8="","",COUNT(K8,P8,U8,Z8,AE8)) -> 1 | AJ8: =IF(B8="","",COUNT(L8,Q8,V8,AA8,AF8)) -> 0 | AK8: =IF(AND(AH8<>"",AH8>0),AVERAGE(J8,O8,T8,Y8,AD8)/('[5]Basic INFO'!$C$101*'[5]Basic INFO'!$C$103),"") | AL8: =IF(AND(AI8<>"",AI8>0),AVERAGE(K8,P8,U8,Z8,AE8),"") -> 105000 | AM8: =IF(AND(AJ8<>"",AJ8>0),AVERAGE(L8,Q8,V8,AA8,AF8)/'[5]Basic INFO'!$C$103,"") | AN8: =IF(SUM(AH8:AJ8)<>0,AVERAGE(AK8:AM8),"") -> 105000 | AO8: IRR | AP8: =IF(B8="","",IF(SUM(AH8:AJ8)=0,"",IF(AO8="IRR",AN8*('[5]Basic INFO'!$C$101*'[5]Basic INFO'!$C$103),IF(AO8="EUR",AN8,AP8)))) -> 7.300629e+10 | AQ8: 2000000000
B9: برآورد هزینه بدون سربار و مالیات بر ارزش افزوده | G9: =SUM(G8) -> 7.300629e+10 | H9: =SUM(H8) -> 0 | AQ9: Total Price (Rials) | AR9: Total Price (Euros)
B10: ضریب سربار تأمین کالا | G10: 1.18 | H10: 1.18
B11: مالیات بر ارزش افزوده | G11: 0.1 | H11: 0.1
B12: هزینه تأمین کالا + سربار + مالیات بر ارزش افزوده | G12: =ROUND((G9*G10*(1+G11))/1000000,0)*1000000 -> 94762000000 | H12: =ROUND(H9*H10*(1+H11)/1000,0)*1000 -> 0
G13: =ROUND(SUMIF(AP:AP,">0",G:G)*G10*(1+G11)/1000000,0)*1000000 -> 94762000000 | H13: =ROUND(SUMIF(AP:AP,">0",H:H)*H10*(1+H11)/1000,0)*1000 -> 0

Sheet AIR COMP.
A1: Project Title: Revamping of Pazanan II Desalting Plant
A2: Sub-Project Title: Basic Design Studies and Preparation of FEED Package for Revamping of Pazanan II Desalting Plant
A3: Project Budget Ref. 03229 (formerly 53-51-91211)
A4: Doc. Title: BASIC MTO & COST ESTMATION REPORT (MECHANICAL)
A5: Doc. Ref. 91211-PZN-ME-RE-451-R02
A6: AIR COMPRESSOR PACKAGES | I6: استعلام 1 | N6: استعلام 2 | S6: استعلام 3
A7: Item No. | B7: Description | C7: Qty. (Set) | E7: GOING UNIT PRICE IRR 1404Q1 | F7: GOING UNIT PRICE FOB EUR 1404Q1 | G7: TOTAL PRICE ریال | H7: TOTAL PRICE FOB € | I7: منبع | J7: بهای واحد (ریال) | K7: بهای واحد (یورو) | L7: بهای واحد (دلار) | M7: تاریخ مرجع | N7: منبع | O7: بهای واحد (ریال) | P7: بهای واحد (یورو) | Q7: بهای واحد (دلار) | R7: تاریخ مرجع | S7: منبع | T7: بهای واحد (ریال) | U7: بهای واحد (یورو) | V7: بهای واحد (دلار) | W7: تاریخ مرجع | AH7: No. of available quotations in IRR | AI7: No. of available quotations in EUR | AJ7: No. of available quotations in USD | AK7: avg. of IRR quotations converted to EUR | AL7: avg. of EUR quotations EUR | AM7: avg. of USD quotations converted to EUR | AN7: aggregate average quoted unit price (all in EUR) | AO7: Ref. Currency | AP7: quoted unit price | AQ7: Unit Price (Rials) | AR7: Unit Price 'FOB' (€) | AS7: NEW ITEM unit price IRR | AT7: NEW ITEM unit price EUR
A8: PK-141 A/B | B8: Air Compressor Packages Type: Non-Lubricated, Reciprocating Normal Flow Rate (m3/hr): 300 Discharge Pressure: 9 Barg Design Code & Standard: API 618 & IPS-M-PM-211 | C8: 2 | E8: =IF(AND(AO8="IRR",SUM(AH8:AJ8)>0),AP8,IF(AND(AO8="IRR",AQ8<>""),AQ8*'[5]Basic INFO'!$E$127,IF(AO8="IRR",AS8,""))) -> 6.7791555e+10 | F8: =IF(AND(AO8="EUR",SUM(AH8:AJ8)>0),AP8,IF(AND(AO8="EUR",AR8<>""),AR8*'[5]Basic INFO'!$C$138,IF(AO8="EUR",AT8,""))) | G8: =IF(AO8="IRR",C8*E8,"") -> 1.3558311e+11 | H8: =IF(AO8="EUR",C8*F8,"") | I8: فراز کمپرسور | M8: no reply | N8: صنایع هوای فشرده | P8: =195000/2 -> 97500 | R8: 45784 | S8: هوایار | W8: no reply | AH8: =IF(B8="","",COUNT(J8,O8,T8,Y8,AD8)) -> 0 | AI8: =IF(B8="","",COUNT(K8,P8,U8,Z8,AE8)) -> 1 | AJ8: =IF(B8="","",COUNT(L8,Q8,V8,AA8,AF8)) -> 0 | AK8: =IF(AND(AH8<>"",AH8>0),AVERAGE(J8,O8,T8,Y8,AD8)/('[5]Basic INFO'!$C$101*'[5]Basic INFO'!$C$103),"") | AL8: =IF(AND(AI8<>"",AI8>0),AVERAGE(K8,P8,U8,Z8,AE8),"") -> 97500 | AM8: =IF(AND(AJ8<>"",AJ8>0),AVERAGE(L8,Q8,V8,AA8,AF8)/'[5]Basic INFO'!$C$103,"") | AN8: =IF(SUM(AH8:AJ8)<>0,AVERAGE(AK8:AM8),"") -> 97500 | AO8: IRR | AP8: =IF(B8="","",IF(SUM(AH8:AJ8)=0,"",IF(AO8="IRR",AN8*('[5]Basic INFO'!$C$101*'[5]Basic INFO'!$C$103),IF(AO8="EUR",AN8,AP8)))) -> 6.7791555e+10 | AQ8: 11000000000
B9: برآورد هزینه بدون سربار و مالیات بر ارزش افزوده | G9: =SUM(G8) -> 1.3558311e+11 | H9: =SUM(H8) -> 0 | AQ9: Total Price (Rials) | AR9: Total Price (Euros)
B10: ضریب سربار تأمین کالا | G10: 1.18 | H10: 1.18
B11: مالیات بر ارزش افزوده | G11: 0.1 | H11: 0.1
B12: هزینه تأمین کالا + سربار + مالیات بر ارزش افزوده | G12: =ROUND((G9*G10*(1+G11))/1000000,0)*1000000 -> 175987000000 | H12: =ROUND(H9*H10*(1+H11)/1000,0)*1000 -> 0
G13: =ROUND(SUMIF(AP:AP,">0",G:G)*G10*(1+G11)/1000000,0)*1000000 -> 175987000000 | H13: =ROUND(SUMIF(AP:AP,">0",H:H)*H10*(1+H11)/1000,0)*1000 -> 0

Sheet AIR DRYER
A1: Project Title: Revamping of Pazanan II Desalting Plant
A2: Sub-Project Title: Basic Design Studies and Preparation of FEED Package for Revamping of Pazanan II Desalting Plant
A3: Project Budget Ref. 03229 (formerly 53-51-91211)
A4: Doc. Title: BASIC MTO & COST ESTMATION REPORT (MECHANICAL)
A5: Doc. Ref. 91211-PZN-ME-RE-451-R02
A6: AIR DRYER PACKAGES | I6: استعلام 1 | N6: استعلام 2 | S6: استعلام 3
A7: Item No. | B7: Description | C7: Qty. (Set) | E7: GOING UNIT PRICE IRR 1404Q1 | F7: GOING UNIT PRICE FOB EUR 1404Q1 | G7: TOTAL PRICE ریال | H7: TOTAL PRICE FOB € | I7: منبع | J7: بهای واحد (ریال) | K7: بهای واحد (یورو) | L7: بهای واحد (دلار) | M7: تاریخ مرجع | N7: منبع | O7: بهای واحد (ریال) | P7: بهای واحد (یورو) | Q7: بهای واحد (دلار) | R7: تاریخ مرجع | S7: منبع | T7: بهای واحد (ریال) | U7: بهای واحد (یورو) | V7: بهای واحد (دلار) | W7: تاریخ مرجع | AH7: No. of available quotations in IRR | AI7: No. of available quotations in EUR | AJ7: No. of available quotations in USD | AK7: avg. of IRR quotations converted to EUR | AL7: avg. of EUR quotations EUR | AM7: avg. of USD quotations converted to EUR | AN7: aggregate average quoted unit price (all in EUR) | AO7: Ref. Currency | AP7: quoted unit price | AQ7: Unit Price (Rials) | AR7: Unit Price 'FOB' (€) | AS7: NEW ITEM unit price IRR | AT7: NEW ITEM unit price EUR
A8: PK-142 | B8: Air Dryer Packages Type: Adsorber (heatless-pressure swig) Drying Medium : Solid Desicant Inlet Flow Rate (m3/hr): 190 Design Pressure: 13.5 Barg Design Temperature: -2.8 / 85 oC Tower Qty.: 2 No. of Pre-Filter Req'd: 2 No. of After-Filter Req'd: 2 Material: C.S. Design Code & Standard: ASME VIII, DIV.1 & IPS-G-ME-150 | C8: 1 | E8: =IF(AND(AO8="IRR",SUM(AH8:AJ8)>0),AP8,IF(AND(AO8="IRR",AQ8<>""),AQ8*'[5]Basic INFO'!$E$127,IF(AO8="IRR",AS8,""))) -> 8.1298077e+09 | F8: =IF(AND(AO8="EUR",SUM(AH8:AJ8)>0),AP8,IF(AND(AO8="EUR",AR8<>""),AR8*'[5]Basic INFO'!$C$138,IF(AO8="EUR",AT8,""))) | G8: =IF(AO8="IRR",C8*E8,"") -> 8.1298077e+09 | H8: =IF(AO8="EUR",C8*F8,"") | I8: فراز کمپرسور | M8: no reply | N8: صنایع هوای فشرده | R8: declined | S8: هوایار | W8: no reply | AH8: =IF(B8="","",COUNT(J8,O8,T8,Y8,AD8)) -> 0 | AI8: =IF(B8="","",COUNT(K8,P8,U8,Z8,AE8)) -> 0 | AJ8: =IF(B8="","",COUNT(L8,Q8,V8,AA8,AF8)) -> 0 | AK8: =IF(AND(AH8<>"",AH8>0),AVERAGE(J8,O8,T8,Y8,AD8)/('[5]Basic INFO'!$C$101*'[5]Basic INFO'!$C$103),"") | AL8: =IF(AND(AI8<>"",AI8>0),AVERAGE(K8,P8,U8,Z8,AE8),"") | AM8: =IF(AND(AJ8<>"",AJ8>0),AVERAGE(L8,Q8,V8,AA8,AF8)/'[5]Basic INFO'!$C$103,"") | AN8: =IF(SUM(AH8:AJ8)<>0,AVERAGE(AK8:AM8),"") | AO8: IRR | AP8: =IF(B8="","",IF(SUM(AH8:AJ8)=0,"",IF(AO8="IRR",AN8*('[5]Basic INFO'!$C$101*'[5]Basic INFO'!$C$103),IF(AO8="EUR",AN8,AP8)))) | AQ8: 500000000
B9: برآورد هزینه بدون سربار و مالیات بر ارزش افزوده | G9: =SUM(G8) -> 8.1298077e+09 | H9: =SUM(H8) -> 0 | AQ9: Total Price (Rials) | AR9: Total Price (Euros)
B10: ضریب سربار تأمین کالا | G10: 1.18 | H10: 1.18
B11: مالیات بر ارزش افزوده | G11: 0.1 | H11: 0.1
B12: هزینه تأمین کالا + سربار + مالیات بر ارزش افزوده | G12: =ROUND((G9*G10*(1+G11))/1000000,0)*1000000 -> 10552000000 | H12: =ROUND(H9*H10*(1+H11)/1000,0)*1000 -> 0
G13: =ROUND(SUMIF(AP:AP,">0",G:G)*G10*(1+G11)/1000000,0)*1000000 -> 0 | H13: =ROUND(SUMIF(AP:AP,">0",H:H)*H10*(1+H11)/1000,0)*1000 -> 0

Sheet CRANES
A1: Project Title: Revamping of Pazanan II Desalting Plant
A2: Sub-Project Title: Basic Design Studies and Preparation of FEED Package for Revamping of Pazanan II Desalting Plant
A3: Project Budget Ref. 03229 (formerly 53-51-91211)
A4: Doc. Title: BASIC MTO & COST ESTMATION REPORT (MECHANICAL)
A5: Doc. Ref. 91211-PZN-ME-RE-451-R02
A6: OVERHEAD TRAVELING CRANES | I6: استعلام 1 | N6: استعلام 2 | S6: استعلام 3
A7: Item No. | B7: Description | C7: Qty. (Set) | E7: GOING UNIT PRICE IRR 1404Q1 | F7: GOING UNIT PRICE FOB EUR 1404Q1 | G7: TOTAL PRICE ریال | H7: TOTAL PRICE FOB € | I7: منبع | J7: بهای واحد (ریال) | K7: بهای واحد (یورو) | L7: بهای واحد (دلار) | M7: تاریخ مرجع | N7: منبع | O7: بهای واحد (ریال) | P7: بهای واحد (یورو) | Q7: بهای واحد (دلار) | R7: تاریخ مرجع | S7: منبع | T7: بهای واحد (ریال) | U7: بهای واحد (یورو) | V7: بهای واحد (دلار) | W7: تاریخ مرجع | AH7: No. of available quotations in IRR | AI7: No. of available quotations in EUR | AJ7: No. of available quotations in USD | AK7: avg. of IRR quotations converted to EUR | AL7: avg. of EUR quotations EUR | AM7: avg. of USD quotations converted to EUR | AN7: aggregate average quoted unit price (all in EUR) | AO7: Ref. Currency | AP7: quoted unit price | AQ7: Unit Price (Rials) | AR7: Unit Price 'FOB' (€) | AS7: NEW ITEM unit price IRR | AT7: NEW ITEM unit price EUR
A8: CN-131 | B8: Disposal Pumps Shelter Cranes Type: Top Running, Elect. Motor Driven Capacity (Kg): 5000 Lift / Span / Travel (m): 5.9 / 8.15 / 24 Motor Charactristics: IP65- 400V,3Ph,50Hz & EEX-e, IIB, T3 Design Code & Standard: BSI 466 & IPS-M-GN-350 | C8: 1 | E8: =IF(AND(AO8="IRR",SUM(AH8:AJ8)>0),AP8,IF(AND(AO8="IRR",AQ8<>""),AQ8*'[5]Basic INFO'!$E$127,IF(AO8="IRR",AS8,""))) -> 3.2663237e+10 | F8: =IF(AND(AO8="EUR",SUM(AH8:AJ8)>0),AP8,IF(AND(AO8="EUR",AR8<>""),AR8*'[5]Basic INFO'!$C$138,IF(AO8="EUR",AT8,""))) | G8: =IF(AO8="IRR",C8*E8,"") -> 3.2663237e+10 | H8: =IF(AO8="EUR",C8*F8,"") | I8: توان سازه کیان | L8: 49600 | M8: 45703 | N8: ماشین سازی منگان | R8: declined | S8: سازه های فلزی و جرثقیل فسان | W8: declined | AH8: =IF(B8="","",COUNT(J8,O8,T8,Y8,AD8)) -> 0 | AI8: =IF(B8="","",COUNT(K8,P8,U8,Z8,AE8)) -> 0 | AJ8: =IF(B8="","",COUNT(L8,Q8,V8,AA8,AF8)) -> 1 | AK8: =IF(AND(AH8<>"",AH8>0),AVERAGE(J8,O8,T8,Y8,AD8)/('[5]Basic INFO'!$C$101*'[5]Basic INFO'!$C$103),"") | AL8: =IF(AND(AI8<>"",AI8>0),AVERAGE(K8,P8,U8,Z8,AE8),"") | AM8: =IF(AND(AJ8<>"",AJ8>0),AVERAGE(L8,Q8,V8,AA8,AF8)/'[5]Basic INFO'!$C$103,"") -> 46977.32 | AN8: =IF(SUM(AH8:AJ8)<>0,AVERAGE(AK8:AM8),"") -> 46977.32 | AO8: IRR | AP8: =IF(B8="","",IF(SUM(AH8:AJ8)=0,"",IF(AO8="IRR",AN8*('[5]Basic INFO'!$C$101*'[5]Basic INFO'!$C$103),IF(AO8="EUR",AN8,AP8)))) -> 3.2663237e+10 | AQ8: 3260000000
A9: CN-141 | B9: Utility Building Crane Type: Top Running, Elect. Motor Driven Capacity (Kg): 5000 Lift / Span / Travel (m): 5.9 / 8.15 / 18 Motor Charactristics: IP65- 400V,3Ph,50Hz Design Code & Standard: BSI 466 & IPS-M-GN-350 | C9: 1 | E9: =IF(AND(AO9="IRR",SUM(AH9:AJ9)>0),AP9,IF(AND(AO9="IRR",AQ9<>""),AQ9*'[5]Basic INFO'!$E$127,IF(AO9="IRR",AS9,""))) -> 14751139200 | F9: =IF(AND(AO9="EUR",SUM(AH9:AJ9)>0),AP9,IF(AND(AO9="EUR",AR9<>""),AR9*'[5]Basic INFO'!$C$138,IF(AO9="EUR",AT9,""))) | G9: =IF(AO9="IRR",C9*E9,"") -> 14751139200 | H9: =IF(AO9="EUR",C9*F9,"") | I9: توان سازه کیان | L9: 22400 | M9: 45703 | N9: ماشین سازی منگان | R9: declined | S9: سازه های فلزی و جرثقیل فسان | W9: declined | AH9: =IF(B9="","",COUNT(J9,O9,T9,Y9,AD9)) -> 0 | AI9: =IF(B9="","",COUNT(K9,P9,U9,Z9,AE9)) -> 0 | AJ9: =IF(B9="","",COUNT(L9,Q9,V9,AA9,AF9)) -> 1 | AK9: =IF(AND(AH9<>"",AH9>0),AVERAGE(J9,O9,T9,Y9,AD9)/('[5]Basic INFO'!$C$101*'[5]Basic INFO'!$C$103),"") | AL9: =IF(AND(AI9<>"",AI9>0),AVERAGE(K9,P9,U9,Z9,AE9),"") | AM9: =IF(AND(AJ9<>"",AJ9>0),AVERAGE(L9,Q9,V9,AA9,AF9)/'[5]Basic INFO'!$C$103,"") -> 21215.564 | AN9: =IF(SUM(AH9:AJ9)<>0,AVERAGE(AK9:AM9),"") -> 21215.564 | AO9: IRR | AP9: =IF(B9="","",IF(SUM(AH9:AJ9)=0,"",IF(AO9="IRR",AN9*('[5]Basic INFO'!$C$101*'[5]Basic INFO'!$C$103),IF(AO9="EUR",AN9,AP9)))) -> 14751139200 | AQ9: 960000000
A10: CN-161 | B10: O.W.S. Pumps Shelter Crane Type: Top Running, Elect. Motor Driven Capacity (Kg): 3000 Lift / Span / Travel (m): 3.9 / 4.15 / 7.5 Motor Charactristics: IP65- 400V,3Ph,50Hz Design Code & Standard: BSI 466 & IPS-M-GN-350 | C10: 1 | E10: =IF(AND(AO10="IRR",SUM(AH10:AJ10)>0),AP10,IF(AND(AO10="IRR",AQ10<>""),AQ10*'[5]Basic INFO'!$E$127,IF(AO10="IRR",AS10,""))) -> 13434073200 | F10: =IF(AND(AO10="EUR",SUM(AH10:AJ10)>0),AP10,IF(AND(AO10="EUR",AR10<>""),AR10*'[5]Basic INFO'!$C$138,IF(AO10="EUR",AT10,""))) | G10: =IF(AO10="IRR",C10*E10,"") -> 13434073200 | H10: =IF(AO10="EUR",C10*F10,"") | I10: توان سازه کیان | L10: 20400 | M10: 45703 | N10: ماشین سازی منگان | R10: declined | S10: سازه های فلزی و جرثقیل فسان | W10: declined | AH10: =IF(B10="","",COUNT(J10,O10,T10,Y10,AD10)) -> 0 | AI10: =IF(B10="","",COUNT(K10,P10,U10,Z10,AE10)) -> 0 | AJ10: =IF(B10="","",COUNT(L10,Q10,V10,AA10,AF10)) -> 1 | AK10: =IF(AND(AH10<>"",AH10>0),AVERAGE(J10,O10,T10,Y10,AD10)/('[5]Basic INFO'!$C$101*'[5]Basic INFO'!$C$103),"") | AL10: =IF(AND(AI10<>"",AI10>0),AVERAGE(K10,P10,U10,Z10,AE10),"") | AM10: =IF(AND(AJ10<>"",AJ10>0),AVERAGE(L10,Q10,V10,AA10,AF10)/'[5]Basic INFO'!$C$103,"") -> 19321.317 | AN10: =IF(SUM(AH10:AJ10)<>0,AVERAGE(AK10:AM10),"") -> 19321.317 | AO10: IRR | AP10: =IF(B10="","",IF(SUM(AH10:AJ10)=0,"",IF(AO10="IRR",AN10*('[5]Basic INFO'!$C$101*'[5]Basic INFO'!$C$103),IF(AO10="EUR",AN10,AP10)))) -> 13434073200 | AQ10: 2800000000
A11: CN-181 | B11: Chemical Storage Shelter Cranes Type: Top Running, Elect. Motor Driven Capacity (Kg): 1000 Lift / Span / Travel (m): 7.3 / 8.15 / 31 Motor Charactristics: IP65- 400V,3Ph,50Hz & EEX-e, IIB, T3 Design Code & Standard: BSI 466 & IPS-M-GN-350 | C11: 1 | E11: =IF(AND(AO11="IRR",SUM(AH11:AJ11)>0),AP11,IF(AND(AO11="IRR",AQ11<>""),AQ11*'[5]Basic INFO'!$E$127,IF(AO11="IRR",AS11,""))) -> 28053505800 | F11: =IF(AND(AO11="EUR",SUM(AH11:AJ11)>0),AP11,IF(AND(AO11="EUR",AR11<>""),AR11*'[5]Basic INFO'!$C$138,IF(AO11="EUR",AT11,""))) | G11: =IF(AO11="IRR",C11*E11,"") -> 28053505800 | H11: =IF(AO11="EUR",C11*F11,"") | I11: توان سازه کیان | L11: 42600 | M11: 45703 | N11: ماشین سازی منگان | R11: declined | S11: سازه های فلزی و جرثقیل فسان | W11: declined | AH11: =IF(B11="","",COUNT(J11,O11,T11,Y11,AD11)) -> 0 | AI11: =IF(B11="","",COUNT(K11,P11,U11,Z11,AE11)) -> 0 | AJ11: =IF(B11="","",COUNT(L11,Q11,V11,AA11,AF11)) -> 1 | AK11: =IF(AND(AH11<>"",AH11>0),AVERAGE(J11,O11,T11,Y11,AD11)/('[5]Basic INFO'!$C$101*'[5]Basic INFO'!$C$103),"") | AL11: =IF(AND(AI11<>"",AI11>0),AVERAGE(K11,P11,U11,Z11,AE11),"") | AM11: =IF(AND(AJ11<>"",AJ11>0),AVERAGE(L11,Q11,V11,AA11,AF11)/'[5]Basic INFO'!$C$103,"") -> 40347.456 | AN11: =IF(SUM(AH11:AJ11)<>0,AVERAGE(AK11:AM11),"") -> 40347.456 | AO11: IRR | AP11: =IF(B11="","",IF(SUM(AH11:AJ11)=0,"",IF(AO11="IRR",AN11*('[5]Basic INFO'!$C$101*'[5]Basic INFO'!$C$103),IF(AO11="EUR",AN11,AP11)))) -> 28053505800 | AQ11: 2950000000
A12: CN-182 | B12: Chemical Inj. Package Shelter Cranes Type: Top Running, Elect. Motor Driven Capacity (Kg): 3000 Lift / Span / Travel (m): 5.9 / 9.15 / 20 Motor Charactristics: IP65- 400V,3Ph,50Hz & EEX-e, IIB, T3 Design Code & Standard: BSI 466 & IPS-M-GN-350 | C12: 1 | E12: =IF(AND(AO12="IRR",SUM(AH12:AJ12)>0),AP12,IF(AND(AO12="IRR",AQ12<>""),AQ12*'[5]Basic INFO'!$E$127,IF(AO12="IRR",AS12,""))) -> 3.0687638e+10 | F12: =IF(AND(AO12="EUR",SUM(AH12:AJ12)>0),AP12,IF(AND(AO12="EUR",AR12<>""),AR12*'[5]Basic INFO'!$C$138,IF(AO12="EUR",AT12,""))) | G12: =IF(AO12="IRR",C12*E12,"") -> 3.0687638e+10 | H12: =IF(AO12="EUR",C12*F12,"") | I12: توان سازه کیان | L12: 46600 | M12: 45703 | N12: ماشین سازی منگان | R12: declined | S12: سازه های فلزی و جرثقیل فسان | W12: declined | AH12: =IF(B12="","",COUNT(J12,O12,T12,Y12,AD12)) -> 0 | AI12: =IF(B12="","",COUNT(K12,P12,U12,Z12,AE12)) -> 0 | AJ12: =IF(B12="","",COUNT(L12,Q12,V12,AA12,AF12)) -> 1 | AK12: =IF(AND(AH12<>"",AH12>0),AVERAGE(J12,O12,T12,Y12,AD12)/('[5]Basic INFO'!$C$101*'[5]Basic INFO'!$C$103),"") | AL12: =IF(AND(AI12<>"",AI12>0),AVERAGE(K12,P12,U12,Z12,AE12),"") | AM12: =IF(AND(AJ12<>"",AJ12>0),AVERAGE(L12,Q12,V12,AA12,AF12)/'[5]Basic INFO'!$C$103,"") -> 44135.95 | AN12: =IF(SUM(AH12:AJ12)<>0,AVERAGE(AK12:AM12),"") -> 44135.95 | AO12: IRR | AP12: =IF(B12="","",IF(SUM(AH12:AJ12)=0,"",IF(AO12="IRR",AN12*('[5]Basic INFO'!$C$101*'[5]Basic INFO'!$C$103),IF(AO12="EUR",AN12,AP12)))) -> 3.0687638e+10 | AQ12: 2950000000
A13: CN-191 | B13: Fire Water Pumps Shelter Crane Type: Top Running, Elect. Motor Driven Capacity (Kg): 5000 Lift / Span / Travel (m): 5.9 / 10.15 / 24 Motor Charactristics: IP65- 400V,3Ph,50Hz Design Code & Standard: BSI 466 & IPS-M-GN-350 | C13: 1 | E13: =IF(AND(AO13="IRR",SUM(AH13:AJ13)>0),AP13,IF(AND(AO13="IRR",AQ13<>""),AQ13*'[5]Basic INFO'!$E$127,IF(AO13="IRR",AS13,""))) -> 15738938700 | F13: =IF(AND(AO13="EUR",SUM(AH13:AJ13)>0),AP13,IF(AND(AO13="EUR",AR13<>""),AR13*'[5]Basic INFO'!$C$138,IF(AO13="EUR",AT13,""))) | G13: =IF(AO13="IRR",C13*E13,"") -> 15738938700 | H13: =IF(AO13="EUR",C13*F13,"") | I13: توان سازه کیان | L13: 23900 | M13: 45703 | N13: ماشین سازی منگان | R13: declined | S13: سازه های فلزی و جرثقیل فسان | W13: declined | AH13: =IF(B13="","",COUNT(J13,O13,T13,Y13,AD13)) -> 0 | AI13: =IF(B13="","",COUNT(K13,P13,U13,Z13,AE13)) -> 0 | AJ13: =IF(B13="","",COUNT(L13,Q13,V13,AA13,AF13)) -> 1 | AK13: =IF(AND(AH13<>"",AH13>0),AVERAGE(J13,O13,T13,Y13,AD13)/('[5]Basic INFO'!$C$101*'[5]Basic INFO'!$C$103),"") | AL13: =IF(AND(AI13<>"",AI13>0),AVERAGE(K13,P13,U13,Z13,AE13),"") | AM13: =IF(AND(AJ13<>"",AJ13>0),AVERAGE(L13,Q13,V13,AA13,AF13)/'[5]Basic INFO'!$C$103,"") -> 22636.249 | AN13: =IF(SUM(AH13:AJ13)<>0,AVERAGE(AK13:AM13),"") -> 22636.249 | AO13: IRR | AP13: =IF(B13="","",IF(SUM(AH13:AJ13)=0,"",IF(AO13="IRR",AN13*('[5]Basic INFO'!$C$101*'[5]Basic INFO'!$C$103),IF(AO13="EUR",AN13,AP13)))) -> 15738938700 | AQ13: 980000000
B14: برآورد هزینه بدون سربار و مالیات بر ارزش افزوده | G14: =SUM(G8:G13) -> 135328531500 | H14: =SUM(H8:H13) -> 0 | AQ14: Total Price (Rials) | AR14: Total Price (Euros)
B15: ضریب سربار تأمین کالا | G15: 1.18 | H15: 1.18
B16: مالیات بر ارزش افزوده | G16: 0.1 | H16: 0.1
B17: هزینه تأمین کالا + سربار + مالیات بر ارزش افزوده | G17: =ROUND((G14*G15*(1+G16))/1000000,0)*1000000 -> 175656000000 | H17: =ROUND(H14*H15*(1+H16)/1000,0)*1000 -> 0
G18: =ROUND(SUMIF(AP:AP,">0",G:G)*G15*(1+G16)/1000000,0)*1000000 -> 175656000000 | H18: =ROUND(SUMIF(AP:AP,">0",H:H)*H15*(1+H16)/1000,0)*1000 -> 0

Sheet Lab Equip
A1: Laboratory equipment list
A2: Desalting plant lab
A3: Item No. | B3: APPARATUS | C3: MODEL & Brand Name | D3: QUANTITY | E3: Cost estimate in 2013 (ref. Gachsaran IV B.R. 89205) | F3: unit price (Euros) | G3: unit price (Rials) | H3: total price (IRR) | I3: total price (Euros)
A4: 1 | B4: ATOMIC ABSORBTION | C4: Model: ZEEnit 700, Brand name: Analytik Jena | D4: 1 | E4: N/A | F4: 11781 | G4: 0 | H4: =D4*G4 -> 0 | I4: =D4*F4 -> 11781
A5: 2 | B5: ION METER | C5: Brand name: METEROHM | D5: 1 | E5: 13750 | F5: =E5 -> 13750 | G5: 0 | H5: =D5*G5 -> 0 | I5: =D5*F5 -> 13750
A6: 3 | B6: OXYGEN METER | C6: Brand name: TOXIRAE | D6: 2 | E6: 1260 | F6: =E6 -> 1260 | G6: 0 | H6: =D6*G6 -> 0 | I6: =D6*F6 -> 2520
A7: 4 | B7: BAROMETER | C7: brand name: DARTON | D7: 2 | E7: 2860 | F7: =E7 -> 2860 | G7: 0 | H7: =D7*G7 -> 0 | I7: =D7*F7 -> 5720
A8: Pazanan II central laboratory
A9: 1 | B9: OIL TEST CENTRIFUGE | C9: Model: 13-2142, Brand name: PETROTEST | D9: 1 | E9: 25500 | F9: =E9 -> 25500 | G9: 0 | H9: =D9*G9 -> 0 | I9: =D9*F9 -> 25500
A10: 2 | B10: DUAL EXTRACTION APPARATUS | C10: Model: K-46600, Brand name: KOEHLER | D10: 1 | E10: 20500 | F10: =E10 -> 20500 | G10: 0 | H10: =D10*G10 -> 0 | I10: =D10*F10 -> 20500
A11: 3 | B11: EVAPORATOR MANTLESS(500 cc) | C11: Model: LG-2ER, Brand name: ISOPAD | D11: 1 | E11: 1200 | F11: =E11 -> 1200 | G11: 0 | H11: =D11*G11 -> 0 | I11: =D11*F11 -> 1200
A12: 4 | B12: WATER STILL (STAINLESS STEEL) | C12: Model: L4, Brand name: MANESTY | D12: 1 | E12: 6700 | F12: =E12 -> 6700 | G12: 0 | H12: =D12*G12 -> 0 | I12: =D12*F12 -> 6700
A13: 5 | B13: PH METER | C13: Model: MP220, Brand name: MERLLER TOLEDO | D13: 1 | E13: 2500 | F13: =E13 -> 2500 | G13: 0 | H13: =D13*G13 -> 0 | I13: =D13*F13 -> 2500
A14: 6 | B14: BALANCE | C14: Model: AB204-S, Brand name: MERLLER TOLEDO | D14: 1 | E14: 6500 | F14: =E14 -> 6500 | G14: 0 | H14: =D14*G14 -> 0 | I14: =D14*F14 -> 6500
A15: 7 | B15: R.V.P AUTOMATIC | C15: Model: H.V.P. 420, Brand name: HERZOG | D15: 1 | E15: 55800 | F15: =E15 -> 55800 | G15: 0 | H15: =D15*G15 -> 0 | I15: =D15*F15 -> 55800
A16: 8 | B16: THERMOSTATIC WATER BATHS | C16: Model: T-1000E, Brand name: TAMSON | D16: 1 | E16: 5400 | F16: =E16 -> 5400 | G16: 0 | H16: =D16*G16 -> 0 | I16: =D16*F16 -> 5400
A17: 9 | B17: DENSITY METER | C17: Model: SVM-3000, Brand name: ANTON PAAR | D17: 1 | E17: 63300 | F17: =E17 -> 63300 | G17: 0 | H17: =D17*G17 -> 0 | I17: =D17*F17 -> 63300
A18: 10 | B18: OXYGEN METER | C18: Model: PGM-36, Brand name: TOXI-RAE | D18: 1 | E18: 1260 | F18: =E18 -> 1260 | G18: 0 | H18: =D18*G18 -> 0 | I18: =D18*F18 -> 1260
A19: 11 | B19: BARO METER | C19: Model: M-564, Brand name: DARTON | D19: 1 | E19: 2860 | F19: =E19 -> 2860 | G19: 0 | H19: =D19*G19 -> 0 | I19: =D19*F19 -> 2860
A20: 12 | B20: SALT IN CRUDE ANALYZER | C20: Model: SC-960, Brand name: HERZOG | D20: 1 | E20: 31000 | F20: =E20 -> 31000 | G20: 0 | H20: =D20*G20 -> 0 | I20: =D20*F20 -> 31000
A21: 13 | B21: WASTEWATER STORAGE TANK | C21: Capacity: 2000 Lit Material: High Density P.E. | D21: 1 | E21: N/A | F21: 0 | G21: 170000000 | H21: =D21*G21 -> 170000000 | I21: 0
B22: برآورد هزینه بدون سربار و مالیات بر ارزش افزوده | H22: =SUM(H4:H21) -> 170000000 | I22: =SUM(I4:I21) -> 256291
B23: ضریب سربار تأمین کالا | H23: 1.18 | I23: 1.18
B24: مالیات بر ارزش افزوده | H24: 0.1 | I24: 0.1
B25: هزینه تأمین کالا + سربار + مالیات بر ارزش افزوده | H25: =ROUND((H22*H23*(1+H24))/1000000,0)*1000000 -> 221000000 | I25: =ROUND(I22*I23*(1+I24)/1000,0)*1000 -> 333000

Sheet Consumables
A1: Ref. Doc. "Chemical Consumption List" 91211-PZN-PR-LI-136-R05
A2: UNIT | B2: TYPE OF CHEMICAL | C2: FLOWRATE | F2: MODE OF OPERATION
C3: MINIMUM (L/h) | D3: MAXIMUM (L/h) | E3: ANNUAL (m³) | F3: CONTINUOUS / INTERMITTENT | G3: FREQUENCY | H3: DURATION | J3: chemical | K3: annual (m3) | L3: commissioning period (m3, 1 month) | M3: 6-month operation | N3: weight (kg) | O3: بهای واحد سال 1392 پروژه گچساران 4 (Rial/Kg) | P3: بهای واحد | Q3: بهای کل
A4: Inlet of Coalescer Tank, Crude oil indirect fired heater & Desalting system | B4: Demulsifier (PK-181) | C4: =5*(378/1000) -> 1.89 | D4: =(80*(431/1000)+80*(444/1000)+80*(379/1000)+80*(436/1000))/4 -> 33.8 | E4: =D4*24*365/1000 -> 296.088 | F4: Continuous | J4: Demulsifier | K4: =SUM(E4,E14) -> 598.1328 | L4: =K4/12 -> 49.8444 | M4: NISOC | N4: =L4*1000 -> 49844.4 | O4: 64000 | P4: 3.6 | Q4: =N4*P4 -> 179439.84 | R4: =Q4/$Q$12 -> 0.40802055
A5: Inlet of Skimmer Tank & IGF System | B5: Reverse Demulsifier (PK-182) | C5: =0.1 -> 0.1 | D5: =2*5 -> 10 | E5: =D5*24*365/1000 -> 87.6 | F5: Continuous | J5: Reverse Demulsifier | K5: =E5 -> 87.6 | L5: =K5/12 -> 7.3 | M5: NISOC | N5: =L5*1000 -> 7300 | O5: 42000 | P5: 2.3 | Q5: =N5*P5 -> 16790 | R5: =Q5/$Q$12 -> 0.038178061
A6: Inlet of Dilution water Tank, dilution water enters sand jets of the Coalescer tank (TK-21) & Disposal water tank | B6: Biocide (Types A&B) (PK-183) | C6: =50*(16/1040) -> 0.76923077 | D6: =400*(132.5/1040) -> 50.961538 | E6: =D6*52*2/1000 -> 5.3 | F6: Intermittent | G6: Once a week | H6: 2 Hours | J6: Biocide (Types A&B) | K6: =E6 -> 5.3 | L6: =K6/12 -> 0.44166667 | M6: NISOC | N6: =L6*1000 -> 441.66667 | O6: 36000 | P6: 1.4 | Q6: =N6*P6 -> 618.33333 | R6: =Q6/$Q$12 -> 0.0014060016
A7: Inlet of Dilution water Tank | B7: Oxygen Scavenger (PK-184) | C7: =(0.1*10)*(16/1420) -> 0.011267606 | D7: =(12*15)*(53/1420) -> 6.7183099 | E7: =D7*24*365/1000 -> 58.852394 | F7: Continuous | J7: Oxygen Scavenger | K7: =SUM(E7:E9) -> 76.734824 | L7: =K7/12 -> 6.3945687 | M7: NISOC | N7: =L7*1000 -> 6394.5687 | O7: 26000 | P7: 1.2 | Q7: =N7*P7 -> 7673.4824 | R7: =Q7/$Q$12 -> 0.017448402
A8: Inlet of Disposal water Tank | B8: Oxygen Scavenger (PK-188) | C8: =(0.1*10)*(132.5/1420) -> 0.093309859 | D8: =(0.1*15)*(132.5/1420) -> 0.13996479 | E8: =D8*24*365/1000 -> 1.2260915 | F8: Continuous | J8: Anti-Scale | K8: =SUM(E10:E12) -> 61.123655 | L8: =K8/12 -> 5.0936379 | M8: NISOC | N8: =L8*1000 -> 5093.6379 | O8: 25000 | P8: 1.3 | Q8: =N8*P8 -> 6621.7293 | R8: =Q8/$Q$12 -> 0.015056866
A9: Evaporation Pond Return Line | B9: Oxygen Scavenger (PK-189) | C9: =(0.1*10)*(15/1420) -> 0.01056338 | D9: =(12*15)*(15/1420) -> 1.9014085 | E9: =D9*24*365/1000 -> 16.656338 | F9: Intermittent | G9: Temporary | J9: Corrosion Inhibitor | K9: =E13 -> 79.655882 | L9: =K9/12 -> 6.6379902 | M9: NISOC | N9: =L9*1000 -> 6637.9902 | O9: 42000 | P9: 1 | Q9: =N9*P9 -> 6637.9902 | R9: =Q9/$Q$12 -> 0.015093841
A10: Inlet of Dilution water Tank | B10: Anti-Scale (PK-185) | C10: =5*(16/1160) -> 0.068965517 | D10: =30*(53/1160) -> 1.3706897 | E10: =D10*24*365/1000 -> 12.007241 | F10: Continuous | J10: Ethylene Glycol | L10: 55 | M10: - | N10: =L10*1000 -> 55000 | O10: 55000 | P10: 4 | Q10: =N10*P10 -> 220000 | R10: =Q10/$Q$12 -> 0.50024856
A11: Inlet of Dilution water/waste water heat Exchanger | B11: Anti-Scale (PK-180) | C11: =5*(84.3/1160) -> 0.36336207 | D11: =30*(84.3/1160) -> 2.1801724 | E11: =D11*24*365/1000 -> 19.09831 | F11: Continuous | J11: other consumables (lubricants, detergents, etc) | N11: 1000 | P11: 2 | Q11: =N11*P11 -> 2000 | R11: =Q11/$Q$12 -> 0.0045477142
A12: Inlet of Disposal water tank | B12: Anti-Scale (PK-187) | C12: =5*(132.5/1160) -> 0.57112069 | D12: =30*(132.5/1160) -> 3.4267241 | E12: =D12*24*365/1000 -> 30.018103 | F12: Continuous | J12: برآورد هزینه بدون سربار و مالیات بر ارزش افزوده (بر حسب یورو) | Q12: =SUM(Q4:Q11) -> 439781.38
A13: Inlet of Dilution water Tank & Disposal water tank | B13: Corrosion Inhibitor (PK-186) | C13: =5*(132.5/1020) -> 0.6495098 | D13: =50*(53/1020)+50*(132.5/1020) -> 9.0931373 | E13: =D13*24*365/1000 -> 79.655882 | F13: Continuous | J13: برآورد هزینه بدون سربار و مالیات بر ارزش افزوده (تبدیل شده به ریال) | Q13: =Q12*'[5]Basic INFO'!$C$101*'[5]Basic INFO'!$C$103 -> 3.0577911e+11
A14: Production Unit Inlet Manifold | B14: Demulsifier (PK-212) | C14: =2 -> 2 | D14: =80*(431/1000) -> 34.48 | E14: =D14*24*365/1000 -> 302.0448 | F14: Continuous | J14: ضریب سربار تأمین کالا | Q14: 1.18
J15: مالیات بر ارزش افزوده | Q15: 0.1
A16: Notes: | J16: هزینه تأمین کالا + سربار + مالیات بر ارزش افزوده | Q16: =ROUND((Q13*Q14*(1+Q15))/1000000,0)*1000000 -> 396901000000 | R16: =Q16/('[5]EPC subtotals'!$B$13+'[5]EPC subtotals'!$A$24*'[5]Basic INFO'!$C$101*'[5]Basic INFO'!$C$103) -> 0.014633685
A17: 1- required value for chemical injection has been concidered as the following:
A18: - O2 Scavenger: 10-15 ppm per 1 ppm O2 in water.
A19: - Corrosion Inhibitor: 5-50 ppm
A20: - Biocide(Types A & B): 50-400 ppm (once a week)
A21: - Anti Scale: 5-30 ppm
A22: - Demulsifier: 5-80 ppm
A23: - Reverse Demulsifier: 0.5-5 lit/h

Sheet Spare parts
A1: Spare parts for process equipment
A2: Seq. | B2: DESCRIPTION | C2: Total Price (Rials) | D2: Total Price (ٍEUR) | E2: درصد اقلام یدکی و راه اندازی از هزینه کل تجهیز | F2: Estimate for spare parts (IRR) | G2: Estimate for spare parts (EUR)
A3: 1 | B3: Desalting Packages | C3: =TOTAL!C8 -> 0 | D3: =TOTAL!D8 -> 1932650.5 | E3: 0.15 | F3: =C3*E3 -> 0 | G3: =D3*E3 -> 289897.58
A4: 2 | B4: Indirect Fired Heater Packages | C4: =TOTAL!C9 -> 0 | D4: =TOTAL!D9 -> 3420217 | E4: 0.12 | F4: =C4*E4 -> 0 | G4: =D4*E4 -> 410426.04
A5: 3 | B5: Vessels | C5: =TOTAL!C10 -> 1.0401658e+11 | D5: =TOTAL!D10 -> 0 | E5: 0.01 | F5: =C5*E5 -> 1.0401658e+09 | G5: =D5*E5 -> 0
A6: 4 | B6: Tanks | C6: =TOTAL!C11 -> 6.0838575e+11 | D6: =TOTAL!D11 -> 0 | E6: 0.01 | F6: =C6*E6 -> 6.0838575e+09 | G6: =D6*E6 -> 0
A7: 5 | B7: Plate & Frame H. Ex. | C7: =TOTAL!C12 -> 0 | D7: =TOTAL!D12 -> 38801.906 | E7: 0.1 | F7: =C7*E7 -> 0 | G7: =D7*E7 -> 3880.1906
A8: 6 | B8: Pumps | C8: =TOTAL!C13 -> 4.8778846e+09 | D8: =TOTAL!D13 -> 2753903.8 | E8: 0.25 | F8: =C8*E8 -> 1.2194712e+09 | G8: =D8*E8 -> 688475.95
A9: 7 | B9: Chemical Inj. Packages | C9: =TOTAL!C14 -> 5.6263675e+11 | D9: =TOTAL!D14 -> 0 | E9: 0.2 | F9: =C9*E9 -> 1.1252735e+11 | G9: =D9*E9 -> 0
A10: 8 | B10: Deaeration Packages | C10: =TOTAL!C15 -> 0 | D10: =TOTAL!D15 -> 1850000 | E10: 0.15 | F10: =C10*E10 -> 0 | G10: =D10*E10 -> 277500
A11: 9 | B11: IGF Packages | C11: =TOTAL!C16 -> 0 | D11: =TOTAL!D16 -> 556479.59 | E11: 0.12 | F11: =C11*E11 -> 0 | G11: =D11*E11 -> 66777.551
A12: 10 | B12: Filters | C12: =TOTAL!C17 -> 1.6259615e+10 | D12: =TOTAL!D17 -> 534220.41 | E12: 0.04 | F12: =C12*E12 -> 6.5038462e+08 | G12: =D12*E12 -> 21368.816
A13: 11 | B13: Flare Packages | C13: =TOTAL!C18 -> 1.2619659e+11 | D13: =TOTAL!D18 -> 0 | E13: 0.08 | F13: =C13*E13 -> 1.0095727e+10 | G13: =D13*E13 -> 0
A14: 12 | B14: Burn Pit Ignition Packages | C14: =TOTAL!C19 -> 7.300629e+10 | D14: =TOTAL!D19 -> 0 | E14: 0.04 | F14: =C14*E14 -> 2.9202516e+09 | G14: =D14*E14 -> 0
... A17: 15 | B17: Overhead Travel. Cranes | C17: =TOTAL!C22 -> 135328531500 | D17: =TOTAL!D22 -> 0 | E17: 0.08 | F17: =C17*E17 -> 10826282520 | G17: =D17*E17 -> 0
A18: TOTAL | F18: =SUM(F3:F17) -> 1.8007225e+11 | G18: =SUM(G3:G17) -> 1758326.1

Sheet TOTAL
A1: Project Title: Revamping of Pazanan II Desalting Plant
A2: Sub-Project Title: Basic Design Studies and Preparation of FEED Package for Revamping of Pazanan II Desalting Plant
A3: Project Budget Ref. 03229 (formerly 53-51-91211)
A4: Doc. Title: BASIC MTO & COST ESTMATION REPORT (MECHANICAL)
A5: Doc. Ref. 91211-PZN-ME-RE-451-R02
A6: TOTAL PROCUREMENT NET PRICE
A7: No. | B7: DESCRIPTION | C7: Total Price (Rials) | D7: Total Price 'FOB' (€) | E7: سهم مبتنی بر استعلامها (شامل سربار و مالیات ارزش افزوده) | F7: سهم مبتنی بر استعلامها (شامل سربار و مالیات ارزش افزوده)
A8: 1 | B8: Desalting Packages | C8: =DESALTER!G9 -> 0 | D8: =DESALTER!H9 -> 1932650.5 | E8: =DESALTER!G13 -> 0 | F8: =DESALTER!H13 -> 2509000
A9: 2 | B9: Indirect Fired Heater Packages | C9: =HEATERS!G10 -> 0 | D9: =HEATERS!H10 -> 3420217 | E9: =HEATERS!G14 -> 0 | F9: =HEATERS!H14 -> 4439000
A10: 3 | B10: Vessels | C10: =VESSELS!G12 -> 1.0401658e+11 | D10: =VESSELS!H12 -> 0 | E10: =VESSELS!G16 -> 135014000000 | F10: =VESSELS!H16 -> 0
A11: 4 | B11: Tanks | C11: =TANKS!G10 -> 6.0838575e+11 | D11: =TANKS!H10 -> 0 | E11: =TANKS!G14 -> 789685000000 | F11: =TANKS!H14 -> 0
A12: 5 | B12: Plate & Frame H. Ex. | C12: =EXCHANG.!G9 -> 0 | D12: =EXCHANG.!H9 -> 38801.906 | E12: =EXCHANG.!G13 -> 0 | F12: =EXCHANG.!H13 -> 0
A13: 6 | B13: Pumps | C13: =PUMPS!G29 -> 4.8778846e+09 | D13: =PUMPS!H29 -> 2753903.8 | E13: =PUMPS!G33 -> 0 | F13: =PUMPS!H33 -> 3474000
A14: 7 | B14: Chemical Inj. Packages | C14: =C.I.P.!G19 -> 5.6263675e+11 | D14: =C.I.P.!H19 -> 0 | E14: =C.I.P.!G23 -> 730302000000 | F14: =C.I.P.!H23 -> 0
A15: 8 | B15: Deaeration Packages | C15: =DEAERATOR!G9 -> 0 | D15: =DEAERATOR!H9 -> 1850000 | E15: =DEAERATOR!G13 -> 0 | F15: =DEAERATOR!H13 -> 2401000
A16: 9 | B16: IGF Packages | C16: =IGF!G9 -> 0 | D16: =IGF!H9 -> 556479.59 | E16: =IGF!G13 -> 0 | F16: =IGF!H13 -> 722000
A17: 10 | B17: Filters | C17: =FILTERS!G10 -> 1.6259615e+10 | D17: =FILTERS!H10 -> 534220.41 | E17: =FILTERS!G14 -> 0 | F17: =FILTERS!H14 -> 693000
A18: 11 | B18: Flare Packages | C18: =FLARE!G9 -> 1.2619659e+11 | D18: =FLARE!H9 -> 0 | E18: =FLARE!G13 -> 163803000000 | F18: =FLARE!H13 -> 0
A19: 12 | B19: Burn Pit Ignition Packages | C19: ='BURN PIT'!G9 -> 7.300629e+10 | D19: ='BURN PIT'!H9 -> 0 | E19: ='BURN PIT'!G13 -> 94762000000 | F19: ='BURN PIT'!H13 -> 0
A20: 13 | B20: Air Comp. Packages | C20: ='AIR COMP.'!G9 -> 1.3558311e+11 | D20: ='AIR COMP.'!H9 -> 0 | E20: ='AIR COMP.'!G13 -> 175987000000 | F20: ='AIR COMP.'!H13 -> 0
A21: 14 | B21: Air Dryer Packages | C21: ='AIR DRYER'!G9 -> 8.1298077e+09 | D21: ='AIR DRYER'!H9 -> 0 | E21: ='AIR DRYER'!G13 -> 0 | F21: ='AIR DRYER'!H13 -> 0
A22: 15 | B22: Overhead Travel. Cranes | C22: =CRANES!G14 -> 135328531500 | D22: =CRANES!H14 -> 0 | E22: =CRANES!G18 -> 175656000000 | F22: =CRANES!H18 -> 0
A23: 16 | B23: Lab. Equipment and Devices | C23: ='Lab Equip'!H25 -> 221000000 | D23: ='Lab Equip'!I25 -> 333000 | E23: 0 | F23: 0
A24: 17 | B24: Chemicals & Consumables | C24: =Consumables!$Q$16 -> 396901000000 | D24: 0 | E24: 0 | F24: 0
A25: 18 | B25: Spare parts | C25: ='Spare parts'!F18 -> 1.8007225e+11 | D25: ='Spare parts'!G18 -> 1758326.1 | E25: 0 | F25: 0
B26: برآورد هزینه بدون سربار و مالیات بر ارزش افزوده | C26: =SUM(C8:C25) -> 2.3516152e+12 | D26: =SUM(D8:D25) -> 13177599
B27: ضریب سربار تأمین کالا | C27: 1.18 | D27: 1.18
B28: مالیات بر ارزش افزوده | C28: 0.1 | D28: 0.1
B29: هزینه تأمین کالا + سربار + مالیات بر ارزش افزوده | C29: =ROUND((C26*C27*(1+C28))/1000000,0)*1000000 -> 3052396000000 | D29: =ROUND(D26*D27*(1+D28)/1000,0)*1000 -> 17105000 | E29: =SUM(E8:E25) -> 2265209000000 | F29: =SUM(F8:F25) -> 14238000

Sheet DE-112  (1)-Asmari
L1: Basic Design Study and FEED Package Preparation for Construct New KOOPAL (ASMARI & BANGESTAN) Desalting Unit
A5: Hirgan Energy Eng. Co. | AE5: NISOC
A7: Project No.: 53-51-91215 | L7: Document Title : MECH. D.S. For DESALTING PACKAGES | AE7: Contract No.: 53-73-1264
A10: Consult. Proj. No.: 9104 | L10: Proj. | P10: Loc. | S10: Disc. | V10: Type | Y10: Seq. | AB10: Rev. | AE10: Page No: 4 of 9
L11: 91215 | P11: KPL | S11: ME | V11: DS | Y11: 463 | AB11: a
A13: ASMARI TRAIN / DESALTING PACKAGE MECH. D.S. / PK-111 (Sheet 7 of 19)
A14: 2st Stage Desalter / DE-112 (1 of 3)
A17: 1 | B17: SERVICE: | U17: MANUFACTURER: | AI17: *
A18: 2 | B18: FOR: | U18: MODEL NO: | AI18: *
A19: 3 | B19: SITE: | U19: TYPE: | AI19: *
A20: 4 | B20: NO. REQUIRED: | F20: TWO
B21: PROCESS DESIGN DATA
A22: 5 | B22: CONTENTS | U22: VAPOUR FLOW | AB22: (kg/h) | AD22: *
A23: 6 | B23: OPERATING TEMP. | H23: (°C) | U23: VAPOUR MOLEC. WT | AB23: (kg/kgmol) | AD23: -
A24: 7 | B24: OPERATING PRESSURE | H24: (barg) | J24: * (REFER SECTION 2.1) | U24: LIQUID SPECIFIC GRAVITY | AD24: REFER SECTION 2.1
A25: 8 | B25: HOLDING CAPACITY | H25: (m3) | J25: * | U25: LIQUID VISCOSITY | AB25: (cP) | AD25: REFER SECTION 2.1
A26: 9 | B26: LIQUID FLOW | H26: (m3/h) | J26: REFER SECTION 2.1 (REMARK 2) | U26: PROCESS DESIGN REQUIREMENTS | AD26: REFER SECTION 2.5 | AI26: Refer Section
B27: MECHANICAL DESIGN DATA
A28: 10 | B28: DESIGN TEMPERATURE (MIN/MAX) | H28: (°C) | U28: VESSEL ORIENTATION | AD28: HORIZONTAL
A29: 11 | B29: DESIGN PRESSURE | H29: (barg) | U29: TOTAL VOLUME MAX. OPER. | AB29: (m3) | AD29: *
A30: 12 | B30: TEST PRESSURE | H30: (barg) | U30: NORMAL LIQUID VOLUME | AB30: (m3) | AD30: *
A31: 13 | B31: INTERNAL VACUUM | H31: (mm Hg) | J31: FULL VACUUM * | U31: ERECTION/SHIPPING WEIGHT | AB31: (kg) | AD31: *
A32: 14 | B32: DIAMETER OF SHELL | H32: (mm) | J32: * | U32: TOTAL OPERATING WEIGHT | AB32: (kg) | AD32: *
A33: 15 | B33: TAN. TO TAN. DIMENSION | H33: (mm) | J33: * | U33: WEIGHT FULL OF WATER | AB33: (kg) | AD33: *
A34: 16 | B34: WALL THICKNESS SHELL | H34: (mm) | J34: * | U34: INTERNALS: | AD34: *
A35: 17 | B35: WALL THICKNESS HEAD | H35: (mm) | J35: * | U35: EXPLOSION BLAST LOAD | AB35: (kN/m2) | AD35: N/A
A36: 18 | B36: CORROSION ALLOWANCE | H36: (mm) | J36: 3.2 | U36: ACCELERATION TOW OUT | AD36: N/A
A37: 19 | B37: JOINT EFFICIENCY | J37: * | U37: WIND LOAD | AB37: (m/s) | AD37: (MAX)
A38: 20 | B38: HEAD FORM | U38: INSULATION THICKNESS | AB38: (mm) | AD38: REMARK 3 (HOLD 5)
B39: STANDARDS AND SPECIFICATIONS
A40: 21 | B40: CODE | J40: ASME VIII DIV 1 + 'U' STAMP | U40: SPECIFICATION | AC40: YAP1-CTEP00-MEVE-SPEQ-1001
B41: MATERIALS
A42: 22 | B42: SHELL | J42: ASME SA 516 GR 70 * | U42: FLANGES | AB42: ASME SA 105*
A43: 23 | B43: HEADS | J43: ASME SA 516 GR 70 * | U43: NOZZLE | Y43: : PIPES | AB43: ASME SA 106 GR B*
A44: 24 | B44: LINING / CLADDING | J44: (NOTE 4) * | U44: NECKS | Y44: : PLATES | AB44: ASME SA 516 GR 70*
A45: 25 | B45: SUPPORT | E45: : SKIRT | J45: N/A | Y45: : FORGINGS | AB45: ASME SA 105*
A46: 26 | E46: : SADDLES | J46: ASME SA 516 GR 70 * | U46: EXTERNAL BOLTS | AB46: ASME SA 193 GR B7M *
A47: 27 | B47: STRUCTURAL SHAPES | J47: CARBON STEEL * | U47: EXTERNAL NUTS | AB47: ASME SA 194 GR 2HM *
A48: 28 | B48: INTERNALS | J48: CARBON STEEL * | U48: INTERNAL BOLTS | AB48: ASME SA 193 GR B8 *
A49: 29 | B49: GASKETS | J49: SPIRAL WOUND GRAPHOIL FILLED * | U49: INTERNAL NUTS | AB49: ASME SA 194 GR 8 *
A50: 30 | B50: LIFTING LUGS | J50: ASME SA 516 GR 70 * | U50: PLATES & PADS | AB50: AS SHELL
B51: FABRICATION AND INSPECTION REQUIREMENTS
A52: 31 | B52: INSPECTION AUTHORITY | J52: THIRD PARTY STAGE INSPECTION (*) | U52: DYE PENETRANT | AB52: PER CODE & SPEC REQUIREMENTS
A53: 32 | B53: POST WELD HEAT TREATMENT | J53: PER CODE & SPEC REQUIREMENTS | U53: ULTRASONIC | AB53: PER CODE & SPEC REQUIREMENTS
A54: 33 | B54: SPECIAL HEAT TREATMENT | J54: PER CODE & SPEC REQUIREMENTS | U54: PNEUMATIC TEST | AB54: N/A
A55: 34 | B55: RADIOGRAPHY | J55: 1 | U55: IMPACT TESTS | AB55: PER CODE & SPEC REQUIREMENTS
A56: 35 | B56: MAGNETIC PARTICLE | J56: PER CODE & SPEC REQUIREMENTS | U56: HYDRO TEST | AB56: PER CODE & SPEC REQUIREMENTS
A57: 36 | B57: MATERIAL CERTIFICATIONS | J57: IN ACCORDANCE WITH BS EN 10204, TYPE 3.1 MINIMUM FOR PRESSURE CONTAINING COMPONENTS AND ATTACHMENTS
B58: PROTECTIVE COATING DATA
A59: 37 | B59: SURFACE PREPARATION | H59: INSIDE : | J59: CLEAN & DRY | Z59: OUTSIDE : | AC59: IPS-E-TP-100
A60: 38 | B60: PAINT | H60: INSIDE : | J60: N/A | Z60: OUTSIDE : | AC60: IPS-E-TP-100
A61: 39
A63: 40 | B63: REMARKS:-
A64: 41 | B64: 1 | C64: DESIGN PRESSURE SPECIFIED IS AT TOP OF VESSEL. VENDOR/BIDDER DESIGN SHALL INCLUDE STATIC HEAD FOR VESSEL HLL WITH LIQUID OF SPECIFIC GRAVITY 1.0.
A65: 42 | B65: 2 | C65: 10% DESIGN MARGIN SHALL BE INCLUDED ON THE FLOW RATE.
A66: 43 | B66: 3 | C66: IF THE VESSEL IS LOCATED IN FIRE HAZARDOUS AREA (WILL BE DETERMINED LATER BASED ON EQUIPMENT LAYOUTS),
A67: 44 | C67: STAINLESS STEEL JACKETING SHALL BE USED OVER INSULATION.
A68: 45 | B68: 4 | C68: VENDOR/BIDDER SHALL DESIGN AND PROVIDE THE INTERNAL SACRIFICIAL ANODES IN ACCORDANCE WITH IPS-E-TP-820 AND IPS-M-TP-750. LIFE OF ANODES SHALL BE
A69: 46 | C69: MINIMUM 5 YEARS.
A70: 47
A71: 48
A72: 49
A73: 50

Sheet DE-112  (2)-Asmari
L1: Basic Design Study and FEED Package Preparation for Construct New KOOPAL (ASMARI & BANGESTAN) Desalting Unit
A5: Hirgan Energy Eng. Co. | AE5: NISOC
A7: Project No.: 53-51-91215 | L7: Document Title : MECH. D.S. For DESALTING PACKAGES | AE7: Contract No.: 53-73-1264
A10: Consult. Proj. No.: 9104 | L10: Proj. | P10: Loc. | S10: Disc. | V10: Type | Y10: Seq. | AB10: Rev. | AE10: Page No: 4 of 9
L11: 91215 | P11: KPL | S11: ME | V11: DS | Y11: 463 | AB11: a
A13: ASMARI TRAIN / DESALTING PACKAGE MECH. D.S. / PK-111 (Sheet 8 of 19)
A14: 2st Stage Desalter / DE-112 (2 of 3)
A16: VESSEL LAYOUT DETAILS
C69: NOTE :
C70: 1 | D70: DIMENSIONS IN MILLIMETRES
C71: 2 | D71: LIQUID LEVELS : VENDOR/BIDDER SHALL ADVISE
C72: 3 | D72: VENDOR/BIDDER SHALL INDICATE INTERNAL DETAILS
C73: 4 | D73: NOZZLE INDICATED ARE MINIMUM REQUIREMENT. VENDOR/BIDDER SHALL PROVIDE ADDITIONAL NOZZLES BASED ON DESIGN.

Sheet DE-112 (3)-Asmari
L1: Basic Design Study and FEED Package Preparation for Construct New KOOPAL (ASMARI & BANGESTAN) Desalting Unit
A5: Hirgan Energy Eng. Co. | AE5: NISOC
A7: Project No.: 53-51-91215 | L7: Document Title : MECH. D.S. For DESALTING PACKAGES | AE7: Contract No.: 53-73-1264
A10: Consult. Proj. No.: 9104 | L10: Proj. | P10: Loc. | S10: Disc. | V10: Type | Y10: Seq. | AB10: Rev. | AE10: Page No: 4 of 9
L11: 91215 | P11: KPL | S11: ME | V11: DS | Y11: 463 | AB11: a
A13: ASMARI TRAIN / DESALTING PACKAGE MECH. D.S. / PK-111 (Sheet 9 of 19)
A14: 2st Stage Desalter / DE-112 (3 of 3)
A16: NOZZLE CONNECTION SCHEDULE *
A17: MK | D17: No: | F17: SIZE | H17: RATING | K17: FACE | N17: TYPE | Q17: SERVICE | W17: ORIENTATION | AB17: STANDOUT | AF17: REMARKS
A18: N1 | D18: 1 * | F18: 12" * | H18: 150# | K18: RF | N18: WN | Q18: FEED INLET | W18: * | AB18: *
A19: N2 | D19: 1 * | F19: 12" * | H19: 150# | K19: RF | N19: WN | Q19: CRUDE OUTLET | W19: * | AB19: *
A20: N3 | D20: 1* | F20: * | H20: * | K20: RF | N20: WN | Q20: GAS OUTLET | W20: * | AB20: *
A21: N4 | D21: 1 * | F21: 2" * | H21: 300# | K21: RF | N21: LWN | Q21: UTILITY | W21: * | AB21: *
A22: N5 | D22: 1 * | F22: 3" * | H22: 300# | K22: RF | N22: WN | Q22: DRAIN | W22: * | AB22: *
A23: N6 | D23: 1 * | F23: 2" * | H23: 300# | K23: RF | N23: LWN | Q23: DRAIN | W23: * | AB23: *
A24: N7 | D24: 1 * | F24: 3" * | H24: 300# | K24: RF | N24: WN | Q24: DRAIN | W24: * | AB24: *
A25: N8 | D25: 1 * | F25: 2" * | H25: 300# | K25: RF | N25: LWN | Q25: VENT | W25: * | AB25: *
A26: N9A/B | D26: 2 * | F26: 4" * | H26: 150# | K26: RF | N26: WN | Q26: LEVEL TRANSMITTER | W26: * | AB26: * | AF26: PAIRDED NOZZLES SHALL BE JIG-SET
A27: N10A/B | D27: 2 * | F27: 2" * | H27: 300# | K27: RF | N27: LWN | Q27: LEVEL GAUGE | W27: * | AB27: * | AF27: PAIRDED NOZZLES SHALL BE JIG-SET
A28: N11 | D28: 1 * | F28: 2" * | H28: 300# | K28: RF | N28: LWN | Q28: PRESSURE TRANSMITTER | W28: * | AB28: *
A29: N12 | D29: 1 * | F29: 2" * | H29: 300# | K29: RF | N29: LWN | Q29: PRESSURE TRANSMITTER | W29: * | AB29: *
A30: N13A/B | D30: 2 * | F30: 4" * | H30: 150# | K30: RF | N30: WN | Q30: LEVEL BRIDLE | W30: * | AB30: * | AF30: PAIRDED NOZZLES SHALL BE JIG-SET
A31: N14 | D31: 1 * | F31: * | H31: * | K31: RF | N31: WN | Q31: PSV | W31: * | AB31: *
A34: MW 1/2 | D34: 2 * | F34: 24" * | H34: 150# | K34: RF | N34: WN | Q34: MANWAY C/W DAVIT | W34: * | AB34: *
B47: NOTES
B48: 1 | C48: THE VENDOR/BIDDER SHALL CONFIRM FLANGE SIZES AND RATING ON BATTERY LIMIT, BETWEEN THE PACKAGE FOR ALL PROCESS AND
C49: UTILITY PIPING.
B50: 2 | C50: NOZZLE INDICATED ABOVE ARE THE MINIMUM REQUIREMENT AND VENDOR/BIDDER SHALL CONFIRM OR PROVIDE ADDITIONAL NOZZLES
C51: REQUIRED, IF ANY.

Sheet DE-112  (1)-Bangestan
L1: Basic Design Study and FEED Package Preparation for Construct New KOOPAL (ASMARI & BANGESTAN) Desalting Unit
A5: Hirgan Energy Eng. Co. | AE5: NISOC
A7: Project No.: 53-51-91215 | L7: Document Title : MECH. D.S. For DESALTING PACKAGES | AE7: Contract No.: 53-73-1264
A10: Consult. Proj. No.: 9104 | L10: Proj. | P10: Loc. | S10: Disc. | V10: Type | Y10: Seq. | AB10: Rev. | AE10: Page No: 4 of 9
L11: 91215 | P11: KPL | S11: ME | V11: DS | Y11: 463 | AB11: a
A13: ASMARI TRAIN / DESALTING PACKAGE MECH. D.S. / PK-111 (Sheet 7 of 16)
A14: 2st Stage Desalter / DE-112 (1 of 3)
A17: 1 | B17: SERVICE: | U17: MANUFACTURER: | AI17: *
A18: 2 | B18: FOR: | U18: MODEL NO: | AI18: *
A19: 3 | B19: SITE: | U19: TYPE: | AI19: *
A20: 4 | B20: NO. REQUIRED: | F20: TWO
B21: PROCESS DESIGN DATA
A22: 5 | B22: CONTENTS | U22: VAPOUR FLOW | AB22: (kg/h) | AD22: *
A23: 6 | B23: OPERATING TEMP. | H23: (°C) | U23: VAPOUR MOLEC. WT | AB23: (kg/kgmol) | AD23: -
A24: 7 | B24: OPERATING PRESSURE | H24: (barg) | J24: * (REFER SECTION 2.1) | U24: LIQUID SPECIFIC GRAVITY | AD24: REFER SECTION 2.1
A25: 8 | B25: HOLDING CAPACITY | H25: (m3) | J25: * | U25: LIQUID VISCOSITY | AB25: (cP) | AD25: REFER SECTION 2.1
A26: 9 | B26: LIQUID FLOW | H26: (m3/h) | J26: REFER SECTION 2.1 (REMARK 2) | U26: PROCESS DESIGN REQUIREMENTS | AD26: REFER SECTION 2.5 | AI26: Refer Section
B27: MECHANICAL DESIGN DATA
A28: 10 | B28: DESIGN TEMPERATURE (MIN/MAX) | H28: (°C) | U28: VESSEL ORIENTATION | AD28: HORIZONTAL
A29: 11 | B29: DESIGN PRESSURE | H29: (barg) | U29: TOTAL VOLUME MAX. OPER. | AB29: (m3) | AD29: *
A30: 12 | B30: TEST PRESSURE | H30: (barg) | U30: NORMAL LIQUID VOLUME | AB30: (m3) | AD30: *
A31: 13 | B31: INTERNAL VACUUM | H31: (mm Hg) | J31: FULL VACUUM * | U31: ERECTION/SHIPPING WEIGHT | AB31: (kg) | AD31: *
A32: 14 | B32: DIAMETER OF SHELL | H32: (mm) | J32: * | U32: TOTAL OPERATING WEIGHT | AB32: (kg) | AD32: *
A33: 15 | B33: TAN. TO TAN. DIMENSION | H33: (mm) | J33: * | U33: WEIGHT FULL OF WATER | AB33: (kg) | AD33: *
A34: 16 | B34: WALL THICKNESS SHELL | H34: (mm) | J34: * | U34: INTERNALS: | AD34: *
A35: 17 | B35: WALL THICKNESS HEAD | H35: (mm) | J35: * | U35: EXPLOSION BLAST LOAD | AB35: (kN/m2) | AD35: N/A
A36: 18 | B36: CORROSION ALLOWANCE | H36: (mm) | J36: 3.2 | U36: ACCELERATION TOW OUT | AD36: N/A
A37: 19 | B37: JOINT EFFICIENCY | J37: * | U37: WIND LOAD | AB37: (m/s) | AD37: (MAX)
A38: 20 | B38: HEAD FORM | U38: INSULATION THICKNESS | AB38: (mm) | AD38: REMARK 3 (HOLD 5)
B39: STANDARDS AND SPECIFICATIONS
A40: 21 | B40: CODE | J40: ASME VIII DIV 1 + 'U' STAMP | U40: SPECIFICATION | AC40: YAP1-CTEP00-MEVE-SPEQ-1001
B41: MATERIALS
A42: 22 | B42: SHELL | J42: ASME SA 516 GR 70 * | U42: FLANGES | AB42: ASME SA 105*
A43: 23 | B43: HEADS | J43: ASME SA 516 GR 70 * | U43: NOZZLE | Y43: : PIPES | AB43: ASME SA 106 GR B*
A44: 24 | B44: LINING / CLADDING | J44: (NOTE 4) * | U44: NECKS | Y44: : PLATES | AB44: ASME SA 516 GR 70*
A45: 25 | B45: SUPPORT | E45: : SKIRT | J45: N/A | Y45: : FORGINGS | AB45: ASME SA 105*
A46: 26 | E46: : SADDLES | J46: ASME SA 516 GR 70 * | U46: EXTERNAL BOLTS | AB46: ASME SA 193 GR B7M *
A47: 27 | B47: STRUCTURAL SHAPES | J47: CARBON STEEL * | U47: EXTERNAL NUTS | AB47: ASME SA 194 GR 2HM *
A48: 28 | B48: INTERNALS | J48: CARBON STEEL * | U48: INTERNAL BOLTS | AB48: ASME SA 193 GR B8 *
A49: 29 | B49: GASKETS | J49: SPIRAL WOUND GRAPHOIL FILLED * | U49: INTERNAL NUTS | AB49: ASME SA 194 GR 8 *
A50: 30 | B50: LIFTING LUGS | J50: ASME SA 516 GR 70 * | U50: PLATES & PADS | AB50: AS SHELL
B51: FABRICATION AND INSPECTION REQUIREMENTS
A52: 31 | B52: INSPECTION AUTHORITY | J52: THIRD PARTY STAGE INSPECTION (*) | U52: DYE PENETRANT | AB52: PER CODE & SPEC REQUIREMENTS
A53: 32 | B53: POST WELD HEAT TREATMENT | J53: PER CODE & SPEC REQUIREMENTS | U53: ULTRASONIC | AB53: PER CODE & SPEC REQUIREMENTS
A54: 33 | B54: SPECIAL HEAT TREATMENT | J54: PER CODE & SPEC REQUIREMENTS | U54: PNEUMATIC TEST | AB54: N/A
A55: 34 | B55: RADIOGRAPHY | J55: 1 | U55: IMPACT TESTS | AB55: PER CODE & SPEC REQUIREMENTS
A56: 35 | B56: MAGNETIC PARTICLE | J56: PER CODE & SPEC REQUIREMENTS | U56: HYDRO TEST | AB56: PER CODE & SPEC REQUIREMENTS
A57: 36 | B57: MATERIAL CERTIFICATIONS | J57: IN ACCORDANCE WITH BS EN 10204, TYPE 3.1 MINIMUM FOR PRESSURE CONTAINING COMPONENTS AND ATTACHMENTS
B58: PROTECTIVE COATING DATA
A59: 37 | B59: SURFACE PREPARATION | H59: INSIDE : | J59: CLEAN & DRY | Z59: OUTSIDE : | AC59: IPS-E-TP-100
A60: 38 | B60: PAINT | H60: INSIDE : | J60: N/A | Z60: OUTSIDE : | AC60: IPS-E-TP-100
A61: 39
A63: 40 | B63: REMARKS:-
A64: 41 | B64: 1 | C64: DESIGN PRESSURE SPECIFIED IS AT TOP OF VESSEL. VENDOR/BIDDER DESIGN SHALL INCLUDE STATIC HEAD FOR VESSEL HLL WITH LIQUID OF SPECIFIC GRAVITY 1.0.
A65: 42 | B65: 2 | C65: 10% DESIGN MARGIN SHALL BE INCLUDED ON THE FLOW RATE.
A66: 43 | B66: 3 | C66: IF THE VESSEL IS LOCATED IN FIRE HAZARDOUS AREA (WILL BE DETERMINED LATER BASED ON EQUIPMENT LAYOUTS),
A67: 44 | C67: STAINLESS STEEL JACKETING SHALL BE USED OVER INSULATION.
A68: 45 | B68: 4 | C68: VENDOR/BIDDER SHALL DESIGN AND PROVIDE THE INTERNAL SACRIFICIAL ANODES IN ACCORDANCE WITH IPS-E-TP-820 AND IPS-M-TP-750. LIFE OF ANODES SHALL BE
A69: 46 | C69: MINIMUM 5 YEARS.
A70: 47
A71: 48
A72: 49
A73: 50

Sheet DE-112  (2)-Bangestan
L1: Basic Design Study and FEED Package Preparation for Construct New KOOPAL (ASMARI & BANGESTAN) Desalting Unit
A5: Hirgan Energy Eng. Co. | AE5: NISOC
A7: Project No.: 53-51-91215 | L7: Document Title : MECH. D.S. For DESALTING PACKAGES | AE7: Contract No.: 53-73-1264
A10: Consult. Proj. No.: 9104 | L10: Proj. | P10: Loc. | S10: Disc. | V10: Type | Y10: Seq. | AB10: Rev. | AE10: Page No: 4 of 9
L11: 91215 | P11: KPL | S11: ME | V11: DS | Y11: 463 | AB11: a
A13: ASMARI TRAIN / DESALTING PACKAGE MECH. D.S. / PK-111 (Sheet 8 of 16)
A14: 2st Stage Desalter / DE-112 (2 of 3)
A16: VESSEL LAYOUT DETAILS
C69: NOTE :
C70: 1 | D70: DIMENSIONS IN MILLIMETRES
C71: 2 | D71: LIQUID LEVELS : VENDOR/BIDDER SHALL ADVISE
C72: 3 | D72: VENDOR/BIDDER SHALL INDICATE INTERNAL DETAILS
C73: 4 | D73: NOZZLE INDICATED ARE MINIMUM REQUIREMENT. VENDOR/BIDDER SHALL PROVIDE ADDITIONAL NOZZLES BASED ON DESIGN.

Sheet DE-112 (3)-Bangestan
L1: Basic Design Study and FEED Package Preparation for Construct New KOOPAL (ASMARI & BANGESTAN) Desalting Unit
A5: Hirgan Energy Eng. Co. | AE5: NISOC
A7: Project No.: 53-51-91215 | L7: Document Title : MECH. D.S. For DESALTING PACKAGES | AE7: Contract No.: 53-73-1264
A10: Consult. Proj. No.: 9104 | L10: Proj. | P10: Loc. | S10: Disc. | V10: Type | Y10: Seq. | AB10: Rev. | AE10: Page No: 4 of 9
L11: 91215 | P11: KPL | S11: ME | V11: DS | Y11: 463 | AB11: a
A13: ASMARI TRAIN / DESALTING PACKAGE MECH. D.S. / PK-111 (Sheet 9 of 16)
A14: 2st Stage Desalter / DE-112 (3 of 3)
A16: NOZZLE CONNECTION SCHEDULE *
A17: MK | D17: No: | F17: SIZE | H17: RATING | K17: FACE | N17: TYPE | Q17: SERVICE | W17: ORIENTATION | AB17: STANDOUT | AF17: REMARKS
A18: N1 | D18: 1 * | F18: 12" * | H18: 150# | K18: RF | N18: WN | Q18: FEED INLET | W18: * | AB18: *
A19: N2 | D19: 1 * | F19: 12" * | H19: 150# | K19: RF | N19: WN | Q19: CRUDE OUTLET | W19: * | AB19: *
A20: N3 | D20: 1* | F20: * | H20: * | K20: RF | N20: WN | Q20: GAS OUTLET | W20: * | AB20: *
A21: N4 | D21: 1 * | F21: 2" * | H21: 300# | K21: RF | N21: LWN | Q21: UTILITY | W21: * | AB21: *
A22: N5 | D22: 1 * | F22: 3" * | H22: 300# | K22: RF | N22: WN | Q22: DRAIN | W22: * | AB22: *
A23: N6 | D23: 1 * | F23: 2" * | H23: 300# | K23: RF | N23: LWN | Q23: DRAIN | W23: * | AB23: *
A24: N7 | D24: 1 * | F24: 3" * | H24: 300# | K24: RF | N24: WN | Q24: DRAIN | W24: * | AB24: *
A25: N8 | D25: 1 * | F25: 2" * | H25: 300# | K25: RF | N25: LWN | Q25: VENT | W25: * | AB25: *
A26: N9A/B | D26: 2 * | F26: 4" * | H26: 150# | K26: RF | N26: WN | Q26: LEVEL TRANSMITTER | W26: * | AB26: * | AF26: PAIRDED NOZZLES SHALL BE JIG-SET
A27: N10A/B | D27: 2 * | F27: 2" * | H27: 300# | K27: RF | N27: LWN | Q27: LEVEL GAUGE | W27: * | AB27: * | AF27: PAIRDED NOZZLES SHALL BE JIG-SET
A28: N11 | D28: 1 * | F28: 2" * | H28: 300# | K28: RF | N28: LWN | Q28: PRESSURE TRANSMITTER | W28: * | AB28: *
A29: N12 | D29: 1 * | F29: 2" * | H29: 300# | K29: RF | N29: LWN | Q29: PRESSURE TRANSMITTER | W29: * | AB29: *
A30: N13A/B | D30: 2 * | F30: 4" * | H30: 150# | K30: RF | N30: WN | Q30: LEVEL BRIDLE | W30: * | AB30: * | AF30: PAIRDED NOZZLES SHALL BE JIG-SET
A31: N14 | D31: 1 * | F31: * | H31: * | K31: RF | N31: WN | Q31: PSV | W31: * | AB31: *
A34: MW 1/2 | D34: 2 * | F34: 24" * | H34: 150# | K34: RF | N34: WN | Q34: MANWAY C/W DAVIT | W34: * | AB34: *
B47: NOTES
B48: 1 | C48: THE VENDOR/BIDDER SHALL CONFIRM FLANGE SIZES AND RATING ON BATTERY LIMIT, BETWEEN THE PACKAGE FOR ALL PROCESS AND
C49: UTILITY PIPING.
B50: 2 | C50: NOZZLE INDICATED ABOVE ARE THE MINIMUM REQUIREMENT AND VENDOR/BIDDER SHALL CONFIRM OR PROVIDE ADDITIONAL NOZZLES
C51: REQUIRED, IF ANY.
