Workbook
Name Administration_cost: 1.005
Name Contingency_Reserve: 1.15
Name Contractor_profit: 1.1
Name Dollar_Adjustment: 0.1
Name Irr_Adjustment: 0.4
Name IRR_EL_Inflation_Factor: 'basic data'!$L$14
Name IRR_IN_Inflation_Factor: 'basic data'!$K$14
Name IRR_Inflation_Factor: 'basic data'!$B$18
Name IRR_ME_Inflation_Factor: AVERAGE('basic data'!$I$14,'basic data'!$J$14)
Name Lighting_Fixture_Factor: 1.9
Name Material_of_Tank: P.ME!$H$10
Name per_Euro: 'basic data'!$B$1
Name Procurement_All_Insuramce: Procurement!$F$51
Name Procurement_Final_Documentation: Procurement!$F$54
Name Procurement_QC_Inspection: Procurement!$F$53
Name smokeless_factor: 2.5
Name USD_Change_IRR: 'basic data'!$B$2
Name USD_Inflation_Factor: 'basic data'!$C$18

Sheet عملكرد كلي
A1: رديف | B1: شرح | C1: (هزار ريال)
C2: (هزار دلار)
A3: 1 | B3: هزينه هاي در تعهد كارفرما | C3: 67888993
A4: 2 | B4: هزينه انجام شده تاكنون طراحي و مهندسي | C4: 39621943
A5: 3 | B5: جمع هزينه شده | C5: =SUM(C3:C4) -> 107510936
A6: 4 | B6: برآورد اعتبار بخش ريالي زير پروژه 002 | C6: ='EPC Summary'!C15/1000 -> 51783851590
A7: 5 | B7: برآورد اعتبار بخش ارزي زير پروژه 002 | C7: ='EPC Summary'!D12/1000 -> 23392
A8: 6 | B8: پیش بینی تعديل معادل 40 درصد برآورد بخش ريالي زيرپروژه 002 | C8: ='EPC Summary'!G15/1000 -> 20713540636
A9: 7 | B9: پيش بيني اضافه­كاري در سقف 25 درصد برآورد بخش ريالي زير پروژه 002 | C9: ='EPC Summary'!H15/1000 -> 12945962897
A10: 8 | B10: پيش بيني اضافه­كاري در سقف 25 درصد برآورد بخش ارزي زير پروژه 002 | C10: ='EPC Summary'!H16/1000 -> 5848
A11: 9 | B11: جمع كل درخواست بخش ريالي | C11: =C5+C6+C8+C9 -> 85550866059
A12: 10 | B12: جمع كل درخواست بخش ارزي | C12: =C7+C10 -> 29240
A13: 11 | B13: اعتبار مصوب بخش ريالي | C13: 268700000
A14: 12 | B14: اعتبار مصوب بخش ارزي | C14: 18000
A15: 13 | B15: مبلغ افزايش اعتبار بخش ريالي | C15: =C11-C13 -> 85282166059
A16: 14 | B16: مبلغ افزايش اعتبار بخش ارزي | C16: =C12-C14 -> 11240

Sheet EPC Summary
B1: برآورد هزينه هاي مستقيم | G1: برآورد با اعمال بالاسري
A2: بخش | C2: بخش ريالي | D2: بخش ارزي (دلار) | E2: مجموع (ريال) | F2: درصد از كل پروژه | G2: بخش ريالي با اعمال سربار | H2: بخش ارزي(دلار) با اعمال سربار | I2: مجموع (ريال با اعمال سربار) | J2: درصد از كل پروژه
A3: E | B3: مهندسي | C3: =ROUNDUP(PEP!E6,-7) -> 994810000000 | E3: =C3 -> 994810000000 | F3: =E3/E$7 -> 0.020546357 | G3: =ROUNDUP(C3*'basic data'!$B$3,-6) -> 1264727000000 | I3: =ROUNDUP(E3*'basic data'!$B$4,-6) -> 1264727000000 | J3: =I3/I$7 -> 0.020546359
A4: P | B4: كالا | C4: =ROUNDUP(PEP!E21,-7) -> 24007580000000 | D4: =ROUNDUP(PEP!F21,-3) -> 23392000 | E4: =D4*USD_Change_IRR+C4 -> 33832220000000 | F4: =E4/E$7 -> 0.6987554 | G4: =ROUNDUP(C4*'basic data'!$B$3+D4*('basic data'!$B$3-1)*USD_Change_IRR,-6) -> 33187108000000 | H4: =D4 -> 23392000 | I4: =ROUNDUP(E4*'basic data'!$B$4,-6) -> 43011748000000 | J4: =I4/I$7 -> 0.69875539
A5: C | B5: اجرا | C5: =ROUNDUP(PEP!E27,-7) -> 13111410000000 | E5: =D5*USD_Change_IRR+C5 -> 13111410000000 | F5: =E5/E$7 -> 0.27079714 | G5: =ROUNDUP(C5*'basic data'!$B$3,-6) -> 16668864000000 | I5: =ROUNDUP(E5*'basic data'!$B$4,-6) -> 16668864000000 | J5: =I5/I$7 -> 0.27079714
A6: Development | B6: توسعه فناوري | C6: =ROUNDUP(PEP!E28,-7) -> 479390000000 | E6: =C6 -> 479390000000 | F6: =E6/E$7 -> 0.0099011046 | G6: =ROUNDUP(C6*'basic data'!$B$3,-6) -> 609461000000 | I6: =ROUNDUP(E6*'basic data'!$B$4,-6) -> 609461000000 | J6: =I6/I$7 -> 0.0099011125
B7: جمع | C7: =SUM(C3:C6) -> 38593190000000 | D7: =SUM(D3:D6) -> 23392000 | E7: =SUM(E3:E6) -> 48417830000000 | F7: =SUM(F3:F6) -> 1 | G7: =SUM(G3:G6) -> 51730160000000 | H7: =SUM(H3:H6) -> 23392000 | I7: =SUM(I3:I6) -> 61554800000000 | J7: =SUM(J3:J6) -> 1
B10: FR(EPC Initial Capex) | C10: ریال | D10: ارز - دلار | E10: مجموع (ريال + ارز تسعير شده) | G10: Adjustment | H10: Over Work | I10: Elevated Price | J10: 89205005
A11: =C11/$A$15 -> 0.021399949 | B11: مهندسي -E | C11: =I3+J11 -> 1318418590000 | E11: =C11 -> 1318418590000 | G11: =Irr_Adjustment*C11 -> 527367436000 | H11: =ROUNDDOWN(0.25*C11,-3) -> 329604647000 | I11: =H11+G11+C11 -> 2175390673000 | J11: =ROUND(88591123000/1.65,-3) -> 53691590000
A12: =(C12+D12*USD_Change_IRR)/$A$15 -> 0.69814642 | B12: کالا- P | C12: =G4 -> 33187108000000 | D12: =H4 -> 23392000 | E12: =C12+D12*USD_Change_IRR -> 43011748000000 | G12: =Irr_Adjustment*C12 -> 13274843200000 | H12: =0.25*C12 -> 8296777000000 | I12: =H12+G12+C12 -> 54758728200000 | J12: Expenditure
A13: =C13/$A$15 -> 0.27056114 | B13: اجرا- C | C13: =G5 -> 16668864000000 | E13: =C13 -> 16668864000000 | G13: =Irr_Adjustment*C13 -> 6667545600000 | H13: =C13*0.25 -> 4167216000000 | I13: =H13+G13+C13+H14+G14+C14 -> 28509236250000 | J13: 107510936000
A14: =C14/$A$15 -> 0.0098924837 | B14: توسعه - De | C14: =G6 -> 609461000000 | E14: =C14 -> 609461000000 | G14: =Irr_Adjustment*C14 -> 243784400000 | H14: =0.25*C14 -> 152365250000 | J14: Request
A15: =C11+C12+C13+C14+D12*USD_Change_IRR -> 61608491590000 | B15: مجموع | C15: =SUM(C11:C14) -> 51783851590000 | D15: =SUM(D12:D14) -> 23392000 | E15: =SUM(E11:E14) -> 61608491590000 | G15: =SUM(G11:G14) -> 20713540636000 | H15: =SUM(H11:H14) -> 12945962897000 | I15: =H15+G15+C15 -> 85443355123000 | J15: =I16+J13 -> 85550866059000
E16: Bpd_Cost_rate | H16: =D12*0.25 -> 5848000 | I16: =I15 -> 85443355123000 | J16: =D12+H16 -> 29240000
A17: فناوري سخت | B17: =C14-B18-B19 -> 549461000000 | E17: =E15/USD_Change_IRR/110000 -> 1333.5171 | J17: Approved Finance
A18: توسعه مديريت | B18: 30000000000 | J18: 268700000000
A19: سهم داخل | B19: 30000000000 | C19: RFCS | J19: 18000000
C20: =C15 -> 51783851590000 | J20: Finance Increment
C21: =ROUNDUP(D15/1.1,-3) -> 21266000 | J21: =J15-J18 -> 85282166059000
A22: نيروگاه خورشيدي | B22: 100000000000 | J22: =J16-J19 -> 11240000
A23: تصفيه پساب | B23: =B17-B22 -> 449461000000

Sheet PEP
A1: ردیف | B1: شرح | E1: ريال | F1: یورو
A2: 1 | B2: خدمات مهندسی | C2: الف | D2: بازنگری و تائید مهندسی مقدماتی | E2: =Engineering!AJ36 -> 45441000000 | F2: 0
C3: ب | D3: انجام خدمات مهندسی تفصیلی | E3: =ROUNDUP(Engineering!AJ37,-6) -> 748916000000 | F3: 0
C4: ج | D4: مطالعات ارزیابی اثرات زیست محیطی، پيوست سلامت، هزاپ، ژئوتكنيك تكميلي، و نقشه برداري تكميلي | E4: =Engineering!AJ38 -> 34650000000 | F4: 0
C5: د | D5: مديريت مهندسي | E5: =ROUNDUP(Engineering!AJ39,-6) -> 165802000000
D6: جمع خدمات مهندسی | E6: =SUM(E2:E5) -> 994809000000 | F6: 0
A7: 2 | B7: 2-1 تهیه و تامین کالا و تجهیزات خارجی بر مبنای DAP (تحويل در محل پروژه) | C7: الف | D7: هزینه تهیه و تامین کالا و تجهیزات خارجی | E7: 0 | F7: =Procurement!C48 -> 20672777
D8: هزینه تهیه و تامین قطعات یدکی برای دوران راه اندازی و 2 ساله تعمیر و نگهداری | E8: 0 | F8: =Procurement!C49 -> 2719000
C9: ب | D9: هزینه حمل خارجی | E9: 0 | F9: در آيتم الف از 1-2 در نظر گرفته شده است
C10: ج | D10: هزینه بیمه کالا و تجهیزات خارجی | F10: در آيتم الف از 1-2 و ج از 2-2 در نظر گرفته شده است
C11: د | D11: هزینه ترخیص شامل عوارض گمرکی و سود بازرگانی کالا و تجهیزات خارجی | E11: =ROUNDUP(Procurement!D50,-6) -> 1813192000000 | F11: 0
C12: ه‍ | D12: هزینه حمل داخلی کالا و تجهیزات خرید خارج و هزينه حمل كالاي داخلي | E12: =ROUNDUP(Procurement!D52,-6) -> 512751000000 | F12: 0
C13: و | D13: هزینه خدمات فنی سازندگان در دوران نصب و راه اندازی | E13: =ROUNDUP(Procurement!D54,-6) -> 832917000000 | F13: 0
C14: ز | D14: هزینه بازرسی کالا و تجهیزات خارجی | E14: =ROUNDUP(Procurement!D53,-6) -> 300719000000 | F14: 0
B15: 2-2 تهیه و تامین کالا و تجهیزات داخلی برمبنای تحويل در محل پروژه | C15: الف | D15: هزینه تهیه و تامین کالا و تجهیزات داخلی | E15: =ROUNDUP(Procurement!D48,-6) -> 19081325000000 | F15: 0
D16: هزینه تهیه و تامین قطعات یدکی برای دوران راه اندازی و 2 ساله تعمیر و نگهداری | E16: =ROUNDUP(Procurement!D49,-6) -> 1165951000000 | F16: 0
C17: ب | D17: هزینه حمل داخلی | E17: در آيتم ه از 1-2 در نظر گرفته شده است | F17: 0
C18: ج | D18: هزینه بیمه کالا و تجهیزات داخلی و هزينه هاي داخلي بيمه كالا و تجهيزات خريد خارج | E18: =ROUNDUP(Procurement!D51,-6) -> 300719000000 | F18: 0
C19: د | D19: هزینه خدمات فنی سازندگان در دوران نصب و راه اندازی | E19: در آيتم و از 1-2 در نظر گرفته شده است | F19: 0
C20: ه‍ | D20: هزینه بازرسی کالا و تجهیزات داخلی | E20: در آيتم ز از 1-2 در نظر گرفته شده است | F20: 0
D21: جمع خدمات تهیه و تامین کالا و تجهیزات | E21: =SUM(E10:E18) -> 24007574000000 | F21: =SUM(F7:F9) -> 23391777
A22: 3 | B22: عملیات ساختمانی و اجرا | C22: الف | D22: تجهیز و برچیدن | E22: =ROUNDUP(Construction!F3,-6) -> 287281000000 | F22: 0
C23: ب | D23: ساخت و نصب و راه اندازی | E23: =ROUNDUP(Construction!F4,-6) -> 11352175000000 | F23: 0
C24: ج | D24: تسهیلات مورد نیاز کارفرما | E24: =ROUNDUP(Construction!F5,-6) -> 1284816000000 | F24: 0
C25: د | D25: الزامات HSE (مقررات ایمنی، بهداشت و محیط زیست شرکت ملی نفت ایران) | E25: =ROUNDUP(Construction!F6,-6) -> 115133000000 | F25: 0
C26: ه‍ | D26: =Construction!K7 -> ه: هزینه دفتر فنی کارگاه | E26: =Construction!F7 -> 72000000000
D27: جمع خدمات ساختمانی | E27: =SUM(E22:E26) -> 13111405000000 | F27: 0
A28: 4 | B28: توسعه فناوريهاي سخت، توسعه قابليتهاي مديريتي و توسعه سهم داخل | C28: الف | D28: يك درصد از كل برآورد | E28: =ROUNDUP((F21*USD_Change_IRR+E27+E21+E6)*1/100,-6) -> 479384000000
D29: جمع کل پروژه ( ردیف های 5 ، 4 ، 3 ، 2 ، 1) | E29: =E6+E21+E27+E28 -> 38593172000000 | F29: =F6+F21+F27 -> 23391777

Sheet basic data
A1: per Euro | B1: =447996/412907 -> 1.0849804 | D1: Year | E1: ME0 | F1: ME | G1: IN | H1: EL | I1: ME0 | J1: ME | K1: IN | L1: EL | M1: درصد تغيير شاخص قيمت توليد كننده در بخش صنعت - طبق آمار منتشر شده در بهمن ماه 1401 در مركز آمار ايران | N1: Year | O1: Ind. PPI | P1: Ind. PPI Variation | Q1: 1395=100
A2: per $ | B2: 420000 | C2: ريال | D2: 94 | E2: -12.6 | F2: -0.62 | G2: -2.3 | H2: -1.6 | I2: =1+E2/100 -> 0.874 | J2: =1+F2/100 -> 0.9938 | K2: =1+G2/100 -> 0.977 | L2: =1+H2/100 -> 0.984 | M2: ME0: ساخت فلزات پايه | N2: 1395 | P2: 4.7
A3: overhead factor (E,G,D) | B3: =Contractor_profit*Contingency_Reserve*Administration_cost -> 1.271325 | D3: 95 | E3: 1.9 | F3: 3.4 | G3: 2.7 | H3: 2 | I3: =1+E3/100 -> 1.019 | J3: =1+F3/100 -> 1.034 | K3: =1+G3/100 -> 1.027 | L3: =1+H3/100 -> 1.02 | M3: ME: ساخت محصولات فلزي ساخته شده به جز ماشين آلات و تجهيزات | N3: 1396 | P3: 13.3
A4: overhead factor (P) | B4: =Contractor_profit*Contingency_Reserve*Administration_cost -> 1.271325 | D4: 96 | E4: 31.8 | F4: 6.7 | G4: 0.8 | H4: 11.5 | I4: =1+E4/100 -> 1.318 | J4: =1+F4/100 -> 1.067 | K4: =1+G4/100 -> 1.008 | L4: =1+H4/100 -> 1.115 | M4: IN: ساخت محصولات رايانه اي، الكترونيكي و نوري | N4: 1397 | P4: 58.6
A5: overhead factor (C) | B5: =Contractor_profit*Contingency_Reserve*Administration_cost -> 1.271325 | D5: 97 | E5: 67.9 | F5: 66.7 | G5: 58.8 | H5: 68.1 | I5: =1+E5/100 -> 1.679 | J5: =1+F5/100 -> 1.667 | K5: =1+G5/100 -> 1.588 | L5: =1+H5/100 -> 1.681 | M5: EL: ساخت تجهيزات برقي | N5: 1398 | O5: 246.2 | P5: 37.1
A6: سال مبنا | B6: تورم ريالي | C6: تورم ارزي | D6: 98 | E6: 32.7 | F6: 49.2 | G6: 43.1 | H6: 43 | I6: =1+E6/100 -> 1.327 | J6: =1+F6/100 -> 1.492 | K6: =1+G6/100 -> 1.431 | L6: =1+H6/100 -> 1.43 | N6: 1399 | O6: 386.1 | P6: 56.8
A7: 1392 | B7: 0.373 | C7: 0.02 | D7: 99 | E7: 105.6 | F7: 62.9 | G7: 37.3 | H7: 71 | I7: =1+E7/100 -> 2.056 | J7: =1+F7/100 -> 1.629 | K7: =1+G7/100 -> 1.373 | L7: =1+H7/100 -> 1.71 | N7: 1400 | O7: 605 | P7: 56.7
A8: 1393 | B8: 0.156 | C8: 0.02 | D8: 1400 | E8: 54.9 | F8: 53.4 | G8: 37.6 | H8: 46.9 | I8: =1+E8/100 -> 1.549 | J8: =1+F8/100 -> 1.534 | K8: =1+G8/100 -> 1.376 | L8: =1+H8/100 -> 1.469 | N8: 99.2 | O8: 355.6 | P8: 23.9
A9: 1394 | B9: 0.119 | C9: 0.02 | D9: 1400.2 | E9: 98.2 | F9: 71.5 | G9: 53.3 | H9: 79.3 | I9: 1 | J9: 1 | K9: 1 | L9: 1 | N9: 99.3 | O9: 433.1 | P9: 37.4
A10: 1395 | B10: 0.09 | C10: 0.02 | D10: 1400.3 | E10: 72.3 | F10: 61.9 | G10: 45 | H10: 60.9 | I10: 1 | J10: 1 | K10: 1 | L10: 1 | N10: 99.4 | O10: 485.8 | P10: 56.8
A11: 1396 | B11: 0.096 | C11: 0.02 | D11: 1400.4 | E11: 54.9 | F11: 53.4 | G11: 37.6 | H11: 46.9 | I11: 1 | J11: 1 | K11: 1 | L11: 1 | N11: 1400.1 | O11: 525.6 | P11: 78.5
A12: 1397 | B12: 0.312 | C12: 0.02 | D12: 1401.1 | E12: 36.5 | F12: 46 | G12: 27.3 | H12: 38.2 | I12: =1+E12/100 -> 1.365 | J12: =1+F12/100 -> 1.46 | K12: =1+G12/100 -> 1.273 | L12: =1+H12/100 -> 1.382 | N12: 1400.2 | O12: 577 | P12: 80.4
A13: 1398 | B13: 0.412 | C13: 0.02 | D13: 1401.2 | E13: 21.6 | F13: 41.6 | G13: 21.2 | H13: 35.4 | I13: 1 | J13: 1 | K13: 1 | L13: 1 | N13: 1400.3 | O13: 633.9 | P13: 69.7
A14: 1399 | B14: 0.471 | C14: 0.012 | I14: =PRODUCT(I2:I13) -> 11.369198 | J14: =PRODUCT(J2:J13) -> 9.9491888 | K14: =PRODUCT(K2:K13) -> 5.5275547 | L14: =PRODUCT(L2:L13) -> 9.3389884 | M14: ضريب تغيير قيمت نسبت به سال مبنا (1395) | N14: 1400.4 | O14: 683.6 | P14: 56.7
A15: 1400 | B15: 0.462 | C15: 0.047 | N15: 1401.1 | O15: 768.9 | P15: 48
A16: 1401 | B16: 0.465 | C16: 0.08 | N16: 1401.2 | O16: 750.9 | P16: 40.4
A17: 1402 | B17: 0.5 | C17: 0.04
B18: =PRODUCT(B7+1,B8+1,B9+1,B10+1,B11+1,B12+1,B13+1,B14+1,B15+1,B16+1,B17+1) -> 18.576033 | C18: =PRODUCT(C7+1,C8+1,C9+1,C10+1,C11+1,C12+1,C13+1,C14+1,C15+1,C16+1,C17+1) -> 1.3670534

Sheet Engineering
B1: لیست مدارک مهندسی تفصیلی پروژه احداث واحد نمکردایی گچساران-4 به روش EPC | AE1: بهاي كل (ریال) | AF1: حق الزحمه (ریال به ازای یک نفرساعت) | AI1: نفرساعت نيروي انساني | AL1: شرح
AF2: مهندس ارشد | AG2: مهندس طراح | AH2: نقشه کش | AI2: مهندس ارشد | AJ2: مهندس طراح | AK2: نقشه کش
AE3: =(AK3*AH3+AJ3*AG3+AI3*AF3) -> 45441000000 | AF3: 9180000 | AI3: =SUM(W9,U9,S9,Q9,O9,M9,K9,I9,G9,E9,C9) -> 4950 | AL3: بازنگری و صحه گذاری اسناد پایه
A4: جدول نفر ساعت مهندسی مورد نیاز انجام مهندسی تفصیلی
AI5: نفرساعت نيروي انساني | AL5: شرح | AN5: شرح | AO5: نفر ساعت مهندسی | AS5: حق الزحمه (ریال) نفر ساعت | AV5: بهای کل
AI6: مهندس ارشد | AJ6: مهندس طراح | AK6: نقشه کش | AO6: سال | AP6: نقشه کش | AQ6: مهندس طراح | AR6: مهندس ارشد | AS6: نقشه کش | AT6: مهندس طراح | AU6: مهندس ارشد | AV6: (ریال)
B7: PR | D7: ME | F7: HV | H7: SF | J7: PI | L7: IN | N7: EL | P7: CV | R7: AR | T7: ST | V7: TC | X7: PC | Z7: DRAFT MAN | AI7: =C23-C9 -> 1269 | AJ7: =B23 -> 5210.65 | AK7: =Z10 -> 624.75 | AL7: بخش فرآيند | AN7: بخش فرآيند | AO7: سال 1402 | AP7: =ROUND(AK$7*0.4,0) -> 250 | AQ7: =ROUND(AJ$7*0.4,0) -> 2084 | AR7: =ROUND(AI$7*0.4,0) -> 508 | AS7: 5120000 | AT7: 6400000 | AU7: 8000000 | AV7: =SUMPRODUCT(AS7:AU7,AP7:AR7) -> 18681600000
B8: Jr | C8: Sr | D8: Jr | E8: Sr | F8: Jr | G8: Sr | H8: Jr | I8: Sr | J8: Jr | K8: Sr | L8: Jr | M8: Sr | N8: Jr | O8: Sr | P8: Jr | Q8: Sr | R8: Jr | S8: Sr | T8: Jr | U8: Sr | V8: Jr | W8: Sr | X8: Jr | Y8: Sr | AI8: =E23-E9 -> 1171.6 | AJ8: =D23 -> 4957.5 | AK8: =Z11 -> 224.25 | AL8: بخش كارهاي مكانيكال | AO8: سال 1403 | AP8: =ROUND(AK$7*0.4,0) -> 250 | AQ8: =ROUND(AJ$7*0.4,0) -> 2084 | AR8: =ROUND($AI$7*0.4,0) -> 508 | AS8: 7168000 | AT8: 8960000 | AU8: 11200000 | AV8: =SUMPRODUCT(AS8:AU8,AP8:AR8) -> 26154240000
A9: Endorsement | B9: 0 | C9: =E.Endorsement!E5 -> 600 | D9: 0 | E9: =E.Endorsement!E10 -> 600 | F9: 0 | G9: =E.Endorsement!E11 -> 400 | H9: 0 | I9: =E.Endorsement!E6 -> 500 | J9: 0 | K9: =E.Endorsement!E12 -> 400 | L9: 0 | M9: =E.Endorsement!E15 -> 400 | N9: 0 | O9: =E.Endorsement!E13 -> 500 | P9: 0 | Q9: =E.Endorsement!E7 -> 400 | R9: 0 | S9: =E.Endorsement!E9 -> 400 | T9: 0 | U9: =E.Endorsement!E8 -> 400 | V9: 0 | W9: =E.Endorsement!E14 -> 350 | X9: 0 | Y9: 0 | Z9: 0 | AI9: =G23-G9 -> 292.4 | AJ9: =F23 -> 1555.55 | AK9: =Z12 -> 1380 | AL9: بخش كارهاي HVAC | AO9: سال 1404 | AP9: =ROUND(AK$7*0.2,0) -> 125 | AQ9: =ROUND(AJ$7*0.2,0) -> 1042 | AR9: =ROUND($AI$7*0.2,0) -> 254 | AS9: 10035200 | AT9: 12544000 | AU9: 15680000 | AV9: =SUMPRODUCT(AS9:AU9,AP9:AR9) -> 18307968000
A10: Process | B10: =E.Process!C146 -> 4045.65 | C10: =E.Process!D146 -> 1109 | D10: =E.Process!E146 -> 161 | E10: =E.Process!F146 -> 23 | F10: =E.Process!G146 -> 0 | G10: =E.Process!H146 -> 1 | H10: =E.Process!I146 -> 5 | I10: =E.Process!J146 -> 2 | ... Z10: =E.Process!AA146 -> 624.75 | AI10: =I23-I9 -> 677.4 | AJ10: =H23 -> 1665.55 | AK10: =Z13 -> 368 | AL10: بخش ایمنی | AN10: بخش كارهاي مكانيكال | AO10: سال 1402 | AP10: =ROUND(AK$8*0.4,0) -> 90 | AQ10: =ROUND(AJ$8*0.4,0) -> 1983 | AR10: =ROUND($AI$8*0.4,0) -> 469 | AS10: 5120000 | AT10: 6400000 | AU10: 8000000 | AV10: =SUMPRODUCT(AS10:AU10,AP10:AR10) -> 16904000000
A11: Mechanic | B11: =E.Mechanic!C145 -> 604 | C11: =E.Mechanic!D145 -> 77 | D11: =E.Mechanic!E145 -> 4649 | E11: =E.Mechanic!F145 -> 1070.6 | F11: =E.Mechanic!G145 -> 0 | G11: =E.Mechanic!H145 -> 0 | H11: =E.Mechanic!I145 -> 6 | I11: =E.Mechanic!J145 -> 1 | ... Z11: =E.Mechanic!AA145 -> 224.25 | AI11: =K23-K9 -> 2404.6 | AJ11: =J23 -> 7970 | AK11: =Z14 -> 4887.5 | AL11: بخش كارهاي لوله كشي و خطوط لوله | AO11: سال 1403 | AP11: =ROUND(AK$8*0.4,0) -> 90 | AQ11: =ROUND(AJ$8*0.4,0) -> 1983 | AR11: =ROUND($AI$8*0.4,0) -> 469 | AS11: 7168000 | AT11: 8960000 | AU11: 11200000 | AV11: =SUMPRODUCT(AS11:AU11,AP11:AR11) -> 23665600000
A12: HVAC | B12: =E.HVAC!C51 -> 0 | C12: =E.HVAC!D51 -> 0 | D12: =E.HVAC!E51 -> 0 | E12: =E.HVAC!F51 -> 0 | F12: =E.HVAC!G51 -> 1543.55 | G12: =E.HVAC!H51 -> 287.4 | H12: =E.HVAC!I51 -> 0 | I12: =E.HVAC!J51 -> 0 | ... Z12: =E.HVAC!AA51 -> 1380 | AI12: =M23-M9 -> 5246.7 | AJ12: =L23 -> 7618.9 | AK12: =Z15 -> 1075.25 | AL12: بخش كارهاي ابزار دقيق | AO12: سال 1404 | AP12: =ROUND(AK$8*0.2,0) -> 45 | AQ12: =ROUND(AJ$8*0.2,0) -> 992 | AR12: =ROUND($AI$8*0.2,0) -> 234 | AS12: 10035200 | AT12: 12544000 | AU12: 15680000 | AV12: =SUMPRODUCT(AS12:AU12,AP12:AR12) -> 16564352000
A13: HSE | B13: =E.HSE!C77 -> 7 | C13: =E.HSE!D77 -> 1 | D13: =E.HSE!E77 -> 20 | E13: =E.HSE!F77 -> 0 | F13: =E.HSE!G77 -> 0 | G13: =E.HSE!H77 -> 0 | H13: =E.HSE!I77 -> 1624.55 | I13: =E.HSE!J77 -> 628.4 | ... Z13: =E.HSE!AA77 -> 368 | AI13: =O23-O9 -> 2437.8 | AJ13: =N23 -> 7549.56 | AK13: =Z16 -> 3772 | AL13: بخش كارهاي برقي | AN13: بخش كارهاي HVAC | AO13: سال 1402 | AP13: =ROUND(AK$9*0.4,0) -> 552 | AQ13: =ROUND(AJ$9*0.4,0) -> 622 | AR13: =ROUND($AI$9*0.4,0) -> 117 | AS13: 5120000 | AT13: 6400000 | AU13: 8000000 | AV13: =SUMPRODUCT(AS13:AU13,AP13:AR13) -> 7743040000
A14: Piping&Pipeline | B14: ='E.Piping&Pipeline'!C151 -> 65 | C14: ='E.Piping&Pipeline'!D151 -> 49 | D14: ='E.Piping&Pipeline'!E151 -> 0 | E14: ='E.Piping&Pipeline'!F151 -> 45 | F14: ='E.Piping&Pipeline'!G151 -> 0 | G14: ='E.Piping&Pipeline'!H151 -> 0 | H14: ='E.Piping&Pipeline'!I151 -> 0 | I14: ='E.Piping&Pipeline'!J151 -> 17 | ... Z14: ='E.Piping&Pipeline'!AA151 -> 4887.5 | AI14: =Q23-Q9 -> 696.4 | AJ14: =P23 -> 3485.8 | AK14: =Z17 -> 598 | AL14: بخش كارهاي مخابرات | AO14: سال 1403 | AP14: =ROUND(AK$9*0.4,0) -> 552 | AQ14: =ROUND(AJ$9*0.4,0) -> 622 | AR14: =ROUND($AI$9*0.4,0) -> 117 | AS14: 7168000 | AT14: 8960000 | AU14: 11200000 | AV14: =SUMPRODUCT(AS14:AU14,AP14:AR14) -> 10840256000
A15: Instrument | B15: =E.Instrument!C192 -> 476 | C15: =E.Instrument!D192 -> 29 | D15: =E.Instrument!E192 -> 0 | E15: =E.Instrument!F192 -> 8 | F15: =E.Instrument!G192 -> 0 | G15: =E.Instrument!H192 -> 0 | H15: =E.Instrument!I192 -> 13 | I15: =E.Instrument!J192 -> 10 | ... Z15: =E.Instrument!AA192 -> 1075.25 | AI15: =S23-S9 -> 296.2 | AJ15: =R23 -> 1763.35 | AK15: =Z18 -> 1919.35 | AL15: بخش كارهاي سيويل | AO15: سال 1404 | AP15: =ROUND(AK$9*0.2,0) -> 276 | AQ15: =ROUND(AJ$9*0.2,0) -> 311 | AR15: =ROUND($AI$9*0.2,0) -> 58 | AS15: 10035200 | AT15: 12544000 | AU15: 15680000 | AV15: =SUMPRODUCT(AS15:AU15,AP15:AR15) -> 7580339200
A16: Electrical | B16: =E.Electrical!C235 -> 5 | C16: =E.Electrical!D235 -> 0 | D16: =E.Electrical!E235 -> 79 | E16: =E.Electrical!F235 -> 8 | F16: =E.Electrical!G235 -> 0 | G16: =E.Electrical!H235 -> 0 | H16: =E.Electrical!I235 -> 0 | I16: =E.Electrical!J235 -> 0 | ... Z16: =E.Electrical!AA235 -> 3772 | AI16: =U23-U9 -> 1008.5 | AJ16: =T23 -> 4983.95 | AK16: =Z19 -> 3254.5 | AL16: بخش كارهاي معماری | AN16: بخش ایمنی | AO16: سال 1402 | AP16: =ROUND(AK$10*0.4,0) -> 147 | AQ16: =ROUND(AJ$10*0.4,0) -> 666 | AR16: =ROUND($AI$10*0.4,0) -> 271 | AS16: 5120000 | AT16: 6400000 | AU16: 8000000 | AV16: =SUMPRODUCT(AS16:AU16,AP16:AR16) -> 7183040000
A17: Telecom | B17: =E.TELECOM!C53 -> 0 | C17: =E.TELECOM!D53 -> 0 | D17: =E.TELECOM!E53 -> 0 | E17: =E.TELECOM!F53 -> 0 | F17: =E.TELECOM!G53 -> 0 | G17: =E.TELECOM!H53 -> 0 | H17: =E.TELECOM!I53 -> 0 | I17: =E.TELECOM!J53 -> 0 | ... Z17: =E.TELECOM!AA53 -> 598 | AI17: =W23-W9 -> 306.8 | AJ17: =V23 -> 1266.5 | AK17: =Z21 -> 3914.6 | AL17: بخش كارهاي سازه | AO17: سال 1403 | AP17: =ROUND(AK$10*0.4,0) -> 147 | AQ17: =ROUND(AJ$10*0.4,0) -> 666 | AR17: =ROUND($AI$10*0.4,0) -> 271 | AS17: 7168000 | AT17: 8960000 | AU17: 11200000 | AV17: =SUMPRODUCT(AS17:AU17,AP17:AR17) -> 10056256000
A18: Civil | B18: =E.Civil!C152 -> 6 | C18: =E.Civil!D152 -> 3 | D18: =E.Civil!E152 -> 8 | E18: =E.Civil!F152 -> 4 | F18: =E.Civil!G152 -> 0 | G18: =E.Civil!H152 -> 0 | H18: =E.Civil!I152 -> 4 | I18: =E.Civil!J152 -> 2 | ... Z18: =E.Civil!AA152 -> 1919.35 | AI18: =Y23-Y9 -> 230 | AJ18: =X23 -> 860 | AK18: =Z22 -> 0 | AL18: کنترل پروژه | AO18: سال 1404 | AP18: =ROUND(AK$10*0.2,0) -> 74 | AQ18: =ROUND(AJ$10*0.2,0) -> 333 | AR18: =ROUND($AI$10*0.2,0) -> 135 | AS18: 10035200 | AT18: 12544000 | AU18: 15680000 | AV18: =SUMPRODUCT(AS18:AU18,AP18:AR18) -> 7036556800
A19: Architectural | B19: =E.Arichitectural!C83 -> 2 | C19: =E.Arichitectural!D83 -> 1 | D19: =E.Arichitectural!E83 -> 14 | E19: =E.Arichitectural!F83 -> 1 | F19: =E.Arichitectural!G83 -> 12 | G19: =E.Arichitectural!H83 -> 4 | H19: =E.Arichitectural!I83 -> 5 | I19: =E.Arichitectural!J83 -> 13 | ... Z19: =E.Arichitectural!AA83 -> 3254.5 | AI19: =SUM(AI7:AI18) -> 16037.4 | AJ19: =SUM(AJ3:AJ18) -> 48887.31 | AK19: =SUM(AK3:AK18) -> 22018.2 | AL19: مجموع | AN19: بخش كارهاي لوله كشي و خطوط لوله | AO19: سال 1402 | AP19: =ROUND(AK$11*0.4,0) -> 1955 | AQ19: =ROUND(AJ$11*0.4,0) -> 3188 | AR19: =ROUND($AI$11*0.4,0) -> 962 | AS19: 5120000 | AT19: 6400000 | AU19: 8000000 | AV19: =SUMPRODUCT(AS19:AU19,AP19:AR19) -> 38108800000
AO20: سال 1403 | AP20: =ROUND(AK$11*0.4,0) -> 1955 | AQ20: =ROUND(AJ$11*0.4,0) -> 3188 | AR20: =ROUND($AI$11*0.4,0) -> 962 | AS20: 7168000 | AT20: 8960000 | AU20: 11200000 | AV20: =SUMPRODUCT(AS20:AU20,AP20:AR20) -> 53352320000
A21: Structural | B21: =E.Structure!C328 -> 0 | C21: =E.Structure!D328 -> 0 | D21: =E.Structure!E328 -> 26.5 | E21: =E.Structure!F328 -> 12 | F21: =E.Structure!G328 -> 0 | G21: =E.Structure!H328 -> 0 | H21: =E.Structure!I328 -> 8 | I21: =E.Structure!J328 -> 4 | ... Z21: =E.Structure!AA328 -> 3914.6 | AJ21: مطالعات زیست محیطی و غیره | AO21: سال 1404 | AP21: =ROUND(AK$11*0.2,0) -> 978 | AQ21: =ROUND(AJ$12*0.2,0) -> 1524 | AR21: =ROUND($AI$11*0.2,0) -> 481 | AS21: 10035200 | AT21: 12544000 | AU21: 15680000 | AV21: =SUMPRODUCT(AS21:AU21,AP21:AR21) -> 36473561600
A22: Project Control | B22: ='E.Project Control'!C13 -> 0 | C22: ='E.Project Control'!D13 -> 0 | D22: ='E.Project Control'!E13 -> 0 | E22: ='E.Project Control'!F13 -> 0 | F22: ='E.Project Control'!G13 -> 0 | G22: ='E.Project Control'!H13 -> 0 | H22: ='E.Project Control'!I13 -> 0 | I22: ='E.Project Control'!J13 -> 0 | ... Z22: ='E.Project Control'!AA13 -> 0 | AJ22: حق الزحمه | AK22: شرح | AN22: بخش كارهاي ابزار دقيق | AO22: سال 1402 | AP22: =ROUND(AK$12*0.4,0) -> 430 | AQ22: =ROUND(AJ$12*0.4,0) -> 3048 | AR22: =ROUND($AI$12*0.4,0) -> 2099 | AS22: 5120000 | AT22: 6400000 | AU22: 8000000 | AV22: =SUMPRODUCT(AS22:AU22,AP22:AR22) -> 38500800000
A23: Total | B23: =SUM(B9:B22) -> 5210.65 | C23: =SUM(C9:C22) -> 1869 | D23: =SUM(D9:D22) -> 4957.5 | E23: =SUM(E9:E22) -> 1771.6 | F23: =SUM(F9:F22) -> 1555.55 | G23: =SUM(G9:G22) -> 692.4 | H23: =SUM(H9:H22) -> 1665.55 | I23: =SUM(I9:I22) -> 1177.4 | ... Z23: =SUM(Z9:Z22) -> 22018.2 | AJ23: 4000000000 | AK23: مطالعات FMEA, HAZID, HAZOP (فاز طرح و ساخت) | AO23: سال 1403 | AP23: =ROUND(AK$12*0.4,0) -> 430 | AQ23: =ROUND(AJ$12*0.4,0) -> 3048 | AR23: =ROUND($AI$12*0.4,0) -> 2099 | AS23: 7168000 | AT23: 8960000 | AU23: 11200000 | AV23: =SUMPRODUCT(AS23:AU23,AP23:AR23) -> 53901120000
AJ24: 1500000000 | AK24: مطالعات پیوست سلامت | AO24: سال 1404 | AP24: =ROUND(AK$12*0.2,0) -> 215 | AQ24: =ROUND(AJ$11*0.2,0) -> 1594 | AR24: =ROUND($AI$12*0.2,0) -> 1049 | AS24: 10035200 | AT24: 12544000 | AU24: 15680000 | AV24: =SUMPRODUCT(AS24:AU24,AP24:AR24) -> 38601024000
AJ25: 3500000000 | AK25: مطالعات ارزیابی اثرات زیست محیطی (فاز طرح و ساخت) | AN25: بخش كارهاي برقي | AO25: سال 1402 | AP25: =ROUND(AK$13*0.4,0) -> 1509 | AQ25: =ROUND(AJ$13*0.4,0) -> 3020 | AR25: =ROUND($AI$13*0.4,0) -> 975 | AS25: 5120000 | AT25: 6400000 | AU25: 8000000 | AV25: =SUMPRODUCT(AS25:AU25,AP25:AR25) -> 34854080000
AJ26: 9000000000 | AK26: مطالعات ژئوتکنیک تکمیلی مورد نیاز برای تهیه مدارک مهندسی | AO26: سال 1403 | AP26: =ROUND(AK$13*0.4,0) -> 1509 | AQ26: =ROUND(AJ$13*0.4,0) -> 3020 | AR26: =ROUND($AI$13*0.4,0) -> 975 | AS26: 7168000 | AT26: 8960000 | AU26: 11200000 | AV26: =SUMPRODUCT(AS26:AU26,AP26:AR26) -> 48795712000
AJ27: 3500000000 | AK27: مطالعات پدافند غیر عامل | AO27: سال 1404 | AP27: =ROUND(AK$13*0.2,0) -> 754 | AQ27: =ROUND(AJ$13*0.2,0) -> 1510 | AR27: =ROUND($AI$13*0.2,0) -> 488 | AS27: 10035200 | AT27: 12544000 | AU27: 15680000 | AV27: =SUMPRODUCT(AS27:AU27,AP27:AR27) -> 34159820800
AJ28: 4000000000 | AK28: عملیات نقشه برداری مورد نیاز برای تهیه مدارک مهندسی | AN28: بخش كارهاي مخابرات | AO28: سال 1402 | AP28: =ROUND(AK$14*0.4,0) -> 239 | AQ28: =ROUND(AJ$14*0.4,0) -> 1394 | AR28: =ROUND($AI$14*0.4,0) -> 279 | AS28: 5120000 | AT28: 6400000 | AU28: 8000000 | AV28: =SUMPRODUCT(AS28:AU28,AP28:AR28) -> 12377280000
AJ29: 4000000000 | AK29: عملیات مستند سازی و استقرار سیستم ارسال مدارک | AO29: سال 1403 | AP29: =ROUND(AK$14*0.4,0) -> 239 | AQ29: =ROUND(AJ$14*0.4,0) -> 1394 | AR29: =ROUND($AI$14*0.4,0) -> 279 | AS29: 7168000 | AT29: 8960000 | AU29: 11200000 | AV29: =SUMPRODUCT(AS29:AU29,AP29:AR29) -> 17328192000
AJ30: 3500000000 | AK30: مهندسی ارزش | AO30: سال 1404 | AP30: =ROUND(AK$14*0.2,0) -> 120 | AQ30: =ROUND(AJ$14*0.2,0) -> 697 | AR30: =ROUND($AI$14*0.2,0) -> 139 | AS30: 10035200 | AT30: 12544000 | AU30: 15680000 | AV30: =SUMPRODUCT(AS30:AU30,AP30:AR30) -> 12126912000
AJ31: =SUM(AJ23:AJ30)*0.05 -> 1650000000 | AK31: ماليات قرارداد شركتهاي ثالث بر عهده پيمانكار به ميزان 5 درصد | AN31: بخش كارهاي سيويل | AO31: سال 1402 | AP31: =ROUND(AK$15*0.4,0) -> 768 | AQ31: =ROUND(AJ$15*0.4,0) -> 705 | AR31: =ROUND($AI$15*0.4,0) -> 118 | AS31: 5120000 | AT31: 6400000 | AU31: 8000000 | AV31: =SUMPRODUCT(AS31:AU31,AP31:AR31) -> 9388160000
AJ32: =SUM(AJ23:AJ31) -> 34650000000 | AK32: مجموع | AO32: سال 1403 | AP32: =ROUND(AK$15*0.4,0) -> 768 | AQ32: =ROUND(AJ$15*0.4,0) -> 705 | AR32: =ROUND($AI$15*0.4,0) -> 118 | AS32: 7168000 | AT32: 8960000 | AU32: 11200000 | AV32: =SUMPRODUCT(AS32:AU32,AP32:AR32) -> 13143424000
AO33: سال 1404 | AP33: =ROUND(AK$15*0.2,0) -> 384 | AQ33: =ROUND(AJ$15*0.2,0) -> 353 | AR33: =ROUND($AI$15*0.2,0) -> 59 | AS33: 10035200 | AT33: 12544000 | AU33: 15680000 | AV33: =SUMPRODUCT(AS33:AU33,AP33:AR33) -> 9206668800
AN34: بخش كارهاي معماری | AO34: سال 1402 | AP34: =ROUND(AK$16*0.4,0) -> 1302 | AQ34: =ROUND(AJ$16*0.4,0) -> 1994 | AR34: =ROUND($AI$16*0.4,0) -> 403 | AS34: 5120000 | AT34: 6400000 | AU34: 8000000 | AV34: =SUMPRODUCT(AS34:AU34,AP34:AR34) -> 22651840000
AJ35: مبلغ (ريال) | AK35: شرح | AO35: سال 1403 | AP35: =ROUND(AK$16*0.4,0) -> 1302 | AQ35: =ROUND(AJ$16*0.4,0) -> 1994 | AR35: =ROUND($AI$16*0.4,0) -> 403 | AS35: 7168000 | AT35: 8960000 | AU35: 11200000 | AV35: =SUMPRODUCT(AS35:AU35,AP35:AR35) -> 31712576000
AJ36: =AE3 -> 45441000000 | AK36: بازنگری و صحه گذاری اسناد پایه | AO36: سال 1404 | AP36: =ROUND(AK$16*0.2,0) -> 651 | AQ36: =ROUND(AJ$16*0.2,0) -> 997 | AR36: =ROUND($AI$16*0.2,0) -> 202 | AS36: 10035200 | AT36: 12544000 | AU36: 15680000 | AV36: =SUMPRODUCT(AS36:AU36,AP36:AR36) -> 22206643200
AJ37: =AV43 -> 748915072000 | AK37: مهندسی تفصیلی | AN37: بخش كارهاي سازه | AO37: سال 1402 | AP37: =ROUND(AK$17*0.4,0) -> 1566 | AQ37: =ROUND(AJ$17*0.4,0) -> 507 | AR37: =ROUND($AI$17*0.4,0) -> 123 | AS37: 5120000 | AT37: 6400000 | AU37: 8000000 | AV37: =SUMPRODUCT(AS37:AU37,AP37:AR37) -> 12246720000
AJ38: =AJ32 -> 34650000000 | AK38: مطالعات زیست محیطی و غیره | AO38: سال 1403 | AP38: =ROUND(AK$17*0.4,0) -> 1566 | AQ38: =ROUND(AJ$17*0.4,0) -> 507 | AR38: =ROUND($AI$17*0.4,0) -> 123 | AS38: 7168000 | AT38: 8960000 | AU38: 11200000 | AV38: =SUMPRODUCT(AS38:AU38,AP38:AR38) -> 17145408000
AJ39: =SUM(AJ36:AJ38)*0.2 -> 165801214400 | AK39: مديريت مهندسي | AO39: سال 1404 | AP39: =ROUND(AK$17*0.2,0) -> 783 | AQ39: =ROUND(AJ$17*0.2,0) -> 253 | AR39: =ROUND($AI$17*0.2,0) -> 61 | AS39: 10035200 | AT39: 12544000 | AU39: 15680000 | AV39: =SUMPRODUCT(AS39:AU39,AP39:AR39) -> 11987673600
AJ40: =SUM(AJ36:AJ39) -> 994807286400 | AK40: مجموع | AN40: کنترل پروژه | AO40: سال 1402 | AP40: =ROUND(AK$18*0.4,0) -> 0 | AQ40: =ROUND(AJ$18*0.4,0) -> 344 | AR40: =ROUND($AI$18*0.4,0) -> 92 | AS40: 5120000 | AT40: 6400000 | AU40: 8000000 | AV40: =SUMPRODUCT(AS40:AU40,AP40:AR40) -> 2937600000
AO41: سال 1403 | AP41: =ROUND(AK$18*0.4,0) -> 0 | AQ41: =ROUND(AJ$18*0.4,0) -> 344 | AR41: =ROUND($AI$18*0.4,0) -> 92 | AS41: 7168000 | AT41: 8960000 | AU41: 11200000 | AV41: =SUMPRODUCT(AS41:AU41,AP41:AR41) -> 4112640000
AO42: سال 1404 | AP42: =ROUND(AK$18*0.2,0) -> 0 | AQ42: =ROUND(AJ$18*0.2,0) -> 172 | AR42: =ROUND($AI$18*0.2,0) -> 46 | AS42: 10035200 | AT42: 12544000 | AU42: 15680000 | AV42: =SUMPRODUCT(AS42:AU42,AP42:AR42) -> 2878848000
AO43: مجموع | AP43: =SUM(AP7:AP42) -> 22021 | AQ43: =SUM(AQ7:AQ42) -> 48888 | AR43: =SUM(AR7:AR42) -> 16038 | AV43: =SUM(AV7:AV42) -> 748915072000

Sheet Procurement
A1: جدول 2.1 -جدول خلاصه مالی تفكيكي تهيه و خريد كالاي مکانیک و لوله و اتصالات مورد نياز پروژه بر اساس پیوست 1،2 و3 | F1: ارز مرجع | G1: =USD_Change_IRR -> 420000
A2: رديف | B2: شرح فعاليت ها | C2: دلار | D2: ريال | F2: ضريب تورم عمومي ريالي | G2: =IRR_Inflation_Factor -> 18.576033
A3: 1 | B3: الكترواستاتيك ها و ادوات مربوطه | C3: =P.ME!I126 -> 7594862.8 | D3: =P.ME!K126 -> 0 | F3: ضريب تورم ارزي دلار | G3: =USD_Inflation_Factor -> 1.3670534
A4: 2 | B4: كوره ها و ادوات مربوطه | C4: =P.ME!I127 -> 6487000 | D4: =P.ME!K127 -> 0
A5: 3 | B5: مبدل نفت / نفت و مبدل آب / آب | C5: =P.ME!I128 -> 0 | D5: =P.ME!K128 -> 625209000000
A6: 4 | B6: تلمبه ها | C6: =P.ME!I129 -> 0 | D6: =P.ME!K129 -> 2082268000000
A7: 5 | B7: شيرآلات و اتصالات ، رنگها و لوله های داخل سایت | C7: =P.ME!I130 -> 0 | D7: =P.ME!K130 -> 2452617000000
A8: 6 | B8: خرید لوله های بیرون سایت | C8: =P.ME!I131 -> 0 | D8: =P.ME!K131 -> 2982846000000
A9: 7 | B9: مخزن های اتمسفریک و تحت فشار | C9: =P.ME!I132 -> 0 | D9: =P.ME!K132 -> 797604000000
A10: 8 | B10: سیستم پساب | C10: =P.ME!I133 -> 4773913.7 | D10: =P.ME!K133 -> 0
A11: 9 | B11: air compressor Packages | C11: =P.ME!I134 -> 0 | D11: =P.ME!K134 -> 418938000000
A12: 10 | B12: Flare & Ignitor | C12: =P.ME!I135 -> 0 | D12: =P.ME!K135 -> 372764000000
B13: بسته های تزریق مواد شیمیایی | C13: =P.ME!I136 -> 0 | D13: =P.ME!K136 -> 337896000000
A14: 12 | B14: Vacuum Deaerator Package | C14: =P.ME!I137 -> 0 | D14: =P.ME!K137 -> 1.3442907e+11
A15: 13 | B15: سیستم HVAC | C15: =P.ME!I138 -> 0 | D15: =P.ME!K138 -> 370840000000
A16: 14 | B16: جرثقیلهای سقفی | C16: =P.ME!I139 -> 0 | D16: =P.ME!K139 -> 401940000000
A17: 15 | B17: خرید اقلام ایمنی و آتش نشانی | C17: =P.ME!I140 -> 0 | D17: =P.ME!K140 -> 163763000000
A18: 16 | B18: گیرنده و فرستنده توپک | C18: =P.ME!I141 -> 0 | D18: =P.ME!K141 -> 94500000000
A19: 17 | B19: مواد شیمیایی مصرفی | C19: =P.ME!I142 -> 0 | D19: =P.ME!K142 -> 592670000000
B20: جمع كل | C20: =P.ME!I143 -> 18855777 | D20: =SUM(D3:D19) -> 1.1828284e+13
A22: جدول 2.4 -جدول خلاصه مالی تفكيكي تهيه و خريد كالاي برق و مخابرات مورد نياز پروژه بر اساس پیوست 4
A23: رديف | B23: شرح فعاليت ها | C23: دلار | D23: ريال
A24: 1 | B24: تابلوها | C24: =P.EL!G173 -> 0 | D24: =ROUNDUP(P.EL!H173,-6) -> 806342000000
A25: 2 | B25: اتصالات برق (شامل گلندها، شرودها، جعبه هاي اتصال، مفصلها و ...) | C25: =P.EL!G174 -> 0 | D25: =ROUNDUP(P.EL!H174,-6) -> 305001000000
A26: 3 | B26: كابلهاي قدرت | C26: =P.EL!G175 -> 0 | D26: =ROUNDUP(P.EL!H175,-6) -> 627631000000
A27: 4 | B27: ترانس ها و UPS دیزل ژنراتور | C27: =ROUNDUP(P.EL!G176,-3) -> 1414000 | D27: =ROUNDUP(P.EL!H176,-6) -> 575848000000
A28: 5 | B28: وسايل و تجهيزات مخابرات، و پیجینگ | C28: =ROUNDUP(P.EL!G177,-3) -> 197000 | D28: =ROUNDUP(P.EL!H177,-6) -> 7581000000
A29: 6 | B29: پایه ها و برجهاي روشنائي و سایر ملحقات و ادوات روشنایی | C29: =P.EL!G178 -> 0 | D29: =ROUNDUP(P.EL!H178,-6) -> 169114000000
A30: 7 | B30: خط انتقال برق شامل کابل ، پایه ها و یراق آلات | C30: =P.EL!G179 -> 0 | D30: =ROUNDUP(P.EL!H179,-6) -> 532980000000
B31: جمع كل | C31: =SUM(C24:C30) -> 1611000 | D31: =SUM(D24:D30) -> 3024497000000
A33: جدول 2.5 -جدول خلاصه مالی تفكيكي تهيه و خريدادوات و تجهیزات ابزاردقیق و تجهیزات آزمایشگاه مورد نياز پروژه بر اساس پیوست 5و6
A34: رديف | B34: شرح فعاليت ها | C34: دلار | D34: ريال
A35: 1 | B35: ادوات ابزار دقیق شامل : ترانسمیترها ، سوئیچ ها ، گیج ها و ... | C35: =ROUNDUP(P.IN!E133+P.IN!E134,-3) -> 206000 | D35: =ROUNDUP(P.IN!G133+P.IN!G134,-6) -> 761483000000
A36: 2 | B36: شیرآلات ابزار شامل : شیر ON/OFF ، شیرهای کنترلی ، PSV ، PCV | C36: =ROUNDUP(P.IN!E135,-3) -> 0 | D36: =ROUNDUP(P.IN!G135,-6) -> 1232422000000
A37: 3 | B37: سيستم كنترل ( DCS,FGS )، ESD | C37: =ROUNDUP(P.IN!E136,-3) -> 0 | D37: =P.IN!G136 -> 701447326000
A38: 4 | B38: ادوات F&G و CO2 Total Flooding و ابزار خاص | C38: =P.IN!E137 -> 0 | D38: =ROUNDUP(P.IN!G137,-6) -> 604298000000
A39: 5 | B39: اقلام بالک ابزار دقیق | C39: =P.IN!E138 -> 0 | D39: =ROUNDUP(P.IN!G138,-6) -> 78020000000
A40: 6 | B40: کابلهای ابزار دقیق و ملحقات شامل : گلند سینی و ... | C40: =P.IN!E139 -> 0 | D40: =ROUNDUP(P.IN!G139+P.IN!G140,-6) -> 229255000000
A41: 7 | B41: تجهیزات آزمایشگاه | C41: =ROUNDUP(P.IN!E141,-3) -> 0 | D41: =ROUNDUP(P.IN!G141,-6) -> 436842000000
A42: 8 | B42: CCTV | C42: =P.IN!E142 -> 0 | D42: =ROUNDUP(P.IN!G142,-6) -> 184776000000
B43: جمع كل | C43: =SUM(C35:C42) -> 206000 | D43: =SUM(D35:D42) -> 4228543326000
A46: جدول 1.7 -جدول خلاصه مالی تفكيكي تهيه و خريد كالاي پروژه
A47: رديف | B47: شرح فعاليت ها | C47: دلار | D47: ريال
A48: 1 | B48: مجموع قیمت خرید تجهیزات مطابق جداول 2.1، 2.4 و 2.5 و اعمال فاكتور تورم ريال و دلار از سال 1395 تا 1402 | C48: =C43+C31+C20 -> 20672777 | D48: =SUM(D43,D31,D20) -> 1.9081324e+13
A49: 2 | B49: لوازم يدكي (شامل لوازم يدكي براي راه اندازي و لوازم يدكي موردنياز براي كاركرد دو ساله) | C49: =ROUNDUP((P.ME!G117+P.IN!C127+P.EL!E166)*per_Euro*USD_Inflation_Factor,-3) -> 2719000 | D49: =ROUNDUP(P.IN!H124+P.EL!F166+P.ME!F117+P.PI!I815*per_Euro*USD_Change_IRR,-6) -> 1165951000000 | F49: ضريب
A50: 3 | B50: ترخيص كالاي خارجي شامل هزينه هاي گمرك و بازرگاني ، عوارض موردنياز ماليات، هزينه‌هاي بانكي و ... | D50: =ROUNDUP(P.ME!J117+P.PI!L815+P.PL!D21+P.IN!F127+P.EL!G166,-6) -> 1813192000000
A51: 4 | B51: بیمه حمل کالاهای داخلی و خارجی، بیمه مسئولیت، تمام خطر نصب و سایر بیمه های مورد نیاز | D51: =ROUNDUP(Procurement_All_Insuramce*(D49+D48)+Procurement_All_Insuramce*(C49+C48)*USD_Change_IRR,-6) -> 300719000000 | F51: 0.01
A52: 5 | B52: هزينه هاي بارگيري ، حمل و تخليه كالاي خارجي، هزينه هاي بارگيري، حمل و تخليه كالاي داخلي | D52: =ROUNDUP((P.ME!K117+P.PI!K815+P.PL!E21+P.EL!J166+P.IN!G127),-6) -> 512751000000 | F52: 0.03
A53: 6 | B53: هزینه های بازرسی اشخاص ثالث | D53: =ROUNDUP(Procurement_QC_Inspection*(D48+D49+(C48+C49)*USD_Change_IRR),-6) -> 300719000000 | F53: 0.01
A54: 7 | B54: خدمات فنی سازندگان در دوران نصب و راه اندازی | D54: =ROUNDUP(Procurement_Final_Documentation*(D48+C48*USD_Change_IRR),-6) -> 832917000000 | F54: 0.03
B55: جمع كل | C55: =SUM(C48:C54) -> 23391777 | D55: =SUM(D48:D54) -> 2.4007573e+13

Sheet Construction
F2: :خلاصه براورد ساخت و اجرا مطابق تفکیک نرخ پیمان- پیوست یک قرارداد
F3: =E27 -> 2.8728056e+11 | K3: الف:تجهیز و برچیدن مطابق جدول ب-1 | Q3: الف
F4: =H27+0.15*H27 -> 1.1352174e+13 | K4: ب:ساخت و نصب و راه اندازی مطابق جدول ب-1 | Q4: ب
F5: =M33 -> 1.2848158e+12 | K5: ج:تسهیلات مورد نیاز کارفرما مطابق جدول ب-2 | Q5: ج
F6: =B36 -> 1.1513294e+11 | K6: د: الزامات HSEمطابق جدول ب-3 | Q6: د
F7: =M38 -> 72000000000 | K7: ه: هزینه دفتر فنی کارگاه | Q7: ه
F8: =SUM(F3:J7) -> 1.3111403e+13 | K8: مجموع
B10: شرح ردیف های الف و ب - برآورد هزینه ساخت و نصب و راه اندازی و تجهیز کارگاه - مطابق جداول
B11: جمع کل | E11: هزینه تجهیز کارگاه | H11: هزینه اجرا پس از اعمال ضریب بروزرسانی | I11: ضریب بروزرسانی به سه ماهه اول 1402 | J11: هزینه اجرا پس از اعمال ضرایب فهرست بهای مربوطه | M11: هزینه اجرامطابق فهرست بهای مربوطه | P11: عنوان
B12: =E12+H12 -> 4.6492494e+11 | E12: ='C.RETAINING WAL'!E25 -> 1.745129e+11 | H12: =ROUND(J12*I12,0) -> 290412038226 | I12: 1.06 | J12: ='C.foundation-2'!A31 -> 2.7397362e+11 | M12: ='C.foundation-2'!B31 -> 175163935524 | P12: اجرای فونداسیون تجهیزات
B13: =H13 -> 637828274396 | E13: یک قلم در ردیف اول محاسبه گردید | H13: =ROUND(J13*I13,0) -> 637828274396 | I13: 1.06 | J13: ='C.ROAD-2'!A27 -> 6.0172479e+11 | M13: ='C.ROAD-2'!B27 -> 380893730036 | P13: اجرای جاده های داخلی و خارجی
B14: =H14 -> 719145156294 | E14: یک قلم در ردیف اول محاسبه گردید | H14: =ROUND(J14*I14,0) -> 719145156294 | I14: 1.06 | J14: ='C.Shelters-2'!A46 -> 6.7843883e+11 | M14: ='C.Shelters-2'!B46 -> 438710828644 | P14: اجرای سایبانها
B15: =H15 -> 1709692715148 | E15: یک قلم در ردیف اول محاسبه گردید | H15: =ROUND(J15*I15,0) -> 1709692715148 | I15: 1.06 | J15: ='C.Buildings'!G20 -> 1612917655800 | M15: =J15/'C.Note'!$G$55 -> 1.0494617e+12 | P15: اجرای ساختمانها
B16: =H16 -> 2158472497849 | E16: یک قلم در ردیف اول محاسبه گردید | H16: =ROUND(J16*I16,0) -> 2158472497849 | I16: 1.06 | J16: ='C.OTHERS-2'!A33 -> 2.0362948e+12 | M16: ='C.OTHERS-2'!B33 -> 1239981269679 | P16: اجرای ابنیه و اقلام متفرقه
B17: =H17 -> 1103852062935 | E17: یک قلم در ردیف اول محاسبه گردید | H17: =ROUND(J17*I17,0) -> 1103852062935 | I17: 1.06 | J17: ='C.SITE-2'!A22 -> 1041369870693 | M17: ='C.SITE-2'!B22 -> 461314673320 | P17: محوطه سازی واحدها
B18: =H18 -> 171750408507 | E18: یک قلم در ردیف اول محاسبه گردید | H18: =ROUND(J18*I18,0) -> 171750408507 | I18: 1.062 | J18: ='C.RETAINING WAL'!A7 -> 161723548500 | M18: ='C.RETAINING WAL'!B7 -> 102421500000 | P18: اجرای دیوار حایل و شیروانی دورواحد
B19: =H19 -> 200075296057 | E19: یک قلم در ردیف اول محاسبه گردید | H19: =ROUND(J19*I19,0) -> 200075296057 | I19: 1.06 | J19: ='C.UG CIVIL-2'!A30 -> 1.8875028e+11 | M19: ='C.UG CIVIL-2'!B30 -> 113706706200 | P19: دفن کابل و لوله های دفنی
B20: =H20 -> 992055090120 | E20: یک قلم در ردیف اول محاسبه گردید | H20: =ROUND(J20*I20,0) -> 992055090120 | I20: 1.06 | J20: ='C.STEEL STRUCTURE (2)'!A29 -> 9.3590103e+11 | M20: ='C.STEEL STRUCTURE (2)'!B29 -> 607865879900 | P20: نصب و اجرای سازه های فلزی متفرقه
B21: =H21 -> 8711234972 | E21: یک قلم در ردیف اول محاسبه گردید | H21: =ROUND(J21*I21,0) -> 8711234972 | I21: 1.06 | J21: ='C.SITE-3'!B17 -> 8218146200 | M21: - | P21: احداث فضای سبز
B22: =SUM(E22:H22) -> 3.4726254e+11 | E22: ='C.Note'!$I$23*Construction!H22 -> 1.965637e+10 | H22: =ROUND(J22*I22,0) -> 327606170624 | I22: 1.061 | J22: ='C.mECHANICAL'!A239 -> 3.0877113e+11 | M22: ='C.mECHANICAL'!B239 -> 150633619879 | P22: اجرا و نصب تجهیزات مکانیک
B23: =SUM(E23:H23) -> 2.9669944e+11 | E23: ='C.Note'!$I$23*Construction!H23 -> 1.6794308e+10 | H23: =ROUND(J23*I23,0) -> 279905133293 | I23: 1.061 | J23: ='C.PIPELINE'!A51 -> 263812566723 | M23: ='C.PIPELINE'!B51 -> 109329700258 | P23: اجرای خطوط لوله
B24: =SUM(E24:H24) -> 9.2517346e+11 | E24: ='C.Note'!$I$23*Construction!H24 -> 5.2368309e+10 | H24: =ROUND(J24*I24,0) -> 872805147240 | I24: 1.06 | J24: ='C.PIPING'!A87 -> 8.2340108e+11 | M24: ='C.PIPING'!B87 -> 328965674112 | P24: اجرای پایپینگ درون واحدها
B25: =SUM(E25:H25) -> 2.1370356e+11 | E25: ='C.Note'!$I$23*Construction!H25 -> 1.2096428e+10 | H25: =ROUND(J25*I25,0) -> 201607130784 | I25: 1.058 | J25: ='C.ELECTRICAL'!A167 -> 190554944030 | M25: ='C.ELECTRICAL'!B167 -> 162341006850 | P25: اجرای برق
B26: =SUM(E26:H26) -> 2.093897e+11 | E26: ='C.Note'!$I$23*Construction!H26 -> 1.1852247e+10 | H26: =ROUND(J26*I26,0) -> 197537455978 | I26: 1.058 | J26: ='C.INSTRUMENT'!A97 -> 186708370490 | M26: ='C.INSTRUMENT'!B97 -> 75559842024 | P26: اجرای ابزاردقیق
B27: =SUM(B12:D26) -> 1.0158736e+13 | E27: =SUM(E12:G26) -> 2.8728056e+11 | H27: =SUM(H12:H26) -> 9871455812423 | J27: =SUM(J12:L26) -> 9.3125607e+12 | M27: =SUM(M12:O26) -> 5.39635e+12 | P27: مجموع
B29: شرح ردیف د - برآورد هزینه ایمنی کارگاه (HSE) | M29: شرح ردیف ج - برآورد تسهیلات کارفرما
B30: ='C.HSE(1)'!B27 -> 8.0139507e+10 | E30: لوازم حفاظت فردی و تجهیزات | M30: ='C.tashilat (2)'!B24 -> 1.1747869e+12 | P30: تسهيلات رفاهي گروه نظارت
B31: ='C.HSE(2)'!B17 -> 2.8588515e+09 | E31: سدجش و اندازه گیری 1 | M31: =SUM('C.tashilat'!C9,'C.tashilat'!C24,'C.tashilat'!C36) -> 1.1002883e+11 | P31: تسهیلات ماموریت داخل و خارج و آموزش
B32: ='C.HSE(2)'!B21 -> 81900000 | E32: سدجش و اندازه گیری 2
B33: ='C.HSE(2)'!B37 -> 5.0526809e+09 | E33: آموزش | M33: =SUM(M30:O32) -> 1.2848158e+12 | P33: مجموع
B34: ='C.HSE(1)'!C34 -> 27000000000 | E34: نیروی انسانی
M35: شرح ردیف ه: هزینه دفتر فنی کارگاه
B36: =SUM(B30:D35) -> 1.1513294e+11 | E36: مجموع | M36: 4 نفر طی بیست و چهار ماه هزینه نفر ماه : 750،000،000 ریال | P36: پرسنل دفتر فنی کارگاه (طبق توضیح بند 6 صفحه قبل (صفحه 4)
M38: =4*24*750000000 -> 72000000000 | P38: مجموع

Sheet C.CONTENT
P2: فهرست
Q3: الف) مبانی محاسبات براورد
Q4: ب) خلاصه برآورد مالی بخش اجرا
Q5: پیوست یک - برآورد هزینه اجرای پروژه بر اساس فهارس بها
B6: جدول 1 - برآورد اجرا بر اساس فهرست بهای ابنیه 1402 - احداث فونداسیون تجهیزات وادوات (بر اساس ریز متره مندرج در جدول الف پیوست 2) | Q6: -
B7: جدول 2 - برآورد اجرا بر اساس فهرست بهای ابنیه 1402 - احداث سایبان تجهیزات(بر اساس ریز متره مندرج در جدول ب پیوست 2) | Q7: -
B8: جدول 3 - برآورد اجرا بر اساس فهرست بهای ابنیه 140 - احداث جاده های دسترسی، جاده های داخل واحدها و پاترول(بر اساس ریز متره مندرج در جدول ج پیوست 2) | Q8: -
B9: جدول 4 - برآورد اجرا بر اساس فهرست بهای ابنیه 1402 - احداث ابنیه متفرقه (بر اساس ریز متره مندرج در جدول د پیوست 2) | Q9: -
B10: جدول 5 - برآورد اجرا بر اساس فهرست بهای ابنیه 1402 -محوطه سازی واحدها (بر اساس ریز متره مندرج در جدول ه پیوست 2) | Q10: -
B11: جدول 6 - برآورد اجرا فضای سبز - خارج از فهرست بها | Q11: -
B12: جدول7 - برآورد اجرا بر اساس فهرست بهای ابنیه 1402 - دفن لوله ها (داخل و خارج واحد) و کابل های زیر زمینی (بر اساس ریز متره مندرج در جدول و پیوست 2) | Q12: -
B13: جدول 8 - برآورد اجرا بر اساس فهرست بهای ابنیه 1402 - سازه های فلزی متفرقه (بر اساس ریز متره مندرج در جدول ط پیوست 2) | Q13: -
B14: جدول10 - برآورد اجرا بر اساس فهرست بهای باند و راه 1402 -ساخت دیوار حایل مجاور تپه و سطوح کوهبری شده و شیروانی دورتادور کارخانه | Q14: -
B15: جدول 11 - برآورد اجرا بر اساس فهرست بهای ابنیه 1402 -تجهیز و برچیدن کارگاه | Q15: -
B16: جدول 12 - برآورد اجرای لوله کشی وپایپینگ بر اساس فهرست بهای اختصاصی تاسیسات نفت و گاز، رشته نصب واحدهای بهره برداری نفت و گاز -1401 | Q16: -
B17: جدول 13 - برآورد اجراو نصب تجهیزات مکانیک بر اساس فهرست بهای اختصاصی تاسیسات نفت و گاز، رشته نصب واحدهای بهره برداری نفت و گاز -1401 | Q17: -
... B29: جدول 18-5: براورد هزینه ایمنی کارگاه : آموزش | Q29: -
C30: پیوست دو - ریز متره و برآورد احجام بخش سیویل وسازه
B31: جدول الف : ریز برآورد متره فونداسیون تجهیزات | Q31: -
B32: جدول ب-1 : ریز برآورد متره سایبانها - فونداسیون و کف سازی | Q32: -
B33: جدول ب-2 : ریز برآورد متره سایبانها - لسکلت فلزی | Q33: -
B34: جدول ج : ریز برآورد متره جاده ها | Q34: -
B35: جدول د : ریز برآورد متره ابنیه متفرقه | Q35: -
B36: جدول ه : ریز برآورد متره محوطه سازی | Q36: -
B37: جدول و : ریز برآورد کانال های لوله ها و کابل های دفنی | Q37: -
B38: جدول ط : ریز برآورد متره سازه های فلزی متفرقه | Q38: -

Sheet C.Note
R4: مبانی محاسبات براورد : | S4: الف)
R6: جهت براورد هزینه اجرای بخش سیویل و سازه از "فهرست بهای واحد پایه رشته ابنیه" سال 1402 استفاده شده است. | S6: -1
B8: با توجه به آنکه این پروژه در حد مهندسی مقدماتی و پایه بوده و نقشه معماری فاز یک آن اماده گردیده لیکن نقشه های فاز 2 معماری، نقشه های اجرایی فونداسیون، سازه بتی و فولادی و نیز نقشه های تاسیسات آن تهیه نگردیده و میبایست در مرحله مهندسی تفصیلی انجام شود، لذا امکان تهیه ریز برآورد اقلام و استفاده از فهرست احاد بهای ابنیه در این مرحله از پروژه میسر نمیباشد. لذا برای برآورد هزینه ساخت و اجرای ساختمانها از ابلاغیه شماره 47855/ش م مورخ 1401/12/16شورای مرکزی سازمان نظام مهندسی ساختمان که بر مبنای متراژ ساخت بنا میباشد، استفاده گردیده است | S8: -2
B13: جهت برآورد هزینه اجرای سایر بخشها از "فهرست بهای اختصاصی تاسیسات نفت و گاز - رشته نصب واحدهای بهره برداری نفت و گاز ایستگاه تراکم گاز" و "فهرست بهای اختصاصی تاسیسات نفت و گاز - رشته خطوط لوله روزمینی جریانی نفت و گاز" سال 1401 استفاده شده است. | S13: -3
R16: ضریب بالاسری بخش اجرا بر اساس فهرست بهای اختصاصی نصب واحدهای بهره برداری که در محاسبه هزینه پروژه منظور شده است معادل است با : | S16: -4
O17: گروه لوله کشی | R17: 1-4-
R18: هزینه بالاسری برای کارهایی که از طریق مناقصات انجام میشود : 48%
R19: ضریب هزینه تفاوت بیمه های تامین اجتماعی به میزان 1
R20: ضریب منطقه ای : 1.12
R21: ضریب بروزرسانی به سه ماهه چهارم 1401 : 1.51
G22: =1.48*1.12*1.51 -> 2.502976 | R22: ضریب اجرا که به صورت خطی در مبالغ محاسبه شده فهرست بها ضرب میگردد : =1.12*1.51 * 1.48 = | S22: -
I23: 0.06 | R23: ضریب هزینه تجهیز و برچیدن کارگاه که مبلغ آن با مبلغ اجرا جمع میگردد = | S23: -
O25: گروه نصب تجهیزات | R25: 2-4-
R26: هزینه بالاسری برای کارهایی که از طریق مناقصات انجام میشود : 48%
R27: ضریب هزینه تفاوت بیمه های تامین اجتماعی به میزان 1
R28: ضریب منطقه ای : 1.12
R29: ضریب بروزرسانی به سه ماهه چهارم 1401 : 1.515
G30: =1.48*1.12*1.515 -> 2.511264 | R30: ضریب اجرا که به صورت خطی در مبالغ محاسبه شده فهرست بها ضرب میگردد : =1.12*1.515 * 1.48 = | S30: -
I31: 0.06 | R31: ضریب هزینه تجهیز و برچیدن کارگاه که مبلغ آن با مبلغ اجرا جمع میگردد = | S31: -
M33: گروه نصب کارهای برقی و ابزار دقیق | R33: 3-4-
R34: هزینه بالاسری برای کارهایی که از طریق مناقصات انجام میشود : 48%
R35: ضریب هزینه تفاوت بیمه های تامین اجتماعی به میزان 1
R36: ضریب منطقه ای : 1.12
R37: ضریب بروزرسانی به سه ماهه چهارم 1401 : 1.491
G38: =1.48*1.12*1.491 -> 2.4714816 | R38: ضریب اجرا که به صورت خطی در مبالغ محاسبه شده فهرست بها ضرب میگردد : =1.12*1.491 * 1.48 = | S38: -
I39: 0.06 | R39: ضریب هزینه تجهیز و برچیدن کارگاه که مبلغ آن با مبلغ اجرا جمع میگردد = | S39: -
R41: ضریب بالاسری بخش اجرا بر اساس فهرست بهای اختصاصی خطوط لوله روزمینی که در محاسبه هزینه پروژه منظور شده است معادل است با : | S41: -5
R43: هزینه بالاسری برای کارهایی که از طریق مناقصات انجام میشود : 48%
R44: ضریب هزینه تفاوت بیمه های تامین اجتماعی به میزان 1
R45: ضریب منطقه ای : 1.11
R46: ضریب بروزرسانی به سه ماهه چهارم 1401 : 1.469
G47: =1.48*1.11*1.469 -> 2.4132732 | R47: ضریب اجرا که به صورت خطی در مبالغ محاسبه شده فهرست بها ضرب میگردد : =1.11*1.469 * 1.48 = | S47: -
I48: 0.06 | R48: ضریب هزینه تجهیز و برچیدن کارگاه که مبلغ آن با مبلغ اجرا جمع میگردد = | S48: -
R51: ضریب بالاسری بخش اجرا بر اساس فهرست رشته ابنیه که در محاسبه هزینه پروژه منظور شده است معادل است با | S51: -5
K52: 1.41 | R52: ضریب بالاسری برای کارهایی که از طریق مناقصات انجام میشود :
R53: ضریب منطقه ای : 1.09 | S53: -
R54: ضریب هزینه تجهیز و برچیدن کارگاه که مبلغ آن با مبلغ اجرا جمع میگردد = 4% | S54: -
G55: =1.41*1*1.09 -> 1.5369 | R55: ضریب اجرا که به صورت خطی در مبالغ محاسبه شده فهرست بها ضرب میگردد : 1.09 * 1.41 = | S55: -
R57: برای دفتر فنی کارگاه 4 نفر به شرح زیر برای مدت 20 ماه در نظر گرفته شده است: | S57: -6
R58: سرپرست دفتر فنی ، کنترل پروژه، دو نفر کارشناس فنی بر حسب نیاز
R59: حقوق هر کارشناس سایت بر اساس تجربه این مشاور 50 ملیون تومان در نظر گرفته شده است که با احتساب مالیات و بیمه 75 ملیون تومان هزینه در نظر گرفته شده است.
R63: ضریب بالاسری بخش اجرا بر اساس فهرست رشته راه و باند که در محاسبه هزینه پروژه منظور شده است معادل است با | S63: 7-
K64: 1.41 | R64: ضریب بالاسری برای کارهایی که از طریق مناقصات انجام میشود :
R65: ضریب منطقه ای : 1.12
R66: ضریب هزینه تجهیز و برچیدن کارگاه که مبلغ آن با مبلغ اجرا جمع میگردد = 4%
G67: =1.41*1*1.12 -> 1.5792 | R67: ضریب اجرا که به صورت خطی در مبالغ محاسبه شده فهرست بها ضرب میگردد : 1.12 * 141 = | S67: -
Q70: با توجه به اینکه نرخ فهارس بها براساس 1402 براساس نرخ سه ماهه چهارم 1401 میباشد لذا جهت بروزرسانی مبالغ به سه ماهه اول 1402 از ضرایب بروزرسانی زیر استفاده شده است : | R70: توضیحات
L71: 1.06 | N71: 1- فهرست ابنیه
L72: 1.062 | N72: 2- فهرست راه و باند
L73: 1.061 | N73: 3- فهرست خطوط لوله روزمینی
L74: 1.061 | M74: گروه نصب | N74: 4- فهرست نصب واحدهای بهره برداری
L75: 1.06 | M75: گروه لوله کشی
L76: 1.058 | M76: گروه برق

Sheet C.foundation-2
A1: جدول 1 - برآورد اجرا بر اساس فهرست بهای ابنیه 1402 - احداث فونداسیون تجهیزات وادوات (بر اساس ریز متره مندرج در جدول الف پیوست 2)
A2: ارزش کار | B2: مبلغ بدون اعمال ضرایب | C2: مقـدار | D2: واحد بــها با اعمال ضریب | E2: واحد بــهامطابق فهرست ابنیه 1402 | F2: واحـد | G2: شــــــــرح | I2: ردیف
F3: * | G3: خاکبرداری و پی کنی با ماشین | I3: * | K3: =ROUND(L4*L5*L6*L7,3) -> 1.537
A4: =C4*D4 -> 26335376064 | B4: =ROUND(C4*E4,0) -> 17134272000 | C4: ='C.Foundation-1'!I36 -> 9664 | D4: =E4*$K$3 -> 2725101 | E4: 1773000 | F4: m3 | G4: کندن زمین در صورت لزوم استفاده از چکش هیدرولیکی در زمین های سنگی و حمل و تخلیه مواد کنده شده تا فاصله ٢٠ متر از مرکز ثقل برداشت | I4: 30504 | K4: منطقه ای گچساران. | L4: 1.09
B5: =ROUND(C5*E5,0) -> 0 | F5: * | G5: قالب بندی فلزی | I5: * | K5: بالاسری | L5: 1.41
A6: =C6*D6 -> 10024235613 | B6: =ROUND(C6*E6,0) -> 6521949000 | C6: ='C.Foundation-1'!K36 -> 4501 | D6: =E6*$K$3 -> 2227113 | E6: 1449000 | F6: m2 | G6: تهیه مصالح و قالب بندی فلزی در پی ها | I6: 60101 | K6: تجهیزکارگاه | L6: 1
B7: =ROUND(C7*E7,0) -> 0 | F7: * | G7: تهیه مصالح و اجرای پی | I7: * | K7: بروزرسانی | L7: 1
A8: =C8*D8 -> 145592263520 | B8: =ROUND(C8*E8,0) -> 94724960000 | C8: ='C.Foundation-1'!N36 -> 376640 | D8: =E8*$K$3 -> 386555.5 | E8: 251500 | F8: Kg | G8: تهیه، بریدن، خم کردن و کار گذاشتن میلگرد آج دار به قطر ١٢ تا ١٨ میلی متر، برای بتن مسلح با سیم پیچی لازم. | I8: 70202
A9: =C9*D9 -> 63865785195 | B9: =ROUND(C9*E9,0) -> 41552235000 | C9: ='C.Foundation-1'!M36 -> 4149 | D9: =E9*$K$3 -> 15393055 | E9: 10015000 | F9: m3 | G9: تهیه و اجرای بتن با شن و ماسه طبیعی با عیار 350 کیلو سیمان | I9: 80106
A10: =C10*D10 -> 5.1271185e+08 | B10: =ROUND(C10*E10,0) -> 333579600 | C10: =C9 -> 4149 | D10: =E10*$K$3 -> 123574.8 | E10: 80400 | F10: m3 | G10: اضافه بهایه ردیفهای بتنه ریزی در بتن مسلح | I10: 80310
A11: =C11*D11 -> 2.5667055e+08 | B11: =ROUND(C11*E11,0) -> 166994500 | C11: 500 | D11: =E11*$K$3 -> 513341.09 | E11: =ROUND(31400*L31,0) -> 333989 | F11: kg | G11: نهیه و نصب انکربولت، میل مهار با مهره مربوطه | I11: 70606
B12: =ROUND(C12*E12,0) -> 0 | F12: * | G12: تهیه خاک مناسب از فاصله 15 کیلومتری | I12: *
A13: =C13*D13 -> 1.323293e+09 | B13: =ROUND(C13*E13,0) -> 860958384 | C13: ='C.Foundation-1'!J36 -> 4472 | D13: =E13*$K$3 -> 295906.31 | E13: =ROUND(18100*L31,0) -> 192522 | F13: m3 | G13: تهیه خاک مناسب از داخل یا خارج از کارگاه شامل کندن و حمل تا 500 متری | I13: 31002
A14: =C14*D14 -> 1670251752 | B14: =ROUND(C14*E14,0) -> 108669600 | C14: =C13 -> 4472 | D14: =E14*$K$3*10 -> 373491 | E14: 24300 | F14: m3-Km | G14: حمل مواد حاصل از عمليات خاكي، فاصله حمل بيش از500 متر تا10 كيلومتر ، براي هر كيلومتر مازاد بر500 متر اول | I14: 30703
A15: =C15*D15 -> 680472936 | B15: =ROUND(C15*E15,0) -> 88545600 | C15: =C13 -> 4472 | D15: =E15*$K$3*5 -> 152163 | E15: 19800 | F15: m3-Km | G15: حمل مواد حاصل از عمليات خاكي،فاصله حمل بيش از10 كيلومتر تا30 كيلومتر باشد، براي هر كيلومتر مازاد بر10 كيلومتر | I15: 30704
B16: =ROUND(C16*E16,0) -> 0 | F16: * | G16: خاکریزی و آبپاشی و کوبیدن با ماشین | I16: *
A17: =C17*D17 -> 961823860 | B17: =ROUND(C17*E17,0) -> 625780000 | C17: ='C.Foundation-1'!O36 -> 2680 | D17: =E17*$K$3 -> 358889.5 | E17: 233500 | F17: m3 | G17: پخش و کوبیدن خاکریزیها با 100% تراکم | I17: 30904
B18: =ROUND(C18*E18,0) -> 0 | F18: * | G18: آبپاشی و کوبیدن سطوح با دست | I18: *
A19: =C19*D19 -> 129452288 | B19: =ROUND(C19*E19,0) -> 84224000 | C19: ='C.Foundation-1'!J36-'C.Foundation-1'!O36 -> 1792 | D19: =E19*$K$3 -> 72239 | E19: 47000 | F19: m2 | G19: آبپاشی و کوبیدن سطوح با تراکم 95 درصد | I19: 20601
B20: =ROUND(C20*E20,0) -> 0 | F20: * | G20: تهیه مصالح و اجرای بتن با عیار 150 کیلو سیمان | I20: *
A21: =C21*D21 -> 1.0945921e+10 | B21: =ROUND(C21*E21,0) -> 7121614200 | C21: ='C.Foundation-1'!L36 -> 795.8 | D21: =E21*$K$3 -> 13754613 | E21: 8949000 | F21: m3 | G21: تهیه و اجرای بتن با شن و ماسه طبیعی با 150 کیلو سیمان | I21: 80102
A22: =C22*D22 -> 2.0732301e+08 | B22: =ROUND(C22*E22,0) -> 134888100 | C22: =C21 -> 795.8 | D22: =E22*$K$3 -> 260521.5 | E22: 169500 | F22: m3 | G22: اضافه بها برای بتن به ضخامت 15 سانتیمتر و کمتر | I22: 80304
B23: =ROUND(C23*E23,0) -> 0 | F23: * | G23: حمل خاک تا km10 با ماشین | I23: *
A24: =C24*D24 -> 1826988864 | B24: =ROUND(C24*E24,0) -> 1188672000 | C24: ='C.Foundation-1'!I36 -> 9664 | D24: =E24*$K$3 -> 189051 | E24: 123000 | F24: m3 | G24: بارگیری موادحاصل عملیات خاکی و حمل تا فاصله 100 متری | I24: 30701
A25: =C26*D25 -> 352772240 | B25: =ROUND(C25*E25,0) -> 45904000 | C25: =C24 -> 9664 | D25: =E25*$K$3*5 -> 36503.75 | E25: 4750 | F25: m3-Km | G25: حمل مواد حاصل از عمليات خاكي برای فاصله حمل بیش از 100متر تا 500متر، به ازایه ر 100 متر مازاد | I25: 30702
A26: =C26*D26 -> 3609417024 | B26: =ROUND(C26*E26,0) -> 234835200 | C26: =C25 -> 9664 | D26: =E26*$K$3*10 -> 373491 | E26: 24300 | F26: m3-Km | G26: حمل مواد حاصل از عمليات خاكي، فاصله حمل بيش از500 متر تا10 كيلومتر ، براي هر كيلومتر مازاد بر500 متر اول | I26: 30703
A27: =C27*D27 -> 9.0591607e+08 | B27: =ROUND(C27*E27,0) -> 589405380 | C27: ='C.Foundation-1'!P36 -> 1410 | D27: =E27*$K$3 -> 642493.67 | E27: =ROUND(39300*L31,0) -> 418018 | F27: مترمربع | G27: تهیه و اجرای بتن آسفالتی با سنگ شکسته از مصالح رودخانه ای برای قشر رویه ( توپکا ) ، هر گاه دانه بندی مصالح صفر تا 12/5 میلی متر باشد ، به ازای هر سانتی متر ضخامت آسفالت | I27: 270306
B28: =ROUND(C28*E28,0) -> 0 | G28: اجرای لایه نفوذ ناپذیر زیر فونداسیون مخازن | I28: *
A29: =C29*D29 -> 3224257120 | B29: =ROUND(C29*E29,0) -> 2097760000 | C29: ='C.Foundation-1'!Q36 -> 2240 | D29: =E29*$K$3 -> 1439400.5 | E29: 936500 | F29: m2 | G29: تهیه و اجرای ژئوممبرین (زمین غشا) از جنس پلی اتیلن سنگین (High Density Poly Ethylene) به ضخامت یک میلی متر | I29: 231206 | K29: چهارم 91 | L29: 481.9
A30: =C30*D30 -> 1548688960 | B30: =ROUND(C30*D30,0) -> 1548688960 | C30: ='C.Foundation-1'!Q36 -> 2240 | D30: =ROUND(65000*L31,0) -> 691379 | E30: - | F30: m2 | G30: تهیه مصالح و اجرای ژئو تکستایل بافته | I30: 231207* | K30: چهارم 1401 | L30: 5125.778
A31: =SUM(A3:A30) -> 2.7397362e+11 | B31: =SUM(B3:B30) -> 175163935524 | G31: مجموع | K31: ضریب بروزرسانی اعمال شده براساس فهرست ابنیه | L31: =L30/L29 -> 10.636601

Sheet C.Shelters-2
A1: جدول 2 - برآورد اجرا بر اساس فهرست بهای ابنیه 1402 - احداث سایبان تجهیزات(بر اساس ریز متره مندرج در جدول ب پیوست 2)
A2: ارزش کار | B2: مبلغ بدون اعمال ضرایب | C2: مقـدار | D2: واحد بــها با اعمال ضریب | E2: واحد بــهامطابق فهرست ابنیه 1402 | F2: واحـد | G2: شــــــــرح | I2: ردیف
F3: * | G3: خاکبرداری و پی کنی با ماشین | I3: * | K3: =ROUND(L4*L5*L6*L7,3) -> 1.537
A4: =C4*D4 -> 1.6926965e+10 | B4: =ROUND(C4*E4,0) -> 11012989500 | C4: ='C.Shelters-1'!F26 -> 6211.5 | D4: =E4*$K$3 -> 2725101 | E4: 1773000 | F4: m3 | G4: کندن زمین در صورت لزوم استفاده از چکش هیدرولیکی در زمین های سنگی و حمل و تخلیه مواد کنده شده تا فاصله ٢٠ متر از مرکز ثقل برداشت | I4: 30504 | K4: منطقه ای گچساران. | L4: 1.09
A5: =C6*D5 -> 2.2674304e+08 | B5: =ROUND(C5*E5,0) -> 29504625 | C5: =C4 -> 6211.5 | D5: =E5*$K$3*5 -> 36503.75 | E5: 4750 | F5: m3-Km | G5: حمل مواد حاصل از عمليات خاكي برای فاصله حمل بیش از 100متر تا 500متر، به ازایهر 100 متر مازاد | I5: 30702 | K5: بالاسری | L5: 1.41
A6: =C6*D6 -> 2.3199393e+09 | B6: =ROUND(C6*E6,0) -> 150939450 | C6: =C5 -> 6211.5 | D6: =E6*$K$3*10 -> 373491 | E6: 24300 | F6: m3-Km | G6: حمل مواد حاصل از عمليات خاكي، فاصله حمل بيش از500 متر تا10 كيلومتر ، براي هر كيلومتر مازاد بر500 متر اول | I6: 30703 | K6: تجهیزکارگاه | L6: 1
B7: =ROUND(C7*E7,0) -> 0 | F7: * | G7: قالب بندی فلزی | I7: * | K7: بروزرسانی | L7: 1
A8: =C8*D8 -> 3287218788 | B8: =ROUND(C8*E8,0) -> 2138724000 | C8: ='C.Shelters-1'!H26 -> 1476 | D8: =E8*$K$3 -> 2227113 | E8: 1449000 | F8: m2 | G8: تهیه مصالح و قالب بندی فلزی در پی ها | I8: 60101
A9: =C9*D9 -> 1.5108956e+08 | B9: =ROUND(C9*E9,0) -> 98301600 | C9: ='C.Shelters-1'!R26 -> 4428 | D9: =E9*$K$3 -> 34121.4 | E9: 22200 | F9: dm3 | G9: تعبیه انواع درز در مقطع عرضی قطعات بتنی بدون پر کرد آن بر حسب حجم درز. | I9: 60912
B10: =ROUND(C10*E10,0) -> 0 | F10: * | G10: تهیه مصالح و اجرای پی | I10: *
A11: =C11*D11 -> 8617682340 | B11: =ROUND(C11*E11,0) -> 5606820000 | C11: ='C.Shelters-1'!Q26 -> 17305 | D11: =E11*$K$3 -> 497988 | E11: 324000 | F11: Kg | G11: تهيه، بريدن، خم كردن و كار گذاشتن ميل گرد ساده به قطر تا 10 ميلي‌متر، براي بتن مسلح | I11: 70101
A12: =C12*D12 -> 1.5452556e+10 | B12: =ROUND(C12*E12,0) -> 10053712500 | C12: ='C.Shelters-1'!K26 -> 39975 | D12: =E12*$K$3 -> 386555.5 | E12: 251500 | F12: Kg | G12: تهیه، بریدن، خم کردن و کار گذاشتن میلگرد آج دار به قطر ١٢ تا ١٨ میلی متر، برای بتن مسلح با سیم پیچی لازم. | I12: 70202
A13: =C13*D13 -> 2.1244725e+10 | B13: =ROUND(C13*E13,0) -> 13822202250 | C13: ='C.Shelters-1'!J26+'C.Shelters-1'!P26 -> 1380.15 | D13: =E13*$K$3 -> 15393055 | E13: 10015000 | F13: m3 | G13: تهیه و اجرای بتن با شن و ماسه طبیعی با عیار 350 کیلو سیمان | I13: 80106
A14: =C14*D14 -> 1.7055176e+08 | B14: =ROUND(C14*E14,0) -> 110964060 | C14: =C13 -> 1380.15 | D14: =E14*$K$3 -> 123574.8 | E14: 80400 | F14: m3 | G14: اضافه بهایه ردیفهای بتنه ریزی در بتن مسلح | I14: 80310
A15: =C15*D15 -> 19011565 | B15: =ROUND(C15*E15,0) -> 12369268 | C15: ='C.Shelters-1'!P26 -> 519.15 | D15: =E15*$K$3 -> 36620.562 | E15: =ROUND(2240*L23,0) -> 23826 | F15: m4 | G15: اضافه بها براي بتن كف‌سازي‌ها با هر وسيله و به هر ضخامت | I15: 80306
A16: =C16*D16 -> 7.8926193e+08 | B16: =ROUND(C16*E16,0) -> 513508088 | C16: ='C.Shelters-1'!M26 -> 1537.5 | D16: =E16*$K$3 -> 513341.09 | E16: =ROUND(31400*L23,0) -> 333989 | F16: kg | G16: نهیه و نصب انکربولت، میل مهار با مهره مربوطه | I16: 70606
B17: =ROUND(C17*E17,0) -> 0 | F17: * | G17: تهیه خاک مناسب از فاصله 15 کیلومتری | I17: *
A18: =C18*D18 -> 1.0918943e+09 | B18: =ROUND(C18*E18,0) -> 710406180 | C18: ='C.Shelters-1'!G26 -> 3690 | D18: =E18*$K$3 -> 295906.31 | E18: =ROUND(18100*L23,0) -> 192522 | F18: m3 | G18: تهیه خاک مناسب از داخل یا خارج از کارگاه شامل کندن و حمل تا 500 متری | I18: 31002
A19: =C19*D19 -> 1378181790 | B19: =ROUND(C19*E19,0) -> 89667000 | C19: =C18 -> 3690 | D19: =E19*$K$3*10 -> 373491 | E19: 24300 | F19: m3-Km | G19: حمل مواد حاصل از عمليات خاكي، فاصله حمل بيش از500 متر تا10 كيلومتر ، براي هر كيلومتر مازاد بر500 متر اول | I19: 30703
A20: =C20*D20 -> 561481470 | B20: =ROUND(C20*E20,0) -> 73062000 | C20: =C18 -> 3690 | D20: =E20*$K$3*5 -> 152163 | E20: 19800 | F20: m3-Km | G20: حمل مواد حاصل از عمليات خاكي،فاصله حمل بيش از10 كيلومتر تا30 كيلومتر باشد، براي هر كيلومتر مازاد بر10 كيلومتر | I20: 30704
B21: =ROUND(C21*E21,0) -> 0 | F21: * | G21: خاکریزی و آبپاشی و کوبیدن با ماشین | I21: * | K21: چهارم 91 | L21: 481.9
A22: =C22*D22 -> 6.6215113e+08 | B22: =ROUND(C22*E22,0) -> 430807500 | C22: ='C.Shelters-1'!L26 -> 1845 | D22: =E22*$K$3 -> 358889.5 | E22: 233500 | F22: m3 | G22: پخش و کوبیدن خاکریزیها با 100% تراکم | I22: 30904 | K22: چهارم 1401 | L22: 5125.778
B23: =ROUND(C23*E23,0) -> 0 | F23: * | G23: آبپاشی و کوبیدن سطوح با دست | I23: * | K23: ضریب بروزرسانی اعمال شده براساس فهرست ابنیه | L23: =L22/L21 -> 10.636601
A24: =C24*D24 -> 133280955 | B24: =ROUND(C24*E24,0) -> 86715000 | C24: ='C.Shelters-1'!G26-'C.Shelters-1'!L26 -> 1845 | D24: =E24*$K$3 -> 72239 | E24: 47000 | F24: m2 | G24: آبپاشی و کوبیدن سطوح با تراکم 95 درصد | I24: 20601
B25: =ROUND(C25*E25,0) -> 0 | F25: * | G25: تهیه مصالح و اجرای بتن با عیار 150 کیلو سیمان | I25: *
A26: =C26*D26 -> 9.9934141e+09 | B26: =ROUND(C26*E26,0) -> 6501895950 | C26: ='C.Shelters-1'!I26+'C.Shelters-1'!O26 -> 726.55 | D26: =E26*$K$3 -> 13754613 | E26: 8949000 | F26: m3 | G26: تهیه و اجرای بتن با شن و ماسه طبیعی با 150 کیلو سیمان | I26: 80102
A27: =C27*D27 -> 1.892819e+08 | B27: =ROUND(C27*E27,0) -> 123150225 | C27: =C26 -> 726.55 | D27: =E27*$K$3 -> 260521.5 | E27: 169500 | F27: m3 | G27: اضافه بها برای بتن به ضخامت 15 سانتیمتر و کمتر | I27: 80304
B28: =ROUND(C28*E28,0) -> 0 | F28: * | G28: حمل خاک تا km10 با ماشین | I28: *
A29: =C29*D29 -> 1.1742903e+09 | B29: =ROUND(C29*E29,0) -> 764014500 | C29: ='C.Shelters-1'!F26 -> 6211.5 | D29: =E29*$K$3 -> 189051 | E29: 123000 | F29: m3 | G29: بارگیری موادحاصل عملیات خاکی و حمل تا فاصله 100 متری | I29: 30701
A30: =C31*D30 -> 2.2674304e+08 | B30: =ROUND(C30*E30,0) -> 29504625 | C30: =C29 -> 6211.5 | D30: =E30*$K$3*5 -> 36503.75 | E30: 4750 | F30: m3-Km | G30: حمل مواد حاصل از عمليات خاكي برای فاصله حمل بیش از 100متر تا 500متر، به ازایه ر 100 متر مازاد | I30: 30702
A31: =C31*D31 -> 2.3199393e+08 | B31: =ROUND(C31*E31,0) -> 150939450 | C31: =C29 -> 6211.5 | D31: =E31*$K$3 -> 37349.1 | E31: 24300 | F31: m3 | G31: حمل از 500 متر تا 10 کیلومتر | I31: 30703
B32: =ROUND(C32*E32,0) -> 0 | G32: عملیات بنایی | I32: *
A33: =C33*D33 -> 8.7022633e+09 | B33: =ROUND(C33*E33,0) -> 5661849900 | C33: ='C.Shelters-1'!N26 -> 1038.3 | D33: =E33*$K$3 -> 8381261 | E33: 5453000 | F33: m3 | G33: سنگ چيني دركف ساختمان (بلوكاژ) با سنگ لاشه. | I33: 40102
B34: =ROUND(C34*E34,0) -> 0 | G34: ساخت سازه فلزی | I34: *
A35: =C35*D35 -> 6.0924142e+10 | B35: =ROUND(C35*E35,0) -> 39638348460 | C35: ='C.Shelters-1 (2)'!F26 -> 118677.69 | D35: =E35*$K$3 -> 513358 | E35: 334000 | F35: Kg | G35: تهیه ، ساخت و نصب ستون از یک تیرآهن | I35: 90101
A36: =C36*D36 -> 5.5913668e+10 | B36: =ROUND(C36*E36,0) -> 36378443739 | C36: ='C.Shelters-1 (2)'!G26 -> 136259.57 | D36: =E36*$K$3 -> 410346.72 | E36: =ROUND(25100*L23,0) -> 266979 | F36: Kg | G36: تهیه و نصب تیرحمال با جوشکاریهای لازم در محل اتصال | I36: 90210
A37: =C37*D37 -> 7.4841167e+10 | B37: =ROUND(C37*E37,0) -> 48693016660 | C37: =SUM(C35:C36) -> 254937.26 | D37: =E37*$K$3 -> 293567 | E37: 191000 | F37: Kg | G37: اضافه بها در صورت مصرف تیراهن پهن | I37: 90605
A38: =C38*D38 -> 1.9660703e+10 | B38: =ROUND(C38*E38,0) -> 12791608885 | C38: ='C.Shelters-1 (2)'!J26 -> 52745.64 | D38: =E38*$K$3 -> 372745.55 | E38: =ROUND(22800*L23,0) -> 242515 | F38: Kg | G38: تهیه و نصب پرلین روی سطح شیبدار اسکلت فلزی از پروفیلZ | I38: 90203
A39: =C39*D39 -> 2.1990251e+10 | B39: =ROUND(C39*E39,0) -> 14307254850 | C39: ='C.Shelters-1 (2)'!I26 -> 43954.7 | D39: =E39*$K$3 -> 500293.5 | E39: 325500 | F39: Kg | G39: تهیه ونصب بادبندبا تمام قطعات اتصال | I39: 90402
A40: =C40*D40 -> 3.2767838e+10 | B40: =ROUND(C40*E40,0) -> 21319348141 | C40: ='C.Shelters-1 (2)'!H26 -> 87909.4 | D40: =E40*$K$3 -> 372745.55 | E40: =ROUND(22800*L23,0) -> 242515 | F40: Kg | G40: تهیه و نصب پرلین روی سطح شیبدار اسکلت فلزی با قطعات اتصال | I40: 90204
A41: =C41*D41 -> 1.8396145e+09 | B41: =ROUND(C41*E41,0) -> 1196886481 | C41: =C40 -> 87909.4 | D41: =E41*$K$3 -> 20926.255 | E41: =ROUND(1280*L23,0) -> 13615 | F41: Kg | G41: اضافه بها به ردیف 90204 برای پرلین افقی | I41: 90217
A42: =C42*D42 -> 4.2250581e+10 | B42: =ROUND(C42*E42,0) -> 27488992500 | C42: ='C.Shelters-1 (2)'!K26 -> 51915 | D42: =E42*$K$3 -> 813841.5 | E42: 529500 | F42: Kg | G42: تهیه مصالح و پوشش سقف با ورق گالوانیزه با وسایل و لوازم نصب | I42: 160302
B43: =ROUND(C43*E43,0) -> 0 | G43: زنگ زدایی و رنگ آمیزی اسکلت فلزی | I43: *
A44: =C44*D44 -> 2.6280207e+11 | B44: =ROUND(C44*E44,0) -> 170983783000 | C44: =SUM('C.Shelters-1 (2)'!F26:J26) -> 439547 | D44: =E44*$K$3 -> 597893 | E44: 389000 | F44: Kg | G44: زنگ زدايي اسكلت‌هاي فلزي، به روش ساچمه پاشي (شات بلاست). | I44: 250104
A45: =C45*D45 -> 1.1898068e+10 | B45: =ROUND(C45*E45,0) -> 7741098257 | C45: ='C.Shelters-1 (2)'!L26 -> 9690.8 | D45: =E45*$K$3 -> 1227769.4 | E45: =ROUND(75100*L23,0) -> 798809 | F45: m2 | G45: تهيه مصالح و اجراي رنگ اپوكسي برايساير كارهاي فلزي، شامل دوقشر ضد زنگ براي اپوكسي، يك قشرآستر و يك قشر رويه. | I45: 250303
A46: =SUM(A2:A45) -> 6.7843883e+11 | B46: =SUM(B2:B45) -> 438710828644 | G46: جمع :

Sheet C.ROAD-2
A1: جدول 3 - برآورد اجرا بر اساس فهرست بهای ابنیه 1402 - احداث جاده های دسترسی، جاده های داخل واحدها و پاترول(بر اساس ریز متره مندرج در جدول ج پیوست2)
A2: ارزش کار | B2: مبلغ بدون اعمال ضرایب | C2: مقـدار | D2: واحد بــها با اعمال ضریب | E2: واحد بــهامطابق فهرست ابنیه 1402 | F2: واحـد | G2: شــــــــرح | I2: ردیف
A3: =C3*D3 -> 3.6577852e+10 | B3: =ROUND(C3*E3,0) -> 23798212400 | C3: ='C.ROAD-1'!H20 -> 8260.4 | D3: =E3*$K$3 -> 4428097 | E3: 2881000 | F3: m3 | G3: تهیه مصالح زیر اساس از مصالح رودخانه ای با دانه بندی صفر تا 50 میلی متر | I3: 260101 | K3: =ROUND(L4*L5*L6*L7,3) -> 1.537
A4: =C4*D4 -> 4.5338254e+10 | B4: =ROUND(C4*E4,0) -> 29497888400 | C4: ='C.ROAD-1'!I20 -> 8260.4 | D4: =E4*$K$3 -> 5488627 | E4: 3571000 | F4: m3 | G4: تهیه مصالح اساس از مصالح رودخانه ای با دانه بندی صفر تا 38 میلی متر ، وقتی که حداقل 50 درصد مصالح مانده روی الک نمره 4 در یک وجه شکسته باشد | I4: 260302 | K4: منطقه ای گچساران. | L4: 1.09
A5: =C5*D5 -> 1.9041305e+09 | B5: =ROUND(C5*E5,0) -> 1238861750 | C5: =C3 -> 8260.4 | D5: =E5*$K$3 -> 230513.11 | E5: =ROUND(14100*L20,0) -> 149976 | F5: m3 | G5: پخش ، آب پاشی ، تسطیح و کوبیدن قشرهای زیر اساس به ضخامت تا 15 سانتی متر ، با حداقل 95 درصد تراکم به روش آشو اصلاحی | I5: 260602 | K5: بالاسری | L5: 1.41
A6: =C6*D6 -> 5.243545e+09 | B6: =ROUND(C6*E6,0) -> 3411545200 | C6: =C4 -> 8260.4 | D6: =E6*$K$3 -> 634781 | E6: 413000 | F6: m3 | G6: پخش ، آب پاشی ، تسطیح و کوبیدن قشرهای اساس به ضخامت بیش از 10 سانتی متر تا 15، با حداقل 100 درصد تراکم به روش آشو اصلاحی | I6: 260605 | K6: تجهیزکارگاه | L6: 1
A7: =C7*D7 -> 1.6732847e+10 | B7: =ROUND(C7*E7,0) -> 10886692800 | C7: ='C.ROAD-1'!J20 -> 55262.4 | D7: =E7*$K$3 -> 302789 | E7: 197000 | F7: kg | G7: تهیه مصالح و اجرای اندود نفوذی ( پریمکت ) با قیر محلول | I7: 270101 | K7: بروزرسانی | L7: 1
A8: =C8*D8 -> 6.806261e+09 | B8: =ROUND(C8*E8,0) -> 4428276534 | C8: ='C.ROAD-1'!K20 -> 18585.9 | D8: =E8*$K$3 -> 366205.62 | E8: =ROUND(22400*L20,0) -> 238260 | F8: kg | G8: تهیه مصالح و اجرای اندود سطحی ( تک کت ) با قیر محلول | I8: 270201
A9: =C9*D9 -> 3.3627755e+11 | B9: =ROUND(C9*E9,0) -> 218788258560 | C9: ='C.ROAD-1'!L20*4 -> 6608.32 | D9: =E9*$K$3 -> 50886996 | E9: 33108000 | F9: مترمربع | G9: تهیه و اجرای بتن آسفالتی با سنگ شکسته از مصالح رودخانه ای برای قشر آستر ( بیندر ) ، هرگاه دانه بندی مصالح صفر تا 19 میلی متر باشد ، به ازای هر سانتی متر ضخامت آسفالت | I9: 270304
A10: =C10*D10 -> 3.5505742e+09 | B10: =ROUND(C10*E10,0) -> 2310067792 | C10: ='C.ROAD-1'!M20*4 -> 5526.24 | D10: =E10*$K$3 -> 642493.67 | E10: =ROUND(39300*L20,0) -> 418018 | F10: مترمربع | G10: تهیه و اجرای بتن آسفالتی با سنگ شکسته از مصالح رودخانه ای برای قشر رویه ( توپکا ) ، هر گاه دانه بندی مصالح صفر تا 12/5 میلی متر باشد ، به ازای هر سانتی متر ضخامت آسفالت | I10: 270306
A11: =C11*D11 -> 3761346400 | B11: =ROUND(C11*E11,0) -> 2447200000 | C11: ='C.ROAD-1'!P20 -> 950 | D11: =E11*$K$3 -> 3959312 | E11: 2576000 | F11: m2 | G11: هيه مصالح رودخانه‌اي (تونان) براي تحكيم بستر راه و محوطه، يا اجراي قشر تقويتي در زير سازي راه و محوطه | I11: 260701
B12: =ROUND(C12*E12,0) -> 0 | F12: * | G12: تهیه خاک مناسب از فاصله 15 کیلومتری | I12: *
A13: =C13*D13 -> 3.7284196e+09 | B13: =ROUND(C13*E13,0) -> 2425777200 | C13: =SUM('C.ROAD-1'!N20:O20) -> 12600 | D13: =E13*$K$3 -> 295906.31 | E13: =ROUND(18100*L20,0) -> 192522 | F13: m3 | G13: تهیه خاک مناسب از داخل یا خارج از کارگاه شامل کندن و حمل تا 500 متری | I13: 31002
A14: =C14*D14 -> 4705986600 | B14: =ROUND(C14*E14,0) -> 306180000 | C14: =C13 -> 12600 | D14: =E14*$K$3*10 -> 373491 | E14: 24300 | F14: m3-Km | G14: حمل مواد حاصل از عمليات خاكي، فاصله حمل بيش از500 متر تا10 كيلومتر ، براي هر كيلومتر مازاد بر500 متر اول | I14: 30703
A15: =C15*D15 -> 1917253800 | B15: =ROUND(C15*E15,0) -> 249480000 | C15: =C13 -> 12600 | D15: =E15*$K$3*5 -> 152163 | E15: 19800 | F15: m3-Km | G15: حمل مواد حاصل از عمليات خاكي،فاصله حمل بيش از10 كيلومتر تا30 كيلومتر باشد، براي هر كيلومتر مازاد بر10 كيلومتر | I15: 30704
B16: =ROUND(C16*E16,0) -> 0 | F16: * | G16: خاکریزی و آبپاشی و کوبیدن با ماشین | I16: *
A17: =C17*D17 -> 340945025 | B17: =ROUND(C17*E17,0) -> 221825000 | C17: ='C.ROAD-1'!N20 -> 950 | D17: =E17*$K$3 -> 358889.5 | E17: 233500 | F17: m3 | G17: پخش و کوبیدن خاکریزیها و تونان با 100% تراکم | I17: 30904
A18: =C18*D18 -> 2992077900 | B18: =ROUND(C18*E18,0) -> 1946700000 | C18: =SUM('C.ROAD-1'!O20:P20) -> 12600 | D18: =E18*$K$3 -> 237466.5 | E18: 154500 | G18: پخش و کوبیدن خاکریزیها و تونان با 90% تراکم | I18: 30902 | K18: چهارم 91 | L18: 481.9
A19: =C19*D19 -> 0 | B19: =ROUND(C19*E19,0) -> 0 | F19: * | G19: حمل خاک تا km10 با ماشین | I19: * | K19: چهارم 1401 | L19: 5125.778
A20: =C20*D20 -> 2019618000 | B20: =ROUND(C20*E20,0) -> 1314000000 | C20: =SUM('C.ROAD-1'!G16:G17)*0.2 -> 7200 | D20: =E20*$K$3 -> 280502.5 | E20: 182500 | F20: m3 | G20: کانال کنی در زمینهای نرم تا عمق 2 متر | I20: 30501 | K20: ضریب بروزرسانی اعمال شده براساس فهرست ابنیه | L20: =L19/L18 -> 10.636601
A21: =C21*D21 -> 7.0448813e+09 | B21: =ROUND(C21*E21,0) -> 4583527200 | C21: =SUM('C.ROAD-1'!G16:G17)*0.7 -> 25200 | D21: =E21*$K$3 -> 279558.78 | E21: =ROUND(17100*L20,0) -> 181886 | F21: m3 | G21: کانال کنی در زمینهای سخت با وسیله مکانیکی تا عمق 2 متر | I21: 30502
A22: =C22*D22 -> 1.0434892e+11 | B22: =ROUND(C22*E22,0) -> 67891294800 | C22: =SUM('C.ROAD-1'!G16:G17)*0.1 -> 3600 | D22: =E22*$K$3 -> 28985811 | E22: =ROUND(1773000*L20,0) -> 18858693 | F22: m3 | G22: کانال کنی در زمینهایسنگی با چکش هیدرولیکی تا عمق 2 متر | I22: 30504
A23: =C23*D23 -> 1.181803e+09 | B23: =ROUND(C23*E23,0) -> 768902400 | C23: =SUM(C21:C22) -> 28800 | D23: =E23*$K$3 -> 41034.826 | E23: =ROUND(2510*L20,0) -> 26698 | F23: m3 | G23: اضافه بها برای فاصله حمل بیش از 20 متر و حداکثر 50متر | I23: 30404
A24: =C24*D24 -> 5444668800 | B24: =ROUND(C24*E24,0) -> 3542400000 | C24: =C23 -> 28800 | D24: =E24*$K$3 -> 189051 | E24: 123000 | F24: m3 | G24: بارگیری موادحاصل عملیات خاکی و حمل تا فاصله 100 متری | I24: 30701
A25: =C25*D25 -> 1051308000 | B25: =ROUND(C25*E25,0) -> 136800000 | C25: =C23 -> 28800 | D25: =E25*$K$3*5 -> 36503.75 | E25: 4750 | F25: m3-Km | G25: حمل مواد حاصل از عمليات خاكي برای فاصله حمل بیش از 100متر تا 500متر، به ازایهر 100 متر مازاد | I25: 30702
A26: =C26*D26 -> 10756540800 | B26: =ROUND(C26*E26,0) -> 699840000 | C26: =C23 -> 28800 | D26: =E26*$K$3*10 -> 373491 | E26: 24300 | F26: m3-Km | G26: حمل مواد حاصل از عمليات خاكي، فاصله حمل بيش از500 متر تا10 كيلومتر ، براي هر كيلومتر مازاد بر500 متر اول | I26: 30703
A27: =SUM(A3:A26) -> 6.0172479e+11 | B27: =SUM(B3:B26) -> 380893730036 | G27: جمع :

Sheet C.OTHERS-2
A1: جدول 4 - برآورد اجرا بر اساس فهرست بهای ابنیه 1402 - احداث ابنیه متفرقه (بر اساس ریز متره مندرج در جدول د پیوست 2)
A2: ارزش کار | B2: مبلغ بدون اعمال ضرایب | C2: مقـدار | D2: واحد بــها با اعمال ضریب | E2: واحد بــهامطابق فهرست ابنیه 1402 | F2: واحـد | G2: شــــــــرح | I2: ردیف
F3: * | G3: خاکبرداری و پی کنی با ماشین | I3: * | K3: =ROUND(L4*L5*L6*L7,3) -> 1.537 | L3: ضریب =
A4: =C4*D4 -> 9.3915439e+11 | B4: =ROUND(C4*E4,0) -> 611030833920 | C4: ='C.OTHERS-1'!F29 -> 344631.04 | D4: =E4*$K$3 -> 2725101 | E4: 1773000 | F4: m3 | G4: کندن زمین در صورت لزوم استفاده از چکش هیدرولیکی در زمین های سنگی و حمل و تخلیه مواد کنده شده تا فاصله ٢٠ متر از مرکز ثقل برداشت | I4: 30504 | K4: منطقه ای گچساران. | L4: 1.09
A5: =C5*D5 -> 0 | F5: * | G5: حمل خاک تا km10 با ماشین | I5: * | K5: بالاسری | L5: 1.41
A6: =C6*D6 -> 6.5152843e+10 | B6: =ROUND(C6*E6,0) -> 42389617920 | C6: ='C.OTHERS-1'!F29 -> 344631.04 | D6: =E6*$K$3 -> 189051 | E6: 123000 | F6: m3 | G6: بارگیری موادحاصل عملیات خاکی و حمل تا فاصله 100 متری | I6: 30701 | K6: تجهیزکارگاه | L6: 1
A7: =C8*D7 -> 1.2580325e+10 | B7: =ROUND(C7*E7,0) -> 1636997440 | C7: =C6 -> 344631.04 | D7: =E7*$K$3*5 -> 36503.75 | E7: 4750 | F7: m3-Km | G7: حمل مواد حاصل از عمليات خاكي برای فاصله حمل بیش از 100متر تا 500متر، به ازایهر 100 متر مازاد | I7: 30702 | K7: بروزرسانی | L7: 1
A8: =C8*D8 -> 1.2871659e+11 | B8: =ROUND(C8*E8,0) -> 8374534272 | C8: =C7 -> 344631.04 | D8: =E8*$K$3*10 -> 373491 | E8: 24300 | F8: m3-Km | G8: حمل مواد حاصل از عمليات خاكي، فاصله حمل بيش از500 متر تا10 كيلومتر ، براي هر كيلومتر مازاد بر500 متر اول | I8: 30703
F9: * | G9: قالب بندی فلزی | I9: *
A10: =C10*D10 -> 81556878060 | B10: =ROUND(C10*E10,0) -> 53062380000 | C10: ='C.OTHERS-1'!H29 -> 36620 | D10: =E10*$K$3 -> 2227113 | E10: 1449000 | F10: m2 | G10: تهیه مصالح و قالب بندی فلزی در پی ها | I10: 60101
F11: * | G11: تهیه مصالح و اجرای پی | I11: *
A12: =C12*D12 -> 2.7870088e+11 | B12: =ROUND(C12*E12,0) -> 181327836007 | C12: ='C.OTHERS-1'!K29 -> 720985.43 | D12: =E12*$K$3 -> 386555.5 | E12: 251500 | F12: Kg | G12: تهیه، بریدن، خم کردن و کار گذاشتن میلگرد آج دار به قطر ١٢ تا ١٨ میلی متر، برای بتن مسلح با سیم پیچی لازم. | I12: 70202
A13: =C13*D13 -> 2.4207888e+11 | B13: =ROUND(C13*E13,0) -> 157500897500 | C13: ='C.OTHERS-1'!J29 -> 15726.5 | D13: =E13*$K$3 -> 15393055 | E13: 10015000 | F13: m3 | G13: تهیه و اجرای بتن با شن و ماسه طبیعی با عیار 350 کیلو سیمان | I13: 80106
A14: =C14*D14 -> 1.9433991e+09 | B14: =ROUND(C14*E14,0) -> 1264410600 | C14: =C13 -> 15726.5 | D14: =E14*$K$3 -> 123574.8 | E14: 80400 | F14: m3 | G14: اضافه بهایه ردیفهای بتنه ریزی در بتن مسلح | I14: 80310
F15: * | G15: تهیه خاک مناسب از فاصله 15 کیلومتری | I15: *
A16: =C16*D16 -> 1.0877516e+10 | B16: =ROUND(C16*E16,0) -> 7077108720 | C16: ='C.OTHERS-1'!G29 -> 36760 | D16: =E16*$K$3 -> 295906.31 | E16: =ROUND(18100*L32,0) -> 192522 | F16: m3 | G16: تهیه خاک مناسب از داخل یا خارج از کارگاه شامل کندن و حمل تا 500 متری | I16: 31002
A17: =C17*D17 -> 13729529160 | B17: =ROUND(C17*E17,0) -> 893268000 | C17: =C16 -> 36760 | D17: =E17*$K$3*10 -> 373491 | E17: 24300 | F17: m3-Km | G17: حمل مواد حاصل از عمليات خاكي، فاصله حمل بيش از500 متر تا10 كيلومتر ، براي هر كيلومتر مازاد بر500 متر اول | I17: 30703
A18: =C18*D18 -> 5593511880 | B18: =ROUND(C18*E18,0) -> 727848000 | C18: =C16 -> 36760 | D18: =E18*$K$3*5 -> 152163 | E18: 19800 | F18: m3-Km | G18: حمل مواد حاصل از عمليات خاكي،فاصله حمل بيش از10 كيلومتر تا30 كيلومتر باشد، براي هر كيلومتر مازاد بر10 كيلومتر | I18: 30704
A19: =C19*D19 -> 0 | F19: * | G19: خاکریزی و آبپاشی و کوبیدن با ماشین | I19: *
A20: =C20*D20 -> 36079161435 | B20: =ROUND(C20*E20,0) -> 23473755000 | C20: ='C.OTHERS-1'!L29 -> 100530 | D20: =E20*$K$3 -> 358889.5 | E20: 233500 | F20: m3 | G20: پخش و کوبیدن خاکریزیها با 100% تراکم | I20: 30904
A21: =C21*D21 -> 0 | F21: * | G21: آبپاشی و کوبیدن سطوح با دست | I21: *
A22: =C22*D22 -> 2655505640 | B22: =ROUND(C22*E22,0) -> 1727720000 | C22: ='C.OTHERS-1'!G29 -> 36760 | D22: =E22*$K$3 -> 72239 | E22: 47000 | F22: m2 | G22: آبپاشی و کوبیدن سطوح با تراکم 95 درصد | I22: 20601
A23: =C23*D23 -> 0 | F23: * | G23: تهیه مصالح و اجرای بتن با عیار 150 کیلو سیمان | I23: *
A24: =C24*D24 -> 3.142764e+10 | B24: =ROUND(C24*E24,0) -> 20447391120 | C24: ='C.OTHERS-1'!I29 -> 2284.88 | D24: =E24*$K$3 -> 13754613 | E24: 8949000 | F24: m3 | G24: تهیه و اجرای بتن با شن و ماسه طبیعی با 150 کیلو سیمان | I24: 80102
A25: =C25*D25 -> 5.9526036e+08 | B25: =ROUND(C25*E25,0) -> 387287160 | C25: =C24 -> 2284.88 | D25: =E25*$K$3 -> 260521.5 | E25: 169500 | F25: m3 | G25: اضافه بها برای بتن به ضخامت 15 سانتیمتر و کمتر | I25: 80304
A26: =C26*D26 -> 0 | H26: فنس | I26: *
A27: =C27*D27 -> 90700076070 | B27: =ROUND(C27*E27,0) -> 59011110000 | C27: ='C.OTHERS-1'!L29 -> 100530 | D27: =E27*$K$3 -> 902219 | E27: 587000 | F27: Kg | G27: تهیه و ساخت و کارگذاری پایه با دستک فلزی از لوله گالوانیزه برای نصب تور یا مشابه | I27: 160208
A28: =C28*D28 -> 34060304250 | B28: =ROUND(C28*E28,0) -> 22160250000 | C28: ='C.OTHERS-1'!M29 -> 60300 | D28: =E28*$K$3 -> 564847.5 | E28: 367500 | F28: Kg | G28: تهیه و نصب تور سیمی گالوانیزه حصاری با لوازم اتصال | I28: 160401
A29: =C29*D29 -> 0 | G29: اجرای لایه نفوذ ناپذیر | I29: *
A30: =C30*D30 -> 23318288100 | B30: =ROUND(C30*E30,0) -> 10114200000 | C30: ='C.OTHERS-1'!N29 -> 10800 | D30: =E30*$K$3*1.5 -> 2159100.8 | E30: 936500 | F30: m2 | G30: تهیه و اجرای ژئوممبرین (زمین غشا) از جنس پلی اتیلن سنگین (High Density Poly Ethylene) به ضخامت یک میلی متر | I30: 231206 | K30: چهارم 91 | L30: 481.9
A31: =C31*D31 -> 7591341420 | B31: =ROUND(C31*D31,0) -> 7591341420 | C31: ='C.OTHERS-1'!O29 -> 10980 | D31: =ROUND(65000*L32,0) -> 691379 | E31: - | F31: m2 | G31: تهیه مصالح و اجرای ژئو تکستایل بافته | I31: 231207* | K31: چهارم 1401 | L31: 5125.778
A32: =C32*D32 -> 29782482600 | B32: =ROUND(C32*D32,0) -> 29782482600 | C32: ='C.OTHERS-1'!P29 -> 200 | D32: =ROUND(14000000*L32,0) -> 148912413 | E32: خارج فهرست بها | F32: m2 | G32: تهیه و اجرای آجر نسوز برای گودال های سوزا | I32: * | K32: ضریب بروزرسانی اعمال شده براساس فهرست ابنیه | L32: =L31/L30 -> 10.636601
A33: =SUM(A4:A32) -> 2.0362948e+12 | B33: =SUM(B4:B32) -> 1239981269679 | G33: جمع :

Sheet C.SITE-2
A1: جدول 5 - برآورد اجرا بر اساس فهرست بهای ابنیه 1402 -محوطه سازی واحدها (بر اساس ریز متره مندرج در جدول ه پیوست2)
A2: ارزش کار | B2: مبلغ بدون اعمال ضرایب | C2: مقـدار | D2: واحد بــها با اعمال ضریب | E2: واحد بــهامطابق فهرست ابنیه 1402 | F2: واحـد | G2: شــــــــرح | I2: ردیف
F3: * | H3: خاکبرداری و پی کنی با ماشین و حمل تا فاصله 10 کیلومتری | I3: * | K3: =ROUND(L4*L5*L6*L7,3) -> 1.537 | L3: ضریب =
A4: =ROUND(C4*D4,0) -> 67590789722 | B4: =ROUND(C4*E4,0) -> 43975790320 | C4: ='C.SITE-1'!I19 -> 534160 | D4: =E4*$K$3 -> 126536.6 | E4: =ROUND(7740*M11,0) -> 82327 | F4: m3 | G4: خاکبرداری در زمین های سخت با هر وسیله مکانیکی و حمل تا فاصله 20 متری | I4: 30104 | K4: منطقه ای گچساران. | L4: 1.09
A5: =ROUND(C5*D5,0) -> 127442445320 | B5: =ROUND(C5*E5,0) -> 82916360000 | C5: ='C.SITE-1'!J19 -> 152560 | D5: =E5*$K$3 -> 835359.5 | E5: 543500 | F5: m3 | G5: خاکبرداری در زمین های سنگی با هر وسیله مکانیکی و حمل تا فاصله 20 متری | I5: 30105 | K5: بالاسری | L5: 1.41
A6: =ROUND(C6*D6,0) -> 48948685300 | B6: =ROUND(C6*E6,0) -> 31846900000 | C6: ='C.SITE-1'!K19 -> 76280 | D6: =E6*$K$3 -> 641697.5 | E6: 417500 | F6: m3 | G6: خاکبرداری در زمین های سنگی با استفاده از چکش هیدرولیکی و حمل تا فاصله 20 متری | I6: 30202 | K6: تجهیزکارگاه | L6: 1
A7: =ROUND(C7*D7,0) -> 44915597300 | B7: =ROUND(C7*E7,0) -> 29222900000 | C7: =SUM(C4:C6) -> 763000 | D7: =E7*$K$3 -> 58867.1 | E7: 38300 | F7: m3 | G7: اضافه بها برای فاصله حمل بیش از 20 متر و حداکثر 50متر | I7: 30404 | K7: بروزرسانی | L7: 1
A8: =ROUND(C8*D8,0) -> 144245913000 | B8: =ROUND(C8*E8,0) -> 93849000000 | C8: =C7 -> 763000 | D8: =E8*$K$3 -> 189051 | E8: 123000 | F8: m3 | G8: بارگیری موادحاصل عملیات خاکی و حمل تا فاصله 100 متری | I8: 30701
A9: =ROUND(C9*D9,0) -> 27852361250 | B9: =ROUND(C9*E9,0) -> 3624250000 | C9: =C7 -> 763000 | D9: =E9*$K$3*5 -> 36503.75 | E9: 4750 | F9: m3-Km | G9: حمل مواد حاصل از عمليات خاكي برای فاصله حمل بیش از 100متر تا 500متر، به ازایهر 100 متر مازاد | I9: 30702 | L9: چهارم 91 | M9: 481.9
A10: =ROUND(C10*D10,0) -> 284973633000 | B10: =ROUND(C10*E10,0) -> 18540900000 | C10: =C7 -> 763000 | D10: =E10*$K$3*10 -> 373491 | E10: 24300 | F10: m3-Km | G10: حمل مواد حاصل از عمليات خاكي، فاصله حمل بيش از500 متر تا10 كيلومتر ، براي هر كيلومتر مازاد بر500 متر اول | I10: 30703 | L10: چهارم 1401 | M10: 5125.778
A11: =ROUND(C11*D11,0) -> 0 | F11: * | G11: تهیه خاک مناسب از فاصله 15 کیلومتری | I11: * | L11: ضریب بروزرسانی اعمال شده براساس فهرست ابنیه | M11: =M10/M9 -> 10.636601
A12: =ROUND(C12*D12,0) -> 34621038738 | B12: =ROUND(C12*E12,0) -> 22525074000 | C12: ='C.SITE-1'!L19 -> 117000 | D12: =E12*$K$3 -> 295906.31 | E12: =ROUND(18100*M11,0) -> 192522 | F12: m3 | G12: تهیه خاک مناسب از داخل یا خارج از کارگاه شامل کندن و حمل تا 500 متری | I12: 31002
A13: =ROUND(C13*D13,0) -> 43698447000 | B13: =ROUND(C13*E13,0) -> 2843100000 | C13: =C12 -> 117000 | D13: =E13*$K$3*10 -> 373491 | E13: 24300 | F13: m3-Km | G13: حمل مواد حاصل از عمليات خاكي، فاصله حمل بيش از500 متر تا10 كيلومتر ، براي هر كيلومتر مازاد بر500 متر اول | I13: 30703
A14: =ROUND(C14*D14,0) -> 17803071000 | B14: =ROUND(C14*E14,0) -> 2316600000 | C14: =C12 -> 117000 | D14: =E14*$K$3*5 -> 152163 | E14: 19800 | F14: m3-Km | G14: حمل مواد حاصل از عمليات خاكي،فاصله حمل بيش از10 كيلومتر تا30 كيلومتر باشد، براي هر كيلومتر مازاد بر10 كيلومتر | I14: 30704
A15: =ROUND(C15*D15,0) -> 0 | F15: * | H15: خاکریزی و آبپاشی و کوبیدن با ماشین | I15: *
A16: =ROUND(C16*D16,0) -> 27783580500 | B16: =ROUND(C16*E16,0) -> 18076500000 | C16: =C12 -> 117000 | D16: =E16*$K$3 -> 237466.5 | E16: 154500 | F16: m3 | H16: پخش و کوبیدن خاکریزیها با 90% تراکم | I16: 30902
A17: =ROUND(C17*D17,0) -> 0 | F17: * | H17: حمل خاک تا km10 با ماشین | I17: *
A18: =ROUND(C18*D18,0) -> 19950395256 | B18: =ROUND(C18*E18,0) -> 12980088000 | C18: ='C.SITE-1'!I19 -> 534160 | D18: =E18*$K$3 -> 37349.1 | E18: 24300 | F18: m3 | H18: حمل از 500 متر تا 10 کیلومتر | I18: 30703
A19: =ROUND(C19*D19,0) -> 0 | H19: محوطه سازی | I19: *
A20: =ROUND(C20*D20,0) -> 10573654707 | B20: =ROUND(C20*E20,0) -> 6879411000 | C20: ='C.SITE-1'!M19 -> 346.5 | D20: =E20*$K$3 -> 30515598 | E20: 19854000 | F20: m3 | H20: تهيه و نصب جدول هاي بتني پيش ساخته با سطح مقطع بيش از 0/05 تا 0/1 مترمربع با بتن به عيار250 كيلو گرم سيمان در مترمكعب | I20: 120102
A21: =ROUND(C21*D21,0) -> 140970258600 | B21: =ROUND(C21*E21,0) -> 91717800000 | C21: ='C.SITE-1'!N19 -> 21300 | D21: =E21*$K$3 -> 6618322 | E21: 4306000 | F21: m3 | H21: تهيه، حمل و ريختن شن طبيعي در داخل كانال‌ها، اطراف پي‌ها و لوله‌ها، كف ساختمان‌ها، معابر محوطه‌ها يا هر محل ديگري كه لازم باشد، به‌انضمام پخش و تسطيح آن‌ها در ضخامت‌هاي لازم. | I21: 40504
A22: =SUM(A3:A21) -> 1041369870693 | B22: =SUM(B3:B21) -> 461314673320 | G22: جمع :
E28: 120102 | F28: تهيه و نصب جدول هاي بتني پيش ساخته با سطح مقطع بيش از 0/05 تا 0/1 مترمربع با بتن به عيار250 كيلو گرم سيمان در مترمكعب و ملات ماسه سيمان 1:5. | G28: مترمكعب | H28: 1517000

Sheet C.SITE-3
A1: جدول 6 - برآورد اجرا فضای سبز - خارج از فهرست بها
A2: توضیحات | B2: هزینه نهایی | C2: مقدار | D2: هزینه واحد | E2: واحد | F2: شرح | H2: ردیف
B3: - | C3: - | D3: =ROUND(9000*M5,0) -> 95733 | E3: متر مربع | F3: اختصاص حداقل 10 درصد از محدوده تعیین شده کارخانه و تاسیسات به فضای سبز | H3: * | L3: چهارم 91 | M3: 481.9
A4: %60 سطح فضای سبز برای کاشت چمن و مابقی برای کاشت گیاهان در نظر گرفته شده است. | B4: =C4*D4 -> 430798500 | C4: 4500 | D4: =ROUND(9000*M5,0) -> 95733 | E4: متر مکعب | F4: تهیه خاک مناسب مخلوط رسی-شنی با PH مناسب | H4: 1 | J4: 45000 | K4: =2*D4 -> 191466 | L4: چهارم 1401 | M4: 5125.778
B5: =C5*D5 -> 861597000 | C5: 9000 | D5: =ROUND(9000*M5,0) -> 95733 | E5: مترمربع | F5: خاکریزی به میزان تقریبی 40سانتی متر | H5: 2 | K5: =2*D5 -> 191466 | L5: ضریب بروزرسانی اعمال شده براساس فهرست ابنیه | M5: =ROUND(M4/M3,3) -> 10.637
B6: =C6*D6 -> 86159700 | C6: 900 | D6: =ROUND(9000*M5,0) -> 95733 | E6: متر مکعب | F6: خاک رس سرندی به میزان 10 سانتی متری | H6: 3 | K6: =2*D6 -> 191466
B7: =C7*D7 -> 861597000 | C7: 9000 | D7: =ROUND(9000*M5,0) -> 95733 | E7: متر مکعب | F7: تسطیح و رگلاژ | H7: 4 | K7: =2*D7 -> 191466
B8: =C8*D8 -> 861597000 | C8: 9000 | D8: =ROUND(9000*M5,0) -> 95733 | E8: مترمربع | F8: کودپاشی | H8: 5 | K8: =2*D8 -> 191466
B9: =C9*D9 -> 670131000 | C9: 7000 | D9: =ROUND(9000*M5,0) -> 95733 | E9: مترمربع | F9: بذر پاشی چمن | H9: 6 | K9: =2*D9 -> 191466
B10: =C10*D10 -> 670131000 | C10: 7000 | D10: =ROUND(9000*M5,0) -> 95733 | E10: مترمربع | F10: اجرت کاشت چمن | H10: 7 | K10: =2*D10 -> 191466
B11: =C11*D11 -> 670131000 | C11: 7000 | D11: =ROUND(9000*M5,0) -> 95733 | E11: مترمربع | F11: نگهداری چمن به مدت یک ماه | H11: 8 | K11: =2*D11 -> 191466
A12: در هر متربع دو عدد | B12: =C12*D12 -> 382932000 | C12: 4000 | D12: =ROUND(9000*M5,0) -> 95733 | E12: عدد | F12: تهیه گیاهان پوششی | H12: 9 | K12: =2*D12 -> 191466
B13: =C13*D13 -> 191466000 | C13: 2000 | D13: =ROUND(9000*M5,0) -> 95733 | E13: متر مربع | F13: کندوکوهی و کود دهی گیاهان پوششی | H13: 10 | K13: =2*D13 -> 191466
B14: =C14*D14 -> 191466000 | C14: 2000 | D14: =ROUND(9000*M5,0) -> 95733 | E14: مترمربع | F14: نگهداری گیاهان پوششی به مدت یک ماه | H14: 11 | K14: =2*D14 -> 191466
B15: =ROUND(200000000*M5,0) -> 2127400000 | C15: مطابق مشخصات فنی فضای سبز پروژه | D15: یک قلم | E15: یک قلم | F15: احداث سیستم آبیاری پروژه به صورت مکانیزه و تحت فشار ( بارانی- قطره ای ) | H15: *
B16: =ROUND(20000000*M5,0) -> 212740000 | D16: یک قلم | E16: یک قلم | F16: تهیه لوازم کشاورزی | H16: *
B17: =SUM(B3:B16) -> 8218146200 | F17: مجموع

Sheet C.UG CIVIL-2
A1: جدول7 - برآورد اجرا بر اساس فهرست بهای ابنیه 1402 - دفن لوله ها (داخل و خارج واحد) و کابل های زیر زمینی (بر اساس ریز متره مندرج در جدول و پیوست2)
A2: ارزش کار | B2: مبلغ بدون اعمال ضرایب | C2: مقـدار | D2: واحد بــها با اعمال ضریب | E2: واحد بــهامطابق فهرست ابنیه 1402 | F2: واحـد | G2: شــــــــرح | I2: ردیف
F3: * | G3: کانال کنس با ماشین | I3: * | K3: =ROUND(L6*L7*L8*L9,3) -> 1.537 | L3: ضریب =
A4: =C4*D4 -> 61042262400 | B4: =ROUND(C4*E4,0) -> 39715200000 | C4: ='C.UG CIVIL-1'!F18 -> 22400 | D4: =E4*$K$3 -> 2725101 | E4: 1773000 | F4: m3 | G4: کندن زمین در صورت لزوم استفاده از چکش هیدرولیکی در زمین های سنگی و حمل و تخلیه مواد کنده شده تا فاصله ٢٠ متر از مرکز ثقل برداشت | I4: 30504
F5: * | G5: حمل خاک تا km10 با ماشین | I5: *
A6: =C6*D6 -> 4234742400 | B6: =ROUND(C6*E6,0) -> 2755200000 | C6: =SUM(C4:C5) -> 22400 | D6: =E6*$K$3 -> 189051 | E6: 123000 | F6: m3 | G6: بارگیری موادحاصل عملیات خاکی و حمل تا فاصله 100 متری | I6: 30701 | K6: منطقه ای گچساران. | L6: 1.09
A7: =C7*D7 -> 817684000 | B7: =ROUND(C7*E7,0) -> 106400000 | C7: =C6 -> 22400 | D7: =E7*$K$3*5 -> 36503.75 | E7: 4750 | F7: m3-Km | G7: حمل مواد حاصل از عمليات خاكي برای فاصله حمل بیش از 100متر تا 500متر، به ازایهر 100 متر مازاد | I7: 30702 | K7: بالاسری | L7: 1.41
A8: =C8*D8 -> 8366198400 | B8: =ROUND(C8*E8,0) -> 544320000 | C8: =C6 -> 22400 | D8: =E8*$K$3*10 -> 373491 | E8: 24300 | F8: m3-Km | G8: حمل مواد حاصل از عمليات خاكي، فاصله حمل بيش از500 متر تا10 كيلومتر ، براي هر كيلومتر مازاد بر500 متر اول | I8: 30703 | K8: تجهیزکارگاه | L8: 1
F9: * | G9: قالب بندی فلزی | I9: * | K9: بروزرسانی | L9: 1
A10: =C10*D10 -> 3117958200 | B10: =ROUND(C10*E10,0) -> 2028600000 | C10: ='C.UG CIVIL-1'!H18 -> 1400 | D10: =E10*$K$3 -> 2227113 | E10: 1449000 | F10: m2 | G10: تهیه مصالح و قالب بندی فلزی در پی ها | I10: 60101
A11: =C11*D11 -> 15354630 | B11: =ROUND(C11*E11,0) -> 9990000 | C11: ='C.UG CIVIL-1'!N18 -> 450 | D11: =E11*$K$3 -> 34121.4 | E11: 22200 | F11: dm3 | G11: تعبیه انواع درز در مقطع عرضی قطعات بتنی بدون پر کرد آن بر حسب حجم درز. | I11: 60912
F12: * | G12: تهیه مصالح و اجرای پی | I12: *
A13: =C13*D13 -> 14147931300 | B13: =ROUND(C13*E13,0) -> 9204900000 | C13: ='C.UG CIVIL-1'!K18 -> 36600 | D13: =E13*$K$3 -> 386555.5 | E13: 251500 | F13: Kg | G13: تهیه، بریدن، خم کردن و کار گذاشتن میلگرد آج دار به قطر ١٢ تا ١٨ میلی متر، برای بتن مسلح با سیم پیچی لازم. | I13: 70202
A14: =C14*D14 -> 15177552230 | B14: =ROUND(C14*E14,0) -> 9874790000 | C14: ='C.UG CIVIL-1'!J18 -> 986 | D14: =E14*$K$3 -> 15393055 | E14: 10015000 | F14: m3 | G14: تهیه و اجرای بتن با شن و ماسه طبیعی با عیار 350 کیلو سیمان | I14: 80106
A15: =C15*D15 -> 65917012 | B15: =ROUND(C15*E15,0) -> 42886800 | C15: ='C.UG CIVIL-1'!J16/0.15 -> 1800 | D15: =E15*$K$3 -> 36620.562 | E15: =ROUND(2240*M18,0) -> 23826 | F15: m4 | G15: اضافه بها براي بتن كف‌سازي‌ها با هر وسيله و به هر ضخامت | I15: 80306
F16: * | G16: تهیه خاک مناسب از فاصله 15 کیلومتری | I16: * | L16: چهارم 91 | M16: 481.9
A17: =C17*D17 -> 3.1661976e+09 | B17: =ROUND(C17*E17,0) -> 2059985400 | C17: ='C.UG CIVIL-1'!G18 -> 10700 | D17: =E17*$K$3 -> 295906.31 | E17: =ROUND(18100*M18,0) -> 192522 | F17: m3 | G17: تهیه خاک مناسب از داخل یا خارج از کارگاه شامل کندن و حمل تا 500 متری | I17: 31002 | L17: چهارم 1401 | M17: 5125.778
A18: =C18*D18 -> 3996353700 | B18: =ROUND(C18*E18,0) -> 260010000 | C18: =C17 -> 10700 | D18: =E18*$K$3*10 -> 373491 | E18: 24300 | F18: m3-Km | G18: حمل مواد حاصل از عمليات خاكي، فاصله حمل بيش از500 متر تا10 كيلومتر ، براي هر كيلومتر مازاد بر500 متر اول | I18: 30703 | L18: ضریب بروزرسانی اعمال شده براساس فهرست ابنیه | M18: =M17/M16 -> 10.636601
A19: =C19*D19 -> 1628144100 | B19: =ROUND(C19*E19,0) -> 211860000 | C19: =C18 -> 10700 | D19: =E19*$K$3*5 -> 152163 | E19: 19800 | F19: m3-Km | G19: حمل مواد حاصل از عمليات خاكي،فاصله حمل بيش از10 كيلومتر تا30 كيلومتر باشد، براي هر كيلومتر مازاد بر10 كيلومتر | I19: 30704
F20: * | G20: تهیه مصالح و اجرای بتن با عیار 150 کیلو سیمان | I20: *
A21: =C21*D21 -> 2145719628 | B21: =ROUND(C21*E21,0) -> 1396044000 | C21: ='C.UG CIVIL-1'!I18 -> 156 | D21: =E21*$K$3 -> 13754613 | E21: 8949000 | F21: m3 | G21: تهیه و اجرای بتن با شن و ماسه طبیعی با 150 کیلو سیمان | I21: 80102
G22: ماسه/خاک نرم ریزی در کانال | I22: *
A23: =C23*D23 -> 52226337800 | B23: =ROUND(C23*E23,0) -> 33979400000 | C23: ='C.UG CIVIL-1'!L18 -> 9100 | D23: =E23*$K$3 -> 5739158 | E23: 3734000 | F23: m3 | G23: تهیه، حمل و ریختن ماسه کفی خاکدار در داخل کانال | I23: 40503
G24: عملیات بنایی | I24: *
A25: =C25*D25 -> 4525880940 | B25: =ROUND(C25*E25,0) -> 2944620000 | C25: ='C.UG CIVIL-1'!M18 -> 540 | D25: =E25*$K$3 -> 8381261 | E25: 5453000 | F25: m3 | G25: سنگ چيني دركف ساختمان (بلوكاژ) با سنگ لاشه. | I25: 40102
F26: * | G26: کانال کنی با ماشین | I26: * | K26: =ROUND(L28*L27*L29*L30,3) -> 1.642 | L26: ضریب =
A27: =C27*D27 -> 11075290000 | B27: =ROUND(C27*E27,0) -> 6745000000 | C27: ='C.UG CIVIL-1'!O18 -> 1000 | D27: =E27*K26 -> 11075290 | E27: 6745000 | F27: مترمكعب | G27: بنايي با سنـگ لاشه و ملات ماسه سيمان 1:3 در پي. | I27: 60203 | K27: منطقه ای گچساران. | L27: 1.12
A28: =C28*D28 -> 2755276000 | B28: =ROUND(C28*E28,0) -> 1678000000 | C28: ='C.UG CIVIL-1'!O18 -> 1000 | D28: =E28*K26 -> 2755276 | E28: 1678000 | F28: مترمكعب | G28: اضافه بها به رديف‌هاي بنايي با سنـگ لاشه در پي، براي بنايي در ديوار. | I28: 60301 | K28: بالاسری | L28: 1.41
A29: =C29*D29 -> 245479000 | B29: =ROUND(C29*E29,0) -> 149500000 | C29: ='C.UG CIVIL-1'!O18 -> 1000 | D29: =E29*K26 -> 245479 | E29: 149500 | F29: مترمربع | G29: اضافه بها به رديف‌هاي خشکه‌چيني و بنايي با سنـگ لاشه، براي سطوح شيب‌دار. | I29: 60403 | K29: تجهیزکارگاه | L29: 1.04
A30: =SUM(A3:A29) -> 1.8875028e+11 | B30: =SUM(B3:B29) -> 113706706200 | G30: مجموع | K30: بروزرسانی | L30: 1

Sheet C.STEEL STRUCTURE (2)
A1: جدول 8 - برآورد اجرا بر اساس فهرست بهای ابنیه 1402 - سازه های فلزی متفرقه (بر اساس ریز متره مندرج در جدول ط پیوست 2)
A2: ارزش کار | B2: مبلغ بدون اعمال ضرایب | C2: مقـدار | D2: واحد بــها با اعمال ضریب | E2: واحد بــهامطابق فهرست ابنیه 1402 | F2: واحـد | G2: شــــــــرح | I2: ردیف
F3: * | G3: خاکبرداری و پی کنی با ماشین | I3: * | K3: =ROUND(M5*M6*M7*M8,3) -> 1.537 | L3: ضریب =
A4: =C4*D4 -> 12017695410 | B4: =ROUND(C4*E4,0) -> 7818930000 | C4: ='C.STEEL STRUCTURE-1'!F17 -> 4410 | D4: =E4*$K$3 -> 2725101 | E4: 1773000 | F4: m3 | G4: پکندن زمین در صورت لزوم استفاده از چکش هیدرولیکی در زمین های سنگی و حمل و تخلیه مواد کنده شده تا فاصله ٢٠ متر از مرکز ثقل برداشت | I4: 30504
A5: =C5*D5 -> 0 | F5: * | G5: حمل خاک تا km10 با ماشین | I5: * | L5: منطقه ای گچساران. | M5: 1.09
A6: =C6*D6 -> 833714910 | B6: =ROUND(C6*E6,0) -> 542430000 | C6: =C4 -> 4410 | D6: =E6*$K$3 -> 189051 | E6: 123000 | F6: m3 | G6: بارگیری موادحاصل عملیات خاکی و حمل تا فاصله 100 متری | I6: 30701 | L6: بالاسری | M6: 1.41
A7: =C8*D7 -> 1.6098154e+08 | B7: =ROUND(C7*E7,0) -> 20947500 | C7: =C6 -> 4410 | D7: =E7*$K$3*5 -> 36503.75 | E7: 4750 | F7: m3-Km | G7: حمل مواد حاصل از عمليات خاكي برای فاصله حمل بیش از 100متر تا 500متر، به ازایهر 100 متر مازاد | I7: 30702 | L7: تجهیزکارگاه | M7: 1
A8: =C8*D8 -> 1647095310 | B8: =ROUND(C8*E8,0) -> 107163000 | C8: =C7 -> 4410 | D8: =E8*$K$3*10 -> 373491 | E8: 24300 | F8: m3-Km | G8: حمل مواد حاصل از عمليات خاكي، فاصله حمل بيش از500 متر تا10 كيلومتر ، براي هر كيلومتر مازاد بر500 متر اول | I8: 30703 | L8: بروزرسانی | M8: 1
F9: * | G9: قالب بندی فلزی | I9: *
A10: =C10*D10 -> 29981395206 | B10: =ROUND(C10*E10,0) -> 19506438000 | C10: ='C.STEEL STRUCTURE-1'!H17 -> 13462 | D10: =E10*$K$3 -> 2227113 | E10: 1449000 | F10: m2 | G10: تهیه مصالح و قالب بندی فلزی در پی ها | I10: 60101
F11: * | G11: تهیه مصالح و اجرای پی | I11: *
A12: =C12*D12 -> 152426564760 | B12: =ROUND(C12*E12,0) -> 99171480000 | C12: ='C.STEEL STRUCTURE-1'!K17 -> 394320 | D12: =E12*$K$3 -> 386555.5 | E12: 251500 | F12: Kg | G12: تهیه، بریدن، خم کردن و کار گذاشتن میلگرد آج دار به قطر ١٢ تا ١٨ میلی متر، برای بتن مسلح با سیم پیچی لازم. | I12: 70202
A13: =C13*D13 -> 46764101090 | B13: =ROUND(C13*E13,0) -> 30425570000 | C13: ='C.STEEL STRUCTURE-1'!I17 -> 3038 | D13: =E13*$K$3 -> 15393055 | E13: 10015000 | F13: m3 | G13: تهیه و اجرای بتن با شن و ماسه طبیعی با عیار 350 کیلو سیمان | I13: 80106
A14: =C14*D14 -> 3.7542024e+08 | B14: =ROUND(C14*E14,0) -> 244255200 | C14: =C13 -> 3038 | D14: =E14*$K$3 -> 123574.8 | E14: 80400 | F14: m3 | G14: اضافه بهایه ردیفهای بتنه ریزی در بتن مسلح | I14: 80310
A15: =C15*D15 -> 0 | F15: * | G15: تهیه مصالح و اجرای بتن با عیار 150 کیلو سیمان | I15: *
A16: =C16*D16 -> 1.4893495e+10 | B16: =ROUND(C16*E16,0) -> 9689977200 | C16: ='C.STEEL STRUCTURE-1'!J17 -> 1082.8 | D16: =E16*$K$3 -> 13754613 | E16: 8949000 | F16: m3 | G16: تهیه و اجرای بتن با شن و ماسه طبیعی با 150 کیلو سیمان | I16: 80102
A17: =C17*D17 -> 2.8209268e+08 | B17: =ROUND(C17*E17,0) -> 183534600 | C17: =C16 -> 1082.8 | D17: =E17*$K$3 -> 260521.5 | E17: 169500 | F17: m3 | G17: اضافه بها برای بتن به ضخامت 15 سانتیمتر و کمتر | I17: 80304
H18: نصب برجها و پایه های روشنایی | I18: *
A19: =C19*D19 -> 76579488 | B19: =ROUND(C19*E19,0) -> 49824000 | C19: ='C.STEEL STRUCTURE-1'!M13+'C.STEEL STRUCTURE-1'!M14 -> 144 | D19: =E19*$K$3 -> 531802 | E19: 346000 | F19: Kg | G19: (تهیه ، ساخت و) نصب ستون از یک قوطی و یا لوله(توضیح : با توجه به انکه پایه ها و برجها جداگانه خرید میگردندو در براورد اجرا فقط نصب آن منظور میگردد، از هزینه فهرست بها10،000 ریال /کیلوگرم بابت تامین مواد پایه ها کم شده است) | I19: *90102
G20: تهیه ونصب استند پایپ مخازن | I20: *
A21: =C21*D21 -> 44726700000 | B21: =ROUND(C21*E21,0) -> 29100000000 | C21: ='C.STEEL STRUCTURE-1'!M9*1000 -> 60000 | D21: =E21*$K$3 -> 745445 | E21: 485000 | F21: Kg | G21: تهیه و ساخت . نصب برجهای فلزی مرتفع (آب) (توضیح : با توجه به مشخصات مشابه استند پایپها با سازه فلزی مخازن مرتفع آب ، از این بند استفاده گردید) | I21: 90501
G22: نصب دکلهای انتقال برق 66 کیلوولت | I22: *
A23: =C23*D23 -> 248625120000 | B23: =ROUND(C23*E23,0) -> 161760000000 | C23: ='C.STEEL STRUCTURE-1'!M12*1000 -> 480000 | D23: =E23*$K$3 -> 517969 | E23: 337000 | F23: Kg | G23: تهیه، ساخت و نصب ستون های خرپایی به اشکال مختلف ا ز تیرآهن ، ناودانی ، نبش ی و مانن د آن، ب ا اتصا ل اعضای خرپا بدون استفاده از ورق. | I23: 90305
G24: ساخت و نصب پلترمها و سایر سازه های فلزی | I24: *
A25: =C25*D25 -> 165756228000 | B25: =ROUND(C25*E25,0) -> 107844000000 | C25: =SUM('C.STEEL STRUCTURE-1'!L9:L11)*1000 -> 264000 | D25: =E25*$K$3 -> 627864.5 | E25: 408500 | F25: Kg | G25: تهیه ، ساخت و نصب قاب ها (تا دهانه 30 متر) | I25: 90401
G26: زنگ زدایی و رنگ آمیزی اسکلت فلزی | I26: *
A27: =C27*D27 -> 210458336000 | B27: =ROUND(C27*E27,0) -> 136928000000 | C27: ='C.STEEL STRUCTURE-1'!L17*1000 -> 352000 | D27: =E27*$K$3 -> 597893 | E27: 389000 | F27: Kg | G27: زنگ زدايي اسكلت‌هاي فلزي، به روش ساچمه پاشي (شات بلاست). | I27: 250104 | L27: چهارم 91 | M27: 481.9
A28: =C28*D28 -> 6.8755088e+09 | B28: =ROUND(C28*E28,0) -> 4473330400 | C28: ='C.STEEL STRUCTURE-1'!N17 -> 5600 | D28: =E28*$K$3 -> 1227769.4 | E28: =ROUND(75100*M29,0) -> 798809 | F28: m2 | G28: تهيه مصالح و اجراي رنگ اپوكسي برايساير كارهاي فلزي، شامل دوقشر ضد زنگ براي اپوكسي، يك قشرآستر و يك قشر رويه. | I28: 250303 | L28: چهارم 1401 | M28: 5125.778
A29: =SUM(A4:A28) -> 9.3590103e+11 | B29: =SUM(B4:B28) -> 607865879900 | G29: جمع : | L29: ضریب بروزرسانی اعمال شده براساس فهرست ابنیه | M29: =M28/M27 -> 10.636601

Sheet C.Buildings
A1: جدول 9- برآورد اجرا بر اساس ابلاغیه شماره 47855 مورخ 1401/12/16 شورای مرکزی سازمان نظام مهندسی ساختمان -احداث ساختمانها
H3: هزینه اجرا | J3: متراژ بر حسب متر | P3: ردیف
G4: =$S$4*J4*$S$5 -> 294344107200 | J4: 936 | O4: احداث اتاق کنترل و مخابرات | P4: 1 | S4: 93000000
G5: =$S$4*(790+J5+790)*$S$5 -> 647808612000 | I5: 790+ | J5: 480 | O5: احداث پست برق | P5: 2 | S5: =ROUND(T8*T9*T10*T11*T12,3)*1.1 -> 3.3814
G6: =$S$4*J6*$S$5 -> 17610331200 | J6: 56 | O6: احداث نگهبانی | P6: 3
G7: =$S$4*J7*$S$5 -> 73271556600 | J7: 233 | O7: احداث کارگاه مهندسی | P7: 4
G8: =$S$4*J8*$S$5 -> 81762252000 | J8: 260 | O8: احداث ساختمان کمپرسور و دیزل ژنراتور | P8: 5 | S8: منطقه ای گچساران. | T8: 1.09
G9: =$S$4*J9*$S$5 -> 7861755000 | J9: 25 | O9: توسعه پست برق بهره برداری | P9: 6 | S9: بالاسری | T9: 1.41
G10: =$S$4*J10*$S$5 -> 20755033200 | J10: 66 | O10: ساختمان رفاهی بهره برداری | P10: 7 | S10: تجهیزکارگاه | T10: 1
G11: =$S$4*J11*$S$5 -> 41824536600 | J11: 133 | O11: توسعه اتاق کنترل بهره برداری | P11: 8 | S11: بروزرسانی | T11: 1
G12: =$S$4*J12*$S$5 -> 61950629400 | J12: 197 | O12: احداث ساختمان کمپرسور واحد بهره برداری | P12: 9 | S12: ضريب تطبيق | T12: 2
G13: =$S$4*J13*$S$5 -> 133649835000 | J13: 425 | O13: ایستگاه برق 33 کیلو ولت | P13: 10 | S13: چهارم 91 | T13: 481.9
G14: =$S$4*J14*$S$5 -> 93397649400 | J14: 297 | O14: پست برق 3.45/33 کیلوولت | P14: 11 | S14: چهارم 1401 | T14: 5125.778
G15: =$S$4*J15*$S$5 -> 15094569600 | J15: 48 | O15: احداث دیزل ژنراتور پست برق | P15: 12 | S15: ضریب بروزرسانی اعمال شده براساس فهرست ابنیه | T15: =T14/T13 -> 10.636601
G16: =$S$4*J16*$S$5 -> 9119635800 | J16: 29 | O16: احداث نگهبانی پست برق | P16: 13
G17: =$S$4*J17*$S$5 -> 71699205600 | J17: 228 | O17: احداث آزمایشگاه مرکزی | P17: 14
G18: =$S$4*J18*$S$5 -> 21383973600 | J18: 68 | O18: احداث انبار فوم | P18: 15
G19: =$S$4*J19*$S$5 -> 21383973600 | J19: 68 | O19: ساختمان انبار مصرفی | P19: 16
G20: =SUM(G4:H19) -> 1612917655800
B23: نحوه محاسبه اجرای ساختمانها با توجه به آنکه این پروژه در حد مهندسی مقدماتی و پایه بوده و نقشه معماری فاز یک آن اماده گردیده لیکن نقشه های فاز 2 معماری، نقشه های اجرایی فونداسیون، سازه بتی و فولادی و نیز نقشه های تاسیسات آن تهیه نگردیده و میبایست در مرحله مهندسی تفصیلی انجام شود، لذا امکان تهیه ریز برآورد اقلام و استفاده از فهرست احاد بهای اببنیه در این مرحله از پروژه میسر نمیباشد. لذا برای برآورد هزینه ساخت و اجرای ساختمانها از ابلاغیه شماره 47855/ش م مورخ 1401/12/16شورای مرکزی سازمان نظام مهندسی ساختمان که بر مبنای متراژ ساخت بنا میباشد، استفاده گردیده است که در ذیل ابلاغیه مذکور درج گردیده است:

Sheet C.RETAINING WAL
A1: جدول10 - برآورد اجرا بر اساس فهرست بهای باند و راه 1402 -ساخت دیوار حایل مجاور تپه و سطوح کوهبری شده و شیروانی دورتادور کارخانه
A2: ارزش کار | B2: مبلغ بدون اعمال ضرایب | C2: مقـدار | D2: واحد بــها با اعمال ضریب | E2: واحد بــهامطابق فهرست راه و باند 1402 | F2: واحـد | G2: شــــــــرح | I2: ردیف
F3: * | G3: کانال کنی با ماشین | I3: * | K3: =ROUND(N4*N5*N7,3) -> 1.579 | L3: ضریب =
A4: =C4*D4 -> 127804260000 | B4: =ROUND(C4*E4,0) -> 80940000000 | C4: 12000 | D4: =E4*$K$3 -> 10650355 | E4: 6745000 | F4: مترمكعب | G4: بنايي با سنـگ لاشه و ملات ماسه سيمان 1:3 در پي. | I4: 60203 | M4: منطقه ای گچساران. | N4: 1.12
A5: =C5*D5 -> 31794744000 | B5: =ROUND(C5*E5,0) -> 20136000000 | C5: 12000 | D5: =E5*$K$3 -> 2649562 | E5: 1678000 | F5: مترمكعب | G5: اضافه بها به رديف‌هاي بنايي با سنـگ لاشه در پي، براي بنايي در ديوار. | I5: 60301 | M5: بالاسری | N5: 1.41
A6: =C6*D6 -> 2124544500 | B6: =ROUND(C6*E6,0) -> 1345500000 | C6: 9000 | D6: =E6*$K$3 -> 236060.5 | E6: 149500 | F6: مترمربع | G6: اضافه بها به رديف‌هاي خشکه‌چيني و بنايي با سنـگ لاشه، براي سطوح شيب‌دار. | I6: 60403 | M6: تجهیزکارگاه | N6: 1
A7: =SUM(A3:A6) -> 161723548500 | B7: =SUM(B3:B6) -> 102421500000 | G7: مجموع | M7: بروزرسانی | N7: 1
A9: جدول 11 - برآورد اجرا بر اساس فهرست بهای راه و باند 1402 -تجهیز و برچیدن کارگاه
A10: توضیحات (ارقام بر اساس اطلاعات برداشت شده از پروژه مشابه درج شده است) | E10: مبلغ | F10: واحد | G10: شرح | I10: ردیف | M10: 4/91 | N10: 469.7
A11: اجاره 400مترمربع مسکونی | E11: =30*20000000*N12 -> 7.1670996e+09 | F11: مقطوع | G11: تامين و تجهيز محل سكونت كارمندان و افراد متخصص پيمانكار. | I11: 420101 | M11: 4/1401 | N11: 5610.6444
A12: احداث 200 متر مربع و تجهیز | E12: =200*4000000*N12 -> 9.5561328e+09 | F12: مقطوع | G12: تامين و تجهيز ساختمان‌هاي اداري و دفاتر كار پيمانكار. | I12: 420103 | N12: =N11/N10 -> 11.945166
A13: طبخ روزانه 100 وعده غذا | E13: =30*30*100*100000*N12 -> 1.0750649e+11 | F13: مقطوع | G13: تامين كمك هزينه يا تسهيلات لازم براي تهيه غذاي كارگران. | I13: 420201
E14: =500000*N12 -> 5972583 | F14: مقطوع | G14: تامين وتجهيزساختمانهاي اداري و دفاتركاركارفرما،مهندس مشاورو .آزمايشگاه | I14: 420302
A15: احداث 500 متر انبار سرپوشیده | E15: =500*2500000*N12 -> 1.4931457e+10 | F15: مقطوع | G15: تامين ساختمان‌هاي پشتيباني و هزينه تجهيز انبارهاي سرپوشيده، آزمايشگاه پيمانكار و موارد مشابه. | I15: 420401
E16: =300000000*N12 -> 3.5835498e+09 | F16: مقطوع | G16: تامين و تجهيز ساختمان‌هاي عمومي، بجز ساختمان‌هاي مسکوني و اداري و دفاتر کار. | I16: 420403
A17: 2000 متر مربع | E17: =200000000*N12 -> 2.3890332e+09 | F17: مقطوع | G17: محوطه سازي. | I17: 420404
A18: ماهیانه 2،000،000 ریال | E18: =30*300000*N12 -> 1.0750649e+08 | F18: مقطوع | G18: تامين آب كارگاه و شبكه آب رساني داخل كارگاه. | I18: 420601
A19: ماهیانه 30،000،000 ریال | E19: =30*30000000*N12 -> 1.0750649e+10 | F19: مقطوع | G19: تامين برق كارگاه و شبكه برق رساني داخل كارگاه. | I19: 420602
E20: =50000000*N12 -> 5.972583e+08 | F20: مقطوع | G20: تامين سيستم‌هاي مخابراتي داخل كارگاه. | I20: 420603
A21: ماهیانه 30،000،000 ریال | E21: =30*30000000*N12 -> 1.0750649e+10 | F21: مقطوع | G21: تامين سيستم سوخت رساني كارگاه. | I21: 420605
F22: مقطوع | G22: تامين راه دسترسي. | I22: 420701
F23: مقطوع | G23: بيمه تجهيز كارگاه. | I23: 421301
E24: =600000000*N12 -> 7.1670996e+09 | F24: مقطوع | G24: برچيدن کارگاه. | I24: 421302
E25: =SUM(E11:E24) -> 1.745129e+11 | G25: جمع :

Sheet C.PIPING
A1: جدول 12 - برآورد اجرای لوله کشی وپایپینگ بر اساس فهرست بهای اختصاصی تاسیسات نفت و گاز، رشته نصب واحدهای بهره برداری نفت و گاز -1401
A2: هزینه تمام شده مطابق فهرست بها | B2: مبلغ بدون اعمال ضرایب | C2: بهای واحد بــها با اعمال ضریب | D2: بهای واحد بــها بدون اعمال ضریب | E2: ردیف | F2: ردیف فهرست بهای نفت سال 1401 | G2: مقدار | H2: واحد | I2: فصل | J2: شرح عمليات
A3: =C3*G3 -> 2.1563274e+10 | B3: =ROUND(G3*D3,0) -> 8614971750 | C3: =D3*$K$4 -> 3733900.3 | D3: 1491770 | E3: 1.01 | F3: 590101101 | G3: 5775 | H3: تن | I3: فصل اول-لوله کشی-حمل و جابجایی مصالح | J3: حمل و جابجايي مصالح در محدوده سايت | U3: =G3*1.5 -> 8662.5
A4: =C4*G4 -> 12233985687 | B4: =ROUND(G4*D4,0) -> 4887729000 | C4: =D4*$K$4 -> 2118439.1 | D4: 846360 | E4: 1.02 | F4: 590111101 | G4: 5775 | H4: تن | I4: فصل اول-لوله کشی-حمل و جابجایی مصالح | J4: بخشی که در محل ساخته و نصب می شود | K4: =ROUND(P4*P5*P6*P7,3) -> 2.503 | O4: منطقه ای گچساران. | P4: 1.12 | U4: =G4*1.5 -> 8662.5
A5: =C5*G5 -> 41196251250 | B5: =ROUND(G5*D5,0) -> 16458750000 | C5: =D5*$K$4 -> 23778.5 | D5: 9500 | E5: 1.03 | F5: 590142101 | G5: 1732500 | H5: تن/کیلومتر | I5: فصل اول-لوله کشی-حمل و جابجایی مصالح | J5: اضافه بهای حمل بیش از 5 کیلومتر | O5: بالاسری | P5: 1.48 | U5: =G5*1.5 -> 2598750
A6: =C6*G6 -> 1.0199347e+11 | B6: =ROUND(G6*D6,0) -> 40748488905 | C6: =D6*$K$4 -> 14657393 | D6: 5855930 | E6: 3.01 | F6: 590301101 | G6: 6958.5 | H6: سرجوش | I6: فصل سوم-گروه لوله كشي-لوله كشي روزميني ( ادامه..) | J6: لوله كشي روزميني، نصب و جوشكاري، كربن استيل با قطر 2 اينچ با ضخامت كوچكتر يا مساوي 375/0 اينچ | O6: تجهیزکارگاه | P6: 1 | U6: =G6*1.5 -> 10437.75
A7: =C7*G7 -> 3.4083236e+10 | B7: =ROUND(G7*D7,0) -> 13616953890 | C7: =D7*$K$4 -> 18353923 | D7: 7332770 | E7: 3.02 | F7: 590301102 | G7: 1857 | H7: سرجوش | I7: فصل سوم-گروه لوله كشي-لوله كشي روزميني ( ادامه..) | J7: لوله كشي روزميني، نصب و جوشكاري، كربن استيل با قطر 3 اينچ با ضخامت كوچكتر يامساوي 375/. اينچ | O7: بروزرسانی | P7: 1.51 | U7: =G7*1.5 -> 2785.5
A8: =C8*G8 -> 2.6619703e+10 | B8: =ROUND(G8*D8,0) -> 10635119040 | C8: =D8*$K$4 -> 21329890 | D8: 8521730 | E8: 3.03 | F8: 590301103 | G8: 1248 | H8: سرجوش | I8: فصل سوم-گروه لوله كشي-لوله كشي روزميني ( ادامه..) | J8: لوله كشي روزميني، نصب و جوشكاري، كربن استيل با قطر 4 اينچ با ضخامت كوچكتر يا مساوي 375/0 اينچ | U8: =G8*1.5 -> 1872
A9: =C9*G9 -> 3.712244e+10 | B9: =ROUND(G9*D9,0) -> 14831178390 | C9: =D9*$K$4 -> 27682654 | D9: 11059790 | E9: 3.04 | F9: 590301105 | G9: 1341 | H9: سرجوش | I9: فصل سوم-گروه لوله كشي-لوله كشي روزميني ( ادامه..) | J9: لوله كشي روزميني، نصب و جوشكاري، كربن استيل با قطر 6 اينچ با ضخامت كوچكتر يا مساوي 375/0 اينچ | U9: =G9*1.5 -> 2011.5
A10: =C10*G10 -> 2.8336381e+10 | B10: =ROUND(G10*D10,0) -> 11320967430 | C10: =D10*$K$4 -> 34409692 | D10: 13747380 | E10: 3.05 | F10: 590301106 | G10: 823.5 | H10: سرجوش | I10: فصل سوم-گروه لوله كشي-لوله كشي روزميني ( ادامه..) | J10: لوله كشي روزميني، نصب و جوشكاري، كربن استيل با قطر 8 اينچ با ضخامت كوچكتر يا مساوي 375/0 اينچ | U10: =G10*1.5 -> 1235.25
A11: =C11*G11 -> 4.4400742e+10 | B11: =ROUND(G11*D11,0) -> 17739009900 | C11: =D11*$K$4 -> 42899267 | D11: 17139140 | E11: 3.06 | F11: 590301107 | G11: 1035 | H11: سرجوش | I11: فصل سوم-گروه لوله كشي-لوله كشي روزميني ( ادامه..) | J11: لوله كشي روزميني، نصب و جوشكاري، كربن استيل با قطر 10 اينچ با ضخامت كوچكتر يا مساوي 375/0 اينچ | U11: =G11*1.5 -> 1552.5
A12: =C12*G12 -> 4.3514434e+10 | B12: =ROUND(G12*D12,0) -> 17384911530 | C12: =D12*$K$4 -> 50804943 | D12: 20297620 | E12: 3.07 | F12: 590301108 | G12: 856.5 | H12: سرجوش | I12: فصل سوم-گروه لوله كشي-لوله كشي روزميني ( ادامه..) | J12: لوله كشي روزميني، نصب و جوشكاري، كربن استيل با قطر 12 اينچ باضخامت كوچكتر يا مساوي 375/0 اينچ | U12: =G12*1.5 -> 1284.75
A13: =C13*G13 -> 7.1120562e+08 | B13: =ROUND(G13*D13,0) -> 284141280 | C13: =D13*$K$4 -> 59267135 | D13: 23678440 | E13: 3.08 | F13: 590301109 | G13: 12 | H13: سرجوش | I13: فصل سوم-گروه لوله كشي-لوله كشي روزميني ( ادامه..) | J13: لوله كشي روزميني، نصب و جوشكاري، كربن استيل با قطر 14 اينچ باضخامت كوچكتر يا مساوي 375/0 اينچ | U13: =G13*1.5 -> 18
A14: =C14*G14 -> 2.4887958e+10 | B14: =ROUND(G14*D14,0) -> 9943251240 | C14: =D14*$K$4 -> 66903113 | D14: 26729170 | E14: 3.09 | F14: 590301110 | G14: 372 | H14: سرجوش | I14: فصل سوم-گروه لوله كشي-لوله كشي روزميني ( ادامه..) | J14: لوله كشي روزميني، نصب و جوشكاري، كربن استيل با قطر 16 اينچ باضخامت كوچكتر يا مساوي 375/0 اينچ | U14: =G14*1.5 -> 558
A15: =C15*G15 -> 8.9485834e+08 | B15: =ROUND(G15*D15,0) -> 357514320 | C15: =D15*$K$4 -> 74571529 | D15: 29792860 | E15: 3.1 | F15: 590301111 | G15: 12 | H15: سرجوش | I15: فصل سوم-گروه لوله كشي-لوله كشي روزميني ( ادامه..) | J15: لوله كشي روزميني، نصب و جوشكاري، كربن استيل با قطر 18 اينچ باضخامت كوچكتر يا مساوي 375/0 اينچ | U15: =G15*1.5 -> 18
A16: =C16*G16 -> 5.2165665e+10 | B16: =ROUND(G16*D16,0) -> 20841256530 | C16: =D16*$K$4 -> 82215390 | D16: 32846740 | E16: 3.11 | F16: 590301112 | G16: 634.5 | H16: سرجوش | I16: فصل سوم-گروه لوله كشي-لوله كشي روزميني ( ادامه..) | J16: لوله كشي روزميني، نصب و جوشكاري، كربن استيل با قطر 20 اينچ باضخامت كوچكتر يا مساوي 375/0 اينچ | K16: 1.529 | U16: =G16*1.5 -> 951.75
A17: =C17*G17 -> 3.1559013e+08 | B17: =ROUND(G17*D17,0) -> 126084750 | C17: =D17*$K$4 -> 1.0519671e+08 | D17: 42028250 | E17: 3.12 | F17: 590301114 | G17: 3 | H17: سرجوش | I17: فصل سوم-گروه لوله كشي-لوله كشي روزميني ( ادامه..) | J17: لوله كشي روزميني، نصب و جوشكاري، كربن استيل با قطر 26 اينچ باضخامت كوچكتر يا مساوي 375/0 اينچ | U17: =G17*1.5 -> 4.5
A18: =C18*G18 -> 72910588 | B18: =ROUND(G18*D18,0) -> 29129280 | C18: =D18*$K$4 -> 759485.29 | D18: 303430 | E18: 3.13 | F18: 590326101 | G18: 96 | H18: سرجوش | I18: فصل سوم-گروه لوله كشي-لوله كشي روزميني ( ادامه..) | J18: لوله كشي روزميني، ساختو نصب در محل، فایبر گلاس ،رزینی قطر 1 اینچ | U18: =G18*1.5 -> 144
A19: =C19*G19 -> 50126029 | B19: =ROUND(G19*D19,0) -> 20026380 | C19: =D19*$K$4 -> 1518970.6 | D19: 606860 | E19: 3.14 | F19: 590326103 | G19: 33 | H19: سرجوش | I19: فصل سوم-گروه لوله كشي-لوله كشي روزميني ( ادامه..) | J19: لوله كشي روزميني، ساختو نصب در محل، فایبر گلاس ،رزینی قطر 2 اینچ | U19: =G19*1.5 -> 49.5
A20: =C20*G20 -> 2.4397905e+08 | B20: =ROUND(G20*D20,0) -> 97474650 | C20: =D20*$K$4 -> 2198009.5 | D20: 878150 | E20: 3.15 | F20: 590326105 | G20: 111 | H20: سرجوش | I20: فصل سوم-گروه لوله كشي-لوله كشي روزميني ( ادامه..) | J20: لوله كشي روزميني، ساختو نصب در محل، فایبر گلاس ،رزینی قطر 3 اینچ | U20: =G20*1.5 -> 166.5
A21: =C21*G21 -> 2.0836126e+09 | B21: =ROUND(G21*D21,0) -> 832446120 | C21: =D21*$K$4 -> 2869989.9 | D21: 1146620 | E21: 3.16 | F21: 590326106 | G21: 726 | H21: سرجوش | I21: فصل سوم-گروه لوله كشي-لوله كشي روزميني ( ادامه..) | J21: لوله كشي روزميني، ساختو نصب در محل، فایبر گلاس ،رزینی قطر 4 اینچ | U21: =G21*1.5 -> 1089
A22: =C22*G22 -> 1.7491284e+08 | B22: =ROUND(G22*D22,0) -> 69881280 | C22: =D22*$K$4 -> 3644017.6 | D22: 1455860 | E22: 3.17 | F22: 590326107 | G22: 48 | H22: سرجوش | I22: فصل سوم-گروه لوله كشي-لوله كشي روزميني ( ادامه..) | J22: لوله كشي روزميني، ساختو نصب در محل، فایبر گلاس ،رزینی قطر 5 اینچ | U22: =G22*1.5 -> 72
A23: =C23*G23 -> 9.8404754e+08 | B23: =ROUND(G23*D23,0) -> 393147240 | C23: =D23*$K$4 -> 4315998 | D23: 1724330 | E23: 3.18 | F23: 590326108 | G23: 228 | H23: سرجوش | I23: فصل سوم-گروه لوله كشي-لوله كشي روزميني ( ادامه..) | J23: لوله كشي روزميني، ساختو نصب در محل، فایبر گلاس ،رزینی قطر 6 اینچ | U23: =G23*1.5 -> 342
A24: =C24*G24 -> 1.326082e+09 | B24: =ROUND(G24*D24,0) -> 529797060 | C24: =D24*$K$4 -> 5667017.3 | D24: 2264090 | E24: 3.19 | F24: 590326109 | G24: 234 | H24: سرجوش | I24: فصل سوم-گروه لوله كشي-لوله كشي روزميني ( ادامه..) | J24: لوله كشي روزميني، ساختو نصب در محل، فایبر گلاس ،رزینی قطر 8 اینچ | U24: =G24*1.5 -> 351
A25: =C25*G25 -> 2.0843569e+09 | B25: =ROUND(G25*D25,0) -> 832743450 | C25: =D25*$K$4 -> 7018036.6 | D25: 2803850 | E25: 3.2 | F25: 590326110 | G25: 297 | H25: سرجوش | I25: فصل سوم-گروه لوله كشي-لوله كشي روزميني ( ادامه..) | J25: لوله كشي روزميني، ساختو نصب در محل، فایبر گلاس ،رزینی قطر 10 اینچ | U25: =G25*1.5 -> 445.5
A26: =C26*G26 -> 2.8140323e+08 | B26: =ROUND(G26*D26,0) -> 112426380 | C26: =D26*$K$4 -> 8527370.6 | D26: 3406860 | E26: 3.21 | F26: 590326111 | G26: 33 | H26: سرجوش | I26: فصل سوم-گروه لوله كشي-لوله كشي روزميني ( ادامه..) | J26: لوله كشي روزميني، ساختو نصب در محل، فایبر گلاس ،رزینی قطر 12 اینچ | U26: =G26*1.5 -> 49.5
A27: =C27*G27 -> 2.5572215e+08 | B27: =ROUND(G27*D27,0) -> 102166260 | C27: =D27*$K$4 -> 358154.27 | D27: 143090 | E27: 3.22 | F27: 590303101 | G27: 714 | H27: سرجوش | I27: فصل سوم-گروه لوله كشي-لوله كشي روزميني ( ادامه..) | J27: لوله كشي روزميني، نصب و جوشكاري، بستن فلنجها با قطر 2 اينچ با كلاس كوچكتر يا مساوي 600 | U27: =G27*1.5 -> 1071
A28: =C28*G28 -> 2.9836336e+08 | B28: =ROUND(G28*D28,0) -> 119202300 | C28: =D28*$K$4 -> 536142.6 | D28: 214200 | E28: 3.23 | F28: 590303102 | G28: 556.5 | H28: سرجوش | I28: فصل سوم-گروه لوله كشي-لوله كشي روزميني ( ادامه..) | J28: لوله كشي روزميني، نصب و جوشكاري، بستن فلنجها با قطر 3 اينچ با كلاس كوچكتر يا مساوي 600 | U28: =G28*1.5 -> 834.75
... A69: =C69*G69 -> 2.8100123e+09 | B69: =ROUND(G69*D69,0) -> 1122657750 | C69: =D69*$K$4 -> 3286564.2 | D69: 1313050 | E69: 15.06 | F69: 591531102 | G69: 855 | H69: عدد | I69: فصل پانزدهم-ساخت و نصب سازه های فلزی و تکیه گاه ها | J69: ساخت و نصب سازه های فلزی و تکیه گاه ها-ساخت و نصب تکیه گاه های 5 تا 10 کیلوگرم | U69: =G69*1.5 -> 1282.5
A70: =C70*G70 -> 4.9796529e+10 | B70: =ROUND(G70*D70,0) -> 19894738050 | C70: =D70*$K$4 -> 1156310.9 | D70: 461970 | E70: 17.01 | F70: 591701101 | G70: =14355*3 -> 43065 | H70: متر مربع | I70: فصل هفدهم- گروه نصب تجهيزات، رنگ وعايق-عمليات زنگ زدايي و رنگ آميزي | J70: رنگ آميزي، كارهاي لوله كشي، سند بلاست | U70: =G70*1.5 -> 64597.5
A71: =C71*G71 -> 1.2114426e+10 | B71: =ROUND(G71*D71,0) -> 4839962400 | C71: =D71*$K$4 -> 349018.32 | D71: 139440 | E71: 17.02 | F71: 591702101 | G71: =17355*2 -> 34710 | H71: متر مربع | I71: فصل هفدهم- گروه نصب تجهيزات، رنگ وعايق-عمليات زنگ زدايي و رنگ آميزي | J71: رنگ آميزي، كارهاي لوله كشي، رنگ در کارگاه | U71: =G71*1.5 -> 52065
A72: =C72*G72 -> 2.8693901e+09 | B72: =ROUND(G72*D72,0) -> 1146380400 | C72: =D72*$K$4 -> 724593.47 | D72: 289490 | E72: 17.03 | F72: 591703101 | G72: =1980*2 -> 3960 | H72: متر مربع | I72: فصل هفدهم- گروه نصب تجهيزات، رنگ وعايق-عمليات زنگ زدايي و رنگ آميزي | J72: رنگ آميزي، كارهاي لوله كشي، رنگ در محل نصب- قطر زیر 2اينچ | U72: =G72*1.5 -> 5940
A73: =C73*G73 -> 2.9598309e+10 | B73: =ROUND(G73*D73,0) -> 11825133600 | C73: =D73*$K$4 -> 623647.48 | D73: 249160 | E73: 17.04 | F73: 591704101 | G73: =23730*2 -> 47460 | H73: متر مربع | I73: فصل هفدهم- گروه نصب تجهيزات، رنگ وعايق-عمليات زنگ زدايي و رنگ آميزي | J73: رنگ آميزي، كارهاي لوله كشي، رنگ در محل نصب قطر بزرگتر يا مساوي 2 اينچ | U73: =G73*1.5 -> 71190
A74: =C74*G74 -> 3.3593742e+10 | B74: =ROUND(G74*D74,0) -> 13421391300 | C74: =D74*$K$4 -> 871094.06 | D74: 348020 | E74: 17.05 | F74: 591731103 | G74: =12855*3 -> 38565 | H74: متر مربع | I74: فصل هفدهم- گروه نصب تجهيزات، رنگ وعايق-عمليات زنگ زدايي و رنگ آميزي | J74: مصالح رنگ آمیزی | U74: =G74*1.5 -> 57847.5
A75: =C75*G75 -> 9.3136194e+10 | B75: =ROUND(G75*D75,0) -> 37209825900 | C75: =D75*$K$4 -> 1207522.3 | D75: 482430 | E75: 17.06 | F75: 591731112 | G75: =25710*3 -> 77130 | H75: متر مربع | I75: فصل هفدهم- گروه نصب تجهيزات، رنگ وعايق-عمليات زنگ زدايي و رنگ آميزي | J75: مصالح رنگ آمیزی | U75: =G75*1.5 -> 115695
A76: =C76*G76 -> 75415800 | B76: =ROUND(G76*D76,0) -> 30130164 | C76: =D76*$K$4 -> 1107427.3 | D76: 442440 | E76: 18.01 | F76: 591801102 | G76: 68.1 | H76: متر | I76: فصل هجدهم - نصب تجهيزات، رنگ و عایق - عمليات عایقکاری حرارتی، رطوبتی، ضدحریق و خوردگی | J76: عایقکاری گرم لوله های راسته-2 تا 6 اینچ | U76: =G76*1.5 -> 102.15
A77: =C77*G77 -> 9.9045659e+08 | B77: =ROUND(G77*D77,0) -> 395707788 | C77: =D77*$K$4 -> 1360330.4 | D77: 543480 | E77: 18.02 | F77: 591801103 | G77: 728.1 | H77: عدد | I77: فصل هجدهم - نصب تجهيزات، رنگ و عایق - عمليات عایقکاری حرارتی، رطوبتی، ضدحریق و خوردگی | J77: عایقکاری گرم لوله های راسته-8 تا 12 اینچ | U77: =G77*1.5 -> 1092.15
A78: =C78*G78 -> 1.7217611e+08 | B78: =ROUND(G78*D78,0) -> 68787900 | C78: =D78*$K$4 -> 1275378.6 | D78: 509540 | E78: 18.03 | F78: 591802101 | G78: 135 | H78: عدد | I78: فصل هجدهم - نصب تجهيزات، رنگ و عایق - عمليات عایقکاری حرارتی، رطوبتی، ضدحریق و خوردگی | J78: عایقکاری گرم شیرآلات و فیتینگ ها-زیر 2 اینچ | U78: =G78*1.5 -> 202.5
A79: =C79*G79 -> 2.1329645e+08 | B79: =ROUND(G79*D79,0) -> 85216320 | C79: =D79*$K$4 -> 2539243.4 | D79: 1014480 | E79: 18.04 | F79: 591802102 | G79: 84 | H79: عدد | I79: فصل هجدهم - نصب تجهيزات، رنگ و عایق - عمليات عایقکاری حرارتی، رطوبتی، ضدحریق و خوردگی | J79: عایقکاری گرم شیرآلات و فیتینگ ها- 2 تا 6 اینچ | U79: =G79*1.5 -> 126
A80: =C80*G80 -> 1.1979791e+09 | B80: =ROUND(G80*D80,0) -> 478617300 | C80: =D80*$K$4 -> 3803108.3 | D80: 1519420 | E80: 18.05 | F80: 591802103 | G80: 315 | H80: عدد | I80: فصل هجدهم - نصب تجهيزات، رنگ و عایق - عمليات عایقکاری حرارتی، رطوبتی، ضدحریق و خوردگی | J80: عایقکاری گرم شیرآلات و فیتینگ ها-8 تا 12 اینچ | U80: =G80*1.5 -> 472.5
A81: =C81*G81 -> 30672763 | B81: =ROUND(G81*D81,0) -> 12254400 | C81: =D81*$K$4 -> 639015.9 | D81: 255300 | E81: 18.06 | F81: 591803101 | G81: 48 | H81: عدد | I81: فصل هجدهم - نصب تجهيزات، رنگ و عایق - عمليات عایقکاری حرارتی، رطوبتی، ضدحریق و خوردگی | J81: عایقکاری گرم فلنجها-زیر 2 اینچ | U81: =G81*1.5 -> 72
A82: =C82*G82 -> 41897517 | B82: =ROUND(G82*D82,0) -> 16738920 | C82: =D82*$K$4 -> 1269621.7 | D82: 507240 | E82: 18.07 | F82: 591803102 | G82: 33 | H82: عدد | I82: فصل هجدهم - نصب تجهيزات، رنگ و عایق - عمليات عایقکاری حرارتی، رطوبتی، ضدحریق و خوردگی | J82: عایقکاری گرم فلنجها-2 تا 6 اینچ | U82: =G82*1.5 -> 49.5
A83: =C83*G83 -> 4.6810866e+08 | B83: =ROUND(G83*D83,0) -> 187019040 | C83: =D83*$K$4 -> 1902880.7 | D83: 760240 | E83: 18.08 | F83: 591803103 | G83: 246 | H83: عدد | I83: فصل هجدهم - نصب تجهيزات، رنگ و عایق - عمليات عایقکاری حرارتی، رطوبتی، ضدحریق و خوردگی | J83: عایقکاری گرم فلنجها-8 تا 12 اینچ | U83: =G83*1.5 -> 369
A84: =C84*G84 -> 2910203058 | B84: =ROUND(G84*D84,0) -> 1162686000 | C84: =D84*$K$4 -> 357628.64 | D84: 142880 | E84: 18.09 | F84: 591861101 | G84: 8137.5 | H84: اینچ/متر | I84: فصل هجدهم - نصب تجهيزات، رنگ و عایق - عمليات عایقکاری حرارتی، رطوبتی، ضدحریق و خوردگی | J84: مصالح عایقکاری گرم لوله های راسته | U84: =G84*1.5 -> 12206.25
A85: =C85*G85 -> 3.1937514e+09 | B85: =ROUND(G85*D85,0) -> 1275969405 | C85: =D85*$K$4 -> 863059.43 | D85: 344810 | E85: 18.1 | F85: 591862101 | G85: 3700.5 | H85: اینچ/قطر | I85: فصل هجدهم - نصب تجهيزات، رنگ و عایق - عمليات عایقکاری حرارتی، رطوبتی، ضدحریق و خوردگی | J85: مصالح عایقکاری گرم شیرآلات و فیتینگ ها | U85: =G85*1.5 -> 5550.75
A86: =C86*G86 -> 5.5162451e+08 | B86: =ROUND(G86*D86,0) -> 220385340 | C86: =D86*$K$4 -> 208474.87 | D86: 83290 | E86: 18.11 | F86: 591863101 | G86: 2646 | H86: اینچ/قطر | I86: فصل هجدهم - نصب تجهيزات، رنگ و عایق - عمليات عایقکاری حرارتی، رطوبتی، ضدحریق و خوردگی | J86: مصالح عایقکاری گرم فلنجها | U86: =G86*1.5 -> 3969
A87: =SUM(A3:A86) -> 8.2340108e+11 | B87: =SUM(B3:B86) -> 328965674112 | J87: مجموع

Sheet C.mECHANICAL
A1: جدول 13 - برآورد اجراو نصب تجهیزات مکانیک بر اساس فهرست بهای اختصاصی تاسیسات نفت و گاز، رشته نصب واحدهای بهره برداری نفت و گاز -1401
A2: هزینه تمام شده مطابق فهرست بها | B2: مبلغ بدون اعمال ضرایب | C2: بهای واحد بــها با اعمال ضریب | D2: بهای واحد بــها بدون اعمال ضریب | E2: ردیف فهرست بهای نفت سال 1401 | F2: مقدار | G2: واحد | H2: شماره تجهیز | J2: شرح | K2: ردیف | O2: وزن واحد
J5: نصب دیسالترها و هیترها | K5: 1
A6: =C6*F6 -> 6172791300 | B6: =ROUND(F6*D6,0) -> 2458300000 | C6: =D6*$N$19 -> 47483.01 | D6: 18910 | E6: کد 591111 ردیف 4 | F6: =O6*2 -> 130000 | G6: Kg | H6: DE | I6: -001-A/B | J6: 1at TRAIN DESALTER | K6: 1.1 | O6: 65000
A7: =C7*F7 -> 6172791300 | B7: =ROUND(F7*D7,0) -> 2458300000 | C7: =D7*$N$19 -> 47483.01 | D7: 18910 | E7: کد 591111 ردیف 4 | F7: =O7*2 -> 130000 | G7: Kg | H7: DE | I7: -002-A/B | J7: 2nd TRAIN DESALTER | K7: 1.2 | O7: 65000
A8: =C8*F8 -> 4902205212 | B8: =ROUND(F8*D8,0) -> 1952292000 | C8: =D8*$N$19 -> 40851710 | D8: 16269100 | E8: کد 591231 ردیف2 | F8: =O8*2 -> 120 | G8: TON | H8: H | I8: -001-A1/A2 | J8: CRUDE OIL INDIRECT FIRED HEATER | K8: 1.3 | O8: 60
A9: =C9*F9 -> 4902205212 | B9: =ROUND(F9*D9,0) -> 1952292000 | C9: =D9*$N$19 -> 40851710 | D9: 16269100 | E9: کد 591231 ردیف 2 | F9: =O9*2 -> 120 | G9: TON | H9: H | I9: -001-B1/B2 | J9: CRUDE OIL INDIRECT FIRED HEATER | K9: 1.4 | O9: 60
B10: =ROUND(F10*D10,0) -> 0 | J10: نصب مبدلهای حرارتی | K10: 2 | R10: منطقه ای گچساران. | S10: 1.12
A11: =C11*F11 -> 205525350 | B11: =ROUND(F11*D11,0) -> 81850000 | C11: =D11*$N$19 -> 41105.07 | D11: 16370 | E11: کد 591111 ردیف 1 | F11: =2*O11 -> 5000 | G11: Kg | H11: E | I11: -001-A/B | J11: SALTY CRUDE / DESALTED CRUDE HEAT EXCHANGER | K11: 2.1 | O11: 2500 | R11: بالاسری | S11: 1.48
A12: =C12*F12 -> 164420280 | B12: =ROUND(F12*D12,0) -> 65480000 | C12: =D12*$N$19 -> 41105.07 | D12: 16370 | E12: کد 591111 ردیف 1 | F12: =2*O12 -> 4000 | G12: Kg | H12: E | I12: -002-A/B | J12: WATER / WATER HEAT EXCHANGER | K12: 2.2 | O12: 2000 | R12: تجهیزکارگاه | S12: 1
B13: =ROUND(F13*D13,0) -> 0 | J13: نصب پمپ ها | K13: 3 | R13: بروزرسانی | S13: 1.515
A14: =C14*F14 -> 5.4076896e+08 | B14: =ROUND(F14*D14,0) -> 215360000 | C14: =D14*$N$19 -> 67596.12 | D14: 26920 | E14: کد 591001 ردیف 04 | F14: =O14*2 -> 8000 | G14: Kg | H14: P | I14: -001-A/B | J14: MAIN TRANSFER PUMPS | K14: 3.1 | O14: 4000
A15: =C15*F15 -> 3.7853827e+08 | B15: =ROUND(F15*D15,0) -> 150752000 | C15: =D15*$N$19 -> 67596.12 | D15: 26920 | E15: کد 591001 ردیف 04 | F15: =O15*2 -> 5600 | G15: Kg | H15: P | I15: -002-A/B | J15: AUXILLIARY TRANSFER PUMPS | K15: 3.2 | O15: 2800
A16: =C16*F16 -> 270058050 | B16: =ROUND(F16*D16,0) -> 107550000 | C16: =D16*$N$19 -> 90019.35 | D16: 35850 | E16: کد 591001 ردیف 03 | F16: =O16*2 -> 3000 | G16: Kg | H16: P | I16: -003-A/B | J16: OFF-SPEC PUMPS | K16: 3.3 | O16: 1500
A17: =C17*F17 -> 159699600 | B17: =ROUND(F17*D17,0) -> 63600000 | C17: =D17*$N$19 -> 159699.6 | D17: 63600 | E17: کد 591001 ردیف 01 | F17: =O17*2 -> 1000 | G17: Kg | H17: P | I17: -005-A/B | J17: DEGASSING WATER PUMPS | K17: 3.4 | O17: 500
A18: =C18*F18 -> 1.252989e+08 | B18: =ROUND(F18*D18,0) -> 49900000 | C18: =D18*$N$19 -> 125298.9 | D18: 49900 | E18: کد 591001 ردیف 02 | F18: =O18*1 -> 1000 | G18: Kg | H18: P | I18: -103 | J18: DILUTION WATER PUMPS | K18: 3.5 | O18: 1000
A19: =C19*F19 -> 187948350 | B19: =ROUND(F19*D19,0) -> 74850000 | C19: =D19*$N$19 -> 125298.9 | D19: 49900 | E19: کد 591001 ردیف 02 | F19: =O19*2 -> 1500 | G19: Kg | H19: P | I19: -106-A1/A2 | J19: DILUTION WATER PUMPS | K19: 3.6 | M19: ضریب | N19: =ROUND(S10*S11*S12*S13,3) -> 2.511 | O19: 750
A20: =C20*F20 -> 79849800 | B20: =ROUND(F20*D20,0) -> 31800000 | C20: =D20*$N$19 -> 159699.6 | D20: 63600 | E20: کد 591001 ردیف 01 | F20: =O20*2 -> 500 | G20: Kg | H20: P | I20: -601-A/B | J20: FLARE K.O DRUM LIQUID PUMPS | K20: 3.7 | O20: 250
A21: =C21*F21 -> 95819760 | B21: =ROUND(F21*D21,0) -> 38160000 | C21: =D21*$N$19 -> 159699.6 | D21: 63600 | E21: کد 591001 ردیف 01 | F21: =O21*2 -> 600 | G21: Kg | H21: P | I21: -102-A/B | J21: DEAERATED WATER PUMPS | K21: 3.8 | O21: 300
A22: =C22*F22 -> 63879840 | B22: =ROUND(F22*D22,0) -> 25440000 | C22: =D22*$N$19 -> 159699.6 | D22: 63600 | E22: کد 591001 ردیف 01 | F22: =O22 -> 400 | G22: Kg | H22: P | I22: -105 | J22: DEAERATED WATER PUMPS | K22: 3.9 | O22: 400
A23: =C23*F23 -> 47909880 | B23: =ROUND(F23*D23,0) -> 19080000 | C23: =D23*$N$19 -> 159699.6 | D23: 63600 | E23: کد 591001 ردیف 01 | F23: =O23 -> 300 | G23: Kg | H23: P | I23: -104 | J23: POTABLE WATER FILLING PUMP | K23: 3.10 | O23: 300
A24: =C24*F24 -> 378081270 | B24: =ROUND(F24*D24,0) -> 150570000 | C24: =D24*$N$19 -> 90019.35 | D24: 35850 | E24: کد 591001 ردیف 03 | F24: =O24*2 -> 4200 | G24: Kg | H24: P | I24: -201-A/B | J24: WATER INJECTION MAIN PUMPS | K24: 3.11 | O24: 2100
A25: =C25*F25 -> 2.5205418e+08 | B25: =ROUND(F25*D25,0) -> 100380000 | C25: =D25*$N$19 -> 90019.35 | D25: 35850 | E25: کد 591001 ردیف 03 | F25: =O25*2 -> 2800 | G25: Kg | H25: P | I25: -206-A/B/C | J25: WATER INJECTION BOOSTER PUMPS | K25: 3.12 | O25: 1400
A26: =C26*F26 -> 79849800 | B26: =ROUND(F26*D26,0) -> 31800000 | C26: =D26*$N$19 -> 159699.6 | D26: 63600 | E26: کد 591001 ردیف 01 | F26: =O26*2 -> 500 | G26: Kg | H26: P | I26: -501-A/B/C | J26: CHEMICAL INJECTION PORTABLE PUMPS | K26: 3.13 | O26: 250
A27: =C27*F27 -> 143729640 | B27: =ROUND(F27*D27,0) -> 57240000 | C27: =D27*$N$19 -> 159699.6 | D27: 63600 | E27: کد 591001 ردیف 01 | F27: =O27*2 -> 900 | G27: Kg | H27: P | I27: -701-A/B | J27: HC CLOSED DRAIN TRANSFER PUMPS | K27: 3.14 | O27: 450
A28: =C28*F28 -> 39924900 | B28: =ROUND(F28*D28,0) -> 15900000 | C28: =D28*$N$19 -> 159699.6 | D28: 63600 | E28: کد 591001 ردیف 01 | F28: =O28 -> 250 | G28: Kg | H28: P | I28: -702 | J28: HC CLOSED DRAIN DRUM SUMP PUMP | K28: 3.15 | O28: 250
A29: =C29*F29 -> 79849800 | B29: =ROUND(F29*D29,0) -> 31800000 | C29: =D29*$N$19 -> 159699.6 | D29: 63600 | E29: کد 591001 ردیف 01 | F29: =O29*2 -> 500 | G29: Kg | H29: P | I29: -703-A/B | J29: CLEAN WATER PUMPS | K29: 3.16 | O29: 250
A30: =C30*F30 -> 95819760 | B30: =ROUND(F30*D30,0) -> 38160000 | C30: =D30*$N$19 -> 159699.6 | D30: 63600 | E30: کد 591001 ردیف 01 | F30: =O30*2 -> 600 | G30: Kg | H30: P | I30: -704-A/B | J30: RECOVERED WASTE OIL PUMPS | K30: 3.17 | O30: 300
A31: =C31*F31 -> 39924900 | B31: =ROUND(F31*D31,0) -> 15900000 | C31: =D31*$N$19 -> 159699.6 | D31: 63600 | E31: کد 591001 ردیف 01 | F31: =O31 -> 250 | G31: Kg | H31: P | I31: -750 | J31: OILY WATER SEPARATOR PUMP | K31: 3.18 | O31: 250
A32: =C32*F32 -> 79849800 | B32: =ROUND(F32*D32,0) -> 31800000 | C32: =D32*$N$19 -> 159699.6 | D32: 63600 | E32: کد 591001 ردیف 01 | F32: =O32*2 -> 500 | G32: Kg | H32: P | I32: -705-A/B | J32: DIRTY OIL PUMPS | K32: 3.19 | O32: 250
A33: =C33*F33 -> 95819760 | B33: =ROUND(F33*D33,0) -> 38160000 | C33: =D33*$N$19 -> 159699.6 | D33: 63600 | E33: کد 591001 ردیف 01 | F33: =O33*2 -> 600 | G33: Kg | H33: P | I33: -706-A/B | J33: RECOVERED WASTE WATER PUMPS | K33: 3.2 | O33: 300
A34: =C34*F34 -> 39924900 | B34: =ROUND(F34*D34,0) -> 15900000 | C34: =D34*$N$19 -> 159699.6 | D34: 63600 | E34: کد 591001 ردیف 01 | F34: =O34 -> 250 | G34: Kg | H34: P | I34: -801 | J34: DIESEL OIL PUMP | K34: 3.21 | O34: 250
A35: =C35*F35 -> 360077400 | B35: =ROUND(F35*D35,0) -> 143400000 | C35: =D35*$N$19 -> 90019.35 | D35: 35850 | E35: کد 591001 ردیف 03 | F35: =O35*2 -> 4000 | G35: Kg | H35: P | I35: -901 | J35: FIRE WATER MAIN ELECTRICAL PUMP | K35: 3.22 | O35: 2000
A36: =C36*F36 -> 288915660 | B36: =ROUND(F36*D36,0) -> 115060000 | C36: =D36*$N$19 -> 52530.12 | D36: 20920 | E36: کد 591001 ردیف 05 | F36: =O36 -> 5500 | G36: Kg | H36: P | I36: 902 | J36: FIRE WATER MAIN DESEL PUMP | K36: 3.23 | O36: 5500
A37: =C37*F37 -> 127759680 | B37: =ROUND(F37*D37,0) -> 50880000 | C37: =D37*$N$19 -> 159699.6 | D37: 63600 | E37: کد 591001 ردیف 01 | F37: =O37*2 -> 800 | G37: Kg | H37: P | I37: -903-A/B | J37: FIRE WATER JOCKEY PUMPS | K37: 3.24 | O37: 400
A38: =C38*F38 -> 127759680 | B38: =ROUND(F38*D38,0) -> 50880000 | C38: =D38*$N$19 -> 159699.6 | D38: 63600 | E38: کد 591001 ردیف 01 | F38: =O38*2 -> 800 | G38: Kg | H38: P | I38: -904 | J38: FIRE WATER LOADING PUMP | K38: 3.25 | O38: 400
B39: =ROUND(F39*D39,0) -> 0 | J39: نصب بسته های فرایندی | K39: 4
A40: =C40*F40 -> 1453241250 | B40: =ROUND(F40*D40,0) -> 578750000 | C40: =D40*$N$19 -> 58129.65 | D40: 23150 | E40: کد 591101 -ردیف 3 | F40: =O40 -> 25000 | G40: No. | H40: PK | I40: -101 | J40: VACUUM DEAERATOR PACKAGE | K40: 4.1 | O40: 25000
A41: =C41*F41 -> 2906482500 | B41: =ROUND(F41*D41,0) -> 1157500000 | C41: =D41*$N$19 -> 58129.65 | D41: 23150 | E41: کد 591101 -ردیف 3 | F41: =O41 -> 50000 | G41: Kg | H41: PK | I41: -201-A/B | J41: IGF PACKAGE | K41: 4.2 | O41: 50000
A42: =C42*F42 -> 1453241250 | B42: =ROUND(F42*D42,0) -> 578750000 | C42: =D42*$N$19 -> 58129.65 | D42: 23150 | E42: کد 591101 -ردیف 3 | F42: =O42 -> 25000 | G42: Kg | H42: PK | I42: -202 | J42: NUTSHELL FILTER PACKAGE | K42: 4.3 | O42: 25000
A43: =C43*F43 -> 846141714 | B43: =ROUND(F43*D43,0) -> 336974000 | C43: =D43*$N$19 -> 79824.69 | D43: 31790 | E43: کد 591011 ردیف 02 | F43: =O43*2 -> 10600 | G43: Kg | H43: PK | I43: -401-A/B | J43: AIR COMPRESSOR PACKAGE | K43: 4.4 | O43: 5300
A44: =C44*F44 -> 77037480 | B44: =ROUND(F44*D44,0) -> 30680000 | C44: =D44*$N$19 -> 77037.48 | D44: 30680 | E44: کد 591101 ردیف 01 | F44: =O44 -> 1000 | G44: Kg | H44: PK | I44: -402 | J44: AIR DRYER PACKAGE | K44: 4.5 | O44: 1000
A45: =C45*F45 -> 894639168 | B45: =ROUND(F45*D45,0) -> 356288000 | C45: =D45*$N$19 -> 117715.68 | D45: 46880 | E45: کد 591011 ردیف 01 | F45: =O45*2 -> 7600 | G45: Kg | H45: PK | I45: -002-A/B | J45: AIR COMPRESSOR PACKAGE | K45: 4.6 | O45: 3800
A46: =C46*F46 -> 77037480 | B46: =ROUND(F46*D46,0) -> 30680000 | C46: =D46*$N$19 -> 77037.48 | D46: 30680 | E46: کد 591101 ردیف 01 | F46: =O46 -> 1000 | G46: Kg | H46: PK | I46: -003 | J46: AIR DRYER PACKAGE | K46: 4.7 | O46: 1000
A47: =C47*F47 -> 201959730 | B47: =ROUND(F47*D47,0) -> 80430000 | C47: =D47*$N$19 -> 67319.91 | D47: 26810 | E47: کد 591101 -ردیف 2 | F47: =O47 -> 3000 | G47: Kg | H47: PK | I47: -501 | J47: DEMULSIFIER INJECTION PACKAGE | K47: 4.8 | O47: 3000
A48: =C48*F48 -> 403919460 | B48: =ROUND(F48*D48,0) -> 160860000 | C48: =D48*$N$19 -> 67319.91 | D48: 26810 | E48: کد 591101 -ردیف 2 | F48: =O48*2 -> 6000 | G48: Kg | H48: PK | I48: -502-A/B | J48: DEMULSIFIER INJECTION PACKAGE | K48: 4.9 | O48: 3000
A49: =C49*F49 -> 1.5407496e+08 | B49: =ROUND(F49*D49,0) -> 61360000 | C49: =D49*$N$19 -> 77037.48 | D49: 30680 | E49: کد 591101 ردیف 01 | F49: =O49 -> 2000 | G49: Kg | H49: PK | I49: -503 | J49: OXYGEN SCAVENGER INJECTION PACKAGE | K49: 4.10 | O49: 2000
A50: =C50*F50 -> 201959730 | B50: =ROUND(F50*D50,0) -> 80430000 | C50: =D50*$N$19 -> 67319.91 | D50: 26810 | E50: کد 591101 -ردیف 2 | F50: =O50 -> 3000 | G50: Kg | H50: PK | I50: -504 | J50: CORROSION INHIBITOR INJECTION PACKAGE | K50: 4.11 | O50: 3000
A51: =C51*F51 -> 201959730 | B51: =ROUND(F51*D51,0) -> 80430000 | C51: =D51*$N$19 -> 67319.91 | D51: 26810 | E51: کد 591101 -ردیف 2 | F51: =O51 -> 3000 | G51: Kg | H51: PK | I51: -505 | J51: REVERSE DEMULSIFIER INJECTION PACKAGE | K51: 4.12 | O51: 3000
A52: =C52*F52 -> 348777900 | B52: =ROUND(F52*D52,0) -> 138900000 | C52: =D52*$N$19 -> 58129.65 | D52: 23150 | E52: کد 591101 -ردیف 3 | F52: =O52*2 -> 6000 | G52: Kg | H52: PK | I52: -506-A | J52: BIOCIDE INJECTION PACKAGE (TYPE A) | K52: 4.13 | O52: 3000
A53: =C53*F53 -> 348777900 | B53: =ROUND(F53*D53,0) -> 138900000 | C53: =D53*$N$19 -> 58129.65 | D53: 23150 | E53: کد 591101 -ردیف 3 | F53: =O53*2 -> 6000 | G53: Kg | H53: PK | I53: -506-B | J53: BIOCIDE INJECTION PACKAGE (TYPE B) | K53: 4.14 | O53: 3000
A54: =C54*F54 -> 201959730 | B54: =ROUND(F54*D54,0) -> 80430000 | C54: =D54*$N$19 -> 67319.91 | D54: 26810 | E54: کد 591101 -ردیف 2 | F54: =O54 -> 3000 | G54: Kg | H54: PK | I54: -507 | J54: ANTI SCALE INJECTION PACKAGE | K54: 4.15 | O54: 3000
B55: =ROUND(F55*D55,0) -> 0 | J55: نصب مخازن تحت فشار | K55: 5
A56: =C56*F56 -> 250740927 | B56: =ROUND(F56*D56,0) -> 99857000 | C56: =D56*$N$19 -> 41105.07 | D56: 16370 | E56: کد 591111 ردیف 1 | F56: =O56 -> 6100 | G56: Kg | H56: V | I56: -601 | J56: FLARE K.O. DRUM | K56: 5.1 | O56: 6100
A57: =C57*F57 -> 49391370 | B57: =ROUND(F57*D57,0) -> 19670000 | C57: =D57*$N$19 -> 49391.37 | D57: 19670 | E57: کد 591112 ردیف 1 | F57: =O57 -> 1000 | G57: Kg | H57: V | I57: -301 | J57: FUEL GAS K.O. DRUM | K57: 5.2 | O57: 1000
A58: =C58*F58 -> 702904230 | B58: =ROUND(F58*D58,0) -> 279930000 | C58: =D58*$N$19 -> 54488.7 | D58: 21700 | E58: کد 591112 ردیف 2 | F58: =O58 -> 12900 | G58: Kg | H58: V | I58: -401 | J58: AIR RECIEVER | K58: 5.3 | O58: 12900
A59: =C59*F59 -> 11680820460 | B59: =ROUND(F59*D59,0) -> 4651860000 | C59: =D59*$N$19 -> 47483.01 | D59: 18910 | E59: کد 591111 ردیف 4 | F59: =O59 -> 246000 | G59: Kg | H59: V | I59: -001-A/B | J59: FREE WATER K.O DRUM | K59: 5.4 | O59: 246000
A60: =C60*F60 -> 1091843064 | B60: =ROUND(F60*D60,0) -> 434824000 | C60: =D60*$N$19 -> 36886.59 | D60: 14690 | E60: کد 591111 ردیف 2 | F60: =O60 -> 29600 | G60: Kg | H60: V | I60: -701 | J60: HC CLOSED DRAIN DRUM | K60: 5.5 | O60: 29600
A61: =C61*F61 -> 171704691 | B61: =ROUND(F61*D61,0) -> 68381000 | C61: =D61*$N$19 -> 28148.31 | D61: 11210 | E61: کد 581113 ردیف 1 | F61: =O61 -> 6100 | G61: Kg | H61: V | I61: -801 | J61: DIESEL STORAGE TANK | K61: 5.6 | O61: 6100
A62: =C62*F62 -> 8.1150498e+08 | B62: =ROUND(F62*D62,0) -> 323180000 | C62: =D62*$N$19 -> 36886.59 | D62: 14690 | E62: کد 591111 ردیف 2 | F62: 22000 | G62: Kg | J62: LUNCHER AND RECEIVER | K62: 5.7
B63: =ROUND(F63*D63,0) -> 0 | J63: نصب فلرها | K63: 6
A64: =C64*F64 -> 2.7577929e+08 | B64: =ROUND(F64*D64,0) -> 109828470 | C64: =D64*$N$19 -> 91926429 | D64: 36609490 | E64: کد 591241 ردیف 01 | F64: 3 | G64: Kg | H64: PK | I64: -602 | J64: FLARE PACKAGE | K64: 6.1 | O64: 3000
A65: =C65*F65 -> 2.2981607e+08 | B65: =ROUND(F65*D65,0) -> 91523725 | C65: =D65*$N$19 -> 91926429 | D65: 36609490 | E65: کد 591241 ردیف 01 | F65: 2.5 | G65: Kg | H65: PK | I65: -603 | J65: COLD FLARE PACKAGE | K65: 6.2 | O65: 2500
B66: =ROUND(F66*D66,0) -> 0 | J66: نصب جرثقیلهای سقفی | K66: 7
A67: =C67*60 -> 3.737275e+09 | B67: =ROUND(12*5*D67,0) -> 1488361200 | C67: =D67*$N$19 -> 62287916 | D67: 24806020 | E67: کد 591401 - ردیف 1 | F67: 12x5 تن | G67: TON | H67: CR | I67: 001~0012 | J67: CRANES | K67: 7.1 | O67: 40
B68: =ROUND(F68*D68,0) -> 0 | J68: نصب مخازن اتمسفریک | K68: 8
B69: =ROUND(F69*D69,0) -> 0 | H69: TK | I69: -003 | J69: OFF-SPEC TANK : نصب و اجرای مخزن | K69: 8.1 | L69: ID= | M69: 25 | N69: 216500
A70: =C70*F70 -> 8.4200909e+08 | B70: =ROUND(F70*D70,0) -> 335328190 | C70: =D70*$N$19 -> 3889187.5 | D70: 1548860 | E70: کد 591301 - ردیف 2 | F70: =N69/1000 -> 216.5 | G70: Ton | J70: تخلیه ، بار اندازی و صفافی مصالح | K70: 8.1.1 | L70: HEIGHT= | M70: 15
A71: =C71*F71 -> 5.4924287e+09 | B71: =ROUND(F71*D71,0) -> 2187347164 | C71: =D71*$N$19 -> 1.425403e+08 | D71: 56766350 | E71: کد 591302 - ردیف 2 | F71: =N71/1000 -> 38.532461 | G71: Ton | J71: نصب و جوشکاری کف مخزن | K71: 8.1.2 | N71: =M69^2*0.25*3.1415*0.01*7850 -> 38532.461
A72: =C72*F72 -> 2.5098408e+10 | B72: =ROUND(F72*D72,0) -> 9995383484 | C72: =D72*$N$19 -> 2.1577852e+08 | D72: 85933300 | E72: کد 591303 - ردیف 2 | F72: =N72/1000 -> 116.3156 | G72: Ton | J72: نصب و جوشکاری بدنه مخزن | K72: 8.1.3 | N72: =N69-N71-N73-N74 -> 116315.6
A73: =C73*F73 -> 5.5609942e+09 | B73: =ROUND(F73*D73,0) -> 2214653192 | C73: =D73*$N$19 -> 1.8039966e+08 | D73: 71843750 | E73: کد 591304 - ردیف 2 | F73: =N73/1000 -> 30.825969 | G73: Ton | J73: نصب و جوشکاری سقف ثابت مخزن | K73: 8.1.4 | N73: =M69^2*0.25*3.1415*0.008*7850 -> 30825.969
A74: =C74*F74 -> 7.493482e+09 | B74: =ROUND(F74*D74,0) -> 2984262035 | C74: =D74*$N$19 -> 243089.91 | D74: 96810 | E74: کد 591308 | F74: =N74 -> 30825.969 | G74: Kg | J74: نصب و جوشکاری سازه سقف ثابت مخزن | K74: 8.1.5 | N74: =N73 -> 30825.969
A75: =C75*F75 -> 8.6546637e+08 | B75: =ROUND(F75*D75,0) -> 344670000 | C75: =D75*$N$19 -> 288488.79 | D75: 114890 | E75: کد 591307 | F75: 3000 | G75: Kg | J75: نصب و جوشکاری پله بدنه | K75: 8.1.6
A76: =C76*F76 -> 6.8318897e+08 | B76: =ROUND(F76*D76,0) -> 272078443 | C76: =D76*$N$19 -> 1391822.2 | D76: 554290 | E76: کد 591741 - ردیف 1 | F76: =M69^2*3.1415/4 -> 490.85938 | G76: M2 | J76: سند بلاست کف مخازن سقف ثابت | K76: 8.1.7
A77: =C77*F77 -> 2.9513852e+09 | B77: =ROUND(F77*D77,0) -> 1175382408 | C77: =D77*$N$19 -> 1670191.7 | D77: 665150 | E77: کد 591741 - ردیف 3 | F77: =1.2*F76+3.1415*M69*M70 -> 1767.0938 | G77: M2 | J77: سند بلاست بدنه خارجی مخازن و سقف ثابت | K77: 8.1.8 | N77: =M74^2*0.25*3.1415*0.01*7850*2 -> 0
A78: =C78*F78 -> 1.6395845e+08 | B78: =ROUND(F78*D78,0) -> 65296078 | C78: =D78*$N$19 -> 208764.54 | D78: 83140 | E78: کد 591741 - ردیف 4 | F78: =3.1415*M69*(M70-5) -> 785.375 | G78: M2 | J78: اضافه بهای سند بلاست بابت ارتفاع بیش از 5 متر | K78: 8.1.9
A79: =C79*F79 -> 2.7874194e+09 | B79: =ROUND(F79*D79,0) -> 1110083385 | C79: =D79*$N$19 -> 1670191.7 | D79: 665150 | E79: کد 591741 - ردیف 3 | F79: =F76+3.1415*M69*M70 -> 1668.9219 | G79: M2 | J79: سند بلاست بدنه داخلی مخازن و کف | K79: 8.1.10 | N79: =M76^2*0.25*3.1415*0.01*7850*2 -> 0
A80: =C80*F80 -> 1.6395845e+08 | B80: =ROUND(F80*D80,0) -> 65296078 | C80: =D80*$N$19 -> 208764.54 | D80: 83140 | E80: کد 591741 - ردیف 4 | F80: =F78 -> 785.375 | G80: M2 | J80: اضافه بهای سند بلاست داخلی بابت ارتفاع بیش از 5 متر | K80: 8.1.11 | N80: =2*N76-N79-N83-N84 -> 0
A81: =C81*F81 -> 1.1758507e+09 | B81: =ROUND(F81*D81,0) -> 468279844 | C81: =D81*$N$19 -> 299436.75 | D81: 119250 | E81: کد 591742 - ردیف 2 | F81: =F76+F77+F79 -> 3926.875 | G81: M2 | J81: رنگ امیزی سطوح داخل و خارج مخزنها | K81: 8.1.12 | N81: =M74^2*0.25*3.1415*0.008*7850*2 -> 0
A82: =C82*F82 -> 56243625 | B82: =ROUND(F82*D82,0) -> 22398895 | C82: =D82*$N$19 -> 35806.86 | D82: 14260 | E82: کد 591742 - ردیف 3 | F82: =F78+F80 -> 1570.75 | G82: M2 | J82: اضافه بهای رنگ امیزی بابت ارتفاع بیش از 5 متر | K82: 8.1.13 | N82: =N81*2 -> 0
A83: =C83*F83 -> 1.5442247e+09 | B83: =ROUND(F83*D83,0) -> 614983967 | C83: =D83*$N$19 -> 873878.22 | D83: 348020 | E83: کد 591731- ردیف 3 | F83: =F77 -> 1767.0938 | G83: M2 | J83: مصالح رنگ خارجی پرایمر | K83: 8.1.14
A84: =C84*F84 -> 4.2812502e+09 | B84: =ROUND(F84*D84,0) -> 1704998076 | C84: =D84*$N$19 -> 1211381.7 | D84: 482430 | E84: کد 591731- ردیف 12 | F84: =2*F83 -> 3534.1875 | G84: M2 | J84: مصالح رنگ خارجی بدنه نهایی و میانی | K84: 8.1.15
A85: =C85*F85 -> 6.0651044e+09 | B85: =ROUND(F85*D85,0) -> 2415413940 | C85: =D85*$N$19 -> 1211381.7 | D85: 482430 | E85: کد 591731- ردیف 12 | F85: =3*F79 -> 5006.7656 | G85: M2 | J85: مصالح رنگ داخلی بدنه و کف (سه لایه پرایمر،میانی و نهایی) | K85: 8.1.16
A86: =C86*F86 -> 1.48294e+09 | B86: =ROUND(F86*D86,0) -> 590577457 | C86: =D86*$N$19 -> 201407.31 | D86: 80210 | E86: کد591901ردیف 2 | F86: =M69^2*3.1415*M70/4 -> 7362.8906 | G86: M3 | J86: تست هیدرواستاتیک | K86: 8.1.17
A87: =C87*F87 -> 39632949 | B87: =ROUND(F87*D87,0) -> 15783731 | C87: =D87*$N$19 -> 53233.2 | D87: 21200 | E87: کد591921 | F87: =15*((M70/1.5)*3+2*M69*3.1415/8) -> 744.51563 | G87: CM | J87: آزمایش پرتو نگاری | K87: 8.1.18
A88: =C88*F88 -> 0 | B88: =ROUND(F88*D88,0) -> 0 | H88: TK | I88: -101 | J88: DILUTION WATER TANK : نصب و اجرای مخزن | K88: 8.2 | M88: 12.5 | N88: 62000
A89: =C89*F89 -> 3.0543096e+08 | B89: =ROUND(F89*D89,0) -> 121637180 | C89: =D89*$N$19 -> 4926305.8 | D89: 1961890 | E89: کد 591301 - ردیف 1 | F89: =N88/1000 -> 62 | G89: Ton | J89: تخلیه ، بار اندازی و صفافی مصالح | K89: 8.2.1 | M89: 12
A90: =C90*F90 -> 1.4872411e+09 | B90: =ROUND(F90*D90,0) -> 592290356 | C90: =D90*$N$19 -> 1.5438838e+08 | D90: 61484820 | E90: کد 591302 - ردیف 1 | F90: =N90/1000 -> 9.6331152 | G90: Ton | J90: نصب و جوشکاری کف مخزن | K90: 8.2.2 | N90: =M88^2*0.25*3.1415*0.01*7850 -> 9633.1152
A91: =C91*F91 -> 8.5475842e+09 | B91: =ROUND(F91*D91,0) -> 3404055835 | C91: =D91*$N$19 -> 2.3130398e+08 | D91: 92116280 | E91: کد 591303 - ردیف 1 | F91: =N91/1000 -> 36.9539 | G91: Ton | J91: نصب و جوشکاری بدنه مخزن | K91: 8.2.3 | N91: =N88-N90-N92-N93 -> 36953.9
A92: =C92*F92 -> 1.5083338e+09 | B92: =ROUND(F92*D92,0) -> 600690471 | C92: =D92*$N$19 -> 1.9572248e+08 | D92: 77946030 | E92: کد 591304 - ردیف 1 | F92: =N92/1000 -> 7.7064922 | G92: Ton | J92: نصب و جوشکاری سقف ثابت مخزن | K92: 8.2.4 | N92: =M88^2*0.25*3.1415*0.008*7850 -> 7706.4922
A93: =C93*F93 -> 1.8733705e+09 | B93: =ROUND(F93*D93,0) -> 746065509 | C93: =D93*$N$19 -> 243089.91 | D93: 96810 | E93: کد 591308 | F93: =N93 -> 7706.4922 | G93: Kg | J93: نصب و جوشکاری سازه سقف ثابت مخزن | K93: 8.2.5 | N93: =N92 -> 7706.4922
A94: =C94*F94 -> 7.2122198e+08 | B94: =ROUND(F94*D94,0) -> 287225000 | C94: =D94*$N$19 -> 288488.79 | D94: 114890 | E94: کد 591307 | F94: 2500 | G94: Kg | J94: نصب و جوشکاری پله بدنه | K94: 8.2.6
A95: =C95*F95 -> 1.7079724e+08 | B95: =ROUND(F95*D95,0) -> 68019611 | C95: =D95*$N$19 -> 1391822.2 | D95: 554290 | E95: کد 591741 - ردیف 1 | F95: =M88^2*3.1415/4 -> 122.71484 | G95: M2 | J95: سند بلاست کف مخازن سقف ثابت | K95: 8.2.7
A96: =C96*F96 -> 1.0329848e+09 | B96: =ROUND(F96*D96,0) -> 411383843 | C96: =D96*$N$19 -> 1670191.7 | D96: 665150 | E96: کد 591741 - ردیف 3 | F96: =1.2*F95+3.1415*M88*M89 -> 618.48281 | G96: M2 | J96: سند بلاست بدنه خارجی مخازن و سقف ثابت | K96: 8.2.8 | N96: =M93^2*0.25*3.1415*0.01*7850*2 -> 0
A97: =C97*F97 -> 57385458 | B97: =ROUND(F97*D97,0) -> 22853627 | C97: =D97*$N$19 -> 208764.54 | D97: 83140 | E97: کد 591741 - ردیف 4 | F97: =3.1415*M88*(M89-5) -> 274.88125 | G97: M2 | J97: اضافه بهای سند بلاست بابت ارتفاع بیش از 5 متر | K97: 8.2.9
A98: =C98*F98 -> 9.9199337e+08 | B98: =ROUND(F98*D98,0) -> 395059087 | C98: =D98*$N$19 -> 1670191.7 | D98: 665150 | E98: کد 591741 - ردیف 3 | F98: =F95+3.1415*M88*M89 -> 593.93984 | G98: M2 | J98: سند بلاست بدنه داخلی مخازن و کف | K98: 8.2.10 | N98: =M95^2*0.25*3.1415*0.01*7850*2 -> 0
A99: =C99*F99 -> 57385458 | B99: =ROUND(F99*D99,0) -> 22853627 | C99: =D99*$N$19 -> 208764.54 | D99: 83140 | E99: کد 591741 - ردیف 4 | F99: =F97 -> 274.88125 | G99: M2 | J99: اضافه بهای سند بلاست داخلی بابت ارتفاع بیش از 5 متر | K99: 8.2.11 | N99: =2*N95-N98-N102-N103 -> 0
A100: =C100*F100 -> 3.9978923e+08 | B100: =ROUND(F100*D100,0) -> 159215147 | C100: =D100*$N$19 -> 299436.75 | D100: 119250 | E100: کد 591742 - ردیف 2 | F100: =F95+F96+F98 -> 1335.1375 | G100: M2 | J100: رنگ امیزی سطوح داخل و خارج مخزنها | K100: 8.2.12 | N100: =M93^2*0.25*3.1415*0.008*7850*2 -> 0
A101: =C101*F101 -> 19685269 | B101: =ROUND(F101*D101,0) -> 7839613 | C101: =D101*$N$19 -> 35806.86 | D101: 14260 | E101: کد 591742 - ردیف 3 | F101: =F97+F99 -> 549.7625 | G101: M2 | J101: اضافه بهای رنگ امیزی بابت ارتفاع بیش از 5 متر | K101: 8.2.13 | N101: =N100*2 -> 0
A102: =C102*F102 -> 5.4047866e+08 | B102: =ROUND(F102*D102,0) -> 215244388 | C102: =D102*$N$19 -> 873878.22 | D102: 348020 | E102: کد 591731- ردیف 3 | F102: =F96 -> 618.48281 | G102: M2 | J102: مصالح رنگ خارجی پرایمر | K102: 8.2.14
...

Sheet C.PIPELINE
A1: جدول 14 - برآورد اجرا ی خطوط لوله بر اساس فهرست بهای اختصاصی تاسیسات نفت و گاز، رشته خطوط لوله روزمینی جریانی نفت و گاز 1401 -
A2: هزینه تمام شده مطابق فهرست بها | B2: مبلغ بدون اعمال ضرایب | C2: بهای واحد بــها با اعمال ضریب | D2: بهای واحد بــها بدون اعمال ضریب | E2: ردیف فهرست بهای نفت سال 1401 | F2: مقدار | G2: واحد | H2: شرح | J2: ردیف
M4: =ROUND(N5*N6*N7*N8,3) -> 2.413 | N4: ضریب
F5: 400 | G5: متر | H5: احداث خط لوله انتقال نفت نمکی 20 اینچ روزمینی با جنسAPI 5L GR.X52/SCH.30/NACE از واحد بهره برداری گچساران 4 به واحد نمک زدایی گچساران 4 به طول تقریبی 1500 متر و شامل الکترود و تست هیدرواستاتیک | J5: 1 | M5: منطقه ای گچساران. | N5: 1.11
F6: 400 | G6: متر | H6: احداث خط لوله انتقال نفت نمک زدایی شده 20 اینچ روزمینی با جنس API 5L GR.X52/SCH.30/NACE از واحد نمک زدایی گچساران 4 به واحد بهره برداری گچساران 4 به طول تقریبی 1500 متر. | J6: 2 | M6: بالاسری | N6: 1.48
A7: =ROUND(C7*F7,0) -> 343340944 | B7: =ROUND(F7*D7,0) -> 142288000 | C7: =D7*$M$4 -> 429176.18 | D7: 177860 | E7: 560101009 | F7: 800 | G7: متر | I7: عملیات ریسه کردن | J7: 2.1 | M7: تجهیزکارگاه | N7: 1
A8: =ROUND(C8*F8,0) -> 4092367062 | B8: =ROUND(F8*D8,0) -> 1695966458 | C8: =D8*$M$4 -> 30313830 | D8: =11964490*1.05 -> 12562714 | E8: 560209008 | F8: 135 | G8: سرجوش | I8: عملیات خم زدن و جوشکاری لوله 20" با ضخامت 0.5" | J8: 2.2 | M8: بروزرسانی | N8: 1.469
A9: =ROUND(C9*F9,0) -> 1411473612 | B9: =ROUND(F9*D9,0) -> 584945550 | C9: =D9*$M$4 -> 10455360 | D9: 4332930 | E9: 56301009 | F9: 135 | G9: سرجوش | I9: پرتو نگاری از جوش لوله، شیر واتصالات فولادی 20" | J9: 2.3
A10: =ROUND(C10*F10,0) -> 1789307064 | B10: =ROUND(F10*D10,0) -> 741528000 | C10: =D10*$M$4 -> 2236633.8 | D10: 926910 | E10: 560401009 | F10: 800 | G10: متر | I10: زنگ زدایی و پرایمر زنی لوله 20" با ماسه پاشی در کارگاه پابت | J10: 2.4
A11: =ROUND(C11*F11,0) -> 1445271176 | B11: =ROUND(F11*D11,0) -> 598952000 | C11: =D11*$M$4 -> 1806589 | D11: 748690 | E11: 560404009 | F11: 800 | G11: متر | I11: اجرای یک لایه ضد زنگ و دولایه رنگ روی قطر 20" | J11: 2.5
A12: =ROUND(C12*F12,0) -> 292786760 | B12: =ROUND(F12*D12,0) -> 121337240 | C12: =D12*$M$4 -> 73196690 | D12: 30334310 | E12: 560501012 | F12: 4 | G12: عدد | I12: نصب شیر 20" تا کلاس 600در هر نقطه از طول خط لوله | J12: 2.6
A13: =ROUND(C13*F13,0) -> 74280248 | B13: =ROUND(F13*D13,0) -> 30783360 | C13: =D13*$M$4 -> 18570062 | D13: 7695840 | E13: 560502012 | F13: 4 | G13: جفت | I13: اتصال یک جفت فلنج 20" تا کلاس 600 در هر نقطه از خط | J13: 2.7
A14: =ROUND(C14*F14,0) -> 1102331900 | B14: =ROUND(F14*D14,0) -> 456830460 | C14: =D14*$M$4 -> 5.5116595e+08 | D14: 228415230 | E14: 560504009 | F14: 2 | G14: عدد | I14: اتصال گرم خط لوله به قطر 20" به لوله اصلی | J14: 2.8
A15: =ROUND(C15*F15,0) -> 551129200 | B15: =ROUND(F15*D15,0) -> 228400000 | C15: =D15*$M$4 -> 688911.5 | D15: 285500 | E15: 560701008 | F15: 800 | G15: متر | I15: آزمایش هیدرواستیتک خط لوله به قطر 20" | J15: 2.9
B16: =ROUND(F16*D16,0) -> 0 | F16: 17000 | G16: m | I16: تعویض خط لوله انتقال نفت از واحد بهره برداری پازنان به واحد بهره برداری گچساران 3 با سایز 12 اینچ | J16: 3
A17: =ROUND(C17*F17,0) -> 4766229990 | B17: =ROUND(F17*D17,0) -> 1975230000 | C17: =D17*$M$4 -> 280366.47 | D17: 116190 | E17: 560101005 | F17: 17000 | G17: متر | I17: عملیات ریسه کردن | J17: 3.1
A18: =ROUND(C18*F18,0) -> 48240250078 | B18: =ROUND(F18*D18,0) -> 19991815200 | C18: =D18*$M$4 -> 16926404 | D18: =1.05*6680640 -> 7014672 | E18: 560205009 | F18: 2850 | G18: سرجوش | I18: عملیات خم زدن و جوشکاری لوله 12" تا ضخامت 0.5" | J18: 3.2
A19: =ROUND(C19*F19,0) -> 19158911136 | B19: =ROUND(F19*D19,0) -> 7939872000 | C19: =D19*$M$4 -> 6722425 | D19: 2785920 | E19: 560301005 | F19: 2850 | G19: سرجوش | I19: پرتو نگاری از جوش لوله، شیر واتصالات فولادی 12" | J19: 3.3
A20: =ROUND(C20*F20,0) -> 22535296560 | B20: =ROUND(F20*D20,0) -> 9339120000 | C20: =D20*$M$4 -> 1325605.7 | D20: 549360 | E20: 560401005 | F20: 17000 | G20: متر | I20: زنگ زدایی و پرایمر زنی لوله 12" با ماسه پاشی در کارگاه پابت | J20: 3.4
A21: =ROUND(C21*F21,0) -> 18466013360 | B21: =ROUND(F21*D21,0) -> 7652720000 | C21: =D21*$M$4 -> 1086236.1 | D21: 450160 | E21: 560404005 | F21: 17000 | G21: متر | I21: اجرای یک لایه ضد زنگ و دولایه رنگ روی قطر 12" | J21: 3.5
A22: =ROUND(C22*F22,0) -> 175672095 | B22: =ROUND(F22*D22,0) -> 72802360 | C22: =D22*$M$4 -> 43918024 | D22: 18200590 | E22: 560501008 | F22: 4 | G22: عدد | I22: نصب شیر 12" تا کلاس 600در هر نقطه از طول خط لوله | J22: 3.6
A23: =ROUND(C23*F23,0) -> 44568110 | B23: =ROUND(F23*D23,0) -> 18470000 | C23: =D23*$M$4 -> 11142028 | D23: 4617500 | E23: 560502008 | F23: 4 | G23: جفت | I23: اتصال یک جفت فلنج 12" تا کلاس 600 در هر نقطه از خط | J23: 3.7
A24: =ROUND(C24*F24,0) -> 822392965 | B24: =ROUND(F24*D24,0) -> 340817640 | C24: =D24*$M$4 -> 4.1119648e+08 | D24: 170408820 | E24: 560504005 | F24: 2 | G24: عدد | I24: اتصال گرم خط لوله به قطر 12" به لوله اصلی | J24: 3.8
A25: =ROUND(C25*F25,0) -> 6780047400 | B25: =ROUND(F25*D25,0) -> 2809800000 | C25: =D25*$M$4 -> 565003.95 | D25: 234150 | E25: 560701005 | F25: 12000 | G25: متر | I25: آزمایش هیدرواستیتک خط لوله به قطر 12" | J25: 3.9
B26: =ROUND(F26*D26,0) -> 0 | F26: 1000 | G26: m | H26: جابجایی حدود 1900 متر از خط لوله 4 اینچ فشار بالای گاز موجود در سمت شرق سایت و احداث مجدد آن در فاصله حداقل 200 متر از حصار تسهیلات بیرون واحد. لازم به ذکر است در این زمینه حریمهای مجاز فاصله از خطوط لوله و تاسیسات مطابق با ضوابط اغلام شده در آیین نامه مناطق نفتخیز جنوب باید مد نظر قرار گیرد. | J26: 4
A27: =ROUND(C27*F27,0) -> 388232396 | B27: =ROUND(F27*D27,0) -> 160892000 | C27: =D27*$M$4 -> 204332.84 | D27: 84680 | E27: 560101001 | F27: 1900 | G27: متر | I27: عملیات ریسه کردن | J27: 4.1
A28: =ROUND(C28*F28,0) -> 3315483717 | B28: =ROUND(F28*D28,0) -> 1374009000 | C28: =D28*$M$4 -> 9472810.6 | D28: =3738800*1.05 -> 3925740 | E28: 560201009 | F28: 350 | G28: سرجوش | I28: عملیات خم زدن و جوشکاری لوله 4" تا ضخامت0.674" | J28: 4.2
A29: =ROUND(C29*F29,0) -> 1232308242 | B29: =ROUND(F29*D29,0) -> 510695500 | C29: =D29*$M$4 -> 3520880.7 | D29: 1459130 | E29: 560301001 | F29: 350 | G29: سرجوش | I29: پرتو نگاری از جوش لوله، شیر واتصالات فولادی 4" | J29: 4.3
A30: =ROUND(C30*F30,0) -> 942293391 | B30: =ROUND(F30*D30,0) -> 390507000 | C30: =D30*$M$4 -> 495943.89 | D30: 205530 | E30: 560401001 | F30: 1900 | G30: متر | I30: زنگ زدایی و پرایمر زنی لوله 4" با ماسه پاشی در کارگاه پابت | J30: 4.4
A31: =ROUND(C31*F31,0) -> 695178061 | B31: =ROUND(F31*D31,0) -> 288097000 | C31: =D31*$M$4 -> 365883.19 | D31: 151630 | E31: 560404001 | F31: 1900 | G31: متر | I31: اجرای یک لایه ضد زنگ و دولایه رنگ روی قطر 4" | J31: 4.5
A32: =ROUND(C32*F32,0) -> 31365284 | B32: =ROUND(F32*D32,0) -> 12998460 | C32: =D32*$M$4 -> 15682642 | D32: 6499230 | E32: 560501004 | F32: 2 | G32: عدد | I32: نصب شیر 4" تا کلاس 600در هر نقطه از طول خط لوله | J32: 4.6
A33: =ROUND(C33*F33,0) -> 21710533 | B33: =ROUND(F33*D33,0) -> 8997320 | C33: =D33*$M$4 -> 5427633.3 | D33: 2249330 | E33: 560502004 | F33: 4 | G33: جفت | I33: اتصال یک جفت فلنج 4" تا کلاس 600 در هر نقطه از خط | J33: 4.7
A34: =ROUND(C34*F34,0) -> 342499772 | B34: =ROUND(F34*D34,0) -> 141939400 | C34: =D34*$M$4 -> 1.7124989e+08 | D34: 70969700 | E34: 560504001 | F34: 2 | G34: عدد | I34: اتصال گرم خط لوله به قطر 4" به لوله اصلی | J34: 4.8
A35: =ROUND(C35*F35,0) -> 424929300 | B35: =ROUND(F35*D35,0) -> 176100000 | C35: =D35*$M$4 -> 424929.3 | D35: 176100 | E35: 560701001 | F35: 1000 | G35: متر | I35: آزمایش هیدرواستیتک خط لوله به قطر 4" | J35: 4.9
B36: =ROUND(F36*D36,0) -> 0 | F36: 500 | G36: m | H36: احداث خط لوله انتقال گاز 6 اینچ فلزی با جنس API5L GR.X52/SCH.80/NACE به صورت روزمینی از واحد بهره برداری گچساران 4 به واحد نمک زدایی گچساران 4 | J36: 5
B37: =ROUND(F37*D37,0) -> 0 | F37: 500 | H37: ·احداث خط انتقال آب 6 اینچ فلزی با جنس API 5L0 به صورت رو زمینی از تصفیه خانه خیر آباد به واحدنمکزدایی گچساران-4 | J37: 6
A38: =ROUND(C38*F38,0) -> 217218260 | B38: =ROUND(F38*D38,0) -> 90020000 | C38: =D38*$M$4 -> 217218.26 | D38: 90020 | E38: 560101002 | F38: 1000 | G38: متر | I38: عملیات ریسه کردن | J38: 6.1
A39: =ROUND(C39*F39,0) -> 2358691333 | B39: =ROUND(F39*D39,0) -> 977493300 | C39: =D39*$M$4 -> 11793457 | D39: =1.05*4654730 -> 4887466.5 | E39: 560202009 | F39: 200 | G39: سرجوش | I39: عملیات خم زدن و جوشکاری لوله 6"تاا ضخامت 0.5" | J39: 6.2
A40: =ROUND(C40*F40,0) -> 871918246 | B40: =ROUND(F40*D40,0) -> 361342000 | C40: =D40*$M$4 -> 4359591.2 | D40: 1806710 | E40: 560301002 | F40: 200 | G40: سرجوش | I40: پرتو نگاری از جوش لوله، شیر واتصالات فولادی 6" | J40: 6.3
A41: =ROUND(C41*F41,0) -> 713017370 | B41: =ROUND(F41*D41,0) -> 295490000 | C41: =D41*$M$4 -> 713017.37 | D41: 295490 | E41: 560401002 | F41: 1000 | G41: متر | I41: زنگ زدایی و پرایمر زنی لوله 6" با ماسه پاشی در کارگاه پابت | J41: 6.4
A42: =ROUND(C42*F42,0) -> 537399230 | B42: =ROUND(F42*D42,0) -> 222710000 | C42: =D42*$M$4 -> 537399.23 | D42: 222710 | E42: 560404002 | F42: 1000 | G42: متر | I42: اجرای یک لایه ضد زنگ و دولایه رنگ روی قطر 6" | J42: 6.5
A43: =ROUND(C43*F43,0) -> 0 | B43: =ROUND(F43*D43,0) -> 0 | C43: =D43*$M$4 -> 19603309 | D43: 8124040 | E43: 560501005 | G43: عدد | I43: نصب شیر 6" تا کلاس 600در هر نقطه از طول خط لوله | J43: 6.6
A44: =ROUND(C44*F44,0) -> 0 | B44: =ROUND(F44*D44,0) -> 0 | C44: =D44*$M$4 -> 6383374.3 | D44: 2645410 | E44: 560502005 | G44: جفت | I44: اتصال یک جفت فلنج 6" تا کلاس 600 در هر نقطه از خط | J44: 6.7
A45: =ROUND(C45*F45,0) -> 218819310 | B45: =ROUND(F45*D45,0) -> 90683510 | C45: =D45*$M$4 -> 2.1881931e+08 | D45: 90683510 | E45: 560504002 | F45: 1 | G45: عدد | I45: اتصال گرم خط لوله به قطر 6" به لوله اصلی | J45: 6.8
A46: =ROUND(C46*F46,0) -> 463899250 | B46: =ROUND(F46*D46,0) -> 192250000 | C46: =D46*$M$4 -> 463899.25 | D46: 192250 | E46: 560701002 | F46: 1000 | G46: متر | I46: آزمایش هیدرواستیتک خط لوله به قطر 6" | J46: 6.9
A47: =ROUND(C47*F47,0) -> 47935789320 | B47: =ROUND(F47*D47,0) -> 19865640000 | C47: =D47*$M$4 -> 7989298.2 | D47: =380000*Q48 -> 3310940 | E47: خارج از فهرست بها | F47: 6000 | G47: m | H47: احداث دو خط لوله انتقال پساب غیر فلزی با جنس RTP زیر زمینی از واحدنمکزدایی گچساران-4 به چاههای تزریق در فاصله تقریبی 3 کیلومتر برای هر خط لوله. | J47: 7 | N47: 4/1400 | O47: 4356.5
A48: =ROUND(C48*F48,0) -> 3994649110 | B48: =ROUND(F48*D48,0) -> 1655470000 | C48: =D48*$M$4 -> 7989298.2 | D48: =380000*Q48 -> 3310940 | E48: خارج از فهرست بها | F48: 500 | G48: m | H48: احداث خط لوله انتقال آب ازاد غیر فلزی با جنس RTP زیر زمینی از واحد بهره برداری گچساران-4 به واحدنمکزدایی گچساران-4 | J48: 8 | N48: 4/1391 | O48: 500 | Q48: =ROUND(O47/O48,3) -> 8.713
A49: =ROUND(C49*F49,0) -> 26806197975 | B49: =ROUND(F49*D49,0) -> 11109075000 | C49: =D49*$M$4 -> 3153670.3 | D49: =150000*Q48 -> 1306950 | E49: خارج از فهرست بها | F49: 8500 | G49: m | H49: خط لوله آب "6 از چاههای لیشتر با جنس PE-100 به طول تقریبی | J49: 9
A50: =ROUND(C50*F50,0) -> 40209296963 | B50: =ROUND(F50*D50,0) -> 16663612500 | C50: =D50*$M$4 -> 4730505.5 | D50: =225000*Q48 -> 1960425 | E50: خارج از فهرست بها | F50: 8500 | G50: m | H50: خط لوله "10 آب آتش نشانی اتصال بین دو واحد با جنس PE-100 به طول تقریبی 500متر | J50: 10
A51: =SUM(A5:A50) -> 263812566723 | B51: =SUM(B5:B50) -> 109329700258 | H51: مجموع | J51: 11
A53: =SUM(A5:A46)/10+A47+A48+A49+A50 -> 1.334326e+11

Sheet C.ELECTRICAL
A1: جدول 15 - برآورد اجرای عملیات برق و مخابرات و کابل کشی بر اساس فهرست بهای اختصاصی تاسیسات نفت و گاز، رشته نصب واحدهای بهره برداری نفت و گاز -1401
A2: هزینه تمام شده مطابق فهرست بها | B2: مبلغ بدون اعمال ضرایب | C2: بهای واحد بــها با اعمال ضریب | D2: بهای واحد بــها بدون اعمال ضریب | E2: ردیف فهرست بهای نفت سال 1401 | F2: مقدار | G2: واحد | H2: شرح | I2: ردیف
A5: =ROUND(C5*F5,0) -> 716960650 | B5: =ROUND(F5*D5,0) -> 290150000 | C5: =D5*$L$6 -> 143392.13 | D5: 58030 | E5: کد 592401 - ردیف 04 | F5: 5000 | G5: Kg | H5: نصب پنل برق MV Switchgear, 33KV, 630A, 3 (with approximately 15 cell)/Location:33KV station | I5: 1 | O5: 1 | P5: SET
A6: =ROUND(C6*F6,0) -> 370761195 | B6: =ROUND(F6*D6,0) -> 150045000 | C6: =D6*$L$6 -> 105931.77 | D6: 42870 | E6: کد 592401 - ردیف 06 | F6: 3500 | G6: Kg | H6: نصب پنل برق MV Switchgear, 3.3KV, 1250A,(with approximately 9 cell) /Location: DE4 Outdoor station | I6: 2 | K6: ضریب = | L6: =ROUND(L8*L9*L10*L11,3) -> 2.471 | O6: 1 | P6: SET
A7: =ROUND(C7*F7,0) -> 423727080 | B7: =ROUND(F7*D7,0) -> 171480000 | C7: =D7*$L$6 -> 105931.77 | D7: 42870 | E7: کد 592401 - ردیف 06 | F7: 4000 | G7: Kg | H7: نصب پنل برق MV Switchgear, 3.3KV, 630A, 3 phase +E, (with approximately 12 cell)/Location:DE4 | I7: 3 | O7: 1 | P7: SET
A8: =ROUND(C8*F8,0) -> 788656715 | B8: =ROUND(F8*D8,0) -> 319165000 | C8: =D8*$L$6 -> 143392.13 | D8: 58030 | E8: کد 592401 - ردیف 04 | F8: 5500 | G8: Kg | H8: LV Switchgear, 400V, 4000A/Location: DE4 | I8: 4 | K8: منطقه ای گچساران. | L8: 1.12 | O8: 1 | P8: SET
A9: =ROUND(C9*F9,0) -> 317795310 | B9: =ROUND(F9*D9,0) -> 128610000 | C9: =D9*$L$6 -> 105931.77 | D9: 42870 | E9: کد 592401 - ردیف 06 | F9: 3000 | G9: Kg | H9: نصب پنل برق 33 KV transformer bay,(2 SET) | I9: 5 | K9: بالاسری | L9: 1.48 | O9: 2 | P9: SET
A10: =ROUND(C10*F10,0) -> 370761195 | B10: =ROUND(F10*D10,0) -> 150045000 | C10: =D10*$L$6 -> 105931.77 | D10: 42870 | E10: کد 592401 - ردیف 06 | F10: 3500 | G10: Kg | H10: نصب پنل برق MV Switchgear, 3.3KV, 630A, (with approximately 9 cell). /Location:Production un | I10: 6 | K10: تجهیزکارگاه | L10: 1 | O10: 1 | P10: SET
A11: =ROUND(C11*F11,0) -> 286784260 | B11: =ROUND(F11*D11,0) -> 116060000 | C11: =D11*$L$6 -> 143392.13 | D11: 58030 | E11: کد 592401 - ردیف 04 | F11: 2000 | G11: Kg | H11: نصب پنل برق GACHSARAN 4-DESALTING UNIT EDP,400V SWITCHGEAR (EDP) | I11: 7 | K11: بروزرسانی | L11: 1.491 | O11: 2 | P11: SET
A12: =C12*F12 -> 0 | C12: =D12*$L$6 -> 0 | F12: 1 | G12: Kg | H12: MV Switchgear, 3.3KV, 1000A, نصب تابلو | I12: 8 | L12: 33 KV transformer bay, withdrawable, outdoor type with OCB and all protection and metering devises in accordance to Dwg no. M9003-EB-EL-SLD-21026
A13: =ROUND(C13*F13,0) -> 212382450 | B13: =ROUND(F13*D13,0) -> 85950000 | C13: =D13*$L$6 -> 84952.98 | D13: 34380 | E13: کد 592411 - ردیف 01 | F13: 2500 | G13: Kg | H13: نصب تابلو روشنایی 37 عدد | I13: 8
A14: =ROUND(C14*F14,0) -> 1869407869 | B14: =ROUND(F14*D14,0) -> 756539000 | C14: =D14*$L$6 -> 2670582.7 | D14: 1080770 | E14: کد 592841 ردیف 1 | F14: 700 | G14: Kg | H14: NGRنصب | I14: 9
A15: =ROUND(C15*F15,0) -> 2071765472 | B15: =ROUND(F15*D15,0) -> 838432000 | C15: =D15*$L$6 -> 10358827 | D15: 4192160 | E15: کد 592451 ستون 1 | F15: 200 | G15: Kg | H15: نصب 62 عدد تابلوی محلی | I15: 10
A16: =ROUND(C16*F16,0) -> 1736910378 | B16: =ROUND(F16*D16,0) -> 702918000 | C16: =D16*$L$6 -> 8684551.9 | D16: 3514590 | E16: کد 592451 ستون 2 | F16: 200 | H16: نصب 62 عدد تابلوی محلی ضد انفجار
A17: =ROUND(C17*F17,0) -> 84631750 | B17: =ROUND(F17*D17,0) -> 34250000 | C17: =D17*$L$6 -> 16926.35 | D17: 6850 | E17: کد 592801 - ردیف 01 - ستون 2 | F17: 5000 | G17: Kg | H17: پیش راه اندازی و راه اندازی پنل برق MV Switchgear, 33KV, 630A, 3 (with approximately 15 cell)/Location:33KV station | I17: 11
A18: =ROUND(C18*F18,0) -> 54831490 | B18: =ROUND(F18*D18,0) -> 22190000 | C18: =D18*$L$6 -> 15666.14 | D18: 6340 | E18: کد 592801 - ردیف 01 - ستون 1 | F18: 3500 | G18: Kg | H18: پیش راه اندازی و راه اندازی پنل برق MV Switchgear, 3.3KV, 1250A,(with approximately 9 cell) /Location: DE4 Outdoor station | I18: 12
A19: =ROUND(C19*F19,0) -> 62664560 | B19: =ROUND(F19*D19,0) -> 25360000 | C19: =D19*$L$6 -> 15666.14 | D19: 6340 | E19: کد 592801 - ردیف 01 - ستون 1 | F19: 4000 | G19: Kg | H19: پیش راه اندازی و راه اندازی پنل برق MV Switchgear, 3.3KV, 630A, 3 phase +E, (with approximately 12 cell)/Location:DE4 | I19: 13
A20: =ROUND(C20*F20,0) -> 705485326 | B20: =ROUND(F20*D20,0) -> 285506000 | C20: =D20*$L$6 -> 3527426.6 | D20: 1427530 | E20: کد 592812 | F20: 200 | G20: OUTGOING | H20: LV Switchgear, 400V, 4000A/Location: DE4 | I20: 14
A21: =ROUND(C21*F21,0) -> 50779050 | B21: =ROUND(F21*D21,0) -> 20550000 | C21: =D21*$L$6 -> 16926.35 | D21: 6850 | E21: کد 592801 - ردیف 01 - ستون 2 | F21: 3000 | G21: Kg | H21: پیش راه اندازی و راه اندازی پنل برق 33 KV transformer bay,(2 SET) | I21: 15
A22: =ROUND(C22*F22,0) -> 54831490 | B22: =ROUND(F22*D22,0) -> 22190000 | C22: =D22*$L$6 -> 15666.14 | D22: 6340 | E22: کد 592801 - ردیف 01 - ستون 1 | F22: 3500 | G22: Kg | H22: پیش راه اندازی و راه اندازی پنل برق MV Switchgear, 3.3KV, 630A, (with approximately 9 cell). /Location:Production un | I22: 16
A23: =ROUND(C23*F23,0) -> 105822799 | B23: =ROUND(F23*D23,0) -> 42825900 | C23: =D23*$L$6 -> 3527426.6 | D23: 1427530 | E23: کد 592812 | F23: 30 | G23: OUTGOING | H23: پیش راه اندازی و راه اندازی پنل برق GACHSARAN 4-DESALTING UNIT EDP,400V SWITCHGEAR (EDP) | I23: 17
A24: =ROUND(C24*F24,0) -> 205834300 | B24: =ROUND(F24*D24,0) -> 83300000 | C24: =D24*$L$6 -> 82333.72 | D24: 33320 | E24: کد 592813 | F24: 2500 | G24: Kg | H24: پیش راه اندازی و راه اندازی تابلو روشنایی 37 عدد | I24: 18
A25: =ROUND(C25*F25,0) -> 1979271 | B25: =ROUND(F25*D25,0) -> 801000 | C25: =D25*$L$6 -> 6597.57 | D25: 2670 | E25: کد 592801 - ردیف 03 - ستون 1 | F25: 300 | G25: Kg | H25: پیش راه اندازی و راه اندازی 62 عدد تابلوی محلی | I25: 19
A26: =ROUND(C26*F26,0) -> 262123680 | B26: =ROUND(F26*D26,0) -> 106080000 | C26: =D26*$L$6 -> 43687.28 | D26: 17680 | E26: کد 592411 - ردیف 04 | F26: 6000 | G26: Kg | H26: TR1 : Power Transformer 2500 KVA, 3.3 / 0.42 Kv - TR1 نصب تارنسفورماتور | I26: 20
A27: =ROUND(C27*F27,0) -> 262123680 | B27: =ROUND(F27*D27,0) -> 106080000 | C27: =D27*$L$6 -> 43687.28 | D27: 17680 | E27: کد 592411 - ردیف 04 | F27: 6000 | G27: Kg | H27: 2500 KVA, 3.3 / 0.42 kV - TR2 نصب ترانسفورماتور | I27: 21
A28: =ROUND(C28*F28,0) -> 349498240 | B28: =ROUND(F28*D28,0) -> 141440000 | C28: =D28*$L$6 -> 43687.28 | D28: 17680 | E28: کد 592411 - ردیف 04 | F28: 8000 | G28: Kg | H28: 6000 KVA, 33 / 3.45kV- PTR1 نصب ترانسفورماتور | I28: 22
... A36: =ROUND(C36*F36,0) -> 127701280 | B36: =ROUND(F36*D36,0) -> 51680000 | C36: =D36*$L$6 -> 63850.64 | D36: 25840 | E36: کد 591034 - ردیف 01 | F36: 2000 | G36: Kg | H36: 0.4 kv, 180 KVA- نصب ژنراتور دیزل | I36: 30
A37: =C37*F37 -> 0 | C37: =D37*$L$6 -> 0 | F37: 1 | H37: UNINTERRUPTIBLE POWER SUPPLY (UPS) | I37: 32
A38: =ROUND(C38*F38,0) -> 5880980 | B38: =ROUND(F38*D38,0) -> 2380000 | C38: =D38*$L$6 -> 11761.96 | D38: 4760 | E38: کد 592821 - ردیف 01- ستون 1 | F38: 500 | G38: Kg | H38: UPS-1, 110V AC UPS, 80KW - نصب پکیج برق | I38: 31
A39: =ROUND(C39*F39,0) -> 3528588 | B39: =ROUND(F39*D39,0) -> 1428000 | C39: =D39*$L$6 -> 11761.96 | D39: 4760 | E39: کد 592821 - ردیف 01- ستون 1 | F39: 300 | G39: Kg | H39: DC-01, 110V DC UPS,13 KW - نصب پکیج برق | I39: 32
A40: =ROUND(C40*F40,0) -> 3528588 | B40: =ROUND(F40*D40,0) -> 1428000 | C40: =D40*$L$6 -> 11761.96 | D40: 4760 | E40: کد 592821 - ردیف 01- ستون 1 | F40: 300 | G40: Kg | H40: DC-02, 24V DC UPS, 18KW - نصب پکیج برق | I40: 33
A41: =ROUND(C41*F41,0) -> 3528588 | B41: =ROUND(F41*D41,0) -> 1428000 | C41: =D41*$L$6 -> 11761.96 | D41: 4760 | E41: کد 592821 - ردیف 01- ستون 1 | F41: 300 | G41: Kg | H41: DC-03, 110V DC UPS, 9 KW - نصب پکیج برق | I41: 34
A42: =ROUND(C42*F42,0) -> 3528588 | B42: =ROUND(F42*D42,0) -> 1428000 | C42: =D42*$L$6 -> 11761.96 | D42: 4760 | E42: کد 592821 - ردیف 01- ستون 1 | F42: 300 | G42: Kg | H42: DC-04, 110V DC UPS, 7.5 KW - نصب پکیج برق | I42: 35
A43: =ROUND(C43*F43,0) -> 3528588 | B43: =ROUND(F43*D43,0) -> 1428000 | C43: =D43*$L$6 -> 11761.96 | D43: 4760 | E43: کد 592821 - ردیف 01- ستون 1 | F43: 300 | G43: Kg | H43: DC-05, 110V DC UPS, 13 KW - نصب پکیج برق | I43: 36
A44: =ROUND(C44*F44,0) -> 849529800 | B44: =ROUND(F44*D44,0) -> 343800000 | C44: =D44*$L$6 -> 84952.98 | D44: 34380 | E44: کد 592411 - ردیف 01 | F44: 10000 | G44: Kg | H44: نصب باتری | I44: 37
A45: =ROUND(C45*F45,0) -> 42476490 | B45: =ROUND(F45*D45,0) -> 17190000 | C45: =D45*$L$6 -> 84952.98 | D45: 34380 | E45: کد 592411 - ردیف 01 | F45: 500 | G45: Kg | H45: UPS-1, 110V AC UPS, 80KW - پیش راه اندازی و راه اندازی پکیج برق | I45: 38
A46: =ROUND(C46*F46,0) -> 25485894 | B46: =ROUND(F46*D46,0) -> 10314000 | C46: =D46*$L$6 -> 84952.98 | D46: 34380 | E46: کد 592411 - ردیف 01 | F46: 300 | G46: Kg | H46: DC-01, 110V DC UPS,13 KW - پیش راه اندازی و راه اندازی پکیج برق | I46: 39
A47: =ROUND(C47*F47,0) -> 25485894 | B47: =ROUND(F47*D47,0) -> 10314000 | C47: =D47*$L$6 -> 84952.98 | D47: 34380 | E47: کد 592411 - ردیف 01 | F47: 300 | G47: Kg | H47: DC-02, 24V DC UPS, 18KW - پیش راه اندازی و راه اندازی پکیج برق | I47: 40
A48: =ROUND(C48*F48,0) -> 25485894 | B48: =ROUND(F48*D48,0) -> 10314000 | C48: =D48*$L$6 -> 84952.98 | D48: 34380 | E48: کد 592411 - ردیف 01 | F48: 300 | G48: Kg | H48: DC-03, 110V DC UPS, 9 KW - پیش راه اندازی و راه اندازی پکیج برق | I48: 41
A49: =ROUND(C49*F49,0) -> 25485894 | B49: =ROUND(F49*D49,0) -> 10314000 | C49: =D49*$L$6 -> 84952.98 | D49: 34380 | E49: کد 592411 - ردیف 01 | F49: 300 | G49: Kg | H49: DC-04, 110V DC UPS, 7.5 KW - پیش راه اندازی و راه اندازی پکیج برق | I49: 42
... A51: =ROUND(C51*F51,0) -> 590225655 | B51: =ROUND(F51*D51,0) -> 238861050 | C51: =D51*$L$6 -> 39348377 | D51: 15924070 | E51: کد 592421 - ردیف 03- ستون 1 | F51: 15 | G51: متر | H51: نصب باسداکت | I51: 44
A52: =C52*F52 -> 0 | C52: =D52*$L$6 -> 0 | F52: 1 | H52: Earting | I52: 45
A53: =ROUND(C53*F53,0) -> 141222592 | B53: =ROUND(F53*D53,0) -> 57152000 | C53: =D53*$L$6 -> 15023.68 | D53: 6080 | E53: کد 592101 ردیف 1 | F53: 9400 | G53: متر | H53: نصب اتصال زمین -سیم کشی | I53: 45
A54: =C54*F54 -> 0 | C54: =D54*$L$6 -> 0 | F54: 500 | H54: نصب اتصال زمین -سیم کشی | I54: 49
A55: =C55*F55 -> 0 | C55: =D55*$L$6 -> 0 | H55: 70 mm2 BARE STRANDED COPPER CONDUCTOR | I55: 50
A56: =C56*F56 -> 0 | C56: =D56*$L$6 -> 0 | F56: 2850 | H56: 70 mm2 INSULATED STRANDED COPPER, GREEN/YELLOW PVC COVERED | I56: 51
A57: =C57*F57 -> 0 | C57: =D57*$L$6 -> 0 | F57: 350 | H57: 35 mm2 INSULATED STRANDED COPPER, GREEN/YELLOW PVC COVERED | I57: 52
A58: =C58*F58 -> 0 | C58: =D58*$L$6 -> 0 | F58: 400 | H58: 16 mm2 INSULATED STRANDED COPPER, GREEN/YELLOW PVC COVERED | I58: 53
A59: =ROUND(C59*F59,0) -> 17180566 | B59: =ROUND(F59*D59,0) -> 6952880 | C59: =D59*$L$6 -> 780934.84 | D59: 316040 | E59: کد 592615 ردیف 1 | F59: 22 | G59: عدد | H59: نصب اتصال زمین تسمه مسی | I59: 46
A60: =ROUND(C60*F60,0) -> 245006816 | B60: =ROUND(F60*D60,0) -> 99152900 | C60: =D60*$L$6 -> 3101352.1 | D60: 1255100 | E60: کد 592612 ردیف 3 | F60: 79 | G60: عدد | H60: نصب اتصال زمین کدولد مسی | I60: 47
A61: =ROUND(C61*F61,0) -> 727172799 | B61: =ROUND(F61*D61,0) -> 294282800 | C61: =D61*$L$6 -> 2597045.7 | D61: 1051010 | E61: کد 592612 ردیف 2 | F61: 280 | G61: عدد | H61: نصب اتصال زمین کدولد مسی | I61: 48
A62: =C62*F62 -> 0 | C62: =D62*$L$6 -> 0 | F62: 160 | G62: عدد | H62: CADWELD,CARTRIDGE, FOR CROSS CONNECTION OF 70x70 mm2 | I62: 57
A63: =C63*F63 -> 0 | C63: =D63*$L$6 -> 0 | F63: 40 | G63: عدد | H63: CADWELD,CARTRIDGE, FOR TEE CONNECTION OF 70x35 mm2 | I63: 58
A64: =C64*F64 -> 0 | C64: =D64*$L$6 -> 0 | F64: 40 | G64: عدد | H64: CADWELD,CARTRIDGE, FOR TEE CONNECTION OF 70x16 mm2 | I64: 59
A65: =C65*F65 -> 0 | C65: =D65*$L$6 -> 0 | F65: 40 | G65: عدد | H65: CADWELD,CARTRIDGE, FOR CONNECTION OF 70 mm2 COPPER CONDUCTOR TO COPPER EARTH PLATE | I65: 60
A66: =C66*F66 -> 0 | C66: =D66*$L$6 -> 0 | F66: 68 | G66: عدد | H66: 10-WAY COPPER EARTH BAR,6mm THICKNESS,50 mm WIDE,700 mm LENGTH AND TWO WASHERS AND ONE NUT FOR EACH HOLE | I66: 61
A67: =ROUND(C67*F67,0) -> 2444970189 | B67: =ROUND(F67*D67,0) -> 989465880 | C67: =D67*$L$6 -> 15672886 | D67: 6342730 | E67: کد 592613 | F67: 156 | G67: عدد | H67: نصب اتصال زمین- الکنرود (میله) زمین | I67: 49
A68: =C68*F68 -> 0 | C68: =D68*$L$6 -> 0 | F68: 64 | G68: NO | H68: "U" bolt rod to cable clamp for nominal rod dia. 20 mm | I68: 63
A69: =C69*F69 -> 0 | C69: =D69*$L$6 -> 0 | F69: 24 | G69: NO | H69: TINNED COPPER COMPRESSION CABLE LUG FOR CABLE SIZE 120 mm2 | I69: 64
A70: =ROUND(C70*F70,0) -> 64121709 | B70: =ROUND(F70*D70,0) -> 25949700 | C70: =D70*$L$6 -> 916024.41 | D70: 370710 | E70: کد 592614 ردیف 1 | F70: 70 | G70: عدد | H70: نصب اتصال زمین- اتصال به تجهیزات | I70: 50
A71: =ROUND(C71*F71,0) -> 249648713 | B71: =ROUND(F71*D71,0) -> 101031450 | C71: =D71*$L$6 -> 1280249.8 | D71: 518110 | E71: کد 592614 ردیف 2 | F71: 195 | G71: عدد | H71: نصب اتصال زمین- اتصال به تجهیزات | I71: 51
A72: =C72*F72 -> 0 | C72: =D72*$L$6 -> 0 | F72: 121 | G72: عدد | H72: نصب اتصال زمین- اتصال به تجهیزات | I72: 67
A73: =C73*F73 -> 0 | C73: =D73*$L$6 -> 0 | F73: 49 | G73: عدد | H73: CONDUIT , HEAVY GUAGE HOT DIP GALVANIZED ,RIGID STEEL,DOUBLE SIDE ISO THREADED, LENGTH 3000mm, size: M50 | I73: 68
A74: =C74*F74 -> 0 | C74: =D74*$L$6 -> 0 | F74: 147 | G74: عدد | H74: Conduit clamp, m50 | I74: 69
A75: =C75*F75 -> 0 | C75: =D75*$L$6 -> 0 | F75: 1 | G75: عدد | H75: Spark gap | I75: 70
A76: =ROUND(C76*F76,0) -> 94243940 | B76: =ROUND(F76*D76,0) -> 38140000 | C76: =D76*$L$6 -> 235609.85 | D76: 95350 | E76: کد 592616 | F76: 400 | G76: Kg | H76: نصب اتصال زمین- مخلوط ذغال
A77: =ROUND(C77*F77,0) -> 48438889 | B77: =ROUND(F77*D77,0) -> 19602950 | C77: =D77*$L$6 -> 9687777.9 | D77: 3920590 | E77: کد 592621 ردیف 1 | F77: 5 | G77: عدد | H77: نصب صاعقه گیر | I77: 52
A78: =C78*G78 -> 0 | C78: =D78*$L$6 -> 0 | G78: 1 | H78: cable | I78: 64.333333
A79: =C79*G79 -> 0 | C79: =D79*$L$6 -> 0 | H79: 0.6/1 KV, Stranded Annealed Copper Conductor, PVC Insulated, Lead Sheath, Extruded PVC Bedding, Galvanized Steel Wire Armored, PVC Sheathed, Cu-PVC-Lsh-Bd-SWA-PVC Power Cable | I79: 64.761905
A80: =ROUND(C80*F80,0) -> 8506686839 | B80: =ROUND(F80*D80,0) -> 3442609000 | C80: =D80*$L$6 -> 203363.3 | D80: 82300 | E80: کد 592103 - ستون 1- ردیف 1 | F80: =SUM(F83:F87,F96:F98)*2+F81+F82 -> 41830 | G80: M | H80: کابل کشی کابل قدرت و کنترل - زیرزمینی -زره دار باغلاف سربی-0.6/1 KV | I80: 53
A81: =ROUND(C81*F81,0) -> 1249767060 | B81: =ROUND(F81*D81,0) -> 505773800 | C81: =D81*$L$6 -> 232298.71 | D81: 94010 | E81: کد 592103 - ستون 1- ردیف 2 | F81: =SUM(F88:F91,F93:F95) -> 5380 | G81: M | H81: کابل کشی کابل قدرت و کنترل - زیرزمینی -زره دار باغلاف سربی-0.6/1 KV | I81: 54
A82: =ROUND(C82*F82,0) -> 217960733 | B82: =ROUND(F82*D82,0) -> 88207500 | C82: =D82*$L$6 -> 290614.31 | D82: 117610 | E82: کد 592103 - ستون 1- ردیف 3 | F82: =F92 -> 750 | G82: M | H82: کابل کشی کابل قدرت و کنترل - زیرزمینی -زره دار باغلاف سربی-0.6/1 KV | I82: 55
A83: =C83*F83 -> 0 | C83: =D83*$L$6 -> 0 | F83: 8200 | G83: M | H83: 3C4 | I83: 56
A84: =C84*F84 -> 0 | C84: =D84*$L$6 -> 0 | G84: M | H84: 3C6 | I84: 57
A85: =C85*F85 -> 0 | C85: =D85*$L$6 -> 0 | F85: 2100 | G85: M | H85: 3C10 | I85: 58
A86: =C86*F86 -> 0 | C86: =D86*$L$6 -> 0 | F86: 4100 | G86: M | H86: 3C16 | I86: 59
A87: =C87*F87 -> 0 | C87: =D87*$L$6 -> 0 | F87: 550 | G87: M | H87: 3C25 | I87: 60
A88: =C88*F88 -> 0 | C88: =D88*$L$6 -> 0 | F88: 250 | G88: M | H88: 3C95 | I88: 61
A89: =C89*F89 -> 0 | C89: =D89*$L$6 -> 0 | G89: M | H89: 3C150 | I89: 62
A90: =C90*F90 -> 0 | C90: =D90*$L$6 -> 0 | G90: M | H90: 3C25+16 | I90: 63
A91: =C91*F91 -> 0 | C91: =D91*$L$6 -> 0 | F91: 200 | G91: M | H91: 3C150+70 | I91: 64
A92: =C92*F92 -> 0 | C92: =D92*$L$6 -> 0 | F92: 750 | G92: M | H92: 3C240+120 | I92: 65
A93: =C93*F93 -> 0 | C93: =D93*$L$6 -> 0 | F93: 280 | G93: M | H93: 3C95+50 | I93: 66
A94: =C94*F94 -> 0 | C94: =D94*$L$6 -> 0 | F94: 3900 | G94: M | H94: 3C70 | I94: 67
A95: =C95*F95 -> 0 | C95: =D95*$L$6 -> 0 | F95: 750 | G95: M | H95: 3C50 | I95: 68
A96: =C96*F96 -> 0 | C96: =D96*$L$6 -> 0 | F96: 1100 | G96: M | H96: 4C4 | I96: 69
A97: =C97*F97 -> 0 | C97: =D97*$L$6 -> 0 | F97: 1500 | G97: M | H97: 4C10 | I97: 70
A98: =C98*F98 -> 0 | C98: =D98*$L$6 -> 0 | F98: 300 | G98: M | H98: 4C16 | I98: 71
A99: =C99*F99 -> 0 | C99: =D99*$L$6 -> 0 | H99: 0.6/1 KV, Stranded Annealed Copper Conductor, PVC Insulated, Galvanized Steel Wire Armored, PVC Sheathed, Cu-PVC-SWA-PVC Power Cable | I99: 72
A100: =ROUND(C100*F100,0) -> 6093862828 | B100: =ROUND(F100*D100,0) -> 2466152500 | C100: =D100*$L$6 -> 183274.07 | D100: 74170 | E100: کد 592102 - ستون 1- ردیف 1 | F100: =SUM(F104:F109,F111:F113)*2+F102+F103+F101 -> 33250 | G100: M | H100: کابل کشی کابل قدرت و کنترل - زیرزمینی - زره دار-0.6/1 KV | I100: 56
A101: =ROUND(C101*F101,0) -> 282780005 | B101: =ROUND(F101*D101,0) -> 114439500 | C101: =D101*$L$6 -> 209466.67 | D101: 84770 | E101: کد 592102 - ستون 1- ردیف 2 | F101: =SUM(F110,F114:F116) -> 1350 | G101: M | H101: کابل کشی کابل قدرت و کنترل - زیرزمینی - زره دار-0.6/1 KV | I101: 57
A102: =ROUND(C102*F102,0) -> 3979219328 | B102: =ROUND(F102*D102,0) -> 1610368000 | C102: =D102*$L$6 -> 216261.92 | D102: 87520 | E102: کد 592102 - ستون2 - ردیف 2 | F102: =SUM(F118:F120) -> 18400 | G102: M | H102: کابل کشی کابل قدرت و کنترل - زیرزمینی - زره دار-3/6 KV | I102: 58
A103: =ROUND(C103*F103,0) -> 938016310 | B103: =ROUND(F103*D103,0) -> 379610000 | C103: =D103*$L$6 -> 268004.66 | D103: 108460 | E103: کد 592102 - ستون2 - ردیف 3 | F103: =SUM(F121:F122) -> 3500 | G103: M | H103: کابل کشی کابل قدرت و کنترل - زیرزمینی - زره دار-3/6 KV | I103: 59
A104: =C104*F104 -> 0 | C104: =D104*$L$6 -> 0 | F104: 2000 | G104: M | H104: 1C300 | I104: 60
A105: =C105*F105 -> 0 | C105: =D105*$L$6 -> 0 | F105: 150 | G105: M | H105: 3C4 | I105: 61
A106: =C106*F106 -> 0 | C106: =D106*$L$6 -> 0 | F106: 250 | G106: M | H106: 3C6 | I106: 62
A107: =C107*F107 -> 0 | C107: =D107*$L$6 -> 0 | F107: 300 | G107: M | H107: 3C16 | I107: 63
A108: =C108*F108 -> 0 | C108: =D108*$L$6 -> 0 | F108: 650 | G108: M | H108: 3C25 | I108: 64
A109: =C109*F109 -> 0 | C109: =D109*$L$6 -> 0 | F109: 500 | G109: M | H109: 3C25+16 | I109: 65
A110: =C110*F110 -> 0 | C110: =D110*$L$6 -> 0 | F110: 100 | G110: M | H110: 3C150+70 | I110: 66
...

Sheet C.INSTRUMENT
A1: جدول 16 - برآورد اجرا و نصب تجهیزات ابزاردقیق بر اساس فهرست بهای اختصاصی تاسیسات نفت و گاز، رشته نصب واحدهای بهره برداری نفت و گاز -1401 | P1: منطقه ای گچساران. | Q1: 1.12
A2: هزینه تمام شده مطابق فهرست بها | B2: مبلغ بدون اعمال ضرایب | C2: بهای واحد بــها با اعمال ضریب | D2: بهای واحد بــها بدون اعمال ضریب | E2: ردیف فهرست بهای نفت سال 1401 | F2: مقدار | G2: واحد | H2: شرح | I2: ردیف | M2: وزن واحد | P2: بالاسری | Q2: 1.48
P3: تجهیزکارگاه | Q3: 1
P4: بروزرسانی | Q4: 1.491
A5: =ROUND(C5*F5,0) -> 6846661800 | B5: =ROUND(F5*D5,0) -> 2770806000 | C5: =ROUND(D5*K5,0) -> 11411103 | D5: 4618010 | E5: کد 593133 ردیف 02 | F5: 600 | G5: کیلوگرم | H5: نصب سیستم های آنالایزر- بیشتر از 10 کیلوگرم | I5: 1 | K5: =ROUND(Q1*Q2*Q3*Q4,3) -> 2.471
A6: =ROUND(C6*F6,0) -> 1686748000 | B6: =ROUND(F6*D6,0) -> 682617600 | C6: =ROUND(D6*K6,0) -> 6024100 | D6: 2437920 | E6: کد 593133 ردیف 01 | F6: 280 | G6: کیلوگرم | H6: نصب سیستم های آنالایزر-تا 10 کیلوگرم | I6: 2 | K6: 2.471
A7: =ROUND(C7*F7,0) -> 548465097 | B7: =ROUND(F7*D7,0) -> 221960780 | C7: =ROUND(D7*K7,0) -> 14823381 | D7: 5998940 | E7: کد 593101 ردیف 02 | F7: 37 | G7: دستگاه | H7: نصب انتقال دهنده جریان | I7: 3 | K7: 2.471
A8: =ROUND(C8*F8,0) -> 182458444 | B8: =ROUND(F8*D8,0) -> 73839920 | C8: =ROUND(D8*K8,0) -> 13032746 | D8: 5274280 | E8: کد 593102 ردیف 04 | F8: 14 | G8: دستگاه | H8: نصب سوییچ جریان | I8: 4 | K8: 2.471
A9: =ROUND(C9*F9,0) -> 253015972 | B9: =ROUND(F9*D9,0) -> 102394160 | C9: =ROUND(D9*K9,0) -> 11500726 | D9: 4654280 | E9: کد 593111 ردیف 09 | F9: 22 | G9: دستگاه | H9: نصب نمایشگر جریان | I9: 5 | K9: 2.471
A10: =ROUND(C10*F10,0) -> 146618670 | B10: =ROUND(F10*D10,0) -> 59335760 | C10: =ROUND(D10*K10,0) -> 6664485 | D10: 2697080 | E10: کد 593119 ردیف 01 | F10: 22 | G10: عدد | H10: نصب/ کالیبراسیون/ کنترل مشخصات جریان سنجهای در طول خط سایز تا 4" | I10: 6 | K10: 2.471
A11: =ROUND(C11*F11,0) -> 54851953 | B11: =ROUND(F11*D11,0) -> 22198280 | C11: =ROUND(D11*K11,0) -> 4219381 | D11: 1707560 | E11: کد 593118 ردیف 01 | F11: 13 | G11: عدد | H11: نصب/ کنترل مشخصات صفحه اوریفیس سایز تا 4" | I11: 7 | K11: 2.471
A12: =ROUND(C12*F12,0) -> 72894630 | B12: =ROUND(F12*D12,0) -> 29500050 | C12: =ROUND(D12*K12,0) -> 4859642 | D12: 1966670 | E12: کد 593118 ردیف 02 | F12: 15 | G12: عدد | H12: نصب/ کنترل مشخصات صفحه اوریفیس سایز از 4" تا 8" | I12: 8 | K12: 2.471
A13: =ROUND(C13*F13,0) -> 94077609 | B13: =ROUND(F13*D13,0) -> 38072690 | C13: =ROUND(D13*K13,0) -> 5533977 | D13: 2239570 | E13: کد 593118 ردیف 03 | F13: 17 | G13: عدد | H13: نصب/ کنترل مشخصات صفحه اوریفیس سایز از 8" تا 12" | I13: 9 | K13: 2.471
A14: =ROUND(C14*F14,0) -> 18880392 | B14: =ROUND(F14*D14,0) -> 7640790 | C14: =ROUND(D14*K14,0) -> 6293464 | D14: 2546930 | E14: کد 593118 ردیف 04 | F14: 3 | G14: عدد | H14: نصب/ کنترل مشخصات صفحه اوریفیس سایز از 12" تا 20" | I14: 10 | K14: 2.471
A15: =ROUND(C15*F15,0) -> 225718934 | B15: =ROUND(F15*D15,0) -> 91347200 | C15: =ROUND(D15*K15,0) -> 16122781 | D15: 6524800 | E15: کد 593111 ردیف01 | F15: 14 | G15: دستگاه | H15: نصب نمایشگر سطح مغناطیسی | I15: 11 | K15: 2.471
A16: =ROUND(C16*F16,0) -> 71257610 | B16: =ROUND(F16*D16,0) -> 28837560 | C16: =ROUND(D16*K16,0) -> 35628805 | D16: 14418780 | E16: کد 593111 ردیف02 | F16: 2 | G16: دستگاه | H16: (FLOAT-CABLE) نصب نمایشگر سطح | I16: 12 | K16: 2.471
A17: =ROUND(C17*F17,0) -> 786352500 | B17: =ROUND(F17*D17,0) -> 318232500 | C17: =ROUND(D17*K17,0) -> 26211750 | D17: 10607750 | E17: کد 593102 ردیف 01 | F17: 30 | G17: دستگاه | H17: نصب سوییچ سطح EXTERNAL | I17: 13 | K17: 2.471
... A96: =ROUND(C96*F96,0) -> 10416175250 | B96: =ROUND(F96*D96,0) -> 4215368500 | C96: =ROUND(D96*K96,0) -> 10964395 | D96: 4437230 | E96: کد 593301- ردیف 2 | F96: 950 | G96: لوپ | H96: عملیات لوپ چک-لوپ حلقه باز | I96: 92 | K96: 2.471
A97: =SUM(A5:A96) -> 186708370490 | B97: =SUM(B5:B96) -> 75559842024 | H97: مجموع

Sheet C.tashilat
C2: جدول 17-1: هزینه تسهیلات کارفرما جهت ماموریت داخل کشور
C3: هزینه | E3: تعداد | G3: هزینه واحد | I3: شرح
C4: =E4*G4 -> 1.2260182e+10 | E4: 300 | G4: =2200000*IRR_Inflation_Factor -> 40867272 | I4: بلیط رفت و برگشت داخلی (با محوریت اهواز)
C5: =E5*G5 -> 1.671843e+09 | E5: 300 | G5: =300000*IRR_Inflation_Factor -> 5572809.9 | I5: ترانسفر فرودگاهی
C6: =E6*G6 -> 1.6068268e+10 | E6: 865 | G6: =1000000*IRR_Inflation_Factor -> 18576033 | I6: ایاب و ذهاب در سطح شهر واسطه و مقصد
C7: =E7*G7 -> 2.4102403e+10 | E7: 865 | G7: =1500000*IRR_Inflation_Factor -> 27864049 | I7: اقامت در هتل پنج ستاره در اتاق تک تخته به ازای هر نفر- شب
C8: =E8*G8 -> 11677500000 | E8: 865 | G8: =1000000*13.5 -> 13500000 | I8: خورد و خوراک 3 وعده در روز
C9: =SUM(C4:D8) -> 6.5780196e+10 | I9: مجموع
B11: توضیح جدول 1-17 : تعداد تقریبی ماموریتهای داخل کشورپرسنل کارفرما معادل 865 نفر-روز مطابق مدرک شرح خدمات و تسهیلات کارفرما به شرح ذیل: 250 نفر -روز جهت شرکت در جلسات و 255 نفر-روز جهت دوره اموزشی و360 نفر روز برای بازدید از مراحل ساخت کالا در تهران یا سایر نقاط کشور (مبدا : اهواز). هر ماموریت بطور متوسط 3 روز منظور شده است. لذا جمعا 300 سفر و به مدت 865 شب اقامت منظور شده است.
C15: جدول 17 -2: هزینه تسهیلات کارفرما جهت ماموریت خارج کشور
C16: هزینه | E16: تعداد | G16: هزینه واحد | I16: شرح
C17: =E17*G17 -> 24000 | E17: 40 | G17: 600 | I17: بلیط رفت و برگشت خارجی و بیمه (متوسط قیمت)
C18: =E18*G18 -> 2000 | E18: 40 | G18: 50 | I18: ترانسفر فرودگاهی
C19: =E19*G19 -> 16000 | E19: 160 | G19: 100 | I19: ایاب و ذهاب در سطح شهر واسطه و مقصد
C20: =E20*G20 -> 19200 | E20: 160 | G20: 120 | I20: اقامت در هتل پنج ستاره در اتاق تک تخته به ازای هر نفر- شب
C21: =E21*G21 -> 12800 | E21: 160 | G21: 80 | I21: خورد و خوراک 3 وعده در روز
C22: =E22*G22 -> 6000 | E22: 40 | G22: 150 | I22: هزینه امور کنسولی و ویزا
C23: =SUM(C17:D22) -> 80000 | G23: =SUM(G17:H22) -> 1100 | I23: مجموع
C24: =C23*USD_Change_IRR*per_Euro -> 3.6455341e+10 | I24: معادل ریالی
B26: توضیح جدول 2-17 : تعداد تقریبی ماموریتهای خارج کشورپرسنل کارفرما مطابق مدرک شرح خدمات و تسهیلات کارفرما معادل است با: 120 نفر شرکت در مراحل ساخت و 40 نفر-روز جهت حضور احتمالی در آزمایشات هر ماموریت بطور متوسط 4 روز منظور شده است. لذا جمعا 40 سفر و به مدت 160 شب اقامت منظور شده است.
C30: جدول 17-3: - هزینه آموزشی عملیاتی (اپراتوری) به میزان 192 نفر-روز
C31: هزینه | E31: تعداد | G31: هزینه واحد | I31: شرح
C32: =E32*G32 -> 2592000000 | E32: 192 | G32: =1000000*13.5 -> 13500000 | I32: خورد و خوراک 3 وعده در روز در سایت
C33: =100000000*IRR_Inflation_Factor -> 1.8576033e+09 | E33: - | G33: یک قلم | I33: امکانات سخت افزاری و نرم افزاری
C34: =30000000*IRR_Inflation_Factor -> 5.5728099e+08 | E34: - | G34: یک قلم | I34: تدارک مواد آموزشی شامل تکثیر جزوه و کتاب
C35: =150000000*IRR_Inflation_Factor -> 2.7864049e+09 | E35: - | G35: یک قلم | I35: برگزاری دوره نقشه برداری
C36: =SUM(C32:D35) -> 7.7932892e+09 | I36: مجموع
B38: مرجع : مدرک شرح خدمات و تسهیلات مورد نیاز کارفرما به شماره M9003-BD-GN-OTH-26010

Sheet C.tashilat (2)
B2: جدول 17-4: هزینه تسهیلات کارفرما مربوط به احداث کمپهای دستگاه نظارت کلیه بندهای اشاره شده در ذیل مربوط به مدرک "مشخصات فنی کمپهای دستگاه نظارت به شماره M9003-BD-GN-OTH-26011میباشد
B3: هزینه (ریال) | C3: توضیحات | H3: شرح
B4: =900*'C.Buildings'!S4*'C.Buildings'!S5 -> 283023180000 | C4: به مساحت 900 متر با هزینه محاسبه شده برای احداث ساختمان | H4: کمپ اصلی استقرار کارفرما مطابق مشخصات منرج در بند 4
B5: =450*320000000*1.1*1.2 -> 190080000000 | C5: توضیح : طبق استعلام مشخصات درخواستی | H5: کمپ فرعی استقرار کارفرمامندرج در بند 5.1
B6: =(B4+B5)*0.4 -> 189241272000 | C6: حراست فيزيكي و سيستم دوربين مدار بسته، روشنايي، فضاي سبز | H6: محوطه سازی کمپ اصلی و فرعی مطابق مشخصات منرج در بند 4.2و5.2
B7: =6*36*(5000000)*IRR_Inflation_Factor -> 2.0062115e+10 | C7: یک نفر آبدارچی به صورت شبانه‌روزی. یک نفر آشپز بصورت روزانه. یک نفر نظافتچی به صورت روزانه. یک نفر نگهبان به صورت شبانه روزی | H7: تامین نیروی خدماتی برای طول مدت پروژه مطابق بند 6.1
B8: =30*36*20*'C.tashilat'!G32 -> 291600000000 | C8: سه وعده غذاي گرم، میوه فصل، دسر ، آب معدنی ، نوشیدنی و غیره در روز به طور ميانگين براي 20 نفر نمایندگان کارفرما در طي زمان قرارداد در تمام روزها | H8: تهيه و تأمين و سرو خورد و خوراک کادر نظارت کارفرما مطابق بند6.3
B9: =4*250000000*IRR_Inflation_Factor -> 1.8576033e+10 | C9: پذیرایی سرد/گرم | H9: پذیرایی از شرکت کنندگان جلسات کارفرما
B10: =4*200000000*IRR_Inflation_Factor -> 1.4860826e+10 | C10: تجهيزات لازم و متعارف براي پرسنل کادر نظارت | H10: تجهیز دفاتر کار، سالنها و اتاقهاي خواب مطابق بند 6.5
B11: =4*50000000*IRR_Inflation_Factor -> 3.7152066e+09 | H11: سيستم اعلان حريق خودكار
B12: =5*50000000*IRR_Inflation_Factor -> 4.6440082e+09 | C12: شامل كپسول آبي و پودري و گازي و غيره | H12: تجهیزات ایمنی و آتش‌نشانی به تعداد كافي
B13: =2*(4*3)*5000000*IRR_Inflation_Factor -> 2.2291239e+09 | H13: جعبه كمكهاي اوليه .
B14: =2*10000000*(5+4*3+3*1+2*0.3)*IRR_Inflation_Factor -> 7.6533255e+09 | C14: (کولرهاي گازي نو تركيبي از پنجره اي و دو تكه، بخاري از نوع رادياتور روغني برقي. سه دستگاه آبگرمكن برقي با مخزن 200 ليتري ) | H14: تجهيزات سرمايشي و گرمايشي در كليه فضاها مطابق بند 7.4
B15: =4*10000000*(2+3+5+0.5)*IRR_Inflation_Factor -> 7.8019338e+09 | C15: ( مبلمان دفتری و مبلمان پذيرايي، کابینت نگهداری نقشه ها و مدارک پروژه، کابینت پرونده و كابينت بايگاني به تعداد كافي، نوشت‌افزار و غيره.) | H15: لوازم و تجهيزات اداري مطابق بند5، 6 و 7.6
B16: =10000000*(2*5+8*2+5*1+5*1+20)*IRR_Inflation_Factor -> 1.0402578e+10 | C16: (تلويزيون رنگي 48 اينچ از نوع LEDبه تعداد 2 دستگاه، تلويزيون رنگي 32 اينچ از نوع LED به تعداد 8 دستگاه، يخچال كوچك در هر اتاق خواب، مبلمان نشيمن، خواب و راحتي و مطالعه.) | H16: لوازم و تجهيزات رفاهي: مطابق بند 7.7 | T16: 2 | V16: =U16*T16 -> 0
B17: =2*10000000*(2+0.8+0.7+1.5+3+1+3+2+2+1)*IRR_Inflation_Factor -> 6.3158512e+09 | C17: يخچال، اجاق و فر گاز، مايكروفر، ماشين لباسشويي، میز و لوازم غذاخوري،تجهيزات آبدارخانه، كابينت‌بندي و تجهيزات و ظروف آشپزخانه، فريزر، كباب‌پز، هود، اگزوزفن، دستگاه تصفيه آب جهت آشپزخانه و غيره | H17: . لوازم و تجهيزات آشپزخانه مطابق بند 7.8:
B18: =2*10000000*(7*5+4*3+3*6+4*1+4*4+4*3+5*5+3)*IRR_Inflation_Factor -> 4.6440082e+10 | C18: هفت دستگاه كامپيوتر روميزي كامل با لوازم جانبي؛ چهار دستگاه چاپگر ليزري، سه دستگاه چاپگر ليزري رنگي؛ چهار دستگاه نمابر؛ چهار دستگاه كپي؛ چهار دستگاه اسكنر؛ پنج دستگاه كامپيوتر لپ‌تاپ؛ سه خط تلفن ثابت؛ گوشي تلفن سيار | H18: . لوازم و تجهيزات كامپيوتري مطابق بند 7.9
B19: =(6*30000000+6*30000000)*IRR_Inflation_Factor -> 6.6873718e+09 | C19: كمپ اصلي و كمپ فرعي | H19: 7.10. لوازم و تجهيزات ورزشي متناسب با فضاهاي پيش‌بيني‌شده
B20: =3*36*500000000 -> 54000000000 | C20: سه دستگاه خودرو شاسي استيشن | H20: وسيله اياب و ذهاب
B21: =36*(5000000+500000+100000+1000000+200000)*IRR_Inflation_Factor*2 -> 9.0948257e+09 | C21: آب و برق و گاز و خطوط تلفن و اشتراك اينترنت در كمپهاي كارفرما | H21: تأمين و پرداخت كليه هزينه‌هاي انشعاب و هزينه جاري
B22: =50000000*IRR_Inflation_Factor -> 9.2880164e+08 | C22: به تعداد مورد نیاز کارفرما | H22: تکثیر نسخ نرم و سخت و اسکن اسناد قرارداد
B23: =2*200000000*IRR_Inflation_Factor -> 7.4304131e+09 | C23: به ظرفيت 5 متر مكعب در روز | H23: بسته تصفيه فاضلاب بهداشتي
B24: =SUM(B4:B23) -> 1.1747869e+12 | H24: مجموع

Sheet C.HSE(1)
B3: جدول 18-1: براورد هزینه ایمنی کارگاه : لوازم حفاظت فردی و تجهیزات
B4: بهای کل (ریال) | E4: تعداد کل | F4: بهای واحد (ریال) | I4: زمان کل پروژه(ماه) | J4: زمان استفاده در هر دوره (ماه) | K4: تعداد | L4: شرح | Q4: ردیف | W4: بهای واحد (ریال)Min | X4: بهای واحد (ریال)Max | Y4: فاکتور
B5: =E5*F5 -> 1.3374744e+10 | E5: =V5*K5 -> 2400 | F5: =(W5+X5)/2*IRR_Inflation_Factor -> 5572809.9 | I5: 36 | J5: 3 | K5: 200 | L5: لباس کار | Q5: 1 | V5: =I5/J5 -> 12 | W5: 220000 | X5: 380000 | Y5: 4900000
B6: =E6*F6 -> 3450000000 | E6: =V6*K6 -> 300 | F6: 11500000 | I6: 36 | J6: 6 | K6: 50 | L6: لباس جوشکار و تجهیزات مربوطه | Q6: 2 | V6: =I6/J6 -> 6 | W6: 500000 | X6: 500000 | Y6: 11500000
B7: =E7*F7 -> 380000000 | E7: =V7*K7 -> 40 | F7: 9500000 | I7: 36 | J7: 42 | K7: 40 | L7: لباس سند بلاست کار و تجهیزات مربوطه | Q7: 3 | V7: 1 | W7: 4800000 | X7: 31500000 | Y7: 9500000
B8: =E8*F8 -> 9.055816e+09 | E8: =V8*K8 -> 1500 | F8: =(W8+X8)/2*IRR_Inflation_Factor -> 6037210.7 | I8: 36 | J8: 6 | K8: 250 | L8: کفش ایمنی | Q8: 4 | V8: =I8/J8 -> 6 | W8: 270000 | X8: 380000 | Y8: 4500000
B9: =E9*F9 -> 4.3885878e+08 | E9: =V9*K9 -> 35 | F9: =(W9+X9)/2*IRR_Inflation_Factor -> 12538822 | I9: 36 | J9: 42 | K9: 35 | L9: کمربند ایمنی | Q9: 5 | V9: 1 | W9: 200000 | X9: 1150000 | Y9: 9000000
B10: =E10*F10 -> 1.5975388e+09 | E10: =V10*K10 -> 400 | F10: =(W10+X10)/2*IRR_Inflation_Factor -> 3993847.1 | I10: 36 | J10: 21 | K10: 200 | L10: کلاه ایمنی | Q10: 6 | V10: 2 | W10: 50000 | X10: 380000 | Y10: 1500000
B11: =E11*F11 -> 1.2037269e+10 | E11: =V11*K11 -> 14400 | F11: =(W11+X11)/2*IRR_Inflation_Factor -> 835921.48 | I11: 36 | J11: 0.5 | K11: 200 | L11: دستکش کارگر ساده | Q11: 7 | V11: =I11/J11 -> 72 | W11: 30000 | X11: 60000 | Y11: 390000
B12: =E12*F12 -> 1.2037269e+09 | E12: =V12*K12 -> 1080 | F12: =(W12+X12)/2*IRR_Inflation_Factor -> 1114562 | I12: 36 | J12: 1 | K12: 30 | L12: دستکش ورق کار | Q12: 8 | V12: =I12/J12 -> 36 | W12: 60000 | X12: 60000 | Y12: 9500000
B13: =E13*F13 -> 1.7554351e+09 | E13: =V13*K13 -> 540 | F13: =(W13+X13)/2*IRR_Inflation_Factor -> 3250805.8 | I13: 36 | J13: 2 | K13: 30 | L13: دستکش مواد شیمیایی | Q13: 9 | V13: =I13/J13 -> 18 | W13: 130000 | X13: 220000 | Y13: 2500000
B14: =E14*F14 -> 1.1368532e+10 | E14: =V14*K14 -> 360 | F14: =(W14+X14)/2*IRR_Inflation_Factor -> 31579256 | I14: 36 | J14: 3 | K14: 30 | L14: دستکش برق کار | Q14: 10 | V14: =I14/J14 -> 12 | W14: 1100000 | X14: 2300000 | Y14: 1800000
B15: =E15*F15 -> 6.419877e+09 | E15: =V15*K15 -> 14400 | F15: =(W15+X15)/2*IRR_Inflation_Factor -> 445824.79 | I15: 36 | J15: 0.5 | K15: 200 | L15: ماسک گرد و غبار استاندارد فیلتر دار | Q15: 11 | V15: =I15/J15 -> 72 | W15: 10000 | X15: 38000 | Y15: 1800000
B16: =E16*F16 -> 2.0619396e+09 | E16: =V16*K16 -> 300 | F16: =(W16+X16)/2*IRR_Inflation_Factor -> 6873132.2 | I16: 36 | J16: 6 | K16: 50 | L16: ماسک فیلتردار جهت رنگ آمیزی مخازن | Q16: 12 | V16: =I16/J16 -> 6 | W16: 90000 | X16: 650000 | Y16: 8000000
B17: =E17*F17 -> 23127161 | E17: =V17*K17 -> 3 | F17: =(W17+X17)/2*IRR_Inflation_Factor -> 7709053.6 | I17: 36 | J17: 42 | K17: 3 | L17: زنگ اعلام شرایط اضطراری | Q17: 13 | V17: 1 | W17: 280000 | X17: 550000
B18: =E18*F18 -> 3.2600938e+09 | E18: =V18*K18 -> 3600 | F18: =(W18+X18)/2*IRR_Inflation_Factor -> 905581.6 | I18: 36 | J18: 1 | K18: 100 | L18: علائم و تابلوهای هشدار دهنده ایمنی و آموزشی | Q18: 14 | V18: =I18/J18 -> 36 | W18: 2500 | X18: 95000
B19: =E19*F19 -> 7.7740698e+08 | E19: =V19*K19 -> 90 | F19: =(W19+X19)/2*IRR_Inflation_Factor -> 8637855.3 | I19: 36 | J19: 6 | K19: 15 | L19: لباس کار،کلاه و چکمه برای کارکنان آشپزخانه و آبدارخانه ها | Q19: 15 | V19: =I19/J19 -> 6 | W19: 380000 | X19: 550000
B20: =E20*F20 -> 4.9887794e+09 | E20: =V20*K20 -> 288 | F20: =(W20+X20)/2*IRR_Inflation_Factor -> 17322151 | I20: 36 | J20: 1 | K20: 8 | L20: جعبه کمکهای اولیه با تجهیزات کامل | Q20: 16 | V20: =I20/J20 -> 36 | W20: 65000 | X20: 1800000
B21: =10*F21 -> 16254029 | E21: مقطوع | F21: =(W21+X21)/2*IRR_Inflation_Factor -> 1625402.9 | I21: 36 | J21: 1 | L21: نوار محدوده خطر | Q21: 17 | V21: =I21/J21 -> 36 | W21: 75000 | X21: 100000
B22: =E22*F22 -> 3.37155e+09 | E22: =V22*K22 -> 60 | F22: =(W22+X22)/2*IRR_Inflation_Factor -> 56192499 | I22: 36 | J22: 42 | K22: 60 | L22: کپسول اطفاء حریق 12Kg (نوعC) (مربوط به دوران شروع تا پایان پروژه) | Q22: 18 | V22: 1 | W22: 2750000 | X22: 3300000
B23: =E23*F23 -> 1.5789628e+08 | E23: =V23*K23 -> 10 | F23: =(W23+X23)/2*IRR_Inflation_Factor -> 15789628 | I23: 36 | J23: 42 | K23: 10 | L23: کپسول اطفاء حریق 12Kg (نوعB) (مربوط به دوران شروع تا پایان پروژه) | Q23: 19 | V23: 1 | W23: 850000 | X23: 850000
B24: =E24*F24 -> 26006446 | E24: 2 | F24: =(W24+X24)/2*IRR_Inflation_Factor -> 13003223 | I24: 36 | J24: 42 | K24: برای کلیه ی اتاقها و اماکن سرپوشیده | L24: سیستم دودیاب و حسگرهای آن (مربوط به دوران شروع تا پایان پروژه) | Q24: 20 | V24: 1 | W24: 700000 | X24: 700000
B25: =E25*F25 -> 1.5882508e+09 | E25: 3 | F25: =(W25+X25)/2*IRR_Inflation_Factor -> 5.2941694e+08 | I25: 36 | J25: 42 | K25: برای تمام ساختمانها و کانکس ها | L25: سیتم ارتینگ (مربوط به دوران شروع تا پایان پروژه) زمین شن زار | Q25: 21 | V25: 1 | W25: 28500000 | X25: 28500000
B26: =E26*F26 -> 2.7864049e+09 | E26: 6 | F26: =(W26+X26)/2*IRR_Inflation_Factor -> 4.6440082e+08 | I26: 36 | J26: 42 | K26: برای 6 ساختمان | L26: صاعقه گیر (مربوط به دوران شروع تا پایان پروژه) | Q26: 22 | V26: 1 | W26: 25000000 | X26: 25000000
B27: =SUM(B5:B26) -> 8.0139507e+10 | L27: مجموع | Q27: 23
C30: جدول 18 -2: براورد هزینه ایمنی کارگاه : نیروی انسانی
C31: جمع (ریال) | F31: زمان کل پروژه(ماه) | H31: مقدار حقوق ماهیانه(ریال) | K31: واحد / نفر | L31: عنوان | Q31: ردیف
C32: =F32*H32 -> 13500000000 | F32: 30 | H32: 450000000 | K32: 1 | L32: کارشناس HSE جهت سایت ویزیتو نظارت برانجام ایمن کارها | Q32: 1
C33: =F33*H33 -> 13500000000 | F33: 30 | H33: 450000000 | K33: 1 | L33: کارشناس IMS جهت مستندسازی فرآیندهای مربوطه و کارهای داکیومنتی | Q33: 2
C34: =SUM(C32:E33) -> 27000000000 | L34: مجموع | Q34: 3

Sheet C.HSE(2)
B2: جدول 18-3 - براورد هزینه ایمنی کارگاه : سنجش و اندازه گیری (1) - اندازه گیری آلاینده های فیزیکی،شیمیایی و ارگونومی در محیط کار
B3: بهای کل ریال | E3: تعداد دفعات اندازه گیری در هر سال | G3: کل زمان پروژه | I3: بهای اندازه گیری در هر دوره | L3: عنوان | Q3: ردیف
B4: =I4*E4*3 -> 16718430 | E4: 30 | G4: 36ماه | I4: =10000*IRR_Inflation_Factor -> 185760.33 | L4: نور | Q4: 1
B5: =I5*E5*3 -> 2.0898037e+08 | E5: 30 | G5: 36ماه | I5: =125000*IRR_Inflation_Factor -> 2322004.1 | L5: صدا(اکتاو،دزیمتری،محیط کار) | Q5: 2
B6: =I6*E6*3 -> 4.1796074e+08 | E6: 10 | G6: 36ماه | I6: =750000*IRR_Inflation_Factor -> 13932025 | L6: هوا | Q6: 3
B7: =I7*E7*3 -> 1.671843e+08 | E7: 10 | G7: 36ماه | I7: =300000*IRR_Inflation_Factor -> 5572809.9 | L7: سنجش غبار زیست محیطی | Q7: 4
B8: =I8*E8*3 -> 1.7832992e+08 | E8: 10 | G8: 36ماه | I8: =320000*IRR_Inflation_Factor -> 5944330.5 | L8: سنجش گازهای محیط کار | Q8: 5
B9: =I9*E9*3 -> 1.671843e+08 | E9: 30 | G9: 36ماه | I9: =100000*IRR_Inflation_Factor -> 1857603.3 | L9: ارتعاش | Q9: 6
B10: =I10*E10*3 -> 25077644 | E10: 10 | G10: 36ماه | I10: =45000*IRR_Inflation_Factor -> 835921.48 | L10: استرس گرمایی | Q10: 7
B11: =I11*E11*3 -> 75232933 | E11: 30 | G11: 36ماه | I11: =45000*IRR_Inflation_Factor -> 835921.48 | L11: اشعهX,UV,IR | Q11: 8
B12: =I12*E12*3 -> 3.3436859e+08 | E12: 20 | G12: 36ماه | I12: =300000*IRR_Inflation_Factor -> 5572809.9 | L12: گرد و غبار | Q12: 9
B13: =I13*E13*3 -> 5.8514504e+08 | E13: 30 | G13: 36ماه | I13: =350000*IRR_Inflation_Factor -> 6501611.5 | L13: فیوم جوشکاری | Q13: 10
B14: =I14*E14*3 -> 3.3436859e+08 | E14: 30 | G14: 36ماه | I14: =200000*IRR_Inflation_Factor -> 3715206.6 | L14: گازهای خروجی ماشین آلات | Q14: 11
B15: =I15*E15*3 -> 3.1765016e+08 | E15: 3 | G15: 36ماه | I15: =1900000*IRR_Inflation_Factor -> 35294462 | L15: آب آشامیدنی | Q15: 12
B16: =I16*E16 -> 30650454 | E16: 3 | G16: 36ماه | I16: =550000*IRR_Inflation_Factor -> 10216818 | L16: کارشناسی | Q16: 13
B17: =SUM(B4:B16) -> 2.8588515e+09 | L17: مجموع | Q17: 14
B19: جدول 18-4: براورد هزینه ایمنی کارگاه : سنجش و اندازه گیری (2)
B20: بهای کل(ریال) | E20: دفعات انجام آزمایش در کل پروژه | G20: کل زمان پروژه | H20: بهای انجام آزمایشات برای هر نفر(ریال) | K20: تعداد نفرات | L20: عنوان | Q20: ردیف
B21: =E21*K21*H21 -> 81900000 | E21: 3 | G21: 36 | H21: 9100000 | K21: 3 | L21: انجام آزمایشات دوره ای طب صنعتی برای پرسنل آبدارخانه و آشپزخانه | Q21: 1
B23: جدول 18-5: براورد هزینه ایمنی کارگاه : آموزش
B24: بهای کل (ریال) | E24: بهای دوره (ریال) | G24: زمان دوره(روز) | H24: تعداد دوره در کل زمان پروژه | I24: زمان کل پروژه (سال) | J24: زمان استفاده در هر دوره (ماه) | K24: تعداد دوره در سال | L24: سرفصل دوره ها | Q24: ردیف
B25: =E25*H25 -> 4.4582479e+08 | E25: =12000000*IRR_Inflation_Factor -> 2.2291239e+08 | G25: 1 | H25: 2 | I25: 3 | J25: =I25*12/H25 -> 18 | K25: 2 | L25: MSDS کار با مواد شیمیایی و | Q25: 1
B26: =E26*H26 -> 6.6873718e+08 | E26: =12000000*IRR_Inflation_Factor -> 2.2291239e+08 | G26: 1 | H26: 3 | I26: 3 | J26: =I26*12/H26 -> 12 | K26: 2 | L26: ایمنی داربستها،کار در ارتفاع،بالابرها،جرثقیل و لیفتراکها | Q26: 2
B27: =E27*H27 -> 2.2291239e+08 | E27: =12000000*IRR_Inflation_Factor -> 2.2291239e+08 | G27: 1 | H27: 1 | I27: 3 | J27: =I27*12/H27 -> 36 | K27: 2 | L27: ایمنی برق و برق صنعتی،صاعقه و رعد و برق و سیستمهای ارتینگ | Q27: 3
B28: =E28*H28 -> 6.6873718e+08 | E28: =12000000*IRR_Inflation_Factor -> 2.2291239e+08 | G28: 1 | H28: 3 | I28: 3 | J28: =I28*12/H28 -> 12 | K28: 3 | L28: آتش نشانی و اطفاء حریق | Q28: 4
B29: =E29*H29 -> 1.8576033e+08 | E29: =10000000*IRR_Inflation_Factor -> 1.8576033e+08 | G29: 1 | H29: 1 | I29: 3 | J29: =I29*12/H29 -> 36 | K29: 1 | L29: آشنایی با استانداردهای Iso9001و TS29001 | Q29: 5
B30: =E30*H30 -> 1.8576033e+08 | E30: =10000000*IRR_Inflation_Factor -> 1.8576033e+08 | G30: 1 | H30: 1 | I30: 3 | J30: =I30*12/H30 -> 36 | K30: 1 | L30: آشنایی با استانداردهای Iso 14001 | Q30: 6
B31: =E31*H31 -> 1.8576033e+08 | E31: =10000000*IRR_Inflation_Factor -> 1.8576033e+08 | G31: 1 | H31: 1 | I31: 3 | J31: =I31*12/H31 -> 36 | K31: 2 | L31: آشنایی باOHSAS18001 | Q31: 7
B32: =E32*H32 -> 3.7152066e+08 | E32: =10000000*IRR_Inflation_Factor -> 1.8576033e+08 | G32: 1 | H32: 2 | I32: 3 | J32: =I32*12/H32 -> 18 | K32: 2 | L32: کنترل عملیاتHSE،IMS و پرمیتها | Q32: 8
B33: =E33*H33 -> 6.6873718e+08 | E33: =12000000*IRR_Inflation_Factor -> 2.2291239e+08 | G33: 1 | H33: 3 | I33: 3 | J33: =I33*12/H33 -> 12 | K33: 1 | L33: ایمنی کار با پرتوها و اشعه ها | Q33: 9
B34: =E34*H34 -> 5.5728099e+08 | E34: =10000000*IRR_Inflation_Factor -> 1.8576033e+08 | G34: 1 | H34: 3 | I34: 3 | J34: =I34*12/H34 -> 12 | K34: 3 | L34: اورژانس ،کمکهای اولیه و ارگونومی و مدیریت بحران | Q34: 10
B35: =E35*H35 -> 6.6873718e+08 | E35: =12000000*IRR_Inflation_Factor -> 2.2291239e+08 | G35: 1 | H35: 3 | I35: 3 | J35: =I35*12/H35 -> 12 | K35: 2 | L35: ایمنی جوشکاری، برشکاری و عملیات سند بلاست | Q35: 11
B36: =E36*H36 -> 2.2291239e+08 | E36: =12000000*IRR_Inflation_Factor -> 2.2291239e+08 | G36: 1 | H36: 1 | I36: 3 | J36: =I36*12/H36 -> 36 | K36: 2 | L36: انبارداری و رعایت اصول مربوطه | Q36: 12
B37: =SUM(B25:B36) -> 5.0526809e+09 | L37: مجموع | Q37: 13
R58: ردیف
R59: 1

Sheet C.Foundation-1
R2: جدول الف : ریز برآورد متره فونداسیون تجهیزات
I3: حجم خاکبرداري | J3: حجم خاکریزی | K3: قالب بندي | L3: بتن با عيار150 | M3: بتن با عيار300 | N3: ميلگرد | O3: کوبیدن خاک | P3: ASPHALT | Q3: Geotextile | R3: Geomembrane
B7: فونداسیون های تجهیزات | I7: متر مکعب | J7: متر مکعب | K7: متر مربع | L7: متر مکعب | M7: متر مکعب | N7: کيلو گرم | O7: متر مکعب | P7: متر مربع | Q7: متر مربع | R7: متر مربع
B9: FOUNDATION OF OFF-SPEC TANK | I9: 1960 | J9: 1480 | K9: 340 | L9: 100 | M9: 320 | N9: 50000 | O9: 1480 | P9: 1000 | Q9: 1340 | R9: 1340
B10: FOUNDATION OF DILUTION WATER TANK | I10: 480 | J10: 100 | K10: 100 | L10: 40 | M10: 240 | N10: 18000 | P10: 160 | Q10: 280 | R10: 280
B11: FOUNDATION OF POTABLE WATER TANK | I11: 90 | J11: 40 | K11: 100 | L11: 5 | M11: 80 | N11: 5800
B12: FOUNDATION OF DISPOSAL TANK | I12: 360 | J12: 300 | K12: 260 | L12: 20 | M12: 240 | N12: 20000 | O12: 200 | P12: 20 | Q12: 280 | R12: 280
B13: FOUNDATION OF DIRTY OILTANK | I13: 90 | K13: 50 | L13: 120 | M13: 20 | N13: 3600 | P13: 20 | Q13: 60 | R13: 60
B14: FOUNDATION OF FIRE WATER STORAGE TANK | I14: 1080 | J14: 200 | K14: 240 | L14: 80 | M14: 500 | N14: 52400 | O14: 180 | P14: 50
B15: FOUNDATION OF SKIMMER TANK | I15: 720 | J15: 560 | K15: 480 | L15: 40 | M15: 480 | N15: 40000 | O15: 400 | P15: 160 | Q15: 280 | R15: 280
B16: FOUNDATION OF FREE WATER K.O DRUM | I16: 1500 | J16: 700 | K16: 900 | L16: 100 | M16: 0 | N16: 76000 | O16: 60
B17: FOUNDATION OF FUEL GAS K.O. DRUM | I17: 64 | J17: 8 | L17: 2 | M17: 50 | N17: 600
B18: FOUNDATION OF AIR RECIEVER | I18: 30 | J18: 16 | K18: 15 | L18: 3 | M18: 20 | N18: 1500
B19: FOUNDATION OF FLARE K.O. DRUM | I19: 28 | K19: 44 | L19: 3 | M19: 20 | N19: 2600
B20: FOUNDATION OF HC CLOSED DRAIN DRUM | I20: 16 | K20: 26 | L20: 2 | M20: 12 | N20: 1800
B21: FOUNDATION OF DIESEL oil STORAGE TANK | I21: 80 | J21: 34 | K21: 30 | L21: 30 | M21: 5 | N21: 3600
B22: FOUNDATION OF DESALTER FOUNDATION | I22: 900 | J22: 500 | K22: 400 | L22: 40 | M22: 500 | N22: 38000 | O22: 100
B23: FOUNDATION OF HEATERS FOUNDATION | I23: 380 | J23: 160 | K23: 280 | L23: 32 | M23: 280 | N23: 18000 | O23: 100
B24: FOUNDATION OF EXCHANGER FOUNDATION | I24: 24 | K24: 36 | L24: 4 | M24: 24 | N24: 2400
B25: FOUNDATION OF DEARATOR FOUNDATION | I25: 38 | J25: 18 | K25: 70 | L25: 26 | M25: 42 | N25: 2140 | O25: 20
B26: FOUNDATION OF IGF FOUNDATION | I26: 240 | J26: 120 | K26: 840 | L26: 30 | M26: 80 | N26: 5600 | O26: 40
B27: FOUNDATION OF NUTSHELL FILTER | I27: 110 | J27: 20 | K27: 84 | L27: 12 | M27: 60 | N27: 5200 | O27: 20
B28: FOUNDATION OF COLD FLARE | I28: 32 | J28: 4 | L28: 2 | M28: 30 | N28: 500
B29: FOUNDATION OF HOT FLARE | I29: 28 | J29: 4 | L29: 2 | M29: 30 | N29: 440
B30: FOUNDATION OF COMPRESSOR (4no.) | I30: 12 | K30: 20 | L30: 4 | M30: 20 | N30: 800
B31: FOUNDATION OF PROCESS PUMPS (~ 40NO.) | I31: 960 | J31: 120 | L31: 60 | M31: 900 | N31: 15000 | O31: 80
B32: FOUNDATION OF FIREWATER PUMP(5 no.) | I32: 50 | K32: 80 | L32: 12 | M32: 36 | N32: 3400
B33: FOUNDATION OF AIR DRYER | I33: 64 | J33: 8 | L33: 2 | M33: 50 | N33: 600
B34: FOUNDATION OF DIESEL GENERATOR | I34: 288 | J34: 80 | K34: 46 | L34: 4.8 | M34: 40 | N34: 3500
B35: FOUNDATION OF INJECTION PACKAGE (9 NO.) | I35: 40 | K35: 60 | L35: 20 | M35: 70 | N35: 5160
B36: TOTAL : | I36: =SUM(I9:I35) -> 9664 | J36: =SUM(J9:J35) -> 4472 | K36: =SUM(K9:K35) -> 4501 | L36: =SUM(L9:L35) -> 795.8 | M36: =SUM(M9:M35) -> 4149 | N36: =SUM(N9:N35) -> 376640 | O36: =SUM(O9:O35) -> 2680 | P36: =SUM(P9:P35) -> 1410 | ... R36: =SUM(R9:R35) -> 2240

Sheet C.Shelters-1
R2: جدول ب-1 : ریز برآورد متره سایبانها - فونداسیون و کف سازی
B3: مشخصات سایبان | F3: فونداسیون | N3: کف سازی
B4: شرح سایبان | E4: متراژ | F4: حجم خاکبرداري | G4: حجم خاکریزی | H4: قالب بندي | I4: بتن با عيار150 | J4: بتن با عيار300 | K4: ميلگرد | L4: کوبیدن خاک | M4: انکربولت | N4: بلوکاژ (30سانتیمتر) | O4: بتن با عيار150 | P4: بتن با عيار300 | Q4: ميلگرد | R4: درزبندی کف
E8: متر مربع | F8: متر مکعب | G8: متر مکعب | H8: متر مربع | I8: متر مکعب | J8: متر مکعب | K8: کيلو گرم | L8: متر مکعب | M8: کیلو گرم | N8: متر مکعب | O8: متر مکعب | P8: متر مکعب | Q8: کيلو گرم | R8: دسی متر مکعب
B10: احداث سایبان پمپ 1 نمکزدایی (ناحیه 8) | E10: 600 | F10: =AG10*$F$30 -> 1010 | G10: =AG10*$G$30 -> 600 | H10: =AG10*$H$30 -> 240 | I10: =AG10*$I$30 -> 90 | J10: =AG10*$J$30 -> 140 | K10: =AG10*$K$30 -> 6500 | L10: =AG10*$L$30 -> 300 | M10: =AG10*$M$30 -> 250 | N10: =0.3*E10 -> 180 | O10: =E10*0.05 -> 30 | P10: =E10*0.15 -> 90 | Q10: =5*E10 -> 3000 | R10: =AG10*$R$30 -> 720 | AG10: =E10/60 -> 10
B11: احداث سایبان پمپ 2 نمکزدایی (ناحیه 9) | E11: 180 | F11: =AG11*$F$30 -> 303 | G11: =AG11*$G$30 -> 180 | H11: =AG11*$H$30 -> 72 | I11: =AG11*$I$30 -> 27 | J11: =AG11*$J$30 -> 42 | K11: =AG11*$K$30 -> 1950 | L11: =AG11*$L$30 -> 90 | M11: =AG11*$M$30 -> 75 | N11: =0.3*E11 -> 54 | O11: =E11*0.05 -> 9 | P11: =E11*0.15 -> 27 | Q11: =5*E11 -> 900 | R11: =AG11*$R$30 -> 216 | AG11: =E11/60 -> 3
B12: احداث سایبان پمپ 3 نمکزدایی (ناحیه 5) | E12: 90 | F12: =AG12*$F$30 -> 151.5 | G12: =AG12*$G$30 -> 90 | H12: =AG12*$H$30 -> 36 | I12: =AG12*$I$30 -> 13.5 | J12: =AG12*$J$30 -> 21 | K12: =AG12*$K$30 -> 975 | L12: =AG12*$L$30 -> 45 | M12: =AG12*$M$30 -> 37.5 | N12: =0.3*E12 -> 27 | O12: =E12*0.05 -> 4.5 | P12: =E12*0.15 -> 13.5 | Q12: =5*E12 -> 450 | R12: =AG12*$R$30 -> 108 | AG12: =E12/60 -> 1.5
B13: احداث سایبان پمپ 4 نمکزدایی (ناحیه 4) | E13: 240 | F13: =AG13*$F$30 -> 404 | G13: =AG13*$G$30 -> 240 | H13: =AG13*$H$30 -> 96 | I13: =AG13*$I$30 -> 36 | J13: =AG13*$J$30 -> 56 | K13: =AG13*$K$30 -> 2600 | L13: =AG13*$L$30 -> 120 | M13: =AG13*$M$30 -> 100 | N13: =0.3*E13 -> 72 | O13: =E13*0.05 -> 12 | P13: =E13*0.15 -> 36 | Q13: =5*E13 -> 1200 | R13: =AG13*$R$30 -> 288 | AG13: =E13/60 -> 4
B14: احداث سایبان پمپ 5 نمکزدایی (ناحیه 1) | E14: 60 | F14: =AG14*$F$30 -> 101 | G14: =AG14*$G$30 -> 60 | H14: =AG14*$H$30 -> 24 | I14: =AG14*$I$30 -> 9 | J14: =AG14*$J$30 -> 14 | K14: =AG14*$K$30 -> 650 | L14: =AG14*$L$30 -> 30 | M14: =AG14*$M$30 -> 25 | N14: =0.3*E14 -> 18 | O14: =E14*0.05 -> 3 | P14: =E14*0.15 -> 9 | Q14: =5*E14 -> 300 | R14: =AG14*$R$30 -> 72 | AG14: =E14/60 -> 1
B15: احداث سایبان پمپ آب آتش نشانی | E15: 420 | F15: =AG15*$F$30 -> 707 | G15: =AG15*$G$30 -> 420 | H15: =AG15*$H$30 -> 168 | I15: =AG15*$I$30 -> 63 | J15: =AG15*$J$30 -> 98 | K15: =AG15*$K$30 -> 4550 | L15: =AG15*$L$30 -> 210 | M15: =AG15*$M$30 -> 175 | N15: =0.3*E15 -> 126 | O15: =E15*0.05 -> 21 | P15: =E15*0.15 -> 63 | Q15: =5*E15 -> 2100 | R15: =AG15*$R$30 -> 504 | AG15: =E15/60 -> 7
B16: احداث سایبان پمپ بهره برداری | E16: 425 | F16: =AG16*$F$30 -> 808 | G16: =AG16*$G$30 -> 480 | H16: =AG16*$H$30 -> 192 | I16: =AG16*$I$30 -> 72 | J16: =AG16*$J$30 -> 112 | K16: =AG16*$K$30 -> 5200 | L16: =AG16*$L$30 -> 240 | M16: =AG16*$M$30 -> 200 | N16: =0.3*E16 -> 127.5 | O16: =E16*0.05 -> 21.25 | P16: =E16*0.15 -> 63.75 | Q16: =5*E16 -> 2125 | R16: =AG16*$R$30 -> 576 | AG16: 8
B17: احداث سایبان پکیج تزریق 1 نمکزدایی | E17: 240 | F17: =AG17*$F$30 -> 505 | G17: =AG17*$G$30 -> 300 | H17: =AG17*$H$30 -> 120 | I17: =AG17*$I$30 -> 45 | J17: =AG17*$J$30 -> 70 | K17: =AG17*$K$30 -> 3250 | L17: =AG17*$L$30 -> 150 | M17: =AG17*$M$30 -> 125 | N17: =0.3*E17 -> 72 | O17: =E17*0.05 -> 12 | P17: =E17*0.15 -> 36 | Q17: =5*E17 -> 1200 | R17: =AG17*$R$30 -> 360 | AG17: 5
B18: احداث سایبان پکیج تزریق 2 نمکزدایی | E18: 180 | F18: =AG18*$F$30 -> 303 | G18: =AG18*$G$30 -> 180 | H18: =AG18*$H$30 -> 72 | I18: =AG18*$I$30 -> 27 | J18: =AG18*$J$30 -> 42 | K18: =AG18*$K$30 -> 1950 | L18: =AG18*$L$30 -> 90 | M18: =AG18*$M$30 -> 75 | N18: =0.3*E18 -> 54 | O18: =E18*0.05 -> 9 | P18: =E18*0.15 -> 27 | Q18: =5*E18 -> 900 | R18: =AG18*$R$30 -> 216 | AG18: 3
B19: احداث انبار مواد1 شیمیایی | E19: 250 | F19: =AG19*$F$30 -> 505 | G19: =AG19*$G$30 -> 300 | H19: =AG19*$H$30 -> 120 | I19: =AG19*$I$30 -> 45 | J19: =AG19*$J$30 -> 70 | K19: =AG19*$K$30 -> 3250 | L19: =AG19*$L$30 -> 150 | M19: =AG19*$M$30 -> 125 | N19: =0.3*E19 -> 75 | O19: =E19*0.05 -> 12.5 | P19: =E19*0.15 -> 37.5 | Q19: =5*E19 -> 1250 | R19: =AG19*$R$30 -> 360 | AG19: 5
B20: احداث انبار مواد2 شیمیایی | E20: 150 | F20: =AG20*$F$30 -> 303 | G20: =AG20*$G$30 -> 180 | H20: =AG20*$H$30 -> 72 | I20: =AG20*$I$30 -> 27 | J20: =AG20*$J$30 -> 42 | K20: =AG20*$K$30 -> 1950 | L20: =AG20*$L$30 -> 90 | M20: =AG20*$M$30 -> 75 | N20: =0.3*E20 -> 45 | O20: =E20*0.05 -> 7.5 | P20: =E20*0.15 -> 22.5 | Q20: =5*E20 -> 750 | R20: =AG20*$R$30 -> 216 | AG20: 3
B21: توسعه سایبان پکیج تزریق بهره داری | E21: 36 | F21: =AG21*$F$30 -> 101 | G21: =AG21*$G$30 -> 60 | H21: =AG21*$H$30 -> 24 | I21: =AG21*$I$30 -> 9 | J21: =AG21*$J$30 -> 14 | K21: =AG21*$K$30 -> 650 | L21: =AG21*$L$30 -> 30 | M21: =AG21*$M$30 -> 25 | N21: =0.3*E21 -> 10.8 | O21: =E21*0.05 -> 1.8 | P21: =E21*0.15 -> 5.4 | Q21: =5*E21 -> 180 | R21: =AG21*$R$30 -> 72 | AG21: 1
B22: احداث انبار مواد شیمیایی بهره برداری گچساران-4 | E22: 90 | F22: =AG22*$F$30 -> 101 | G22: =AG22*$G$30 -> 60 | H22: =AG22*$H$30 -> 24 | I22: =AG22*$I$30 -> 9 | J22: =AG22*$J$30 -> 14 | K22: =AG22*$K$30 -> 650 | L22: =AG22*$L$30 -> 30 | M22: =AG22*$M$30 -> 25 | N22: =0.3*E22 -> 27 | O22: =E22*0.05 -> 4.5 | P22: =E22*0.15 -> 13.5 | Q22: =5*E22 -> 450 | R22: =AG22*$R$30 -> 72 | AG22: 1
B23: احداث پارکینگ | E23: 310 | F23: =AG23*$F$30 -> 505 | G23: =AG23*$G$30 -> 300 | H23: =AG23*$H$30 -> 120 | I23: =AG23*$I$30 -> 45 | J23: =AG23*$J$30 -> 70 | K23: =AG23*$K$30 -> 3250 | L23: =AG23*$L$30 -> 150 | M23: =AG23*$M$30 -> 125 | N23: =0.3*E23 -> 93 | O23: =E23*0.05 -> 15.5 | P23: =E23*0.15 -> 46.5 | Q23: =5*E23 -> 1550 | R23: =AG23*$R$30 -> 360 | AG23: 5
