Workbook

Sheet Guide
A1: راهنمای بانک قیمت پمپ – نسخه ۸
A2: بر اساس شرح نیاز و اصلاحات سازمانی مهر ۱۴۰۵
A4: ترتیب ستون‌ها | B4: شناسایی ← مشخصات کلیدی (نوع و متریال API 610، دبی، هد، توان، استانداردها، آب‌بند) ← مشخصات تکمیلی ← قیمت ← دامنه کار ← منبع ← محاسبات ← کنترل. ستون‌های فرعی گروه‌بندی شده‌اند و با «+» بالای ستون باز می‌شوند.
A5: رنگ‌ها | B5: سرستون زرد = ورودی Dropdown؛ آبی روشن = ورودی آزاد؛ خاکستری = فرمول. سلول زرد پررنگ = مقدار استنباطی (شاهد در Note). سلول آبی در ستون IRR = تبدیل با نرخ بانک؛ نرخ و قیمت پروژه در Note.
A6: Standards | B6: ستون Standards خودکار از ستون‌های جمع‌شده Pump Standard، IPS، NACE و NFPA 20 ساخته می‌شود. ورودی‌ها را در همان ستون‌های جمع‌شده تغییر دهید.
A7: نرمال‌سازی | B7: Normalized EUR = قیمت یورویی سال منبع ÷ (MAT × SEAL × DRIVE × SCOPE) = قیمت معادل پیکربندی پایه. ضرایب در Factors_ROT و هنوز کالیبره نشده‌اند.
A8: تعدیل | B8: یورو × PPI(هدف)/PPI(پایه)، با کف ۲۵٬۰۰۰ یورو (۱۴۰۴) برای API 610 گریز از مرکز کلاس S/D؛ دلار و ریال با نرخ‌های سال هدف. شاخص PPI از Eurostat C28.13 (EA20)؛ عدد ۱۴۰۵ پیش‌بینی است. CPI استفاده نمی‌شود.
A9: Price Basis چیست؟ | B9: ستون Price Basis می‌گوید عدد قیمت «چه نوع قیمتی» است و از کدام سند آمده: پیشنهاد فروشنده (Inquiry)، برآورد مشاور در MTO مرحله FEED یا Basic، یا قیمت خرید. برچسب کلاس برآورد که در خود سند منبع نوشته شده، عیناً داخل همین متن آمده است.
A10: Incoterm چیست؟ | B10: ستون Incoterm شرط تحویل قیمت است (EXW، FOB و ...). Note هر سلول صریحاً می‌گوید این قیمت «شامل» چه هزینه‌هایی هست و «شامل» چه هزینه‌هایی نیست (حمل، بیمه، ترخیص، بازرسی، یدکی، سربار، مالیات، نصب) و هر کدام در کدام سلول سند منبع جداگانه آمده است. جدول معرفی حالت‌ها در Executive Dashboard است.
A11: یعنی چه قیمتی می‌بینیم؟ | B11: Unit Price (Reference) و معادل‌های یورو/دلار/ریال سال منبع = قیمت تجهیز در سطح فروشنده، بدون سربار پروژه، مالیات و نصب (جز آنچه Note همان ردیف خلاف آن را بگوید). قیمت‌های Escalated همان قیمت است که فقط از نظر زمان به سال هدف آورده شده؛ هیچ هزینه دیگری به آن اضافه نشده است.
A12: Estimator | B12: پارامترها در سمت چپ با ضریب متناظر در ستون C؛ محاسبات و نتیجه در پنل سمت راست.
A13: Search | B13: فیلترها در سه بلوک بالا؛ خلاصه نتایج و لیست رکوردها زیر آن.
A14: Vendor_Quotes | B14: سند پیوست استعلام‌ها؛ در محاسبات Master استفاده نمی‌شود.
A15: رکورد جدید | B15: آخرین ردیف Master را کپی و زیر آن Paste کنید تا فرمول‌ها منتقل شوند (Dropdownها تا ردیف ۶۰۰).
... A17: ستون‌های عددی | B17: ستون‌های عددی فقط عدد یا خالی‌اند؛ دلیل خالی بودن در QA Flag آمده.

Sheet Executive Dashboard
A1: EXECUTIVE DASHBOARD – بانک قیمت پمپ
A2: فقط رکوردهای Include = Y شمارش می‌شوند. روی سرستون‌ها و سلول‌ها Note توضیحی یا ترجمه فارسی هست.
A4: Target year | B4: ='Assumptions & FX Reference'!$I$5 -> 1404 | C4: EUR→IRR | D4: ='Assumptions & FX Reference'!$I$8 -> 695268 | E4: USD→IRR | F4: ='Assumptions & FX Reference'!$I$11 -> 658533 | G4: PPI target | H4: ='Assumptions & FX Reference'!$I$12 -> 123.416
A6: 1) Pump sub-categories
A7: Sub-Category | B7: Full Name | C7: شرح | D7: Records | E7: With escalated price | F7: % Material stated | G7: % Seal stated | H7: % Size driver
A8: ROT-CRU | B8: Crude Oil & Main Transfer Pumps | C8: پمپ‌های نفت خام: انتقال نفت شور و نمک‌زدایی‌شده، Booster، Off-spec و انتقال اصلی | D8: =COUNTIFS('Master Database'!$BG$5:$BG$600,"Y",'Master Database'!$E$5:$E$600,A8) -> 15 | E8: =COUNTIFS('Master Database'!$BG$5:$BG$600,"Y",'Master Database'!$E$5:$E$600,A8,'Master Database'!$AG$5:$AG$600,">0") -> 10 | F8: =IF(D8=0,"",COUNTIFS('Master Database'!$BG$5:$BG$600,"Y",'Master Database'!$E$5:$E$600,A8,'Master Database'!$G$5:$G$600,"<>Not stated")/D8) -> 0.46666667 | G8: =IF(D8=0,"",COUNTIFS('Master Database'!$BG$5:$BG$600,"Y",'Master Database'!$E$5:$E$600,A8,'Master Database'!$P$5:$P$600,"<>Not stated")/D8) -> 0 | H8: =IF(D8=0,"",COUNTIFS('Master Database'!$BG$5:$BG$600,"Y",'Master Database'!$E$5:$E$600,A8,'Master Database'!$K$5:$K$600,">0")/D8) -> 0.93333333
A9: ROT-WAT | B9: Desalting & Process Water Pumps | C9: آب فرآیندی واحد: آب رقیق‌سازی، Recycle دیسالتر، آب هوازدایی‌شده، آب شیرین و آب خنک‌کن | D9: =COUNTIFS('Master Database'!$BG$5:$BG$600,"Y",'Master Database'!$E$5:$E$600,A9) -> 36 | E9: =COUNTIFS('Master Database'!$BG$5:$BG$600,"Y",'Master Database'!$E$5:$E$600,A9,'Master Database'!$AG$5:$AG$600,">0") -> 28 | F9: =IF(D9=0,"",COUNTIFS('Master Database'!$BG$5:$BG$600,"Y",'Master Database'!$E$5:$E$600,A9,'Master Database'!$G$5:$G$600,"<>Not stated")/D9) -> 0.66666667 | G9: =IF(D9=0,"",COUNTIFS('Master Database'!$BG$5:$BG$600,"Y",'Master Database'!$E$5:$E$600,A9,'Master Database'!$P$5:$P$600,"<>Not stated")/D9) -> 0 | H9: =IF(D9=0,"",COUNTIFS('Master Database'!$BG$5:$BG$600,"Y",'Master Database'!$E$5:$E$600,A9,'Master Database'!$K$5:$K$600,">0")/D9) -> 0.91666667
A10: ROT-INJ | B10: Produced Water & Disposal Injection Pumps | C10: آب تولیدی و پساب: Booster و پمپ‌های پرفشار تزریق به چاه دفعی | D10: =COUNTIFS('Master Database'!$BG$5:$BG$600,"Y",'Master Database'!$E$5:$E$600,A10) -> 21 | E10: =COUNTIFS('Master Database'!$BG$5:$BG$600,"Y",'Master Database'!$E$5:$E$600,A10,'Master Database'!$AG$5:$AG$600,">0") -> 15 | F10: =IF(D10=0,"",COUNTIFS('Master Database'!$BG$5:$BG$600,"Y",'Master Database'!$E$5:$E$600,A10,'Master Database'!$G$5:$G$600,"<>Not stated")/D10) -> 0.80952381 | G10: =IF(D10=0,"",COUNTIFS('Master Database'!$BG$5:$BG$600,"Y",'Master Database'!$E$5:$E$600,A10,'Master Database'!$P$5:$P$600,"<>Not stated")/D10) -> 0 | H10: =IF(D10=0,"",COUNTIFS('Master Database'!$BG$5:$BG$600,"Y",'Master Database'!$E$5:$E$600,A10,'Master Database'!$K$5:$K$600,">0")/D10) -> 0.76190476
A11: ROT-DRN | B11: Drainage, Flare & OWS Pumps | C11: درین بسته و باز، Flare KO Drum، جداکننده آب و نفت (OWS)، نفت بازیافتی و لجن | D11: =COUNTIFS('Master Database'!$BG$5:$BG$600,"Y",'Master Database'!$E$5:$E$600,A11) -> 33 | E11: =COUNTIFS('Master Database'!$BG$5:$BG$600,"Y",'Master Database'!$E$5:$E$600,A11,'Master Database'!$AG$5:$AG$600,">0") -> 27 | F11: =IF(D11=0,"",COUNTIFS('Master Database'!$BG$5:$BG$600,"Y",'Master Database'!$E$5:$E$600,A11,'Master Database'!$G$5:$G$600,"<>Not stated")/D11) -> 0.75757576 | G11: =IF(D11=0,"",COUNTIFS('Master Database'!$BG$5:$BG$600,"Y",'Master Database'!$E$5:$E$600,A11,'Master Database'!$P$5:$P$600,"<>Not stated")/D11) -> 0 | H11: =IF(D11=0,"",COUNTIFS('Master Database'!$BG$5:$BG$600,"Y",'Master Database'!$E$5:$E$600,A11,'Master Database'!$K$5:$K$600,">0")/D11) -> 0.63636364
A12: ROT-AUX | B12: Chemical, Fuel & Auxiliary Pumps | C12: پمپ‌های جانبی: مواد شیمیایی، گلایکول، گازوئیل و سوخت | D12: =COUNTIFS('Master Database'!$BG$5:$BG$600,"Y",'Master Database'!$E$5:$E$600,A12) -> 11 | E12: =COUNTIFS('Master Database'!$BG$5:$BG$600,"Y",'Master Database'!$E$5:$E$600,A12,'Master Database'!$AG$5:$AG$600,">0") -> 9 | F12: =IF(D12=0,"",COUNTIFS('Master Database'!$BG$5:$BG$600,"Y",'Master Database'!$E$5:$E$600,A12,'Master Database'!$G$5:$G$600,"<>Not stated")/D12) -> 0.63636364 | G12: =IF(D12=0,"",COUNTIFS('Master Database'!$BG$5:$BG$600,"Y",'Master Database'!$E$5:$E$600,A12,'Master Database'!$P$5:$P$600,"<>Not stated")/D12) -> 0 | H12: =IF(D12=0,"",COUNTIFS('Master Database'!$BG$5:$BG$600,"Y",'Master Database'!$E$5:$E$600,A12,'Master Database'!$K$5:$K$600,">0")/D12) -> 0.54545455
A13: ROT-FIR | B13: Firewater & Safety Pumps | C13: آتش‌نشانی: پمپ اصلی برقی و دیزلی، Jockey و بارگیری آب آتش‌نشانی | D13: =COUNTIFS('Master Database'!$BG$5:$BG$600,"Y",'Master Database'!$E$5:$E$600,A13) -> 16 | E13: =COUNTIFS('Master Database'!$BG$5:$BG$600,"Y",'Master Database'!$E$5:$E$600,A13,'Master Database'!$AG$5:$AG$600,">0") -> 16 | F13: =IF(D13=0,"",COUNTIFS('Master Database'!$BG$5:$BG$600,"Y",'Master Database'!$E$5:$E$600,A13,'Master Database'!$G$5:$G$600,"<>Not stated")/D13) -> 0.75 | G13: =IF(D13=0,"",COUNTIFS('Master Database'!$BG$5:$BG$600,"Y",'Master Database'!$E$5:$E$600,A13,'Master Database'!$P$5:$P$600,"<>Not stated")/D13) -> 0 | H13: =IF(D13=0,"",COUNTIFS('Master Database'!$BG$5:$BG$600,"Y",'Master Database'!$E$5:$E$600,A13,'Master Database'!$K$5:$K$600,">0")/D13) -> 1
A14: TOTAL | D14: =COUNTIFS('Master Database'!$BG$5:$BG$600,"Y") -> 132 | E14: =COUNTIFS('Master Database'!$BG$5:$BG$600,"Y",'Master Database'!$AG$5:$AG$600,">0") -> 105 | F14: =IF(D14=0,"",COUNTIFS('Master Database'!$BG$5:$BG$600,"Y",'Master Database'!$G$5:$G$600,"<>Not stated")/D14) -> 0.6969697 | G14: =IF(D14=0,"",COUNTIFS('Master Database'!$BG$5:$BG$600,"Y",'Master Database'!$P$5:$P$600,"<>Not stated")/D14) -> 0 | H14: =IF(D14=0,"",COUNTIFS('Master Database'!$BG$5:$BG$600,"Y",'Master Database'!$K$5:$K$600,">0")/D14) -> 0.8030303
A16: 2) API 610 material classes (Table H.1)
A17: Class | B17: Casing | C17: Impeller | D17: Wear rings / Shaft | E17: Typical service
A18: I-1 | B18: Cast iron | C18: Cast iron | D18: Cast-iron rings; carbon-steel shaft | E18: Water and non-corrosive services, low temperature
A19: I-2 | B19: Cast iron | C19: Bronze | D19: Bronze rings; carbon-steel shaft | E19: Water, fire water, fresh water
A20: S-1 | B20: Carbon steel | C20: Cast iron | D20: Cast-iron rings; carbon-steel shaft | E20: Non-corrosive hydrocarbons
A21: S-3 | B21: Carbon steel | C21: Ni-resist | D21: Ni-resist rings; AISI 4140 shaft | E21: Mildly abrasive or corrosive services
A22: S-4 | B22: Carbon steel | C22: Carbon steel | D22: Cast-iron rings; carbon-steel shaft | E22: General hydrocarbons
A23: S-5 | B23: Carbon steel | C23: Carbon steel | D23: Hardened 12% Cr rings; AISI 4140 shaft | E23: General and hot hydrocarbons
A24: S-6 | B24: Carbon steel | C24: 12% Cr | D24: Hardened 12% Cr rings; 12% Cr shaft | E24: Hot hydrocarbons, sour water, mild corrosion
A25: S-8 | B25: Carbon steel | C25: 316 stainless steel | D25: Hard-faced 316 rings; 316 shaft | E25: More corrosive services
A26: S-9 | B26: Carbon steel | C26: Ni-Cu alloy | D26: Ni-Cu rings; Ni-Cu shaft | E26: Special corrosive services
A27: C-6 | B27: 12% Cr | C27: 12% Cr | D27: Hardened 12% Cr rings; 12% Cr shaft | E27: Boiler feed water, hot hydrocarbons
A28: A-7 | B28: Austenitic stainless steel | C28: Austenitic stainless steel | D28: Hard-faced rings; austenitic shaft | E28: High corrosion, low temperature
... A33: Not stated | B33: — | C33: — | D33: — | E33: Not stated in source
A36: 3) Pump types per API 610
A37: Type | B37: Name | C37: Description
A38: OH1 | B38: Overhung, foot-mounted | C38: Single-stage overhung, foot-mounted; moderate temperature and pressure
A39: OH2 | B39: Overhung, centreline-mounted | C39: Single-stage overhung, centreline-mounted; the most common refinery process pump, suitable for high temperature
A40: OH3 | B40: Vertical in-line, separate bearing bracket | C40: Vertical in-line pump with separate bearing bracket
A41: OH4 | B41: Vertical in-line, rigidly coupled | C41: Vertical in-line pump, rigidly coupled
A42: OH5 | B42: Vertical in-line, close-coupled | C42: Vertical in-line pump, close-coupled (impeller on the motor shaft)
A43: OH6 | B43: High-speed integral gear | C43: High-speed integral-gear pump; low flow, high head
A44: BB1 | B44: Between bearings, 1–2 stage, axially split | C44: Between bearings, 1–2 stage, axially split casing
A45: BB2 | B45: Between bearings, 1–2 stage, radially split | C45: Between bearings, 1–2 stage, radially split; high temperature and pressure
A46: BB3 | B46: Between bearings, multistage, axially split | C46: Multistage, axially split casing; water injection and high-pressure transfer
A47: BB4 | B47: Between bearings, multistage, single casing radially split | C47: Multistage single-casing ring-section pump
A48: BB5 | B48: Between bearings, multistage, double casing (barrel) | C48: Multistage double-casing (barrel) pump; the most severe high-pressure services
... A60: Not stated | B60: — | C60: Pump type not stated in source
A63: 4) Incoterm – delivery basis of prices
A64: Incoterm | B64: Meaning | C64: توضیح فارسی | D64: Used in this bank for
A65: EXW | B65: Ex Works – goods made available at the seller's works; buyer bears all transport, insurance, export/import costs | C65: تحویل درب کارخانه؛ همه هزینه‌های حمل، بیمه، گمرک و ترخیص با خریدار | D65: گچساران ۴ (هزینه حمل، بیمه، بازرسی و یدکی جدا) و اقلام ریالی کوپال
A66: FCA | B66: Free Carrier – delivered to the buyer's carrier at a named place | C66: تحویل به حمل‌کننده خریدار در محل تعیین‌شده | D66: —
A67: FOB | B67: Free On Board – loaded on the vessel at the port of shipment; sea freight, insurance and import costs for buyer | C67: تحویل روی کشتی در بندر مبدأ؛ کرایه حمل دریایی، بیمه و هزینه‌های ورود با خریدار | D67: پازنان ۲ (۱۳۹۳ و ۱۴۰۴) و اقلام ارزی کوپال
A68: CFR | B68: Cost and Freight – seller pays sea freight to the destination port; insurance for buyer | C68: فروشنده کرایه حمل تا بندر مقصد را می‌پردازد؛ بیمه با خریدار | D68: —
A69: CIF | B69: Cost, Insurance and Freight – seller pays sea freight and minimum insurance to the destination port | C69: فروشنده کرایه حمل و بیمه تا بندر مقصد را می‌پردازد | D69: —
A70: DAP | B70: Delivered At Place – delivered at the named destination, not unloaded; import duties for buyer | C70: تحویل در مقصد تعیین‌شده (مثلاً سایت)؛ حقوق ورودی و ترخیص با خریدار | D70: —
A71: DDP | B71: Delivered Duty Paid – delivered at destination with all duties paid by the seller | C71: تحویل در مقصد با پرداخت همه عوارض و حقوق گمرکی توسط فروشنده | D71: —
A72: Domestic Delivered (IRR) | B72: Domestic supply in rials, delivered to site | C72: خرید داخلی ریالی با تحویل در سایت | D72: —
A73: Not stated | B73: Delivery basis not stated in the source | C73: شرط تحویل در منبع ذکر نشده است | D73: رکوردهای CSV و نمونه قیمتی (بدون پروژه و سال)
A74: در همه رکوردها قیمت در سطح فروشنده است: سربار پروژه، مالیات بر ارزش افزوده و هزینه نصب در هیچ قیمتی نیست. آنچه هر قیمت دقیقاً شامل هست یا نیست، در Note ستون Incoterm همان ردیف در Master Database آمده است.

Sheet Master Database
A1: MASTER PUMP PRICE DATABASE – v8
A2: ستون‌های گروه‌بندی‌شده با دکمه «+» بالای ستون‌ها باز می‌شوند. سرستون زرد = ورودی Dropdown، خاکستری = فرمول. سلول زرد پررنگ = مقدار استنباطی (شاهد در Note)؛ سلول آبی = تبدیل ارز با نرخ بانک (نرخ پروژه در Note). روی هر سرستون Note توضیحی هست.
A3: شناسایی | F3: مشخصات کلیدی | V3: مشخصات تکمیلی | Y3: قیمت | AJ3: منبع و سازنده | AL3: دامنه کار (Scope) | AS3: کنترل و ردیابی | AT3: محاسبات نرمال‌سازی و تعدیل (فرمول) | BE3: کنترل و ردیابی | BH3: شناسه اپلیکیشن
A4: Row | B4: Equipment Name | C4: Project Name | D4: Tag No. | E4: Sub-Category | F4: API 610 Type | G4: API 610 Material Class | H4: Capacity (m³/h) | I4: Diff. Head (m) | J4: Power (kW) | K4: Size Driver kW (est.) | L4: Standards | M4: Pump Standard | N4: IPS Standard | O4: NACE MR0175 (Y/N) | P4: Seal Type / Arrangement | Q4: API 682 Category | R4: API 682 Seal Plan | S4: Driver Type | T4: Service Fluid | U4: Quantity | V4: Pump Family | W4: Discharge Pressure (barg) | X4: Power Basis | Y4: Cost Year (Jalali) | Z4: Reference Currency | AA4: Unit Price (Reference) | AB4: Unit Price EUR (source yr) | AC4: Unit Price USD (source yr) | AD4: Unit Price IRR (source yr) | AE4: Price Basis (as stated in source) | AF4: Incoterm | AG4: Escalated Unit Price EUR (target yr) | AH4: Escalated Unit Price USD (target yr) | AI4: Escalated Unit Price IRR (target yr) | AJ4: Manufacturer / Supplier (as in source) | AK4: Project Phase | AL4: Scope: Driver incl. | AM4: Scope: Baseplate & Coupling | AN4: Scope: Seal Support System | AO4: Scope: Comm. Spares | AP4: Scope: 2-yr Spares | AQ4: Scope: TPI | AR4: Scope: Witnessed FAT | AS4: QA Flag | AT4: MAT_F | AU4: SEAL_F | AV4: DRIVE_F | AW4: SCOPE_F | AX4: ALL_F | AY4: Normalized EUR (base config, source yr) | AZ4: PPI Base | BA4: PPI Target | BB4: Floor Applies | BC4: Normalized Escalated EUR | BD4: Cost Coefficient (NormEsc EUR / kW^n) | BE4: Source Document | BF4: Remarks & Notes | BG4: Include in Totals (Y/N) | BH4: Equipment Code | BI4: Record ID
A5: 1 | B5: 2nd Stage Separators Oil Pumps | C5: (نام پروژه در فایل قید نشده است) – CSV 18061405 | D5: (Not stated in source document) | E5: ROT-CRU | F5: Not stated | G5: Not stated | I5: 95.8 | J5: 54.3 | K5: =IF(ISNUMBER(J5),J5,IF(AND(ISNUMBER(H5),ISNUMBER(I5)),H5*I5/(367*'Assumptions & FX Reference'!$I$17),"")) -> 54.3 | L5: =IF(IF(OR(M5="Not stated",M5=""),""," + "&M5)&IF(OR(N5="None",N5=""),""," + "&N5)&IF(O5="Y"," + NACE MR0175","")="","Not stated",MID(IF(OR(M5="Not stated",M5=""),""," + "&M5)&IF(OR(N5="None",N5=""),""," + "&N5)&IF(O5="Y"," + NACE MR0175",""),4,300)) -> Not stated | M5: Not stated | N5: None | O5: Not stated | P5: Not stated | Q5: Not stated | R5: Not stated | S5: Electric Motor | T5: Crude Oil | U5: 1 | V5: Centrifugal | X5: Not stated | Y5: (Not stated) | Z5: USD | AA5: 240000 | AB5: =IF(NOT(ISNUMBER(AA5)),"",IF(NOT(ISNUMBER(Y5)),"",IFERROR(IF(Z5="EUR",AA5,IF(Z5="IRR",AA5/INDEX('Assumptions & FX Reference'!$C$5:$C$25,MATCH(Y5,'Assumptions & FX Reference'!$A$5:$A$25,0)),IF(Z5="USD",AA5*INDEX('Assumptions & FX Reference'!$B$5:$B$25,MATCH(Y5,'Assumptions & FX Reference'!$A$5:$A$25,0))/INDEX('Assumptions & FX Reference'!$C$5:$C$25,MATCH(Y5,'Assumptions & FX Reference'!$A$5:$A$25,0)),""))),""))) | AC5: =IF(NOT(ISNUMBER(AA5)),"",IF(NOT(ISNUMBER(Y5)),"",IFERROR(IF(Z5="USD",AA5,IF(Z5="IRR",AA5/INDEX('Assumptions & FX Reference'!$B$5:$B$25,MATCH(Y5,'Assumptions & FX Reference'!$A$5:$A$25,0)),IF(Z5="EUR",AA5*INDEX('Assumptions & FX Reference'!$C$5:$C$25,MATCH(Y5,'Assumptions & FX Reference'!$A$5:$A$25,0))/INDEX('Assumptions & FX Reference'!$B$5:$B$25,MATCH(Y5,'Assumptions & FX Reference'!$A$5:$A$25,0)),""))),""))) | AD5: =IF(NOT(ISNUMBER(AA5)),"",IF(NOT(ISNUMBER(Y5)),"",IFERROR(IF(Z5="IRR",AA5,IF(Z5="USD",AA5*INDEX('Assumptions & FX Reference'!$B$5:$B$25,MATCH(Y5,'Assumptions & FX Reference'!$A$5:$A$25,0)),IF(Z5="EUR",AA5*INDEX('Assumptions & FX Reference'!$C$5:$C$25,MATCH(Y5,'Assumptions & FX Reference'!$A$5:$A$25,0)),""))),""))) | AE5: Purchase price (USD) – 18061405 pump CSV; project and year not stated | AF5: Not stated | AG5: =IF(AND(Z5="EUR",N(AA5)>5000000),"",IF(AND(ISNUMBER(AB5),ISNUMBER(AZ5),ISNUMBER(BA5)),IF(AND(BB5="Y",ISNUMBER('Assumptions & FX Reference'!$I$15)),MAX(AB5*BA5/AZ5,'Assumptions & FX Reference'!$I$13*BA5/'Assumptions & FX Reference'!$I$15),AB5*BA5/AZ5),"")) | AH5: =IF(AND(ISNUMBER(AG5),ISNUMBER('Assumptions & FX Reference'!$I$8),ISNUMBER('Assumptions & FX Reference'!$I$11)),AG5*'Assumptions & FX Reference'!$I$8/'Assumptions & FX Reference'!$I$11,"") | AI5: =IF(AND(ISNUMBER(AG5),ISNUMBER('Assumptions & FX Reference'!$I$8)),AG5*'Assumptions & FX Reference'!$I$8,"") | AJ5: (Not stated in source document) | AK5: Not stated | AL5: Not stated | AM5: Not stated | AN5: Not stated | AO5: Not stated | AP5: Not stated | AQ5: Not stated | AR5: Not stated | AS5: =IF(AND(Z5="EUR",N(AA5)>5000000),"Check currency (EUR>5M); ","")&IF(NOT(ISNUMBER(AA5)),"No price; ","")&IF(G5="Not stated","Material missing; ","")&IF(P5="Not stated","Seal missing; ","")&IF(K5="","Size driver missing; ","")&IF(NOT(ISNUMBER(AZ5)),"Base-year PPI missing; ","") -> Material missing; Seal missing; Base-year PPI missing; | AT5: =IFERROR(INDEX(Factors_ROT!$F$5:$F$200,MATCH("MAT|"&G5,Factors_ROT!$A$5:$A$200,0)),1) -> 1 | AU5: =IFERROR(INDEX(Factors_ROT!$F$5:$F$200,MATCH("SEAL_ARR|"&P5,Factors_ROT!$A$5:$A$200,0)),1)*IFERROR(INDEX(Factors_ROT!$F$5:$F$200,MATCH("SEAL_CAT|"&Q5,Factors_ROT!$A$5:$A$200,0)),1)*IFERROR(INDEX(Factors_ROT!$F$5:$F$200,MATCH("SEAL_PLAN|"&R5,Factors_ROT!$A$5:$A$200,0)),1) -> 1 | AV5: =IFERROR(INDEX(Factors_ROT!$F$5:$F$200,MATCH("DRV|"&S5,Factors_ROT!$A$5:$A$200,0)),1)*IFERROR(INDEX(Factors_ROT!$F$5:$F$200,MATCH("NACE|"&O5,Factors_ROT!$A$5:$A$200,0)),1) -> 1 | AW5: =IFERROR(INDEX(Factors_ROT!$F$5:$F$200,MATCH("SC_DRV|"&AL5,Factors_ROT!$A$5:$A$200,0)),1)*IFERROR(INDEX(Factors_ROT!$F$5:$F$200,MATCH("SC_BSP|"&AM5,Factors_ROT!$A$5:$A$200,0)),1)*IFERROR(INDEX(Factors_ROT!$F$5:$F$200,MATCH("SC_SEAL|"&AN5,Factors_ROT!$A$5:$A$200,0)),1)*IFERROR(INDEX(Factors_ROT!$F$5:$F$200,MATCH("SC_COMM|"&AO5,Factors_ROT!$A$5:$A$200,0)),1)*IFERROR(INDEX(Factors_ROT!$F$5:$F$200,MATCH("SC_2Y|"&AP5,Factors_ROT!$A$5:$A$200,0)),1)*IFERROR(INDEX(Factors_ROT!$F$5:$F$200,MATCH("SC_TPI|"&AQ5,Factors_ROT!$A$5:$A$200,0)),1)*IFERROR(INDEX(Factors_ROT!$F$5:$F$200,MATCH("SC_FAT|"&AR5,Factors_ROT!$A$5:$A$200,0)),1) -> 1 | AX5: =AT5*AU5*AV5*AW5 -> 1 | AY5: =IF(ISNUMBER(AB5),AB5/AX5,"") | AZ5: =IFERROR(IF(N(INDEX(Escalation_Index!$B$5:$B$25,MATCH(Y5,Escalation_Index!$A$5:$A$25,0)))>0,INDEX(Escalation_Index!$B$5:$B$25,MATCH(Y5,Escalation_Index!$A$5:$A$25,0)),""),"") | BA5: =IF(ISNUMBER('Assumptions & FX Reference'!$I$12),'Assumptions & FX Reference'!$I$12,"") -> 123.416 | BB5: =IF(AND(M5="API 610",LEFT(V5,11)="Centrifugal",OR(LEFT(G5,2)="S-",LEFT(G5,2)="D-")),"Y","N") -> N | BC5: =IF(ISNUMBER(AG5),AG5/AX5,"") | BD5: =IF(AND(ISNUMBER(BC5),ISNUMBER(K5)),IF(K5>0,BC5/K5^'Assumptions & FX Reference'!$I$16,""),"") | BE5: 18061405_Pump_only_CSV.csv – section Pumps (row 1) | BF5: Type: Centrifugal | Driver: موتور الکتریکی (E) | Power: 54.3 kW | Head: 95.8 m | گمرک و حمل: $14400 | Duplicate of the xlsx-sourced record for the same pump (see PUMPS.csv row); kept for reference, excluded from totals. | Original type text: Centrifugal | BG5: N | BH5: PMP | BI5: ="PMP-"&TEXT(A5,"0000") -> PMP-0001
A6: 2 | B6: 3rd Stage Separators Oil Pumps | C6: (نام پروژه در فایل قید نشده است) – CSV 18061405 | D6: (Not stated in source document) | E6: ROT-CRU | F6: Not stated | G6: Not stated | I6: 59.9 | J6: 33.1 | K6: =IF(ISNUMBER(J6),J6,IF(AND(ISNUMBER(H6),ISNUMBER(I6)),H6*I6/(367*'Assumptions & FX Reference'!$I$17),"")) -> 33.1 | L6: =IF(IF(OR(M6="Not stated",M6=""),""," + "&M6)&IF(OR(N6="None",N6=""),""," + "&N6)&IF(O6="Y"," + NACE MR0175","")="","Not stated",MID(IF(OR(M6="Not stated",M6=""),""," + "&M6)&IF(OR(N6="None",N6=""),""," + "&N6)&IF(O6="Y"," + NACE MR0175",""),4,300)) -> Not stated | M6: Not stated | N6: None | O6: Not stated | P6: Not stated | Q6: Not stated | R6: Not stated | S6: Electric Motor | T6: Crude Oil | U6: 1 | V6: Centrifugal | X6: Not stated | Y6: (Not stated) | Z6: USD | AA6: 280000 | AB6: =IF(NOT(ISNUMBER(AA6)),"",IF(NOT(ISNUMBER(Y6)),"",IFERROR(IF(Z6="EUR",AA6,IF(Z6="IRR",AA6/INDEX('Assumptions & FX Reference'!$C$5:$C$25,MATCH(Y6,'Assumptions & FX Reference'!$A$5:$A$25,0)),IF(Z6="USD",AA6*INDEX('Assumptions & FX Reference'!$B$5:$B$25,MATCH(Y6,'Assumptions & FX Reference'!$A$5:$A$25,0))/INDEX('Assumptions & FX Reference'!$C$5:$C$25,MATCH(Y6,'Assumptions & FX Reference'!$A$5:$A$25,0)),""))),""))) | AC6: =IF(NOT(ISNUMBER(AA6)),"",IF(NOT(ISNUMBER(Y6)),"",IFERROR(IF(Z6="USD",AA6,IF(Z6="IRR",AA6/INDEX('Assumptions & FX Reference'!$B$5:$B$25,MATCH(Y6,'Assumptions & FX Reference'!$A$5:$A$25,0)),IF(Z6="EUR",AA6*INDEX('Assumptions & FX Reference'!$C$5:$C$25,MATCH(Y6,'Assumptions & FX Reference'!$A$5:$A$25,0))/INDEX('Assumptions & FX Reference'!$B$5:$B$25,MATCH(Y6,'Assumptions & FX Reference'!$A$5:$A$25,0)),""))),""))) | AD6: =IF(NOT(ISNUMBER(AA6)),"",IF(NOT(ISNUMBER(Y6)),"",IFERROR(IF(Z6="IRR",AA6,IF(Z6="USD",AA6*INDEX('Assumptions & FX Reference'!$B$5:$B$25,MATCH(Y6,'Assumptions & FX Reference'!$A$5:$A$25,0)),IF(Z6="EUR",AA6*INDEX('Assumptions & FX Reference'!$C$5:$C$25,MATCH(Y6,'Assumptions & FX Reference'!$A$5:$A$25,0)),""))),""))) | AE6: Purchase price (USD) – 18061405 pump CSV; project and year not stated | AF6: Not stated | AG6: =IF(AND(Z6="EUR",N(AA6)>5000000),"",IF(AND(ISNUMBER(AB6),ISNUMBER(AZ6),ISNUMBER(BA6)),IF(AND(BB6="Y",ISNUMBER('Assumptions & FX Reference'!$I$15)),MAX(AB6*BA6/AZ6,'Assumptions & FX Reference'!$I$13*BA6/'Assumptions & FX Reference'!$I$15),AB6*BA6/AZ6),"")) | AH6: =IF(AND(ISNUMBER(AG6),ISNUMBER('Assumptions & FX Reference'!$I$8),ISNUMBER('Assumptions & FX Reference'!$I$11)),AG6*'Assumptions & FX Reference'!$I$8/'Assumptions & FX Reference'!$I$11,"") | AI6: =IF(AND(ISNUMBER(AG6),ISNUMBER('Assumptions & FX Reference'!$I$8)),AG6*'Assumptions & FX Reference'!$I$8,"") | AJ6: (Not stated in source document) | AK6: Not stated | AL6: Not stated | AM6: Not stated | AN6: Not stated | AO6: Not stated | AP6: Not stated | AQ6: Not stated | AR6: Not stated | AS6: =IF(AND(Z6="EUR",N(AA6)>5000000),"Check currency (EUR>5M); ","")&IF(NOT(ISNUMBER(AA6)),"No price; ","")&IF(G6="Not stated","Material missing; ","")&IF(P6="Not stated","Seal missing; ","")&IF(K6="","Size driver missing; ","")&IF(NOT(ISNUMBER(AZ6)),"Base-year PPI missing; ","") -> Material missing; Seal missing; Base-year PPI missing; | AT6: =IFERROR(INDEX(Factors_ROT!$F$5:$F$200,MATCH("MAT|"&G6,Factors_ROT!$A$5:$A$200,0)),1) -> 1 | AU6: =IFERROR(INDEX(Factors_ROT!$F$5:$F$200,MATCH("SEAL_ARR|"&P6,Factors_ROT!$A$5:$A$200,0)),1)*IFERROR(INDEX(Factors_ROT!$F$5:$F$200,MATCH("SEAL_CAT|"&Q6,Factors_ROT!$A$5:$A$200,0)),1)*IFERROR(INDEX(Factors_ROT!$F$5:$F$200,MATCH("SEAL_PLAN|"&R6,Factors_ROT!$A$5:$A$200,0)),1) -> 1 | AV6: =IFERROR(INDEX(Factors_ROT!$F$5:$F$200,MATCH("DRV|"&S6,Factors_ROT!$A$5:$A$200,0)),1)*IFERROR(INDEX(Factors_ROT!$F$5:$F$200,MATCH("NACE|"&O6,Factors_ROT!$A$5:$A$200,0)),1) -> 1 | AW6: =IFERROR(INDEX(Factors_ROT!$F$5:$F$200,MATCH("SC_DRV|"&AL6,Factors_ROT!$A$5:$A$200,0)),1)*IFERROR(INDEX(Factors_ROT!$F$5:$F$200,MATCH("SC_BSP|"&AM6,Factors_ROT!$A$5:$A$200,0)),1)*IFERROR(INDEX(Factors_ROT!$F$5:$F$200,MATCH("SC_SEAL|"&AN6,Factors_ROT!$A$5:$A$200,0)),1)*IFERROR(INDEX(Factors_ROT!$F$5:$F$200,MATCH("SC_COMM|"&AO6,Factors_ROT!$A$5:$A$200,0)),1)*IFERROR(INDEX(Factors_ROT!$F$5:$F$200,MATCH("SC_2Y|"&AP6,Factors_ROT!$A$5:$A$200,0)),1)*IFERROR(INDEX(Factors_ROT!$F$5:$F$200,MATCH("SC_TPI|"&AQ6,Factors_ROT!$A$5:$A$200,0)),1)*IFERROR(INDEX(Factors_ROT!$F$5:$F$200,MATCH("SC_FAT|"&AR6,Factors_ROT!$A$5:$A$200,0)),1) -> 1 | AX6: =AT6*AU6*AV6*AW6 -> 1 | AY6: =IF(ISNUMBER(AB6),AB6/AX6,"") | AZ6: =IFERROR(IF(N(INDEX(Escalation_Index!$B$5:$B$25,MATCH(Y6,Escalation_Index!$A$5:$A$25,0)))>0,INDEX(Escalation_Index!$B$5:$B$25,MATCH(Y6,Escalation_Index!$A$5:$A$25,0)),""),"") | BA6: =IF(ISNUMBER('Assumptions & FX Reference'!$I$12),'Assumptions & FX Reference'!$I$12,"") -> 123.416 | BB6: =IF(AND(M6="API 610",LEFT(V6,11)="Centrifugal",OR(LEFT(G6,2)="S-",LEFT(G6,2)="D-")),"Y","N") -> N | BC6: =IF(ISNUMBER(AG6),AG6/AX6,"") | BD6: =IF(AND(ISNUMBER(BC6),ISNUMBER(K6)),IF(K6>0,BC6/K6^'Assumptions & FX Reference'!$I$16,""),"") | BE6: 18061405_Pump_only_CSV.csv – section Pumps (row 2) | BF6: Type: Centrifugal | Driver: موتور الکتریکی (E) | Power: 33.1 kW | Head: 59.9 m | گمرک و حمل: $16800 | Duplicate of the xlsx-sourced record for the same pump (see PUMPS.csv row); kept for reference, excluded from totals. | Original type text: Centrifugal | BG6: N | BH6: PMP | BI6: ="PMP-"&TEXT(A6,"0000") -> PMP-0002
A7: 3 | B7: Stabilized Oil Pump | C7: (نام پروژه در فایل قید نشده است) – CSV 18061405 | D7: (Not stated in source document) | E7: ROT-CRU | F7: Not stated | G7: Not stated | I7: 34.8 | J7: 57.4 | K7: =IF(ISNUMBER(J7),J7,IF(AND(ISNUMBER(H7),ISNUMBER(I7)),H7*I7/(367*'Assumptions & FX Reference'!$I$17),"")) -> 57.4 | L7: =IF(IF(OR(M7="Not stated",M7=""),""," + "&M7)&IF(OR(N7="None",N7=""),""," + "&N7)&IF(O7="Y"," + NACE MR0175","")="","Not stated",MID(IF(OR(M7="Not stated",M7=""),""," + "&M7)&IF(OR(N7="None",N7=""),""," + "&N7)&IF(O7="Y"," + NACE MR0175",""),4,300)) -> Not stated | M7: Not stated | N7: None | O7: Not stated | P7: Not stated | Q7: Not stated | R7: Not stated | S7: Electric Motor | T7: Crude Oil | U7: 1 | V7: Centrifugal | X7: Not stated | Y7: (Not stated) | Z7: USD | AA7: 250000 | AB7: =IF(NOT(ISNUMBER(AA7)),"",IF(NOT(ISNUMBER(Y7)),"",IFERROR(IF(Z7="EUR",AA7,IF(Z7="IRR",AA7/INDEX('Assumptions & FX Reference'!$C$5:$C$25,MATCH(Y7,'Assumptions & FX Reference'!$A$5:$A$25,0)),IF(Z7="USD",AA7*INDEX('Assumptions & FX Reference'!$B$5:$B$25,MATCH(Y7,'Assumptions & FX Reference'!$A$5:$A$25,0))/INDEX('Assumptions & FX Reference'!$C$5:$C$25,MATCH(Y7,'Assumptions & FX Reference'!$A$5:$A$25,0)),""))),""))) | AC7: =IF(NOT(ISNUMBER(AA7)),"",IF(NOT(ISNUMBER(Y7)),"",IFERROR(IF(Z7="USD",AA7,IF(Z7="IRR",AA7/INDEX('Assumptions & FX Reference'!$B$5:$B$25,MATCH(Y7,'Assumptions & FX Reference'!$A$5:$A$25,0)),IF(Z7="EUR",AA7*INDEX('Assumptions & FX Reference'!$C$5:$C$25,MATCH(Y7,'Assumptions & FX Reference'!$A$5:$A$25,0))/INDEX('Assumptions & FX Reference'!$B$5:$B$25,MATCH(Y7,'Assumptions & FX Reference'!$A$5:$A$25,0)),""))),""))) | AD7: =IF(NOT(ISNUMBER(AA7)),"",IF(NOT(ISNUMBER(Y7)),"",IFERROR(IF(Z7="IRR",AA7,IF(Z7="USD",AA7*INDEX('Assumptions & FX Reference'!$B$5:$B$25,MATCH(Y7,'Assumptions & FX Reference'!$A$5:$A$25,0)),IF(Z7="EUR",AA7*INDEX('Assumptions & FX Reference'!$C$5:$C$25,MATCH(Y7,'Assumptions & FX Reference'!$A$5:$A$25,0)),""))),""))) | AE7: Purchase price (USD) – 18061405 pump CSV; project and year not stated | AF7: Not stated | AG7: =IF(AND(Z7="EUR",N(AA7)>5000000),"",IF(AND(ISNUMBER(AB7),ISNUMBER(AZ7),ISNUMBER(BA7)),IF(AND(BB7="Y",ISNUMBER('Assumptions & FX Reference'!$I$15)),MAX(AB7*BA7/AZ7,'Assumptions & FX Reference'!$I$13*BA7/'Assumptions & FX Reference'!$I$15),AB7*BA7/AZ7),"")) | AH7: =IF(AND(ISNUMBER(AG7),ISNUMBER('Assumptions & FX Reference'!$I$8),ISNUMBER('Assumptions & FX Reference'!$I$11)),AG7*'Assumptions & FX Reference'!$I$8/'Assumptions & FX Reference'!$I$11,"") | AI7: =IF(AND(ISNUMBER(AG7),ISNUMBER('Assumptions & FX Reference'!$I$8)),AG7*'Assumptions & FX Reference'!$I$8,"") | AJ7: (Not stated in source document) | AK7: Not stated | AL7: Not stated | AM7: Not stated | AN7: Not stated | AO7: Not stated | AP7: Not stated | AQ7: Not stated | AR7: Not stated | AS7: =IF(AND(Z7="EUR",N(AA7)>5000000),"Check currency (EUR>5M); ","")&IF(NOT(ISNUMBER(AA7)),"No price; ","")&IF(G7="Not stated","Material missing; ","")&IF(P7="Not stated","Seal missing; ","")&IF(K7="","Size driver missing; ","")&IF(NOT(ISNUMBER(AZ7)),"Base-year PPI missing; ","") -> Material missing; Seal missing; Base-year PPI missing; | AT7: =IFERROR(INDEX(Factors_ROT!$F$5:$F$200,MATCH("MAT|"&G7,Factors_ROT!$A$5:$A$200,0)),1) -> 1 | AU7: =IFERROR(INDEX(Factors_ROT!$F$5:$F$200,MATCH("SEAL_ARR|"&P7,Factors_ROT!$A$5:$A$200,0)),1)*IFERROR(INDEX(Factors_ROT!$F$5:$F$200,MATCH("SEAL_CAT|"&Q7,Factors_ROT!$A$5:$A$200,0)),1)*IFERROR(INDEX(Factors_ROT!$F$5:$F$200,MATCH("SEAL_PLAN|"&R7,Factors_ROT!$A$5:$A$200,0)),1) -> 1 | AV7: =IFERROR(INDEX(Factors_ROT!$F$5:$F$200,MATCH("DRV|"&S7,Factors_ROT!$A$5:$A$200,0)),1)*IFERROR(INDEX(Factors_ROT!$F$5:$F$200,MATCH("NACE|"&O7,Factors_ROT!$A$5:$A$200,0)),1) -> 1 | AW7: =IFERROR(INDEX(Factors_ROT!$F$5:$F$200,MATCH("SC_DRV|"&AL7,Factors_ROT!$A$5:$A$200,0)),1)*IFERROR(INDEX(Factors_ROT!$F$5:$F$200,MATCH("SC_BSP|"&AM7,Factors_ROT!$A$5:$A$200,0)),1)*IFERROR(INDEX(Factors_ROT!$F$5:$F$200,MATCH("SC_SEAL|"&AN7,Factors_ROT!$A$5:$A$200,0)),1)*IFERROR(INDEX(Factors_ROT!$F$5:$F$200,MATCH("SC_COMM|"&AO7,Factors_ROT!$A$5:$A$200,0)),1)*IFERROR(INDEX(Factors_ROT!$F$5:$F$200,MATCH("SC_2Y|"&AP7,Factors_ROT!$A$5:$A$200,0)),1)*IFERROR(INDEX(Factors_ROT!$F$5:$F$200,MATCH("SC_TPI|"&AQ7,Factors_ROT!$A$5:$A$200,0)),1)*IFERROR(INDEX(Factors_ROT!$F$5:$F$200,MATCH("SC_FAT|"&AR7,Factors_ROT!$A$5:$A$200,0)),1) -> 1 | AX7: =AT7*AU7*AV7*AW7 -> 1 | AY7: =IF(ISNUMBER(AB7),AB7/AX7,"") | AZ7: =IFERROR(IF(N(INDEX(Escalation_Index!$B$5:$B$25,MATCH(Y7,Escalation_Index!$A$5:$A$25,0)))>0,INDEX(Escalation_Index!$B$5:$B$25,MATCH(Y7,Escalation_Index!$A$5:$A$25,0)),""),"") | BA7: =IF(ISNUMBER('Assumptions & FX Reference'!$I$12),'Assumptions & FX Reference'!$I$12,"") -> 123.416 | BB7: =IF(AND(M7="API 610",LEFT(V7,11)="Centrifugal",OR(LEFT(G7,2)="S-",LEFT(G7,2)="D-")),"Y","N") -> N | BC7: =IF(ISNUMBER(AG7),AG7/AX7,"") | BD7: =IF(AND(ISNUMBER(BC7),ISNUMBER(K7)),IF(K7>0,BC7/K7^'Assumptions & FX Reference'!$I$16,""),"") | BE7: 18061405_Pump_only_CSV.csv – section Pumps (row 3) | BF7: Type: Centrifugal | Driver: موتور الکتریکی (E) | Power: 57.4 kW | Head: 34.8 m | گمرک و حمل: $15000 | Duplicate of the xlsx-sourced record for the same pump (see PUMPS.csv row); kept for reference, excluded from totals. | Original type text: Centrifugal | BG7: N | BH7: PMP | BI7: ="PMP-"&TEXT(A7,"0000") -> PMP-0003
A8: 4 | B8: Product Oil Pump | C8: (نام پروژه در فایل قید نشده است) – CSV 18061405 | D8: (Not stated in source document) | E8: ROT-CRU | F8: Not stated | G8: Not stated | I8: 329 | J8: 379 | K8: =IF(ISNUMBER(J8),J8,IF(AND(ISNUMBER(H8),ISNUMBER(I8)),H8*I8/(367*'Assumptions & FX Reference'!$I$17),"")) -> 379 | L8: =IF(IF(OR(M8="Not stated",M8=""),""," + "&M8)&IF(OR(N8="None",N8=""),""," + "&N8)&IF(O8="Y"," + NACE MR0175","")="","Not stated",MID(IF(OR(M8="Not stated",M8=""),""," + "&M8)&IF(OR(N8="None",N8=""),""," + "&N8)&IF(O8="Y"," + NACE MR0175",""),4,300)) -> Not stated | M8: Not stated | N8: None | O8: Not stated | P8: Not stated | Q8: Not stated | R8: Not stated | S8: Electric Motor | T8: Crude Oil | U8: 1 | V8: Centrifugal | X8: Not stated | Y8: (Not stated) | Z8: USD | AA8: 420000 | AB8: =IF(NOT(ISNUMBER(AA8)),"",IF(NOT(ISNUMBER(Y8)),"",IFERROR(IF(Z8="EUR",AA8,IF(Z8="IRR",AA8/INDEX('Assumptions & FX Reference'!$C$5:$C$25,MATCH(Y8,'Assumptions & FX Reference'!$A$5:$A$25,0)),IF(Z8="USD",AA8*INDEX('Assumptions & FX Reference'!$B$5:$B$25,MATCH(Y8,'Assumptions & FX Reference'!$A$5:$A$25,0))/INDEX('Assumptions & FX Reference'!$C$5:$C$25,MATCH(Y8,'Assumptions & FX Reference'!$A$5:$A$25,0)),""))),""))) | AC8: =IF(NOT(ISNUMBER(AA8)),"",IF(NOT(ISNUMBER(Y8)),"",IFERROR(IF(Z8="USD",AA8,IF(Z8="IRR",AA8/INDEX('Assumptions & FX Reference'!$B$5:$B$25,MATCH(Y8,'Assumptions & FX Reference'!$A$5:$A$25,0)),IF(Z8="EUR",AA8*INDEX('Assumptions & FX Reference'!$C$5:$C$25,MATCH(Y8,'Assumptions & FX Reference'!$A$5:$A$25,0))/INDEX('Assumptions & FX Reference'!$B$5:$B$25,MATCH(Y8,'Assumptions & FX Reference'!$A$5:$A$25,0)),""))),""))) | AD8: =IF(NOT(ISNUMBER(AA8)),"",IF(NOT(ISNUMBER(Y8)),"",IFERROR(IF(Z8="IRR",AA8,IF(Z8="USD",AA8*INDEX('Assumptions & FX Reference'!$B$5:$B$25,MATCH(Y8,'Assumptions & FX Reference'!$A$5:$A$25,0)),IF(Z8="EUR",AA8*INDEX('Assumptions & FX Reference'!$C$5:$C$25,MATCH(Y8,'Assumptions & FX Reference'!$A$5:$A$25,0)),""))),""))) | AE8: Purchase price (USD) – 18061405 pump CSV; project and year not stated | AF8: Not stated | AG8: =IF(AND(Z8="EUR",N(AA8)>5000000),"",IF(AND(ISNUMBER(AB8),ISNUMBER(AZ8),ISNUMBER(BA8)),IF(AND(BB8="Y",ISNUMBER('Assumptions & FX Reference'!$I$15)),MAX(AB8*BA8/AZ8,'Assumptions & FX Reference'!$I$13*BA8/'Assumptions & FX Reference'!$I$15),AB8*BA8/AZ8),"")) | AH8: =IF(AND(ISNUMBER(AG8),ISNUMBER('Assumptions & FX Reference'!$I$8),ISNUMBER('Assumptions & FX Reference'!$I$11)),AG8*'Assumptions & FX Reference'!$I$8/'Assumptions & FX Reference'!$I$11,"") | AI8: =IF(AND(ISNUMBER(AG8),ISNUMBER('Assumptions & FX Reference'!$I$8)),AG8*'Assumptions & FX Reference'!$I$8,"") | AJ8: (Not stated in source document) | AK8: Not stated | AL8: Not stated | AM8: Not stated | AN8: Not stated | AO8: Not stated | AP8: Not stated | AQ8: Not stated | AR8: Not stated | AS8: =IF(AND(Z8="EUR",N(AA8)>5000000),"Check currency (EUR>5M); ","")&IF(NOT(ISNUMBER(AA8)),"No price; ","")&IF(G8="Not stated","Material missing; ","")&IF(P8="Not stated","Seal missing; ","")&IF(K8="","Size driver missing; ","")&IF(NOT(ISNUMBER(AZ8)),"Base-year PPI missing; ","") -> Material missing; Seal missing; Base-year PPI missing; | AT8: =IFERROR(INDEX(Factors_ROT!$F$5:$F$200,MATCH("MAT|"&G8,Factors_ROT!$A$5:$A$200,0)),1) -> 1 | AU8: =IFERROR(INDEX(Factors_ROT!$F$5:$F$200,MATCH("SEAL_ARR|"&P8,Factors_ROT!$A$5:$A$200,0)),1)*IFERROR(INDEX(Factors_ROT!$F$5:$F$200,MATCH("SEAL_CAT|"&Q8,Factors_ROT!$A$5:$A$200,0)),1)*IFERROR(INDEX(Factors_ROT!$F$5:$F$200,MATCH("SEAL_PLAN|"&R8,Factors_ROT!$A$5:$A$200,0)),1) -> 1 | AV8: =IFERROR(INDEX(Factors_ROT!$F$5:$F$200,MATCH("DRV|"&S8,Factors_ROT!$A$5:$A$200,0)),1)*IFERROR(INDEX(Factors_ROT!$F$5:$F$200,MATCH("NACE|"&O8,Factors_ROT!$A$5:$A$200,0)),1) -> 1 | AW8: =IFERROR(INDEX(Factors_ROT!$F$5:$F$200,MATCH("SC_DRV|"&AL8,Factors_ROT!$A$5:$A$200,0)),1)*IFERROR(INDEX(Factors_ROT!$F$5:$F$200,MATCH("SC_BSP|"&AM8,Factors_ROT!$A$5:$A$200,0)),1)*IFERROR(INDEX(Factors_ROT!$F$5:$F$200,MATCH("SC_SEAL|"&AN8,Factors_ROT!$A$5:$A$200,0)),1)*IFERROR(INDEX(Factors_ROT!$F$5:$F$200,MATCH("SC_COMM|"&AO8,Factors_ROT!$A$5:$A$200,0)),1)*IFERROR(INDEX(Factors_ROT!$F$5:$F$200,MATCH("SC_2Y|"&AP8,Factors_ROT!$A$5:$A$200,0)),1)*IFERROR(INDEX(Factors_ROT!$F$5:$F$200,MATCH("SC_TPI|"&AQ8,Factors_ROT!$A$5:$A$200,0)),1)*IFERROR(INDEX(Factors_ROT!$F$5:$F$200,MATCH("SC_FAT|"&AR8,Factors_ROT!$A$5:$A$200,0)),1) -> 1 | AX8: =AT8*AU8*AV8*AW8 -> 1 | AY8: =IF(ISNUMBER(AB8),AB8/AX8,"") | AZ8: =IFERROR(IF(N(INDEX(Escalation_Index!$B$5:$B$25,MATCH(Y8,Escalation_Index!$A$5:$A$25,0)))>0,INDEX(Escalation_Index!$B$5:$B$25,MATCH(Y8,Escalation_Index!$A$5:$A$25,0)),""),"") | BA8: =IF(ISNUMBER('Assumptions & FX Reference'!$I$12),'Assumptions & FX Reference'!$I$12,"") -> 123.416 | BB8: =IF(AND(M8="API 610",LEFT(V8,11)="Centrifugal",OR(LEFT(G8,2)="S-",LEFT(G8,2)="D-")),"Y","N") -> N | BC8: =IF(ISNUMBER(AG8),AG8/AX8,"") | BD8: =IF(AND(ISNUMBER(BC8),ISNUMBER(K8)),IF(K8>0,BC8/K8^'Assumptions & FX Reference'!$I$16,""),"") | BE8: 18061405_Pump_only_CSV.csv – section Pumps (row 4) | BF8: Type: Centrifugal | Driver: موتور الکتریکی (E) | Power: 379 kW | Head: 329 m | گمرک و حمل: $25200 | Duplicate of the xlsx-sourced record for the same pump (see PUMPS.csv row); kept for reference, excluded from totals. | Original type text: Centrifugal | BG8: N | BH8: PMP | BI8: ="PMP-"&TEXT(A8,"0000") -> PMP-0004
A9: 5 | B9: Off Spec Crude Pump | C9: (نام پروژه در فایل قید نشده است) – CSV 18061405 | D9: (Not stated in source document) | E9: ROT-CRU | F9: Not stated | G9: Not stated | I9: 311.3 | J9: 48 | K9: =IF(ISNUMBER(J9),J9,IF(AND(ISNUMBER(H9),ISNUMBER(I9)),H9*I9/(367*'Assumptions & FX Reference'!$I$17),"")) -> 48 | L9: =IF(IF(OR(M9="Not stated",M9=""),""," + "&M9)&IF(OR(N9="None",N9=""),""," + "&N9)&IF(O9="Y"," + NACE MR0175","")="","Not stated",MID(IF(OR(M9="Not stated",M9=""),""," + "&M9)&IF(OR(N9="None",N9=""),""," + "&N9)&IF(O9="Y"," + NACE MR0175",""),4,300)) -> Not stated | M9: Not stated | N9: None | O9: Not stated | P9: Not stated | Q9: Not stated | R9: Not stated | S9: Electric Motor | T9: Crude Oil | U9: 1 | V9: Centrifugal | X9: Not stated | Y9: (Not stated) | Z9: USD | AA9: 75000 | AB9: =IF(NOT(ISNUMBER(AA9)),"",IF(NOT(ISNUMBER(Y9)),"",IFERROR(IF(Z9="EUR",AA9,IF(Z9="IRR",AA9/INDEX('Assumptions & FX Reference'!$C$5:$C$25,MATCH(Y9,'Assumptions & FX Reference'!$A$5:$A$25,0)),IF(Z9="USD",AA9*INDEX('Assumptions & FX Reference'!$B$5:$B$25,MATCH(Y9,'Assumptions & FX Reference'!$A$5:$A$25,0))/INDEX('Assumptions & FX Reference'!$C$5:$C$25,MATCH(Y9,'Assumptions & FX Reference'!$A$5:$A$25,0)),""))),""))) | AC9: =IF(NOT(ISNUMBER(AA9)),"",IF(NOT(ISNUMBER(Y9)),"",IFERROR(IF(Z9="USD",AA9,IF(Z9="IRR",AA9/INDEX('Assumptions & FX Reference'!$B$5:$B$25,MATCH(Y9,'Assumptions & FX Reference'!$A$5:$A$25,0)),IF(Z9="EUR",AA9*INDEX('Assumptions & FX Reference'!$C$5:$C$25,MATCH(Y9,'Assumptions & FX Reference'!$A$5:$A$25,0))/INDEX('Assumptions & FX Reference'!$B$5:$B$25,MATCH(Y9,'Assumptions & FX Reference'!$A$5:$A$25,0)),""))),""))) | AD9: =IF(NOT(ISNUMBER(AA9)),"",IF(NOT(ISNUMBER(Y9)),"",IFERROR(IF(Z9="IRR",AA9,IF(Z9="USD",AA9*INDEX('Assumptions & FX Reference'!$B$5:$B$25,MATCH(Y9,'Assumptions & FX Reference'!$A$5:$A$25,0)),IF(Z9="EUR",AA9*INDEX('Assumptions & FX Reference'!$C$5:$C$25,MATCH(Y9,'Assumptions & FX Reference'!$A$5:$A$25,0)),""))),""))) | AE9: Purchase price (USD) – 18061405 pump CSV; project and year not stated | AF9: Not stated | AG9: =IF(AND(Z9="EUR",N(AA9)>5000000),"",IF(AND(ISNUMBER(AB9),ISNUMBER(AZ9),ISNUMBER(BA9)),IF(AND(BB9="Y",ISNUMBER('Assumptions & FX Reference'!$I$15)),MAX(AB9*BA9/AZ9,'Assumptions & FX Reference'!$I$13*BA9/'Assumptions & FX Reference'!$I$15),AB9*BA9/AZ9),"")) | AH9: =IF(AND(ISNUMBER(AG9),ISNUMBER('Assumptions & FX Reference'!$I$8),ISNUMBER('Assumptions & FX Reference'!$I$11)),AG9*'Assumptions & FX Reference'!$I$8/'Assumptions & FX Reference'!$I$11,"") | AI9: =IF(AND(ISNUMBER(AG9),ISNUMBER('Assumptions & FX Reference'!$I$8)),AG9*'Assumptions & FX Reference'!$I$8,"") | AJ9: (Not stated in source document) | AK9: Not stated | AL9: Not stated | AM9: Not stated | AN9: Not stated | AO9: Not stated | AP9: Not stated | AQ9: Not stated | AR9: Not stated | AS9: =IF(AND(Z9="EUR",N(AA9)>5000000),"Check currency (EUR>5M); ","")&IF(NOT(ISNUMBER(AA9)),"No price; ","")&IF(G9="Not stated","Material missing; ","")&IF(P9="Not stated","Seal missing; ","")&IF(K9="","Size driver missing; ","")&IF(NOT(ISNUMBER(AZ9)),"Base-year PPI missing; ","") -> Material missing; Seal missing; Base-year PPI missing; | AT9: =IFERROR(INDEX(Factors_ROT!$F$5:$F$200,MATCH("MAT|"&G9,Factors_ROT!$A$5:$A$200,0)),1) -> 1 | AU9: =IFERROR(INDEX(Factors_ROT!$F$5:$F$200,MATCH("SEAL_ARR|"&P9,Factors_ROT!$A$5:$A$200,0)),1)*IFERROR(INDEX(Factors_ROT!$F$5:$F$200,MATCH("SEAL_CAT|"&Q9,Factors_ROT!$A$5:$A$200,0)),1)*IFERROR(INDEX(Factors_ROT!$F$5:$F$200,MATCH("SEAL_PLAN|"&R9,Factors_ROT!$A$5:$A$200,0)),1) -> 1 | AV9: =IFERROR(INDEX(Factors_ROT!$F$5:$F$200,MATCH("DRV|"&S9,Factors_ROT!$A$5:$A$200,0)),1)*IFERROR(INDEX(Factors_ROT!$F$5:$F$200,MATCH("NACE|"&O9,Factors_ROT!$A$5:$A$200,0)),1) -> 1 | AW9: =IFERROR(INDEX(Factors_ROT!$F$5:$F$200,MATCH("SC_DRV|"&AL9,Factors_ROT!$A$5:$A$200,0)),1)*IFERROR(INDEX(Factors_ROT!$F$5:$F$200,MATCH("SC_BSP|"&AM9,Factors_ROT!$A$5:$A$200,0)),1)*IFERROR(INDEX(Factors_ROT!$F$5:$F$200,MATCH("SC_SEAL|"&AN9,Factors_ROT!$A$5:$A$200,0)),1)*IFERROR(INDEX(Factors_ROT!$F$5:$F$200,MATCH("SC_COMM|"&AO9,Factors_ROT!$A$5:$A$200,0)),1)*IFERROR(INDEX(Factors_ROT!$F$5:$F$200,MATCH("SC_2Y|"&AP9,Factors_ROT!$A$5:$A$200,0)),1)*IFERROR(INDEX(Factors_ROT!$F$5:$F$200,MATCH("SC_TPI|"&AQ9,Factors_ROT!$A$5:$A$200,0)),1)*IFERROR(INDEX(Factors_ROT!$F$5:$F$200,MATCH("SC_FAT|"&AR9,Factors_ROT!$A$5:$A$200,0)),1) -> 1 | AX9: =AT9*AU9*AV9*AW9 -> 1 | AY9: =IF(ISNUMBER(AB9),AB9/AX9,"") | AZ9: =IFERROR(IF(N(INDEX(Escalation_Index!$B$5:$B$25,MATCH(Y9,Escalation_Index!$A$5:$A$25,0)))>0,INDEX(Escalation_Index!$B$5:$B$25,MATCH(Y9,Escalation_Index!$A$5:$A$25,0)),""),"") | BA9: =IF(ISNUMBER('Assumptions & FX Reference'!$I$12),'Assumptions & FX Reference'!$I$12,"") -> 123.416 | BB9: =IF(AND(M9="API 610",LEFT(V9,11)="Centrifugal",OR(LEFT(G9,2)="S-",LEFT(G9,2)="D-")),"Y","N") -> N | BC9: =IF(ISNUMBER(AG9),AG9/AX9,"") | BD9: =IF(AND(ISNUMBER(BC9),ISNUMBER(K9)),IF(K9>0,BC9/K9^'Assumptions & FX Reference'!$I$16,""),"") | BE9: 18061405_Pump_only_CSV.csv – section Pumps (row 5) | BF9: Type: Centrifugal | Driver: موتور الکتریکی (E) | Power: 48 kW | Head: 311.3 m | گمرک و حمل: $4500 | Duplicate of the xlsx-sourced record for the same pump (see PUMPS.csv row); kept for reference, excluded from totals. | Original type text: Centrifugal | BG9: N | BH9: PMP | BI9: ="PMP-"&TEXT(A9,"0000") -> PMP-0005
A10: 6 | B10: Second Stage Desalter Water Criculated Pump | C10: (نام پروژه در فایل قید نشده است) – CSV 18061405 | D10: (Not stated in source document) | E10: ROT-WAT | F10: Not stated | G10: Not stated | I10: 32 | J10: 2.2 | K10: =IF(ISNUMBER(J10),J10,IF(AND(ISNUMBER(H10),ISNUMBER(I10)),H10*I10/(367*'Assumptions & FX Reference'!$I$17),"")) -> 2.2 | L10: =IF(IF(OR(M10="Not stated",M10=""),""," + "&M10)&IF(OR(N10="None",N10=""),""," + "&N10)&IF(O10="Y"," + NACE MR0175","")="","Not stated",MID(IF(OR(M10="Not stated",M10=""),""," + "&M10)&IF(OR(N10="None",N10=""),""," + "&N10)&IF(O10="Y"," + NACE MR0175",""),4,300)) -> Not stated | M10: Not stated | N10: None | O10: Not stated | P10: Not stated | Q10: Not stated | R10: Not stated | S10: Electric Motor | T10: Process / Dilution Water | U10: 1 | V10: Centrifugal | X10: Not stated | Y10: (Not stated) | Z10: USD | AA10: 60000 | AB10: =IF(NOT(ISNUMBER(AA10)),"",IF(NOT(ISNUMBER(Y10)),"",IFERROR(IF(Z10="EUR",AA10,IF(Z10="IRR",AA10/INDEX('Assumptions & FX Reference'!$C$5:$C$25,MATCH(Y10,'Assumptions & FX Reference'!$A$5:$A$25,0)),IF(Z10="USD",AA10*INDEX('Assumptions & FX Reference'!$B$5:$B$25,MATCH(Y10,'Assumptions & FX Reference'!$A$5:$A$25,0))/INDEX('Assumptions & FX Reference'!$C$5:$C$25,MATCH(Y10,'Assumptions & FX Reference'!$A$5:$A$25,0)),""))),""))) | AC10: =IF(NOT(ISNUMBER(AA10)),"",IF(NOT(ISNUMBER(Y10)),"",IFERROR(IF(Z10="USD",AA10,IF(Z10="IRR",AA10/INDEX('Assumptions & FX Reference'!$B$5:$B$25,MATCH(Y10,'Assumptions & FX Reference'!$A$5:$A$25,0)),IF(Z10="EUR",AA10*INDEX('Assumptions & FX Reference'!$C$5:$C$25,MATCH(Y10,'Assumptions & FX Reference'!$A$5:$A$25,0))/INDEX('Assumptions & FX Reference'!$B$5:$B$25,MATCH(Y10,'Assumptions & FX Reference'!$A$5:$A$25,0)),""))),""))) | AD10: =IF(NOT(ISNUMBER(AA10)),"",IF(NOT(ISNUMBER(Y10)),"",IFERROR(IF(Z10="IRR",AA10,IF(Z10="USD",AA10*INDEX('Assumptions & FX Reference'!$B$5:$B$25,MATCH(Y10,'Assumptions & FX Reference'!$A$5:$A$25,0)),IF(Z10="EUR",AA10*INDEX('Assumptions & FX Reference'!$C$5:$C$25,MATCH(Y10,'Assumptions & FX Reference'!$A$5:$A$25,0)),""))),""))) | AE10: Purchase price (USD) – 18061405 pump CSV; project and year not stated | AF10: Not stated | AG10: =IF(AND(Z10="EUR",N(AA10)>5000000),"",IF(AND(ISNUMBER(AB10),ISNUMBER(AZ10),ISNUMBER(BA10)),IF(AND(BB10="Y",ISNUMBER('Assumptions & FX Reference'!$I$15)),MAX(AB10*BA10/AZ10,'Assumptions & FX Reference'!$I$13*BA10/'Assumptions & FX Reference'!$I$15),AB10*BA10/AZ10),"")) | AH10: =IF(AND(ISNUMBER(AG10),ISNUMBER('Assumptions & FX Reference'!$I$8),ISNUMBER('Assumptions & FX Reference'!$I$11)),AG10*'Assumptions & FX Reference'!$I$8/'Assumptions & FX Reference'!$I$11,"") | AI10: =IF(AND(ISNUMBER(AG10),ISNUMBER('Assumptions & FX Reference'!$I$8)),AG10*'Assumptions & FX Reference'!$I$8,"") | AJ10: (Not stated in source document) | AK10: Not stated | AL10: Not stated | AM10: Not stated | AN10: Not stated | AO10: Not stated | AP10: Not stated | AQ10: Not stated | AR10: Not stated | AS10: =IF(AND(Z10="EUR",N(AA10)>5000000),"Check currency (EUR>5M); ","")&IF(NOT(ISNUMBER(AA10)),"No price; ","")&IF(G10="Not stated","Material missing; ","")&IF(P10="Not stated","Seal missing; ","")&IF(K10="","Size driver missing; ","")&IF(NOT(ISNUMBER(AZ10)),"Base-year PPI missing; ","") -> Material missing; Seal missing; Base-year PPI missing; | AT10: =IFERROR(INDEX(Factors_ROT!$F$5:$F$200,MATCH("MAT|"&G10,Factors_ROT!$A$5:$A$200,0)),1) -> 1 | AU10: =IFERROR(INDEX(Factors_ROT!$F$5:$F$200,MATCH("SEAL_ARR|"&P10,Factors_ROT!$A$5:$A$200,0)),1)*IFERROR(INDEX(Factors_ROT!$F$5:$F$200,MATCH("SEAL_CAT|"&Q10,Factors_ROT!$A$5:$A$200,0)),1)*IFERROR(INDEX(Factors_ROT!$F$5:$F$200,MATCH("SEAL_PLAN|"&R10,Factors_ROT!$A$5:$A$200,0)),1) -> 1 | AV10: =IFERROR(INDEX(Factors_ROT!$F$5:$F$200,MATCH("DRV|"&S10,Factors_ROT!$A$5:$A$200,0)),1)*IFERROR(INDEX(Factors_ROT!$F$5:$F$200,MATCH("NACE|"&O10,Factors_ROT!$A$5:$A$200,0)),1) -> 1 | AW10: =IFERROR(INDEX(Factors_ROT!$F$5:$F$200,MATCH("SC_DRV|"&AL10,Factors_ROT!$A$5:$A$200,0)),1)*IFERROR(INDEX(Factors_ROT!$F$5:$F$200,MATCH("SC_BSP|"&AM10,Factors_ROT!$A$5:$A$200,0)),1)*IFERROR(INDEX(Factors_ROT!$F$5:$F$200,MATCH("SC_SEAL|"&AN10,Factors_ROT!$A$5:$A$200,0)),1)*IFERROR(INDEX(Factors_ROT!$F$5:$F$200,MATCH("SC_COMM|"&AO10,Factors_ROT!$A$5:$A$200,0)),1)*IFERROR(INDEX(Factors_ROT!$F$5:$F$200,MATCH("SC_2Y|"&AP10,Factors_ROT!$A$5:$A$200,0)),1)*IFERROR(INDEX(Factors_ROT!$F$5:$F$200,MATCH("SC_TPI|"&AQ10,Factors_ROT!$A$5:$A$200,0)),1)*IFERROR(INDEX(Factors_ROT!$F$5:$F$200,MATCH("SC_FAT|"&AR10,Factors_ROT!$A$5:$A$200,0)),1) -> 1 | AX10: =AT10*AU10*AV10*AW10 -> 1 | AY10: =IF(ISNUMBER(AB10),AB10/AX10,"") | AZ10: =IFERROR(IF(N(INDEX(Escalation_Index!$B$5:$B$25,MATCH(Y10,Escalation_Index!$A$5:$A$25,0)))>0,INDEX(Escalation_Index!$B$5:$B$25,MATCH(Y10,Escalation_Index!$A$5:$A$25,0)),""),"") | BA10: =IF(ISNUMBER('Assumptions & FX Reference'!$I$12),'Assumptions & FX Reference'!$I$12,"") -> 123.416 | BB10: =IF(AND(M10="API 610",LEFT(V10,11)="Centrifugal",OR(LEFT(G10,2)="S-",LEFT(G10,2)="D-")),"Y","N") -> N | BC10: =IF(ISNUMBER(AG10),AG10/AX10,"") | BD10: =IF(AND(ISNUMBER(BC10),ISNUMBER(K10)),IF(K10>0,BC10/K10^'Assumptions & FX Reference'!$I$16,""),"") | BE10: 18061405_Pump_only_CSV.csv – section Pumps (row 6) | BF10: Type: Centrifugal | Driver: موتور الکتریکی (E) | Power: 2.2 kW | Head: 32 m | گمرک و حمل: $3600 | Duplicate of the xlsx-sourced record for the same pump (see PUMPS.csv row); kept for reference, excluded from totals. | Original type text: Centrifugal | BG10: N | BH10: PMP | BI10: ="PMP-"&TEXT(A10,"0000") -> PMP-0006
A11: 7 | B11: Degassing Water Pump | C11: (نام پروژه در فایل قید نشده است) – CSV 18061405 | D11: (Not stated in source document) | E11: ROT-WAT | F11: Not stated | G11: Not stated | I11: 36.2 | J11: 13.1 | K11: =IF(ISNUMBER(J11),J11,IF(AND(ISNUMBER(H11),ISNUMBER(I11)),H11*I11/(367*'Assumptions & FX Reference'!$I$17),"")) -> 13.1 | L11: =IF(IF(OR(M11="Not stated",M11=""),""," + "&M11)&IF(OR(N11="None",N11=""),""," + "&N11)&IF(O11="Y"," + NACE MR0175","")="","Not stated",MID(IF(OR(M11="Not stated",M11=""),""," + "&M11)&IF(OR(N11="None",N11=""),""," + "&N11)&IF(O11="Y"," + NACE MR0175",""),4,300)) -> Not stated | M11: Not stated | N11: None | O11: Not stated | P11: Not stated | Q11: Not stated | R11: Not stated | S11: Electric Motor | T11: Process / Dilution Water | U11: 1 | V11: Centrifugal | X11: Not stated | Y11: (Not stated) | Z11: USD | AA11: 60000 | AB11: =IF(NOT(ISNUMBER(AA11)),"",IF(NOT(ISNUMBER(Y11)),"",IFERROR(IF(Z11="EUR",AA11,IF(Z11="IRR",AA11/INDEX('Assumptions & FX Reference'!$C$5:$C$25,MATCH(Y11,'Assumptions & FX Reference'!$A$5:$A$25,0)),IF(Z11="USD",AA11*INDEX('Assumptions & FX Reference'!$B$5:$B$25,MATCH(Y11,'Assumptions & FX Reference'!$A$5:$A$25,0))/INDEX('Assumptions & FX Reference'!$C$5:$C$25,MATCH(Y11,'Assumptions & FX Reference'!$A$5:$A$25,0)),""))),""))) | AC11: =IF(NOT(ISNUMBER(AA11)),"",IF(NOT(ISNUMBER(Y11)),"",IFERROR(IF(Z11="USD",AA11,IF(Z11="IRR",AA11/INDEX('Assumptions & FX Reference'!$B$5:$B$25,MATCH(Y11,'Assumptions & FX Reference'!$A$5:$A$25,0)),IF(Z11="EUR",AA11*INDEX('Assumptions & FX Reference'!$C$5:$C$25,MATCH(Y11,'Assumptions & FX Reference'!$A$5:$A$25,0))/INDEX('Assumptions & FX Reference'!$B$5:$B$25,MATCH(Y11,'Assumptions & FX Reference'!$A$5:$A$25,0)),""))),""))) | AD11: =IF(NOT(ISNUMBER(AA11)),"",IF(NOT(ISNUMBER(Y11)),"",IFERROR(IF(Z11="IRR",AA11,IF(Z11="USD",AA11*INDEX('Assumptions & FX Reference'!$B$5:$B$25,MATCH(Y11,'Assumptions & FX Reference'!$A$5:$A$25,0)),IF(Z11="EUR",AA11*INDEX('Assumptions & FX Reference'!$C$5:$C$25,MATCH(Y11,'Assumptions & FX Reference'!$A$5:$A$25,0)),""))),""))) | AE11: Purchase price (USD) – 18061405 pump CSV; project and year not stated | AF11: Not stated | AG11: =IF(AND(Z11="EUR",N(AA11)>5000000),"",IF(AND(ISNUMBER(AB11),ISNUMBER(AZ11),ISNUMBER(BA11)),IF(AND(BB11="Y",ISNUMBER('Assumptions & FX Reference'!$I$15)),MAX(AB11*BA11/AZ11,'Assumptions & FX Reference'!$I$13*BA11/'Assumptions & FX Reference'!$I$15),AB11*BA11/AZ11),"")) | AH11: =IF(AND(ISNUMBER(AG11),ISNUMBER('Assumptions & FX Reference'!$I$8),ISNUMBER('Assumptions & FX Reference'!$I$11)),AG11*'Assumptions & FX Reference'!$I$8/'Assumptions & FX Reference'!$I$11,"") | AI11: =IF(AND(ISNUMBER(AG11),ISNUMBER('Assumptions & FX Reference'!$I$8)),AG11*'Assumptions & FX Reference'!$I$8,"") | AJ11: (Not stated in source document) | AK11: Not stated | AL11: Not stated | AM11: Not stated | AN11: Not stated | AO11: Not stated | AP11: Not stated | AQ11: Not stated | AR11: Not stated | AS11: =IF(AND(Z11="EUR",N(AA11)>5000000),"Check currency (EUR>5M); ","")&IF(NOT(ISNUMBER(AA11)),"No price; ","")&IF(G11="Not stated","Material missing; ","")&IF(P11="Not stated","Seal missing; ","")&IF(K11="","Size driver missing; ","")&IF(NOT(ISNUMBER(AZ11)),"Base-year PPI missing; ","") -> Material missing; Seal missing; Base-year PPI missing; | AT11: =IFERROR(INDEX(Factors_ROT!$F$5:$F$200,MATCH("MAT|"&G11,Factors_ROT!$A$5:$A$200,0)),1) -> 1 | AU11: =IFERROR(INDEX(Factors_ROT!$F$5:$F$200,MATCH("SEAL_ARR|"&P11,Factors_ROT!$A$5:$A$200,0)),1)*IFERROR(INDEX(Factors_ROT!$F$5:$F$200,MATCH("SEAL_CAT|"&Q11,Factors_ROT!$A$5:$A$200,0)),1)*IFERROR(INDEX(Factors_ROT!$F$5:$F$200,MATCH("SEAL_PLAN|"&R11,Factors_ROT!$A$5:$A$200,0)),1) -> 1 | AV11: =IFERROR(INDEX(Factors_ROT!$F$5:$F$200,MATCH("DRV|"&S11,Factors_ROT!$A$5:$A$200,0)),1)*IFERROR(INDEX(Factors_ROT!$F$5:$F$200,MATCH("NACE|"&O11,Factors_ROT!$A$5:$A$200,0)),1) -> 1 | AW11: =IFERROR(INDEX(Factors_ROT!$F$5:$F$200,MATCH("SC_DRV|"&AL11,Factors_ROT!$A$5:$A$200,0)),1)*IFERROR(INDEX(Factors_ROT!$F$5:$F$200,MATCH("SC_BSP|"&AM11,Factors_ROT!$A$5:$A$200,0)),1)*IFERROR(INDEX(Factors_ROT!$F$5:$F$200,MATCH("SC_SEAL|"&AN11,Factors_ROT!$A$5:$A$200,0)),1)*IFERROR(INDEX(Factors_ROT!$F$5:$F$200,MATCH("SC_COMM|"&AO11,Factors_ROT!$A$5:$A$200,0)),1)*IFERROR(INDEX(Factors_ROT!$F$5:$F$200,MATCH("SC_2Y|"&AP11,Factors_ROT!$A$5:$A$200,0)),1)*IFERROR(INDEX(Factors_ROT!$F$5:$F$200,MATCH("SC_TPI|"&AQ11,Factors_ROT!$A$5:$A$200,0)),1)*IFERROR(INDEX(Factors_ROT!$F$5:$F$200,MATCH("SC_FAT|"&AR11,Factors_ROT!$A$5:$A$200,0)),1) -> 1 | AX11: =AT11*AU11*AV11*AW11 -> 1 | AY11: =IF(ISNUMBER(AB11),AB11/AX11,"") | AZ11: =IFERROR(IF(N(INDEX(Escalation_Index!$B$5:$B$25,MATCH(Y11,Escalation_Index!$A$5:$A$25,0)))>0,INDEX(Escalation_Index!$B$5:$B$25,MATCH(Y11,Escalation_Index!$A$5:$A$25,0)),""),"") | BA11: =IF(ISNUMBER('Assumptions & FX Reference'!$I$12),'Assumptions & FX Reference'!$I$12,"") -> 123.416 | BB11: =IF(AND(M11="API 610",LEFT(V11,11)="Centrifugal",OR(LEFT(G11,2)="S-",LEFT(G11,2)="D-")),"Y","N") -> N | BC11: =IF(ISNUMBER(AG11),AG11/AX11,"") | BD11: =IF(AND(ISNUMBER(BC11),ISNUMBER(K11)),IF(K11>0,BC11/K11^'Assumptions & FX Reference'!$I$16,""),"") | BE11: 18061405_Pump_only_CSV.csv – section Pumps (row 7) | BF11: Type: Centrifugal | Driver: موتور الکتریکی (E) | Power: 13.1 kW | Head: 36.2 m | گمرک و حمل: $3600 | Duplicate of the xlsx-sourced record for the same pump (see PUMPS.csv row); kept for reference, excluded from totals. | Original type text: Centrifugal | BG11: N | BH11: PMP | BI11: ="PMP-"&TEXT(A11,"0000") -> PMP-0007
A12: 8 | B12: Disposal Water Pump | C12: (نام پروژه در فایل قید نشده است) – CSV 18061405 | D12: (Not stated in source document) | E12: ROT-INJ | F12: Not stated | G12: Not stated | I12: 1383 | J12: 423 | K12: =IF(ISNUMBER(J12),J12,IF(AND(ISNUMBER(H12),ISNUMBER(I12)),H12*I12/(367*'Assumptions & FX Reference'!$I$17),"")) -> 423 | L12: =IF(IF(OR(M12="Not stated",M12=""),""," + "&M12)&IF(OR(N12="None",N12=""),""," + "&N12)&IF(O12="Y"," + NACE MR0175","")="","Not stated",MID(IF(OR(M12="Not stated",M12=""),""," + "&M12)&IF(OR(N12="None",N12=""),""," + "&N12)&IF(O12="Y"," + NACE MR0175",""),4,300)) -> Not stated | M12: Not stated | N12: None | O12: Not stated | P12: Not stated | Q12: Not stated | R12: Not stated | S12: Electric Motor | T12: Produced / Disposal Water | U12: 1 | V12: Centrifugal | X12: Not stated | Y12: (Not stated) | Z12: USD | AA12: 410000 | AB12: =IF(NOT(ISNUMBER(AA12)),"",IF(NOT(ISNUMBER(Y12)),"",IFERROR(IF(Z12="EUR",AA12,IF(Z12="IRR",AA12/INDEX('Assumptions & FX Reference'!$C$5:$C$25,MATCH(Y12,'Assumptions & FX Reference'!$A$5:$A$25,0)),IF(Z12="USD",AA12*INDEX('Assumptions & FX Reference'!$B$5:$B$25,MATCH(Y12,'Assumptions & FX Reference'!$A$5:$A$25,0))/INDEX('Assumptions & FX Reference'!$C$5:$C$25,MATCH(Y12,'Assumptions & FX Reference'!$A$5:$A$25,0)),""))),""))) | AC12: =IF(NOT(ISNUMBER(AA12)),"",IF(NOT(ISNUMBER(Y12)),"",IFERROR(IF(Z12="USD",AA12,IF(Z12="IRR",AA12/INDEX('Assumptions & FX Reference'!$B$5:$B$25,MATCH(Y12,'Assumptions & FX Reference'!$A$5:$A$25,0)),IF(Z12="EUR",AA12*INDEX('Assumptions & FX Reference'!$C$5:$C$25,MATCH(Y12,'Assumptions & FX Reference'!$A$5:$A$25,0))/INDEX('Assumptions & FX Reference'!$B$5:$B$25,MATCH(Y12,'Assumptions & FX Reference'!$A$5:$A$25,0)),""))),""))) | AD12: =IF(NOT(ISNUMBER(AA12)),"",IF(NOT(ISNUMBER(Y12)),"",IFERROR(IF(Z12="IRR",AA12,IF(Z12="USD",AA12*INDEX('Assumptions & FX Reference'!$B$5:$B$25,MATCH(Y12,'Assumptions & FX Reference'!$A$5:$A$25,0)),IF(Z12="EUR",AA12*INDEX('Assumptions & FX Reference'!$C$5:$C$25,MATCH(Y12,'Assumptions & FX Reference'!$A$5:$A$25,0)),""))),""))) | AE12: Purchase price (USD) – 18061405 pump CSV; project and year not stated | AF12: Not stated | AG12: =IF(AND(Z12="EUR",N(AA12)>5000000),"",IF(AND(ISNUMBER(AB12),ISNUMBER(AZ12),ISNUMBER(BA12)),IF(AND(BB12="Y",ISNUMBER('Assumptions & FX Reference'!$I$15)),MAX(AB12*BA12/AZ12,'Assumptions & FX Reference'!$I$13*BA12/'Assumptions & FX Reference'!$I$15),AB12*BA12/AZ12),"")) | AH12: =IF(AND(ISNUMBER(AG12),ISNUMBER('Assumptions & FX Reference'!$I$8),ISNUMBER('Assumptions & FX Reference'!$I$11)),AG12*'Assumptions & FX Reference'!$I$8/'Assumptions & FX Reference'!$I$11,"") | AI12: =IF(AND(ISNUMBER(AG12),ISNUMBER('Assumptions & FX Reference'!$I$8)),AG12*'Assumptions & FX Reference'!$I$8,"") | AJ12: (Not stated in source document) | AK12: Not stated | AL12: Not stated | AM12: Not stated | AN12: Not stated | AO12: Not stated | AP12: Not stated | AQ12: Not stated | AR12: Not stated | AS12: =IF(AND(Z12="EUR",N(AA12)>5000000),"Check currency (EUR>5M); ","")&IF(NOT(ISNUMBER(AA12)),"No price; ","")&IF(G12="Not stated","Material missing; ","")&IF(P12="Not stated","Seal missing; ","")&IF(K12="","Size driver missing; ","")&IF(NOT(ISNUMBER(AZ12)),"Base-year PPI missing; ","") -> Material missing; Seal missing; Base-year PPI missing; | AT12: =IFERROR(INDEX(Factors_ROT!$F$5:$F$200,MATCH("MAT|"&G12,Factors_ROT!$A$5:$A$200,0)),1) -> 1 | AU12: =IFERROR(INDEX(Factors_ROT!$F$5:$F$200,MATCH("SEAL_ARR|"&P12,Factors_ROT!$A$5:$A$200,0)),1)*IFERROR(INDEX(Factors_ROT!$F$5:$F$200,MATCH("SEAL_CAT|"&Q12,Factors_ROT!$A$5:$A$200,0)),1)*IFERROR(INDEX(Factors_ROT!$F$5:$F$200,MATCH("SEAL_PLAN|"&R12,Factors_ROT!$A$5:$A$200,0)),1) -> 1 | AV12: =IFERROR(INDEX(Factors_ROT!$F$5:$F$200,MATCH("DRV|"&S12,Factors_ROT!$A$5:$A$200,0)),1)*IFERROR(INDEX(Factors_ROT!$F$5:$F$200,MATCH("NACE|"&O12,Factors_ROT!$A$5:$A$200,0)),1) -> 1 | AW12: =IFERROR(INDEX(Factors_ROT!$F$5:$F$200,MATCH("SC_DRV|"&AL12,Factors_ROT!$A$5:$A$200,0)),1)*IFERROR(INDEX(Factors_ROT!$F$5:$F$200,MATCH("SC_BSP|"&AM12,Factors_ROT!$A$5:$A$200,0)),1)*IFERROR(INDEX(Factors_ROT!$F$5:$F$200,MATCH("SC_SEAL|"&AN12,Factors_ROT!$A$5:$A$200,0)),1)*IFERROR(INDEX(Factors_ROT!$F$5:$F$200,MATCH("SC_COMM|"&AO12,Factors_ROT!$A$5:$A$200,0)),1)*IFERROR(INDEX(Factors_ROT!$F$5:$F$200,MATCH("SC_2Y|"&AP12,Factors_ROT!$A$5:$A$200,0)),1)*IFERROR(INDEX(Factors_ROT!$F$5:$F$200,MATCH("SC_TPI|"&AQ12,Factors_ROT!$A$5:$A$200,0)),1)*IFERROR(INDEX(Factors_ROT!$F$5:$F$200,MATCH("SC_FAT|"&AR12,Factors_ROT!$A$5:$A$200,0)),1) -> 1 | AX12: =AT12*AU12*AV12*AW12 -> 1 | AY12: =IF(ISNUMBER(AB12),AB12/AX12,"") | AZ12: =IFERROR(IF(N(INDEX(Escalation_Index!$B$5:$B$25,MATCH(Y12,Escalation_Index!$A$5:$A$25,0)))>0,INDEX(Escalation_Index!$B$5:$B$25,MATCH(Y12,Escalation_Index!$A$5:$A$25,0)),""),"") | BA12: =IF(ISNUMBER('Assumptions & FX Reference'!$I$12),'Assumptions & FX Reference'!$I$12,"") -> 123.416 | BB12: =IF(AND(M12="API 610",LEFT(V12,11)="Centrifugal",OR(LEFT(G12,2)="S-",LEFT(G12,2)="D-")),"Y","N") -> N | BC12: =IF(ISNUMBER(AG12),AG12/AX12,"") | BD12: =IF(AND(ISNUMBER(BC12),ISNUMBER(K12)),IF(K12>0,BC12/K12^'Assumptions & FX Reference'!$I$16,""),"") | BE12: 18061405_Pump_only_CSV.csv – section Pumps (row 8) | BF12: Type: Centrifugal | Driver: موتور الکتریکی (E) | Power: 423 kW | Head: 1383 m | گمرک و حمل: $24600 | Duplicate of the xlsx-sourced record for the same pump (see PUMPS.csv row); kept for reference, excluded from totals. | Original type text: Centrifugal | BG12: N | BH12: PMP | BI12: ="PMP-"&TEXT(A12,"0000") -> PMP-0008
A13: 9 | B13: Fresh Water Pump | C13: (نام پروژه در فایل قید نشده است) – CSV 18061405 | D13: (Not stated in source document) | E13: ROT-WAT | F13: Not stated | G13: Not stated | I13: 41 | J13: 3.9 | K13: =IF(ISNUMBER(J13),J13,IF(AND(ISNUMBER(H13),ISNUMBER(I13)),H13*I13/(367*'Assumptions & FX Reference'!$I$17),"")) -> 3.9 | L13: =IF(IF(OR(M13="Not stated",M13=""),""," + "&M13)&IF(OR(N13="None",N13=""),""," + "&N13)&IF(O13="Y"," + NACE MR0175","")="","Not stated",MID(IF(OR(M13="Not stated",M13=""),""," + "&M13)&IF(OR(N13="None",N13=""),""," + "&N13)&IF(O13="Y"," + NACE MR0175",""),4,300)) -> Not stated | M13: Not stated | N13: None | O13: Not stated | P13: Not stated | Q13: Not stated | R13: Not stated | S13: Electric Motor | T13: Fresh / Potable Water | U13: 1 | V13: Centrifugal | X13: Not stated | Y13: (Not stated) | Z13: USD | AA13: 8000 | AB13: =IF(NOT(ISNUMBER(AA13)),"",IF(NOT(ISNUMBER(Y13)),"",IFERROR(IF(Z13="EUR",AA13,IF(Z13="IRR",AA13/INDEX('Assumptions & FX Reference'!$C$5:$C$25,MATCH(Y13,'Assumptions & FX Reference'!$A$5:$A$25,0)),IF(Z13="USD",AA13*INDEX('Assumptions & FX Reference'!$B$5:$B$25,MATCH(Y13,'Assumptions & FX Reference'!$A$5:$A$25,0))/INDEX('Assumptions & FX Reference'!$C$5:$C$25,MATCH(Y13,'Assumptions & FX Reference'!$A$5:$A$25,0)),""))),""))) | AC13: =IF(NOT(ISNUMBER(AA13)),"",IF(NOT(ISNUMBER(Y13)),"",IFERROR(IF(Z13="USD",AA13,IF(Z13="IRR",AA13/INDEX('Assumptions & FX Reference'!$B$5:$B$25,MATCH(Y13,'Assumptions & FX Reference'!$A$5:$A$25,0)),IF(Z13="EUR",AA13*INDEX('Assumptions & FX Reference'!$C$5:$C$25,MATCH(Y13,'Assumptions & FX Reference'!$A$5:$A$25,0))/INDEX('Assumptions & FX Reference'!$B$5:$B$25,MATCH(Y13,'Assumptions & FX Reference'!$A$5:$A$25,0)),""))),""))) | AD13: =IF(NOT(ISNUMBER(AA13)),"",IF(NOT(ISNUMBER(Y13)),"",IFERROR(IF(Z13="IRR",AA13,IF(Z13="USD",AA13*INDEX('Assumptions & FX Reference'!$B$5:$B$25,MATCH(Y13,'Assumptions & FX Reference'!$A$5:$A$25,0)),IF(Z13="EUR",AA13*INDEX('Assumptions & FX Reference'!$C$5:$C$25,MATCH(Y13,'Assumptions & FX Reference'!$A$5:$A$25,0)),""))),""))) | AE13: Purchase price (USD) – 18061405 pump CSV; project and year not stated | AF13: Not stated | AG13: =IF(AND(Z13="EUR",N(AA13)>5000000),"",IF(AND(ISNUMBER(AB13),ISNUMBER(AZ13),ISNUMBER(BA13)),IF(AND(BB13="Y",ISNUMBER('Assumptions & FX Reference'!$I$15)),MAX(AB13*BA13/AZ13,'Assumptions & FX Reference'!$I$13*BA13/'Assumptions & FX Reference'!$I$15),AB13*BA13/AZ13),"")) | AH13: =IF(AND(ISNUMBER(AG13),ISNUMBER('Assumptions & FX Reference'!$I$8),ISNUMBER('Assumptions & FX Reference'!$I$11)),AG13*'Assumptions & FX Reference'!$I$8/'Assumptions & FX Reference'!$I$11,"") | AI13: =IF(AND(ISNUMBER(AG13),ISNUMBER('Assumptions & FX Reference'!$I$8)),AG13*'Assumptions & FX Reference'!$I$8,"") | AJ13: (Not stated in source document) | AK13: Not stated | AL13: Not stated | AM13: Not stated | AN13: Not stated | AO13: Not stated | AP13: Not stated | AQ13: Not stated | AR13: Not stated | AS13: =IF(AND(Z13="EUR",N(AA13)>5000000),"Check currency (EUR>5M); ","")&IF(NOT(ISNUMBER(AA13)),"No price; ","")&IF(G13="Not stated","Material missing; ","")&IF(P13="Not stated","Seal missing; ","")&IF(K13="","Size driver missing; ","")&IF(NOT(ISNUMBER(AZ13)),"Base-year PPI missing; ","") -> Material missing; Seal missing; Base-year PPI missing; | AT13: =IFERROR(INDEX(Factors_ROT!$F$5:$F$200,MATCH("MAT|"&G13,Factors_ROT!$A$5:$A$200,0)),1) -> 1 | AU13: =IFERROR(INDEX(Factors_ROT!$F$5:$F$200,MATCH("SEAL_ARR|"&P13,Factors_ROT!$A$5:$A$200,0)),1)*IFERROR(INDEX(Factors_ROT!$F$5:$F$200,MATCH("SEAL_CAT|"&Q13,Factors_ROT!$A$5:$A$200,0)),1)*IFERROR(INDEX(Factors_ROT!$F$5:$F$200,MATCH("SEAL_PLAN|"&R13,Factors_ROT!$A$5:$A$200,0)),1) -> 1 | AV13: =IFERROR(INDEX(Factors_ROT!$F$5:$F$200,MATCH("DRV|"&S13,Factors_ROT!$A$5:$A$200,0)),1)*IFERROR(INDEX(Factors_ROT!$F$5:$F$200,MATCH("NACE|"&O13,Factors_ROT!$A$5:$A$200,0)),1) -> 1 | AW13: =IFERROR(INDEX(Factors_ROT!$F$5:$F$200,MATCH("SC_DRV|"&AL13,Factors_ROT!$A$5:$A$200,0)),1)*IFERROR(INDEX(Factors_ROT!$F$5:$F$200,MATCH("SC_BSP|"&AM13,Factors_ROT!$A$5:$A$200,0)),1)*IFERROR(INDEX(Factors_ROT!$F$5:$F$200,MATCH("SC_SEAL|"&AN13,Factors_ROT!$A$5:$A$200,0)),1)*IFERROR(INDEX(Factors_ROT!$F$5:$F$200,MATCH("SC_COMM|"&AO13,Factors_ROT!$A$5:$A$200,0)),1)*IFERROR(INDEX(Factors_ROT!$F$5:$F$200,MATCH("SC_2Y|"&AP13,Factors_ROT!$A$5:$A$200,0)),1)*IFERROR(INDEX(Factors_ROT!$F$5:$F$200,MATCH("SC_TPI|"&AQ13,Factors_ROT!$A$5:$A$200,0)),1)*IFERROR(INDEX(Factors_ROT!$F$5:$F$200,MATCH("SC_FAT|"&AR13,Factors_ROT!$A$5:$A$200,0)),1) -> 1 | AX13: =AT13*AU13*AV13*AW13 -> 1 | AY13: =IF(ISNUMBER(AB13),AB13/AX13,"") | AZ13: =IFERROR(IF(N(INDEX(Escalation_Index!$B$5:$B$25,MATCH(Y13,Escalation_Index!$A$5:$A$25,0)))>0,INDEX(Escalation_Index!$B$5:$B$25,MATCH(Y13,Escalation_Index!$A$5:$A$25,0)),""),"") | BA13: =IF(ISNUMBER('Assumptions & FX Reference'!$I$12),'Assumptions & FX Reference'!$I$12,"") -> 123.416 | BB13: =IF(AND(M13="API 610",LEFT(V13,11)="Centrifugal",OR(LEFT(G13,2)="S-",LEFT(G13,2)="D-")),"Y","N") -> N | BC13: =IF(ISNUMBER(AG13),AG13/AX13,"") | BD13: =IF(AND(ISNUMBER(BC13),ISNUMBER(K13)),IF(K13>0,BC13/K13^'Assumptions & FX Reference'!$I$16,""),"") | BE13: 18061405_Pump_only_CSV.csv – section Pumps (row 9) | BF13: Type: Centrifugal | Driver: موتور الکتریکی (E) | Power: 3.9 kW | Head: 41 m | گمرک و حمل: $480 | Duplicate of the xlsx-sourced record for the same pump (see PUMPS.csv row); kept for reference, excluded from totals. | Original type text: Centrifugal | BG13: N | BH13: PMP | BI13: ="PMP-"&TEXT(A13,"0000") -> PMP-0009
A14: 10 | B14: Closed Drain Pump | C14: (نام پروژه در فایل قید نشده است) – CSV 18061405 | D14: (Not stated in source document) | E14: ROT-DRN | F14: Not stated | G14: Not stated | I14: 120 | J14: 13.7 | K14: =IF(ISNUMBER(J14),J14,IF(AND(ISNUMBER(H14),ISNUMBER(I14)),H14*I14/(367*'Assumptions & FX Reference'!$I$17),"")) -> 13.7 | L14: =IF(IF(OR(M14="Not stated",M14=""),""," + "&M14)&IF(OR(N14="None",N14=""),""," + "&N14)&IF(O14="Y"," + NACE MR0175","")="","Not stated",MID(IF(OR(M14="Not stated",M14=""),""," + "&M14)&IF(OR(N14="None",N14=""),""," + "&N14)&IF(O14="Y"," + NACE MR0175",""),4,300)) -> Not stated | M14: Not stated | N14: None | O14: Not stated | P14: Not stated | Q14: Not stated | R14: Not stated | S14: Electric Motor | T14: Oily Water / Drain | U14: 1 | V14: Centrifugal | X14: Not stated | Y14: (Not stated) | Z14: USD | AA14: 40000 | AB14: =IF(NOT(ISNUMBER(AA14)),"",IF(NOT(ISNUMBER(Y14)),"",IFERROR(IF(Z14="EUR",AA14,IF(Z14="IRR",AA14/INDEX('Assumptions & FX Reference'!$C$5:$C$25,MATCH(Y14,'Assumptions & FX Reference'!$A$5:$A$25,0)),IF(Z14="USD",AA14*INDEX('Assumptions & FX Reference'!$B$5:$B$25,MATCH(Y14,'Assumptions & FX Reference'!$A$5:$A$25,0))/INDEX('Assumptions & FX Reference'!$C$5:$C$25,MATCH(Y14,'Assumptions & FX Reference'!$A$5:$A$25,0)),""))),""))) | AC14: =IF(NOT(ISNUMBER(AA14)),"",IF(NOT(ISNUMBER(Y14)),"",IFERROR(IF(Z14="USD",AA14,IF(Z14="IRR",AA14/INDEX('Assumptions & FX Reference'!$B$5:$B$25,MATCH(Y14,'Assumptions & FX Reference'!$A$5:$A$25,0)),IF(Z14="EUR",AA14*INDEX('Assumptions & FX Reference'!$C$5:$C$25,MATCH(Y14,'Assumptions & FX Reference'!$A$5:$A$25,0))/INDEX('Assumptions & FX Reference'!$B$5:$B$25,MATCH(Y14,'Assumptions & FX Reference'!$A$5:$A$25,0)),""))),""))) | AD14: =IF(NOT(ISNUMBER(AA14)),"",IF(NOT(ISNUMBER(Y14)),"",IFERROR(IF(Z14="IRR",AA14,IF(Z14="USD",AA14*INDEX('Assumptions & FX Reference'!$B$5:$B$25,MATCH(Y14,'Assumptions & FX Reference'!$A$5:$A$25,0)),IF(Z14="EUR",AA14*INDEX('Assumptions & FX Reference'!$C$5:$C$25,MATCH(Y14,'Assumptions & FX Reference'!$A$5:$A$25,0)),""))),""))) | AE14: Purchase price (USD) – 18061405 pump CSV; project and year not stated | AF14: Not stated | AG14: =IF(AND(Z14="EUR",N(AA14)>5000000),"",IF(AND(ISNUMBER(AB14),ISNUMBER(AZ14),ISNUMBER(BA14)),IF(AND(BB14="Y",ISNUMBER('Assumptions & FX Reference'!$I$15)),MAX(AB14*BA14/AZ14,'Assumptions & FX Reference'!$I$13*BA14/'Assumptions & FX Reference'!$I$15),AB14*BA14/AZ14),"")) | AH14: =IF(AND(ISNUMBER(AG14),ISNUMBER('Assumptions & FX Reference'!$I$8),ISNUMBER('Assumptions & FX Reference'!$I$11)),AG14*'Assumptions & FX Reference'!$I$8/'Assumptions & FX Reference'!$I$11,"") | AI14: =IF(AND(ISNUMBER(AG14),ISNUMBER('Assumptions & FX Reference'!$I$8)),AG14*'Assumptions & FX Reference'!$I$8,"") | AJ14: (Not stated in source document) | AK14: Not stated | AL14: Not stated | AM14: Not stated | AN14: Not stated | AO14: Not stated | AP14: Not stated | AQ14: Not stated | AR14: Not stated | AS14: =IF(AND(Z14="EUR",N(AA14)>5000000),"Check currency (EUR>5M); ","")&IF(NOT(ISNUMBER(AA14)),"No price; ","")&IF(G14="Not stated","Material missing; ","")&IF(P14="Not stated","Seal missing; ","")&IF(K14="","Size driver missing; ","")&IF(NOT(ISNUMBER(AZ14)),"Base-year PPI missing; ","") -> Material missing; Seal missing; Base-year PPI missing; | AT14: =IFERROR(INDEX(Factors_ROT!$F$5:$F$200,MATCH("MAT|"&G14,Factors_ROT!$A$5:$A$200,0)),1) -> 1 | AU14: =IFERROR(INDEX(Factors_ROT!$F$5:$F$200,MATCH("SEAL_ARR|"&P14,Factors_ROT!$A$5:$A$200,0)),1)*IFERROR(INDEX(Factors_ROT!$F$5:$F$200,MATCH("SEAL_CAT|"&Q14,Factors_ROT!$A$5:$A$200,0)),1)*IFERROR(INDEX(Factors_ROT!$F$5:$F$200,MATCH("SEAL_PLAN|"&R14,Factors_ROT!$A$5:$A$200,0)),1) -> 1 | AV14: =IFERROR(INDEX(Factors_ROT!$F$5:$F$200,MATCH("DRV|"&S14,Factors_ROT!$A$5:$A$200,0)),1)*IFERROR(INDEX(Factors_ROT!$F$5:$F$200,MATCH("NACE|"&O14,Factors_ROT!$A$5:$A$200,0)),1) -> 1 | AW14: =IFERROR(INDEX(Factors_ROT!$F$5:$F$200,MATCH("SC_DRV|"&AL14,Factors_ROT!$A$5:$A$200,0)),1)*IFERROR(INDEX(Factors_ROT!$F$5:$F$200,MATCH("SC_BSP|"&AM14,Factors_ROT!$A$5:$A$200,0)),1)*IFERROR(INDEX(Factors_ROT!$F$5:$F$200,MATCH("SC_SEAL|"&AN14,Factors_ROT!$A$5:$A$200,0)),1)*IFERROR(INDEX(Factors_ROT!$F$5:$F$200,MATCH("SC_COMM|"&AO14,Factors_ROT!$A$5:$A$200,0)),1)*IFERROR(INDEX(Factors_ROT!$F$5:$F$200,MATCH("SC_2Y|"&AP14,Factors_ROT!$A$5:$A$200,0)),1)*IFERROR(INDEX(Factors_ROT!$F$5:$F$200,MATCH("SC_TPI|"&AQ14,Factors_ROT!$A$5:$A$200,0)),1)*IFERROR(INDEX(Factors_ROT!$F$5:$F$200,MATCH("SC_FAT|"&AR14,Factors_ROT!$A$5:$A$200,0)),1) -> 1 | AX14: =AT14*AU14*AV14*AW14 -> 1 | AY14: =IF(ISNUMBER(AB14),AB14/AX14,"") | AZ14: =IFERROR(IF(N(INDEX(Escalation_Index!$B$5:$B$25,MATCH(Y14,Escalation_Index!$A$5:$A$25,0)))>0,INDEX(Escalation_Index!$B$5:$B$25,MATCH(Y14,Escalation_Index!$A$5:$A$25,0)),""),"") | BA14: =IF(ISNUMBER('Assumptions & FX Reference'!$I$12),'Assumptions & FX Reference'!$I$12,"") -> 123.416 | BB14: =IF(AND(M14="API 610",LEFT(V14,11)="Centrifugal",OR(LEFT(G14,2)="S-",LEFT(G14,2)="D-")),"Y","N") -> N | BC14: =IF(ISNUMBER(AG14),AG14/AX14,"") | BD14: =IF(AND(ISNUMBER(BC14),ISNUMBER(K14)),IF(K14>0,BC14/K14^'Assumptions & FX Reference'!$I$16,""),"") | BE14: 18061405_Pump_only_CSV.csv – section Pumps (row 10) | BF14: Type: Centrifugal | Driver: موتور الکتریکی (E) | Power: 13.7 kW | Head: 120 m | گمرک و حمل: $2400 | Duplicate of the xlsx-sourced record for the same pump (see PUMPS.csv row); kept for reference, excluded from totals. | Original type text: Centrifugal | BG14: N | BH14: PMP | BI14: ="PMP-"&TEXT(A14,"0000") -> PMP-0010
A15: 11 | B15: Diesel Unlodaing pump | C15: (نام پروژه در فایل قید نشده است) – CSV 18061405 | D15: (Not stated in source document) | E15: ROT-AUX | F15: N/A (non-API 610) | G15: Not stated | I15: 27.2 | J15: 4 | K15: =IF(ISNUMBER(J15),J15,IF(AND(ISNUMBER(H15),ISNUMBER(I15)),H15*I15/(367*'Assumptions & FX Reference'!$I$17),"")) -> 4 | L15: =IF(IF(OR(M15="Not stated",M15=""),""," + "&M15)&IF(OR(N15="None",N15=""),""," + "&N15)&IF(O15="Y"," + NACE MR0175","")="","Not stated",MID(IF(OR(M15="Not stated",M15=""),""," + "&M15)&IF(OR(N15="None",N15=""),""," + "&N15)&IF(O15="Y"," + NACE MR0175",""),4,300)) -> Not stated | M15: Not stated | N15: None | O15: Not stated | P15: Not stated | Q15: Not stated | R15: Not stated | S15: Electric Motor | T15: Diesel / Fuel Oil | U15: 1 | V15: PD-Rotary (Sliding Vane) | X15: Not stated | Y15: (Not stated) | Z15: USD | AA15: 5000 | AB15: =IF(NOT(ISNUMBER(AA15)),"",IF(NOT(ISNUMBER(Y15)),"",IFERROR(IF(Z15="EUR",AA15,IF(Z15="IRR",AA15/INDEX('Assumptions & FX Reference'!$C$5:$C$25,MATCH(Y15,'Assumptions & FX Reference'!$A$5:$A$25,0)),IF(Z15="USD",AA15*INDEX('Assumptions & FX Reference'!$B$5:$B$25,MATCH(Y15,'Assumptions & FX Reference'!$A$5:$A$25,0))/INDEX('Assumptions & FX Reference'!$C$5:$C$25,MATCH(Y15,'Assumptions & FX Reference'!$A$5:$A$25,0)),""))),""))) | AC15: =IF(NOT(ISNUMBER(AA15)),"",IF(NOT(ISNUMBER(Y15)),"",IFERROR(IF(Z15="USD",AA15,IF(Z15="IRR",AA15/INDEX('Assumptions & FX Reference'!$B$5:$B$25,MATCH(Y15,'Assumptions & FX Reference'!$A$5:$A$25,0)),IF(Z15="EUR",AA15*INDEX('Assumptions & FX Reference'!$C$5:$C$25,MATCH(Y15,'Assumptions & FX Reference'!$A$5:$A$25,0))/INDEX('Assumptions & FX Reference'!$B$5:$B$25,MATCH(Y15,'Assumptions & FX Reference'!$A$5:$A$25,0)),""))),""))) | AD15: =IF(NOT(ISNUMBER(AA15)),"",IF(NOT(ISNUMBER(Y15)),"",IFERROR(IF(Z15="IRR",AA15,IF(Z15="USD",AA15*INDEX('Assumptions & FX Reference'!$B$5:$B$25,MATCH(Y15,'Assumptions & FX Reference'!$A$5:$A$25,0)),IF(Z15="EUR",AA15*INDEX('Assumptions & FX Reference'!$C$5:$C$25,MATCH(Y15,'Assumptions & FX Reference'!$A$5:$A$25,0)),""))),""))) | AE15: Purchase price (USD) – 18061405 pump CSV; project and year not stated | AF15: Not stated | AG15: =IF(AND(Z15="EUR",N(AA15)>5000000),"",IF(AND(ISNUMBER(AB15),ISNUMBER(AZ15),ISNUMBER(BA15)),IF(AND(BB15="Y",ISNUMBER('Assumptions & FX Reference'!$I$15)),MAX(AB15*BA15/AZ15,'Assumptions & FX Reference'!$I$13*BA15/'Assumptions & FX Reference'!$I$15),AB15*BA15/AZ15),"")) | AH15: =IF(AND(ISNUMBER(AG15),ISNUMBER('Assumptions & FX Reference'!$I$8),ISNUMBER('Assumptions & FX Reference'!$I$11)),AG15*'Assumptions & FX Reference'!$I$8/'Assumptions & FX Reference'!$I$11,"") | AI15: =IF(AND(ISNUMBER(AG15),ISNUMBER('Assumptions & FX Reference'!$I$8)),AG15*'Assumptions & FX Reference'!$I$8,"") | AJ15: (Not stated in source document) | AK15: Not stated | AL15: Not stated | AM15: Not stated | AN15: Not stated | AO15: Not stated | AP15: Not stated | AQ15: Not stated | AR15: Not stated | AS15: =IF(AND(Z15="EUR",N(AA15)>5000000),"Check currency (EUR>5M); ","")&IF(NOT(ISNUMBER(AA15)),"No price; ","")&IF(G15="Not stated","Material missing; ","")&IF(P15="Not stated","Seal missing; ","")&IF(K15="","Size driver missing; ","")&IF(NOT(ISNUMBER(AZ15)),"Base-year PPI missing; ","") -> Material missing; Seal missing; Base-year PPI missing; | AT15: =IFERROR(INDEX(Factors_ROT!$F$5:$F$200,MATCH("MAT|"&G15,Factors_ROT!$A$5:$A$200,0)),1) -> 1 | AU15: =IFERROR(INDEX(Factors_ROT!$F$5:$F$200,MATCH("SEAL_ARR|"&P15,Factors_ROT!$A$5:$A$200,0)),1)*IFERROR(INDEX(Factors_ROT!$F$5:$F$200,MATCH("SEAL_CAT|"&Q15,Factors_ROT!$A$5:$A$200,0)),1)*IFERROR(INDEX(Factors_ROT!$F$5:$F$200,MATCH("SEAL_PLAN|"&R15,Factors_ROT!$A$5:$A$200,0)),1) -> 1 | AV15: =IFERROR(INDEX(Factors_ROT!$F$5:$F$200,MATCH("DRV|"&S15,Factors_ROT!$A$5:$A$200,0)),1)*IFERROR(INDEX(Factors_ROT!$F$5:$F$200,MATCH("NACE|"&O15,Factors_ROT!$A$5:$A$200,0)),1) -> 1 | AW15: =IFERROR(INDEX(Factors_ROT!$F$5:$F$200,MATCH("SC_DRV|"&AL15,Factors_ROT!$A$5:$A$200,0)),1)*IFERROR(INDEX(Factors_ROT!$F$5:$F$200,MATCH("SC_BSP|"&AM15,Factors_ROT!$A$5:$A$200,0)),1)*IFERROR(INDEX(Factors_ROT!$F$5:$F$200,MATCH("SC_SEAL|"&AN15,Factors_ROT!$A$5:$A$200,0)),1)*IFERROR(INDEX(Factors_ROT!$F$5:$F$200,MATCH("SC_COMM|"&AO15,Factors_ROT!$A$5:$A$200,0)),1)*IFERROR(INDEX(Factors_ROT!$F$5:$F$200,MATCH("SC_2Y|"&AP15,Factors_ROT!$A$5:$A$200,0)),1)*IFERROR(INDEX(Factors_ROT!$F$5:$F$200,MATCH("SC_TPI|"&AQ15,Factors_ROT!$A$5:$A$200,0)),1)*IFERROR(INDEX(Factors_ROT!$F$5:$F$200,MATCH("SC_FAT|"&AR15,Factors_ROT!$A$5:$A$200,0)),1) -> 1 | AX15: =AT15*AU15*AV15*AW15 -> 1 | AY15: =IF(ISNUMBER(AB15),AB15/AX15,"") | AZ15: =IFERROR(IF(N(INDEX(Escalation_Index!$B$5:$B$25,MATCH(Y15,Escalation_Index!$A$5:$A$25,0)))>0,INDEX(Escalation_Index!$B$5:$B$25,MATCH(Y15,Escalation_Index!$A$5:$A$25,0)),""),"") | BA15: =IF(ISNUMBER('Assumptions & FX Reference'!$I$12),'Assumptions & FX Reference'!$I$12,"") -> 123.416 | BB15: =IF(AND(M15="API 610",LEFT(V15,11)="Centrifugal",OR(LEFT(G15,2)="S-",LEFT(G15,2)="D-")),"Y","N") -> N | BC15: =IF(ISNUMBER(AG15),AG15/AX15,"") | BD15: =IF(AND(ISNUMBER(BC15),ISNUMBER(K15)),IF(K15>0,BC15/K15^'Assumptions & FX Reference'!$I$16,""),"") | BE15: 18061405_Pump_only_CSV.csv – section Pumps (row 11) | BF15: Type: Sliding valve | Driver: موتور الکتریکی (E) | Power: 4 kW | Head: 27.2 m | گمرک و حمل: $300 | Duplicate of the xlsx-sourced record for the same pump (see PUMPS.csv row); kept for reference, excluded from totals. | Original type text: Sliding valve | BG15: N | BH15: PMP | BI15: ="PMP-"&TEXT(A15,"0000") -> PMP-0011
A16: 12 | B16: Diesel Transfer pump | C16: (نام پروژه در فایل قید نشده است) – CSV 18061405 | D16: (Not stated in source document) | E16: ROT-AUX | F16: N/A (non-API 610) | G16: Not stated | I16: 40.8 | J16: 0.8 | K16: =IF(ISNUMBER(J16),J16,IF(AND(ISNUMBER(H16),ISNUMBER(I16)),H16*I16/(367*'Assumptions & FX Reference'!$I$17),"")) -> 0.8 | L16: =IF(IF(OR(M16="Not stated",M16=""),""," + "&M16)&IF(OR(N16="None",N16=""),""," + "&N16)&IF(O16="Y"," + NACE MR0175","")="","Not stated",MID(IF(OR(M16="Not stated",M16=""),""," + "&M16)&IF(OR(N16="None",N16=""),""," + "&N16)&IF(O16="Y"," + NACE MR0175",""),4,300)) -> Not stated | M16: Not stated | N16: None | O16: Not stated | P16: Not stated | Q16: Not stated | R16: Not stated | S16: Electric Motor | T16: Diesel / Fuel Oil | U16: 1 | V16: PD-Rotary (Screw) | X16: Not stated | Y16: (Not stated) | Z16: USD | AA16: 3000 | AB16: =IF(NOT(ISNUMBER(AA16)),"",IF(NOT(ISNUMBER(Y16)),"",IFERROR(IF(Z16="EUR",AA16,IF(Z16="IRR",AA16/INDEX('Assumptions & FX Reference'!$C$5:$C$25,MATCH(Y16,'Assumptions & FX Reference'!$A$5:$A$25,0)),IF(Z16="USD",AA16*INDEX('Assumptions & FX Reference'!$B$5:$B$25,MATCH(Y16,'Assumptions & FX Reference'!$A$5:$A$25,0))/INDEX('Assumptions & FX Reference'!$C$5:$C$25,MATCH(Y16,'Assumptions & FX Reference'!$A$5:$A$25,0)),""))),""))) | AC16: =IF(NOT(ISNUMBER(AA16)),"",IF(NOT(ISNUMBER(Y16)),"",IFERROR(IF(Z16="USD",AA16,IF(Z16="IRR",AA16/INDEX('Assumptions & FX Reference'!$B$5:$B$25,MATCH(Y16,'Assumptions & FX Reference'!$A$5:$A$25,0)),IF(Z16="EUR",AA16*INDEX('Assumptions & FX Reference'!$C$5:$C$25,MATCH(Y16,'Assumptions & FX Reference'!$A$5:$A$25,0))/INDEX('Assumptions & FX Reference'!$B$5:$B$25,MATCH(Y16,'Assumptions & FX Reference'!$A$5:$A$25,0)),""))),""))) | AD16: =IF(NOT(ISNUMBER(AA16)),"",IF(NOT(ISNUMBER(Y16)),"",IFERROR(IF(Z16="IRR",AA16,IF(Z16="USD",AA16*INDEX('Assumptions & FX Reference'!$B$5:$B$25,MATCH(Y16,'Assumptions & FX Reference'!$A$5:$A$25,0)),IF(Z16="EUR",AA16*INDEX('Assumptions & FX Reference'!$C$5:$C$25,MATCH(Y16,'Assumptions & FX Reference'!$A$5:$A$25,0)),""))),""))) | AE16: Purchase price (USD) – 18061405 pump CSV; project and year not stated | AF16: Not stated | AG16: =IF(AND(Z16="EUR",N(AA16)>5000000),"",IF(AND(ISNUMBER(AB16),ISNUMBER(AZ16),ISNUMBER(BA16)),IF(AND(BB16="Y",ISNUMBER('Assumptions & FX Reference'!$I$15)),MAX(AB16*BA16/AZ16,'Assumptions & FX Reference'!$I$13*BA16/'Assumptions & FX Reference'!$I$15),AB16*BA16/AZ16),"")) | AH16: =IF(AND(ISNUMBER(AG16),ISNUMBER('Assumptions & FX Reference'!$I$8),ISNUMBER('Assumptions & FX Reference'!$I$11)),AG16*'Assumptions & FX Reference'!$I$8/'Assumptions & FX Reference'!$I$11,"") | AI16: =IF(AND(ISNUMBER(AG16),ISNUMBER('Assumptions & FX Reference'!$I$8)),AG16*'Assumptions & FX Reference'!$I$8,"") | AJ16: (Not stated in source document) | AK16: Not stated | AL16: Not stated | AM16: Not stated | AN16: Not stated | AO16: Not stated | AP16: Not stated | AQ16: Not stated | AR16: Not stated | AS16: =IF(AND(Z16="EUR",N(AA16)>5000000),"Check currency (EUR>5M); ","")&IF(NOT(ISNUMBER(AA16)),"No price; ","")&IF(G16="Not stated","Material missing; ","")&IF(P16="Not stated","Seal missing; ","")&IF(K16="","Size driver missing; ","")&IF(NOT(ISNUMBER(AZ16)),"Base-year PPI missing; ","") -> Material missing; Seal missing; Base-year PPI missing; | AT16: =IFERROR(INDEX(Factors_ROT!$F$5:$F$200,MATCH("MAT|"&G16,Factors_ROT!$A$5:$A$200,0)),1) -> 1 | AU16: =IFERROR(INDEX(Factors_ROT!$F$5:$F$200,MATCH("SEAL_ARR|"&P16,Factors_ROT!$A$5:$A$200,0)),1)*IFERROR(INDEX(Factors_ROT!$F$5:$F$200,MATCH("SEAL_CAT|"&Q16,Factors_ROT!$A$5:$A$200,0)),1)*IFERROR(INDEX(Factors_ROT!$F$5:$F$200,MATCH("SEAL_PLAN|"&R16,Factors_ROT!$A$5:$A$200,0)),1) -> 1 | AV16: =IFERROR(INDEX(Factors_ROT!$F$5:$F$200,MATCH("DRV|"&S16,Factors_ROT!$A$5:$A$200,0)),1)*IFERROR(INDEX(Factors_ROT!$F$5:$F$200,MATCH("NACE|"&O16,Factors_ROT!$A$5:$A$200,0)),1) -> 1 | AW16: =IFERROR(INDEX(Factors_ROT!$F$5:$F$200,MATCH("SC_DRV|"&AL16,Factors_ROT!$A$5:$A$200,0)),1)*IFERROR(INDEX(Factors_ROT!$F$5:$F$200,MATCH("SC_BSP|"&AM16,Factors_ROT!$A$5:$A$200,0)),1)*IFERROR(INDEX(Factors_ROT!$F$5:$F$200,MATCH("SC_SEAL|"&AN16,Factors_ROT!$A$5:$A$200,0)),1)*IFERROR(INDEX(Factors_ROT!$F$5:$F$200,MATCH("SC_COMM|"&AO16,Factors_ROT!$A$5:$A$200,0)),1)*IFERROR(INDEX(Factors_ROT!$F$5:$F$200,MATCH("SC_2Y|"&AP16,Factors_ROT!$A$5:$A$200,0)),1)*IFERROR(INDEX(Factors_ROT!$F$5:$F$200,MATCH("SC_TPI|"&AQ16,Factors_ROT!$A$5:$A$200,0)),1)*IFERROR(INDEX(Factors_ROT!$F$5:$F$200,MATCH("SC_FAT|"&AR16,Factors_ROT!$A$5:$A$200,0)),1) -> 1 | AX16: =AT16*AU16*AV16*AW16 -> 1 | AY16: =IF(ISNUMBER(AB16),AB16/AX16,"") | AZ16: =IFERROR(IF(N(INDEX(Escalation_Index!$B$5:$B$25,MATCH(Y16,Escalation_Index!$A$5:$A$25,0)))>0,INDEX(Escalation_Index!$B$5:$B$25,MATCH(Y16,Escalation_Index!$A$5:$A$25,0)),""),"") | BA16: =IF(ISNUMBER('Assumptions & FX Reference'!$I$12),'Assumptions & FX Reference'!$I$12,"") -> 123.416 | BB16: =IF(AND(M16="API 610",LEFT(V16,11)="Centrifugal",OR(LEFT(G16,2)="S-",LEFT(G16,2)="D-")),"Y","N") -> N | BC16: =IF(ISNUMBER(AG16),AG16/AX16,"") | BD16: =IF(AND(ISNUMBER(BC16),ISNUMBER(K16)),IF(K16>0,BC16/K16^'Assumptions & FX Reference'!$I$16,""),"") | BE16: 18061405_Pump_only_CSV.csv – section Pumps (row 12) | BF16: Type: Screw | Driver: موتور الکتریکی (E) | Power: 0.8 kW | Head: 40.8 m | گمرک و حمل: $180 | Duplicate of the xlsx-sourced record for the same pump (see PUMPS.csv row); kept for reference, excluded from totals. | Original type text: Screw | BG16: N | BH16: PMP | BI16: ="PMP-"&TEXT(A16,"0000") -> PMP-0012
... A18: 14 | B18: Flare KO Drum Pumps | C18: (نام پروژه در فایل قید نشده است) – CSV 18061405 | D18: (Not stated in source document) | E18: ROT-DRN | F18: Not stated | G18: Not stated | I18: 18 | J18: 2 | K18: =IF(ISNUMBER(J18),J18,IF(AND(ISNUMBER(H18),ISNUMBER(I18)),H18*I18/(367*'Assumptions & FX Reference'!$I$17),"")) -> 2 | L18: =IF(IF(OR(M18="Not stated",M18=""),""," + "&M18)&IF(OR(N18="None",N18=""),""," + "&N18)&IF(O18="Y"," + NACE MR0175","")="","Not stated",MID(IF(OR(M18="Not stated",M18=""),""," + "&M18)&IF(OR(N18="None",N18=""),""," + "&N18)&IF(O18="Y"," + NACE MR0175",""),4,300)) -> Not stated | M18: Not stated | N18: None | O18: Not stated | P18: Not stated | Q18: Not stated | R18: Not stated | S18: Electric Motor | T18: Oily Water / Drain | U18: 1 | V18: Centrifugal | X18: Not stated | Y18: (Not stated) | Z18: USD | AA18: 40000 | AB18: =IF(NOT(ISNUMBER(AA18)),"",IF(NOT(ISNUMBER(Y18)),"",IFERROR(IF(Z18="EUR",AA18,IF(Z18="IRR",AA18/INDEX('Assumptions & FX Reference'!$C$5:$C$25,MATCH(Y18,'Assumptions & FX Reference'!$A$5:$A$25,0)),IF(Z18="USD",AA18*INDEX('Assumptions & FX Reference'!$B$5:$B$25,MATCH(Y18,'Assumptions & FX Reference'!$A$5:$A$25,0))/INDEX('Assumptions & FX Reference'!$C$5:$C$25,MATCH(Y18,'Assumptions & FX Reference'!$A$5:$A$25,0)),""))),""))) | AC18: =IF(NOT(ISNUMBER(AA18)),"",IF(NOT(ISNUMBER(Y18)),"",IFERROR(IF(Z18="USD",AA18,IF(Z18="IRR",AA18/INDEX('Assumptions & FX Reference'!$B$5:$B$25,MATCH(Y18,'Assumptions & FX Reference'!$A$5:$A$25,0)),IF(Z18="EUR",AA18*INDEX('Assumptions & FX Reference'!$C$5:$C$25,MATCH(Y18,'Assumptions & FX Reference'!$A$5:$A$25,0))/INDEX('Assumptions & FX Reference'!$B$5:$B$25,MATCH(Y18,'Assumptions & FX Reference'!$A$5:$A$25,0)),""))),""))) | AD18: =IF(NOT(ISNUMBER(AA18)),"",IF(NOT(ISNUMBER(Y18)),"",IFERROR(IF(Z18="IRR",AA18,IF(Z18="USD",AA18*INDEX('Assumptions & FX Reference'!$B$5:$B$25,MATCH(Y18,'Assumptions & FX Reference'!$A$5:$A$25,0)),IF(Z18="EUR",AA18*INDEX('Assumptions & FX Reference'!$C$5:$C$25,MATCH(Y18,'Assumptions & FX Reference'!$A$5:$A$25,0)),""))),""))) | AE18: Purchase price (USD) – 18061405 pump CSV; project and year not stated | AF18: Not stated | AG18: =IF(AND(Z18="EUR",N(AA18)>5000000),"",IF(AND(ISNUMBER(AB18),ISNUMBER(AZ18),ISNUMBER(BA18)),IF(AND(BB18="Y",ISNUMBER('Assumptions & FX Reference'!$I$15)),MAX(AB18*BA18/AZ18,'Assumptions & FX Reference'!$I$13*BA18/'Assumptions & FX Reference'!$I$15),AB18*BA18/AZ18),"")) | AH18: =IF(AND(ISNUMBER(AG18),ISNUMBER('Assumptions & FX Reference'!$I$8),ISNUMBER('Assumptions & FX Reference'!$I$11)),AG18*'Assumptions & FX Reference'!$I$8/'Assumptions & FX Reference'!$I$11,"") | AI18: =IF(AND(ISNUMBER(AG18),ISNUMBER('Assumptions & FX Reference'!$I$8)),AG18*'Assumptions & FX Reference'!$I$8,"") | AJ18: (Not stated in source document) | AK18: Not stated | AL18: Not stated | AM18: Not stated | AN18: Not stated | AO18: Not stated | AP18: Not stated | AQ18: Not stated | AR18: Not stated | AS18: =IF(AND(Z18="EUR",N(AA18)>5000000),"Check currency (EUR>5M); ","")&IF(NOT(ISNUMBER(AA18)),"No price; ","")&IF(G18="Not stated","Material missing; ","")&IF(P18="Not stated","Seal missing; ","")&IF(K18="","Size driver missing; ","")&IF(NOT(ISNUMBER(AZ18)),"Base-year PPI missing; ","") -> Material missing; Seal missing; Base-year PPI missing; | AT18: =IFERROR(INDEX(Factors_ROT!$F$5:$F$200,MATCH("MAT|"&G18,Factors_ROT!$A$5:$A$200,0)),1) -> 1 | AU18: =IFERROR(INDEX(Factors_ROT!$F$5:$F$200,MATCH("SEAL_ARR|"&P18,Factors_ROT!$A$5:$A$200,0)),1)*IFERROR(INDEX(Factors_ROT!$F$5:$F$200,MATCH("SEAL_CAT|"&Q18,Factors_ROT!$A$5:$A$200,0)),1)*IFERROR(INDEX(Factors_ROT!$F$5:$F$200,MATCH("SEAL_PLAN|"&R18,Factors_ROT!$A$5:$A$200,0)),1) -> 1 | AV18: =IFERROR(INDEX(Factors_ROT!$F$5:$F$200,MATCH("DRV|"&S18,Factors_ROT!$A$5:$A$200,0)),1)*IFERROR(INDEX(Factors_ROT!$F$5:$F$200,MATCH("NACE|"&O18,Factors_ROT!$A$5:$A$200,0)),1) -> 1 | AW18: =IFERROR(INDEX(Factors_ROT!$F$5:$F$200,MATCH("SC_DRV|"&AL18,Factors_ROT!$A$5:$A$200,0)),1)*IFERROR(INDEX(Factors_ROT!$F$5:$F$200,MATCH("SC_BSP|"&AM18,Factors_ROT!$A$5:$A$200,0)),1)*IFERROR(INDEX(Factors_ROT!$F$5:$F$200,MATCH("SC_SEAL|"&AN18,Factors_ROT!$A$5:$A$200,0)),1)*IFERROR(INDEX(Factors_ROT!$F$5:$F$200,MATCH("SC_COMM|"&AO18,Factors_ROT!$A$5:$A$200,0)),1)*IFERROR(INDEX(Factors_ROT!$F$5:$F$200,MATCH("SC_2Y|"&AP18,Factors_ROT!$A$5:$A$200,0)),1)*IFERROR(INDEX(Factors_ROT!$F$5:$F$200,MATCH("SC_TPI|"&AQ18,Factors_ROT!$A$5:$A$200,0)),1)*IFERROR(INDEX(Factors_ROT!$F$5:$F$200,MATCH("SC_FAT|"&AR18,Factors_ROT!$A$5:$A$200,0)),1) -> 1 | AX18: =AT18*AU18*AV18*AW18 -> 1 | AY18: =IF(ISNUMBER(AB18),AB18/AX18,"") | AZ18: =IFERROR(IF(N(INDEX(Escalation_Index!$B$5:$B$25,MATCH(Y18,Escalation_Index!$A$5:$A$25,0)))>0,INDEX(Escalation_Index!$B$5:$B$25,MATCH(Y18,Escalation_Index!$A$5:$A$25,0)),""),"") | BA18: =IF(ISNUMBER('Assumptions & FX Reference'!$I$12),'Assumptions & FX Reference'!$I$12,"") -> 123.416 | BB18: =IF(AND(M18="API 610",LEFT(V18,11)="Centrifugal",OR(LEFT(G18,2)="S-",LEFT(G18,2)="D-")),"Y","N") -> N | BC18: =IF(ISNUMBER(AG18),AG18/AX18,"") | BD18: =IF(AND(ISNUMBER(BC18),ISNUMBER(K18)),IF(K18>0,BC18/K18^'Assumptions & FX Reference'!$I$16,""),"") | BE18: 18061405_Pump_only_CSV.csv – section Pumps (row 14) | BF18: Type: Centrifugal | Driver: موتور الکتریکی (E) | Power: 2 kW | Head: 18 m | گمرک و حمل: $2400 | Duplicate of the xlsx-sourced record for the same pump (see PUMPS.csv row); kept for reference, excluded from totals. | Original type text: Centrifugal | BG18: N | BH18: PMP | BI18: ="PMP-"&TEXT(A18,"0000") -> PMP-0014
A19: 15 | B19: MAIN TRANSFER PUMPS | C19: Gachsaran 4 | D19: P-001-A/B | E19: ROT-CRU | F19: Not stated | G19: Not stated | H19: 500 | J19: 216.3 | K19: =IF(ISNUMBER(J19),J19,IF(AND(ISNUMBER(H19),ISNUMBER(I19)),H19*I19/(367*'Assumptions & FX Reference'!$I$17),"")) -> 216.3 | L19: =IF(IF(OR(M19="Not stated",M19=""),""," + "&M19)&IF(OR(N19="None",N19=""),""," + "&N19)&IF(O19="Y"," + NACE MR0175","")="","Not stated",MID(IF(OR(M19="Not stated",M19=""),""," + "&M19)&IF(OR(N19="None",N19=""),""," + "&N19)&IF(O19="Y"," + NACE MR0175",""),4,300)) -> Not stated | M19: Not stated | N19: None | O19: Not stated | P19: Not stated | Q19: Not stated | R19: Not stated | S19: Electric Motor | T19: Crude Oil | U19: 2 | V19: Centrifugal | W19: 15.2 | X19: Not stated | Y19: 1402 | Z19: EUR | AA19: 385000 | AB19: =IF(NOT(ISNUMBER(AA19)),"",IF(NOT(ISNUMBER(Y19)),"",IFERROR(IF(Z19="EUR",AA19,IF(Z19="IRR",AA19/INDEX('Assumptions & FX Reference'!$C$5:$C$25,MATCH(Y19,'Assumptions & FX Reference'!$A$5:$A$25,0)),IF(Z19="USD",AA19*INDEX('Assumptions & FX Reference'!$B$5:$B$25,MATCH(Y19,'Assumptions & FX Reference'!$A$5:$A$25,0))/INDEX('Assumptions & FX Reference'!$C$5:$C$25,MATCH(Y19,'Assumptions & FX Reference'!$A$5:$A$25,0)),""))),""))) -> 385000 | AC19: =IF(NOT(ISNUMBER(AA19)),"",IF(NOT(ISNUMBER(Y19)),"",IFERROR(IF(Z19="USD",AA19,IF(Z19="IRR",AA19/INDEX('Assumptions & FX Reference'!$B$5:$B$25,MATCH(Y19,'Assumptions & FX Reference'!$A$5:$A$25,0)),IF(Z19="EUR",AA19*INDEX('Assumptions & FX Reference'!$C$5:$C$25,MATCH(Y19,'Assumptions & FX Reference'!$A$5:$A$25,0))/INDEX('Assumptions & FX Reference'!$B$5:$B$25,MATCH(Y19,'Assumptions & FX Reference'!$A$5:$A$25,0)),""))),""))) -> 485375 | AD19: =IF(NOT(ISNUMBER(AA19)),"",IF(NOT(ISNUMBER(Y19)),"",IFERROR(IF(Z19="IRR",AA19,IF(Z19="USD",AA19*INDEX('Assumptions & FX Reference'!$B$5:$B$25,MATCH(Y19,'Assumptions & FX Reference'!$A$5:$A$25,0)),IF(Z19="EUR",AA19*INDEX('Assumptions & FX Reference'!$C$5:$C$25,MATCH(Y19,'Assumptions & FX Reference'!$A$5:$A$25,0)),""))),""))) -> 203857500000 | AE19: Consultant basic-design estimate – PEP Rev.1402/05, sheet P.ME «هزینه واحد بدون ضریب»; EUR figure (converted in the PEP at 420,000×1.085 IRR/EUR) | source label: AACE Class 2 | AF19: EXW | AG19: =IF(AND(Z19="EUR",N(AA19)>5000000),"",IF(AND(ISNUMBER(AB19),ISNUMBER(AZ19),ISNUMBER(BA19)),IF(AND(BB19="Y",ISNUMBER('Assumptions & FX Reference'!$I$15)),MAX(AB19*BA19/AZ19,'Assumptions & FX Reference'!$I$13*BA19/'Assumptions & FX Reference'!$I$15),AB19*BA19/AZ19),"")) -> 398446.64 | AH19: =IF(AND(ISNUMBER(AG19),ISNUMBER('Assumptions & FX Reference'!$I$8),ISNUMBER('Assumptions & FX Reference'!$I$11)),AG19*'Assumptions & FX Reference'!$I$8/'Assumptions & FX Reference'!$I$11,"") -> 420673.22 | AI19: =IF(AND(ISNUMBER(AG19),ISNUMBER('Assumptions & FX Reference'!$I$8)),AG19*'Assumptions & FX Reference'!$I$8,"") -> 2.770272e+11 | AJ19: (Gachsaran 4 Basic Design MTO) | AK19: Basic Design | AL19: Not stated | AM19: Not stated | AN19: Not stated | AO19: N | AP19: N | AQ19: N | AR19: Not stated | AS19: =IF(AND(Z19="EUR",N(AA19)>5000000),"Check currency (EUR>5M); ","")&IF(NOT(ISNUMBER(AA19)),"No price; ","")&IF(G19="Not stated","Material missing; ","")&IF(P19="Not stated","Seal missing; ","")&IF(K19="","Size driver missing; ","")&IF(NOT(ISNUMBER(AZ19)),"Base-year PPI missing; ","") -> Material missing; Seal missing; | AT19: =IFERROR(INDEX(Factors_ROT!$F$5:$F$200,MATCH("MAT|"&G19,Factors_ROT!$A$5:$A$200,0)),1) -> 1 | AU19: =IFERROR(INDEX(Factors_ROT!$F$5:$F$200,MATCH("SEAL_ARR|"&P19,Factors_ROT!$A$5:$A$200,0)),1)*IFERROR(INDEX(Factors_ROT!$F$5:$F$200,MATCH("SEAL_CAT|"&Q19,Factors_ROT!$A$5:$A$200,0)),1)*IFERROR(INDEX(Factors_ROT!$F$5:$F$200,MATCH("SEAL_PLAN|"&R19,Factors_ROT!$A$5:$A$200,0)),1) -> 1 | AV19: =IFERROR(INDEX(Factors_ROT!$F$5:$F$200,MATCH("DRV|"&S19,Factors_ROT!$A$5:$A$200,0)),1)*IFERROR(INDEX(Factors_ROT!$F$5:$F$200,MATCH("NACE|"&O19,Factors_ROT!$A$5:$A$200,0)),1) -> 1 | AW19: =IFERROR(INDEX(Factors_ROT!$F$5:$F$200,MATCH("SC_DRV|"&AL19,Factors_ROT!$A$5:$A$200,0)),1)*IFERROR(INDEX(Factors_ROT!$F$5:$F$200,MATCH("SC_BSP|"&AM19,Factors_ROT!$A$5:$A$200,0)),1)*IFERROR(INDEX(Factors_ROT!$F$5:$F$200,MATCH("SC_SEAL|"&AN19,Factors_ROT!$A$5:$A$200,0)),1)*IFERROR(INDEX(Factors_ROT!$F$5:$F$200,MATCH("SC_COMM|"&AO19,Factors_ROT!$A$5:$A$200,0)),1)*IFERROR(INDEX(Factors_ROT!$F$5:$F$200,MATCH("SC_2Y|"&AP19,Factors_ROT!$A$5:$A$200,0)),1)*IFERROR(INDEX(Factors_ROT!$F$5:$F$200,MATCH("SC_TPI|"&AQ19,Factors_ROT!$A$5:$A$200,0)),1)*IFERROR(INDEX(Factors_ROT!$F$5:$F$200,MATCH("SC_FAT|"&AR19,Factors_ROT!$A$5:$A$200,0)),1) -> 0.98 | AX19: =AT19*AU19*AV19*AW19 -> 0.98 | AY19: =IF(ISNUMBER(AB19),AB19/AX19,"") -> 392857.14 | AZ19: =IFERROR(IF(N(INDEX(Escalation_Index!$B$5:$B$25,MATCH(Y19,Escalation_Index!$A$5:$A$25,0)))>0,INDEX(Escalation_Index!$B$5:$B$25,MATCH(Y19,Escalation_Index!$A$5:$A$25,0)),""),"") -> 119.251 | BA19: =IF(ISNUMBER('Assumptions & FX Reference'!$I$12),'Assumptions & FX Reference'!$I$12,"") -> 123.416 | BB19: =IF(AND(M19="API 610",LEFT(V19,11)="Centrifugal",OR(LEFT(G19,2)="S-",LEFT(G19,2)="D-")),"Y","N") -> N | BC19: =IF(ISNUMBER(AG19),AG19/AX19,"") -> 406578.2 | BD19: =IF(AND(ISNUMBER(BC19),ISNUMBER(K19)),IF(K19>0,BC19/K19^'Assumptions & FX Reference'!$I$16,""),"") -> 16147.682 | BE19: File PEP-Rev 140205 Gachsaran 4.xlsx, sheet 'P.ME', cells A11:H11 (service in D, spec in E, unit price in H) | BF19: Type: Centrifugal (API 610) | Driver: موتور الکتریکی (E) | Power: 216.3 kW | مشخصات کاتالوگی: 500m3/hr, 15.2 bar, 216.3 kw | Original type text: Centrifugal (assumed) | GCH4 review 1405-07: Source IRR = EUR 385,000 × 1.085 × 420,000 (P.ME H11); previous bank stored the IRR figure as 1399 IRR, which overstated EUR ≈2.6× | BG19: Y | BH19: PMP | BI19: ="PMP-"&TEXT(A19,"0000") -> PMP-0015
A20: 16 | B20: AUXILLIARY TRANSFER PUMPS | C20: Gachsaran 4 | D20: P-002-A/B | E20: ROT-CRU | F20: Not stated | G20: Not stated | H20: 250 | J20: 108.1 | K20: =IF(ISNUMBER(J20),J20,IF(AND(ISNUMBER(H20),ISNUMBER(I20)),H20*I20/(367*'Assumptions & FX Reference'!$I$17),"")) -> 108.1 | L20: =IF(IF(OR(M20="Not stated",M20=""),""," + "&M20)&IF(OR(N20="None",N20=""),""," + "&N20)&IF(O20="Y"," + NACE MR0175","")="","Not stated",MID(IF(OR(M20="Not stated",M20=""),""," + "&M20)&IF(OR(N20="None",N20=""),""," + "&N20)&IF(O20="Y"," + NACE MR0175",""),4,300)) -> Not stated | M20: Not stated | N20: None | O20: Not stated | P20: Not stated | Q20: Not stated | R20: Not stated | S20: Electric Motor | T20: Crude Oil | U20: 2 | V20: Centrifugal | W20: 15.2 | X20: Not stated | Y20: 1402 | Z20: EUR | AA20: 135000 | AB20: =IF(NOT(ISNUMBER(AA20)),"",IF(NOT(ISNUMBER(Y20)),"",IFERROR(IF(Z20="EUR",AA20,IF(Z20="IRR",AA20/INDEX('Assumptions & FX Reference'!$C$5:$C$25,MATCH(Y20,'Assumptions & FX Reference'!$A$5:$A$25,0)),IF(Z20="USD",AA20*INDEX('Assumptions & FX Reference'!$B$5:$B$25,MATCH(Y20,'Assumptions & FX Reference'!$A$5:$A$25,0))/INDEX('Assumptions & FX Reference'!$C$5:$C$25,MATCH(Y20,'Assumptions & FX Reference'!$A$5:$A$25,0)),""))),""))) -> 135000 | AC20: =IF(NOT(ISNUMBER(AA20)),"",IF(NOT(ISNUMBER(Y20)),"",IFERROR(IF(Z20="USD",AA20,IF(Z20="IRR",AA20/INDEX('Assumptions & FX Reference'!$B$5:$B$25,MATCH(Y20,'Assumptions & FX Reference'!$A$5:$A$25,0)),IF(Z20="EUR",AA20*INDEX('Assumptions & FX Reference'!$C$5:$C$25,MATCH(Y20,'Assumptions & FX Reference'!$A$5:$A$25,0))/INDEX('Assumptions & FX Reference'!$B$5:$B$25,MATCH(Y20,'Assumptions & FX Reference'!$A$5:$A$25,0)),""))),""))) -> 170196.43 | AD20: =IF(NOT(ISNUMBER(AA20)),"",IF(NOT(ISNUMBER(Y20)),"",IFERROR(IF(Z20="IRR",AA20,IF(Z20="USD",AA20*INDEX('Assumptions & FX Reference'!$B$5:$B$25,MATCH(Y20,'Assumptions & FX Reference'!$A$5:$A$25,0)),IF(Z20="EUR",AA20*INDEX('Assumptions & FX Reference'!$C$5:$C$25,MATCH(Y20,'Assumptions & FX Reference'!$A$5:$A$25,0)),""))),""))) -> 71482500000 | AE20: Consultant basic-design estimate – PEP Rev.1402/05, sheet P.ME «هزینه واحد بدون ضریب»; EUR figure (converted in the PEP at 420,000×1.085 IRR/EUR) | source label: AACE Class 2 | AF20: EXW | AG20: =IF(AND(Z20="EUR",N(AA20)>5000000),"",IF(AND(ISNUMBER(AB20),ISNUMBER(AZ20),ISNUMBER(BA20)),IF(AND(BB20="Y",ISNUMBER('Assumptions & FX Reference'!$I$15)),MAX(AB20*BA20/AZ20,'Assumptions & FX Reference'!$I$13*BA20/'Assumptions & FX Reference'!$I$15),AB20*BA20/AZ20),"")) -> 139715.05 | AH20: =IF(AND(ISNUMBER(AG20),ISNUMBER('Assumptions & FX Reference'!$I$8),ISNUMBER('Assumptions & FX Reference'!$I$11)),AG20*'Assumptions & FX Reference'!$I$8/'Assumptions & FX Reference'!$I$11,"") -> 147508.79 | AI20: =IF(AND(ISNUMBER(AG20),ISNUMBER('Assumptions & FX Reference'!$I$8)),AG20*'Assumptions & FX Reference'!$I$8,"") -> 9.7139407e+10 | AJ20: (Gachsaran 4 Basic Design MTO) | AK20: Basic Design | AL20: Not stated | AM20: Not stated | AN20: Not stated | AO20: N | AP20: N | AQ20: N | AR20: Not stated | AS20: =IF(AND(Z20="EUR",N(AA20)>5000000),"Check currency (EUR>5M); ","")&IF(NOT(ISNUMBER(AA20)),"No price; ","")&IF(G20="Not stated","Material missing; ","")&IF(P20="Not stated","Seal missing; ","")&IF(K20="","Size driver missing; ","")&IF(NOT(ISNUMBER(AZ20)),"Base-year PPI missing; ","") -> Material missing; Seal missing; | AT20: =IFERROR(INDEX(Factors_ROT!$F$5:$F$200,MATCH("MAT|"&G20,Factors_ROT!$A$5:$A$200,0)),1) -> 1 | AU20: =IFERROR(INDEX(Factors_ROT!$F$5:$F$200,MATCH("SEAL_ARR|"&P20,Factors_ROT!$A$5:$A$200,0)),1)*IFERROR(INDEX(Factors_ROT!$F$5:$F$200,MATCH("SEAL_CAT|"&Q20,Factors_ROT!$A$5:$A$200,0)),1)*IFERROR(INDEX(Factors_ROT!$F$5:$F$200,MATCH("SEAL_PLAN|"&R20,Factors_ROT!$A$5:$A$200,0)),1) -> 1 | AV20: =IFERROR(INDEX(Factors_ROT!$F$5:$F$200,MATCH("DRV|"&S20,Factors_ROT!$A$5:$A$200,0)),1)*IFERROR(INDEX(Factors_ROT!$F$5:$F$200,MATCH("NACE|"&O20,Factors_ROT!$A$5:$A$200,0)),1) -> 1 | AW20: =IFERROR(INDEX(Factors_ROT!$F$5:$F$200,MATCH("SC_DRV|"&AL20,Factors_ROT!$A$5:$A$200,0)),1)*IFERROR(INDEX(Factors_ROT!$F$5:$F$200,MATCH("SC_BSP|"&AM20,Factors_ROT!$A$5:$A$200,0)),1)*IFERROR(INDEX(Factors_ROT!$F$5:$F$200,MATCH("SC_SEAL|"&AN20,Factors_ROT!$A$5:$A$200,0)),1)*IFERROR(INDEX(Factors_ROT!$F$5:$F$200,MATCH("SC_COMM|"&AO20,Factors_ROT!$A$5:$A$200,0)),1)*IFERROR(INDEX(Factors_ROT!$F$5:$F$200,MATCH("SC_2Y|"&AP20,Factors_ROT!$A$5:$A$200,0)),1)*IFERROR(INDEX(Factors_ROT!$F$5:$F$200,MATCH("SC_TPI|"&AQ20,Factors_ROT!$A$5:$A$200,0)),1)*IFERROR(INDEX(Factors_ROT!$F$5:$F$200,MATCH("SC_FAT|"&AR20,Factors_ROT!$A$5:$A$200,0)),1) -> 0.98 | AX20: =AT20*AU20*AV20*AW20 -> 0.98 | AY20: =IF(ISNUMBER(AB20),AB20/AX20,"") -> 137755.1 | AZ20: =IFERROR(IF(N(INDEX(Escalation_Index!$B$5:$B$25,MATCH(Y20,Escalation_Index!$A$5:$A$25,0)))>0,INDEX(Escalation_Index!$B$5:$B$25,MATCH(Y20,Escalation_Index!$A$5:$A$25,0)),""),"") -> 119.251 | BA20: =IF(ISNUMBER('Assumptions & FX Reference'!$I$12),'Assumptions & FX Reference'!$I$12,"") -> 123.416 | BB20: =IF(AND(M20="API 610",LEFT(V20,11)="Centrifugal",OR(LEFT(G20,2)="S-",LEFT(G20,2)="D-")),"Y","N") -> N | BC20: =IF(ISNUMBER(AG20),AG20/AX20,"") -> 142566.38 | BD20: =IF(AND(ISNUMBER(BC20),ISNUMBER(K20)),IF(K20>0,BC20/K20^'Assumptions & FX Reference'!$I$16,""),"") -> 8584.6326 | BE20: File PEP-Rev 140205 Gachsaran 4.xlsx, sheet 'P.ME', cells A12:H12 (service in D, spec in E, unit price in H) | BF20: Type: Centrifugal (API 610) | Driver: موتور الکتریکی (E) | Power: 108.1 kW | مشخصات کاتالوگی: 250m3/hr, 15.2 bar, 108.1 kw | Original type text: Centrifugal (assumed) | GCH4 review 1405-07: Source IRR = EUR 135,000 × 1.085 × 420,000 (P.ME H12); previous bank stored the IRR figure as 1399 IRR, which overstated EUR ≈2.6× | BG20: Y | BH20: PMP | BI20: ="PMP-"&TEXT(A20,"0000") -> PMP-0016
A21: 17 | B21: OFF-SPEC PUMPS | C21: Gachsaran 4 | D21: P-003-A/B | E21: ROT-CRU | F21: Not stated | G21: Not stated | H21: 100 | J21: 44.2 | K21: =IF(ISNUMBER(J21),J21,IF(AND(ISNUMBER(H21),ISNUMBER(I21)),H21*I21/(367*'Assumptions & FX Reference'!$I$17),"")) -> 44.2 | L21: =IF(IF(OR(M21="Not stated",M21=""),""," + "&M21)&IF(OR(N21="None",N21=""),""," + "&N21)&IF(O21="Y"," + NACE MR0175","")="","Not stated",MID(IF(OR(M21="Not stated",M21=""),""," + "&M21)&IF(OR(N21="None",N21=""),""," + "&N21)&IF(O21="Y"," + NACE MR0175",""),4,300)) -> Not stated | M21: Not stated | N21: None | O21: Not stated | P21: Not stated | Q21: Not stated | R21: Not stated | S21: Electric Motor | T21: Crude Oil | U21: 2 | V21: Centrifugal | W21: 15.5 | X21: Not stated | Y21: 1402 | Z21: EUR | AA21: 140000 | AB21: =IF(NOT(ISNUMBER(AA21)),"",IF(NOT(ISNUMBER(Y21)),"",IFERROR(IF(Z21="EUR",AA21,IF(Z21="IRR",AA21/INDEX('Assumptions & FX Reference'!$C$5:$C$25,MATCH(Y21,'Assumptions & FX Reference'!$A$5:$A$25,0)),IF(Z21="USD",AA21*INDEX('Assumptions & FX Reference'!$B$5:$B$25,MATCH(Y21,'Assumptions & FX Reference'!$A$5:$A$25,0))/INDEX('Assumptions & FX Reference'!$C$5:$C$25,MATCH(Y21,'Assumptions & FX Reference'!$A$5:$A$25,0)),""))),""))) -> 140000 | AC21: =IF(NOT(ISNUMBER(AA21)),"",IF(NOT(ISNUMBER(Y21)),"",IFERROR(IF(Z21="USD",AA21,IF(Z21="IRR",AA21/INDEX('Assumptions & FX Reference'!$B$5:$B$25,MATCH(Y21,'Assumptions & FX Reference'!$A$5:$A$25,0)),IF(Z21="EUR",AA21*INDEX('Assumptions & FX Reference'!$C$5:$C$25,MATCH(Y21,'Assumptions & FX Reference'!$A$5:$A$25,0))/INDEX('Assumptions & FX Reference'!$B$5:$B$25,MATCH(Y21,'Assumptions & FX Reference'!$A$5:$A$25,0)),""))),""))) -> 176500 | AD21: =IF(NOT(ISNUMBER(AA21)),"",IF(NOT(ISNUMBER(Y21)),"",IFERROR(IF(Z21="IRR",AA21,IF(Z21="USD",AA21*INDEX('Assumptions & FX Reference'!$B$5:$B$25,MATCH(Y21,'Assumptions & FX Reference'!$A$5:$A$25,0)),IF(Z21="EUR",AA21*INDEX('Assumptions & FX Reference'!$C$5:$C$25,MATCH(Y21,'Assumptions & FX Reference'!$A$5:$A$25,0)),""))),""))) -> 74130000000 | AE21: Consultant basic-design estimate – PEP Rev.1402/05, sheet P.ME «هزینه واحد بدون ضریب»; EUR figure (converted in the PEP at 420,000×1.085 IRR/EUR) | source label: AACE Class 2 | AF21: EXW | AG21: =IF(AND(Z21="EUR",N(AA21)>5000000),"",IF(AND(ISNUMBER(AB21),ISNUMBER(AZ21),ISNUMBER(BA21)),IF(AND(BB21="Y",ISNUMBER('Assumptions & FX Reference'!$I$15)),MAX(AB21*BA21/AZ21,'Assumptions & FX Reference'!$I$13*BA21/'Assumptions & FX Reference'!$I$15),AB21*BA21/AZ21),"")) -> 144889.69 | AH21: =IF(AND(ISNUMBER(AG21),ISNUMBER('Assumptions & FX Reference'!$I$8),ISNUMBER('Assumptions & FX Reference'!$I$11)),AG21*'Assumptions & FX Reference'!$I$8/'Assumptions & FX Reference'!$I$11,"") -> 152972.08 | AI21: =IF(AND(ISNUMBER(AG21),ISNUMBER('Assumptions & FX Reference'!$I$8)),AG21*'Assumptions & FX Reference'!$I$8,"") -> 1.0073716e+11 | AJ21: (Gachsaran 4 Basic Design MTO) | AK21: Basic Design | AL21: Not stated | AM21: Not stated | AN21: Not stated | AO21: N | AP21: N | AQ21: N | AR21: Not stated | AS21: =IF(AND(Z21="EUR",N(AA21)>5000000),"Check currency (EUR>5M); ","")&IF(NOT(ISNUMBER(AA21)),"No price; ","")&IF(G21="Not stated","Material missing; ","")&IF(P21="Not stated","Seal missing; ","")&IF(K21="","Size driver missing; ","")&IF(NOT(ISNUMBER(AZ21)),"Base-year PPI missing; ","") -> Material missing; Seal missing; | AT21: =IFERROR(INDEX(Factors_ROT!$F$5:$F$200,MATCH("MAT|"&G21,Factors_ROT!$A$5:$A$200,0)),1) -> 1 | AU21: =IFERROR(INDEX(Factors_ROT!$F$5:$F$200,MATCH("SEAL_ARR|"&P21,Factors_ROT!$A$5:$A$200,0)),1)*IFERROR(INDEX(Factors_ROT!$F$5:$F$200,MATCH("SEAL_CAT|"&Q21,Factors_ROT!$A$5:$A$200,0)),1)*IFERROR(INDEX(Factors_ROT!$F$5:$F$200,MATCH("SEAL_PLAN|"&R21,Factors_ROT!$A$5:$A$200,0)),1) -> 1 | AV21: =IFERROR(INDEX(Factors_ROT!$F$5:$F$200,MATCH("DRV|"&S21,Factors_ROT!$A$5:$A$200,0)),1)*IFERROR(INDEX(Factors_ROT!$F$5:$F$200,MATCH("NACE|"&O21,Factors_ROT!$A$5:$A$200,0)),1) -> 1 | AW21: =IFERROR(INDEX(Factors_ROT!$F$5:$F$200,MATCH("SC_DRV|"&AL21,Factors_ROT!$A$5:$A$200,0)),1)*IFERROR(INDEX(Factors_ROT!$F$5:$F$200,MATCH("SC_BSP|"&AM21,Factors_ROT!$A$5:$A$200,0)),1)*IFERROR(INDEX(Factors_ROT!$F$5:$F$200,MATCH("SC_SEAL|"&AN21,Factors_ROT!$A$5:$A$200,0)),1)*IFERROR(INDEX(Factors_ROT!$F$5:$F$200,MATCH("SC_COMM|"&AO21,Factors_ROT!$A$5:$A$200,0)),1)*IFERROR(INDEX(Factors_ROT!$F$5:$F$200,MATCH("SC_2Y|"&AP21,Factors_ROT!$A$5:$A$200,0)),1)*IFERROR(INDEX(Factors_ROT!$F$5:$F$200,MATCH("SC_TPI|"&AQ21,Factors_ROT!$A$5:$A$200,0)),1)*IFERROR(INDEX(Factors_ROT!$F$5:$F$200,MATCH("SC_FAT|"&AR21,Factors_ROT!$A$5:$A$200,0)),1) -> 0.98 | AX21: =AT21*AU21*AV21*AW21 -> 0.98 | AY21: =IF(ISNUMBER(AB21),AB21/AX21,"") -> 142857.14 | AZ21: =IFERROR(IF(N(INDEX(Escalation_Index!$B$5:$B$25,MATCH(Y21,Escalation_Index!$A$5:$A$25,0)))>0,INDEX(Escalation_Index!$B$5:$B$25,MATCH(Y21,Escalation_Index!$A$5:$A$25,0)),""),"") -> 119.251 | BA21: =IF(ISNUMBER('Assumptions & FX Reference'!$I$12),'Assumptions & FX Reference'!$I$12,"") -> 123.416 | BB21: =IF(AND(M21="API 610",LEFT(V21,11)="Centrifugal",OR(LEFT(G21,2)="S-",LEFT(G21,2)="D-")),"Y","N") -> N | BC21: =IF(ISNUMBER(AG21),AG21/AX21,"") -> 147846.62 | BD21: =IF(AND(ISNUMBER(BC21),ISNUMBER(K21)),IF(K21>0,BC21/K21^'Assumptions & FX Reference'!$I$16,""),"") -> 15225.026 | BE21: File PEP-Rev 140205 Gachsaran 4.xlsx, sheet 'P.ME', cells A13:H13 (service in D, spec in E, unit price in H) | BF21: Type: Centrifugal (API 610) | Driver: موتور الکتریکی (E) | Power: 44.2 kW | NACE MR0175: YES | مشخصات کاتالوگی: 100 m3/hr , 15.5 bar,44.2 kw | Original type text: Centrifugal (assumed) | GCH4 review 1405-07: Source IRR = EUR 140,000 × 1.085 × 420,000 (P.ME H13); previous bank stored the IRR figure as 1399 IRR, which overstated EUR ≈2.6× | BG21: Y | BH21: PMP | BI21: ="PMP-"&TEXT(A21,"0000") -> PMP-0017
A22: 18 | B22: DEGASSING WATER PUMPS | C22: Gachsaran 4 | D22: P-005-A/B | E22: ROT-WAT | F22: Not stated | G22: Not stated | H22: 30 | J22: 2.7 | K22: =IF(ISNUMBER(J22),J22,IF(AND(ISNUMBER(H22),ISNUMBER(I22)),H22*I22/(367*'Assumptions & FX Reference'!$I$17),"")) -> 2.7 | L22: =IF(IF(OR(M22="Not stated",M22=""),""," + "&M22)&IF(OR(N22="None",N22=""),""," + "&N22)&IF(O22="Y"," + NACE MR0175","")="","Not stated",MID(IF(OR(M22="Not stated",M22=""),""," + "&M22)&IF(OR(N22="None",N22=""),""," + "&N22)&IF(O22="Y"," + NACE MR0175",""),4,300)) -> Not stated | M22: Not stated | N22: None | O22: Not stated | P22: Not stated | Q22: Not stated | R22: Not stated | S22: Electric Motor | T22: Process / Dilution Water | U22: 2 | V22: Centrifugal | W22: 3 | X22: Not stated | Y22: 1402 | Z22: EUR | AA22: 34000 | AB22: =IF(NOT(ISNUMBER(AA22)),"",IF(NOT(ISNUMBER(Y22)),"",IFERROR(IF(Z22="EUR",AA22,IF(Z22="IRR",AA22/INDEX('Assumptions & FX Reference'!$C$5:$C$25,MATCH(Y22,'Assumptions & FX Reference'!$A$5:$A$25,0)),IF(Z22="USD",AA22*INDEX('Assumptions & FX Reference'!$B$5:$B$25,MATCH(Y22,'Assumptions & FX Reference'!$A$5:$A$25,0))/INDEX('Assumptions & FX Reference'!$C$5:$C$25,MATCH(Y22,'Assumptions & FX Reference'!$A$5:$A$25,0)),""))),""))) -> 34000 | AC22: =IF(NOT(ISNUMBER(AA22)),"",IF(NOT(ISNUMBER(Y22)),"",IFERROR(IF(Z22="USD",AA22,IF(Z22="IRR",AA22/INDEX('Assumptions & FX Reference'!$B$5:$B$25,MATCH(Y22,'Assumptions & FX Reference'!$A$5:$A$25,0)),IF(Z22="EUR",AA22*INDEX('Assumptions & FX Reference'!$C$5:$C$25,MATCH(Y22,'Assumptions & FX Reference'!$A$5:$A$25,0))/INDEX('Assumptions & FX Reference'!$B$5:$B$25,MATCH(Y22,'Assumptions & FX Reference'!$A$5:$A$25,0)),""))),""))) -> 42864.286 | AD22: =IF(NOT(ISNUMBER(AA22)),"",IF(NOT(ISNUMBER(Y22)),"",IFERROR(IF(Z22="IRR",AA22,IF(Z22="USD",AA22*INDEX('Assumptions & FX Reference'!$B$5:$B$25,MATCH(Y22,'Assumptions & FX Reference'!$A$5:$A$25,0)),IF(Z22="EUR",AA22*INDEX('Assumptions & FX Reference'!$C$5:$C$25,MATCH(Y22,'Assumptions & FX Reference'!$A$5:$A$25,0)),""))),""))) -> 18003000000 | AE22: Consultant basic-design estimate – PEP Rev.1402/05, sheet P.ME «هزینه واحد بدون ضریب»; EUR figure (converted in the PEP at 420,000×1.085 IRR/EUR) | source label: AACE Class 2 | AF22: EXW | AG22: =IF(AND(Z22="EUR",N(AA22)>5000000),"",IF(AND(ISNUMBER(AB22),ISNUMBER(AZ22),ISNUMBER(BA22)),IF(AND(BB22="Y",ISNUMBER('Assumptions & FX Reference'!$I$15)),MAX(AB22*BA22/AZ22,'Assumptions & FX Reference'!$I$13*BA22/'Assumptions & FX Reference'!$I$15),AB22*BA22/AZ22),"")) -> 35187.495 | AH22: =IF(AND(ISNUMBER(AG22),ISNUMBER('Assumptions & FX Reference'!$I$8),ISNUMBER('Assumptions & FX Reference'!$I$11)),AG22*'Assumptions & FX Reference'!$I$8/'Assumptions & FX Reference'!$I$11,"") -> 37150.362 | AI22: =IF(AND(ISNUMBER(AG22),ISNUMBER('Assumptions & FX Reference'!$I$8)),AG22*'Assumptions & FX Reference'!$I$8,"") -> 2.4464739e+10 | AJ22: (Gachsaran 4 Basic Design MTO) | AK22: Basic Design | AL22: Not stated | AM22: Not stated | AN22: Not stated | AO22: N | AP22: N | AQ22: N | AR22: Not stated | AS22: =IF(AND(Z22="EUR",N(AA22)>5000000),"Check currency (EUR>5M); ","")&IF(NOT(ISNUMBER(AA22)),"No price; ","")&IF(G22="Not stated","Material missing; ","")&IF(P22="Not stated","Seal missing; ","")&IF(K22="","Size driver missing; ","")&IF(NOT(ISNUMBER(AZ22)),"Base-year PPI missing; ","") -> Material missing; Seal missing; | AT22: =IFERROR(INDEX(Factors_ROT!$F$5:$F$200,MATCH("MAT|"&G22,Factors_ROT!$A$5:$A$200,0)),1) -> 1 | AU22: =IFERROR(INDEX(Factors_ROT!$F$5:$F$200,MATCH("SEAL_ARR|"&P22,Factors_ROT!$A$5:$A$200,0)),1)*IFERROR(INDEX(Factors_ROT!$F$5:$F$200,MATCH("SEAL_CAT|"&Q22,Factors_ROT!$A$5:$A$200,0)),1)*IFERROR(INDEX(Factors_ROT!$F$5:$F$200,MATCH("SEAL_PLAN|"&R22,Factors_ROT!$A$5:$A$200,0)),1) -> 1 | AV22: =IFERROR(INDEX(Factors_ROT!$F$5:$F$200,MATCH("DRV|"&S22,Factors_ROT!$A$5:$A$200,0)),1)*IFERROR(INDEX(Factors_ROT!$F$5:$F$200,MATCH("NACE|"&O22,Factors_ROT!$A$5:$A$200,0)),1) -> 1 | AW22: =IFERROR(INDEX(Factors_ROT!$F$5:$F$200,MATCH("SC_DRV|"&AL22,Factors_ROT!$A$5:$A$200,0)),1)*IFERROR(INDEX(Factors_ROT!$F$5:$F$200,MATCH("SC_BSP|"&AM22,Factors_ROT!$A$5:$A$200,0)),1)*IFERROR(INDEX(Factors_ROT!$F$5:$F$200,MATCH("SC_SEAL|"&AN22,Factors_ROT!$A$5:$A$200,0)),1)*IFERROR(INDEX(Factors_ROT!$F$5:$F$200,MATCH("SC_COMM|"&AO22,Factors_ROT!$A$5:$A$200,0)),1)*IFERROR(INDEX(Factors_ROT!$F$5:$F$200,MATCH("SC_2Y|"&AP22,Factors_ROT!$A$5:$A$200,0)),1)*IFERROR(INDEX(Factors_ROT!$F$5:$F$200,MATCH("SC_TPI|"&AQ22,Factors_ROT!$A$5:$A$200,0)),1)*IFERROR(INDEX(Factors_ROT!$F$5:$F$200,MATCH("SC_FAT|"&AR22,Factors_ROT!$A$5:$A$200,0)),1) -> 0.98 | AX22: =AT22*AU22*AV22*AW22 -> 0.98 | AY22: =IF(ISNUMBER(AB22),AB22/AX22,"") -> 34693.878 | AZ22: =IFERROR(IF(N(INDEX(Escalation_Index!$B$5:$B$25,MATCH(Y22,Escalation_Index!$A$5:$A$25,0)))>0,INDEX(Escalation_Index!$B$5:$B$25,MATCH(Y22,Escalation_Index!$A$5:$A$25,0)),""),"") -> 119.251 | BA22: =IF(ISNUMBER('Assumptions & FX Reference'!$I$12),'Assumptions & FX Reference'!$I$12,"") -> 123.416 | BB22: =IF(AND(M22="API 610",LEFT(V22,11)="Centrifugal",OR(LEFT(G22,2)="S-",LEFT(G22,2)="D-")),"Y","N") -> N | BC22: =IF(ISNUMBER(AG22),AG22/AX22,"") -> 35905.607 | BD22: =IF(AND(ISNUMBER(BC22),ISNUMBER(K22)),IF(K22>0,BC22/K22^'Assumptions & FX Reference'!$I$16,""),"") -> 19785.363 | BE22: File PEP-Rev 140205 Gachsaran 4.xlsx, sheet 'P.ME', cells A14:H14 (service in D, spec in E, unit price in H) | BF22: Type: Centrifugal (API 610) | Driver: موتور الکتریکی (E) | Power: 2.7 kW | مشخصات کاتالوگی: 30m3/hr, 3bar, 2.7 kw | Original type text: Centrifugal (assumed) | GCH4 review 1405-07: Source IRR = EUR 34,000 × 1.085 × 420,000 (P.ME H14); previous bank stored the IRR figure as 1399 IRR, which overstated EUR ≈2.6× | BG22: Y | BH22: PMP | BI22: ="PMP-"&TEXT(A22,"0000") -> PMP-0018
A23: 19 | B23: DILUTION WATER PUMPS | C23: Gachsaran 4 | D23: P-103 | E23: ROT-WAT | F23: Not stated | G23: Not stated | H23: 40 | J23: 12 | K23: =IF(ISNUMBER(J23),J23,IF(AND(ISNUMBER(H23),ISNUMBER(I23)),H23*I23/(367*'Assumptions & FX Reference'!$I$17),"")) -> 12 | L23: =IF(IF(OR(M23="Not stated",M23=""),""," + "&M23)&IF(OR(N23="None",N23=""),""," + "&N23)&IF(O23="Y"," + NACE MR0175","")="","Not stated",MID(IF(OR(M23="Not stated",M23=""),""," + "&M23)&IF(OR(N23="None",N23=""),""," + "&N23)&IF(O23="Y"," + NACE MR0175",""),4,300)) -> Not stated | M23: Not stated | N23: None | O23: Not stated | P23: Not stated | Q23: Not stated | R23: Not stated | S23: Electric Motor | T23: Process / Dilution Water | U23: 1 | V23: Centrifugal | W23: 10.4 | X23: Not stated | Y23: 1402 | Z23: EUR | AA23: 29000 | AB23: =IF(NOT(ISNUMBER(AA23)),"",IF(NOT(ISNUMBER(Y23)),"",IFERROR(IF(Z23="EUR",AA23,IF(Z23="IRR",AA23/INDEX('Assumptions & FX Reference'!$C$5:$C$25,MATCH(Y23,'Assumptions & FX Reference'!$A$5:$A$25,0)),IF(Z23="USD",AA23*INDEX('Assumptions & FX Reference'!$B$5:$B$25,MATCH(Y23,'Assumptions & FX Reference'!$A$5:$A$25,0))/INDEX('Assumptions & FX Reference'!$C$5:$C$25,MATCH(Y23,'Assumptions & FX Reference'!$A$5:$A$25,0)),""))),""))) -> 29000 | AC23: =IF(NOT(ISNUMBER(AA23)),"",IF(NOT(ISNUMBER(Y23)),"",IFERROR(IF(Z23="USD",AA23,IF(Z23="IRR",AA23/INDEX('Assumptions & FX Reference'!$B$5:$B$25,MATCH(Y23,'Assumptions & FX Reference'!$A$5:$A$25,0)),IF(Z23="EUR",AA23*INDEX('Assumptions & FX Reference'!$C$5:$C$25,MATCH(Y23,'Assumptions & FX Reference'!$A$5:$A$25,0))/INDEX('Assumptions & FX Reference'!$B$5:$B$25,MATCH(Y23,'Assumptions & FX Reference'!$A$5:$A$25,0)),""))),""))) -> 36560.714 | AD23: =IF(NOT(ISNUMBER(AA23)),"",IF(NOT(ISNUMBER(Y23)),"",IFERROR(IF(Z23="IRR",AA23,IF(Z23="USD",AA23*INDEX('Assumptions & FX Reference'!$B$5:$B$25,MATCH(Y23,'Assumptions & FX Reference'!$A$5:$A$25,0)),IF(Z23="EUR",AA23*INDEX('Assumptions & FX Reference'!$C$5:$C$25,MATCH(Y23,'Assumptions & FX Reference'!$A$5:$A$25,0)),""))),""))) -> 15355500000 | AE23: Consultant basic-design estimate – PEP Rev.1402/05, sheet P.ME «هزینه واحد بدون ضریب»; EUR figure (converted in the PEP at 420,000×1.085 IRR/EUR) | source label: AACE Class 2 | AF23: EXW | AG23: =IF(AND(Z23="EUR",N(AA23)>5000000),"",IF(AND(ISNUMBER(AB23),ISNUMBER(AZ23),ISNUMBER(BA23)),IF(AND(BB23="Y",ISNUMBER('Assumptions & FX Reference'!$I$15)),MAX(AB23*BA23/AZ23,'Assumptions & FX Reference'!$I$13*BA23/'Assumptions & FX Reference'!$I$15),AB23*BA23/AZ23),"")) -> 30012.864 | AH23: =IF(AND(ISNUMBER(AG23),ISNUMBER('Assumptions & FX Reference'!$I$8),ISNUMBER('Assumptions & FX Reference'!$I$11)),AG23*'Assumptions & FX Reference'!$I$8/'Assumptions & FX Reference'!$I$11,"") -> 31687.074 | AI23: =IF(AND(ISNUMBER(AG23),ISNUMBER('Assumptions & FX Reference'!$I$8)),AG23*'Assumptions & FX Reference'!$I$8,"") -> 2.0866984e+10 | AJ23: (Gachsaran 4 Basic Design MTO) | AK23: Basic Design | AL23: Not stated | AM23: Not stated | AN23: Not stated | AO23: N | AP23: N | AQ23: N | AR23: Not stated | AS23: =IF(AND(Z23="EUR",N(AA23)>5000000),"Check currency (EUR>5M); ","")&IF(NOT(ISNUMBER(AA23)),"No price; ","")&IF(G23="Not stated","Material missing; ","")&IF(P23="Not stated","Seal missing; ","")&IF(K23="","Size driver missing; ","")&IF(NOT(ISNUMBER(AZ23)),"Base-year PPI missing; ","") -> Material missing; Seal missing; | AT23: =IFERROR(INDEX(Factors_ROT!$F$5:$F$200,MATCH("MAT|"&G23,Factors_ROT!$A$5:$A$200,0)),1) -> 1 | AU23: =IFERROR(INDEX(Factors_ROT!$F$5:$F$200,MATCH("SEAL_ARR|"&P23,Factors_ROT!$A$5:$A$200,0)),1)*IFERROR(INDEX(Factors_ROT!$F$5:$F$200,MATCH("SEAL_CAT|"&Q23,Factors_ROT!$A$5:$A$200,0)),1)*IFERROR(INDEX(Factors_ROT!$F$5:$F$200,MATCH("SEAL_PLAN|"&R23,Factors_ROT!$A$5:$A$200,0)),1) -> 1 | AV23: =IFERROR(INDEX(Factors_ROT!$F$5:$F$200,MATCH("DRV|"&S23,Factors_ROT!$A$5:$A$200,0)),1)*IFERROR(INDEX(Factors_ROT!$F$5:$F$200,MATCH("NACE|"&O23,Factors_ROT!$A$5:$A$200,0)),1) -> 1 | AW23: =IFERROR(INDEX(Factors_ROT!$F$5:$F$200,MATCH("SC_DRV|"&AL23,Factors_ROT!$A$5:$A$200,0)),1)*IFERROR(INDEX(Factors_ROT!$F$5:$F$200,MATCH("SC_BSP|"&AM23,Factors_ROT!$A$5:$A$200,0)),1)*IFERROR(INDEX(Factors_ROT!$F$5:$F$200,MATCH("SC_SEAL|"&AN23,Factors_ROT!$A$5:$A$200,0)),1)*IFERROR(INDEX(Factors_ROT!$F$5:$F$200,MATCH("SC_COMM|"&AO23,Factors_ROT!$A$5:$A$200,0)),1)*IFERROR(INDEX(Factors_ROT!$F$5:$F$200,MATCH("SC_2Y|"&AP23,Factors_ROT!$A$5:$A$200,0)),1)*IFERROR(INDEX(Factors_ROT!$F$5:$F$200,MATCH("SC_TPI|"&AQ23,Factors_ROT!$A$5:$A$200,0)),1)*IFERROR(INDEX(Factors_ROT!$F$5:$F$200,MATCH("SC_FAT|"&AR23,Factors_ROT!$A$5:$A$200,0)),1) -> 0.98 | AX23: =AT23*AU23*AV23*AW23 -> 0.98 | AY23: =IF(ISNUMBER(AB23),AB23/AX23,"") -> 29591.837 | AZ23: =IFERROR(IF(N(INDEX(Escalation_Index!$B$5:$B$25,MATCH(Y23,Escalation_Index!$A$5:$A$25,0)))>0,INDEX(Escalation_Index!$B$5:$B$25,MATCH(Y23,Escalation_Index!$A$5:$A$25,0)),""),"") -> 119.251 | BA23: =IF(ISNUMBER('Assumptions & FX Reference'!$I$12),'Assumptions & FX Reference'!$I$12,"") -> 123.416 | BB23: =IF(AND(M23="API 610",LEFT(V23,11)="Centrifugal",OR(LEFT(G23,2)="S-",LEFT(G23,2)="D-")),"Y","N") -> N | BC23: =IF(ISNUMBER(AG23),AG23/AX23,"") -> 30625.371 | BD23: =IF(AND(ISNUMBER(BC23),ISNUMBER(K23)),IF(K23>0,BC23/K23^'Assumptions & FX Reference'!$I$16,""),"") -> 6895.6087 | BE23: File PEP-Rev 140205 Gachsaran 4.xlsx, sheet 'P.ME', cells A17:H17 (service in D, spec in E, unit price in H) | BF23: Type: Centrifugal (API 610) | Driver: موتور الکتریکی (E) | Power: 12 kW | مشخصات کاتالوگی: 40m3/hr , 10.4 bar, 12 kw | Original type text: Centrifugal (assumed) | GCH4 review 1405-07: Source IRR = EUR 29,000 × 1.085 × 420,000 (P.ME H17); previous bank stored the IRR figure as 1399 IRR, which overstated EUR ≈2.6× | BG23: Y | BH23: PMP | BI23: ="PMP-"&TEXT(A23,"0000") -> PMP-0019
A24: 20 | B24: DILUTION WATER PUMPS | C24: Gachsaran 4 | D24: P-106-A1/A2 | E24: ROT-WAT | F24: Not stated | G24: Not stated | H24: 20 | J24: 6 | K24: =IF(ISNUMBER(J24),J24,IF(AND(ISNUMBER(H24),ISNUMBER(I24)),H24*I24/(367*'Assumptions & FX Reference'!$I$17),"")) -> 6 | L24: =IF(IF(OR(M24="Not stated",M24=""),""," + "&M24)&IF(OR(N24="None",N24=""),""," + "&N24)&IF(O24="Y"," + NACE MR0175","")="","Not stated",MID(IF(OR(M24="Not stated",M24=""),""," + "&M24)&IF(OR(N24="None",N24=""),""," + "&N24)&IF(O24="Y"," + NACE MR0175",""),4,300)) -> Not stated | M24: Not stated | N24: None | O24: Not stated | P24: Not stated | Q24: Not stated | R24: Not stated | S24: Electric Motor | T24: Process / Dilution Water | U24: 2 | V24: Centrifugal | W24: 10.4 | X24: Not stated | Y24: 1402 | Z24: EUR | AA24: 27500 | AB24: =IF(NOT(ISNUMBER(AA24)),"",IF(NOT(ISNUMBER(Y24)),"",IFERROR(IF(Z24="EUR",AA24,IF(Z24="IRR",AA24/INDEX('Assumptions & FX Reference'!$C$5:$C$25,MATCH(Y24,'Assumptions & FX Reference'!$A$5:$A$25,0)),IF(Z24="USD",AA24*INDEX('Assumptions & FX Reference'!$B$5:$B$25,MATCH(Y24,'Assumptions & FX Reference'!$A$5:$A$25,0))/INDEX('Assumptions & FX Reference'!$C$5:$C$25,MATCH(Y24,'Assumptions & FX Reference'!$A$5:$A$25,0)),""))),""))) -> 27500 | AC24: =IF(NOT(ISNUMBER(AA24)),"",IF(NOT(ISNUMBER(Y24)),"",IFERROR(IF(Z24="USD",AA24,IF(Z24="IRR",AA24/INDEX('Assumptions & FX Reference'!$B$5:$B$25,MATCH(Y24,'Assumptions & FX Reference'!$A$5:$A$25,0)),IF(Z24="EUR",AA24*INDEX('Assumptions & FX Reference'!$C$5:$C$25,MATCH(Y24,'Assumptions & FX Reference'!$A$5:$A$25,0))/INDEX('Assumptions & FX Reference'!$B$5:$B$25,MATCH(Y24,'Assumptions & FX Reference'!$A$5:$A$25,0)),""))),""))) -> 34669.643 | AD24: =IF(NOT(ISNUMBER(AA24)),"",IF(NOT(ISNUMBER(Y24)),"",IFERROR(IF(Z24="IRR",AA24,IF(Z24="USD",AA24*INDEX('Assumptions & FX Reference'!$B$5:$B$25,MATCH(Y24,'Assumptions & FX Reference'!$A$5:$A$25,0)),IF(Z24="EUR",AA24*INDEX('Assumptions & FX Reference'!$C$5:$C$25,MATCH(Y24,'Assumptions & FX Reference'!$A$5:$A$25,0)),""))),""))) -> 14561250000 | AE24: Consultant basic-design estimate – PEP Rev.1402/05, sheet P.ME «هزینه واحد بدون ضریب»; EUR figure (converted in the PEP at 420,000×1.085 IRR/EUR) | source label: AACE Class 2 | AF24: EXW | AG24: =IF(AND(Z24="EUR",N(AA24)>5000000),"",IF(AND(ISNUMBER(AB24),ISNUMBER(AZ24),ISNUMBER(BA24)),IF(AND(BB24="Y",ISNUMBER('Assumptions & FX Reference'!$I$15)),MAX(AB24*BA24/AZ24,'Assumptions & FX Reference'!$I$13*BA24/'Assumptions & FX Reference'!$I$15),AB24*BA24/AZ24),"")) -> 28460.474 | AH24: =IF(AND(ISNUMBER(AG24),ISNUMBER('Assumptions & FX Reference'!$I$8),ISNUMBER('Assumptions & FX Reference'!$I$11)),AG24*'Assumptions & FX Reference'!$I$8/'Assumptions & FX Reference'!$I$11,"") -> 30048.087 | AI24: =IF(AND(ISNUMBER(AG24),ISNUMBER('Assumptions & FX Reference'!$I$8)),AG24*'Assumptions & FX Reference'!$I$8,"") -> 1.9787657e+10 | AJ24: (Gachsaran 4 Basic Design MTO) | AK24: Basic Design | AL24: Not stated | AM24: Not stated | AN24: Not stated | AO24: N | AP24: N | AQ24: N | AR24: Not stated | AS24: =IF(AND(Z24="EUR",N(AA24)>5000000),"Check currency (EUR>5M); ","")&IF(NOT(ISNUMBER(AA24)),"No price; ","")&IF(G24="Not stated","Material missing; ","")&IF(P24="Not stated","Seal missing; ","")&IF(K24="","Size driver missing; ","")&IF(NOT(ISNUMBER(AZ24)),"Base-year PPI missing; ","") -> Material missing; Seal missing; | AT24: =IFERROR(INDEX(Factors_ROT!$F$5:$F$200,MATCH("MAT|"&G24,Factors_ROT!$A$5:$A$200,0)),1) -> 1 | AU24: =IFERROR(INDEX(Factors_ROT!$F$5:$F$200,MATCH("SEAL_ARR|"&P24,Factors_ROT!$A$5:$A$200,0)),1)*IFERROR(INDEX(Factors_ROT!$F$5:$F$200,MATCH("SEAL_CAT|"&Q24,Factors_ROT!$A$5:$A$200,0)),1)*IFERROR(INDEX(Factors_ROT!$F$5:$F$200,MATCH("SEAL_PLAN|"&R24,Factors_ROT!$A$5:$A$200,0)),1) -> 1 | AV24: =IFERROR(INDEX(Factors_ROT!$F$5:$F$200,MATCH("DRV|"&S24,Factors_ROT!$A$5:$A$200,0)),1)*IFERROR(INDEX(Factors_ROT!$F$5:$F$200,MATCH("NACE|"&O24,Factors_ROT!$A$5:$A$200,0)),1) -> 1 | AW24: =IFERROR(INDEX(Factors_ROT!$F$5:$F$200,MATCH("SC_DRV|"&AL24,Factors_ROT!$A$5:$A$200,0)),1)*IFERROR(INDEX(Factors_ROT!$F$5:$F$200,MATCH("SC_BSP|"&AM24,Factors_ROT!$A$5:$A$200,0)),1)*IFERROR(INDEX(Factors_ROT!$F$5:$F$200,MATCH("SC_SEAL|"&AN24,Factors_ROT!$A$5:$A$200,0)),1)*IFERROR(INDEX(Factors_ROT!$F$5:$F$200,MATCH("SC_COMM|"&AO24,Factors_ROT!$A$5:$A$200,0)),1)*IFERROR(INDEX(Factors_ROT!$F$5:$F$200,MATCH("SC_2Y|"&AP24,Factors_ROT!$A$5:$A$200,0)),1)*IFERROR(INDEX(Factors_ROT!$F$5:$F$200,MATCH("SC_TPI|"&AQ24,Factors_ROT!$A$5:$A$200,0)),1)*IFERROR(INDEX(Factors_ROT!$F$5:$F$200,MATCH("SC_FAT|"&AR24,Factors_ROT!$A$5:$A$200,0)),1) -> 0.98 | AX24: =AT24*AU24*AV24*AW24 -> 0.98 | AY24: =IF(ISNUMBER(AB24),AB24/AX24,"") -> 28061.224 | AZ24: =IFERROR(IF(N(INDEX(Escalation_Index!$B$5:$B$25,MATCH(Y24,Escalation_Index!$A$5:$A$25,0)))>0,INDEX(Escalation_Index!$B$5:$B$25,MATCH(Y24,Escalation_Index!$A$5:$A$25,0)),""),"") -> 119.251 | BA24: =IF(ISNUMBER('Assumptions & FX Reference'!$I$12),'Assumptions & FX Reference'!$I$12,"") -> 123.416 | BB24: =IF(AND(M24="API 610",LEFT(V24,11)="Centrifugal",OR(LEFT(G24,2)="S-",LEFT(G24,2)="D-")),"Y","N") -> N | BC24: =IF(ISNUMBER(AG24),AG24/AX24,"") -> 29041.3 | BD24: =IF(AND(ISNUMBER(BC24),ISNUMBER(K24)),IF(K24>0,BC24/K24^'Assumptions & FX Reference'!$I$16,""),"") -> 9911.1787 | BE24: File PEP-Rev 140205 Gachsaran 4.xlsx, sheet 'P.ME', cells A18:H18 (service in D, spec in E, unit price in H) | BF24: Type: Centrifugal (API 610) | Driver: موتور الکتریکی (E) | Power: 6 kW | مشخصات کاتالوگی: 20 m3/hr, 10.4 bar, 6 kw | Original type text: Centrifugal (assumed) | GCH4 review 1405-07: Source IRR = EUR 27,500 × 1.085 × 420,000 (P.ME H18); previous bank stored the IRR figure as 1399 IRR, which overstated EUR ≈2.6× | BG24: Y | BH24: PMP | BI24: ="PMP-"&TEXT(A24,"0000") -> PMP-0020
A25: 21 | B25: DEAERATED WATER PUMPS | C25: Gachsaran 4 | D25: P-102-A/B | E25: ROT-WAT | F25: Not stated | G25: Not stated | H25: 20 | J25: 1.35 | K25: =IF(ISNUMBER(J25),J25,IF(AND(ISNUMBER(H25),ISNUMBER(I25)),H25*I25/(367*'Assumptions & FX Reference'!$I$17),"")) -> 1.35 | L25: =IF(IF(OR(M25="Not stated",M25=""),""," + "&M25)&IF(OR(N25="None",N25=""),""," + "&N25)&IF(O25="Y"," + NACE MR0175","")="","Not stated",MID(IF(OR(M25="Not stated",M25=""),""," + "&M25)&IF(OR(N25="None",N25=""),""," + "&N25)&IF(O25="Y"," + NACE MR0175",""),4,300)) -> Not stated | M25: Not stated | N25: None | O25: Not stated | P25: Not stated | Q25: Not stated | R25: Not stated | S25: Electric Motor | T25: Deaerated Water | U25: 2 | V25: Centrifugal | W25: 2.4 | X25: Not stated | Y25: 1402 | Z25: EUR | AA25: 15000 | AB25: =IF(NOT(ISNUMBER(AA25)),"",IF(NOT(ISNUMBER(Y25)),"",IFERROR(IF(Z25="EUR",AA25,IF(Z25="IRR",AA25/INDEX('Assumptions & FX Reference'!$C$5:$C$25,MATCH(Y25,'Assumptions & FX Reference'!$A$5:$A$25,0)),IF(Z25="USD",AA25*INDEX('Assumptions & FX Reference'!$B$5:$B$25,MATCH(Y25,'Assumptions & FX Reference'!$A$5:$A$25,0))/INDEX('Assumptions & FX Reference'!$C$5:$C$25,MATCH(Y25,'Assumptions & FX Reference'!$A$5:$A$25,0)),""))),""))) -> 15000 | AC25: =IF(NOT(ISNUMBER(AA25)),"",IF(NOT(ISNUMBER(Y25)),"",IFERROR(IF(Z25="USD",AA25,IF(Z25="IRR",AA25/INDEX('Assumptions & FX Reference'!$B$5:$B$25,MATCH(Y25,'Assumptions & FX Reference'!$A$5:$A$25,0)),IF(Z25="EUR",AA25*INDEX('Assumptions & FX Reference'!$C$5:$C$25,MATCH(Y25,'Assumptions & FX Reference'!$A$5:$A$25,0))/INDEX('Assumptions & FX Reference'!$B$5:$B$25,MATCH(Y25,'Assumptions & FX Reference'!$A$5:$A$25,0)),""))),""))) -> 18910.714 | AD25: =IF(NOT(ISNUMBER(AA25)),"",IF(NOT(ISNUMBER(Y25)),"",IFERROR(IF(Z25="IRR",AA25,IF(Z25="USD",AA25*INDEX('Assumptions & FX Reference'!$B$5:$B$25,MATCH(Y25,'Assumptions & FX Reference'!$A$5:$A$25,0)),IF(Z25="EUR",AA25*INDEX('Assumptions & FX Reference'!$C$5:$C$25,MATCH(Y25,'Assumptions & FX Reference'!$A$5:$A$25,0)),""))),""))) -> 7942500000 | AE25: Consultant basic-design estimate – PEP Rev.1402/05, sheet P.ME «هزینه واحد بدون ضریب»; EUR figure (converted in the PEP at 420,000×1.085 IRR/EUR) | source label: AACE Class 2 | AF25: EXW | AG25: =IF(AND(Z25="EUR",N(AA25)>5000000),"",IF(AND(ISNUMBER(AB25),ISNUMBER(AZ25),ISNUMBER(BA25)),IF(AND(BB25="Y",ISNUMBER('Assumptions & FX Reference'!$I$15)),MAX(AB25*BA25/AZ25,'Assumptions & FX Reference'!$I$13*BA25/'Assumptions & FX Reference'!$I$15),AB25*BA25/AZ25),"")) -> 15523.895 | AH25: =IF(AND(ISNUMBER(AG25),ISNUMBER('Assumptions & FX Reference'!$I$8),ISNUMBER('Assumptions & FX Reference'!$I$11)),AG25*'Assumptions & FX Reference'!$I$8/'Assumptions & FX Reference'!$I$11,"") -> 16389.866 | AI25: =IF(AND(ISNUMBER(AG25),ISNUMBER('Assumptions & FX Reference'!$I$8)),AG25*'Assumptions & FX Reference'!$I$8,"") -> 1.0793267e+10 | AJ25: (Gachsaran 4 Basic Design MTO) | AK25: Basic Design | AL25: Not stated | AM25: Not stated | AN25: Not stated | AO25: N | AP25: N | AQ25: N | AR25: Not stated | AS25: =IF(AND(Z25="EUR",N(AA25)>5000000),"Check currency (EUR>5M); ","")&IF(NOT(ISNUMBER(AA25)),"No price; ","")&IF(G25="Not stated","Material missing; ","")&IF(P25="Not stated","Seal missing; ","")&IF(K25="","Size driver missing; ","")&IF(NOT(ISNUMBER(AZ25)),"Base-year PPI missing; ","") -> Material missing; Seal missing; | AT25: =IFERROR(INDEX(Factors_ROT!$F$5:$F$200,MATCH("MAT|"&G25,Factors_ROT!$A$5:$A$200,0)),1) -> 1 | AU25: =IFERROR(INDEX(Factors_ROT!$F$5:$F$200,MATCH("SEAL_ARR|"&P25,Factors_ROT!$A$5:$A$200,0)),1)*IFERROR(INDEX(Factors_ROT!$F$5:$F$200,MATCH("SEAL_CAT|"&Q25,Factors_ROT!$A$5:$A$200,0)),1)*IFERROR(INDEX(Factors_ROT!$F$5:$F$200,MATCH("SEAL_PLAN|"&R25,Factors_ROT!$A$5:$A$200,0)),1) -> 1 | AV25: =IFERROR(INDEX(Factors_ROT!$F$5:$F$200,MATCH("DRV|"&S25,Factors_ROT!$A$5:$A$200,0)),1)*IFERROR(INDEX(Factors_ROT!$F$5:$F$200,MATCH("NACE|"&O25,Factors_ROT!$A$5:$A$200,0)),1) -> 1 | AW25: =IFERROR(INDEX(Factors_ROT!$F$5:$F$200,MATCH("SC_DRV|"&AL25,Factors_ROT!$A$5:$A$200,0)),1)*IFERROR(INDEX(Factors_ROT!$F$5:$F$200,MATCH("SC_BSP|"&AM25,Factors_ROT!$A$5:$A$200,0)),1)*IFERROR(INDEX(Factors_ROT!$F$5:$F$200,MATCH("SC_SEAL|"&AN25,Factors_ROT!$A$5:$A$200,0)),1)*IFERROR(INDEX(Factors_ROT!$F$5:$F$200,MATCH("SC_COMM|"&AO25,Factors_ROT!$A$5:$A$200,0)),1)*IFERROR(INDEX(Factors_ROT!$F$5:$F$200,MATCH("SC_2Y|"&AP25,Factors_ROT!$A$5:$A$200,0)),1)*IFERROR(INDEX(Factors_ROT!$F$5:$F$200,MATCH("SC_TPI|"&AQ25,Factors_ROT!$A$5:$A$200,0)),1)*IFERROR(INDEX(Factors_ROT!$F$5:$F$200,MATCH("SC_FAT|"&AR25,Factors_ROT!$A$5:$A$200,0)),1) -> 0.98 | AX25: =AT25*AU25*AV25*AW25 -> 0.98 | AY25: =IF(ISNUMBER(AB25),AB25/AX25,"") -> 15306.122 | AZ25: =IFERROR(IF(N(INDEX(Escalation_Index!$B$5:$B$25,MATCH(Y25,Escalation_Index!$A$5:$A$25,0)))>0,INDEX(Escalation_Index!$B$5:$B$25,MATCH(Y25,Escalation_Index!$A$5:$A$25,0)),""),"") -> 119.251 | BA25: =IF(ISNUMBER('Assumptions & FX Reference'!$I$12),'Assumptions & FX Reference'!$I$12,"") -> 123.416 | BB25: =IF(AND(M25="API 610",LEFT(V25,11)="Centrifugal",OR(LEFT(G25,2)="S-",LEFT(G25,2)="D-")),"Y","N") -> N | BC25: =IF(ISNUMBER(AG25),AG25/AX25,"") -> 15840.709 | BD25: =IF(AND(ISNUMBER(BC25),ISNUMBER(K25)),IF(K25>0,BC25/K25^'Assumptions & FX Reference'!$I$16,""),"") -> 13230.442 | BE25: File PEP-Rev 140205 Gachsaran 4.xlsx, sheet 'P.ME', cells A20:H20 (service in D, spec in E, unit price in H) | BF25: Type: Centrifugal (API 610) | Driver: موتور الکتریکی (E) | Power: 1.35 kW | مشخصات کاتالوگی: 20m3/hr, 2.4 bar, 1.35 kw | Original type text: Centrifugal (assumed) | GCH4 review 1405-07: Source IRR = EUR 15,000 × 1.085 × 420,000 (P.ME H20); previous bank stored the IRR figure as 1399 IRR, which overstated EUR ≈2.6× | BG25: Y | BH25: PMP | BI25: ="PMP-"&TEXT(A25,"0000") -> PMP-0021
A26: 22 | B26: DEAERATED WATER PUMPS | C26: Gachsaran 4 | D26: P-105 | E26: ROT-WAT | F26: Not stated | G26: Not stated | H26: 40 | J26: 2.7 | K26: =IF(ISNUMBER(J26),J26,IF(AND(ISNUMBER(H26),ISNUMBER(I26)),H26*I26/(367*'Assumptions & FX Reference'!$I$17),"")) -> 2.7 | L26: =IF(IF(OR(M26="Not stated",M26=""),""," + "&M26)&IF(OR(N26="None",N26=""),""," + "&N26)&IF(O26="Y"," + NACE MR0175","")="","Not stated",MID(IF(OR(M26="Not stated",M26=""),""," + "&M26)&IF(OR(N26="None",N26=""),""," + "&N26)&IF(O26="Y"," + NACE MR0175",""),4,300)) -> Not stated | M26: Not stated | N26: None | O26: Not stated | P26: Not stated | Q26: Not stated | R26: Not stated | S26: Electric Motor | T26: Deaerated Water | U26: 1 | V26: Centrifugal | W26: 2.4 | X26: Not stated | Y26: 1402 | Z26: EUR | AA26: 17000 | AB26: =IF(NOT(ISNUMBER(AA26)),"",IF(NOT(ISNUMBER(Y26)),"",IFERROR(IF(Z26="EUR",AA26,IF(Z26="IRR",AA26/INDEX('Assumptions & FX Reference'!$C$5:$C$25,MATCH(Y26,'Assumptions & FX Reference'!$A$5:$A$25,0)),IF(Z26="USD",AA26*INDEX('Assumptions & FX Reference'!$B$5:$B$25,MATCH(Y26,'Assumptions & FX Reference'!$A$5:$A$25,0))/INDEX('Assumptions & FX Reference'!$C$5:$C$25,MATCH(Y26,'Assumptions & FX Reference'!$A$5:$A$25,0)),""))),""))) -> 17000 | AC26: =IF(NOT(ISNUMBER(AA26)),"",IF(NOT(ISNUMBER(Y26)),"",IFERROR(IF(Z26="USD",AA26,IF(Z26="IRR",AA26/INDEX('Assumptions & FX Reference'!$B$5:$B$25,MATCH(Y26,'Assumptions & FX Reference'!$A$5:$A$25,0)),IF(Z26="EUR",AA26*INDEX('Assumptions & FX Reference'!$C$5:$C$25,MATCH(Y26,'Assumptions & FX Reference'!$A$5:$A$25,0))/INDEX('Assumptions & FX Reference'!$B$5:$B$25,MATCH(Y26,'Assumptions & FX Reference'!$A$5:$A$25,0)),""))),""))) -> 21432.143 | AD26: =IF(NOT(ISNUMBER(AA26)),"",IF(NOT(ISNUMBER(Y26)),"",IFERROR(IF(Z26="IRR",AA26,IF(Z26="USD",AA26*INDEX('Assumptions & FX Reference'!$B$5:$B$25,MATCH(Y26,'Assumptions & FX Reference'!$A$5:$A$25,0)),IF(Z26="EUR",AA26*INDEX('Assumptions & FX Reference'!$C$5:$C$25,MATCH(Y26,'Assumptions & FX Reference'!$A$5:$A$25,0)),""))),""))) -> 9001500000 | AE26: Consultant basic-design estimate – PEP Rev.1402/05, sheet P.ME «هزینه واحد بدون ضریب»; EUR figure (converted in the PEP at 420,000×1.085 IRR/EUR) | source label: AACE Class 2 | AF26: EXW | AG26: =IF(AND(Z26="EUR",N(AA26)>5000000),"",IF(AND(ISNUMBER(AB26),ISNUMBER(AZ26),ISNUMBER(BA26)),IF(AND(BB26="Y",ISNUMBER('Assumptions & FX Reference'!$I$15)),MAX(AB26*BA26/AZ26,'Assumptions & FX Reference'!$I$13*BA26/'Assumptions & FX Reference'!$I$15),AB26*BA26/AZ26),"")) -> 17593.748 | AH26: =IF(AND(ISNUMBER(AG26),ISNUMBER('Assumptions & FX Reference'!$I$8),ISNUMBER('Assumptions & FX Reference'!$I$11)),AG26*'Assumptions & FX Reference'!$I$8/'Assumptions & FX Reference'!$I$11,"") -> 18575.181 | AI26: =IF(AND(ISNUMBER(AG26),ISNUMBER('Assumptions & FX Reference'!$I$8)),AG26*'Assumptions & FX Reference'!$I$8,"") -> 1.223237e+10 | AJ26: (Gachsaran 4 Basic Design MTO) | AK26: Basic Design | AL26: Not stated | AM26: Not stated | AN26: Not stated | AO26: N | AP26: N | AQ26: N | AR26: Not stated | AS26: =IF(AND(Z26="EUR",N(AA26)>5000000),"Check currency (EUR>5M); ","")&IF(NOT(ISNUMBER(AA26)),"No price; ","")&IF(G26="Not stated","Material missing; ","")&IF(P26="Not stated","Seal missing; ","")&IF(K26="","Size driver missing; ","")&IF(NOT(ISNUMBER(AZ26)),"Base-year PPI missing; ","") -> Material missing; Seal missing; | AT26: =IFERROR(INDEX(Factors_ROT!$F$5:$F$200,MATCH("MAT|"&G26,Factors_ROT!$A$5:$A$200,0)),1) -> 1 | AU26: =IFERROR(INDEX(Factors_ROT!$F$5:$F$200,MATCH("SEAL_ARR|"&P26,Factors_ROT!$A$5:$A$200,0)),1)*IFERROR(INDEX(Factors_ROT!$F$5:$F$200,MATCH("SEAL_CAT|"&Q26,Factors_ROT!$A$5:$A$200,0)),1)*IFERROR(INDEX(Factors_ROT!$F$5:$F$200,MATCH("SEAL_PLAN|"&R26,Factors_ROT!$A$5:$A$200,0)),1) -> 1 | AV26: =IFERROR(INDEX(Factors_ROT!$F$5:$F$200,MATCH("DRV|"&S26,Factors_ROT!$A$5:$A$200,0)),1)*IFERROR(INDEX(Factors_ROT!$F$5:$F$200,MATCH("NACE|"&O26,Factors_ROT!$A$5:$A$200,0)),1) -> 1 | AW26: =IFERROR(INDEX(Factors_ROT!$F$5:$F$200,MATCH("SC_DRV|"&AL26,Factors_ROT!$A$5:$A$200,0)),1)*IFERROR(INDEX(Factors_ROT!$F$5:$F$200,MATCH("SC_BSP|"&AM26,Factors_ROT!$A$5:$A$200,0)),1)*IFERROR(INDEX(Factors_ROT!$F$5:$F$200,MATCH("SC_SEAL|"&AN26,Factors_ROT!$A$5:$A$200,0)),1)*IFERROR(INDEX(Factors_ROT!$F$5:$F$200,MATCH("SC_COMM|"&AO26,Factors_ROT!$A$5:$A$200,0)),1)*IFERROR(INDEX(Factors_ROT!$F$5:$F$200,MATCH("SC_2Y|"&AP26,Factors_ROT!$A$5:$A$200,0)),1)*IFERROR(INDEX(Factors_ROT!$F$5:$F$200,MATCH("SC_TPI|"&AQ26,Factors_ROT!$A$5:$A$200,0)),1)*IFERROR(INDEX(Factors_ROT!$F$5:$F$200,MATCH("SC_FAT|"&AR26,Factors_ROT!$A$5:$A$200,0)),1) -> 0.98 | AX26: =AT26*AU26*AV26*AW26 -> 0.98 | AY26: =IF(ISNUMBER(AB26),AB26/AX26,"") -> 17346.939 | AZ26: =IFERROR(IF(N(INDEX(Escalation_Index!$B$5:$B$25,MATCH(Y26,Escalation_Index!$A$5:$A$25,0)))>0,INDEX(Escalation_Index!$B$5:$B$25,MATCH(Y26,Escalation_Index!$A$5:$A$25,0)),""),"") -> 119.251 | BA26: =IF(ISNUMBER('Assumptions & FX Reference'!$I$12),'Assumptions & FX Reference'!$I$12,"") -> 123.416 | BB26: =IF(AND(M26="API 610",LEFT(V26,11)="Centrifugal",OR(LEFT(G26,2)="S-",LEFT(G26,2)="D-")),"Y","N") -> N | BC26: =IF(ISNUMBER(AG26),AG26/AX26,"") -> 17952.804 | BD26: =IF(AND(ISNUMBER(BC26),ISNUMBER(K26)),IF(K26>0,BC26/K26^'Assumptions & FX Reference'!$I$16,""),"") -> 9892.6814 | BE26: File PEP-Rev 140205 Gachsaran 4.xlsx, sheet 'P.ME', cells A21:H21 (service in D, spec in E, unit price in H) | BF26: Type: Centrifugal (API 610) | Driver: موتور الکتریکی (E) | Power: 2.7 kW | مشخصات کاتالوگی: 40m3/hr, 2.4 bar, 2.7 kw | Original type text: Centrifugal (assumed) | GCH4 review 1405-07: Source IRR = EUR 17,000 × 1.085 × 420,000 (P.ME H21); previous bank stored the IRR figure as 1399 IRR, which overstated EUR ≈2.6× | BG26: Y | BH26: PMP | BI26: ="PMP-"&TEXT(A26,"0000") -> PMP-0022
A27: 23 | B27: POTABLE WATER FILLING PUMP | C27: Gachsaran 4 | D27: P-104 | E27: ROT-WAT | F27: Not stated | G27: Not stated | H27: 20 | J27: 1.4 | K27: =IF(ISNUMBER(J27),J27,IF(AND(ISNUMBER(H27),ISNUMBER(I27)),H27*I27/(367*'Assumptions & FX Reference'!$I$17),"")) -> 1.4 | L27: =IF(IF(OR(M27="Not stated",M27=""),""," + "&M27)&IF(OR(N27="None",N27=""),""," + "&N27)&IF(O27="Y"," + NACE MR0175","")="","Not stated",MID(IF(OR(M27="Not stated",M27=""),""," + "&M27)&IF(OR(N27="None",N27=""),""," + "&N27)&IF(O27="Y"," + NACE MR0175",""),4,300)) -> Not stated | M27: Not stated | N27: None | O27: Not stated | P27: Not stated | Q27: Not stated | R27: Not stated | S27: Electric Motor | T27: Fresh / Potable Water | U27: 1 | V27: Centrifugal | W27: 2.5 | X27: Not stated | Y27: 1402 | Z27: EUR | AA27: 11000 | AB27: =IF(NOT(ISNUMBER(AA27)),"",IF(NOT(ISNUMBER(Y27)),"",IFERROR(IF(Z27="EUR",AA27,IF(Z27="IRR",AA27/INDEX('Assumptions & FX Reference'!$C$5:$C$25,MATCH(Y27,'Assumptions & FX Reference'!$A$5:$A$25,0)),IF(Z27="USD",AA27*INDEX('Assumptions & FX Reference'!$B$5:$B$25,MATCH(Y27,'Assumptions & FX Reference'!$A$5:$A$25,0))/INDEX('Assumptions & FX Reference'!$C$5:$C$25,MATCH(Y27,'Assumptions & FX Reference'!$A$5:$A$25,0)),""))),""))) -> 11000 | AC27: =IF(NOT(ISNUMBER(AA27)),"",IF(NOT(ISNUMBER(Y27)),"",IFERROR(IF(Z27="USD",AA27,IF(Z27="IRR",AA27/INDEX('Assumptions & FX Reference'!$B$5:$B$25,MATCH(Y27,'Assumptions & FX Reference'!$A$5:$A$25,0)),IF(Z27="EUR",AA27*INDEX('Assumptions & FX Reference'!$C$5:$C$25,MATCH(Y27,'Assumptions & FX Reference'!$A$5:$A$25,0))/INDEX('Assumptions & FX Reference'!$B$5:$B$25,MATCH(Y27,'Assumptions & FX Reference'!$A$5:$A$25,0)),""))),""))) -> 13867.857 | AD27: =IF(NOT(ISNUMBER(AA27)),"",IF(NOT(ISNUMBER(Y27)),"",IFERROR(IF(Z27="IRR",AA27,IF(Z27="USD",AA27*INDEX('Assumptions & FX Reference'!$B$5:$B$25,MATCH(Y27,'Assumptions & FX Reference'!$A$5:$A$25,0)),IF(Z27="EUR",AA27*INDEX('Assumptions & FX Reference'!$C$5:$C$25,MATCH(Y27,'Assumptions & FX Reference'!$A$5:$A$25,0)),""))),""))) -> 5824500000 | AE27: Consultant basic-design estimate – PEP Rev.1402/05, sheet P.ME «هزینه واحد بدون ضریب»; EUR figure (converted in the PEP at 420,000×1.085 IRR/EUR) | source label: AACE Class 2 | AF27: EXW | AG27: =IF(AND(Z27="EUR",N(AA27)>5000000),"",IF(AND(ISNUMBER(AB27),ISNUMBER(AZ27),ISNUMBER(BA27)),IF(AND(BB27="Y",ISNUMBER('Assumptions & FX Reference'!$I$15)),MAX(AB27*BA27/AZ27,'Assumptions & FX Reference'!$I$13*BA27/'Assumptions & FX Reference'!$I$15),AB27*BA27/AZ27),"")) -> 11384.19 | AH27: =IF(AND(ISNUMBER(AG27),ISNUMBER('Assumptions & FX Reference'!$I$8),ISNUMBER('Assumptions & FX Reference'!$I$11)),AG27*'Assumptions & FX Reference'!$I$8/'Assumptions & FX Reference'!$I$11,"") -> 12019.235 | AI27: =IF(AND(ISNUMBER(AG27),ISNUMBER('Assumptions & FX Reference'!$I$8)),AG27*'Assumptions & FX Reference'!$I$8,"") -> 7.9150628e+09 | AJ27: (Gachsaran 4 Basic Design MTO) | AK27: Basic Design | AL27: Not stated | AM27: Not stated | AN27: Not stated | AO27: N | AP27: N | AQ27: N | AR27: Not stated | AS27: =IF(AND(Z27="EUR",N(AA27)>5000000),"Check currency (EUR>5M); ","")&IF(NOT(ISNUMBER(AA27)),"No price; ","")&IF(G27="Not stated","Material missing; ","")&IF(P27="Not stated","Seal missing; ","")&IF(K27="","Size driver missing; ","")&IF(NOT(ISNUMBER(AZ27)),"Base-year PPI missing; ","") -> Material missing; Seal missing; | AT27: =IFERROR(INDEX(Factors_ROT!$F$5:$F$200,MATCH("MAT|"&G27,Factors_ROT!$A$5:$A$200,0)),1) -> 1 | AU27: =IFERROR(INDEX(Factors_ROT!$F$5:$F$200,MATCH("SEAL_ARR|"&P27,Factors_ROT!$A$5:$A$200,0)),1)*IFERROR(INDEX(Factors_ROT!$F$5:$F$200,MATCH("SEAL_CAT|"&Q27,Factors_ROT!$A$5:$A$200,0)),1)*IFERROR(INDEX(Factors_ROT!$F$5:$F$200,MATCH("SEAL_PLAN|"&R27,Factors_ROT!$A$5:$A$200,0)),1) -> 1 | AV27: =IFERROR(INDEX(Factors_ROT!$F$5:$F$200,MATCH("DRV|"&S27,Factors_ROT!$A$5:$A$200,0)),1)*IFERROR(INDEX(Factors_ROT!$F$5:$F$200,MATCH("NACE|"&O27,Factors_ROT!$A$5:$A$200,0)),1) -> 1 | AW27: =IFERROR(INDEX(Factors_ROT!$F$5:$F$200,MATCH("SC_DRV|"&AL27,Factors_ROT!$A$5:$A$200,0)),1)*IFERROR(INDEX(Factors_ROT!$F$5:$F$200,MATCH("SC_BSP|"&AM27,Factors_ROT!$A$5:$A$200,0)),1)*IFERROR(INDEX(Factors_ROT!$F$5:$F$200,MATCH("SC_SEAL|"&AN27,Factors_ROT!$A$5:$A$200,0)),1)*IFERROR(INDEX(Factors_ROT!$F$5:$F$200,MATCH("SC_COMM|"&AO27,Factors_ROT!$A$5:$A$200,0)),1)*IFERROR(INDEX(Factors_ROT!$F$5:$F$200,MATCH("SC_2Y|"&AP27,Factors_ROT!$A$5:$A$200,0)),1)*IFERROR(INDEX(Factors_ROT!$F$5:$F$200,MATCH("SC_TPI|"&AQ27,Factors_ROT!$A$5:$A$200,0)),1)*IFERROR(INDEX(Factors_ROT!$F$5:$F$200,MATCH("SC_FAT|"&AR27,Factors_ROT!$A$5:$A$200,0)),1) -> 0.98 | AX27: =AT27*AU27*AV27*AW27 -> 0.98 | AY27: =IF(ISNUMBER(AB27),AB27/AX27,"") -> 11224.49 | AZ27: =IFERROR(IF(N(INDEX(Escalation_Index!$B$5:$B$25,MATCH(Y27,Escalation_Index!$A$5:$A$25,0)))>0,INDEX(Escalation_Index!$B$5:$B$25,MATCH(Y27,Escalation_Index!$A$5:$A$25,0)),""),"") -> 119.251 | BA27: =IF(ISNUMBER('Assumptions & FX Reference'!$I$12),'Assumptions & FX Reference'!$I$12,"") -> 123.416 | BB27: =IF(AND(M27="API 610",LEFT(V27,11)="Centrifugal",OR(LEFT(G27,2)="S-",LEFT(G27,2)="D-")),"Y","N") -> N | BC27: =IF(ISNUMBER(AG27),AG27/AX27,"") -> 11616.52 | BD27: =IF(AND(ISNUMBER(BC27),ISNUMBER(K27)),IF(K27>0,BC27/K27^'Assumptions & FX Reference'!$I$16,""),"") -> 9492.907 | BE27: File PEP-Rev 140205 Gachsaran 4.xlsx, sheet 'P.ME', cells A23:H23 (service in D, spec in E, unit price in H) | BF27: Type: Centrifugal (API 610) | Driver: موتور الکتریکی (E) | Power: 1.4 kW | مشخصات کاتالوگی: 20m3/hr, 2.5 bar, 1.4 kw | Original type text: Centrifugal (assumed) | GCH4 review 1405-07: Source IRR = EUR 11,000 × 1.085 × 420,000 (P.ME H23); previous bank stored the IRR figure as 1399 IRR, which overstated EUR ≈2.6× | BG27: Y | BH27: PMP | BI27: ="PMP-"&TEXT(A27,"0000") -> PMP-0023
A28: 24 | B28: WATER INJECTION MAIN PUMPS | C28: Gachsaran 4 | D28: P-201-A/B/C | E28: ROT-INJ | F28: Not stated | G28: Not stated | H28: 73 | J28: 73.6 | K28: =IF(ISNUMBER(J28),J28,IF(AND(ISNUMBER(H28),ISNUMBER(I28)),H28*I28/(367*'Assumptions & FX Reference'!$I$17),"")) -> 73.6 | L28: =IF(IF(OR(M28="Not stated",M28=""),""," + "&M28)&IF(OR(N28="None",N28=""),""," + "&N28)&IF(O28="Y"," + NACE MR0175","")="","Not stated",MID(IF(OR(M28="Not stated",M28=""),""," + "&M28)&IF(OR(N28="None",N28=""),""," + "&N28)&IF(O28="Y"," + NACE MR0175",""),4,300)) -> Not stated | M28: Not stated | N28: None | O28: Not stated | P28: Not stated | Q28: Not stated | R28: Not stated | S28: Electric Motor | T28: Produced / Disposal Water | U28: 3 | V28: Centrifugal | W28: 36.3 | X28: Not stated | Y28: 1402 | Z28: EUR | AA28: 430000 | AB28: =IF(NOT(ISNUMBER(AA28)),"",IF(NOT(ISNUMBER(Y28)),"",IFERROR(IF(Z28="EUR",AA28,IF(Z28="IRR",AA28/INDEX('Assumptions & FX Reference'!$C$5:$C$25,MATCH(Y28,'Assumptions & FX Reference'!$A$5:$A$25,0)),IF(Z28="USD",AA28*INDEX('Assumptions & FX Reference'!$B$5:$B$25,MATCH(Y28,'Assumptions & FX Reference'!$A$5:$A$25,0))/INDEX('Assumptions & FX Reference'!$C$5:$C$25,MATCH(Y28,'Assumptions & FX Reference'!$A$5:$A$25,0)),""))),""))) -> 430000 | AC28: =IF(NOT(ISNUMBER(AA28)),"",IF(NOT(ISNUMBER(Y28)),"",IFERROR(IF(Z28="USD",AA28,IF(Z28="IRR",AA28/INDEX('Assumptions & FX Reference'!$B$5:$B$25,MATCH(Y28,'Assumptions & FX Reference'!$A$5:$A$25,0)),IF(Z28="EUR",AA28*INDEX('Assumptions & FX Reference'!$C$5:$C$25,MATCH(Y28,'Assumptions & FX Reference'!$A$5:$A$25,0))/INDEX('Assumptions & FX Reference'!$B$5:$B$25,MATCH(Y28,'Assumptions & FX Reference'!$A$5:$A$25,0)),""))),""))) -> 542107.14 | AD28: =IF(NOT(ISNUMBER(AA28)),"",IF(NOT(ISNUMBER(Y28)),"",IFERROR(IF(Z28="IRR",AA28,IF(Z28="USD",AA28*INDEX('Assumptions & FX Reference'!$B$5:$B$25,MATCH(Y28,'Assumptions & FX Reference'!$A$5:$A$25,0)),IF(Z28="EUR",AA28*INDEX('Assumptions & FX Reference'!$C$5:$C$25,MATCH(Y28,'Assumptions & FX Reference'!$A$5:$A$25,0)),""))),""))) -> 227685000000 | AE28: Consultant basic-design estimate – PEP Rev.1402/05, sheet P.ME «هزینه واحد بدون ضریب»; EUR figure (converted in the PEP at 420,000×1.085 IRR/EUR) | source label: AACE Class 2 | AF28: EXW | AG28: =IF(AND(Z28="EUR",N(AA28)>5000000),"",IF(AND(ISNUMBER(AB28),ISNUMBER(AZ28),ISNUMBER(BA28)),IF(AND(BB28="Y",ISNUMBER('Assumptions & FX Reference'!$I$15)),MAX(AB28*BA28/AZ28,'Assumptions & FX Reference'!$I$13*BA28/'Assumptions & FX Reference'!$I$15),AB28*BA28/AZ28),"")) -> 445018.32 | AH28: =IF(AND(ISNUMBER(AG28),ISNUMBER('Assumptions & FX Reference'!$I$8),ISNUMBER('Assumptions & FX Reference'!$I$11)),AG28*'Assumptions & FX Reference'!$I$8/'Assumptions & FX Reference'!$I$11,"") -> 469842.82 | AI28: =IF(AND(ISNUMBER(AG28),ISNUMBER('Assumptions & FX Reference'!$I$8)),AG28*'Assumptions & FX Reference'!$I$8,"") -> 3.09407e+11 | AJ28: (Gachsaran 4 Basic Design MTO) | AK28: Basic Design | AL28: Not stated | AM28: Not stated | AN28: Not stated | AO28: N | AP28: N | AQ28: N | AR28: Not stated | AS28: =IF(AND(Z28="EUR",N(AA28)>5000000),"Check currency (EUR>5M); ","")&IF(NOT(ISNUMBER(AA28)),"No price; ","")&IF(G28="Not stated","Material missing; ","")&IF(P28="Not stated","Seal missing; ","")&IF(K28="","Size driver missing; ","")&IF(NOT(ISNUMBER(AZ28)),"Base-year PPI missing; ","") -> Material missing; Seal missing; | AT28: =IFERROR(INDEX(Factors_ROT!$F$5:$F$200,MATCH("MAT|"&G28,Factors_ROT!$A$5:$A$200,0)),1) -> 1 | AU28: =IFERROR(INDEX(Factors_ROT!$F$5:$F$200,MATCH("SEAL_ARR|"&P28,Factors_ROT!$A$5:$A$200,0)),1)*IFERROR(INDEX(Factors_ROT!$F$5:$F$200,MATCH("SEAL_CAT|"&Q28,Factors_ROT!$A$5:$A$200,0)),1)*IFERROR(INDEX(Factors_ROT!$F$5:$F$200,MATCH("SEAL_PLAN|"&R28,Factors_ROT!$A$5:$A$200,0)),1) -> 1 | AV28: =IFERROR(INDEX(Factors_ROT!$F$5:$F$200,MATCH("DRV|"&S28,Factors_ROT!$A$5:$A$200,0)),1)*IFERROR(INDEX(Factors_ROT!$F$5:$F$200,MATCH("NACE|"&O28,Factors_ROT!$A$5:$A$200,0)),1) -> 1 | AW28: =IFERROR(INDEX(Factors_ROT!$F$5:$F$200,MATCH("SC_DRV|"&AL28,Factors_ROT!$A$5:$A$200,0)),1)*IFERROR(INDEX(Factors_ROT!$F$5:$F$200,MATCH("SC_BSP|"&AM28,Factors_ROT!$A$5:$A$200,0)),1)*IFERROR(INDEX(Factors_ROT!$F$5:$F$200,MATCH("SC_SEAL|"&AN28,Factors_ROT!$A$5:$A$200,0)),1)*IFERROR(INDEX(Factors_ROT!$F$5:$F$200,MATCH("SC_COMM|"&AO28,Factors_ROT!$A$5:$A$200,0)),1)*IFERROR(INDEX(Factors_ROT!$F$5:$F$200,MATCH("SC_2Y|"&AP28,Factors_ROT!$A$5:$A$200,0)),1)*IFERROR(INDEX(Factors_ROT!$F$5:$F$200,MATCH("SC_TPI|"&AQ28,Factors_ROT!$A$5:$A$200,0)),1)*IFERROR(INDEX(Factors_ROT!$F$5:$F$200,MATCH("SC_FAT|"&AR28,Factors_ROT!$A$5:$A$200,0)),1) -> 0.98 | AX28: =AT28*AU28*AV28*AW28 -> 0.98 | AY28: =IF(ISNUMBER(AB28),AB28/AX28,"") -> 438775.51 | AZ28: =IFERROR(IF(N(INDEX(Escalation_Index!$B$5:$B$25,MATCH(Y28,Escalation_Index!$A$5:$A$25,0)))>0,INDEX(Escalation_Index!$B$5:$B$25,MATCH(Y28,Escalation_Index!$A$5:$A$25,0)),""),"") -> 119.251 | BA28: =IF(ISNUMBER('Assumptions & FX Reference'!$I$12),'Assumptions & FX Reference'!$I$12,"") -> 123.416 | BB28: =IF(AND(M28="API 610",LEFT(V28,11)="Centrifugal",OR(LEFT(G28,2)="S-",LEFT(G28,2)="D-")),"Y","N") -> N | BC28: =IF(ISNUMBER(AG28),AG28/AX28,"") -> 454100.33 | BD28: =IF(AND(ISNUMBER(BC28),ISNUMBER(K28)),IF(K28>0,BC28/K28^'Assumptions & FX Reference'!$I$16,""),"") -> 34436.986 | BE28: File PEP-Rev 140205 Gachsaran 4.xlsx, sheet 'P.ME', cells A24:H24 (service in D, spec in E, unit price in H) | BF28: Type: Centrifugal (API 610) | Driver: موتور الکتریکی (E) | Power: 73.6 kW | NACE MR0175: YES | مشخصات کاتالوگی: 73m3/hr (each),36.3 bar, 73.6 kw | Original type text: Centrifugal (assumed) | GCH4 review 1405-07: Source IRR = EUR 430,000 × 1.085 × 420,000 (P.ME H24); previous bank stored the IRR figure as 1399 IRR, which overstated EUR ≈2.6× | BG28: Y | BH28: PMP | BI28: ="PMP-"&TEXT(A28,"0000") -> PMP-0024
A29: 25 | B29: WATER INJECTION BOOSTER PUMPS | C29: Gachsaran 4 | D29: P-206-A/B/C | E29: ROT-INJ | F29: Not stated | G29: Not stated | H29: 36.5 | J29: 36.5 | K29: =IF(ISNUMBER(J29),J29,IF(AND(ISNUMBER(H29),ISNUMBER(I29)),H29*I29/(367*'Assumptions & FX Reference'!$I$17),"")) -> 36.5 | L29: =IF(IF(OR(M29="Not stated",M29=""),""," + "&M29)&IF(OR(N29="None",N29=""),""," + "&N29)&IF(O29="Y"," + NACE MR0175","")="","Not stated",MID(IF(OR(M29="Not stated",M29=""),""," + "&M29)&IF(OR(N29="None",N29=""),""," + "&N29)&IF(O29="Y"," + NACE MR0175",""),4,300)) -> Not stated | M29: Not stated | N29: None | O29: Not stated | P29: Not stated | Q29: Not stated | R29: Not stated | S29: Electric Motor | T29: Produced / Disposal Water | U29: 3 | V29: Centrifugal | W29: 36.3 | X29: Not stated | Y29: 1402 | Z29: EUR | AA29: 285000 | AB29: =IF(NOT(ISNUMBER(AA29)),"",IF(NOT(ISNUMBER(Y29)),"",IFERROR(IF(Z29="EUR",AA29,IF(Z29="IRR",AA29/INDEX('Assumptions & FX Reference'!$C$5:$C$25,MATCH(Y29,'Assumptions & FX Reference'!$A$5:$A$25,0)),IF(Z29="USD",AA29*INDEX('Assumptions & FX Reference'!$B$5:$B$25,MATCH(Y29,'Assumptions & FX Reference'!$A$5:$A$25,0))/INDEX('Assumptions & FX Reference'!$C$5:$C$25,MATCH(Y29,'Assumptions & FX Reference'!$A$5:$A$25,0)),""))),""))) -> 285000 | AC29: =IF(NOT(ISNUMBER(AA29)),"",IF(NOT(ISNUMBER(Y29)),"",IFERROR(IF(Z29="USD",AA29,IF(Z29="IRR",AA29/INDEX('Assumptions & FX Reference'!$B$5:$B$25,MATCH(Y29,'Assumptions & FX Reference'!$A$5:$A$25,0)),IF(Z29="EUR",AA29*INDEX('Assumptions & FX Reference'!$C$5:$C$25,MATCH(Y29,'Assumptions & FX Reference'!$A$5:$A$25,0))/INDEX('Assumptions & FX Reference'!$B$5:$B$25,MATCH(Y29,'Assumptions & FX Reference'!$A$5:$A$25,0)),""))),""))) -> 359303.57 | AD29: =IF(NOT(ISNUMBER(AA29)),"",IF(NOT(ISNUMBER(Y29)),"",IFERROR(IF(Z29="IRR",AA29,IF(Z29="USD",AA29*INDEX('Assumptions & FX Reference'!$B$5:$B$25,MATCH(Y29,'Assumptions & FX Reference'!$A$5:$A$25,0)),IF(Z29="EUR",AA29*INDEX('Assumptions & FX Reference'!$C$5:$C$25,MATCH(Y29,'Assumptions & FX Reference'!$A$5:$A$25,0)),""))),""))) -> 150907500000 | AE29: Consultant basic-design estimate – PEP Rev.1402/05, sheet P.ME «هزینه واحد بدون ضریب»; EUR figure (converted in the PEP at 420,000×1.085 IRR/EUR) | source label: AACE Class 2 | AF29: EXW | AG29: =IF(AND(Z29="EUR",N(AA29)>5000000),"",IF(AND(ISNUMBER(AB29),ISNUMBER(AZ29),ISNUMBER(BA29)),IF(AND(BB29="Y",ISNUMBER('Assumptions & FX Reference'!$I$15)),MAX(AB29*BA29/AZ29,'Assumptions & FX Reference'!$I$13*BA29/'Assumptions & FX Reference'!$I$15),AB29*BA29/AZ29),"")) -> 294954 | AH29: =IF(AND(ISNUMBER(AG29),ISNUMBER('Assumptions & FX Reference'!$I$8),ISNUMBER('Assumptions & FX Reference'!$I$11)),AG29*'Assumptions & FX Reference'!$I$8/'Assumptions & FX Reference'!$I$11,"") -> 311407.45 | AI29: =IF(AND(ISNUMBER(AG29),ISNUMBER('Assumptions & FX Reference'!$I$8)),AG29*'Assumptions & FX Reference'!$I$8,"") -> 2.0507208e+11 | AJ29: (Gachsaran 4 Basic Design MTO) | AK29: Basic Design | AL29: Not stated | AM29: Not stated | AN29: Not stated | AO29: N | AP29: N | AQ29: N | AR29: Not stated | AS29: =IF(AND(Z29="EUR",N(AA29)>5000000),"Check currency (EUR>5M); ","")&IF(NOT(ISNUMBER(AA29)),"No price; ","")&IF(G29="Not stated","Material missing; ","")&IF(P29="Not stated","Seal missing; ","")&IF(K29="","Size driver missing; ","")&IF(NOT(ISNUMBER(AZ29)),"Base-year PPI missing; ","") -> Material missing; Seal missing; | AT29: =IFERROR(INDEX(Factors_ROT!$F$5:$F$200,MATCH("MAT|"&G29,Factors_ROT!$A$5:$A$200,0)),1) -> 1 | AU29: =IFERROR(INDEX(Factors_ROT!$F$5:$F$200,MATCH("SEAL_ARR|"&P29,Factors_ROT!$A$5:$A$200,0)),1)*IFERROR(INDEX(Factors_ROT!$F$5:$F$200,MATCH("SEAL_CAT|"&Q29,Factors_ROT!$A$5:$A$200,0)),1)*IFERROR(INDEX(Factors_ROT!$F$5:$F$200,MATCH("SEAL_PLAN|"&R29,Factors_ROT!$A$5:$A$200,0)),1) -> 1 | AV29: =IFERROR(INDEX(Factors_ROT!$F$5:$F$200,MATCH("DRV|"&S29,Factors_ROT!$A$5:$A$200,0)),1)*IFERROR(INDEX(Factors_ROT!$F$5:$F$200,MATCH("NACE|"&O29,Factors_ROT!$A$5:$A$200,0)),1) -> 1 | AW29: =IFERROR(INDEX(Factors_ROT!$F$5:$F$200,MATCH("SC_DRV|"&AL29,Factors_ROT!$A$5:$A$200,0)),1)*IFERROR(INDEX(Factors_ROT!$F$5:$F$200,MATCH("SC_BSP|"&AM29,Factors_ROT!$A$5:$A$200,0)),1)*IFERROR(INDEX(Factors_ROT!$F$5:$F$200,MATCH("SC_SEAL|"&AN29,Factors_ROT!$A$5:$A$200,0)),1)*IFERROR(INDEX(Factors_ROT!$F$5:$F$200,MATCH("SC_COMM|"&AO29,Factors_ROT!$A$5:$A$200,0)),1)*IFERROR(INDEX(Factors_ROT!$F$5:$F$200,MATCH("SC_2Y|"&AP29,Factors_ROT!$A$5:$A$200,0)),1)*IFERROR(INDEX(Factors_ROT!$F$5:$F$200,MATCH("SC_TPI|"&AQ29,Factors_ROT!$A$5:$A$200,0)),1)*IFERROR(INDEX(Factors_ROT!$F$5:$F$200,MATCH("SC_FAT|"&AR29,Factors_ROT!$A$5:$A$200,0)),1) -> 0.98 | AX29: =AT29*AU29*AV29*AW29 -> 0.98 | AY29: =IF(ISNUMBER(AB29),AB29/AX29,"") -> 290816.33 | AZ29: =IFERROR(IF(N(INDEX(Escalation_Index!$B$5:$B$25,MATCH(Y29,Escalation_Index!$A$5:$A$25,0)))>0,INDEX(Escalation_Index!$B$5:$B$25,MATCH(Y29,Escalation_Index!$A$5:$A$25,0)),""),"") -> 119.251 | BA29: =IF(ISNUMBER('Assumptions & FX Reference'!$I$12),'Assumptions & FX Reference'!$I$12,"") -> 123.416 | BB29: =IF(AND(M29="API 610",LEFT(V29,11)="Centrifugal",OR(LEFT(G29,2)="S-",LEFT(G29,2)="D-")),"Y","N") -> N | BC29: =IF(ISNUMBER(AG29),AG29/AX29,"") -> 300973.47 | BD29: =IF(AND(ISNUMBER(BC29),ISNUMBER(K29)),IF(K29>0,BC29/K29^'Assumptions & FX Reference'!$I$16,""),"") -> 34765.822 | BE29: File PEP-Rev 140205 Gachsaran 4.xlsx, sheet 'P.ME', cells A25:H25 (service in D, spec in E, unit price in H) | BF29: Type: Centrifugal (API 610) | Driver: موتور الکتریکی (E) | Power: 36.5 kW | NACE MR0175: YES | مشخصات کاتالوگی: 36.5m3/hr (each),36.3 bar, 36.5 kw | Original type text: Centrifugal (assumed) | GCH4 review 1405-07: Source IRR = EUR 285,000 × 1.085 × 420,000 (P.ME H25); previous bank stored the IRR figure as 1399 IRR, which overstated EUR ≈2.6× | BG29: Y | BH29: PMP | BI29: ="PMP-"&TEXT(A29,"0000") -> PMP-0025
A30: 26 | B30: CHEMICAL INJECTION PORTABLE PUMPS | C30: Gachsaran 4 | D30: P-501-A/B/C | E30: ROT-AUX | F30: Not stated | G30: Not stated | J30: 0.45 | K30: =IF(ISNUMBER(J30),J30,IF(AND(ISNUMBER(H30),ISNUMBER(I30)),H30*I30/(367*'Assumptions & FX Reference'!$I$17),"")) -> 0.45 | L30: =IF(IF(OR(M30="Not stated",M30=""),""," + "&M30)&IF(OR(N30="None",N30=""),""," + "&N30)&IF(O30="Y"," + NACE MR0175","")="","Not stated",MID(IF(OR(M30="Not stated",M30=""),""," + "&M30)&IF(OR(N30="None",N30=""),""," + "&N30)&IF(O30="Y"," + NACE MR0175",""),4,300)) -> Not stated | M30: Not stated | N30: None | O30: Not stated | P30: Not stated | Q30: Not stated | R30: Not stated | S30: Electric Motor | T30: Chemical | U30: 3 | V30: Centrifugal | W30: 2 | X30: Not stated | Y30: 1402 | Z30: EUR | AA30: 9000 | AB30: =IF(NOT(ISNUMBER(AA30)),"",IF(NOT(ISNUMBER(Y30)),"",IFERROR(IF(Z30="EUR",AA30,IF(Z30="IRR",AA30/INDEX('Assumptions & FX Reference'!$C$5:$C$25,MATCH(Y30,'Assumptions & FX Reference'!$A$5:$A$25,0)),IF(Z30="USD",AA30*INDEX('Assumptions & FX Reference'!$B$5:$B$25,MATCH(Y30,'Assumptions & FX Reference'!$A$5:$A$25,0))/INDEX('Assumptions & FX Reference'!$C$5:$C$25,MATCH(Y30,'Assumptions & FX Reference'!$A$5:$A$25,0)),""))),""))) -> 9000 | AC30: =IF(NOT(ISNUMBER(AA30)),"",IF(NOT(ISNUMBER(Y30)),"",IFERROR(IF(Z30="USD",AA30,IF(Z30="IRR",AA30/INDEX('Assumptions & FX Reference'!$B$5:$B$25,MATCH(Y30,'Assumptions & FX Reference'!$A$5:$A$25,0)),IF(Z30="EUR",AA30*INDEX('Assumptions & FX Reference'!$C$5:$C$25,MATCH(Y30,'Assumptions & FX Reference'!$A$5:$A$25,0))/INDEX('Assumptions & FX Reference'!$B$5:$B$25,MATCH(Y30,'Assumptions & FX Reference'!$A$5:$A$25,0)),""))),""))) -> 11346.429 | AD30: =IF(NOT(ISNUMBER(AA30)),"",IF(NOT(ISNUMBER(Y30)),"",IFERROR(IF(Z30="IRR",AA30,IF(Z30="USD",AA30*INDEX('Assumptions & FX Reference'!$B$5:$B$25,MATCH(Y30,'Assumptions & FX Reference'!$A$5:$A$25,0)),IF(Z30="EUR",AA30*INDEX('Assumptions & FX Reference'!$C$5:$C$25,MATCH(Y30,'Assumptions & FX Reference'!$A$5:$A$25,0)),""))),""))) -> 4765500000 | AE30: Consultant basic-design estimate – PEP Rev.1402/05, sheet P.ME «هزینه واحد بدون ضریب»; EUR figure (converted in the PEP at 420,000×1.085 IRR/EUR) | source label: AACE Class 2 | AF30: EXW | AG30: =IF(AND(Z30="EUR",N(AA30)>5000000),"",IF(AND(ISNUMBER(AB30),ISNUMBER(AZ30),ISNUMBER(BA30)),IF(AND(BB30="Y",ISNUMBER('Assumptions & FX Reference'!$I$15)),MAX(AB30*BA30/AZ30,'Assumptions & FX Reference'!$I$13*BA30/'Assumptions & FX Reference'!$I$15),AB30*BA30/AZ30),"")) -> 9314.337 | AH30: =IF(AND(ISNUMBER(AG30),ISNUMBER('Assumptions & FX Reference'!$I$8),ISNUMBER('Assumptions & FX Reference'!$I$11)),AG30*'Assumptions & FX Reference'!$I$8/'Assumptions & FX Reference'!$I$11,"") -> 9833.9194 | AI30: =IF(AND(ISNUMBER(AG30),ISNUMBER('Assumptions & FX Reference'!$I$8)),AG30*'Assumptions & FX Reference'!$I$8,"") -> 6.4759604e+09 | AJ30: (Gachsaran 4 Basic Design MTO) | AK30: Basic Design | AL30: Not stated | AM30: Not stated | AN30: Not stated | AO30: N | AP30: N | AQ30: N | AR30: Not stated | AS30: =IF(AND(Z30="EUR",N(AA30)>5000000),"Check currency (EUR>5M); ","")&IF(NOT(ISNUMBER(AA30)),"No price; ","")&IF(G30="Not stated","Material missing; ","")&IF(P30="Not stated","Seal missing; ","")&IF(K30="","Size driver missing; ","")&IF(NOT(ISNUMBER(AZ30)),"Base-year PPI missing; ","") -> Material missing; Seal missing; | AT30: =IFERROR(INDEX(Factors_ROT!$F$5:$F$200,MATCH("MAT|"&G30,Factors_ROT!$A$5:$A$200,0)),1) -> 1 | AU30: =IFERROR(INDEX(Factors_ROT!$F$5:$F$200,MATCH("SEAL_ARR|"&P30,Factors_ROT!$A$5:$A$200,0)),1)*IFERROR(INDEX(Factors_ROT!$F$5:$F$200,MATCH("SEAL_CAT|"&Q30,Factors_ROT!$A$5:$A$200,0)),1)*IFERROR(INDEX(Factors_ROT!$F$5:$F$200,MATCH("SEAL_PLAN|"&R30,Factors_ROT!$A$5:$A$200,0)),1) -> 1 | AV30: =IFERROR(INDEX(Factors_ROT!$F$5:$F$200,MATCH("DRV|"&S30,Factors_ROT!$A$5:$A$200,0)),1)*IFERROR(INDEX(Factors_ROT!$F$5:$F$200,MATCH("NACE|"&O30,Factors_ROT!$A$5:$A$200,0)),1) -> 1 | AW30: =IFERROR(INDEX(Factors_ROT!$F$5:$F$200,MATCH("SC_DRV|"&AL30,Factors_ROT!$A$5:$A$200,0)),1)*IFERROR(INDEX(Factors_ROT!$F$5:$F$200,MATCH("SC_BSP|"&AM30,Factors_ROT!$A$5:$A$200,0)),1)*IFERROR(INDEX(Factors_ROT!$F$5:$F$200,MATCH("SC_SEAL|"&AN30,Factors_ROT!$A$5:$A$200,0)),1)*IFERROR(INDEX(Factors_ROT!$F$5:$F$200,MATCH("SC_COMM|"&AO30,Factors_ROT!$A$5:$A$200,0)),1)*IFERROR(INDEX(Factors_ROT!$F$5:$F$200,MATCH("SC_2Y|"&AP30,Factors_ROT!$A$5:$A$200,0)),1)*IFERROR(INDEX(Factors_ROT!$F$5:$F$200,MATCH("SC_TPI|"&AQ30,Factors_ROT!$A$5:$A$200,0)),1)*IFERROR(INDEX(Factors_ROT!$F$5:$F$200,MATCH("SC_FAT|"&AR30,Factors_ROT!$A$5:$A$200,0)),1) -> 0.98 | AX30: =AT30*AU30*AV30*AW30 -> 0.98 | AY30: =IF(ISNUMBER(AB30),AB30/AX30,"") -> 9183.6735 | AZ30: =IFERROR(IF(N(INDEX(Escalation_Index!$B$5:$B$25,MATCH(Y30,Escalation_Index!$A$5:$A$25,0)))>0,INDEX(Escalation_Index!$B$5:$B$25,MATCH(Y30,Escalation_Index!$A$5:$A$25,0)),""),"") -> 119.251 | BA30: =IF(ISNUMBER('Assumptions & FX Reference'!$I$12),'Assumptions & FX Reference'!$I$12,"") -> 123.416 | BB30: =IF(AND(M30="API 610",LEFT(V30,11)="Centrifugal",OR(LEFT(G30,2)="S-",LEFT(G30,2)="D-")),"Y","N") -> N | BC30: =IF(ISNUMBER(AG30),AG30/AX30,"") -> 9504.4255 | BD30: =IF(AND(ISNUMBER(BC30),ISNUMBER(K30)),IF(K30>0,BC30/K30^'Assumptions & FX Reference'!$I$16,""),"") -> 15346.112 | BE30: File PEP-Rev 140205 Gachsaran 4.xlsx, sheet 'P.ME', cells A36:H36 (service in D, spec in E, unit price in H) | BF30: Type: Centrifugal (API 610) | Driver: موتور الکتریکی (E) | Power: 0.45 kW | NACE MR0175: YES | مشخصات کاتالوگی: .8m/h, 2bar, 0.45 kw | Original type text: Centrifugal (assumed) | GCH4 review 1405-07: Source IRR = EUR 9,000 × 1.085 × 420,000 (P.ME H36); previous bank stored the IRR figure as 1399 IRR, which overstated EUR ≈2.6× | BG30: Y | BH30: PMP | BI30: ="PMP-"&TEXT(A30,"0000") -> PMP-0026
A31: 27 | B31: FLARE K.O DRUM LIQUID PUMPS | C31: Gachsaran 4 | D31: P-601-A/B | E31: ROT-DRN | F31: Not stated | G31: Not stated | H31: 15 | J31: 0.33 | K31: =IF(ISNUMBER(J31),J31,IF(AND(ISNUMBER(H31),ISNUMBER(I31)),H31*I31/(367*'Assumptions & FX Reference'!$I$17),"")) -> 0.33 | L31: =IF(IF(OR(M31="Not stated",M31=""),""," + "&M31)&IF(OR(N31="None",N31=""),""," + "&N31)&IF(O31="Y"," + NACE MR0175","")="","Not stated",MID(IF(OR(M31="Not stated",M31=""),""," + "&M31)&IF(OR(N31="None",N31=""),""," + "&N31)&IF(O31="Y"," + NACE MR0175",""),4,300)) -> Not stated | M31: Not stated | N31: None | O31: Not stated | P31: Not stated | Q31: Not stated | R31: Not stated | S31: Electric Motor | T31: Oily Water / Drain | U31: 2 | V31: Centrifugal | W31: 0.8 | X31: Not stated | Y31: 1402 | Z31: EUR | AA31: 28000 | AB31: =IF(NOT(ISNUMBER(AA31)),"",IF(NOT(ISNUMBER(Y31)),"",IFERROR(IF(Z31="EUR",AA31,IF(Z31="IRR",AA31/INDEX('Assumptions & FX Reference'!$C$5:$C$25,MATCH(Y31,'Assumptions & FX Reference'!$A$5:$A$25,0)),IF(Z31="USD",AA31*INDEX('Assumptions & FX Reference'!$B$5:$B$25,MATCH(Y31,'Assumptions & FX Reference'!$A$5:$A$25,0))/INDEX('Assumptions & FX Reference'!$C$5:$C$25,MATCH(Y31,'Assumptions & FX Reference'!$A$5:$A$25,0)),""))),""))) -> 28000 | AC31: =IF(NOT(ISNUMBER(AA31)),"",IF(NOT(ISNUMBER(Y31)),"",IFERROR(IF(Z31="USD",AA31,IF(Z31="IRR",AA31/INDEX('Assumptions & FX Reference'!$B$5:$B$25,MATCH(Y31,'Assumptions & FX Reference'!$A$5:$A$25,0)),IF(Z31="EUR",AA31*INDEX('Assumptions & FX Reference'!$C$5:$C$25,MATCH(Y31,'Assumptions & FX Reference'!$A$5:$A$25,0))/INDEX('Assumptions & FX Reference'!$B$5:$B$25,MATCH(Y31,'Assumptions & FX Reference'!$A$5:$A$25,0)),""))),""))) -> 35300 | AD31: =IF(NOT(ISNUMBER(AA31)),"",IF(NOT(ISNUMBER(Y31)),"",IFERROR(IF(Z31="IRR",AA31,IF(Z31="USD",AA31*INDEX('Assumptions & FX Reference'!$B$5:$B$25,MATCH(Y31,'Assumptions & FX Reference'!$A$5:$A$25,0)),IF(Z31="EUR",AA31*INDEX('Assumptions & FX Reference'!$C$5:$C$25,MATCH(Y31,'Assumptions & FX Reference'!$A$5:$A$25,0)),""))),""))) -> 14826000000 | AE31: Consultant basic-design estimate – PEP Rev.1402/05, sheet P.ME «هزینه واحد بدون ضریب»; EUR figure (converted in the PEP at 420,000×1.085 IRR/EUR) | source label: AACE Class 2 | AF31: EXW | AG31: =IF(AND(Z31="EUR",N(AA31)>5000000),"",IF(AND(ISNUMBER(AB31),ISNUMBER(AZ31),ISNUMBER(BA31)),IF(AND(BB31="Y",ISNUMBER('Assumptions & FX Reference'!$I$15)),MAX(AB31*BA31/AZ31,'Assumptions & FX Reference'!$I$13*BA31/'Assumptions & FX Reference'!$I$15),AB31*BA31/AZ31),"")) -> 28977.937 | AH31: =IF(AND(ISNUMBER(AG31),ISNUMBER('Assumptions & FX Reference'!$I$8),ISNUMBER('Assumptions & FX Reference'!$I$11)),AG31*'Assumptions & FX Reference'!$I$8/'Assumptions & FX Reference'!$I$11,"") -> 30594.416 | AI31: =IF(AND(ISNUMBER(AG31),ISNUMBER('Assumptions & FX Reference'!$I$8)),AG31*'Assumptions & FX Reference'!$I$8,"") -> 2.0147433e+10 | AJ31: (Gachsaran 4 Basic Design MTO) | AK31: Basic Design | AL31: Not stated | AM31: Not stated | AN31: Not stated | AO31: N | AP31: N | AQ31: N | AR31: Not stated | AS31: =IF(AND(Z31="EUR",N(AA31)>5000000),"Check currency (EUR>5M); ","")&IF(NOT(ISNUMBER(AA31)),"No price; ","")&IF(G31="Not stated","Material missing; ","")&IF(P31="Not stated","Seal missing; ","")&IF(K31="","Size driver missing; ","")&IF(NOT(ISNUMBER(AZ31)),"Base-year PPI missing; ","") -> Material missing; Seal missing; | AT31: =IFERROR(INDEX(Factors_ROT!$F$5:$F$200,MATCH("MAT|"&G31,Factors_ROT!$A$5:$A$200,0)),1) -> 1 | AU31: =IFERROR(INDEX(Factors_ROT!$F$5:$F$200,MATCH("SEAL_ARR|"&P31,Factors_ROT!$A$5:$A$200,0)),1)*IFERROR(INDEX(Factors_ROT!$F$5:$F$200,MATCH("SEAL_CAT|"&Q31,Factors_ROT!$A$5:$A$200,0)),1)*IFERROR(INDEX(Factors_ROT!$F$5:$F$200,MATCH("SEAL_PLAN|"&R31,Factors_ROT!$A$5:$A$200,0)),1) -> 1 | AV31: =IFERROR(INDEX(Factors_ROT!$F$5:$F$200,MATCH("DRV|"&S31,Factors_ROT!$A$5:$A$200,0)),1)*IFERROR(INDEX(Factors_ROT!$F$5:$F$200,MATCH("NACE|"&O31,Factors_ROT!$A$5:$A$200,0)),1) -> 1 | AW31: =IFERROR(INDEX(Factors_ROT!$F$5:$F$200,MATCH("SC_DRV|"&AL31,Factors_ROT!$A$5:$A$200,0)),1)*IFERROR(INDEX(Factors_ROT!$F$5:$F$200,MATCH("SC_BSP|"&AM31,Factors_ROT!$A$5:$A$200,0)),1)*IFERROR(INDEX(Factors_ROT!$F$5:$F$200,MATCH("SC_SEAL|"&AN31,Factors_ROT!$A$5:$A$200,0)),1)*IFERROR(INDEX(Factors_ROT!$F$5:$F$200,MATCH("SC_COMM|"&AO31,Factors_ROT!$A$5:$A$200,0)),1)*IFERROR(INDEX(Factors_ROT!$F$5:$F$200,MATCH("SC_2Y|"&AP31,Factors_ROT!$A$5:$A$200,0)),1)*IFERROR(INDEX(Factors_ROT!$F$5:$F$200,MATCH("SC_TPI|"&AQ31,Factors_ROT!$A$5:$A$200,0)),1)*IFERROR(INDEX(Factors_ROT!$F$5:$F$200,MATCH("SC_FAT|"&AR31,Factors_ROT!$A$5:$A$200,0)),1) -> 0.98 | AX31: =AT31*AU31*AV31*AW31 -> 0.98 | AY31: =IF(ISNUMBER(AB31),AB31/AX31,"") -> 28571.429 | AZ31: =IFERROR(IF(N(INDEX(Escalation_Index!$B$5:$B$25,MATCH(Y31,Escalation_Index!$A$5:$A$25,0)))>0,INDEX(Escalation_Index!$B$5:$B$25,MATCH(Y31,Escalation_Index!$A$5:$A$25,0)),""),"") -> 119.251 | BA31: =IF(ISNUMBER('Assumptions & FX Reference'!$I$12),'Assumptions & FX Reference'!$I$12,"") -> 123.416 | BB31: =IF(AND(M31="API 610",LEFT(V31,11)="Centrifugal",OR(LEFT(G31,2)="S-",LEFT(G31,2)="D-")),"Y","N") -> N | BC31: =IF(ISNUMBER(AG31),AG31/AX31,"") -> 29569.324 | BD31: =IF(AND(ISNUMBER(BC31),ISNUMBER(K31)),IF(K31>0,BC31/K31^'Assumptions & FX Reference'!$I$16,""),"") -> 57508.631 | BE31: File PEP-Rev 140205 Gachsaran 4.xlsx, sheet 'P.ME', cells A46:H46 (service in D, spec in E, unit price in H) | BF31: Type: Centrifugal (API 610) | Driver: موتور الکتریکی (E) | Power: 0.33 kW | مشخصات کاتالوگی: 15m3/hr, 0.8 bar, 0.33 kw | Original type text: Centrifugal (assumed) | GCH4 review 1405-07: Source IRR = EUR 28,000 × 1.085 × 420,000 (P.ME H46); previous bank stored the IRR figure as 1399 IRR, which overstated EUR ≈2.6× | BG31: Y | BH31: PMP | BI31: ="PMP-"&TEXT(A31,"0000") -> PMP-0027
A32: 28 | B32: HC CLOSED DRAIN TRANSFER PUMPS | C32: Gachsaran 4 | D32: P-701-A/B | E32: ROT-DRN | F32: Not stated | G32: Not stated | H32: 27.5 | J32: 3.3 | K32: =IF(ISNUMBER(J32),J32,IF(AND(ISNUMBER(H32),ISNUMBER(I32)),H32*I32/(367*'Assumptions & FX Reference'!$I$17),"")) -> 3.3 | L32: =IF(IF(OR(M32="Not stated",M32=""),""," + "&M32)&IF(OR(N32="None",N32=""),""," + "&N32)&IF(O32="Y"," + NACE MR0175","")="","Not stated",MID(IF(OR(M32="Not stated",M32=""),""," + "&M32)&IF(OR(N32="None",N32=""),""," + "&N32)&IF(O32="Y"," + NACE MR0175",""),4,300)) -> Not stated | M32: Not stated | N32: None | O32: Not stated | P32: Not stated | Q32: Not stated | R32: Not stated | S32: Electric Motor | T32: Oily Water / Drain | U32: 2 | V32: Centrifugal | W32: 4.3 | X32: Not stated | Y32: 1402 | Z32: EUR | AA32: 53000 | AB32: =IF(NOT(ISNUMBER(AA32)),"",IF(NOT(ISNUMBER(Y32)),"",IFERROR(IF(Z32="EUR",AA32,IF(Z32="IRR",AA32/INDEX('Assumptions & FX Reference'!$C$5:$C$25,MATCH(Y32,'Assumptions & FX Reference'!$A$5:$A$25,0)),IF(Z32="USD",AA32*INDEX('Assumptions & FX Reference'!$B$5:$B$25,MATCH(Y32,'Assumptions & FX Reference'!$A$5:$A$25,0))/INDEX('Assumptions & FX Reference'!$C$5:$C$25,MATCH(Y32,'Assumptions & FX Reference'!$A$5:$A$25,0)),""))),""))) -> 53000 | AC32: =IF(NOT(ISNUMBER(AA32)),"",IF(NOT(ISNUMBER(Y32)),"",IFERROR(IF(Z32="USD",AA32,IF(Z32="IRR",AA32/INDEX('Assumptions & FX Reference'!$B$5:$B$25,MATCH(Y32,'Assumptions & FX Reference'!$A$5:$A$25,0)),IF(Z32="EUR",AA32*INDEX('Assumptions & FX Reference'!$C$5:$C$25,MATCH(Y32,'Assumptions & FX Reference'!$A$5:$A$25,0))/INDEX('Assumptions & FX Reference'!$B$5:$B$25,MATCH(Y32,'Assumptions & FX Reference'!$A$5:$A$25,0)),""))),""))) -> 66817.857 | AD32: =IF(NOT(ISNUMBER(AA32)),"",IF(NOT(ISNUMBER(Y32)),"",IFERROR(IF(Z32="IRR",AA32,IF(Z32="USD",AA32*INDEX('Assumptions & FX Reference'!$B$5:$B$25,MATCH(Y32,'Assumptions & FX Reference'!$A$5:$A$25,0)),IF(Z32="EUR",AA32*INDEX('Assumptions & FX Reference'!$C$5:$C$25,MATCH(Y32,'Assumptions & FX Reference'!$A$5:$A$25,0)),""))),""))) -> 28063500000 | AE32: Consultant basic-design estimate – PEP Rev.1402/05, sheet P.ME «هزینه واحد بدون ضریب»; EUR figure (converted in the PEP at 420,000×1.085 IRR/EUR) | source label: AACE Class 2 | AF32: EXW | AG32: =IF(AND(Z32="EUR",N(AA32)>5000000),"",IF(AND(ISNUMBER(AB32),ISNUMBER(AZ32),ISNUMBER(BA32)),IF(AND(BB32="Y",ISNUMBER('Assumptions & FX Reference'!$I$15)),MAX(AB32*BA32/AZ32,'Assumptions & FX Reference'!$I$13*BA32/'Assumptions & FX Reference'!$I$15),AB32*BA32/AZ32),"")) -> 54851.096 | AH32: =IF(AND(ISNUMBER(AG32),ISNUMBER('Assumptions & FX Reference'!$I$8),ISNUMBER('Assumptions & FX Reference'!$I$11)),AG32*'Assumptions & FX Reference'!$I$8/'Assumptions & FX Reference'!$I$11,"") -> 57910.859 | AI32: =IF(AND(ISNUMBER(AG32),ISNUMBER('Assumptions & FX Reference'!$I$8)),AG32*'Assumptions & FX Reference'!$I$8,"") -> 3.8136212e+10 | AJ32: (Gachsaran 4 Basic Design MTO) | AK32: Basic Design | AL32: Not stated | AM32: Not stated | AN32: Not stated | AO32: N | AP32: N | AQ32: N | AR32: Not stated | AS32: =IF(AND(Z32="EUR",N(AA32)>5000000),"Check currency (EUR>5M); ","")&IF(NOT(ISNUMBER(AA32)),"No price; ","")&IF(G32="Not stated","Material missing; ","")&IF(P32="Not stated","Seal missing; ","")&IF(K32="","Size driver missing; ","")&IF(NOT(ISNUMBER(AZ32)),"Base-year PPI missing; ","") -> Material missing; Seal missing; | AT32: =IFERROR(INDEX(Factors_ROT!$F$5:$F$200,MATCH("MAT|"&G32,Factors_ROT!$A$5:$A$200,0)),1) -> 1 | AU32: =IFERROR(INDEX(Factors_ROT!$F$5:$F$200,MATCH("SEAL_ARR|"&P32,Factors_ROT!$A$5:$A$200,0)),1)*IFERROR(INDEX(Factors_ROT!$F$5:$F$200,MATCH("SEAL_CAT|"&Q32,Factors_ROT!$A$5:$A$200,0)),1)*IFERROR(INDEX(Factors_ROT!$F$5:$F$200,MATCH("SEAL_PLAN|"&R32,Factors_ROT!$A$5:$A$200,0)),1) -> 1 | AV32: =IFERROR(INDEX(Factors_ROT!$F$5:$F$200,MATCH("DRV|"&S32,Factors_ROT!$A$5:$A$200,0)),1)*IFERROR(INDEX(Factors_ROT!$F$5:$F$200,MATCH("NACE|"&O32,Factors_ROT!$A$5:$A$200,0)),1) -> 1 | AW32: =IFERROR(INDEX(Factors_ROT!$F$5:$F$200,MATCH("SC_DRV|"&AL32,Factors_ROT!$A$5:$A$200,0)),1)*IFERROR(INDEX(Factors_ROT!$F$5:$F$200,MATCH("SC_BSP|"&AM32,Factors_ROT!$A$5:$A$200,0)),1)*IFERROR(INDEX(Factors_ROT!$F$5:$F$200,MATCH("SC_SEAL|"&AN32,Factors_ROT!$A$5:$A$200,0)),1)*IFERROR(INDEX(Factors_ROT!$F$5:$F$200,MATCH("SC_COMM|"&AO32,Factors_ROT!$A$5:$A$200,0)),1)*IFERROR(INDEX(Factors_ROT!$F$5:$F$200,MATCH("SC_2Y|"&AP32,Factors_ROT!$A$5:$A$200,0)),1)*IFERROR(INDEX(Factors_ROT!$F$5:$F$200,MATCH("SC_TPI|"&AQ32,Factors_ROT!$A$5:$A$200,0)),1)*IFERROR(INDEX(Factors_ROT!$F$5:$F$200,MATCH("SC_FAT|"&AR32,Factors_ROT!$A$5:$A$200,0)),1) -> 0.98 | AX32: =AT32*AU32*AV32*AW32 -> 0.98 | AY32: =IF(ISNUMBER(AB32),AB32/AX32,"") -> 54081.633 | AZ32: =IFERROR(IF(N(INDEX(Escalation_Index!$B$5:$B$25,MATCH(Y32,Escalation_Index!$A$5:$A$25,0)))>0,INDEX(Escalation_Index!$B$5:$B$25,MATCH(Y32,Escalation_Index!$A$5:$A$25,0)),""),"") -> 119.251 | BA32: =IF(ISNUMBER('Assumptions & FX Reference'!$I$12),'Assumptions & FX Reference'!$I$12,"") -> 123.416 | BB32: =IF(AND(M32="API 610",LEFT(V32,11)="Centrifugal",OR(LEFT(G32,2)="S-",LEFT(G32,2)="D-")),"Y","N") -> N | BC32: =IF(ISNUMBER(AG32),AG32/AX32,"") -> 55970.506 | BD32: =IF(AND(ISNUMBER(BC32),ISNUMBER(K32)),IF(K32>0,BC32/K32^'Assumptions & FX Reference'!$I$16,""),"") -> 27343.296 | BE32: File PEP-Rev 140205 Gachsaran 4.xlsx, sheet 'P.ME', cells A50:H50 (service in D, spec in E, unit price in H) | BF32: Type: Centrifugal (API 610) | Driver: موتور الکتریکی (E) | Power: 3.3 kW | مشخصات کاتالوگی: 27.5m3/hr, 4.3 bar, 3.3 kw | Original type text: Centrifugal (assumed) | GCH4 review 1405-07: Source IRR = EUR 53,000 × 1.085 × 420,000 (P.ME H50); previous bank stored the IRR figure as 1399 IRR, which overstated EUR ≈2.6× | BG32: Y | BH32: PMP | BI32: ="PMP-"&TEXT(A32,"0000") -> PMP-0028
A33: 29 | B33: HC CLOSED DRAIN DRUM SUMP PUMP | C33: Gachsaran 4 | D33: P-702A/B | E33: ROT-DRN | F33: Not stated | G33: Not stated | H33: 5.5 | J33: 0.11 | K33: =IF(ISNUMBER(J33),J33,IF(AND(ISNUMBER(H33),ISNUMBER(I33)),H33*I33/(367*'Assumptions & FX Reference'!$I$17),"")) -> 0.11 | L33: =IF(IF(OR(M33="Not stated",M33=""),""," + "&M33)&IF(OR(N33="None",N33=""),""," + "&N33)&IF(O33="Y"," + NACE MR0175","")="","Not stated",MID(IF(OR(M33="Not stated",M33=""),""," + "&M33)&IF(OR(N33="None",N33=""),""," + "&N33)&IF(O33="Y"," + NACE MR0175",""),4,300)) -> Not stated | M33: Not stated | N33: None | O33: Not stated | P33: Not stated | Q33: Not stated | R33: Not stated | S33: Electric Motor | T33: Oily Water / Drain | U33: 2 | V33: Centrifugal | W33: 7 | X33: Not stated | Y33: 1402 | Z33: EUR | AA33: 53000 | AB33: =IF(NOT(ISNUMBER(AA33)),"",IF(NOT(ISNUMBER(Y33)),"",IFERROR(IF(Z33="EUR",AA33,IF(Z33="IRR",AA33/INDEX('Assumptions & FX Reference'!$C$5:$C$25,MATCH(Y33,'Assumptions & FX Reference'!$A$5:$A$25,0)),IF(Z33="USD",AA33*INDEX('Assumptions & FX Reference'!$B$5:$B$25,MATCH(Y33,'Assumptions & FX Reference'!$A$5:$A$25,0))/INDEX('Assumptions & FX Reference'!$C$5:$C$25,MATCH(Y33,'Assumptions & FX Reference'!$A$5:$A$25,0)),""))),""))) -> 53000 | AC33: =IF(NOT(ISNUMBER(AA33)),"",IF(NOT(ISNUMBER(Y33)),"",IFERROR(IF(Z33="USD",AA33,IF(Z33="IRR",AA33/INDEX('Assumptions & FX Reference'!$B$5:$B$25,MATCH(Y33,'Assumptions & FX Reference'!$A$5:$A$25,0)),IF(Z33="EUR",AA33*INDEX('Assumptions & FX Reference'!$C$5:$C$25,MATCH(Y33,'Assumptions & FX Reference'!$A$5:$A$25,0))/INDEX('Assumptions & FX Reference'!$B$5:$B$25,MATCH(Y33,'Assumptions & FX Reference'!$A$5:$A$25,0)),""))),""))) -> 66817.857 | AD33: =IF(NOT(ISNUMBER(AA33)),"",IF(NOT(ISNUMBER(Y33)),"",IFERROR(IF(Z33="IRR",AA33,IF(Z33="USD",AA33*INDEX('Assumptions & FX Reference'!$B$5:$B$25,MATCH(Y33,'Assumptions & FX Reference'!$A$5:$A$25,0)),IF(Z33="EUR",AA33*INDEX('Assumptions & FX Reference'!$C$5:$C$25,MATCH(Y33,'Assumptions & FX Reference'!$A$5:$A$25,0)),""))),""))) -> 28063500000 | AE33: Consultant basic-design estimate – PEP Rev.1402/05, sheet P.ME «هزینه واحد بدون ضریب»; EUR figure (converted in the PEP at 420,000×1.085 IRR/EUR) | source label: AACE Class 2 | AF33: EXW | AG33: =IF(AND(Z33="EUR",N(AA33)>5000000),"",IF(AND(ISNUMBER(AB33),ISNUMBER(AZ33),ISNUMBER(BA33)),IF(AND(BB33="Y",ISNUMBER('Assumptions & FX Reference'!$I$15)),MAX(AB33*BA33/AZ33,'Assumptions & FX Reference'!$I$13*BA33/'Assumptions & FX Reference'!$I$15),AB33*BA33/AZ33),"")) -> 54851.096 | AH33: =IF(AND(ISNUMBER(AG33),ISNUMBER('Assumptions & FX Reference'!$I$8),ISNUMBER('Assumptions & FX Reference'!$I$11)),AG33*'Assumptions & FX Reference'!$I$8/'Assumptions & FX Reference'!$I$11,"") -> 57910.859 | AI33: =IF(AND(ISNUMBER(AG33),ISNUMBER('Assumptions & FX Reference'!$I$8)),AG33*'Assumptions & FX Reference'!$I$8,"") -> 3.8136212e+10 | AJ33: (Gachsaran 4 Basic Design MTO) | AK33: Basic Design | AL33: Not stated | AM33: Not stated | AN33: Not stated | AO33: N | AP33: N | AQ33: N | AR33: Not stated | AS33: =IF(AND(Z33="EUR",N(AA33)>5000000),"Check currency (EUR>5M); ","")&IF(NOT(ISNUMBER(AA33)),"No price; ","")&IF(G33="Not stated","Material missing; ","")&IF(P33="Not stated","Seal missing; ","")&IF(K33="","Size driver missing; ","")&IF(NOT(ISNUMBER(AZ33)),"Base-year PPI missing; ","") -> Material missing; Seal missing; | AT33: =IFERROR(INDEX(Factors_ROT!$F$5:$F$200,MATCH("MAT|"&G33,Factors_ROT!$A$5:$A$200,0)),1) -> 1 | AU33: =IFERROR(INDEX(Factors_ROT!$F$5:$F$200,MATCH("SEAL_ARR|"&P33,Factors_ROT!$A$5:$A$200,0)),1)*IFERROR(INDEX(Factors_ROT!$F$5:$F$200,MATCH("SEAL_CAT|"&Q33,Factors_ROT!$A$5:$A$200,0)),1)*IFERROR(INDEX(Factors_ROT!$F$5:$F$200,MATCH("SEAL_PLAN|"&R33,Factors_ROT!$A$5:$A$200,0)),1) -> 1 | AV33: =IFERROR(INDEX(Factors_ROT!$F$5:$F$200,MATCH("DRV|"&S33,Factors_ROT!$A$5:$A$200,0)),1)*IFERROR(INDEX(Factors_ROT!$F$5:$F$200,MATCH("NACE|"&O33,Factors_ROT!$A$5:$A$200,0)),1) -> 1 | AW33: =IFERROR(INDEX(Factors_ROT!$F$5:$F$200,MATCH("SC_DRV|"&AL33,Factors_ROT!$A$5:$A$200,0)),1)*IFERROR(INDEX(Factors_ROT!$F$5:$F$200,MATCH("SC_BSP|"&AM33,Factors_ROT!$A$5:$A$200,0)),1)*IFERROR(INDEX(Factors_ROT!$F$5:$F$200,MATCH("SC_SEAL|"&AN33,Factors_ROT!$A$5:$A$200,0)),1)*IFERROR(INDEX(Factors_ROT!$F$5:$F$200,MATCH("SC_COMM|"&AO33,Factors_ROT!$A$5:$A$200,0)),1)*IFERROR(INDEX(Factors_ROT!$F$5:$F$200,MATCH("SC_2Y|"&AP33,Factors_ROT!$A$5:$A$200,0)),1)*IFERROR(INDEX(Factors_ROT!$F$5:$F$200,MATCH("SC_TPI|"&AQ33,Factors_ROT!$A$5:$A$200,0)),1)*IFERROR(INDEX(Factors_ROT!$F$5:$F$200,MATCH("SC_FAT|"&AR33,Factors_ROT!$A$5:$A$200,0)),1) -> 0.98 | AX33: =AT33*AU33*AV33*AW33 -> 0.98 | AY33: =IF(ISNUMBER(AB33),AB33/AX33,"") -> 54081.633 | AZ33: =IFERROR(IF(N(INDEX(Escalation_Index!$B$5:$B$25,MATCH(Y33,Escalation_Index!$A$5:$A$25,0)))>0,INDEX(Escalation_Index!$B$5:$B$25,MATCH(Y33,Escalation_Index!$A$5:$A$25,0)),""),"") -> 119.251 | BA33: =IF(ISNUMBER('Assumptions & FX Reference'!$I$12),'Assumptions & FX Reference'!$I$12,"") -> 123.416 | BB33: =IF(AND(M33="API 610",LEFT(V33,11)="Centrifugal",OR(LEFT(G33,2)="S-",LEFT(G33,2)="D-")),"Y","N") -> N | BC33: =IF(ISNUMBER(AG33),AG33/AX33,"") -> 55970.506 | BD33: =IF(AND(ISNUMBER(BC33),ISNUMBER(K33)),IF(K33>0,BC33/K33^'Assumptions & FX Reference'!$I$16,""),"") -> 210437.74 | BE33: File PEP-Rev 140205 Gachsaran 4.xlsx, sheet 'P.ME', cells A51:H51 (service in D, spec in E, unit price in H) | BF33: Type: Centrifugal (API 610) | Driver: موتور الکتریکی (E) | Power: 0.11 kW | مشخصات کاتالوگی: 5.5m3/hr, 7 bar. 0.11 kw | Original type text: Centrifugal (assumed) | GCH4 review 1405-07: Source IRR = EUR 53,000 × 1.085 × 420,000 (P.ME H51); previous bank stored the IRR figure as 1399 IRR, which overstated EUR ≈2.6× | BG33: Y | BH33: PMP | BI33: ="PMP-"&TEXT(A33,"0000") -> PMP-0029
A34: 30 | B34: CLEAN WATER PUMPS | C34: Gachsaran 4 | D34: P-703-A/B | E34: ROT-WAT | F34: Not stated | G34: Not stated | H34: 11 | J34: 0.54 | K34: =IF(ISNUMBER(J34),J34,IF(AND(ISNUMBER(H34),ISNUMBER(I34)),H34*I34/(367*'Assumptions & FX Reference'!$I$17),"")) -> 0.54 | L34: =IF(IF(OR(M34="Not stated",M34=""),""," + "&M34)&IF(OR(N34="None",N34=""),""," + "&N34)&IF(O34="Y"," + NACE MR0175","")="","Not stated",MID(IF(OR(M34="Not stated",M34=""),""," + "&M34)&IF(OR(N34="None",N34=""),""," + "&N34)&IF(O34="Y"," + NACE MR0175",""),4,300)) -> Not stated | M34: Not stated | N34: None | O34: Not stated | P34: Not stated | Q34: Not stated | R34: Not stated | S34: Electric Motor | T34: Process / Dilution Water | U34: 2 | V34: Centrifugal | W34: 1.8 | X34: Not stated | Y34: 1402 | Z34: EUR | AA34: 29000 | AB34: =IF(NOT(ISNUMBER(AA34)),"",IF(NOT(ISNUMBER(Y34)),"",IFERROR(IF(Z34="EUR",AA34,IF(Z34="IRR",AA34/INDEX('Assumptions & FX Reference'!$C$5:$C$25,MATCH(Y34,'Assumptions & FX Reference'!$A$5:$A$25,0)),IF(Z34="USD",AA34*INDEX('Assumptions & FX Reference'!$B$5:$B$25,MATCH(Y34,'Assumptions & FX Reference'!$A$5:$A$25,0))/INDEX('Assumptions & FX Reference'!$C$5:$C$25,MATCH(Y34,'Assumptions & FX Reference'!$A$5:$A$25,0)),""))),""))) -> 29000 | AC34: =IF(NOT(ISNUMBER(AA34)),"",IF(NOT(ISNUMBER(Y34)),"",IFERROR(IF(Z34="USD",AA34,IF(Z34="IRR",AA34/INDEX('Assumptions & FX Reference'!$B$5:$B$25,MATCH(Y34,'Assumptions & FX Reference'!$A$5:$A$25,0)),IF(Z34="EUR",AA34*INDEX('Assumptions & FX Reference'!$C$5:$C$25,MATCH(Y34,'Assumptions & FX Reference'!$A$5:$A$25,0))/INDEX('Assumptions & FX Reference'!$B$5:$B$25,MATCH(Y34,'Assumptions & FX Reference'!$A$5:$A$25,0)),""))),""))) -> 36560.714 | AD34: =IF(NOT(ISNUMBER(AA34)),"",IF(NOT(ISNUMBER(Y34)),"",IFERROR(IF(Z34="IRR",AA34,IF(Z34="USD",AA34*INDEX('Assumptions & FX Reference'!$B$5:$B$25,MATCH(Y34,'Assumptions & FX Reference'!$A$5:$A$25,0)),IF(Z34="EUR",AA34*INDEX('Assumptions & FX Reference'!$C$5:$C$25,MATCH(Y34,'Assumptions & FX Reference'!$A$5:$A$25,0)),""))),""))) -> 15355500000 | AE34: Consultant basic-design estimate – PEP Rev.1402/05, sheet P.ME «هزینه واحد بدون ضریب»; EUR figure (converted in the PEP at 420,000×1.085 IRR/EUR) | source label: AACE Class 2 | AF34: EXW | AG34: =IF(AND(Z34="EUR",N(AA34)>5000000),"",IF(AND(ISNUMBER(AB34),ISNUMBER(AZ34),ISNUMBER(BA34)),IF(AND(BB34="Y",ISNUMBER('Assumptions & FX Reference'!$I$15)),MAX(AB34*BA34/AZ34,'Assumptions & FX Reference'!$I$13*BA34/'Assumptions & FX Reference'!$I$15),AB34*BA34/AZ34),"")) -> 30012.864 | AH34: =IF(AND(ISNUMBER(AG34),ISNUMBER('Assumptions & FX Reference'!$I$8),ISNUMBER('Assumptions & FX Reference'!$I$11)),AG34*'Assumptions & FX Reference'!$I$8/'Assumptions & FX Reference'!$I$11,"") -> 31687.074 | AI34: =IF(AND(ISNUMBER(AG34),ISNUMBER('Assumptions & FX Reference'!$I$8)),AG34*'Assumptions & FX Reference'!$I$8,"") -> 2.0866984e+10 | AJ34: (Gachsaran 4 Basic Design MTO) | AK34: Basic Design | AL34: Not stated | AM34: Not stated | AN34: Not stated | AO34: N | AP34: N | AQ34: N | AR34: Not stated | AS34: =IF(AND(Z34="EUR",N(AA34)>5000000),"Check currency (EUR>5M); ","")&IF(NOT(ISNUMBER(AA34)),"No price; ","")&IF(G34="Not stated","Material missing; ","")&IF(P34="Not stated","Seal missing; ","")&IF(K34="","Size driver missing; ","")&IF(NOT(ISNUMBER(AZ34)),"Base-year PPI missing; ","") -> Material missing; Seal missing; | AT34: =IFERROR(INDEX(Factors_ROT!$F$5:$F$200,MATCH("MAT|"&G34,Factors_ROT!$A$5:$A$200,0)),1) -> 1 | AU34: =IFERROR(INDEX(Factors_ROT!$F$5:$F$200,MATCH("SEAL_ARR|"&P34,Factors_ROT!$A$5:$A$200,0)),1)*IFERROR(INDEX(Factors_ROT!$F$5:$F$200,MATCH("SEAL_CAT|"&Q34,Factors_ROT!$A$5:$A$200,0)),1)*IFERROR(INDEX(Factors_ROT!$F$5:$F$200,MATCH("SEAL_PLAN|"&R34,Factors_ROT!$A$5:$A$200,0)),1) -> 1 | AV34: =IFERROR(INDEX(Factors_ROT!$F$5:$F$200,MATCH("DRV|"&S34,Factors_ROT!$A$5:$A$200,0)),1)*IFERROR(INDEX(Factors_ROT!$F$5:$F$200,MATCH("NACE|"&O34,Factors_ROT!$A$5:$A$200,0)),1) -> 1 | AW34: =IFERROR(INDEX(Factors_ROT!$F$5:$F$200,MATCH("SC_DRV|"&AL34,Factors_ROT!$A$5:$A$200,0)),1)*IFERROR(INDEX(Factors_ROT!$F$5:$F$200,MATCH("SC_BSP|"&AM34,Factors_ROT!$A$5:$A$200,0)),1)*IFERROR(INDEX(Factors_ROT!$F$5:$F$200,MATCH("SC_SEAL|"&AN34,Factors_ROT!$A$5:$A$200,0)),1)*IFERROR(INDEX(Factors_ROT!$F$5:$F$200,MATCH("SC_COMM|"&AO34,Factors_ROT!$A$5:$A$200,0)),1)*IFERROR(INDEX(Factors_ROT!$F$5:$F$200,MATCH("SC_2Y|"&AP34,Factors_ROT!$A$5:$A$200,0)),1)*IFERROR(INDEX(Factors_ROT!$F$5:$F$200,MATCH("SC_TPI|"&AQ34,Factors_ROT!$A$5:$A$200,0)),1)*IFERROR(INDEX(Factors_ROT!$F$5:$F$200,MATCH("SC_FAT|"&AR34,Factors_ROT!$A$5:$A$200,0)),1) -> 0.98 | AX34: =AT34*AU34*AV34*AW34 -> 0.98 | AY34: =IF(ISNUMBER(AB34),AB34/AX34,"") -> 29591.837 | AZ34: =IFERROR(IF(N(INDEX(Escalation_Index!$B$5:$B$25,MATCH(Y34,Escalation_Index!$A$5:$A$25,0)))>0,INDEX(Escalation_Index!$B$5:$B$25,MATCH(Y34,Escalation_Index!$A$5:$A$25,0)),""),"") -> 119.251 | BA34: =IF(ISNUMBER('Assumptions & FX Reference'!$I$12),'Assumptions & FX Reference'!$I$12,"") -> 123.416 | BB34: =IF(AND(M34="API 610",LEFT(V34,11)="Centrifugal",OR(LEFT(G34,2)="S-",LEFT(G34,2)="D-")),"Y","N") -> N | BC34: =IF(ISNUMBER(AG34),AG34/AX34,"") -> 30625.371 | BD34: =IF(AND(ISNUMBER(BC34),ISNUMBER(K34)),IF(K34>0,BC34/K34^'Assumptions & FX Reference'!$I$16,""),"") -> 44324.628 | BE34: File PEP-Rev 140205 Gachsaran 4.xlsx, sheet 'P.ME', cells A53:H53 (service in D, spec in E, unit price in H) | BF34: Type: Centrifugal (API 610) | Driver: موتور الکتریکی (E) | Power: 0.54 kW | مشخصات کاتالوگی: 11m3/hr, 1.8 bar, 0.54 kw | Original type text: Centrifugal (assumed) | GCH4 review 1405-07: Source IRR = EUR 29,000 × 1.085 × 420,000 (P.ME H53); previous bank stored the IRR figure as 1399 IRR, which overstated EUR ≈2.6× | BG34: Y | BH34: PMP | BI34: ="PMP-"&TEXT(A34,"0000") -> PMP-0030
A35: 31 | B35: RECOVERED WASTE OIL PUMPS | C35: Gachsaran 4 | D35: P-704-A/B | E35: ROT-DRN | F35: Not stated | G35: Not stated | H35: 11 | J35: 0.8 | K35: =IF(ISNUMBER(J35),J35,IF(AND(ISNUMBER(H35),ISNUMBER(I35)),H35*I35/(367*'Assumptions & FX Reference'!$I$17),"")) -> 0.8 | L35: =IF(IF(OR(M35="Not stated",M35=""),""," + "&M35)&IF(OR(N35="None",N35=""),""," + "&N35)&IF(O35="Y"," + NACE MR0175","")="","Not stated",MID(IF(OR(M35="Not stated",M35=""),""," + "&M35)&IF(OR(N35="None",N35=""),""," + "&N35)&IF(O35="Y"," + NACE MR0175",""),4,300)) -> Not stated | M35: Not stated | N35: None | O35: Not stated | P35: Not stated | Q35: Not stated | R35: Not stated | S35: Electric Motor | T35: Slop / Dirty Oil | U35: 2 | V35: Centrifugal | W35: 2.7 | X35: Not stated | Y35: 1402 | Z35: EUR | AA35: 35000 | AB35: =IF(NOT(ISNUMBER(AA35)),"",IF(NOT(ISNUMBER(Y35)),"",IFERROR(IF(Z35="EUR",AA35,IF(Z35="IRR",AA35/INDEX('Assumptions & FX Reference'!$C$5:$C$25,MATCH(Y35,'Assumptions & FX Reference'!$A$5:$A$25,0)),IF(Z35="USD",AA35*INDEX('Assumptions & FX Reference'!$B$5:$B$25,MATCH(Y35,'Assumptions & FX Reference'!$A$5:$A$25,0))/INDEX('Assumptions & FX Reference'!$C$5:$C$25,MATCH(Y35,'Assumptions & FX Reference'!$A$5:$A$25,0)),""))),""))) -> 35000 | AC35: =IF(NOT(ISNUMBER(AA35)),"",IF(NOT(ISNUMBER(Y35)),"",IFERROR(IF(Z35="USD",AA35,IF(Z35="IRR",AA35/INDEX('Assumptions & FX Reference'!$B$5:$B$25,MATCH(Y35,'Assumptions & FX Reference'!$A$5:$A$25,0)),IF(Z35="EUR",AA35*INDEX('Assumptions & FX Reference'!$C$5:$C$25,MATCH(Y35,'Assumptions & FX Reference'!$A$5:$A$25,0))/INDEX('Assumptions & FX Reference'!$B$5:$B$25,MATCH(Y35,'Assumptions & FX Reference'!$A$5:$A$25,0)),""))),""))) -> 44125 | AD35: =IF(NOT(ISNUMBER(AA35)),"",IF(NOT(ISNUMBER(Y35)),"",IFERROR(IF(Z35="IRR",AA35,IF(Z35="USD",AA35*INDEX('Assumptions & FX Reference'!$B$5:$B$25,MATCH(Y35,'Assumptions & FX Reference'!$A$5:$A$25,0)),IF(Z35="EUR",AA35*INDEX('Assumptions & FX Reference'!$C$5:$C$25,MATCH(Y35,'Assumptions & FX Reference'!$A$5:$A$25,0)),""))),""))) -> 18532500000 | AE35: Consultant basic-design estimate – PEP Rev.1402/05, sheet P.ME «هزینه واحد بدون ضریب»; EUR figure (converted in the PEP at 420,000×1.085 IRR/EUR) | source label: AACE Class 2 | AF35: EXW | AG35: =IF(AND(Z35="EUR",N(AA35)>5000000),"",IF(AND(ISNUMBER(AB35),ISNUMBER(AZ35),ISNUMBER(BA35)),IF(AND(BB35="Y",ISNUMBER('Assumptions & FX Reference'!$I$15)),MAX(AB35*BA35/AZ35,'Assumptions & FX Reference'!$I$13*BA35/'Assumptions & FX Reference'!$I$15),AB35*BA35/AZ35),"")) -> 36222.422 | AH35: =IF(AND(ISNUMBER(AG35),ISNUMBER('Assumptions & FX Reference'!$I$8),ISNUMBER('Assumptions & FX Reference'!$I$11)),AG35*'Assumptions & FX Reference'!$I$8/'Assumptions & FX Reference'!$I$11,"") -> 38243.02 | AI35: =IF(AND(ISNUMBER(AG35),ISNUMBER('Assumptions & FX Reference'!$I$8)),AG35*'Assumptions & FX Reference'!$I$8,"") -> 2.5184291e+10 | AJ35: (Gachsaran 4 Basic Design MTO) | AK35: Basic Design | AL35: Not stated | AM35: Not stated | AN35: Not stated | AO35: N | AP35: N | AQ35: N | AR35: Not stated | AS35: =IF(AND(Z35="EUR",N(AA35)>5000000),"Check currency (EUR>5M); ","")&IF(NOT(ISNUMBER(AA35)),"No price; ","")&IF(G35="Not stated","Material missing; ","")&IF(P35="Not stated","Seal missing; ","")&IF(K35="","Size driver missing; ","")&IF(NOT(ISNUMBER(AZ35)),"Base-year PPI missing; ","") -> Material missing; Seal missing; | AT35: =IFERROR(INDEX(Factors_ROT!$F$5:$F$200,MATCH("MAT|"&G35,Factors_ROT!$A$5:$A$200,0)),1) -> 1 | AU35: =IFERROR(INDEX(Factors_ROT!$F$5:$F$200,MATCH("SEAL_ARR|"&P35,Factors_ROT!$A$5:$A$200,0)),1)*IFERROR(INDEX(Factors_ROT!$F$5:$F$200,MATCH("SEAL_CAT|"&Q35,Factors_ROT!$A$5:$A$200,0)),1)*IFERROR(INDEX(Factors_ROT!$F$5:$F$200,MATCH("SEAL_PLAN|"&R35,Factors_ROT!$A$5:$A$200,0)),1) -> 1 | AV35: =IFERROR(INDEX(Factors_ROT!$F$5:$F$200,MATCH("DRV|"&S35,Factors_ROT!$A$5:$A$200,0)),1)*IFERROR(INDEX(Factors_ROT!$F$5:$F$200,MATCH("NACE|"&O35,Factors_ROT!$A$5:$A$200,0)),1) -> 1 | AW35: =IFERROR(INDEX(Factors_ROT!$F$5:$F$200,MATCH("SC_DRV|"&AL35,Factors_ROT!$A$5:$A$200,0)),1)*IFERROR(INDEX(Factors_ROT!$F$5:$F$200,MATCH("SC_BSP|"&AM35,Factors_ROT!$A$5:$A$200,0)),1)*IFERROR(INDEX(Factors_ROT!$F$5:$F$200,MATCH("SC_SEAL|"&AN35,Factors_ROT!$A$5:$A$200,0)),1)*IFERROR(INDEX(Factors_ROT!$F$5:$F$200,MATCH("SC_COMM|"&AO35,Factors_ROT!$A$5:$A$200,0)),1)*IFERROR(INDEX(Factors_ROT!$F$5:$F$200,MATCH("SC_2Y|"&AP35,Factors_ROT!$A$5:$A$200,0)),1)*IFERROR(INDEX(Factors_ROT!$F$5:$F$200,MATCH("SC_TPI|"&AQ35,Factors_ROT!$A$5:$A$200,0)),1)*IFERROR(INDEX(Factors_ROT!$F$5:$F$200,MATCH("SC_FAT|"&AR35,Factors_ROT!$A$5:$A$200,0)),1) -> 0.98 | AX35: =AT35*AU35*AV35*AW35 -> 0.98 | AY35: =IF(ISNUMBER(AB35),AB35/AX35,"") -> 35714.286 | AZ35: =IFERROR(IF(N(INDEX(Escalation_Index!$B$5:$B$25,MATCH(Y35,Escalation_Index!$A$5:$A$25,0)))>0,INDEX(Escalation_Index!$B$5:$B$25,MATCH(Y35,Escalation_Index!$A$5:$A$25,0)),""),"") -> 119.251 | BA35: =IF(ISNUMBER('Assumptions & FX Reference'!$I$12),'Assumptions & FX Reference'!$I$12,"") -> 123.416 | BB35: =IF(AND(M35="API 610",LEFT(V35,11)="Centrifugal",OR(LEFT(G35,2)="S-",LEFT(G35,2)="D-")),"Y","N") -> N | BC35: =IF(ISNUMBER(AG35),AG35/AX35,"") -> 36961.655 | BD35: =IF(AND(ISNUMBER(BC35),ISNUMBER(K35)),IF(K35>0,BC35/K35^'Assumptions & FX Reference'!$I$16,""),"") -> 42256.879 | BE35: File PEP-Rev 140205 Gachsaran 4.xlsx, sheet 'P.ME', cells A54:H54 (service in D, spec in E, unit price in H) | BF35: Type: Centrifugal (API 610) | Driver: موتور الکتریکی (E) | Power: 0.8 kW | NACE MR0175: YES | مشخصات کاتالوگی: 11 m3/hr, 2.7 bar, 0.8 kw | Original type text: Centrifugal (assumed) | GCH4 review 1405-07: Source IRR = EUR 35,000 × 1.085 × 420,000 (P.ME H54); previous bank stored the IRR figure as 1399 IRR, which overstated EUR ≈2.6× | BG35: Y | BH35: PMP | BI35: ="PMP-"&TEXT(A35,"0000") -> PMP-0031
A36: 32 | B36: OILY WATER SEPARATOR PUMP | C36: Gachsaran 4 | D36: P-750 | E36: ROT-DRN | F36: Not stated | G36: Not stated | H36: 1 | J36: 0.02 | K36: =IF(ISNUMBER(J36),J36,IF(AND(ISNUMBER(H36),ISNUMBER(I36)),H36*I36/(367*'Assumptions & FX Reference'!$I$17),"")) -> 0.02 | L36: =IF(IF(OR(M36="Not stated",M36=""),""," + "&M36)&IF(OR(N36="None",N36=""),""," + "&N36)&IF(O36="Y"," + NACE MR0175","")="","Not stated",MID(IF(OR(M36="Not stated",M36=""),""," + "&M36)&IF(OR(N36="None",N36=""),""," + "&N36)&IF(O36="Y"," + NACE MR0175",""),4,300)) -> Not stated | M36: Not stated | N36: None | O36: Not stated | P36: Not stated | Q36: Not stated | R36: Not stated | S36: Electric Motor | T36: Oily Water / Drain | U36: 1 | V36: Centrifugal | W36: 0.84 | X36: Not stated | Y36: 1402 | Z36: EUR | AA36: 13350 | AB36: =IF(NOT(ISNUMBER(AA36)),"",IF(NOT(ISNUMBER(Y36)),"",IFERROR(IF(Z36="EUR",AA36,IF(Z36="IRR",AA36/INDEX('Assumptions & FX Reference'!$C$5:$C$25,MATCH(Y36,'Assumptions & FX Reference'!$A$5:$A$25,0)),IF(Z36="USD",AA36*INDEX('Assumptions & FX Reference'!$B$5:$B$25,MATCH(Y36,'Assumptions & FX Reference'!$A$5:$A$25,0))/INDEX('Assumptions & FX Reference'!$C$5:$C$25,MATCH(Y36,'Assumptions & FX Reference'!$A$5:$A$25,0)),""))),""))) -> 13350 | AC36: =IF(NOT(ISNUMBER(AA36)),"",IF(NOT(ISNUMBER(Y36)),"",IFERROR(IF(Z36="USD",AA36,IF(Z36="IRR",AA36/INDEX('Assumptions & FX Reference'!$B$5:$B$25,MATCH(Y36,'Assumptions & FX Reference'!$A$5:$A$25,0)),IF(Z36="EUR",AA36*INDEX('Assumptions & FX Reference'!$C$5:$C$25,MATCH(Y36,'Assumptions & FX Reference'!$A$5:$A$25,0))/INDEX('Assumptions & FX Reference'!$B$5:$B$25,MATCH(Y36,'Assumptions & FX Reference'!$A$5:$A$25,0)),""))),""))) -> 16830.536 | AD36: =IF(NOT(ISNUMBER(AA36)),"",IF(NOT(ISNUMBER(Y36)),"",IFERROR(IF(Z36="IRR",AA36,IF(Z36="USD",AA36*INDEX('Assumptions & FX Reference'!$B$5:$B$25,MATCH(Y36,'Assumptions & FX Reference'!$A$5:$A$25,0)),IF(Z36="EUR",AA36*INDEX('Assumptions & FX Reference'!$C$5:$C$25,MATCH(Y36,'Assumptions & FX Reference'!$A$5:$A$25,0)),""))),""))) -> 7068825000 | AE36: Consultant basic-design estimate – PEP Rev.1402/05, sheet P.ME «هزینه واحد بدون ضریب»; EUR figure (converted in the PEP at 420,000×1.085 IRR/EUR) | source label: AACE Class 2 | AF36: EXW | AG36: =IF(AND(Z36="EUR",N(AA36)>5000000),"",IF(AND(ISNUMBER(AB36),ISNUMBER(AZ36),ISNUMBER(BA36)),IF(AND(BB36="Y",ISNUMBER('Assumptions & FX Reference'!$I$15)),MAX(AB36*BA36/AZ36,'Assumptions & FX Reference'!$I$13*BA36/'Assumptions & FX Reference'!$I$15),AB36*BA36/AZ36),"")) -> 13816.267 | AH36: =IF(AND(ISNUMBER(AG36),ISNUMBER('Assumptions & FX Reference'!$I$8),ISNUMBER('Assumptions & FX Reference'!$I$11)),AG36*'Assumptions & FX Reference'!$I$8/'Assumptions & FX Reference'!$I$11,"") -> 14586.98 | AI36: =IF(AND(ISNUMBER(AG36),ISNUMBER('Assumptions & FX Reference'!$I$8)),AG36*'Assumptions & FX Reference'!$I$8,"") -> 9.606008e+09 | AJ36: (Gachsaran 4 Basic Design MTO) | AK36: Basic Design | AL36: Not stated | AM36: Not stated | AN36: Not stated | AO36: N | AP36: N | AQ36: N | AR36: Not stated | AS36: =IF(AND(Z36="EUR",N(AA36)>5000000),"Check currency (EUR>5M); ","")&IF(NOT(ISNUMBER(AA36)),"No price; ","")&IF(G36="Not stated","Material missing; ","")&IF(P36="Not stated","Seal missing; ","")&IF(K36="","Size driver missing; ","")&IF(NOT(ISNUMBER(AZ36)),"Base-year PPI missing; ","") -> Material missing; Seal missing; | AT36: =IFERROR(INDEX(Factors_ROT!$F$5:$F$200,MATCH("MAT|"&G36,Factors_ROT!$A$5:$A$200,0)),1) -> 1 | AU36: =IFERROR(INDEX(Factors_ROT!$F$5:$F$200,MATCH("SEAL_ARR|"&P36,Factors_ROT!$A$5:$A$200,0)),1)*IFERROR(INDEX(Factors_ROT!$F$5:$F$200,MATCH("SEAL_CAT|"&Q36,Factors_ROT!$A$5:$A$200,0)),1)*IFERROR(INDEX(Factors_ROT!$F$5:$F$200,MATCH("SEAL_PLAN|"&R36,Factors_ROT!$A$5:$A$200,0)),1) -> 1 | AV36: =IFERROR(INDEX(Factors_ROT!$F$5:$F$200,MATCH("DRV|"&S36,Factors_ROT!$A$5:$A$200,0)),1)*IFERROR(INDEX(Factors_ROT!$F$5:$F$200,MATCH("NACE|"&O36,Factors_ROT!$A$5:$A$200,0)),1) -> 1 | AW36: =IFERROR(INDEX(Factors_ROT!$F$5:$F$200,MATCH("SC_DRV|"&AL36,Factors_ROT!$A$5:$A$200,0)),1)*IFERROR(INDEX(Factors_ROT!$F$5:$F$200,MATCH("SC_BSP|"&AM36,Factors_ROT!$A$5:$A$200,0)),1)*IFERROR(INDEX(Factors_ROT!$F$5:$F$200,MATCH("SC_SEAL|"&AN36,Factors_ROT!$A$5:$A$200,0)),1)*IFERROR(INDEX(Factors_ROT!$F$5:$F$200,MATCH("SC_COMM|"&AO36,Factors_ROT!$A$5:$A$200,0)),1)*IFERROR(INDEX(Factors_ROT!$F$5:$F$200,MATCH("SC_2Y|"&AP36,Factors_ROT!$A$5:$A$200,0)),1)*IFERROR(INDEX(Factors_ROT!$F$5:$F$200,MATCH("SC_TPI|"&AQ36,Factors_ROT!$A$5:$A$200,0)),1)*IFERROR(INDEX(Factors_ROT!$F$5:$F$200,MATCH("SC_FAT|"&AR36,Factors_ROT!$A$5:$A$200,0)),1) -> 0.98 | AX36: =AT36*AU36*AV36*AW36 -> 0.98 | AY36: =IF(ISNUMBER(AB36),AB36/AX36,"") -> 13622.449 | AZ36: =IFERROR(IF(N(INDEX(Escalation_Index!$B$5:$B$25,MATCH(Y36,Escalation_Index!$A$5:$A$25,0)))>0,INDEX(Escalation_Index!$B$5:$B$25,MATCH(Y36,Escalation_Index!$A$5:$A$25,0)),""),"") -> 119.251 | BA36: =IF(ISNUMBER('Assumptions & FX Reference'!$I$12),'Assumptions & FX Reference'!$I$12,"") -> 123.416 | BB36: =IF(AND(M36="API 610",LEFT(V36,11)="Centrifugal",OR(LEFT(G36,2)="S-",LEFT(G36,2)="D-")),"Y","N") -> N | BC36: =IF(ISNUMBER(AG36),AG36/AX36,"") -> 14098.231 | BD36: =IF(AND(ISNUMBER(BC36),ISNUMBER(K36)),IF(K36>0,BC36/K36^'Assumptions & FX Reference'!$I$16,""),"") -> 147416.68 | BE36: File PEP-Rev 140205 Gachsaran 4.xlsx, sheet 'P.ME', cells A55:H55 (service in D, spec in E, unit price in H) | BF36: Type: Centrifugal (API 610) | Driver: موتور الکتریکی (E) | Power: 0.02 kW | مشخصات کاتالوگی: 1m3/hr, 0.84 bar, 0.02kw | Original type text: Centrifugal (assumed) | GCH4 review 1405-07: Source IRR = EUR 13,350 × 1.085 × 420,000 (P.ME H55); previous bank stored the IRR figure as 1399 IRR, which overstated EUR ≈2.6× | BG36: Y | BH36: PMP | BI36: ="PMP-"&TEXT(A36,"0000") -> PMP-0032
A37: 33 | B37: DIRTY OIL PUMPS | C37: Gachsaran 4 | D37: P-705-A/B | E37: ROT-DRN | F37: Not stated | G37: Not stated | H37: 5 | J37: 0.3 | K37: =IF(ISNUMBER(J37),J37,IF(AND(ISNUMBER(H37),ISNUMBER(I37)),H37*I37/(367*'Assumptions & FX Reference'!$I$17),"")) -> 0.3 | L37: =IF(IF(OR(M37="Not stated",M37=""),""," + "&M37)&IF(OR(N37="None",N37=""),""," + "&N37)&IF(O37="Y"," + NACE MR0175","")="","Not stated",MID(IF(OR(M37="Not stated",M37=""),""," + "&M37)&IF(OR(N37="None",N37=""),""," + "&N37)&IF(O37="Y"," + NACE MR0175",""),4,300)) -> Not stated | M37: Not stated | N37: None | O37: Not stated | P37: Not stated | Q37: Not stated | R37: Not stated | S37: Electric Motor | T37: Slop / Dirty Oil | U37: 2 | V37: Centrifugal | W37: 2 | X37: Not stated | Y37: 1402 | Z37: EUR | AA37: 31000 | AB37: =IF(NOT(ISNUMBER(AA37)),"",IF(NOT(ISNUMBER(Y37)),"",IFERROR(IF(Z37="EUR",AA37,IF(Z37="IRR",AA37/INDEX('Assumptions & FX Reference'!$C$5:$C$25,MATCH(Y37,'Assumptions & FX Reference'!$A$5:$A$25,0)),IF(Z37="USD",AA37*INDEX('Assumptions & FX Reference'!$B$5:$B$25,MATCH(Y37,'Assumptions & FX Reference'!$A$5:$A$25,0))/INDEX('Assumptions & FX Reference'!$C$5:$C$25,MATCH(Y37,'Assumptions & FX Reference'!$A$5:$A$25,0)),""))),""))) -> 31000 | AC37: =IF(NOT(ISNUMBER(AA37)),"",IF(NOT(ISNUMBER(Y37)),"",IFERROR(IF(Z37="USD",AA37,IF(Z37="IRR",AA37/INDEX('Assumptions & FX Reference'!$B$5:$B$25,MATCH(Y37,'Assumptions & FX Reference'!$A$5:$A$25,0)),IF(Z37="EUR",AA37*INDEX('Assumptions & FX Reference'!$C$5:$C$25,MATCH(Y37,'Assumptions & FX Reference'!$A$5:$A$25,0))/INDEX('Assumptions & FX Reference'!$B$5:$B$25,MATCH(Y37,'Assumptions & FX Reference'!$A$5:$A$25,0)),""))),""))) -> 39082.143 | AD37: =IF(NOT(ISNUMBER(AA37)),"",IF(NOT(ISNUMBER(Y37)),"",IFERROR(IF(Z37="IRR",AA37,IF(Z37="USD",AA37*INDEX('Assumptions & FX Reference'!$B$5:$B$25,MATCH(Y37,'Assumptions & FX Reference'!$A$5:$A$25,0)),IF(Z37="EUR",AA37*INDEX('Assumptions & FX Reference'!$C$5:$C$25,MATCH(Y37,'Assumptions & FX Reference'!$A$5:$A$25,0)),""))),""))) -> 16414500000 | AE37: Consultant basic-design estimate – PEP Rev.1402/05, sheet P.ME «هزینه واحد بدون ضریب»; EUR figure (converted in the PEP at 420,000×1.085 IRR/EUR) | source label: AACE Class 2 | AF37: EXW | AG37: =IF(AND(Z37="EUR",N(AA37)>5000000),"",IF(AND(ISNUMBER(AB37),ISNUMBER(AZ37),ISNUMBER(BA37)),IF(AND(BB37="Y",ISNUMBER('Assumptions & FX Reference'!$I$15)),MAX(AB37*BA37/AZ37,'Assumptions & FX Reference'!$I$13*BA37/'Assumptions & FX Reference'!$I$15),AB37*BA37/AZ37),"")) -> 32082.716 | AH37: =IF(AND(ISNUMBER(AG37),ISNUMBER('Assumptions & FX Reference'!$I$8),ISNUMBER('Assumptions & FX Reference'!$I$11)),AG37*'Assumptions & FX Reference'!$I$8/'Assumptions & FX Reference'!$I$11,"") -> 33872.389 | AI37: =IF(AND(ISNUMBER(AG37),ISNUMBER('Assumptions & FX Reference'!$I$8)),AG37*'Assumptions & FX Reference'!$I$8,"") -> 2.2306086e+10 | AJ37: (Gachsaran 4 Basic Design MTO) | AK37: Basic Design | AL37: Not stated | AM37: Not stated | AN37: Not stated | AO37: N | AP37: N | AQ37: N | AR37: Not stated | AS37: =IF(AND(Z37="EUR",N(AA37)>5000000),"Check currency (EUR>5M); ","")&IF(NOT(ISNUMBER(AA37)),"No price; ","")&IF(G37="Not stated","Material missing; ","")&IF(P37="Not stated","Seal missing; ","")&IF(K37="","Size driver missing; ","")&IF(NOT(ISNUMBER(AZ37)),"Base-year PPI missing; ","") -> Material missing; Seal missing; | AT37: =IFERROR(INDEX(Factors_ROT!$F$5:$F$200,MATCH("MAT|"&G37,Factors_ROT!$A$5:$A$200,0)),1) -> 1 | AU37: =IFERROR(INDEX(Factors_ROT!$F$5:$F$200,MATCH("SEAL_ARR|"&P37,Factors_ROT!$A$5:$A$200,0)),1)*IFERROR(INDEX(Factors_ROT!$F$5:$F$200,MATCH("SEAL_CAT|"&Q37,Factors_ROT!$A$5:$A$200,0)),1)*IFERROR(INDEX(Factors_ROT!$F$5:$F$200,MATCH("SEAL_PLAN|"&R37,Factors_ROT!$A$5:$A$200,0)),1) -> 1 | AV37: =IFERROR(INDEX(Factors_ROT!$F$5:$F$200,MATCH("DRV|"&S37,Factors_ROT!$A$5:$A$200,0)),1)*IFERROR(INDEX(Factors_ROT!$F$5:$F$200,MATCH("NACE|"&O37,Factors_ROT!$A$5:$A$200,0)),1) -> 1 | AW37: =IFERROR(INDEX(Factors_ROT!$F$5:$F$200,MATCH("SC_DRV|"&AL37,Factors_ROT!$A$5:$A$200,0)),1)*IFERROR(INDEX(Factors_ROT!$F$5:$F$200,MATCH("SC_BSP|"&AM37,Factors_ROT!$A$5:$A$200,0)),1)*IFERROR(INDEX(Factors_ROT!$F$5:$F$200,MATCH("SC_SEAL|"&AN37,Factors_ROT!$A$5:$A$200,0)),1)*IFERROR(INDEX(Factors_ROT!$F$5:$F$200,MATCH("SC_COMM|"&AO37,Factors_ROT!$A$5:$A$200,0)),1)*IFERROR(INDEX(Factors_ROT!$F$5:$F$200,MATCH("SC_2Y|"&AP37,Factors_ROT!$A$5:$A$200,0)),1)*IFERROR(INDEX(Factors_ROT!$F$5:$F$200,MATCH("SC_TPI|"&AQ37,Factors_ROT!$A$5:$A$200,0)),1)*IFERROR(INDEX(Factors_ROT!$F$5:$F$200,MATCH("SC_FAT|"&AR37,Factors_ROT!$A$5:$A$200,0)),1) -> 0.98 | AX37: =AT37*AU37*AV37*AW37 -> 0.98 | AY37: =IF(ISNUMBER(AB37),AB37/AX37,"") -> 31632.653 | AZ37: =IFERROR(IF(N(INDEX(Escalation_Index!$B$5:$B$25,MATCH(Y37,Escalation_Index!$A$5:$A$25,0)))>0,INDEX(Escalation_Index!$B$5:$B$25,MATCH(Y37,Escalation_Index!$A$5:$A$25,0)),""),"") -> 119.251 | BA37: =IF(ISNUMBER('Assumptions & FX Reference'!$I$12),'Assumptions & FX Reference'!$I$12,"") -> 123.416 | BB37: =IF(AND(M37="API 610",LEFT(V37,11)="Centrifugal",OR(LEFT(G37,2)="S-",LEFT(G37,2)="D-")),"Y","N") -> N | BC37: =IF(ISNUMBER(AG37),AG37/AX37,"") -> 32737.466 | BD37: =IF(AND(ISNUMBER(BC37),ISNUMBER(K37)),IF(K37>0,BC37/K37^'Assumptions & FX Reference'!$I$16,""),"") -> 67417.447 | BE37: File PEP-Rev 140205 Gachsaran 4.xlsx, sheet 'P.ME', cells A57:H57 (service in D, spec in E, unit price in H) | BF37: Type: Centrifugal (API 610) | Driver: موتور الکتریکی (E) | Power: 0.3 kW | NACE MR0175: YES | مشخصات کاتالوگی: 5m3/hr, 2bar, 0.3 kw | Original type text: Centrifugal (assumed) | GCH4 review 1405-07: Source IRR = EUR 31,000 × 1.085 × 420,000 (P.ME H57); previous bank stored the IRR figure as 1399 IRR, which overstated EUR ≈2.6× | BG37: Y | BH37: PMP | BI37: ="PMP-"&TEXT(A37,"0000") -> PMP-0033
