Workbook

Sheet COVER
H1: Modular Oil Treating And Desalting Unit
H2: Title:
H3: =A19 -> 0
A4: Page 1 of 12 | H4: Document No.: | AI4: Class: 3
AI5: REV. C
A10: Total Estimate Price (Euro)
E11: Vessels | L11: ='VESSELS(SEPARATOR)'!W18 -> 206652
E12: Tanks | L12: =TANKS!W23 -> 4355900
E13: DeSalters | L13: ='DESALTER PACKAGE'!Y22 -> 4001350
E14: Rotary | L14: =ROTARY!V30 -> 6170183
E15: Stack | L15: =STACK!Y20 -> 1114300
E16: H-EX & Heaters | L16: ='H-EX & HEATER'!Z20 -> 2743204
E17: Structures | L17: =STRUCTURE!Y20 -> 2127300
E18: Package | L18: =PACKAGE!S20 -> 2431200
E19: Civil Work | L19: ='Civil Work'!T20 -> 3536383
E20: Pipe & Fitting & Valves | L20: ='PIPE & FITTING & Valves'!Z21 -> 7212560
E21: E&I&C | L21: ='E&I&C'!Y21 -> 6977544
E22: Mob-Demobilization | L22: ='Mob-Demobilization'!F17 -> 2276262
E23: Engineering | L23: 4052000
E24: Machinery | L24: =Machinery!I19 -> 547172 | AK24: =55126279-L27 -> 0
E25: Salary & Accomodations | L25: ='employee Salary & Accomodation '!I6 -> 2722032
E26: Instrument & Control Room Systems | L26: ='Instruments , Power & CCR '!E18 -> 5368879
E27: TOTAL (Euro) | L27: =SUM(L11:AG26) -> 55842921 | AJ27: =L27-#REF! -> #REF!
A30: =L27*1.18 -> 65894646 | W30: USD
A34: C
A35: B
A36: A | C36: FEB. 2025 | H36: Issue for Comment | P36: E.P | W36: A.N | AE36: R.S | AL36: ---
A37: Rev | C37: Issue Date | H37: Status | P37: Prepared | W37: Checked | AE37: Approved | AL37: Client Approval

Sheet Insurance
E1: Total Estimate Price (Euro)
E2: Description | F2: Total Price (Euro) | H2: Insurance coefficient
E3: Vessels | F3: 206652 | G3: cons | H3: 0.1
E4: Tanks | F4: 4355900 | G4: cons | H4: 0.1
E5: DeSalters | F5: 4001350 | G5: cons | H5: 0.1
E6: Rotary | F6: 6170183 | G6: prc | H6: 0
E7: Stack | F7: 1114300 | G7: cons | H7: 0.1
E8: H-EX & Heaters | F8: 2743204 | G8: cons | H8: 0.1
E9: Structures | F9: 2127300 | G9: cons | H9: 0.1
E10: Package | F10: 2431200 | G10: cons | H10: 0.1
E11: Civil Work | F11: 3536383 | G11: cons | H11: 0.1
E12: Pipe & Fitting & Valves | F12: 7212560 | G12: prc- | H12: 0
E13: E&I&C | F13: 6977544 | G13: prc | H13: 0
E14: Mob-Demobilization | F14: 2276262 | G14: cons | H14: 0.1
E15: Engineering | F15: 4052000 | G15: HR | H15: 0.1667
E16: Machinery | F16: 547172 | G16: Rental | H16: 0.08 | AE16: 0
E17: Salary & Accomodations | F17: 2722032 | G17: HR | H17: 0.1667
E18: Instrument & Control Room Systems | F18: 5368879 | G18: prc | H18: 0
E19: TOTAL (Euro) | F19: =SUM(F3:F18) -> 55842921

Sheet VESSELS(SEPARATOR)
H1: Modular Oil Treating And Desalting Unit
H2: Title:
H3: Main Equipment List - Train No1
A4: Page 2 of 12 | H4: Document No.: | P4: =#NAME? -> #NAME?
P5: =#NAME? -> #NAME?
A7: ITEM NO. | D7: DESCRIPTION | J7: QTY | K7: FLUID CONTENT | L7: MATERIAL | M7: DIMENSION | N7: TEMP. | O7: PRESS. | P7: ORIENTATION | R7: REMARKS | S7: estimation price (euro) | T7: Nominal Weight (Kg) | U7: Unit Price (euro/kg) | V7: Overhead 30% | W7: Total Estimation Price (Euro/Kg)
N8: DESIGN (MAX) | O8: DESIGN (BARG)
A11: V-120 | D11: FUEL GAS K.O. DRUM | J11: 1 | K11: FUEL GAS | L11: SA 516 GR.70 | M11: ID x T/T: 800mm x 2350 mm | N11: 85 | O11: 5 | P11: VERTICAL | S11: =U11*T11 -> 11143 | T11: 2026 | U11: 5.5 | V11: 0.3
A12: V-140 | D12: AIR RECEIVER | J12: 1 | K12: AIR | L12: SA 516 GR.70 | M12: ID x T/T: 1800mm x 5400 mm | N12: 85 | O12: 10 | P12: VERTICAL | S12: =U12*T12 -> 39000 | T12: 7091 | U12: 5.5 | V12: 0.3
A13: V-160 | D13: FLARE K.O. DRUM | J13: 1 | K13: GAS | L13: SA 516 GR.70 | M13: ID x T/T: 2100mm x 4000 mm | N13: 85 | O13: 3.5 | P13: HORIZONTAL | S13: =U13*T13 -> 39000 | T13: 7091 | U13: 5.5 | V13: 0.3
A14: PK-141 A/B | D14: AIR DRYER PACKAGE | J14: 2 | K14: AIR | L14: SA 516 GR.70 | M14: WILL BE FINALIZED LATER | N14: 85 | O14: 10 | P14: VERTICAL | S14: =U14*T14 -> 27857 | T14: 5065 | U14: 5.5 | V14: 0.3
A15: CY-180A/B | D15: VESSEL | J15: 2 | K15: WATER/CRUDE | L15: SA 516 GR.70 | M15: 350mm x 1500mm | N15: WILL BE FINALIZED LATER | O15: 12.5 | P15: HORIZONTAL | S15: =U15*T15 -> 27857 | T15: 5065 | U15: 5.5 | V15: 0.3
A16: F-180 A/B | D16: WALNUT FILTER | J16: 2 | K16: OILY WATER | L16: SA 516 GR.70 | M16: ID x T/T: 2200mm x 2200 mm | N16: _ | O16: _ | P16: _ | S16: =U16*T16 -> 22286 | T16: 4052 | U16: 5.5 | V16: 0.3
A17: V-150 | D17: H/C CLOSED DRAIN VESSEL | J17: 1 | K17: CRUDE OIL | L17: SA 516 GR.70 | M17: ID x T/T: 2500mm x 6000 mm | N17: 85 | O17: 3.5 | P17: HORIZONTAL | S17: =U17*T17 -> 94715 | T17: 17221 | U17: 5.5 | V17: 0.3
A18: Installation Included | S18: =SUM(S11:S17) -> 261860 | V18: =S18*30/100 -> 78558 | W18: 206652
A20: NOTES:
I21: 1 - B.V.: BY VENDOR 2 - N.A.: NOT APPLICABLE 3 - ATM.: ATMOSPHERIC

Sheet TANKS
H1: Modular Oil Treating And Desalting Unit
H2: Title:
H3: Main Equipment List - Train No1
A4: Page 3 of 12 | H4: Document No.: | P4: =#NAME? -> #NAME?
P5: =#NAME? -> #NAME?
A7: ITEM NO. | D7: DESCRIPTION | J7: QTY | K7: FLUID CONTENT | L7: MATERIAL | M7: DIMENSION | N7: TEMP. | O7: PRESS. | P7: ORIENTATION | R7: REMARKS | S7: estimation price (euro) | T7: Nominal Weight (Kg) | U7: Unit Price (euro/kg) | V7: Overhead 30% | W7: Total Estimation Price (Euro/Kg)
N8: DESIGN (MAX) | O8: DESIGN (BARG)
A11: TK-110 | D11: DILUTION WATER TANK | J11: 1 | K11: WATER | L11: SA 516 GR.70 | M11: ID x HEIGHT: 8000mm x 10000 mm | N11: 85 | O11: -0.005/+0.17 | P11: VERTICAL | S11: 384727 | T11: 60780 | U11: 4.2 | V11: 0.3
A12: TK-130 | D12: FUEL OIL TANK | J12: 1 | K12: FUEL OIL | L12: SA 516 GR.70 | M12: ID x T/T: 2000mm x 3100 mm | N12: 85 | O12: ATM | P12: HORIZONTAL | S12: 53182 | T12: 4558 | U12: 4.2 | V12: 0.3
A13: TK-112 | D13: ELEVATED POTABLE WATER TANK | J13: 1 | K13: WATER | L13: SA 516 GR.70 | M13: ID x HEIGHT: 3500mm x 3500 mm | N13: 85 | O13: ATM | P13: VERTICAL | S13: 50650 | T13: 9623 | U13: 4.2 | V13: 0.3
A14: TK-190 | D14: FIRE WATER STORAGE TANK | J14: 1 | K14: WATER | L14: SA 516 GR.70 | M14: ID x HEIGHT: 14000mm x 12000 mm | N14: 85 | O14: ATM | P14: VERTICAL | S14: 638190 | T14: 91170 | U14: 4.2 | V14: 0.3
A15: TK-113 | D15: RAW WATER TANK | J15: 1 | K15: WATER | L15: SA 516 GR.70 | M15: ID x HEIGHT: 8000mm x 10000 mm | N15: 85 | O15: ATM | P15: VERTICAL | S15: 384829 | T15: 45585 | U15: 4.2 | V15: 0.3
A16: TK-100 | D16: DEGASSING TANK | J16: 1 | K16: OIL/GAS/ WATER | L16: SA 516 GR.70 | M16: ID x HEIGHT: 12500mm x 12000 mm | N16: 85 | O16: -0.005~0.22 | P16: VERTICAL | S16: 561607 | T16: 89144 | U16: 4.2 | V16: 0.3
A17: TK-195 | D17: SKIMMER TANK | J17: 1 | K17: CRUDE / OILY WATER | L17: SA 516 GR.70 | M17: ID x HEIGHT: 10000mm x 5000 mm | N17: 85 | O17: -0.005/+0.17 | P17: VERTICAL | S17: 351004 | T17: 55715 | U17: 4.2 | V17: 0.3
A18: TK-170 | D18: DIRTY OIL TANK | J18: 1 | K18: CRUDE OIL | L18: SA 516 GR.70 | M18: ID x HEIGHT: 3000mm x 2000 mm | N18: 85 | O18: -0.005/+0.17 | P18: VERTICAL | S18: 5065 | T18: 20260 | U18: 4.2 | V18: 0.3
A19: TK-180 | D19: DISPOSAL TANK | J19: 1 | K19: OILY WATER | L19: SA 516 GR.70 | M19: ID x HEIGHT: 8000mm x 10000 mm | N19: 85 | O19: -0.005/+0.17 | P19: VERTICAL | S19: 384829 | T19: 60780 | U19: 4.2 | V19: 0.3
A20: SU-150 | D20: H/C CLOSE DRAIN SUMP | J20: 1 | K20: OILY WATER | L20: WILL BE FINALIZED LATER | M20: 10000x15000x4000 mm | N20: _ | O20: ATM | P20: _ | S20: 638190 | T20: 101300 | U20: 4.2 | V20: 0.3
A21: TK-101 | D21: OFF SPEC. TANK | J21: 1 | K21: CRUDE OIL | L21: SA 516 GR.70 | M21: ID x HEIGHT: 14000mm x 12000 mm | N21: 85 | O21: -0.005/+0.17 | P21: VERTICAL | S21: 638190 | T21: 121560 | U21: 4.2 | V21: 0.3
B22: Installation Included
A23: NOTES: | S23: 4355900 | T23: =SUM(T11:T21) -> 660476 | V23: =V21*S23 -> 1306770 | W23: 4355900
I24: 1 - B.V.: BY VENDOR 2 - N.A.: NOT APPLICABLE 3 - ATM.: ATMOSPHERIC

Sheet DESALTER PACKAGE
H1: Modular Oil Treating And Desalting Unit
H2: Title:
H3: Main Equipment List - Train No1
A4: Page 4 of 12 | H4: Document No.: | R4: =#NAME? -> #NAME?
R5: =#NAME? -> #NAME?
A7: ITEM NO. | D7: DESCRIPTION | J7: QTY | K7: FLUID CONTENT | L7: TYPE | M7: MATERIAL | N7: DIMENSION ID x T/T: | O7: PRESS. | P7: TEMP. | R7: ORIENTATION | T7: REMARKS | U7: estimation price (euro) | V7: Nominal Weight (Kg) | W7: Unit Price (euro/kg) | X7: Overhead 30% | Y7: Total Estimation Price (Euro/Kg)
O8: DESIGN (BARG) | P8: DESIGN
A11: D-100 | D11: DESALTER | J11: 1 | K11: CRUDE OIL | L11: _ | M11: SA 516 GR.70 | N11: 3658x 13717 | O11: 14 | P11: 85 | R11: HORZINTAL | U11: =W11*V11 -> 729360 | V11: 60780 | W11: 12 | X11: 0.3
A12: D-101 | D12: DESALTER | J12: 1 | K12: CRUDE OIL | L12: _ | M12: SA 516 GR.70 | N12: 3658x 13717 | O12: 14 | P12: 85 | R12: HORZINTAL | U12: =W12*V12 -> 729360 | V12: 60780 | W12: 12 | X12: 0.3
D13: Internals & Transformators | J13: 1 | U13: 2532500
D14: Desalter Installation | J14: 1 | U14: 322557
A20: NOTES:
I21: 1 - B.V.: BY VENDOR 2 - N.A.: NOT APPLICABLE 3 - ATM.: ATMOSPHERIC
U22: 4001350 | V22: =SUM(V11:V21) -> 121560 | X22: =X12*U22 -> 1200405 | Y22: =U22 -> 4001350

Sheet ROTARY
H1: Modular Oil Treating And Desalting Unit
H2: Title:
H3: Main Equipment List - Train No1
A4: Page 5 of 12 | H4: Document No.: | P4: =#NAME? -> #NAME?
P5: =#NAME? -> #NAME?
A7: ITEM NO. | D7: DESCRIPTION | J7: QTY | K7: FLUID CONTENT | L7: MATERIAL | M7: DIMENSION | N7: CAPACITY | O7: DIFF PRESS. | P7: ORIENTATION | R7: REMARKS | S7: estimation price (euro/Unit) | T7: Total Price (Euro) | U7: Overhead 30% | V7: Total Estimation Price (Euro/Kg)
O8: (BARG)
A11: P-110 A/B | D11: DILUTION WATER PUMP | J11: 3 | K11: WATER | L11: CASING:CAST IRON SHAFT:S.S MARTENSITE (TCV) | M11: B.V | N11: 20.5 M3/HR | O11: 11.6 | P11: _ | S11: 45585 | T11: =S11*J11 -> 136755 | U11: 0.6
A12: P-130 | D12: FUEL OIL LOADING & UNLOADING PUMP | J12: 2 | K12: FUEL OIL | L12: CASING:CAST IRON SHAFT:S.S MARTENSITE (TCV) | M12: B.V | N12: 10 M3/HR | O12: 1.5 | P12: _ | S12: 25325 | T12: =S12*J12 -> 50650 | U12: 0.6
A13: PK-140 A/B | D13: AIR COMPRESSOR PACKAGE | J13: 3 | K13: AIR | L13: B.V | M13: B.V | N13: 200 SM3/HR | O13: 8 | P13: _ | S13: 111430 | T13: =S13*J13 -> 334290 | U13: 0.6
A14: P-115 A/B/C | D14: RAW WATER MAIN PUMPS | J14: 4 | K14: WATER | L14: CASING:CAST IRON SHAFT:S.S MARTENSITE (TCV) | M14: B.V | N14: 25 M3/HR | O14: 77 | P14: _ | S14: 91170 | T14: =S14*J14 -> 364680 | U14: 0.6
A15: P-120 A/B/C | D15: RAW WATER PUMPS | J15: 4 | K15: WATER | L15: CASING:CAST IRON SHAFT:S.S MARTENSITE (TCV) | M15: B.V | N15: 250 M3/HR | O15: 58 | P15: 151950 | S15: 607800 | T15: =S15*J15 -> 2431200 | U15: 0.6
A16: P-102 A/B | D16: FREE WATER TRANSFER PUMPS | J16: 3 | K16: WATER | L16: CASING:CAST IRON SHAFT:S.S MARTENSITE (TCV) | M16: B.V | N16: 22.3 M3/HR | O16: 24 | P16: _ | S16: 70910 | T16: =S16*J16 -> 212730 | U16: 0.6
D17: AIR SMOKELESS (FAN BLOWER) | J17: 2 | S17: 20260 | T17: =S17*J17 -> 40520 | U17: 0.6
A18: P-101 A/B | D18: RECYCLE PUMPS | J18: 3 | K18: WATER | L18: CASING:CAST IRON SHAFT:S.S MARTENSITE (TCV) | M18: B.V | N18: 21 M3/HR | O18: 4.3 | S18: 25325 | T18: =S18*J18 -> 75975 | U18: 0.6
A19: P-180 A/B | D19: WATER INJECTION BOOSTER PUMPS | J19: 3 | K19: WATER | L19: CASING:CAST IRON SHAFT:S.S MARTENSITE (TCV) | M19: B.V | N19: 65 M3/HR | O19: 5.1 | S19: 40520 | T19: =S19*J19 -> 121560 | U19: 0.6
A20: P-181 A/B | D20: WATER INJECTION MAIN PUMPS | J20: 3 | K20: WATER | L20: CASING:CAST IRON SHAFT:S.S MARTENSITE (TCV) | M20: B.V | N20: 65.3 M3/HR | O20: 81 | P20: 1823400 | S20: 91170 | T20: =S20*J20 -> 273510 | U20: 0.6
A21: P-170 A/B | D21: REMOVED OIL TRANSFER PUMPS | J21: 3 | K21: CRUDE OIL | L21: CASING:CAST IRON SHAFT:S.S MARTENSITE (TCV) | M21: B.V | N21: 2 M3/HR | O21: 2 | S21: 10130 | T21: =S21*J21 -> 30390 | U21: 0.6
A22: P-103 | D22: CRUDE FEED PUMP | J22: 2 | K22: CRUDE OIL | L22: CASING:CAST IRON SHAFT:S.S MARTENSITE (TCV) | M22: B.V | N22: 33 M3/HR | O22: 2 | S22: 25325 | T22: =S22*J22 -> 50650 | U22: 0.6
A23: P-153 A/B | D23: OILY WATER SEPARATOR WATER PUMP | J23: 3 | K23: OILY WATER | L23: CASING:CAST IRON SHAFT:S.S MARTENSITE (TCV) | M23: B.V | N23: 15 M3/HR | O23: 2 | S23: 25325 | T23: =S23*J23 -> 75975 | U23: 0.6
A24: P-150 | D24: CLOSED DRAIN VESSEL SUMP PUMP | J24: 2 | K24: OILY WATER | L24: CASING:CAST IRON SHAFT:S.S MARTENSITE (TCV) | M24: B.V | N24: 8 M3/HR | O24: 2 | S24: 20260 | T24: =S24*J24 -> 40520 | U24: 0.6
A25: P-151 A/B | D25: H/C CLOSED DRAIN TRANSFER PUMP | K25: CRUDE OIL | L25: CASING:CAST IRON SHAFT:S.S MARTENSITE (TCV) | M25: B.V | N25: 17 M3/HR | O25: 5 | S25: 30390 | T25: =S25*J25 -> 0 | U25: 0.6
A26: P-152 A/B | D26: OILY WATER SEPARATOR OIL PUMP | J26: 3 | K26: CRUDE OIL | L26: CASING:CAST IRON SHAFT:S.S MARTENSITE (TCV) | M26: B.V | N26: 4 M3/HR | O26: 2 | S26: 20260 | T26: =S26*J26 -> 60780 | U26: 0.6
A27: P-177 A/B | D27: CHEMICAL LOADING PUMPS | J27: 3 | K27: CORROSION INHIBITOR/DEMULSIFIER | L27: WILL BE FINALIZED LATER | M27: _ | N27: 3 M3/HR | O27: 0.7 | S27: 15195 | T27: =S27*J27 -> 45585 | U27: 0.6
A28: MI-180 A/B | D28: WALNUT FILTER MIXER | J28: 3 | K28: _ | L28: WILL BE FINALIZED LATER | M28: DIA. OF BLADE: 1800 mm | N28: _ | O28: _ | S28: 10130 | T28: =S28*J28 -> 30390 | U28: 0.6
A29: Installation | T29: 911700
A30: NOTES: | S30: 5157183 | T30: =SUM(T11:T29) -> 5287860 | U30: =U28*S30 -> 3094310 | V30: 6170183
I31: 1 - B.V.: BY VENDOR 2 - N.A.: NOT APPLICABLE 3 - ATM.: ATMOSPHERIC
J34: =SUM(J11:J28) -> 49

Sheet STACK
H1: Modular Oil Treating And Desalting Unit
H2: Title:
H3: Main Equipment List - Train No1
A4: Page 6 of 12 | H4: Document No.: | S4: =#NAME? -> #NAME?
S5: =#NAME? -> #NAME?
A7: ITEM NO. | D7: DESCRIPTION | J7: QTY | K7: STACK & TIP DIAMETER | M7: STACK HEIGHT | P7: REMARKS | V7: estimation price (euro/Unit) | W7: Total Price (Euro) | X7: Overhead 30% | Y7: Total Estimation Price (Euro/Kg)
A11: FL-160 | D11: FLARE ASSEMBLY | J11: 1 | K11: 16" & 8" | M11: 10000 mm | V11: 303900 | W11: =V11*J11 -> 303900 | X11: 0.3
A12: FL-161 | D12: COLD FLARE | J12: 1 | K12: 16" & 8" | M12: 10000 mm | V12: 303900 | W12: =V12*J12 -> 303900 | X12: 0.3
A13: Installation Included
W20: =SUM(W11:W19) -> 607800 | X20: =W20*X12 -> 182340 | Y20: 1114300
F21: NOTES: | I21: 1 - B.V.: BY VENDOR 2 - N.A.: NOT APPLICABLE 3 - ATM.: ATMOSPHERIC
Y29: =X29+V29 -> 0

Sheet H-EX & HEATER
H1: Modular Oil Treating And Desalting Unit
H2: Title:
H3: Main Equipment List - Train No1
A4: Page 7 of 12 | H4: Document No.: | T4: =#NAME? -> #NAME?
T5: =#NAME? -> #NAME?
A7: ITEM NO. | D7: DESCRIPTION | J7: QTY | K7: FLUID CONTENT | L7: TYPE | M7: MATERIAL | N7: DIMENSION | O7: TEMP. | P7: PRESS. | Q7: DUTY | S7: DIMENSION | T7: ORIENTATION | V7: REMARKS | W7: estimation price (euro/Unit) | X7: Total Price (Euro) | Y7: Overhead 30% | Z7: Total Estimation Price (Euro/Kg)
O8: DESIGN (MAX) | P8: DESIGN (BARG) | S8: Diameter (mm) Hight (Length)- TL to TL (mm)
A11: E-101 | D11: WATER/WATER HEAT EXCHANGER | J11: 1 | K11: WATER | L11: PLATE AND FRAME | M11: SA 516 GR.70 | N11: B.V | O11: HOT/COLD: 88.7/73.7 | P11: 13.4 | Q11: 1082.4 KW | T11: HORZINTAL | V11: 99274 | W11: 65845 | X11: =W11*J11 -> 65845 | Y11: 0.3
A12: E-100 | D12: CRUDE/CRUDE HEAT EXCHANGER | J12: 1 | K12: CRUDE OIL | L12: PLATE AND FRAME | M12: SA 516 GR.70 | N12: B.V | O12: HOT/COLD: 89/89 | P12: 16 | Q12: 5784 KW | T12: HORZINTAL | V12: 212730 | W12: 222860 | X12: =W12*J12 -> 222860 | Y12: 0.3
A13: H-100 A | D13: INDIRECT FIRED HEATER | J13: 1 | K13: CRUDE OIL | L13: TUBE AND BATH | M13: SA 516 GR.70 | N13: 3558x15240 | O13: 93 | P13: TUBE/BATH: 16/3.5 | Q13: 3900 | T13: HORZINTAL | V13: 1215600 | W13: 1620800 | X13: =W13*J13 -> 1620800 | Y13: 0.3
A14: H-100B | D14: INDIRECT FIRED HEATER | J14: 1 | K14: CRUDE OIL | L14: TUBE AND BATH | M14: SA 516 GR.70 | N14: 3558x15240 | O14: 93 | P14: TUBE/BATH: 16/3.5 | Q14: 3900 | T14: HORZINTAL | V14: 1215600 | W14: 1620800 | X14: =W14*J14 -> 1620800 | Y14: 0.3
A15: Installation | W15: 1 | X15: 151950
V16: =SUM(V11:V14) -> 2743204
X20: =SUM(X11:X19) -> 3682255 | Y20: =X20*Y12 -> 1104676 | Z20: =V16 -> 2743204
F21: NOTES: | I21: 1 - B.V.: BY VENDOR 2 - N.A.: NOT APPLICABLE 3 - ATM.: ATMOSPHERIC
Z29: =Y29+W29 -> 0

Sheet STRUCTURE
H1: Modular Oil Treating And Desalting Unit
H2: Title:
H3: Main Equipment List - Train No1
A4: Page 8 of 12 | H4: Document No.: | S4: =#NAME? -> #NAME?
S5: =#NAME? -> #NAME?
A7: ITEM NO. | D7: DESCRIPTION | J7: QTY (kg) | K7: FLUID CONTENT | L7: TYPE | M7: MATERIAL | N7: DIMENSION | O7: CAPACITY | P7: DIFF PRESS. | Q7: DUTY | S7: ORIENTATION | U7: REMARKS | V7: estimation price (euro/kg) | W7: Total Price (Euro) | X7: Overhead 30% | Y7: Total Estimation Price (Euro/Kg)
P8: (BARG)
D11: estimation steel structure fo whole package | J11: 709100 | V11: 3 | W11: =V11*J11 -> 2127300 | X11: 0.3
D12: installation | V12: 1 | W12: 202600 | X12: 0.3
X13: 0.3
X14: 0.3
V19: 2127300
A20: NOTES: | W20: =SUM(W11:W19) -> 2329900 | X20: =W20*X12 -> 698970 | Y20: =V19 -> 2127300
I21: 1 - B.V.: BY VENDOR 2 - N.A.: NOT APPLICABLE 3 - ATM.: ATMOSPHERIC
Y29: =X29+V29 -> 0

Sheet PACKAGE
E1: Modular Oil Treating And Desalting Unit
E2: Title:
E3: Main Equipment List - Train No1
A4: Page 9 of 12 | E4: Document No.: | M4: =#NAME? -> #NAME?
M5: =#NAME? -> #NAME?
A7: ITEM NO. | D7: DESCRIPTION | J7: QTY | K7: CAPACITY | L7: VOLUME | M7: INJECTION PRESSURE | O7: REMARKS | P7: estimation price (euro/Unit) | Q7: Total Price (Euro) | R7: Overhead 30% | S7: Total Estimation Price (Euro/Kg)
A11: PK-176 | D11: DEMULSIFIER INJECTION PACKAGE | J11: 1 | K11: 25 LIT/HR | L11: 2.5 M3 | M11: 42 BARG | O11: 172210 | P11: 506500 | Q11: =P11*J11 -> 506500 | R11: 0.3
A12: PK-170 | D12: DEMULSIFIER INJECTION PACKAGE | J12: 1 | K12: 15 LIT/HR | L12: 2.5 M3 | M12: 12 BARG | P12: 607800 | Q12: =P12*J12 -> 607800 | R12: 0.3
A13: PK-171 | D13: CORROSION INHIBITOR INJECTION | J13: 1 | K13: 7 LIT/HR | L13: 0.5 M3 | M13: 10 BARG | P13: 455850 | Q13: =P13*J13 -> 455850 | R13: 0.3
A14: PK-172 | D14: OXYGEN SCAVENGER INJECTION PACKAGE | J14: 1 | K14: 6 LIT/HR | L14: 0.5 M3 | M14: 4.3 BARG | P14: 557150 | Q14: =P14*J14 -> 557150 | R14: 0.3
A15: PK-173 | D15: REVERSE DEMULSIFIER INJECTION PACKAGE | J15: 1 | K15: 5 LIT/HR | L15: 0.5 M3 | M15: 10.3 BARG | P15: 354550 | Q15: =P15*J15 -> 354550 | R15: 0.3
A16: PK-174 | D16: SCALE INHIBITOR INJECTION PACKAGE | J16: 1 | K16: 6 LIT/HR | L16: 0.5 M3 | M16: 2.5 BARG | P16: 455850 | Q16: =P16*J16 -> 455850 | R16: 0.3
A17: PK-175 | D17: BIOCIDE INJECTION PACKAGE | J17: 1 | K17: 8/50 LIT/HR | L17: 2.5 M3 | M17: 2.5 BARG | P17: 354550 | Q17: =P17*J17 -> 354550 | R17: 0.3
A18: PK-110 | D18: VACUUM DEAERATION PACKAGE | J18: 1 | K18: 20.5 M3/HR | L18: _ | M18: 3.5/FULL VAC BARG | O18: 1874050 | P18: 861050 | Q18: =P18*J18 -> 861050 | R18: 0.3
A19: Installation | P19: 1 | Q19: 607800 | R19: 0.3
A20: NOTES: | P20: 2431200 | Q20: =SUM(Q11:Q19) -> 4761100 | R20: =Q20*R12 -> 1428330 | S20: =P20 -> 2431200
I21: 1 - B.V.: BY VENDOR 2 - N.A.: NOT APPLICABLE 3 - ATM.: ATMOSPHERIC
S24: 3
S29: =R29+P29 -> 0

Sheet Civil Work
H1: Modular Oil Treating And Desalting Unit
H2: Title:
H3: Main Equipment List - Train No1
A4: Page 10 of 12 | H4: Document No.: | N4: =#NAME? -> #NAME?
N5: =#NAME? -> #NAME?
A7: ITEM NO. | D7: DESCRIPTION | J7: QTY | K7: FLUID CONTENT | L7: MATERIAL | M7: DIMENSION (MM) | N7: ORIENTATION | P7: REMARKS | Q7: estimation price (euro/Unit) | R7: Total Price (Euro) | S7: Overhead 30% | T7: Total Estimation Price (Euro/Kg)
A11: X-151 | D11: EVAPORATION POND | J11: 1 | K11: OILY WATER | L11: CONCRETE | M11: 93000x60000x2000 | Q11: 911700 | R11: =Q11*J11 -> 911700 | S11: 0.3
A12: PK-150 | D12: BURN PIT | J12: 1 | K12: GAS | L12: CONCRETE | M12: 11000x12000x2000 | Q12: 121560 | R12: =Q12*J12 -> 121560 | S12: 0.3
A13: OS-150 | D13: OILY WATER SWPARATOR | J13: 1 | K13: OILY WATER | L13: CONCRETE | M13: 9000x3500x3000 | Q13: 121560 | R13: =Q13*J13 -> 121560 | S13: 0.3
D14: Construction Activity (Excaviation & Civil Work) | J14: 1 | Q14: 1114300 | R14: =Q14*J14 -> 1114300 | S14: 0.3
D15: construction , pre comissioning & comissioning contractors | J15: 1 | Q15: 1823400 | R15: =Q15*J15 -> 1823400 | S15: 0.3
R16: =Q16*J16 -> 0 | S16: 0.3
R17: =Q17*J17 -> 0 | S17: 0.3
Q18: 3536383 | R18: =Q18*J18 -> 0 | S18: 0.3
R19: =Q19*K19 -> 0 | S19: 0.3
A20: NOTES: | R20: =(SUM(R11:R19))*1.2 -> 4911024 | S20: =R20*S12 -> 1473307 | T20: =Q18 -> 3536383
I21: 1 - B.V.: BY VENDOR 2 - N.A.: NOT APPLICABLE 3 - ATM.: ATMOSPHERIC
T29: =S29+Q29 -> 0

Sheet PIPE & FITTING & Valves
H1: Modular Oil Treating And Desalting Unit
H2: Title:
H3: Main Equipment List - Train No1
A4: Page 11 of 12 | H4: Document No.: | Q4: =#NAME? -> #NAME?
Q5: =#NAME? -> #NAME?
A7: ITEM NO. | D7: DESCRIPTION | J7: Estimation Length (m) | K7: Size (inch) | L7: TYPE | M7: MATERIAL | N7: DIMENSION | O7: CAPACITY | P7: DIFF PRESS. | Q7: ORIENTATION | S7: REMARKS | T7: estimation price (euro/kg) | U7: estimation price (euro/m) | V7: weight / m (kg) | W7: Total Weight(kg) | X7: total price (euro) | Y7: overhead (30%) | Z7: Total Estimation Price (Euro/Kg)
P8: (BARG)
D11: oil line (10 inch ) | J11: 12156 | K11: 10 | T11: 2 | V11: 60.31 | W11: =V11*J11 -> 733128 | X11: =W11*T11 -> 1466257 | Y11: 0.3
D12: gas line (4 inch) | J12: 1013 | K12: 4 | T12: 1 | V12: 17 | W12: =V12*J12 -> 17221 | X12: =W12*T12 -> 17221 | Y12: 0.3
D13: fuel gas | J13: 6078 | K13: 6 | T13: 1 | V13: 42.55 | W13: =V13*J13 -> 258619 | X13: =W13*T13 -> 258619 | Y13: 0.3
D14: dilution water line (6 inch) | J14: 2532 | K14: 6 | U14: 5 | V14: 42 | W14: =U14*J14 -> 12662 | X14: =W14 -> 12662 | Y14: 0.3
D15: disposal water line (4 inch) | J15: 20260 | K15: 6 | U15: 7 | V15: 28.26 | W15: =U15*J15 -> 141820 | X15: =W15 -> 141820 | Y15: 0.3
D16: inter connection line | J16: 2026 | K16: 2~10 | T16: 0.9 | V16: 80 | W16: =V16*J16 -> 162080 | X16: =W16*T16 -> 145872 | Y16: 0.3
D17: flare line | J17: 100 | K17: 16 | V17: 210 | W17: =V17*J17 -> 21273 | X17: =W17 -> 21273 | Y17: 0.3
D18: Welding construction Estimate | J18: 28364 | T18: 25 | V18: =T18*M18 -> 0 | W18: =J18 -> 28364 | X18: =W18*T18 -> 709100 | Y18: 0.3
D19: contractor | V19: =T19*M19 -> 0 | W19: =V19*J19 -> 0 | X19: 2026000 | Y19: 0.3
D20: Valves/ Control Valves | J20: 1 | V20: =T20*N20 -> 0 | W20: =V20*J20 -> 0 | X20: 2026000 | Y20: 0.3
A21: NOTES: | V21: =SUM(V11:V20) -> 480.12 | X21: =SUM(X11:X20) -> 6824824 | Y21: =Y18*X21 -> 2047447 | Z21: 7212560
I22: 1 - B.V.: BY VENDOR 2 - N.A.: NOT APPLICABLE 3 - ATM.: ATMOSPHERIC
T23: 7212560
X24: Existing Flare move | Y24: 1013000
W26: =Z21*35/100 -> 2524396
Z30: =#REF!+T30 -> #REF!

Sheet E&I&C
H1: Modular Oil Treating And Desalting Unit
H2: Title:
H3: Main Equipment List - Train No1
A4: Page 12 of 12 | H4: Document No.: | S4: =#NAME? -> #NAME?
S5: =#NAME? -> #NAME?
A7: ITEM NO. | D7: DESCRIPTION | J7: QTY | K7: FLUID CONTENT | L7: TYPE | M7: MATERIAL | N7: DIMENSION | O7: CAPACITY | P7: DIFF PRESS. | Q7: DUTY | S7: ORIENTATION | U7: REMARKS | V7: estimation price (euro/Unit) | W7: Total Price (Euro) | X7: Overhead 30% | Y7: Total Estimation Price (Euro/Kg)
P8: (BARG)
A11: PK-140 | D11: COMPRESSOR CONTROL PANEL | J11: 1 | V11: 101300 | W11: =V11*J11 -> 101300 | X11: 0.4
A12: PK-141 | D12: AIR DRYER PACKAGE CONTROL PANEL | J12: 1 | V12: 121560 | W12: =V12*J12 -> 121560 | X12: 0.4
A13: PK-160 | D13: IGNITION CONTROL PANEL & TRANSFORMER | J13: 1 | V13: 91170 | W13: =V13*J13 -> 91170 | X13: 0.4
A14: PK-150 | D14: IGNITION CONTROL PANEL & TRANSFORMER | J14: 1 | V14: 70910 | W14: =V14*J14 -> 70910 | X14: 0.4
A15: H-100 A | D15: BURNER MANAGEMENT SYSTEM | J15: 1 | V15: 121560 | W15: =V15*J15 -> 121560 | X15: 0.4
A16: H-100 B | D16: BURNER MANAGEMENT SYSTEM | J16: 1 | V16: 121560 | W16: =V16*J16 -> 121560 | X16: 0.4
D17: F&G System | J17: 1 | V17: 2228600 | W17: =V17*J17 -> 2228600 | X17: 0.4
D18: Gas Generator | J18: 2 | V18: 506500 | W18: =V18*J18 -> 1013000 | X18: 0.4
D19: Metering System | J19: 1 | V19: 3039000 | W19: =V19*J19 -> 3039000 | X19: 0.4
D20: Automatic Sampling System | J20: 1 | V20: 1013000 | W20: =V20*J20 -> 1013000 | X20: 0.4
A21: NOTES: | W21: =SUM(W11:W20) -> 7921660 | X21: =W21*X12 -> 3168664 | Y21: 6977544
I22: 1 - B.V.: BY VENDOR 2 - N.A.: NOT APPLICABLE 3 - ATM.: ATMOSPHERIC
Y30: =X30+V30 -> 0

Sheet Instruments , Power & CCR 
A1: R | B1: Instruments | C1: QTY | D1: Unit Price (Euro) | E1: Total Price (Euro)
A2: 1 | B2: Instruments | C2: 1 | D2: 2026000 | E2: =D2*C2 -> 2026000
A3: 2 | B3: Instruments Installation | C3: 1 | D3: 303900 | E3: =D3*C3 -> 303900
A4: 3 | B4: CCR | C4: 1 | D4: 405200 | E4: =D4*C4 -> 405200
A5: 4 | B5: Power | C5: 1 | D5: 506500 | E5: =D5*C5 -> 506500
A6: 5 | B6: Power Installation | C6: 1 | D6: 151950 | E6: =D6*C6 -> 151950
A7: 6 | B7: F&G System | C7: 1 | D7: 1519500 | E7: =D7*C7 -> 1519500
A8: 7 | B8: HSE Equipment | C8: 1 | D8: 1013000 | E8: =D8*C8 -> 1013000
A9: 8 | E9: =D9*C9 -> 0
A10: 9 | E10: =D10*C10 -> 0
A11: 10 | E11: =D11*C11 -> 0
A12: 11 | E12: =D12*C12 -> 0
A13: 12 | E13: =D13*C13 -> 0
A14: 13 | E14: =D14*C14 -> 0
A15: 14 | E15: =D15*C15 -> 0
A16: 15 | E16: =D16*C16 -> 0
A17: 16 | E17: =SUM(E2:E16) -> 5926050
E18: =3273000+2026979 -> 5368879

Sheet Mob-Demobilization
A1: Site Mobilization
A2: R | B2: Site Mobilization | C2: QTY | F2: Total Price (Euro) | G2: Description
A3: 1 | B3: ofiice building (Contractor offices) | C3: 700 | D3: m2 | E3: 250 | F3: =E3*C3 -> 177275
A4: 2 | B4: office building (Client offices) | C4: 250 | D4: m2 | E4: 250 | F4: =E4*C4 -> 63312
A5: 3 | B5: office furnish | C5: 303900 | D5: total | E5: 1 | F5: =E5*C5 -> 303900
A6: 4 | B6: Healthcare Station | C6: 35455 | E6: 1 | F6: =E6*C6 -> 35455 | G6: 12m2 conex+first aid equipment+ambulance
A7: 5 | B7: Fire Fighting Station | C7: 202600 | E7: 1 | F7: =E7*C7 -> 202600 | G7: 1 fire fighting car
A8: 6 | B8: fence | C8: 800 | D8: m | E8: 70 | F8: =E8*C8 -> 56728
A9: 7 | B9: Labors Dormitory | C9: 700 | D9: m2 | E9: 250 | F9: =E9*C9 -> 177275 | G9: 6m2 per each persons
A10: 8 | B10: Engineers Dormitory | C10: 300 | D10: m2 | E10: 250 | F10: =E10*C10 -> 75975
A11: 9 | B11: Dormitory furnish | C11: 202600 | D11: m2 | E11: 1 | F11: =E11*C11 -> 202600
A12: 10 | B12: Transfers (ticket,cars,…) | C12: 202600 | E12: 1 | F12: =E12*C12 -> 202600 | G12: Domestic & International Transfers
A13: 11 | B13: Demobilization | C13: 151950 | E13: 1 | F13: =E13*C13 -> 151950
A14: 12 | B14: HSE consumption | C14: 101300 | E14: 1 | F14: =E14*C14 -> 101300
A15: 13 | F15: =E15*C15 -> 0
A16: 14 | F16: =SUM(F3:F15) -> 1750970
A17: 15 | F17: =F16*1.3 -> 2276262
A18: 16
A19: 17
A20: 18
A21: 19
A22: 20

Sheet Machinery
A1: R | B1: Machine List | C1: QTY | D1: rent month | E1: unit/month | F1: Overheads (30%) | G1: total price (Euro) | I1: Total+Overheads
A2: 1 | B2: bulldozer | C2: 1 | D2: 3 | E2: 10130 | F2: 0.3 | G2: =E2*C2*D2 -> 30390 | H2: =G2*F2 -> 9117 | I2: =H2+G2 -> 39507
A3: 2 | B3: Excavator | C3: 3 | D3: 3 | E3: 5065 | F3: 0.3 | G3: =E3*C3*D3 -> 45585 | H3: =G3*F3 -> 13675 | I3: =H3+G3 -> 59260
A4: 3 | B4: Loader | C4: 2 | D4: 3 | E4: 3039 | F4: 0.3 | G4: =E4*C4*D4 -> 18234 | H4: =G4*F4 -> 5470 | I4: =H4+G4 -> 23704
A5: 4 | B5: Truck 10 tons | C5: 8 | D5: 3 | E5: 2026 | F5: 0.3 | G5: =E5*C5*D5 -> 48624 | H5: =G5*F5 -> 14587 | I5: =H5+G5 -> 63211
A6: 5 | B6: Water Sprinkler Machine | C6: 2 | D6: 3 | E6: 1519 | F6: 0.3 | G6: =E6*C6*D6 -> 9117 | H6: =G6*F6 -> 2735 | I6: =H6+G6 -> 11852
A7: 6 | B7: Roller Machine | C7: 1 | D7: 3 | E7: 3039 | F7: 0.3 | G7: =E7*C7*D7 -> 9117 | H7: =G7*F7 -> 2735 | I7: =H7+G7 -> 11852
A8: 7 | B8: Mixer | C8: 3 | D8: 3 | E8: 3545 | F8: 0.3 | G8: =E8*C8*D8 -> 31909 | H8: =G8*F8 -> 9573 | I8: =H8+G8 -> 41482
A9: 8 | B9: Boom truck crane 10 tons | C9: 2 | D9: 12 | E9: 2026 | F9: 0.3 | G9: =E9*C9*D9 -> 48624 | H9: =G9*F9 -> 14587 | I9: =H9+G9 -> 63211
A10: 9 | B10: Forklift 10 tons | C10: 1 | D10: 12 | E10: 2026 | F10: 0.3 | G10: =E10*C10*D10 -> 24312 | H10: =G10*F10 -> 7294 | I10: =H10+G10 -> 31606
A11: 10 | B11: Grider | C11: 1 | D11: 3 | E11: 2026 | F11: 0.3 | G11: =E11*C11*D11 -> 6078 | H11: =G11*F11 -> 1823 | I11: =H11+G11 -> 7901
A12: 11 | B12: Bilbackho | C12: 1 | D12: 12 | E12: 1519 | F12: 0.3 | G12: =E12*C12*D12 -> 18234 | H12: =G12*F12 -> 5470 | I12: =H12+G12 -> 23704
A13: 12 | B13: Mini Bus | C13: 3 | D13: 13 | E13: 1013 | F13: 0.3 | G13: =E13*C13*D13 -> 39507 | H13: =G13*F13 -> 11852 | I13: =H13+G13 -> 51359
A14: 13 | B14: Personal Cars | C14: 6 | D14: 15 | E14: 1013 | F14: 0.3 | G14: =E14*C14*D14 -> 91170 | H14: =G14*F14 -> 27351 | I14: =H14+G14 -> 118521
A15: 14 | G15: =E15*C15*D15 -> 0 | I15: =H15+G15 -> 0
A16: 15 | G16: =E16*C16*D16 -> 0 | I16: =H16+G16 -> 0
A17: 16 | G17: =E17*C17*D17 -> 0 | I17: =H17+G17 -> 0
A18: 17 | G18: =E18*C18*D18 -> 0 | I18: =H18+G18 -> 0
A19: 18 | G19: =SUM(G2:G18) -> 420901 | H19: =SUM(H2:H18) -> 126270 | I19: =SUM(I2:I18) -> 547172

Sheet employee Salary & Accomodation 
A1: R | B1: description | C1: QTY | E1: Total month | F1: salary / month | G1: overheads | H1: total salary/month | I1: Total salary commulate (euro) | J1: description
A2: 1 | B2: salary | C2: 90 | D2: person/month | E2: 13 | F2: 121560 | G2: 0.3 | H2: =F2*G2+F2 -> 158028 | I2: =H2*E2 -> 2054364
A3: 2 | B3: Accomodation | C3: 90 | D3: person/month | E3: 13 | F3: 30390 | G3: 0.3 | H3: =F3*G3+F3 -> 39507 | I3: =H3*E3 -> 513591 | J3: breakfast,lunch,dinner,camp costs
A4: 3 | B4: Personal HSE Equipment | C4: 90 | D4: person/month | E4: 13 | F4: 9117 | G4: 0.3 | H4: =F4*G4+F4 -> 11852 | I4: =H4*E4 -> 154077 | J4: protective shoes , hamlet , dress , …
A5: 4
A6: 15 | I6: =SUM(I2:I5) -> 2722032
